Workbook

Sheet 封面与摘要
A1: 三环集团（300408.SZ / 06951.HK）财务与估值模型
A2: 编制日期：2026-09-30｜单位：百万元人民币（另注明除外）｜数据截至2026年半年报（2026-08-28）
A4: 使用说明
A5: 1. 在“假设”表C5修改情景（1=基准，2=乐观，3=悲观）；所有蓝字均为可修改输入，黄底为关键假设。
A6: 2. 颜色约定：蓝字=录入值/假设；黑字=本表公式；绿字=跨表链接。预测列为灰底。
A7: 3. 模型链路：假设 → 分部预测（含SOFC隔膜片子模型）→ 三表预测（货币资金由现金流量表倒挤）→ DCF估值 / 相对估值。
A8: 4. 历史数据：历史利润表/资产负债表/现金流量表来自Wind公司公告值；分部口径来自2025年年报；季度数据来自Wind单季报表。
A9: 5. “校验”表汇总应为0；A股股价、汇率、可比公司倍数请按最新行情更新。
A11: 核心输出（随情景自动更新）
A12: 指标 | C12: 2025A | D12: 2026E | E12: 2027E | F12: 2028E | G12: 2029E | H12: 2030E
A13: 营业收入 | C13: =三表预测!G6 -> 9007.1539 | D13: =三表预测!H6 -> 13715.092 | E13: =三表预测!I6 -> 17294.044 | F13: =三表预测!J6 -> 19666.727 | G13: =三表预测!K6 -> 21594.74 | H13: =三表预测!L6 -> 23011.833
A14: 同比 | C14: =三表预测!G7 -> 0.22131053 | D14: =三表预测!H7 -> 0.52268874 | E14: =三表预测!I7 -> 0.26094991 | F14: =三表预测!J7 -> 0.13719658 | G14: =三表预测!K7 -> 0.098034216 | H14: =三表预测!L7 -> 0.065622168
A15: 毛利率 | C15: =三表预测!G10 -> 0.4213753 | D15: =三表预测!H10 -> 0.4398758 | E15: =三表预测!I10 -> 0.44668386 | F15: =三表预测!J10 -> 0.44082098 | G15: =三表预测!K10 -> 0.43277791 | H15: =三表预测!L10 -> 0.42847829
A16: 归母净利润 | C16: =三表预测!G29 -> 2618.3839 | D16: =三表预测!H29 -> 4201.9635 | E16: =三表预测!I29 -> 5460.6668 | F16: =三表预测!J29 -> 6023.7652 | G16: =三表预测!K29 -> 6417.4399 | H16: =三表预测!L29 -> 6761.9358
A17: 同比 | C17: =三表预测!G30 -> 0.1953639 | D17: =三表预测!H30 -> 0.60479274 | E17: =三表预测!I30 -> 0.29955124 | F17: =三表预测!J30 -> 0.10311897 | G17: =三表预测!K30 -> 0.065353601 | H17: =三表预测!L30 -> 0.053681196
A18: EPS（元） | C18: =三表预测!G32 -> 1.3699036 | D18: =三表预测!H32 -> 2.1257377 | E18: =三表预测!I32 -> 2.7625051 | F18: =三表预测!J32 -> 3.0473717 | G18: =三表预测!K32 -> 3.2465284 | H18: =三表预测!L32 -> 3.420806
A19: ROE（平均） | C19: =三表预测!G87 -> 0.12611169 | D19: =三表预测!H87 -> 0.16101767 | E19: =三表预测!I87 -> 0.16765515 | F19: =三表预测!J87 -> 0.16405166 | G19: =三表预测!K87 -> 0.15635368 | H19: =三表预测!L87 -> 0.148349
A20: 自由现金流 | C20: =三表预测!G83 -> 2297.5171 | D20: =三表预测!H83 -> 1883.508 | E20: =三表预测!I83 -> 2647.7705 | F20: =三表预测!J83 -> 4164.5711 | G20: =三表预测!K83 -> 5271.3224 | H20: =三表预测!L83 -> 6268.1998
A21: 净现金 | C21: =三表预测!G93 -> 11544.363 | D21: =三表预测!H93 -> 18100.965 | E21: =三表预测!I93 -> 19362.087 | F21: =三表预测!J93 -> 21724.639 | G21: =三表预测!K93 -> 25008.118 | H21: =三表预测!L93 -> 29158.563
A22: PE（当前股价） | C22: =三表预测!G97 -> 86.502435 | D22: =三表预测!H97 -> 55.745354 | E22: =三表预测!I97 -> 42.895849 | F22: =三表预测!J97 -> 38.885968 | G22: =三表预测!K97 -> 36.500527 | H22: =三表预测!L97 -> 34.640959
A23: SOFC隔膜片收入 | C23: =分部预测!G13 -> 330.72 | D23: =分部预测!H13 -> 889.33333 | E23: =分部预测!I13 -> 1254.1667 | F23: =分部预测!J13 -> 1110.1538 | G23: =分部预测!K13 -> 1140 | H23: =分部预测!L13 -> 1046.5714
A24: SOFC隔膜片毛利占公司毛利 | D24: =IFERROR(分部预测!H16/分部预测!H44,0) -> 0.058965199 | E24: =IFERROR(分部预测!I16/分部预测!I44,0) -> 0.06494092 | F24: =IFERROR(分部预测!J16/分部预测!J44,0) -> 0.049940561 | G24: =IFERROR(分部预测!K16/分部预测!K44,0) -> 0.046352738 | H24: =IFERROR(分部预测!L16/分部预测!L44,0) -> 0.040334106
A26: 估值摘要
A27: 当前情景（1基准/2乐观/3悲观） | C27: =假设!$C$5 -> 1
A28: A股股价（元） | C28: =假设!$C$6 -> 118.5
A29: WACC | C29: =DCF估值!$C$7 -> 0.089299
A30: 永续增长率 | C30: =DCF估值!$C$8 -> 0.03
A31: DCF每股价值（元，2026-12-31） | C31: =DCF估值!$C$33 -> 60.66906
A32: DCF每股价值折回当前（元） | C32: =DCF估值!$C$34 -> 59.369152
A33: 相对当前股价空间 | C33: =DCF估值!$C$36 -> -0.49899449
A34: DCF隐含2027E PE | C34: =DCF估值!$C$38 -> 21.96161
A35: PE区间估值（2027E EPS × PE下限/上限，元） | C35: =TEXT(假设!$C$31*三表预测!I32,"0.0")&" - "&TEXT(假设!$C$32*三表预测!I32,"0.0") -> 82.9 - 151.9
A36: 模型校验汇总（应为0） | C36: =校验!C13 -> 0
A38: 免责声明：本模型基于公开信息与产业链调研整理，假设具有主观性，不构成任何投资建议。

Sheet 假设
A1: 核心假设（所有蓝字均可修改；黄底为关键假设）
A2: 单位：百万元人民币，另注明除外。情景选择：1=基准，2=乐观，3=悲观。年份列与“三表预测”对齐（H:L=2026E-2030E）。
A4: 一、全局与市场参数
A5: 情景选择（1=基准，2=乐观，3=悲观） | C5: 1 | D5: 修改此格切换全模型情景
A6: A股股价（元/股） | C6: 118.5 | D6: Wind一致预期表2026-09-30：2026E PE 56.42×EPS 2.10倒算；请按最新行情更新
A7: H股发行价（港元/股） | C7: 100.3 | D7: 三环H股招股章程/配售结果（2026-07-09上市）
A8: 港元兑人民币（HKD/CNY） | C8: 0.915 | D8: 假设值，请按最新汇率更新
A9: H股发行股数（股，含部分行使超额配股权） | C9: 80221200 | D9: 2026年半年报：合计发行80,221,200股H股
A10: H股发行费用率 | C10: 0.025 | D10: 假设值（上市费用、承销佣金）
A11: 2025年末总股本（股） | C11: 1916497371 | D11: 2025年年报
A12: 2025年末库存股（股） | C12: 5133800 | D12: 2025年年报：回购专户5,133,800股
A13: 2026年第一期回购股数（股） | C13: 8547300 | D13: 2026年半年报：7月底完成，累计8,547,300股
A14: 2026年第一期回购金额 | C14: 895 | D14: 2026年半年报：约8.95亿元
A15: 2026年第二期回购金额（下限5亿、上限10亿，取中值） | C15: 750 | D15: 2026年半年报；中值为假设
A16: 2026年已派发2025年度现金股利 | C16: 860.11 | D16: 2025年度利润分配：每10股4.50元，共860,113,606.95元，2026-05-11实施
... A19: 少数股东损益占净利润比例 | C19: 0 | D19: 历史接近0（2025年-1.4百万元）
A21: 二、估值参数
A22: 无风险利率 | C22: 0.019 | D22: 假设：中国10年期国债收益率约1.8%-1.9%
A23: Beta | C23: 1.1 | D23: 假设值
A24: 股权风险溢价 | C24: 0.065 | D24: 假设值
A25: 税前债务成本 | C25: 0.035 | D25: 2025年利息费用/平均有息负债约3.9%，取3.5%
A26: 目标债务占比 D/(D+E) | C26: 0.02 | D26: 公司几乎无净负债，取2%
A27: 永续增长率 | C27: 0.03 | D27: 假设值
A28: 第二阶段（2031E-2035E）FCFF增速起点 | C28: 0.1 | D28: 假设：2031年增速，线性递减至终点
A29: 第二阶段FCFF增速终点（2035E） | C29: 0.05 | D29: 假设值
A30: 其他非流动资产计入类现金比例 | C30: 0.9 | D30: 其他非流动资产主要为一年以上定期存款/大额存单（年报附注），假设90%可视同现金
A31: 相对估值：PE下限 | C31: 30 | D31: 用户可调
A32: 相对估值：PE上限 | C32: 55 | D32: 用户可调
A34: 逐年假设 | B34: 单位 | C34: 2021A | D34: 2022A | E34: 2023A | F34: 2024A | G34: 2025A | H34: 2026E | I34: 2027E | J34: 2028E | K34: 2029E | L34: 2030E
A35: 三、分部收入与毛利率（电子元件=MLCC、陶瓷封装基座等；通信器件=插芯、套筒等光通信产品；电子及陶瓷材料=陶瓷基片、电子浆料、SOFC隔膜片等）
A36: 电子元件 收入增速—基准 | B36: % | H36: 0.7 | I36: 0.35 | J36: 0.2 | K36: 0.12 | L36: 0.08
A37: 电子元件 收入增速—乐观 | B37: % | H37: 0.8 | I37: 0.45 | J37: 0.25 | K37: 0.15 | L37: 0.1
A38: 电子元件 收入增速—悲观 | B38: % | H38: 0.55 | I38: 0.2 | J38: 0.1 | K38: 0.06 | L38: 0.04
A39: 电子元件 收入增速（采用值） | B39: % | H39: =CHOOSE($C$5,H36,H37,H38) -> 0.7 | I39: =CHOOSE($C$5,I36,I37,I38) -> 0.35 | J39: =CHOOSE($C$5,J36,J37,J38) -> 0.2 | K39: =CHOOSE($C$5,K36,K37,K38) -> 0.12 | L39: =CHOOSE($C$5,L36,L37,L38) -> 0.08 | M39: 2025A +43.95%；2026H1公司整体+54.82%，主要由MLCC量价齐升驱动（2026年半年报）
A40: 电子元件 毛利率—基准 | B40: % | H40: 0.46 | I40: 0.47 | J40: 0.46 | K40: 0.45 | L40: 0.44
A41: 电子元件 毛利率—乐观 | B41: % | H41: 0.48 | I41: 0.49 | J41: 0.48 | K41: 0.47 | L41: 0.46
A42: 电子元件 毛利率—悲观 | B42: % | H42: 0.44 | I42: 0.43 | J42: 0.42 | K42: 0.41 | L42: 0.4
A43: 电子元件 毛利率（采用值） | B43: % | H43: =CHOOSE($C$5,H40,H41,H42) -> 0.46 | I43: =CHOOSE($C$5,I40,I41,I42) -> 0.47 | J43: =CHOOSE($C$5,J40,J41,J42) -> 0.46 | K43: =CHOOSE($C$5,K40,K41,K42) -> 0.45 | L43: =CHOOSE($C$5,L40,L41,L42) -> 0.44 | M43: 2025A 42.30%（2024A 44.37%）；2026H1主营毛利率44.23%，同比+2.52pct
A44: 通信器件 收入增速—基准 | B44: % | H44: 0.4 | I44: 0.25 | J44: 0.15 | K44: 0.1 | L44: 0.08
A45: 通信器件 收入增速—乐观 | B45: % | H45: 0.5 | I45: 0.35 | J45: 0.2 | K45: 0.12 | L45: 0.1
A46: 通信器件 收入增速—悲观 | B46: % | H46: 0.25 | I46: 0.12 | J46: 0.08 | K46: 0.05 | L46: 0.04
A47: 通信器件 收入增速（采用值） | B47: % | H47: =CHOOSE($C$5,H44,H45,H46) -> 0.4 | I47: =CHOOSE($C$5,I44,I45,I46) -> 0.25 | J47: =CHOOSE($C$5,J44,J45,J46) -> 0.15 | K47: =CHOOSE($C$5,K44,K45,K46) -> 0.1 | L47: =CHOOSE($C$5,L44,L45,L46) -> 0.08 | M47: 2025A +12.50%；2026H1插芯及套筒等光通信产品同比增长（数据中心光器件需求）
A48: 通信器件 毛利率—基准 | B48: % | H48: 0.46 | I48: 0.46 | J48: 0.45 | K48: 0.44 | L48: 0.44
A49: 通信器件 毛利率—乐观 | B49: % | H49: 0.48 | I49: 0.48 | J49: 0.47 | K49: 0.46 | L49: 0.46
A50: 通信器件 毛利率—悲观 | B50: % | H50: 0.44 | I50: 0.43 | J50: 0.42 | K50: 0.42 | L50: 0.41
A51: 通信器件 毛利率（采用值） | B51: % | H51: =CHOOSE($C$5,H48,H49,H50) -> 0.46 | I51: =CHOOSE($C$5,I48,I49,I50) -> 0.46 | J51: =CHOOSE($C$5,J48,J49,J50) -> 0.45 | K51: =CHOOSE($C$5,K48,K49,K50) -> 0.44 | L51: =CHOOSE($C$5,L48,L49,L50) -> 0.44 | M51: 2025A 44.36%（2024A 43.93%）
A52: 电子及陶瓷材料（不含SOFC隔膜片）收入增速—基准 | B52: % | H52: 0.15 | I52: 0.12 | J52: 0.1 | K52: 0.08 | L52: 0.06
A53: 电子及陶瓷材料（不含SOFC隔膜片）收入增速—乐观 | B53: % | H53: 0.2 | I53: 0.15 | J53: 0.12 | K53: 0.1 | L53: 0.08
A54: 电子及陶瓷材料（不含SOFC隔膜片）收入增速—悲观 | B54: % | H54: 0.08 | I54: 0.06 | J54: 0.05 | K54: 0.04 | L54: 0.03
A55: 电子及陶瓷材料（不含SOFC隔膜片）收入增速（采用值） | B55: % | H55: =CHOOSE($C$5,H52,H53,H54) -> 0.15 | I55: =CHOOSE($C$5,I52,I53,I54) -> 0.12 | J55: =CHOOSE($C$5,J52,J53,J54) -> 0.1 | K55: =CHOOSE($C$5,K52,K53,K54) -> 0.08 | L55: =CHOOSE($C$5,L52,L53,L54) -> 0.06 | M55: 2025A分部整体+16.82%；SOFC隔膜片单列见下方子模型
A56: 电子及陶瓷材料（不含SOFC）毛利率—基准 | B56: % | H56: 0.38 | I56: 0.38 | J56: 0.38 | K56: 0.37 | L56: 0.37
A57: 电子及陶瓷材料（不含SOFC）毛利率—乐观 | B57: % | H57: 0.4 | I57: 0.4 | J57: 0.4 | K57: 0.39 | L57: 0.39
A58: 电子及陶瓷材料（不含SOFC）毛利率—悲观 | B58: % | H58: 0.36 | I58: 0.35 | J58: 0.35 | K58: 0.34 | L58: 0.34
A59: 电子及陶瓷材料（不含SOFC）毛利率（采用值） | B59: % | H59: =CHOOSE($C$5,H56,H57,H58) -> 0.38 | I59: =CHOOSE($C$5,I56,I57,I58) -> 0.38 | J59: =CHOOSE($C$5,J56,J57,J58) -> 0.38 | K59: =CHOOSE($C$5,K56,K57,K58) -> 0.37 | L59: =CHOOSE($C$5,L56,L57,L58) -> 0.37 | M59: 2025A分部毛利率38.09%（2024A 40.57%）
A60: 设备组件 收入增速—基准 | B60: % | H60: 0.15 | I60: 0.12 | J60: 0.1 | K60: 0.08 | L60: 0.06
A61: 设备组件 收入增速—乐观 | B61: % | H61: 0.2 | I61: 0.15 | J61: 0.12 | K61: 0.1 | L61: 0.08
A62: 设备组件 收入增速—悲观 | B62: % | H62: 0.08 | I62: 0.06 | J62: 0.05 | K62: 0.04 | L62: 0.03
A63: 设备组件 收入增速（采用值） | B63: % | H63: =CHOOSE($C$5,H60,H61,H62) -> 0.15 | I63: =CHOOSE($C$5,I60,I61,I62) -> 0.12 | J63: =CHOOSE($C$5,J60,J61,J62) -> 0.1 | K63: =CHOOSE($C$5,K60,K61,K62) -> 0.08 | L63: =CHOOSE($C$5,L60,L61,L62) -> 0.06 | M63: 2025A +12.09%
A64: 设备组件 毛利率—基准 | B64: % | H64: 0.58 | I64: 0.58 | J64: 0.57 | K64: 0.57 | L64: 0.56
A65: 设备组件 毛利率—乐观 | B65: % | H65: 0.6 | I65: 0.6 | J65: 0.59 | K65: 0.59 | L65: 0.58
A66: 设备组件 毛利率—悲观 | B66: % | H66: 0.55 | I66: 0.54 | J66: 0.54 | K66: 0.53 | L66: 0.53
A67: 设备组件 毛利率（采用值） | B67: % | H67: =CHOOSE($C$5,H64,H65,H66) -> 0.58 | I67: =CHOOSE($C$5,I64,I65,I66) -> 0.58 | J67: =CHOOSE($C$5,J64,J65,J66) -> 0.57 | K67: =CHOOSE($C$5,K64,K65,K66) -> 0.57 | L67: =CHOOSE($C$5,L64,L65,L66) -> 0.56 | M67: 2025A约58.5%（Wind主营构成：毛利351.80/收入601.75）
A68: 其他主营 收入增速 | B68: % | H68: 0 | I68: 0 | J68: 0 | K68: 0 | L68: 0 | M68: 2025A -9.59%；假设持平
A69: 其他主营 毛利率 | B69: % | H69: 0.09 | I69: 0.09 | J69: 0.09 | K69: 0.09 | L69: 0.09 | M69: 2025A约9.1%（Wind：36.88/405.00）
A70: 其他业务 收入—基准 | B70: 百万元 | H70: 600 | I70: 630 | J70: 660 | K70: 690 | L70: 720
A71: 其他业务 收入—乐观 | B71: 百万元 | H71: 650 | I71: 700 | J71: 750 | K71: 800 | L71: 850
A72: 其他业务 收入—悲观 | B72: 百万元 | H72: 450 | I72: 450 | J72: 450 | K72: 450 | L72: 450
A73: 其他业务 收入（采用值） | B73: 百万元 | H73: =CHOOSE($C$5,H70,H71,H72) -> 600 | I73: =CHOOSE($C$5,I70,I71,I72) -> 630 | J73: =CHOOSE($C$5,J70,J71,J72) -> 660 | K73: =CHOOSE($C$5,K70,K71,K72) -> 690 | L73: =CHOOSE($C$5,L70,L71,L72) -> 720 | M73: 2025A 138.6；2026H1已达342.6（半年报主营外收入），全年假设600
A74: 其他业务 毛利率 | B74: % | H74: 0.45 | I74: 0.45 | J74: 0.45 | K74: 0.45 | L74: 0.45 | M74: 2026H1约46.0%（157.48/342.59）；2025A约79.6%
A75: 四、SOFC隔膜片子模型（Bloom电池片层需求×每GW片数×三环份额×单价；2025A以三环第一大客户销售额330.7百万元为代理）
A76: Bloom电池片层需求—基准 | B76: GW | H76: 1.45 | I76: 2.5 | J76: 3.2 | K76: 3.8 | L76: 4.4
A77: Bloom电池片层需求—乐观 | B77: GW | H77: 1.6 | I77: 3 | J77: 4 | K77: 4.8 | L77: 5.5
A78: Bloom电池片层需求—悲观 | B78: GW | H78: 1.3 | I78: 2 | J78: 2.4 | K78: 2.8 | L78: 3.2
A79: Bloom电池片层需求（采用值） | B79: GW | G79: 0.725 | H79: =CHOOSE($C$5,H76,H77,H78) -> 1.45 | I79: =CHOOSE($C$5,I76,I77,I78) -> 2.5 | J79: =CHOOSE($C$5,J76,J77,J78) -> 3.2 | K79: =CHOOSE($C$5,K76,K77,K78) -> 3.8 | L79: =CHOOSE($C$5,L76,L77,L78) -> 4.4 | M79: 2025A约0.65-0.8GW（验收约500MW+约25%-30%翻新）；Bloom 2026年收入指引39-42亿美元（约同比翻倍）；产业链调研：电堆产能2028-29年约5GW
A80: 单片功率—基准 | B80: W/片 | H80: 30 | I80: 30 | J80: 32.5 | K80: 32.5 | L80: 35
A81: 单片功率—乐观 | B81: W/片 | H81: 25 | I81: 25 | J81: 30 | K81: 30 | L81: 32.5
A82: 单片功率—悲观 | B82: W/片 | H82: 32.5 | I82: 32.5 | J82: 35 | K82: 35 | L82: 37.5
A83: 单片功率（采用值） | B83: W/片 | H83: =CHOOSE($C$5,H80,H81,H82) -> 30 | I83: =CHOOSE($C$5,I80,I81,I82) -> 30 | J83: =CHOOSE($C$5,J80,J81,J82) -> 32.5 | K83: =CHOOSE($C$5,K80,K81,K82) -> 32.5 | L83: =CHOOSE($C$5,L80,L81,L82) -> 35 | M83: Hunterbrook转引Bloom 2021年材料约25W/片；产业链调研约65kW对应2,000片即32.5W/片；新一代产品提高单片功率
A84: 三环份额—基准 | B84: % | H84: 0.8 | I84: 0.7 | J84: 0.55 | K84: 0.5 | L84: 0.45
A85: 三环份额—乐观 | B85: % | H85: 0.9 | I85: 0.8 | J85: 0.7 | K85: 0.65 | L85: 0.6
A86: 三环份额—悲观 | B86: % | H86: 0.7 | I86: 0.55 | J86: 0.4 | K86: 0.35 | L86: 0.3
A87: 三环份额（采用值） | B87: % | H87: =CHOOSE($C$5,H84,H85,H86) -> 0.8 | I87: =CHOOSE($C$5,I84,I85,I86) -> 0.7 | J87: =CHOOSE($C$5,J84,J85,J86) -> 0.55 | K87: =CHOOSE($C$5,K84,K85,K86) -> 0.5 | L87: =CHOOSE($C$5,L84,L85,L86) -> 0.45 | M87: 二供Amosense 2026年Q3月产能扩至60万片；2028年前后美国受禁外国实体（PFE）规则门槛升至50%
A88: 单价—基准 | B88: 元/片 | H88: 23 | I88: 21.5 | J88: 20.5 | K88: 19.5 | L88: 18.5
A89: 单价—乐观 | B89: 元/片 | H89: 25 | I89: 23.5 | J89: 22.5 | K89: 21.5 | L89: 20.5
A90: 单价—悲观 | B90: 元/片 | H90: 20 | I90: 19 | J90: 18 | K90: 17 | L90: 16
A91: 单价（采用值） | B91: 元/片 | H91: =CHOOSE($C$5,H88,H89,H90) -> 23 | I91: =CHOOSE($C$5,I88,I89,I90) -> 21.5 | J91: =CHOOSE($C$5,J88,J89,J90) -> 20.5 | K91: =CHOOSE($C$5,K88,K89,K90) -> 19.5 | L91: =CHOOSE($C$5,L88,L89,L90) -> 18.5 | M91: 市场流传25-30元（2023年）；2025年倒推覆盖率显示单价或已降至20元附近
A92: SOFC隔膜片毛利率—基准 | B92: % | H92: 0.4 | I92: 0.4 | J92: 0.39 | K92: 0.38 | L92: 0.38
A93: SOFC隔膜片毛利率—乐观 | B93: % | H93: 0.42 | I93: 0.42 | J93: 0.41 | K93: 0.4 | L93: 0.4
A94: SOFC隔膜片毛利率—悲观 | B94: % | H94: 0.36 | I94: 0.35 | J94: 0.34 | K94: 0.33 | L94: 0.33
A95: SOFC隔膜片毛利率（采用值） | B95: % | H95: =CHOOSE($C$5,H92,H93,H94) -> 0.4 | I95: =CHOOSE($C$5,I92,I93,I94) -> 0.4 | J95: =CHOOSE($C$5,J92,J93,J94) -> 0.39 | K95: =CHOOSE($C$5,K92,K93,K94) -> 0.38 | L95: =CHOOSE($C$5,L92,L93,L94) -> 0.38 | M95: 所在分部2025A毛利率38.09%；假设略高于分部
A97: 五、费用与其他损益（占营业收入比例，另注明除外）
A98: 税金及附加率 | B98: % | H98: 0.01 | I98: 0.01 | J98: 0.01 | K98: 0.01 | L98: 0.01 | M98: 2025A 1.20%；2026H1 0.94%
A99: 销售费用率 | B99: % | H99: 0.008 | I99: 0.008 | J99: 0.008 | K99: 0.008 | L99: 0.008 | M99: 2025A 1.03%；2026H1 0.70%
A100: 管理费用率 | B100: % | H100: 0.043 | I100: 0.042 | J100: 0.042 | K100: 0.041 | L100: 0.041 | M100: 2025A 5.34%；2026H1 3.97%（四季度通常偏高）
A101: 研发费用率 | B101: % | H101: 0.056 | I101: 0.056 | J101: 0.057 | K101: 0.058 | L101: 0.058 | M101: 2025A 7.25%；2026H1 5.30%
A102: 其他收益（政府补助等）占收入 | B102: % | H102: 0.022 | I102: 0.02 | J102: 0.018 | K102: 0.016 | L102: 0.015 | M102: 2025A 4.33%；2026H1 2.17%
A103: 资产及信用减值损失占收入 | B103: % | H103: 0.01 | I103: 0.008 | J103: 0.008 | K103: 0.008 | L103: 0.008 | M103: 2025A 0.47%；2026H1 2.02%
A104: 交易性金融资产收益率（投资收益+公允价值变动，按期初余额） | B104: % | H104: 0.016 | I104: 0.016 | J104: 0.016 | K104: 0.016 | L104: 0.016 | M104: 2025A约1.9%（(41.71+30.47)/期初5,053.4）
A105: 利息收入率（按期初货币资金+其他非流动资产） | B105: % | H105: 0.022 | I105: 0.02 | J105: 0.019 | K105: 0.018 | L105: 0.018 | M105: 2025A约2.3%（利息收入196.9/期初6,023.7）
A106: 借款利率（按期初有息负债） | B106: % | H106: 0.035 | I106: 0.035 | J106: 0.035 | K106: 0.035 | L106: 0.035 | M106: 2025A约4.2%（利息费用20.4/期初484.3）
...

Sheet 分部预测
A1: 分部收入与毛利预测（含SOFC隔膜片子模型）
A2: 2024A-2025A分部口径来自2025年年报“营业收入构成”（新四分部口径，与H股招股章程一致）；预测为公式，驱动来自“假设”。
A4: 项目（百万元） | B4: 单位 | C4: 2021A | D4: 2022A | E4: 2023A | F4: 2024A | G4: 2025A | H4: 2026E | I4: 2027E | J4: 2028E | K4: 2029E | L4: 2030E
A5: A. SOFC隔膜片子模型
A6: Bloom电池片层需求 | B6: GW | G6: =假设!G79 -> 0.725 | H6: =假设!H79 -> 1.45 | I6: =假设!I79 -> 2.5 | J6: =假设!J79 -> 3.2 | K6: =假设!K79 -> 3.8 | L6: =假设!L79 -> 4.4
A7: 单片功率 | B7: W/片 | G7: 30 | H7: =假设!H83 -> 30 | I7: =假设!I83 -> 30 | J7: =假设!J83 -> 32.5 | K7: =假设!K83 -> 32.5 | L7: =假设!L83 -> 35
A8: 每GW所需隔膜片 | B8: 百万片/GW | H8: =IFERROR(1000/H7,0) -> 33.333333 | I8: =IFERROR(1000/I7,0) -> 33.333333 | J8: =IFERROR(1000/J7,0) -> 30.769231 | K8: =IFERROR(1000/K7,0) -> 30.769231 | L8: =IFERROR(1000/L7,0) -> 28.571429
A9: Bloom隔膜片需求 | B9: 百万片 | H9: =H6*H8 -> 48.333333 | I9: =I6*I8 -> 83.333333 | J9: =J6*J8 -> 98.461538 | K9: =K6*K8 -> 116.92308 | L9: =L6*L8 -> 125.71429
A10: 三环份额 | B10: % | H10: =假设!H87 -> 0.8 | I10: =假设!I87 -> 0.7 | J10: =假设!J87 -> 0.55 | K10: =假设!K87 -> 0.5 | L10: =假设!L87 -> 0.45
A11: 三环隔膜片出货 | B11: 百万片 | H11: =H9*H10 -> 38.666667 | I11: =I9*I10 -> 58.333333 | J11: =J9*J10 -> 54.153846 | K11: =K9*K10 -> 58.461538 | L11: =L9*L10 -> 56.571429
A12: 单价 | B12: 元/片 | H12: =假设!H91 -> 23 | I12: =假设!I91 -> 21.5 | J12: =假设!J91 -> 20.5 | K12: =假设!K91 -> 19.5 | L12: =假设!L91 -> 18.5
A13: SOFC隔膜片收入 | B13: 百万元 | E13: 449.32 | F13: 323.87 | G13: 330.72 | H13: =H11*H12 -> 889.33333 | I13: =I11*I12 -> 1254.1667 | J13: =J11*J12 -> 1110.1538 | K13: =K11*K12 -> 1140 | L13: =L11*L12 -> 1046.5714
A14: 每GW隔膜片价值量（100%份额） | B14: 百万元/GW | H14: =H8*H12 -> 766.66667 | I14: =I8*I12 -> 716.66667 | J14: =J8*J12 -> 630.76923 | K14: =K8*K12 -> 600 | L14: =L8*L12 -> 528.57143
A15: SOFC隔膜片毛利率 | B15: % | H15: =假设!H95 -> 0.4 | I15: =假设!I95 -> 0.4 | J15: =假设!J95 -> 0.39 | K15: =假设!K95 -> 0.38 | L15: =假设!L95 -> 0.38
A16: SOFC隔膜片毛利 | B16: 百万元 | H16: =H13*H15 -> 355.73333 | I16: =I13*I15 -> 501.66667 | J16: =J13*J15 -> 432.96 | K16: =K13*K15 -> 433.2 | L16: =L13*L15 -> 397.69714
A18: B. 分部收入
A19: 电子元件 | B19: 百万元 | F19: 2298.16 | G19: 3308.09 | H19: =G19*(1+假设!H39) -> 5623.753 | I19: =H19*(1+假设!I39) -> 7592.0665 | J19: =I19*(1+假设!J39) -> 9110.4799 | K19: =J19*(1+假设!K39) -> 10203.737 | L19: =K19*(1+假设!L39) -> 11020.036
A20: 通信器件 | B20: 百万元 | F20: 2305.98 | G20: 2594.31 | H20: =G20*(1+假设!H47) -> 3632.034 | I20: =H20*(1+假设!I47) -> 4540.0425 | J20: =I20*(1+假设!J47) -> 5221.0489 | K20: =J20*(1+假设!K47) -> 5743.1538 | L20: =K20*(1+假设!L47) -> 6202.6061
A21: 电子及陶瓷材料（分部合计） | B21: 百万元 | F21: 1677.23 | G21: 1959.38 | H21: =H22+H13 -> 2762.2923 | I21: =I22+I13 -> 3351.8807 | J21: =J22+J13 -> 3417.6393 | K21: =K22+K13 -> 3632.0843 | L21: =L22+L13 -> 3688.1808
A22: 其中：不含SOFC隔膜片 | B22: 百万元 | F22: =F21-F13 -> 1353.36 | G22: =G21-G13 -> 1628.66 | H22: =G22*(1+假设!H55) -> 1872.959 | I22: =H22*(1+假设!I55) -> 2097.7141 | J22: =I22*(1+假设!J55) -> 2307.4855 | K22: =J22*(1+假设!K55) -> 2492.0843 | L22: =K22*(1+假设!L55) -> 2641.6094
A23: 其中：SOFC隔膜片 | B23: 百万元 | F23: =F13 -> 323.87 | G23: =G13 -> 330.72 | H23: =H13 -> 889.33333 | I23: =I13 -> 1254.1667 | J23: =J13 -> 1110.1538 | K23: =K13 -> 1140 | L23: =L13 -> 1046.5714
A24: 设备组件 | B24: 百万元 | F24: 536.82 | G24: 601.75 | H24: =G24*(1+假设!H63) -> 692.0125 | I24: =H24*(1+假设!I63) -> 775.054 | J24: =I24*(1+假设!J63) -> 852.5594 | K24: =J24*(1+假设!K63) -> 920.76415 | L24: =K24*(1+假设!L63) -> 976.01
A25: 其他主营 | B25: 百万元 | F25: 447.93 | G25: 405 | H25: =G25*(1+假设!H68) -> 405 | I25: =H25*(1+假设!I68) -> 405 | J25: =I25*(1+假设!J68) -> 405 | K25: =J25*(1+假设!K68) -> 405 | L25: =K25*(1+假设!L68) -> 405
A26: 其他业务 | B26: 百万元 | F26: 108.86 | G26: 138.63 | H26: =假设!H73 -> 600 | I26: =假设!I73 -> 630 | J26: =假设!J73 -> 660 | K26: =假设!K73 -> 690 | L26: =假设!L73 -> 720
A27: 营业收入合计 | B27: 百万元 | F27: =F19+F20+F21+F24+F25+F26 -> 7374.98 | G27: =G19+G20+G21+G24+G25+G26 -> 9007.16 | H27: =H19+H20+H21+H24+H25+H26 -> 13715.092 | I27: =I19+I20+I21+I24+I25+I26 -> 17294.044 | J27: =J19+J20+J21+J24+J25+J26 -> 19666.727 | K27: =K19+K20+K21+K24+K25+K26 -> 21594.74 | L27: =L19+L20+L21+L24+L25+L26 -> 23011.833
A29: C. 分部增速
A30: 电子元件 同比 | B30: % | G30: =IFERROR(G19/F19-1,0) -> 0.43945156 | H30: =IFERROR(H19/G19-1,0) -> 0.7 | I30: =IFERROR(I19/H19-1,0) -> 0.35 | J30: =IFERROR(J19/I19-1,0) -> 0.2 | K30: =IFERROR(K19/J19-1,0) -> 0.12 | L30: =IFERROR(L19/K19-1,0) -> 0.08
A31: 通信器件 同比 | B31: % | G31: =IFERROR(G20/F20-1,0) -> 0.12503578 | H31: =IFERROR(H20/G20-1,0) -> 0.4 | I31: =IFERROR(I20/H20-1,0) -> 0.25 | J31: =IFERROR(J20/I20-1,0) -> 0.15 | K31: =IFERROR(K20/J20-1,0) -> 0.1 | L31: =IFERROR(L20/K20-1,0) -> 0.08
A32: 电子及陶瓷材料 同比 | B32: % | G32: =IFERROR(G21/F21-1,0) -> 0.1682238 | H32: =IFERROR(H21/G21-1,0) -> 0.40977877 | I32: =IFERROR(I21/H21-1,0) -> 0.21344172 | J32: =IFERROR(J21/I21-1,0) -> 0.019618415 | K32: =IFERROR(K21/J21-1,0) -> 0.062746525 | L32: =IFERROR(L21/K21-1,0) -> 0.01544471
A33: SOFC隔膜片 同比 | B33: % | F33: =IFERROR(F13/E13-1,0) -> -0.27919968 | G33: =IFERROR(G13/F13-1,0) -> 0.021150462 | H33: =IFERROR(H13/G13-1,0) -> 1.6890824 | I33: =IFERROR(I13/H13-1,0) -> 0.41023238 | J33: =IFERROR(J13/I13-1,0) -> -0.1148275 | K33: =IFERROR(K13/J13-1,0) -> 0.026884701 | L33: =IFERROR(L13/K13-1,0) -> -0.081954887
A34: 设备组件 同比 | B34: % | G34: =IFERROR(G24/F24-1,0) -> 0.12095302 | H34: =IFERROR(H24/G24-1,0) -> 0.15 | I34: =IFERROR(I24/H24-1,0) -> 0.12 | J34: =IFERROR(J24/I24-1,0) -> 0.1 | K34: =IFERROR(K24/J24-1,0) -> 0.08 | L34: =IFERROR(L24/K24-1,0) -> 0.06
A35: 营业收入合计 同比 | B35: % | G35: =IFERROR(G27/F27-1,0) -> 0.22131314 | H35: =IFERROR(H27/G27-1,0) -> 0.52268771 | I35: =IFERROR(I27/H27-1,0) -> 0.26094991 | J35: =IFERROR(J27/I27-1,0) -> 0.13719658 | K35: =IFERROR(K27/J27-1,0) -> 0.098034216 | L35: =IFERROR(L27/K27-1,0) -> 0.065622168
A37: D. 分部毛利
A38: 电子元件 毛利 | B38: 百万元 | F38: =F19*F46 -> 1019.6936 | G38: 1399.45 | H38: =H19*假设!H43 -> 2586.9264 | I38: =I19*假设!I43 -> 3568.2713 | J38: =J19*假设!J43 -> 4190.8207 | K38: =K19*假设!K43 -> 4591.6818 | L38: =L19*假设!L43 -> 4848.816
A39: 通信器件 毛利 | B39: 百万元 | F39: =F20*F47 -> 1013.017 | G39: 1150.71 | H39: =H20*假设!H51 -> 1670.7356 | I39: =I20*假设!I51 -> 2088.4196 | J39: =J20*假设!J51 -> 2349.472 | K39: =K20*假设!K51 -> 2526.9877 | L39: =L20*假设!L51 -> 2729.1467
A40: 电子及陶瓷材料 毛利（合计） | B40: 百万元 | F40: =F21*F48 -> 680.45221 | G40: 746.26 | H40: =H22*假设!H59+H16 -> 1067.4578 | I40: =I22*假设!I59+I16 -> 1298.798 | J40: =J22*假设!J59+J16 -> 1309.8045 | K40: =K22*假设!K59+K16 -> 1355.2712 | L40: =L22*假设!L59+L16 -> 1375.0926
A41: 设备组件 毛利 | B41: 百万元 | G41: 351.8 | H41: =H24*假设!H67 -> 401.36725 | I41: =I24*假设!I67 -> 449.53132 | J41: =J24*假设!J67 -> 485.95886 | K41: =K24*假设!K67 -> 524.83557 | L41: =L24*假设!L67 -> 546.5656
A42: 其他主营 毛利 | B42: 百万元 | G42: 36.88 | H42: =H25*假设!H69 -> 36.45 | I42: =I25*假设!I69 -> 36.45 | J42: =J25*假设!J69 -> 36.45 | K42: =K25*假设!K69 -> 36.45 | L42: =L25*假设!L69 -> 36.45
A43: 其他业务 毛利 | B43: 百万元 | G43: 110.3 | H43: =H26*假设!H74 -> 270 | I43: =I26*假设!I74 -> 283.5 | J43: =J26*假设!J74 -> 297 | K43: =K26*假设!K74 -> 310.5 | L43: =L26*假设!L74 -> 324
A44: 毛利合计 | B44: 百万元 | G44: =SUM(G38:G43) -> 3795.4 | H44: =SUM(H38:H43) -> 6032.937 | I44: =SUM(I38:I43) -> 7724.9702 | J44: =SUM(J38:J43) -> 8669.5061 | K44: =SUM(K38:K43) -> 9345.7263 | L44: =SUM(L38:L43) -> 9860.0709
A45: 分部毛利率
A46: 电子元件 | B46: % | F46: 0.4437 | G46: =IFERROR(G38/G19,0) -> 0.42303867 | H46: =IFERROR(H38/H19,0) -> 0.46 | I46: =IFERROR(I38/I19,0) -> 0.47 | J46: =IFERROR(J38/J19,0) -> 0.46 | K46: =IFERROR(K38/K19,0) -> 0.45 | L46: =IFERROR(L38/L19,0) -> 0.44
A47: 通信器件 | B47: % | F47: 0.4393 | G47: =IFERROR(G39/G20,0) -> 0.44355146 | H47: =IFERROR(H39/H20,0) -> 0.46 | I47: =IFERROR(I39/I20,0) -> 0.46 | J47: =IFERROR(J39/J20,0) -> 0.45 | K47: =IFERROR(K39/K20,0) -> 0.44 | L47: =IFERROR(L39/L20,0) -> 0.44
A48: 电子及陶瓷材料 | B48: % | F48: 0.4057 | G48: =IFERROR(G40/G21,0) -> 0.38086538 | H48: =IFERROR(H40/H21,0) -> 0.3864391 | I48: =IFERROR(I40/I21,0) -> 0.38748336 | J48: =IFERROR(J40/J21,0) -> 0.38324831 | K48: =IFERROR(K40/K21,0) -> 0.37313869 | L48: =IFERROR(L40/L21,0) -> 0.37283764
A49: 设备组件 | B49: % | G49: =IFERROR(G41/G24,0) -> 0.58462817 | H49: =IFERROR(H41/H24,0) -> 0.58 | I49: =IFERROR(I41/I24,0) -> 0.58 | J49: =IFERROR(J41/J24,0) -> 0.57 | K49: =IFERROR(K41/K24,0) -> 0.57 | L49: =IFERROR(L41/L24,0) -> 0.56
A50: 其他主营 | B50: % | G50: =IFERROR(G42/G25,0) -> 0.091061728 | H50: =IFERROR(H42/H25,0) -> 0.09 | I50: =IFERROR(I42/I25,0) -> 0.09 | J50: =IFERROR(J42/J25,0) -> 0.09 | K50: =IFERROR(K42/K25,0) -> 0.09 | L50: =IFERROR(L42/L25,0) -> 0.09
A51: 其他业务 | B51: % | G51: =IFERROR(G43/G26,0) -> 0.79564308 | H51: =IFERROR(H43/H26,0) -> 0.45 | I51: =IFERROR(I43/I26,0) -> 0.45 | J51: =IFERROR(J43/J26,0) -> 0.45 | K51: =IFERROR(K43/K26,0) -> 0.45 | L51: =IFERROR(L43/L26,0) -> 0.45
A52: 综合毛利率 | B52: % | G52: =IFERROR(G44/G27,0) -> 0.42137588 | H52: =IFERROR(H44/H27,0) -> 0.4398758 | I52: =IFERROR(I44/I27,0) -> 0.44668386 | J52: =IFERROR(J44/J27,0) -> 0.44082098 | K52: =IFERROR(K44/K27,0) -> 0.43277791 | L52: =IFERROR(L44/L27,0) -> 0.42847829
A54: E. 半年度校验：2026E全年隐含下半年
A55: 2026H1营业收入（半年报） | H55: =历史利润表!K6 -> 6423.3318
A56: 2026E隐含下半年营业收入 | H56: =H27-H55 -> 7291.76
A57: 2026E下半年/上半年 | H57: =IFERROR(H56/H55,0) -> 1.135199
A58: 2026Q2单季收入×2（下半年环比持平参照） | H58: =季度数据!L5*2 -> 7484.6768
A59: 参照：2025年下半年/上半年 | H59: =IFERROR((历史利润表!I6-历史利润表!J6)/历史利润表!J6,0) -> 1.1710289

Sheet 三表预测
A1: 三表联动预测（利润表、资产负债表、现金流量表）
A2: 2021A-2025A链接历史报表（绿字）；2026E-2030E为公式。货币资金由现金流量表倒挤，资产负债表自动配平。
A4: 项目（百万元） | B4: 说明 | C4: 2021A | D4: 2022A | E4: 2023A | F4: 2024A | G4: 2025A | H4: 2026E | I4: 2027E | J4: 2028E | K4: 2029E | L4: 2030E
A5: 利润表
A6: 营业收入 | C6: =N(历史利润表!E6) -> 6218.042 | D6: =N(历史利润表!F6) -> 5149.3869 | E6: =N(历史利润表!G6) -> 5726.6885 | F6: =N(历史利润表!H6) -> 7374.9908 | G6: =N(历史利润表!I6) -> 9007.1539 | H6: =分部预测!H27 -> 13715.092 | I6: =分部预测!I27 -> 17294.044 | J6: =分部预测!J27 -> 19666.727 | K6: =分部预测!K27 -> 21594.74 | L6: =分部预测!L27 -> 23011.833
A7: 同比增速 | D7: =IFERROR(D6/C6-1,0) -> -0.1718636 | E7: =IFERROR(E6/D6-1,0) -> 0.11211074 | F7: =IFERROR(F6/E6-1,0) -> 0.28782818 | G7: =IFERROR(G6/F6-1,0) -> 0.22131053 | H7: =IFERROR(H6/G6-1,0) -> 0.52268874 | I7: =IFERROR(I6/H6-1,0) -> 0.26094991 | J7: =IFERROR(J6/I6-1,0) -> 0.13719658 | K7: =IFERROR(K6/J6-1,0) -> 0.098034216 | L7: =IFERROR(L6/K6-1,0) -> 0.065622168
A8: 营业成本 | C8: =N(历史利润表!E8) -> 3186.5095 | D8: =N(历史利润表!F8) -> 2878.3209 | E8: =N(历史利润表!G8) -> 3445.5299 | F8: =N(历史利润表!H8) -> 4204.8637 | G8: =N(历史利润表!I8) -> 5211.7617 | H8: =H6-分部预测!H44 -> 7682.1548 | I8: =I6-分部预测!I44 -> 9569.0736 | J8: =J6-分部预测!J44 -> 10997.221 | K8: =K6-分部预测!K44 -> 12249.013 | L8: =L6-分部预测!L44 -> 13151.762
A9: 毛利 | C9: =C6-C8 -> 3031.5325 | D9: =D6-D8 -> 2271.066 | E9: =E6-E8 -> 2281.1586 | F9: =F6-F8 -> 3170.1271 | G9: =G6-G8 -> 3795.3922 | H9: =H6-H8 -> 6032.937 | I9: =I6-I8 -> 7724.9702 | J9: =J6-J8 -> 8669.5061 | ... L9: =L6-L8 -> 9860.0709
A10: 毛利率 | C10: =IFERROR(C9/C6,0) -> 0.48753812 | D10: =IFERROR(D9/D6,0) -> 0.44103619 | E10: =IFERROR(E9/E6,0) -> 0.39833817 | F10: =IFERROR(F9/F6,0) -> 0.42984828 | G10: =IFERROR(G9/G6,0) -> 0.4213753 | H10: =IFERROR(H9/H6,0) -> 0.4398758 | I10: =IFERROR(I9/I6,0) -> 0.44668386 | J10: =IFERROR(J9/J6,0) -> 0.44082098 | ... L10: =IFERROR(L9/L6,0) -> 0.42847829
A11: 税金及附加 | C11: =N(历史利润表!E9) -> 58.7828 | D11: =N(历史利润表!F9) -> 63.2677 | E11: =N(历史利润表!G9) -> 84.2832 | F11: =N(历史利润表!H9) -> 79.1745 | G11: =N(历史利润表!I9) -> 107.7827 | H11: =H6*假设!H98 -> 137.15092 | I11: =I6*假设!I98 -> 172.94044 | J11: =J6*假设!J98 -> 196.66727 | K11: =K6*假设!K98 -> 215.9474 | L11: =L6*假设!L98 -> 230.11833
A12: 销售费用 | C12: =N(历史利润表!E10) -> 51.3154 | D12: =N(历史利润表!F10) -> 57.308 | E12: =N(历史利润表!G10) -> 74.3431 | F12: =N(历史利润表!H10) -> 79.3918 | G12: =N(历史利润表!I10) -> 93.1993 | H12: =H6*假设!H99 -> 109.72073 | I12: =I6*假设!I99 -> 138.35235 | J12: =J6*假设!J99 -> 157.33382 | K12: =K6*假设!K99 -> 172.75792 | L12: =L6*假设!L99 -> 184.09467
A13: 管理费用 | C13: =N(历史利润表!E11) -> 453.2391 | D13: =N(历史利润表!F11) -> 479.3491 | E13: =N(历史利润表!G11) -> 429.4141 | F13: =N(历史利润表!H11) -> 409.8445 | G13: =N(历史利润表!I11) -> 480.9502 | H13: =H6*假设!H100 -> 589.74895 | I13: =I6*假设!I100 -> 726.34984 | J13: =J6*假设!J100 -> 826.00255 | K13: =K6*假设!K100 -> 885.38433 | L13: =L6*假设!L100 -> 943.48517
A14: 研发费用 | C14: =N(历史利润表!E12) -> 418.5388 | D14: =N(历史利润表!F12) -> 452.1724 | E14: =N(历史利润表!G12) -> 545.8062 | F14: =N(历史利润表!H12) -> 583.0724 | G14: =N(历史利润表!I12) -> 653.4367 | H14: =H6*假设!H101 -> 768.04514 | I14: =I6*假设!I101 -> 968.46645 | J14: =J6*假设!J101 -> 1121.0035 | K14: =K6*假设!K101 -> 1252.4949 | L14: =L6*假设!L101 -> 1334.6863
A15: 财务费用（负数为净收益） | C15: =N(历史利润表!E13) -> -96.1326 | D15: =N(历史利润表!F13) -> -174.2752 | E15: =N(历史利润表!G13) -> -161.5113 | F15: =N(历史利润表!H13) -> -172.5019 | G15: =N(历史利润表!I13) -> -127.772 | H15: =H17-H16 -> -176.85451 | I15: =I17-I16 -> -290.10275 | J15: =J17-J16 -> -298.56558 | K15: =K17-K16 -> -324.33187 | L15: =L17-L16 -> -383.43451
A16: 其中：利息收入 | C16: =N(历史利润表!E15) -> 103.223 | D16: =N(历史利润表!F15) -> 154.5883 | E16: =N(历史利润表!G15) -> 174.943 | F16: =N(历史利润表!H15) -> 203.5985 | G16: =N(历史利润表!I15) -> 196.88 | H16: =(G41+G52)*假设!H105 -> 196.72182 | I16: =(H41+H52)*假设!I105 -> 309.97006 | J16: =(I41+I52)*假设!J105 -> 318.43288 | K16: =(J41+J52)*假设!K105 -> 344.19918 | L16: =(K41+K52)*假设!L105 -> 403.30182
A17: 其中：利息费用 | C17: =N(历史利润表!E14) -> 5.6211 | D17: =N(历史利润表!F14) -> 8.8993 | E17: =N(历史利润表!G14) -> 22.4881 | F17: =N(历史利润表!H14) -> 27.7001 | G17: =N(历史利润表!I14) -> 20.396 | H17: =G55*假设!H106 -> 19.867309 | I17: =H55*假设!I106 -> 19.867309 | J17: =I55*假设!J106 -> 19.867309 | K17: =J55*假设!K106 -> 19.867309 | L17: =K55*假设!L106 -> 19.867309
A18: 其他收益 | C18: =N(历史利润表!E16) -> 136.3169 | D18: =N(历史利润表!F16) -> 218.1716 | E18: =N(历史利润表!G16) -> 348.6995 | F18: =N(历史利润表!H16) -> 305.0967 | G18: =N(历史利润表!I16) -> 390.1677 | H18: =H6*假设!H102 -> 301.73202 | I18: =I6*假设!I102 -> 345.88088 | J18: =J6*假设!J102 -> 354.00109 | K18: =K6*假设!K102 -> 345.51583 | L18: =L6*假设!L102 -> 345.1775
A19: 投资收益+公允价值变动 | C19: =N(历史利润表!E17)+N(历史利润表!E19) -> 74.986 | D19: =N(历史利润表!F17)+N(历史利润表!F19) -> 117.738 | E19: =N(历史利润表!G17)+N(历史利润表!G19) -> 111.5562 | F19: =N(历史利润表!H17)+N(历史利润表!H19) -> 66.8886 | G19: =N(历史利润表!I17)+N(历史利润表!I19) -> 72.1716 | H19: =G42*假设!H104 -> 60.136186 | I19: =H42*假设!I104 -> 60.136186 | J19: =I42*假设!J104 -> 60.136186 | K19: =J42*假设!K104 -> 60.136186 | L19: =K42*假设!L104 -> 60.136186
A20: 资产及信用减值损失 | C20: =N(历史利润表!E20)+N(历史利润表!E21) -> -58.719 | D20: =N(历史利润表!F20)+N(历史利润表!F21) -> -66.4599 | E20: =N(历史利润表!G20)+N(历史利润表!G21) -> 6.6362 | F20: =N(历史利润表!H20)+N(历史利润表!H21) -> -39.0838 | G20: =N(历史利润表!I20)+N(历史利润表!I21) -> -42.0392 | H20: =-H6*假设!H103 -> -137.15092 | I20: =-I6*假设!I103 -> -138.35235 | J20: =-J6*假设!J103 -> -157.33382 | K20: =-K6*假设!K103 -> -172.75792 | L20: =-L6*假设!L103 -> -184.09467
A21: 资产处置收益 | C21: =N(历史利润表!E22) -> -3.8453 | D21: =N(历史利润表!F22) -> -1.2666 | E21: =N(历史利润表!G22) -> 1.9312 | F21: =N(历史利润表!H22) -> -1.3421 | G21: =N(历史利润表!I22) -> 0.3699 | H21: =0 -> 0 | I21: =0 -> 0 | J21: =0 -> 0 | K21: =0 -> 0 | L21: =0 -> 0
A22: 营业利润 | C22: =C9-C11-C12-C13-C14-C15+C18+C19+C20+C21 -> 2294.5276 | D22: =D9-D11-D12-D13-D14-D15+D18+D19+D20+D21 -> 1661.4271 | E22: =E9-E11-E12-E13-E14-E15+E18+E19+E20+E21 -> 1777.6464 | F22: =F9-F11-F12-F13-F14-F15+F18+F19+F20+F21 -> 2522.7052 | G22: =G9-G11-G12-G13-G14-G15+G18+G19+G20+G21 -> 3008.4653 | H22: =H9-H11-H12-H13-H14-H15+H18+H19+H20+H21 -> 4829.8431 | I22: =I9-I11-I12-I13-I14-I15+I18+I19+I20+I21 -> 6276.6285 | J22: =J9-J11-J12-J13-J14-J15+J18+J19+J20+J21 -> 6923.868 | ... L22: =L9-L11-L12-L13-L14-L15+L18+L19+L20+L21 -> 7772.3399
A23: 营业外收支净额 | C23: =历史利润表!E24-历史利润表!E25 -> 9.0005 | D23: =历史利润表!F24-历史利润表!F25 -> 4.8907 | E23: =历史利润表!G24-历史利润表!G25 -> 5.201 | F23: =历史利润表!H24-历史利润表!H25 -> -3.7615 | G23: =历史利润表!I24-历史利润表!I25 -> -0.2892 | H23: =0 -> 0 | I23: =0 -> 0 | J23: =0 -> 0 | K23: =0 -> 0 | L23: =0 -> 0
A24: 利润总额 | C24: =C22+C23 -> 2303.5281 | D24: =D22+D23 -> 1666.3178 | E24: =E22+E23 -> 1782.8474 | F24: =F22+F23 -> 2518.9437 | G24: =G22+G23 -> 3008.1761 | H24: =H22+H23 -> 4829.8431 | I24: =I22+I23 -> 6276.6285 | J24: =J22+J23 -> 6923.868 | ... L24: =L22+L23 -> 7772.3399
A25: 所得税 | C25: =N(历史利润表!E27) -> 290.216 | D25: =N(历史利润表!F27) -> 160.2146 | E25: =N(历史利润表!G27) -> 199.697 | F25: =N(历史利润表!H27) -> 328.7101 | G25: =N(历史利润表!I27) -> 391.1963 | H25: =H24*假设!$C$18 -> 627.8796 | I25: =I24*假设!$C$18 -> 815.96171 | J25: =J24*假设!$C$18 -> 900.10284 | K25: =K24*假设!$C$18 -> 958.9278 | L25: =L24*假设!$C$18 -> 1010.4042
A26: 实际税率 | C26: =IFERROR(C25/C24,0) -> 0.12598761 | D26: =IFERROR(D25/D24,0) -> 0.096148886 | E26: =IFERROR(E25/E24,0) -> 0.11201015 | F26: =IFERROR(F25/F24,0) -> 0.13049522 | G26: =IFERROR(G25/G24,0) -> 0.13004435 | H26: =IFERROR(H25/H24,0) -> 0.13 | I26: =IFERROR(I25/I24,0) -> 0.13 | J26: =IFERROR(J25/J24,0) -> 0.13 | ... L26: =IFERROR(L25/L24,0) -> 0.13
A27: 净利润 | C27: =C24-C25 -> 2013.3121 | D27: =D24-D25 -> 1506.1032 | E27: =E24-E25 -> 1583.1504 | F27: =F24-F25 -> 2190.2336 | G27: =G24-G25 -> 2616.9798 | H27: =H24-H25 -> 4201.9635 | I27: =I24-I25 -> 5460.6668 | J27: =J24-J25 -> 6023.7652 | ... L27: =L24-L25 -> 6761.9358
A28: 少数股东损益 | C28: =N(历史利润表!E30) -> 2.5006 | D28: =N(历史利润表!F30) -> 1.3972 | E28: =N(历史利润表!G30) -> 2.1646 | F28: =N(历史利润表!H30) -> -0.2156 | G28: =N(历史利润表!I30) -> -1.4041 | H28: =H27*假设!$C$19 -> 0 | I28: =I27*假设!$C$19 -> 0 | J28: =J27*假设!$C$19 -> 0 | K28: =K27*假设!$C$19 -> 0 | L28: =L27*假设!$C$19 -> 0
A29: 归母净利润 | C29: =C27-C28 -> 2010.8115 | D29: =D27-D28 -> 1504.706 | E29: =E27-E28 -> 1580.9858 | F29: =F27-F28 -> 2190.4492 | G29: =G27-G28 -> 2618.3839 | H29: =H27-H28 -> 4201.9635 | I29: =I27-I28 -> 5460.6668 | J29: =J27-J28 -> 6023.7652 | ... L29: =L27-L28 -> 6761.9358
A30: 同比增速 | D30: =IFERROR(D29/C29-1,0) -> -0.25169217 | E30: =IFERROR(E29/D29-1,0) -> 0.050694156 | F30: =IFERROR(F29/E29-1,0) -> 0.38549581 | G30: =IFERROR(G29/F29-1,0) -> 0.1953639 | H30: =IFERROR(H29/G29-1,0) -> 0.60479274 | I30: =IFERROR(I29/H29-1,0) -> 0.29955124 | J30: =IFERROR(J29/I29-1,0) -> 0.10311897 | K30: =IFERROR(K29/J29-1,0) -> 0.065353601 | L30: =IFERROR(L29/K29-1,0) -> 0.053681196
A31: 归母净利率 | C31: =IFERROR(C29/C6,0) -> 0.32338339 | D31: =IFERROR(D29/D6,0) -> 0.29221071 | E31: =IFERROR(E29/E6,0) -> 0.2760733 | F31: =IFERROR(F29/F6,0) -> 0.29701043 | G31: =IFERROR(G29/G6,0) -> 0.29070047 | H31: =IFERROR(H29/H6,0) -> 0.30637516 | I31: =IFERROR(I29/I6,0) -> 0.31575419 | J31: =IFERROR(J29/J6,0) -> 0.3062922 | ... L31: =IFERROR(L29/L6,0) -> 0.29384603
A32: EPS（摊薄，元/股） | C32: =IFERROR(C29/股本与每股!C11,0) -> 1.0492117 | D32: =IFERROR(D29/股本与每股!D11,0) -> 0.78513335 | E32: =IFERROR(E29/股本与每股!E11,0) -> 0.82493502 | F32: =IFERROR(F29/股本与每股!F11,0) -> 1.142944 | G32: =IFERROR(G29/股本与每股!G11,0) -> 1.3699036 | H32: =IFERROR(H29/股本与每股!H11,0) -> 2.1257377 | I32: =IFERROR(I29/股本与每股!I11,0) -> 2.7625051 | J32: =IFERROR(J29/股本与每股!J11,0) -> 3.0473717 | ... L32: =IFERROR(L29/股本与每股!L11,0) -> 3.420806
A33: 利润表分析
A34: EBIT（剔除利息、投资收益与公允价值变动） | C34: =C22+C15-C19 -> 2123.409 | D34: =D22+D15-D19 -> 1369.4139 | E34: =E22+E15-E19 -> 1504.5789 | F34: =F22+F15-F19 -> 2283.3147 | G34: =G22+G15-G19 -> 2808.5217 | H34: =H22+H15-H19 -> 4592.8524 | I34: =I22+I15-I19 -> 5926.3896 | J34: =J22+J15-J19 -> 6565.1662 | ... L34: =L22+L15-L19 -> 7328.7693
A35: 折旧与摊销 | C35: =N(历史现金流量表!E43)+N(历史现金流量表!E44)+N(历史现金流量表!E45)+N(历史现金流量表!E46) -> 387.5088 | D35: =N(历史现金流量表!F43)+N(历史现金流量表!F44)+N(历史现金流量表!F45)+N(历史现金流量表!F46) -> 544.3751 | E35: =N(历史现金流量表!G43)+N(历史现金流量表!G44)+N(历史现金流量表!G45)+N(历史现金流量表!G46) -> 609.4324 | F35: =N(历史现金流量表!H43)+N(历史现金流量表!H44)+N(历史现金流量表!H45)+N(历史现金流量表!H46) -> 659.1195 | G35: =N(历史现金流量表!I43)+N(历史现金流量表!I44)+N(历史现金流量表!I45)+N(历史现金流量表!I46) -> 744.1504 | H35: =H68+H69 -> 787.81725 | I35: =I68+I69 -> 907.66826 | J35: =J68+J69 -> 1094.2364 | K35: =K68+K69 -> 1224.8492 | L35: =L68+L69 -> 1294.4416
A36: EBITDA | C36: =C34+C35 -> 2510.9178 | D36: =D34+D35 -> 1913.789 | E36: =E34+E35 -> 2114.0113 | F36: =F34+F35 -> 2942.4342 | G36: =G34+G35 -> 3552.6721 | H36: =H34+H35 -> 5380.6696 | I36: =I34+I35 -> 6834.0579 | J36: =J34+J35 -> 7659.4026 | ... L36: =L34+L35 -> 8623.2108
A37: EBITDA利润率 | C37: =IFERROR(C36/C6,0) -> 0.40381165 | D37: =IFERROR(D36/D6,0) -> 0.37165376 | E37: =IFERROR(E36/E6,0) -> 0.36915074 | F37: =IFERROR(F36/F6,0) -> 0.39897463 | G37: =IFERROR(G36/G6,0) -> 0.39442782 | H37: =IFERROR(H36/H6,0) -> 0.39231743 | I37: =IFERROR(I36/I6,0) -> 0.3951683 | J37: =IFERROR(J36/J6,0) -> 0.38945995 | ... L37: =IFERROR(L36/L6,0) -> 0.37472941
A38: 期间费用率（销售+管理+研发） | C38: =IFERROR((C12+C13+C14)/C6,0) -> 0.14845401 | D38: =IFERROR((D12+D13+D14)/D6,0) -> 0.19202859 | E38: =IFERROR((E12+E13+E14)/E6,0) -> 0.1832758 | F38: =IFERROR((F12+F13+F14)/F6,0) -> 0.14539797 | G38: =IFERROR((G12+G13+G14)/G6,0) -> 0.13629013 | H38: =IFERROR((H12+H13+H14)/H6,0) -> 0.107 | I38: =IFERROR((I12+I13+I14)/I6,0) -> 0.106 | J38: =IFERROR((J12+J13+J14)/J6,0) -> 0.107 | ... L38: =IFERROR((L12+L13+L14)/L6,0) -> 0.107
A39: 校验：营业利润-报告值（历史） | C39: =C22-历史利润表!E23 -> 0 | D39: =D22-历史利润表!F23 -> 0.0001 | E39: =E22-历史利润表!G23 -> -0.0001 | F39: =F22-历史利润表!H23 -> -0.0001 | G39: =G22-历史利润表!I23 -> -0.0003
A40: 资产负债表
A41: 货币资金 | C41: =N(历史资产负债表!E5) -> 5552.412 | D41: =N(历史资产负债表!F5) -> 4509.4292 | E41: =N(历史资产负债表!G5) -> 2841.6149 | F41: =N(历史资产负债表!H5) -> 3062.8452 | G41: =N(历史资产负债表!I5) -> 3057.7786 | H41: =G41+H82 -> 9614.3806 | I41: =H41+I82 -> 10875.503 | J41: =I41+J82 -> 13238.054 | K41: =J41+K82 -> 16521.534 | L41: =K41+L82 -> 20671.979
A42: 交易性金融资产 | C42: =N(历史资产负债表!E6) -> 2693.5949 | D42: =N(历史资产负债表!F6) -> 4255.0144 | E42: =N(历史资产负债表!G6) -> 3846.7081 | F42: =N(历史资产负债表!H6) -> 5053.3869 | G42: =N(历史资产负债表!I6) -> 3758.5116 | H42: =G42 -> 3758.5116 | I42: =H42 -> 3758.5116 | J42: =I42 -> 3758.5116 | K42: =J42 -> 3758.5116 | L42: =K42 -> 3758.5116
A43: 应收票据、账款及应收款项融资 | C43: =N(历史资产负债表!E7)+N(历史资产负债表!E10) -> 2276.8328 | D43: =N(历史资产负债表!F7)+N(历史资产负债表!F10) -> 1714.9956 | E43: =N(历史资产负债表!G7)+N(历史资产负债表!G10) -> 2259.271 | F43: =N(历史资产负债表!H7)+N(历史资产负债表!H10) -> 2686.3347 | G43: =N(历史资产负债表!I7)+N(历史资产负债表!I10) -> 3259.9217 | H43: =H6*假设!H108/365 -> 4884.8272 | I43: =I6*假设!I108/365 -> 6159.5224 | J43: =J6*假设!J108/365 -> 6896.825 | K43: =K6*假设!K108/365 -> 7572.9498 | L43: =L6*假设!L108/365 -> 7880.7648
A44: 预付款项 | C44: =N(历史资产负债表!E11) -> 56.4665 | D44: =N(历史资产负债表!F11) -> 22.8533 | E44: =N(历史资产负债表!G11) -> 45.7734 | F44: =N(历史资产负债表!H11) -> 62.2607 | G44: =N(历史资产负债表!I11) -> 75.5091 | H44: =H6*假设!H111 -> 123.43583 | I44: =I6*假设!I111 -> 155.64639 | J44: =J6*假设!J111 -> 177.00055 | K44: =K6*假设!K111 -> 194.35266 | L44: =L6*假设!L111 -> 207.1065
A45: 其他应收款 | C45: =N(历史资产负债表!E12) -> 151.249 | D45: =N(历史资产负债表!F12) -> 83.7475 | E45: =N(历史资产负债表!G12) -> 44.234 | F45: =N(历史资产负债表!H12) -> 28.6627 | G45: =N(历史资产负债表!I12) -> 18.4395 | H45: =H6*假设!H112 -> 27.430184 | I45: =I6*假设!I112 -> 34.588088 | J45: =J6*假设!J112 -> 39.333455 | K45: =K6*假设!K112 -> 43.189479 | L45: =L6*假设!L112 -> 46.023667
A46: 存货 | C46: =N(历史资产负债表!E16) -> 1796.5411 | D46: =N(历史资产负债表!F16) -> 1885.8512 | E46: =N(历史资产负债表!G16) -> 1753.5978 | F46: =N(历史资产负债表!H16) -> 2180.7115 | G46: =N(历史资产负债表!I16) -> 2391.7224 | H46: =H8*假设!H109/365 -> 3157.0499 | I46: =I8*假设!I109/365 -> 3932.496 | J46: =J8*假设!J109/365 -> 4519.4061 | K46: =K8*假设!K109/365 -> 4966.7232 | L46: =L8*假设!L109/365 -> 5332.7694
A47: 其他流动资产 | C47: =N(历史资产负债表!E17) -> 259.4314 | D47: =N(历史资产负债表!F17) -> 348.8942 | E47: =N(历史资产负债表!G17) -> 488.1799 | F47: =N(历史资产负债表!H17) -> 527.8337 | G47: =N(历史资产负债表!I17) -> 519.6397 | H47: =H6*假设!H113 -> 685.75459 | I47: =I6*假设!I113 -> 830.1141 | J47: =J6*假设!J113 -> 904.66946 | K47: =K6*假设!K113 -> 971.76329 | L47: =L6*假设!L113 -> 1035.5325
A48: 流动资产合计 | C48: =SUM(C41:C47) -> 12786.528 | D48: =SUM(D41:D47) -> 12820.785 | E48: =SUM(E41:E47) -> 11279.379 | F48: =SUM(F41:F47) -> 13602.035 | G48: =SUM(G41:G47) -> 13081.523 | H48: =SUM(H41:H47) -> 22251.39 | I48: =SUM(I41:I47) -> 25746.382 | J48: =SUM(J41:J47) -> 29533.8 | ... L48: =SUM(L41:L47) -> 38932.687
A49: 固定资产+在建工程 | C49: =N(历史资产负债表!E22)+N(历史资产负债表!E25) -> 5037.4875 | D49: =N(历史资产负债表!F22)+N(历史资产负债表!F25) -> 5881.0911 | E49: =N(历史资产负债表!G22)+N(历史资产负债表!G25) -> 5783.8854 | F49: =N(历史资产负债表!H22)+N(历史资产负债表!H25) -> 6327.452 | G49: =N(历史资产负债表!I22)+N(历史资产负债表!I25) -> 6589.7152 | H49: =G49+H73-H68 -> 7631.898 | I49: =H49+I73-I68 -> 9254.2297 | J49: =I49+J73-J68 -> 10389.993 | K49: =J49+K73-K68 -> 10995.144 | L49: =K49+L73-L68 -> 11230.702
A50: 无形资产、商誉、使用权资产及其他长期资产 | C50: =N(历史资产负债表!E19)+N(历史资产负债表!E20)+N(历史资产负债表!E21)+N(历史资产负债表!E27)+N(历史资产负债表!E28)+N(历史资产负债表!E29)+N(历史资产负债表!E30) -> 548.5102 | D50: =N(历史资产负债表!F19)+N(历史资产负债表!F20)+N(历史资产负债表!F21)+N(历史资产负债表!F27)+N(历史资产负债表!F28)+N(历史资产负债表!F29)+N(历史资产负债表!F30) -> 651.7735 | E50: =N(历史资产负债表!G19)+N(历史资产负债表!G20)+N(历史资产负债表!G21)+N(历史资产负债表!G27)+N(历史资产负债表!G28)+N(历史资产负债表!G29)+N(历史资产负债表!G30) -> 869.4089 | F50: =N(历史资产负债表!H19)+N(历史资产负债表!H20)+N(历史资产负债表!H21)+N(历史资产负债表!H27)+N(历史资产负债表!H28)+N(历史资产负债表!H29)+N(历史资产负债表!H30) -> 778.2482 | G50: =N(历史资产负债表!I19)+N(历史资产负债表!I20)+N(历史资产负债表!I21)+N(历史资产负债表!I27)+N(历史资产负债表!I28)+N(历史资产负债表!I29)+N(历史资产负债表!I30) -> 786.7931 | H50: =G50-H69 -> 756.7931 | I50: =H50-I69 -> 726.7931 | J50: =I50-J69 -> 696.7931 | K50: =J50-K69 -> 666.7931 | L50: =K50-L69 -> 636.7931
A51: 递延所得税资产 | C51: =N(历史资产负债表!E31) -> 98.7072 | D51: =N(历史资产负债表!F31) -> 187.4023 | E51: =N(历史资产负债表!G31) -> 182.164 | F51: =N(历史资产负债表!H31) -> 247.2083 | G51: =N(历史资产负债表!I31) -> 163.9345 | H51: =G51 -> 163.9345 | I51: =H51 -> 163.9345 | J51: =I51 -> 163.9345 | K51: =J51 -> 163.9345 | L51: =K51 -> 163.9345
A52: 其他非流动资产（主要为定期存款/大额存单） | C52: =N(历史资产负债表!E32) -> 148.8167 | D52: =N(历史资产负债表!F32) -> 52.3243 | E52: =N(历史资产负债表!G32) -> 3712.1273 | F52: =N(历史资产负债表!H32) -> 2960.8591 | G52: =N(历史资产负债表!I32) -> 5884.1223 | H52: =G52 -> 5884.1223 | I52: =H52 -> 5884.1223 | J52: =I52 -> 5884.1223 | K52: =J52 -> 5884.1223 | L52: =K52 -> 5884.1223
A53: 非流动资产合计 | C53: =SUM(C49:C52) -> 5833.5216 | D53: =SUM(D49:D52) -> 6772.5912 | E53: =SUM(E49:E52) -> 10547.586 | F53: =SUM(F49:F52) -> 10313.768 | G53: =SUM(G49:G52) -> 13424.565 | H53: =SUM(H49:H52) -> 14436.748 | I53: =SUM(I49:I52) -> 16029.08 | J53: =SUM(J49:J52) -> 17134.843 | ... L53: =SUM(L49:L52) -> 17915.552
A54: 资产总计 | C54: =C48+C53 -> 18620.049 | D54: =D48+D53 -> 19593.377 | E54: =E48+E53 -> 21826.965 | F54: =F48+F53 -> 23915.803 | G54: =G48+G53 -> 26506.088 | H54: =H48+H53 -> 36688.138 | I54: =I48+I53 -> 41775.461 | J54: =J48+J53 -> 46668.644 | ... L54: =L48+L53 -> 56848.24
A55: 有息负债（短期借款+一年内到期+长期借款） | C55: =N(历史资产负债表!E35)+N(历史资产负债表!E46)+N(历史资产负债表!E49) -> 49.9492 | D55: =N(历史资产负债表!F35)+N(历史资产负债表!F46)+N(历史资产负债表!F49) -> 185.4354 | E55: =N(历史资产负债表!G35)+N(历史资产负债表!G46)+N(历史资产负债表!G49) -> 745.2792 | F55: =N(历史资产负债表!H35)+N(历史资产负债表!H46)+N(历史资产负债表!H49) -> 479.3472 | G55: =N(历史资产负债表!I35)+N(历史资产负债表!I46)+N(历史资产负债表!I49) -> 567.6374 | H55: =G55 -> 567.6374 | I55: =H55 -> 567.6374 | J55: =I55 -> 567.6374 | K55: =J55 -> 567.6374 | L55: =K55 -> 567.6374
A56: 应付票据及应付账款 | C56: =N(历史资产负债表!E36) -> 830.1951 | D56: =N(历史资产负债表!F36) -> 635.0511 | E56: =N(历史资产负债表!G36) -> 980.6995 | F56: =N(历史资产负债表!H36) -> 1295.3039 | G56: =N(历史资产负债表!I36) -> 1927.9853 | H56: =H8*假设!H110/365 -> 2736.1099 | I56: =I8*假设!I110/365 -> 3355.7299 | J56: =J8*假设!J110/365 -> 3766.1717 | K56: =K8*假设!K110/365 -> 4194.8676 | L56: =L8*假设!L110/365 -> 4504.0282
A57: 其他流动负债合计 | C57: =N(历史资产负债表!E39)+N(历史资产负债表!E40)+N(历史资产负债表!E41)+N(历史资产负债表!E42)+N(历史资产负债表!E43)+N(历史资产负债表!E47) -> 693.8564 | D57: =N(历史资产负债表!F39)+N(历史资产负债表!F40)+N(历史资产负债表!F41)+N(历史资产负债表!F42)+N(历史资产负债表!F43)+N(历史资产负债表!F47) -> 662.8052 | E57: =N(历史资产负债表!G39)+N(历史资产负债表!G40)+N(历史资产负债表!G41)+N(历史资产负债表!G42)+N(历史资产负债表!G43)+N(历史资产负债表!G47) -> 674.5635 | F57: =N(历史资产负债表!H39)+N(历史资产负债表!H40)+N(历史资产负债表!H41)+N(历史资产负债表!H42)+N(历史资产负债表!H43)+N(历史资产负债表!H47) -> 819.6007 | G57: =N(历史资产负债表!I39)+N(历史资产负债表!I40)+N(历史资产负债表!I41)+N(历史资产负债表!I42)+N(历史资产负债表!I43)+N(历史资产负债表!I47) -> 1009.7921 | H57: =H6*假设!H114 -> 1508.6601 | I57: =I6*假设!I114 -> 1902.3448 | J57: =J6*假设!J114 -> 2163.34 | K57: =K6*假设!K114 -> 2375.4214 | L57: =L6*假设!L114 -> 2531.3017
A58: 非流动负债（租赁、递延收益、递延所得税等） | C58: =N(历史资产负债表!E50)+N(历史资产负债表!E51)+N(历史资产负债表!E54)+N(历史资产负债表!E55)+N(历史资产负债表!E56)+N(历史资产负债表!E57) -> 854.475 | D58: =N(历史资产负债表!F50)+N(历史资产负债表!F51)+N(历史资产负债表!F54)+N(历史资产负债表!F55)+N(历史资产负债表!F56)+N(历史资产负债表!F57) -> 1006.6733 | E58: =N(历史资产负债表!G50)+N(历史资产负债表!G51)+N(历史资产负债表!G54)+N(历史资产负债表!G55)+N(历史资产负债表!G56)+N(历史资产负债表!G57) -> 1187.3221 | F58: =N(历史资产负债表!H50)+N(历史资产负债表!H51)+N(历史资产负债表!H54)+N(历史资产负债表!H55)+N(历史资产负债表!H56)+N(历史资产负债表!H57) -> 1449.7828 | G58: =N(历史资产负债表!I50)+N(历史资产负债表!I51)+N(历史资产负债表!I54)+N(历史资产负债表!I55)+N(历史资产负债表!I56)+N(历史资产负债表!I57) -> 1337.6307 | H58: =G58 -> 1337.6307 | I58: =H58 -> 1337.6307 | J58: =I58 -> 1337.6307 | K58: =J58 -> 1337.6307 | L58: =K58 -> 1337.6307
A59: 负债合计 | C59: =SUM(C55:C58) -> 2428.4757 | D59: =SUM(D55:D58) -> 2489.965 | E59: =SUM(E55:E58) -> 3587.8643 | F59: =SUM(F55:F58) -> 4044.0346 | G59: =SUM(G55:G58) -> 4843.0455 | H59: =SUM(H55:H58) -> 6150.0381 | I59: =SUM(I55:I58) -> 7163.3428 | J59: =SUM(J55:J58) -> 7834.7798 | ... L59: =SUM(L55:L58) -> 8940.598
A60: 归母所有者权益 | C60: =N(历史资产负债表!E66) -> 16190.297 | D60: =N(历史资产负债表!F66) -> 17099.674 | E60: =N(历史资产负债表!G66) -> 18233.198 | F60: =N(历史资产负债表!H66) -> 19866.081 | G60: =N(历史资产负债表!I66) -> 21658.759 | H60: =G60+H29-H76-H77+H78 -> 30533.817 | I60: =H60+I29-I76-I77+I78 -> 34607.836 | J60: =I60+J29-J76-J77+J78 -> 38829.581 | K60: =J60+K29-K76-K77+K78 -> 43259.178 | L60: =K60+L29-L76-L77+L78 -> 47903.359
A61: 少数股东权益 | C61: =N(历史资产负债表!E67) -> 1.2769 | D61: =N(历史资产负债表!F67) -> 3.7382 | E61: =N(历史资产负债表!G67) -> 5.9029 | F61: =N(历史资产负债表!H67) -> 5.6872 | G61: =N(历史资产负债表!I67) -> 4.2831 | H61: =G61+H28 -> 4.2831 | I61: =H61+I28 -> 4.2831 | J61: =I61+J28 -> 4.2831 | K61: =J61+K28 -> 4.2831 | L61: =K61+L28 -> 4.2831
A62: 所有者权益合计 | C62: =C60+C61 -> 16191.574 | D62: =D60+D61 -> 17103.412 | E62: =E60+E61 -> 18239.101 | F62: =F60+F61 -> 19871.768 | G62: =G60+G61 -> 21663.042 | H62: =H60+H61 -> 30538.1 | I62: =I60+I61 -> 34612.119 | J62: =J60+J61 -> 38833.864 | ... L62: =L60+L61 -> 47907.642
A63: 负债和所有者权益总计 | C63: =C59+C62 -> 18620.049 | D63: =D59+D62 -> 19593.377 | E63: =E59+E62 -> 21826.965 | F63: =F59+F62 -> 23915.803 | G63: =G59+G62 -> 26506.088 | H63: =H59+H62 -> 36688.138 | I63: =I59+I62 -> 41775.462 | J63: =J59+J62 -> 46668.644 | ... L63: =L59+L62 -> 56848.24
A64: 校验：资产-负债-权益 | C64: =ROUND(C54-C63,3) -> 0 | D64: =ROUND(D54-D63,3) -> 0 | E64: =ROUND(E54-E63,3) -> 0 | F64: =ROUND(F54-F63,3) -> 0 | G64: =ROUND(G54-G63,3) -> 0 | H64: =ROUND(H54-H63,3) -> 0 | I64: =ROUND(I54-I63,3) -> 0 | J64: =ROUND(J54-J63,3) -> 0 | ... L64: =ROUND(L54-L63,3) -> 0
A65: 校验：资产总计-报告值（历史） | C65: =ROUND(C54-历史资产负债表!E34,3) -> 0 | D65: =ROUND(D54-历史资产负债表!F34,3) -> 0 | E65: =ROUND(E54-历史资产负债表!G34,3) -> 0 | F65: =ROUND(F54-历史资产负债表!H34,3) -> 0 | G65: =ROUND(G54-历史资产负债表!I34,3) -> 0
A66: 现金流量表（预测为间接法；历史为报告值）
A67: 净利润 | C67: =N(历史现金流量表!E40) -> 2013.312 | D67: =N(历史现金流量表!F40) -> 1506.1032 | E67: =N(历史现金流量表!G40) -> 1583.1506 | F67: =N(历史现金流量表!H40) -> 2190.2338 | G67: =N(历史现金流量表!I40) -> 2616.9802 | H67: =H27 -> 4201.9635 | I67: =I27 -> 5460.6668 | J67: =J27 -> 6023.7652 | K67: =K27 -> 6417.4399 | L67: =L27 -> 6761.9358
A68: 固定资产折旧 | C68: =N(历史现金流量表!E43) -> 364.7864 | D68: =N(历史现金流量表!F43) -> 515.7214 | E68: =N(历史现金流量表!G43) -> 583.1808 | F68: =N(历史现金流量表!H43) -> 632.0889 | G68: =N(历史现金流量表!I43) -> 715.1475 | H68: =G49*假设!H119 -> 757.81725 | I68: =H49*假设!I119 -> 877.66826 | J68: =I49*假设!J119 -> 1064.2364 | K68: =J49*假设!K119 -> 1194.8492 | L68: =K49*假设!L119 -> 1264.4416
A69: 无形资产及其他摊销 | C69: =N(历史现金流量表!E44)+N(历史现金流量表!E45)+N(历史现金流量表!E46) -> 22.7224 | D69: =N(历史现金流量表!F44)+N(历史现金流量表!F45)+N(历史现金流量表!F46) -> 28.6537 | E69: =N(历史现金流量表!G44)+N(历史现金流量表!G45)+N(历史现金流量表!G46) -> 26.2516 | F69: =N(历史现金流量表!H44)+N(历史现金流量表!H45)+N(历史现金流量表!H46) -> 27.0306 | G69: =N(历史现金流量表!I44)+N(历史现金流量表!I45)+N(历史现金流量表!I46) -> 29.0029 | H69: =假设!H120 -> 30 | I69: =假设!I120 -> 30 | J69: =假设!J120 -> 30 | K69: =假设!K120 -> 30 | L69: =假设!L120 -> 30
A70: 营运资本变动（增加为负） | C70: =历史现金流量表!E54+历史现金流量表!E55+历史现金流量表!E56 -> -1302.7071 | D70: =历史现金流量表!F54+历史现金流量表!F55+历史现金流量表!F56 -> 129.5803 | E70: =历史现金流量表!G54+历史现金流量表!G55+历史现金流量表!G56 -> -335.6004 | F70: =历史现金流量表!H54+历史现金流量表!H55+历史现金流量表!H56 -> -360.6942 | G70: =历史现金流量表!I54+历史现金流量表!I55+历史现金流量表!I56 -> -322.7482 | H70: =-((H43+H44+H45+H46+H47-H56-H57)-(G43+G44+G45+G46+G47-G56-G57)) -> -1306.2727 | I70: =-((I43+I44+I45+I46+I47-I56-I57)-(H43+H44+H45+H46+H47-H56-H57)) -> -1220.5646 | J70: =-((J43+J44+J45+J46+J47-J56-J57)-(I43+I44+I45+I46+I47-I56-I57)) -> -753.43047 | K70: =-((K43+K44+K45+K46+K47-K56-K57)-(J43+J44+J45+J46+J47-J56-J57)) -> -570.96674 | L70: =-((L43+L44+L45+L46+L47-L56-L57)-(K43+K44+K45+K46+K47-K56-K57)) -> -288.17752
A71: 其他非现金项目（历史） | C71: =历史现金流量表!E14-C67-C68-C69-C70 -> 56.2085 | D71: =历史现金流量表!F14-D67-D68-D69-D70 -> -106.185 | E71: =历史现金流量表!G14-E67-E68-E69-E70 -> -138.0146 | F71: =历史现金流量表!H14-F67-F68-F69-F70 -> -85.5368 | G71: =历史现金流量表!I14-G67-G68-G69-G70 -> -160.7733 | H71: =0 -> 0 | I71: =0 -> 0 | J71: =0 -> 0 | K71: =0 -> 0 | L71: =0 -> 0
A72: 经营活动现金流量净额 | C72: =历史现金流量表!E14 -> 1154.3222 | D72: =历史现金流量表!F14 -> 2073.8736 | E72: =历史现金流量表!G14 -> 1718.968 | F72: =历史现金流量表!H14 -> 2403.1223 | G72: =历史现金流量表!I14 -> 2877.6091 | H72: =H67+H68+H69+H70+H71 -> 3683.508 | I72: =I67+I68+I69+I70+I71 -> 5147.7705 | J72: =J67+J68+J69+J70+J71 -> 6364.5711 | K72: =K67+K68+K69+K70+K71 -> 7071.3224 | L72: =L67+L68+L69+L70+L71 -> 7768.1998
A73: 资本开支 | C73: =历史现金流量表!E20 -> 1910.3652 | D73: =历史现金流量表!F20 -> 1124.8091 | E73: =历史现金流量表!G20 -> 545.8847 | F73: =历史现金流量表!H20 -> 639.0352 | G73: =历史现金流量表!I20 -> 580.092 | H73: =假设!H118 -> 1800 | I73: =假设!I118 -> 2500 | J73: =假设!J118 -> 2200 | K73: =假设!K118 -> 1800 | L73: =假设!L118 -> 1500
A74: 其他投资活动（交易性金融资产、定期存款等变动） | C74: =历史现金流量表!E24+C73 -> 33.601 | D74: =历史现金流量表!F24+D73 -> -2681.9178 | E74: =历史现金流量表!G24+E73 -> -3229.0403 | F74: =历史现金流量表!H24+F73 -> -714.8959 | G74: =历史现金流量表!I24+G73 -> -244.2684 | H74: =-(H42-G42)-(H52-G52)-(H51-G51) -> 0 | I74: =-(I42-H42)-(I52-H52)-(I51-H51) -> 0 | J74: =-(J42-I42)-(J52-I52)-(J51-I51) -> 0 | K74: =-(K42-J42)-(K52-J52)-(K51-J51) -> 0 | L74: =-(L42-K42)-(L52-K52)-(L51-K51) -> 0
A75: 投资活动现金流量净额 | C75: =历史现金流量表!E24 -> -1876.7642 | D75: =历史现金流量表!F24 -> -3806.7269 | E75: =历史现金流量表!G24 -> -3774.925 | F75: =历史现金流量表!H24 -> -1353.9311 | G75: =历史现金流量表!I24 -> -824.3604 | H75: =-H73+H74 -> -1800 | I75: =-I73+I74 -> -2500 | J75: =-J73+J74 -> -2200 | K75: =-K73+K74 -> -1800 | L75: =-L73+L74 -> -1500
A76: 现金股利 | C76: =历史现金流量表!E31 -> 454.2265 | D76: =历史现金流量表!F31 -> 617.7758 | E76: =历史现金流量表!G31 -> 489.9347 | F76: =历史现金流量表!H31 -> 553.6596 | G76: =历史现金流量表!I31 -> 726.6256 | H76: =股本与每股!H12 -> 860.11 | I76: =股本与每股!I12 -> 1386.6479 | J76: =股本与每股!J12 -> 1802.0201 | K76: =股本与每股!K12 -> 1987.8425 | L76: =股本与每股!L12 -> 2117.7552
A77: 股份回购 | C77: =0 -> 0 | D77: =0 -> 0 | E77: =0 -> 0 | F77: =0 -> 0 | G77: =股本与每股!G8 -> 175.42 | H77: =股本与每股!H8 -> 1645 | I77: =股本与每股!I8 -> 0 | J77: =股本与每股!J8 -> 0 | K77: =股本与每股!K8 -> 0 | L77: =股本与每股!L8 -> 0
A78: H股募资净额 | C78: =0 -> 0 | D78: =0 -> 0 | E78: =0 -> 0 | F78: =0 -> 0 | G78: =0 -> 0 | H78: =股本与每股!H6 -> 7178.204 | I78: =股本与每股!I6 -> 0 | J78: =股本与每股!J6 -> 0 | K78: =股本与每股!K6 -> 0 | L78: =股本与每股!L6 -> 0
A79: 其他筹资活动（借款变动、非流动负债变动等） | C79: =历史现金流量表!E35+C76+C77-C78 -> 3782.3355 | D79: =历史现金流量表!F35+D76+D77-D78 -> -11.1512 | E79: =历史现金流量表!G35+E76+E77-E78 -> 643.8705 | F79: =历史现金流量表!H35+F76+F77-F78 -> -651.8675 | G79: =历史现金流量表!I35+G76+G77-G78 -> 8.365 | H79: =(H55-G55)+(H58-G58) -> 0 | I79: =(I55-H55)+(I58-H58) -> 0 | J79: =(J55-I55)+(J58-I58) -> 0 | K79: =(K55-J55)+(K58-J58) -> 0 | L79: =(L55-K55)+(L58-K58) -> 0
A80: 筹资活动现金流量净额 | C80: =历史现金流量表!E35 -> 3328.109 | D80: =历史现金流量表!F35 -> -628.927 | E80: =历史现金流量表!G35 -> 153.9358 | F80: =历史现金流量表!H35 -> -1205.5271 | G80: =历史现金流量表!I35 -> -893.6806 | H80: =-H76-H77+H78+H79 -> 4673.094 | I80: =-I76-I77+I78+I79 -> -1386.6479 | J80: =-J76-J77+J78+J79 -> -1802.0201 | K80: =-K76-K77+K78+K79 -> -1987.8425 | L80: =-L76-L77+L78+L79 -> -2117.7552
A81: 汇率变动影响 | C81: =历史现金流量表!E36 -> -8.1464 | D81: =历史现金流量表!F36 -> 9.9994 | E81: =历史现金流量表!G36 -> 7.436 | F81: =历史现金流量表!H36 -> -0.4631 | G81: =历史现金流量表!I36 -> -14.4299 | H81: =0 -> 0 | I81: =0 -> 0 | J81: =0 -> 0 | K81: =0 -> 0 | L81: =0 -> 0
A82: 现金净增加额 | C82: =C72+C75+C80+C81 -> 2597.5206 | D82: =D72+D75+D80+D81 -> -2351.7809 | E82: =E72+E75+E80+E81 -> -1894.5852 | F82: =F72+F75+F80+F81 -> -156.799 | G82: =G72+G75+G80+G81 -> 1145.1382 | H82: =H72+H75+H80+H81 -> 6556.602 | I82: =I72+I75+I80+I81 -> 1261.1226 | J82: =J72+J75+J80+J81 -> 2362.551 | ... L82: =L72+L75+L80+L81 -> 4150.4446
A83: 自由现金流（经营现金流-资本开支） | C83: =C72-C73 -> -756.043 | D83: =D72-D73 -> 949.0645 | E83: =E72-E73 -> 1173.0833 | F83: =F72-F73 -> 1764.0871 | G83: =G72-G73 -> 2297.5171 | H83: =H72-H73 -> 1883.508 | I83: =I72-I73 -> 2647.7705 | J83: =J72-J73 -> 4164.5711 | ... L83: =L72-L73 -> 6268.1998
A84: 校验：现金净增加额-报告值（历史） | C84: =ROUND(C82-历史现金流量表!E37,3) -> 0 | D84: =ROUND(D82-历史现金流量表!F37,3) -> 0 | E84: =ROUND(E82-历史现金流量表!G37,3) -> 0 | F84: =ROUND(F82-历史现金流量表!H37,3) -> 0 | G84: =ROUND(G82-历史现金流量表!I37,3) -> 0
A85: 关键比率
A86: ROE（归母，期末权益） | C86: =IFERROR(C29/C60,0) -> 0.12419856 | D86: =IFERROR(D29/D60,0) -> 0.087996183 | E86: =IFERROR(E29/E60,0) -> 0.08670919 | F86: =IFERROR(F29/F60,0) -> 0.11026076 | G86: =IFERROR(G29/G60,0) -> 0.12089261 | H86: =IFERROR(H29/H60,0) -> 0.13761671 | I86: =IFERROR(I29/I60,0) -> 0.15778701 | J86: =IFERROR(J29/J60,0) -> 0.15513341 | ... L86: =IFERROR(L29/L60,0) -> 0.14115786
A87: ROE（归母，平均权益） | D87: =IFERROR(D29/AVERAGE(C60,D60),0) -> 0.090399961 | E87: =IFERROR(E29/AVERAGE(D60,E60),0) -> 0.089490933 | F87: =IFERROR(F29/AVERAGE(E60,F60),0) -> 0.11498639 | G87: =IFERROR(G29/AVERAGE(F60,G60),0) -> 0.12611169 | H87: =IFERROR(H29/AVERAGE(G60,H60),0) -> 0.16101767 | I87: =IFERROR(I29/AVERAGE(H60,I60),0) -> 0.16765515 | J87: =IFERROR(J29/AVERAGE(I60,J60),0) -> 0.16405166 | K87: =IFERROR(K29/AVERAGE(J60,K60),0) -> 0.15635368 | L87: =IFERROR(L29/AVERAGE(K60,L60),0) -> 0.148349
A88: ROA | C88: =IFERROR(C27/C54,0) -> 0.10812603 | D88: =IFERROR(D27/D54,0) -> 0.076867976 | E88: =IFERROR(E27/E54,0) -> 0.072531862 | F88: =IFERROR(F27/F54,0) -> 0.091581019 | G88: =IFERROR(G27/G54,0) -> 0.098731274 | H88: =IFERROR(H27/H54,0) -> 0.11453194 | I88: =IFERROR(I27/I54,0) -> 0.1307147 | J88: =IFERROR(J27/J54,0) -> 0.12907521 | ... L88: =IFERROR(L27/L54,0) -> 0.11894714
A89: ROIC（EBIT×(1-税率)/(权益+有息负债-现金类资产)） | C89: =IFERROR(C34*(1-假设!$C$18)/(C62+C55-C41-C42-C52),0) -> 0.23543223 | D89: =IFERROR(D34*(1-假设!$C$18)/(D62+D55-D41-D42-D52),0) -> 0.14062547 | E89: =IFERROR(E34*(1-假设!$C$18)/(E62+E55-E41-E42-E52),0) -> 0.15249236 | F89: =IFERROR(F34*(1-假设!$C$18)/(F62+F55-F41-F42-F52),0) -> 0.21419868 | G89: =IFERROR(G34*(1-假设!$C$18)/(G62+G55-G41-G42-G52),0) -> 0.25638461 | H89: =IFERROR(H34*(1-假设!$C$18)/(H62+H55-H41-H42-H52),0) -> 0.33723311 | I89: =IFERROR(I34*(1-假设!$C$18)/(I62+I55-I41-I42-I52),0) -> 0.35166368 | J89: =IFERROR(J34*(1-假设!$C$18)/(J62+J55-J41-J42-J52),0) -> 0.34572721 | ... L89: =IFERROR(L34*(1-假设!$C$18)/(L62+L55-L41-L42-L52),0) -> 0.35109004
A90: 应收周转天数 | C90: =IFERROR(C43/C6*365,0) -> 133.65043 | D90: =IFERROR(D43/D6*365,0) -> 121.5627 | E90: =IFERROR(E43/E6*365,0) -> 143.99839 | F90: =IFERROR(F43/F6*365,0) -> 132.95097 | G90: =IFERROR(G43/G6*365,0) -> 132.10293 | H90: =IFERROR(H43/H6*365,0) -> 130 | I90: =IFERROR(I43/I6*365,0) -> 130 | J90: =IFERROR(J43/J6*365,0) -> 128 | ... L90: =IFERROR(L43/L6*365,0) -> 125
A91: 存货周转天数 | C91: =IFERROR(C46/C8*365,0) -> 205.78552 | D91: =IFERROR(D46/D8*365,0) -> 239.14487 | E91: =IFERROR(E46/E8*365,0) -> 185.76626 | F91: =IFERROR(F46/F8*365,0) -> 189.29501 | G91: =IFERROR(G46/G8*365,0) -> 167.50165 | H91: =IFERROR(H46/H8*365,0) -> 150 | I91: =IFERROR(I46/I8*365,0) -> 150 | J91: =IFERROR(J46/J8*365,0) -> 150 | ... L91: =IFERROR(L46/L8*365,0) -> 148
A92: 应付周转天数 | C92: =IFERROR(C56/C8*365,0) -> 95.095028 | D92: =IFERROR(D56/D8*365,0) -> 80.530858 | E92: =IFERROR(E56/E8*365,0) -> 103.88977 | F92: =IFERROR(F56/F8*365,0) -> 112.43787 | G92: =IFERROR(G56/G8*365,0) -> 135.02433 | H92: =IFERROR(H56/H8*365,0) -> 130 | I92: =IFERROR(I56/I8*365,0) -> 128 | J92: =IFERROR(J56/J8*365,0) -> 125 | ... L92: =IFERROR(L56/L8*365,0) -> 125
A93: 净现金（货币资金+交易性金融资产+类现金定期存款-有息负债） | C93: =C41+C42+C52*假设!$C$30-C55 -> 8329.9927 | D93: =D41+D42+D52*假设!$C$30-D55 -> 8626.1001 | E93: =E41+E42+E52*假设!$C$30-E55 -> 9283.9584 | F93: =F41+F42+F52*假设!$C$30-F55 -> 10301.658 | G93: =G41+G42+G52*假设!$C$30-G55 -> 11544.363 | H93: =H41+H42+H52*假设!$C$30-H55 -> 18100.965 | I93: =I41+I42+I52*假设!$C$30-I55 -> 19362.087 | J93: =J41+J42+J52*假设!$C$30-J55 -> 21724.639 | ... L93: =L41+L42+L52*假设!$C$30-L55 -> 29158.563
A94: 资本开支/收入 | C94: =IFERROR(C73/C6,0) -> 0.30722938 | D94: =IFERROR(D73/D6,0) -> 0.21843554 | E94: =IFERROR(E73/E6,0) -> 0.095322925 | F94: =IFERROR(F73/F6,0) -> 0.086648949 | G94: =IFERROR(G73/G6,0) -> 0.064403474 | H94: =IFERROR(H73/H6,0) -> 0.13124229 | I94: =IFERROR(I73/I6,0) -> 0.14455844 | J94: =IFERROR(J73/J6,0) -> 0.11186406 | ... L94: =IFERROR(L73/L6,0) -> 0.065183855
A95: 分红率（当年派息/上年归母净利润） | D95: =IFERROR(D76/C29,0) -> 0.30722711 | E95: =IFERROR(E76/D29,0) -> 0.32560161 | F95: =IFERROR(F76/E29,0) -> 0.35019897 | G95: =IFERROR(G76/F29,0) -> 0.33172447 | H95: =IFERROR(H76/G29,0) -> 0.32848888 | I95: =IFERROR(I76/H29,0) -> 0.33 | J95: =IFERROR(J76/I29,0) -> 0.33 | K95: =IFERROR(K76/J29,0) -> 0.33 | L95: =IFERROR(L76/K29,0) -> 0.33
A96: 每股净资产（元） | C96: =IFERROR(C60/股本与每股!C11,0) -> 8.4478575 | D96: =IFERROR(D60/股本与每股!D11,0) -> 8.9223569 | E96: =IFERROR(E60/股本与每股!E11,0) -> 9.513813 | F96: =IFERROR(F60/股本与每股!F11,0) -> 10.365827 | G96: =IFERROR(G60/股本与每股!G11,0) -> 11.331575 | H96: =IFERROR(H60/股本与每股!H11,0) -> 15.446799 | I96: =IFERROR(I60/股本与每股!I11,0) -> 17.507811 | J96: =IFERROR(J60/股本与每股!J11,0) -> 19.643556 | ... L96: =IFERROR(L60/股本与每股!L11,0) -> 24.233903
A97: PE（当前股价） | C97: =IFERROR(假设!$C$6/C32,0) -> 112.94193 | D97: =IFERROR(假设!$C$6/D32,0) -> 150.92978 | E97: =IFERROR(假设!$C$6/E32,0) -> 143.64768 | F97: =IFERROR(假设!$C$6/F32,0) -> 103.67962 | G97: =IFERROR(假设!$C$6/G32,0) -> 86.502435 | H97: =IFERROR(假设!$C$6/H32,0) -> 55.745354 | I97: =IFERROR(假设!$C$6/I32,0) -> 42.895849 | J97: =IFERROR(假设!$C$6/J32,0) -> 38.885968 | ... L97: =IFERROR(假设!$C$6/L32,0) -> 34.640959
A98: PB（当前股价） | C98: =IFERROR(假设!$C$6/C96,0) -> 14.027225 | D98: =IFERROR(假设!$C$6/D96,0) -> 13.281244 | E98: =IFERROR(假设!$C$6/E96,0) -> 12.455574 | F98: =IFERROR(假设!$C$6/F96,0) -> 11.431794 | G98: =IFERROR(假设!$C$6/G96,0) -> 10.457505 | H98: =IFERROR(假设!$C$6/H96,0) -> 7.6714923 | I98: =IFERROR(假设!$C$6/I96,0) -> 6.7684077 | J98: =IFERROR(假设!$C$6/J96,0) -> 6.0325127 | ... L98: =IFERROR(假设!$C$6/L96,0) -> 4.8898438

Sheet 股本与每股
A1: 股本、库存股与H股募资
A2: 期末口径：总股本扣除库存股（用于摊薄EPS与每股价值）。H股于2026-07-09上市。
A4: 项目 | B4: 单位 | C4: 2021A | D4: 2022A | E4: 2023A | F4: 2024A | G4: 2025A | H4: 2026E | I4: 2027E | J4: 2028E | K4: 2029E | L4: 2030E
A5: H股新发股数 | B5: 百万股 | H5: =假设!$C$9/1000000 -> 80.2212 | I5: 0 | J5: 0 | K5: 0 | L5: 0
A6: H股募资净额 | B6: 百万元 | H6: =假设!$C$9*假设!$C$7*假设!$C$8*(1-假设!$C$10)/1000000 -> 7178.204 | I6: 0 | J6: 0 | K6: 0 | L6: 0
A7: 期末总股本 | B7: 百万股 | C7: 1916.4974 | D7: 1916.4974 | E7: 1916.4974 | F7: 1916.4974 | G7: =假设!$C$11/1000000 -> 1916.4974 | H7: =G7+H5 -> 1996.7186 | I7: =H7+I5 -> 1996.7186 | J7: =I7+J5 -> 1996.7186 | K7: =J7+K5 -> 1996.7186 | L7: =K7+L5 -> 1996.7186
A8: 当年回购金额 | B8: 百万元 | G8: 175.42 | H8: =假设!$C$14+假设!$C$15 -> 1645 | I8: 0 | J8: 0 | K8: 0 | L8: 0
A9: 当年回购股数 | B9: 百万股 | G9: 5.1338 | H9: =假设!$C$13/1000000+IFERROR(假设!$C$15/假设!$C$6,0) -> 14.876414 | I9: 0 | J9: 0 | K9: 0 | L9: 0
A10: 期末库存股 | B10: 百万股 | C10: 0 | D10: 0 | E10: 0 | F10: 0 | G10: =假设!$C$12/1000000 -> 5.1338 | H10: =G10+H9 -> 20.010214 | I10: =H10+I9 -> 20.010214 | J10: =I10+J9 -> 20.010214 | K10: =J10+K9 -> 20.010214 | L10: =K10+L9 -> 20.010214
A11: 期末流通股本（扣除库存股） | B11: 百万股 | C11: =C7-C10 -> 1916.4974 | D11: =D7-D10 -> 1916.4974 | E11: =E7-E10 -> 1916.4974 | F11: =F7-F10 -> 1916.4974 | G11: =G7-G10 -> 1911.3636 | H11: =H7-H10 -> 1976.7084 | I11: =I7-I10 -> 1976.7084 | J11: =J7-J10 -> 1976.7084 | ... L11: =L7-L10 -> 1976.7084
A12: 当年派发现金股利 | B12: 百万元 | G12: 726.63 | H12: =假设!$C$16 -> 860.11 | I12: =假设!$C$17*三表预测!H29 -> 1386.6479 | J12: =假设!$C$17*三表预测!I29 -> 1802.0201 | K12: =假设!$C$17*三表预测!J29 -> 1987.8425 | L12: =假设!$C$17*三表预测!K29 -> 2117.7552

Sheet DCF估值
A1: DCF估值（FCFF，三阶段）
A2: 估值基准日：2026-12-31（使用2026E年末净现金）。第一阶段2027E-2030E取自三表；第二阶段2031E-2035E按FCFF增速线性递减；之后永续增长。
A4: WACC
A5: 股权成本 = 无风险利率 + Beta × 股权风险溢价 | C5: =假设!$C$22+假设!$C$23*假设!$C$24 -> 0.0905
A6: 税后债务成本 | C6: =假设!$C$25*(1-假设!$C$18) -> 0.03045
A7: WACC | C7: =(1-假设!$C$26)*$C$5+假设!$C$26*$C$6 -> 0.089299
A8: 永续增长率 | C8: =假设!$C$27 -> 0.03
A10: 自由现金流（FCFF）
A11: 项目（百万元） | C11: 2027E | D11: 2028E | E11: 2029E | F11: 2030E | G11: 2031E | H11: 2032E | I11: 2033E | J11: 2034E | K11: 2035E
A12: 折现期（年） | C12: 1 | D12: 2 | E12: 3 | F12: 4 | G12: 5 | H12: 6 | I12: 7 | J12: 8 | K12: 9
A13: EBIT | C13: =三表预测!I34 -> 5926.3896 | D13: =三表预测!J34 -> 6565.1662 | E13: =三表预测!K34 -> 6991.8996 | F13: =三表预测!L34 -> 7328.7693
A14: 减：EBIT所得税 | C14: =-C13*假设!$C$18 -> -770.43065 | D14: =-D13*假设!$C$18 -> -853.47161 | E14: =-E13*假设!$C$18 -> -908.94695 | F14: =-F13*假设!$C$18 -> -952.74
A15: 加：折旧与摊销 | C15: =三表预测!I35 -> 907.66826 | D15: =三表预测!J35 -> 1094.2364 | E15: =三表预测!K35 -> 1224.8492 | F15: =三表预测!L35 -> 1294.4416
A16: 减：资本开支 | C16: =-三表预测!I73 -> -2500 | D16: =-三表预测!J73 -> -2200 | E16: =-三表预测!K73 -> -1800 | F16: =-三表预测!L73 -> -1500
A17: 减：营运资本增加 | C17: =三表预测!I70 -> -1220.5646 | D17: =三表预测!J70 -> -753.43047 | E17: =三表预测!K70 -> -570.96674 | F17: =三表预测!L70 -> -288.17752
A18: FCFF增速（第二阶段） | G18: =假设!$C$28+(假设!$C$29-假设!$C$28)*0/4 -> 0.1 | H18: =假设!$C$28+(假设!$C$29-假设!$C$28)*1/4 -> 0.0875 | I18: =假设!$C$28+(假设!$C$29-假设!$C$28)*2/4 -> 0.075 | J18: =假设!$C$28+(假设!$C$29-假设!$C$28)*3/4 -> 0.0625 | K18: =假设!$C$28+(假设!$C$29-假设!$C$28)*4/4 -> 0.05
A19: FCFF | C19: =C13+C14+C15+C16+C17 -> 2343.0626 | D19: =D13+D14+D15+D16+D17 -> 3852.5006 | E19: =E13+E14+E15+E16+E17 -> 4936.8352 | F19: =F13+F14+F15+F16+F17 -> 5882.2933 | G19: =F19*(1+G18) -> 6470.5226 | H19: =G19*(1+H18) -> 7036.6933 | I19: =H19*(1+I18) -> 7564.4454 | J19: =I19*(1+J18) -> 8037.2232 | K19: =J19*(1+K18) -> 8439.0843
A20: 折现系数 | C20: =1/(1+$C$7)^C12 -> 0.91802159 | D20: =1/(1+$C$7)^D12 -> 0.84276364 | E20: =1/(1+$C$7)^E12 -> 0.77367522 | F20: =1/(1+$C$7)^F12 -> 0.71025055 | G20: =1/(1+$C$7)^G12 -> 0.65202534 | H20: =1/(1+$C$7)^H12 -> 0.59857334 | I20: =1/(1+$C$7)^I12 -> 0.54950325 | J20: =1/(1+$C$7)^J12 -> 0.50445585 | K20: =1/(1+$C$7)^K12 -> 0.46310136
A21: FCFF现值 | C21: =C19*C20 -> 2150.9821 | D21: =D19*D20 -> 3246.7474 | E21: =E19*E20 -> 3819.507 | F21: =F19*F20 -> 4177.9021 | G21: =G19*G20 -> 4218.9447 | H21: =H19*H20 -> 4211.977 | I21: =I19*I20 -> 4156.6873 | J21: =J19*J20 -> 4054.4242 | K21: =K19*K20 -> 3908.1514
A23: 企业价值与股权价值
A24: FCFF现值合计（2027E-2035E） | C24: =SUM(C21:K21) -> 33945.323
A25: 终值（2035E） | C25: =K19*(1+$C$8)/($C$7-$C$8) -> 146583.53
A26: 终值现值 | C26: =$C$25*K20 -> 67883.033
A27: 企业价值（EV） | C27: =$C$24+$C$26 -> 101828.36
A28: 终值占EV比例 | C28: =IFERROR($C$26/$C$27,0) -> 0.66664174
A29: 加：2026E年末净现金（含类现金定期存款） | C29: =三表预测!H93 -> 18100.965
A30: 减：少数股东权益 | C30: =三表预测!H61 -> 4.2831
A31: 股权价值 | C31: =$C$27+$C$29-$C$30 -> 119925.04
A32: 流通股本（百万股，2026E年末） | C32: =股本与每股!H11 -> 1976.7084
A33: 每股价值（元，2026-12-31） | C33: =IFERROR($C$31/$C$32,0) -> 60.66906
A34: 每股价值折回2026-09-30（按股权成本折现0.25年） | C34: =$C$33/(1+$C$5)^0.25 -> 59.369152
A35: 当前A股股价（元） | C35: =假设!$C$6 -> 118.5
A36: 相对当前股价空间 | C36: =IFERROR($C$34/$C$35-1,0) -> -0.49899449
A37: 隐含EV/EBITDA（2027E） | C37: =IFERROR($C$27/三表预测!I36,0) -> 14.900131
A38: 隐含PE（2027E） | C38: =IFERROR($C$33/三表预测!I32,0) -> 21.96161
A40: 敏感性：每股价值（元，2026-12-31）— WACC（行）× 永续增长率（列）
A41: WACC \ 永续增长率 | C41: =$C$8+(-0.01) -> 0.02 | D41: =$C$8+(-0.005) -> 0.025 | E41: =$C$8+(0) -> 0.03 | F41: =$C$8+(0.005) -> 0.035 | G41: =$C$8+(0.01) -> 0.04
B42: =$C$7+(-0.01) -> 0.079299 | C42: =IFERROR((SUMPRODUCT($C$19:$K$19/(1+$B42)^$C$12:$K$12)+$K$19*(1+C$41)/($B42-C$41)/(1+$B42)^$K$12+$C$29-$C$30)/$C$32,0) -> 64.143544 | D42: =IFERROR((SUMPRODUCT($C$19:$K$19/(1+$B42)^$C$12:$K$12)+$K$19*(1+D$41)/($B42-D$41)/(1+$B42)^$K$12+$C$29-$C$30)/$C$32,0) -> 67.743932 | E42: =IFERROR((SUMPRODUCT($C$19:$K$19/(1+$B42)^$C$12:$K$12)+$K$19*(1+E$41)/($B42-E$41)/(1+$B42)^$K$12+$C$29-$C$30)/$C$32,0) -> 72.074637 | F42: =IFERROR((SUMPRODUCT($C$19:$K$19/(1+$B42)^$C$12:$K$12)+$K$19*(1+F$41)/($B42-F$41)/(1+$B42)^$K$12+$C$29-$C$30)/$C$32,0) -> 77.38295 | G42: =IFERROR((SUMPRODUCT($C$19:$K$19/(1+$B42)^$C$12:$K$12)+$K$19*(1+G$41)/($B42-G$41)/(1+$B42)^$K$12+$C$29-$C$30)/$C$32,0) -> 84.042013
B43: =$C$7+(-0.005) -> 0.084299 | C43: =IFERROR((SUMPRODUCT($C$19:$K$19/(1+$B43)^$C$12:$K$12)+$K$19*(1+C$41)/($B43-C$41)/(1+$B43)^$K$12+$C$29-$C$30)/$C$32,0) -> 59.441943 | D43: =IFERROR((SUMPRODUCT($C$19:$K$19/(1+$B43)^$C$12:$K$12)+$K$19*(1+D$41)/($B43-D$41)/(1+$B43)^$K$12+$C$29-$C$30)/$C$32,0) -> 62.372018 | E43: =IFERROR((SUMPRODUCT($C$19:$K$19/(1+$B43)^$C$12:$K$12)+$K$19*(1+E$41)/($B43-E$41)/(1+$B43)^$K$12+$C$29-$C$30)/$C$32,0) -> 65.841711 | F43: =IFERROR((SUMPRODUCT($C$19:$K$19/(1+$B43)^$C$12:$K$12)+$K$19*(1+F$41)/($B43-F$41)/(1+$B43)^$K$12+$C$29-$C$30)/$C$32,0) -> 70.015211 | G43: =IFERROR((SUMPRODUCT($C$19:$K$19/(1+$B43)^$C$12:$K$12)+$K$19*(1+G$41)/($B43-G$41)/(1+$B43)^$K$12+$C$29-$C$30)/$C$32,0) -> 75.13083
B44: =$C$7+(0) -> 0.089299 | C44: =IFERROR((SUMPRODUCT($C$19:$K$19/(1+$B44)^$C$12:$K$12)+$K$19*(1+C$41)/($B44-C$41)/(1+$B44)^$K$12+$C$29-$C$30)/$C$32,0) -> 55.428212 | D44: =IFERROR((SUMPRODUCT($C$19:$K$19/(1+$B44)^$C$12:$K$12)+$K$19*(1+D$41)/($B44-D$41)/(1+$B44)^$K$12+$C$29-$C$30)/$C$32,0) -> 57.844868 | E44: =IFERROR((SUMPRODUCT($C$19:$K$19/(1+$B44)^$C$12:$K$12)+$K$19*(1+E$41)/($B44-E$41)/(1+$B44)^$K$12+$C$29-$C$30)/$C$32,0) -> 60.66906 | F44: =IFERROR((SUMPRODUCT($C$19:$K$19/(1+$B44)^$C$12:$K$12)+$K$19*(1+F$41)/($B44-F$41)/(1+$B44)^$K$12+$C$29-$C$30)/$C$32,0) -> 64.013371 | G44: =IFERROR((SUMPRODUCT($C$19:$K$19/(1+$B44)^$C$12:$K$12)+$K$19*(1+G$41)/($B44-G$41)/(1+$B44)^$K$12+$C$29-$C$30)/$C$32,0) -> 68.036056
B45: =$C$7+(0.005) -> 0.094299 | C45: =IFERROR((SUMPRODUCT($C$19:$K$19/(1+$B45)^$C$12:$K$12)+$K$19*(1+C$41)/($B45-C$41)/(1+$B45)^$K$12+$C$29-$C$30)/$C$32,0) -> 51.963195 | D45: =IFERROR((SUMPRODUCT($C$19:$K$19/(1+$B45)^$C$12:$K$12)+$K$19*(1+D$41)/($B45-D$41)/(1+$B45)^$K$12+$C$29-$C$30)/$C$32,0) -> 53.979354 | E45: =IFERROR((SUMPRODUCT($C$19:$K$19/(1+$B45)^$C$12:$K$12)+$K$19*(1+E$41)/($B45-E$41)/(1+$B45)^$K$12+$C$29-$C$30)/$C$32,0) -> 56.309073 | F45: =IFERROR((SUMPRODUCT($C$19:$K$19/(1+$B45)^$C$12:$K$12)+$K$19*(1+F$41)/($B45-F$41)/(1+$B45)^$K$12+$C$29-$C$30)/$C$32,0) -> 59.031668 | G45: =IFERROR((SUMPRODUCT($C$19:$K$19/(1+$B45)^$C$12:$K$12)+$K$19*(1+G$41)/($B45-G$41)/(1+$B45)^$K$12+$C$29-$C$30)/$C$32,0) -> 62.255672
B46: =$C$7+(0.01) -> 0.099299 | C46: =IFERROR((SUMPRODUCT($C$19:$K$19/(1+$B46)^$C$12:$K$12)+$K$19*(1+C$41)/($B46-C$41)/(1+$B46)^$K$12+$C$29-$C$30)/$C$32,0) -> 48.942842 | D46: =IFERROR((SUMPRODUCT($C$19:$K$19/(1+$B46)^$C$12:$K$12)+$K$19*(1+D$41)/($B46-D$41)/(1+$B46)^$K$12+$C$29-$C$30)/$C$32,0) -> 50.641655 | E46: =IFERROR((SUMPRODUCT($C$19:$K$19/(1+$B46)^$C$12:$K$12)+$K$19*(1+E$41)/($B46-E$41)/(1+$B46)^$K$12+$C$29-$C$30)/$C$32,0) -> 52.585609 | F46: =IFERROR((SUMPRODUCT($C$19:$K$19/(1+$B46)^$C$12:$K$12)+$K$19*(1+F$41)/($B46-F$41)/(1+$B46)^$K$12+$C$29-$C$30)/$C$32,0) -> 54.831895 | G46: =IFERROR((SUMPRODUCT($C$19:$K$19/(1+$B46)^$C$12:$K$12)+$K$19*(1+G$41)/($B46-G$41)/(1+$B46)^$K$12+$C$29-$C$30)/$C$32,0) -> 57.456986
A48: 敏感性：每股价值（元）— WACC（行）× 第二阶段增速起点（列）
A49: WACC \ 第二阶段起点增速 | C49: 0.06 | D49: 0.08 | E49: 0.1 | F49: 0.12 | G49: 0.14
B50: =$C$7+(-0.01) -> 0.079299 | C50: =IFERROR((SUMPRODUCT($C$19:$F$19/(1+$B50)^$C$12:$F$12)+$F$19*(1+(C$49+(假设!$C$29-C$49)*0/4))/(1+$B50)^5+$F$19*(1+(C$49+(假设!$C$29-C$49)*0/4))*(1+(C$49+(假设!$C$29-C$49)*1/4))/(1+$B50)^6+$F$19*(1+(C$49+(假设!$C$29-C$49)*0/4))*(1+(C$49+(假设!$C$29-C$49)*1/4))*(1+(C$49+(假设!$C$29-C$49)*2/4))/(1+$B50)^7+$F$19*(1+(C$49+(假设!$C$29-C$49)*0/4))*(1+(C$49+(假设!$C$29-C$49)*1/4))*(1+(C$49+(假设!$C$29-C$49)*2/4))*(1+(C$49+(假设!$C$29-C$49)*3/4))/(1+$B50)^8+$F$19*(1+(C$49+(假设!$C$29-C$49)*0/4))*(1+(C$49+(假设!$C$29-C$49)*1/4))*(1+(C$49+(假设!$C$29-C$49)*2/4))*(1+(C$49+(假设!$C$29-C$49)*3/4))*(1+(C$49+(假设!$C$29-C$49)*4/4))/(1+$B50)^9+$F$19*(1+(C$49+(假设!$C$29-C$49)*0/4))*(1+(C$49+(假设!$C$29-C$49)*1/4))*(1+(C$49+(假设!$C$29-C$49)*2/4))*(1+(C$49+(假设!$C$29-C$49)*3/4))*(1+(C$49+(假设!$C$29-C$49)*4/4))*(1+$C$8)/($B50-$C$8)/(1+$B50)^9+$C$29-$C$30)/$C$32,0) -> 67.28731 | D50: =IFERROR((SUMPRODUCT($C$19:$F$19/(1+$B50)^$C$12:$F$12)+$F$19*(1+(D$49+(假设!$C$29-D$49)*0/4))/(1+$B50)^5+$F$19*(1+(D$49+(假设!$C$29-D$49)*0/4))*(1+(D$49+(假设!$C$29-D$49)*1/4))/(1+$B50)^6+$F$19*(1+(D$49+(假设!$C$29-D$49)*0/4))*(1+(D$49+(假设!$C$29-D$49)*1/4))*(1+(D$49+(假设!$C$29-D$49)*2/4))/(1+$B50)^7+$F$19*(1+(D$49+(假设!$C$29-D$49)*0/4))*(1+(D$49+(假设!$C$29-D$49)*1/4))*(1+(D$49+(假设!$C$29-D$49)*2/4))*(1+(D$49+(假设!$C$29-D$49)*3/4))/(1+$B50)^8+$F$19*(1+(D$49+(假设!$C$29-D$49)*0/4))*(1+(D$49+(假设!$C$29-D$49)*1/4))*(1+(D$49+(假设!$C$29-D$49)*2/4))*(1+(D$49+(假设!$C$29-D$49)*3/4))*(1+(D$49+(假设!$C$29-D$49)*4/4))/(1+$B50)^9+$F$19*(1+(D$49+(假设!$C$29-D$49)*0/4))*(1+(D$49+(假设!$C$29-D$49)*1/4))*(1+(D$49+(假设!$C$29-D$49)*2/4))*(1+(D$49+(假设!$C$29-D$49)*3/4))*(1+(D$49+(假设!$C$29-D$49)*4/4))*(1+$C$8)/($B50-$C$8)/(1+$B50)^9+$C$29-$C$30)/$C$32,0) -> 69.643358 | E50: =IFERROR((SUMPRODUCT($C$19:$F$19/(1+$B50)^$C$12:$F$12)+$F$19*(1+(E$49+(假设!$C$29-E$49)*0/4))/(1+$B50)^5+$F$19*(1+(E$49+(假设!$C$29-E$49)*0/4))*(1+(E$49+(假设!$C$29-E$49)*1/4))/(1+$B50)^6+$F$19*(1+(E$49+(假设!$C$29-E$49)*0/4))*(1+(E$49+(假设!$C$29-E$49)*1/4))*(1+(E$49+(假设!$C$29-E$49)*2/4))/(1+$B50)^7+$F$19*(1+(E$49+(假设!$C$29-E$49)*0/4))*(1+(E$49+(假设!$C$29-E$49)*1/4))*(1+(E$49+(假设!$C$29-E$49)*2/4))*(1+(E$49+(假设!$C$29-E$49)*3/4))/(1+$B50)^8+$F$19*(1+(E$49+(假设!$C$29-E$49)*0/4))*(1+(E$49+(假设!$C$29-E$49)*1/4))*(1+(E$49+(假设!$C$29-E$49)*2/4))*(1+(E$49+(假设!$C$29-E$49)*3/4))*(1+(E$49+(假设!$C$29-E$49)*4/4))/(1+$B50)^9+$F$19*(1+(E$49+(假设!$C$29-E$49)*0/4))*(1+(E$49+(假设!$C$29-E$49)*1/4))*(1+(E$49+(假设!$C$29-E$49)*2/4))*(1+(E$49+(假设!$C$29-E$49)*3/4))*(1+(E$49+(假设!$C$29-E$49)*4/4))*(1+$C$8)/($B50-$C$8)/(1+$B50)^9+$C$29-$C$30)/$C$32,0) -> 72.074637 | F50: =IFERROR((SUMPRODUCT($C$19:$F$19/(1+$B50)^$C$12:$F$12)+$F$19*(1+(F$49+(假设!$C$29-F$49)*0/4))/(1+$B50)^5+$F$19*(1+(F$49+(假设!$C$29-F$49)*0/4))*(1+(F$49+(假设!$C$29-F$49)*1/4))/(1+$B50)^6+$F$19*(1+(F$49+(假设!$C$29-F$49)*0/4))*(1+(F$49+(假设!$C$29-F$49)*1/4))*(1+(F$49+(假设!$C$29-F$49)*2/4))/(1+$B50)^7+$F$19*(1+(F$49+(假设!$C$29-F$49)*0/4))*(1+(F$49+(假设!$C$29-F$49)*1/4))*(1+(F$49+(假设!$C$29-F$49)*2/4))*(1+(F$49+(假设!$C$29-F$49)*3/4))/(1+$B50)^8+$F$19*(1+(F$49+(假设!$C$29-F$49)*0/4))*(1+(F$49+(假设!$C$29-F$49)*1/4))*(1+(F$49+(假设!$C$29-F$49)*2/4))*(1+(F$49+(假设!$C$29-F$49)*3/4))*(1+(F$49+(假设!$C$29-F$49)*4/4))/(1+$B50)^9+$F$19*(1+(F$49+(假设!$C$29-F$49)*0/4))*(1+(F$49+(假设!$C$29-F$49)*1/4))*(1+(F$49+(假设!$C$29-F$49)*2/4))*(1+(F$49+(假设!$C$29-F$49)*3/4))*(1+(F$49+(假设!$C$29-F$49)*4/4))*(1+$C$8)/($B50-$C$8)/(1+$B50)^9+$C$29-$C$30)/$C$32,0) -> 74.582623 | G50: =IFERROR((SUMPRODUCT($C$19:$F$19/(1+$B50)^$C$12:$F$12)+$F$19*(1+(G$49+(假设!$C$29-G$49)*0/4))/(1+$B50)^5+$F$19*(1+(G$49+(假设!$C$29-G$49)*0/4))*(1+(G$49+(假设!$C$29-G$49)*1/4))/(1+$B50)^6+$F$19*(1+(G$49+(假设!$C$29-G$49)*0/4))*(1+(G$49+(假设!$C$29-G$49)*1/4))*(1+(G$49+(假设!$C$29-G$49)*2/4))/(1+$B50)^7+$F$19*(1+(G$49+(假设!$C$29-G$49)*0/4))*(1+(G$49+(假设!$C$29-G$49)*1/4))*(1+(G$49+(假设!$C$29-G$49)*2/4))*(1+(G$49+(假设!$C$29-G$49)*3/4))/(1+$B50)^8+$F$19*(1+(G$49+(假设!$C$29-G$49)*0/4))*(1+(G$49+(假设!$C$29-G$49)*1/4))*(1+(G$49+(假设!$C$29-G$49)*2/4))*(1+(G$49+(假设!$C$29-G$49)*3/4))*(1+(G$49+(假设!$C$29-G$49)*4/4))/(1+$B50)^9+$F$19*(1+(G$49+(假设!$C$29-G$49)*0/4))*(1+(G$49+(假设!$C$29-G$49)*1/4))*(1+(G$49+(假设!$C$29-G$49)*2/4))*(1+(G$49+(假设!$C$29-G$49)*3/4))*(1+(G$49+(假设!$C$29-G$49)*4/4))*(1+$C$8)/($B50-$C$8)/(1+$B50)^9+$C$29-$C$30)/$C$32,0) -> 77.168804
B51: =$C$7+(-0.005) -> 0.084299 | C51: =IFERROR((SUMPRODUCT($C$19:$F$19/(1+$B51)^$C$12:$F$12)+$F$19*(1+(C$49+(假设!$C$29-C$49)*0/4))/(1+$B51)^5+$F$19*(1+(C$49+(假设!$C$29-C$49)*0/4))*(1+(C$49+(假设!$C$29-C$49)*1/4))/(1+$B51)^6+$F$19*(1+(C$49+(假设!$C$29-C$49)*0/4))*(1+(C$49+(假设!$C$29-C$49)*1/4))*(1+(C$49+(假设!$C$29-C$49)*2/4))/(1+$B51)^7+$F$19*(1+(C$49+(假设!$C$29-C$49)*0/4))*(1+(C$49+(假设!$C$29-C$49)*1/4))*(1+(C$49+(假设!$C$29-C$49)*2/4))*(1+(C$49+(假设!$C$29-C$49)*3/4))/(1+$B51)^8+$F$19*(1+(C$49+(假设!$C$29-C$49)*0/4))*(1+(C$49+(假设!$C$29-C$49)*1/4))*(1+(C$49+(假设!$C$29-C$49)*2/4))*(1+(C$49+(假设!$C$29-C$49)*3/4))*(1+(C$49+(假设!$C$29-C$49)*4/4))/(1+$B51)^9+$F$19*(1+(C$49+(假设!$C$29-C$49)*0/4))*(1+(C$49+(假设!$C$29-C$49)*1/4))*(1+(C$49+(假设!$C$29-C$49)*2/4))*(1+(C$49+(假设!$C$29-C$49)*3/4))*(1+(C$49+(假设!$C$29-C$49)*4/4))*(1+$C$8)/($B51-$C$8)/(1+$B51)^9+$C$29-$C$30)/$C$32,0) -> 61.596588 | D51: =IFERROR((SUMPRODUCT($C$19:$F$19/(1+$B51)^$C$12:$F$12)+$F$19*(1+(D$49+(假设!$C$29-D$49)*0/4))/(1+$B51)^5+$F$19*(1+(D$49+(假设!$C$29-D$49)*0/4))*(1+(D$49+(假设!$C$29-D$49)*1/4))/(1+$B51)^6+$F$19*(1+(D$49+(假设!$C$29-D$49)*0/4))*(1+(D$49+(假设!$C$29-D$49)*1/4))*(1+(D$49+(假设!$C$29-D$49)*2/4))/(1+$B51)^7+$F$19*(1+(D$49+(假设!$C$29-D$49)*0/4))*(1+(D$49+(假设!$C$29-D$49)*1/4))*(1+(D$49+(假设!$C$29-D$49)*2/4))*(1+(D$49+(假设!$C$29-D$49)*3/4))/(1+$B51)^8+$F$19*(1+(D$49+(假设!$C$29-D$49)*0/4))*(1+(D$49+(假设!$C$29-D$49)*1/4))*(1+(D$49+(假设!$C$29-D$49)*2/4))*(1+(D$49+(假设!$C$29-D$49)*3/4))*(1+(D$49+(假设!$C$29-D$49)*4/4))/(1+$B51)^9+$F$19*(1+(D$49+(假设!$C$29-D$49)*0/4))*(1+(D$49+(假设!$C$29-D$49)*1/4))*(1+(D$49+(假设!$C$29-D$49)*2/4))*(1+(D$49+(假设!$C$29-D$49)*3/4))*(1+(D$49+(假设!$C$29-D$49)*4/4))*(1+$C$8)/($B51-$C$8)/(1+$B51)^9+$C$29-$C$30)/$C$32,0) -> 63.685927 | E51: =IFERROR((SUMPRODUCT($C$19:$F$19/(1+$B51)^$C$12:$F$12)+$F$19*(1+(E$49+(假设!$C$29-E$49)*0/4))/(1+$B51)^5+$F$19*(1+(E$49+(假设!$C$29-E$49)*0/4))*(1+(E$49+(假设!$C$29-E$49)*1/4))/(1+$B51)^6+$F$19*(1+(E$49+(假设!$C$29-E$49)*0/4))*(1+(E$49+(假设!$C$29-E$49)*1/4))*(1+(E$49+(假设!$C$29-E$49)*2/4))/(1+$B51)^7+$F$19*(1+(E$49+(假设!$C$29-E$49)*0/4))*(1+(E$49+(假设!$C$29-E$49)*1/4))*(1+(E$49+(假设!$C$29-E$49)*2/4))*(1+(E$49+(假设!$C$29-E$49)*3/4))/(1+$B51)^8+$F$19*(1+(E$49+(假设!$C$29-E$49)*0/4))*(1+(E$49+(假设!$C$29-E$49)*1/4))*(1+(E$49+(假设!$C$29-E$49)*2/4))*(1+(E$49+(假设!$C$29-E$49)*3/4))*(1+(E$49+(假设!$C$29-E$49)*4/4))/(1+$B51)^9+$F$19*(1+(E$49+(假设!$C$29-E$49)*0/4))*(1+(E$49+(假设!$C$29-E$49)*1/4))*(1+(E$49+(假设!$C$29-E$49)*2/4))*(1+(E$49+(假设!$C$29-E$49)*3/4))*(1+(E$49+(假设!$C$29-E$49)*4/4))*(1+$C$8)/($B51-$C$8)/(1+$B51)^9+$C$29-$C$30)/$C$32,0) -> 65.841711 | F51: =IFERROR((SUMPRODUCT($C$19:$F$19/(1+$B51)^$C$12:$F$12)+$F$19*(1+(F$49+(假设!$C$29-F$49)*0/4))/(1+$B51)^5+$F$19*(1+(F$49+(假设!$C$29-F$49)*0/4))*(1+(F$49+(假设!$C$29-F$49)*1/4))/(1+$B51)^6+$F$19*(1+(F$49+(假设!$C$29-F$49)*0/4))*(1+(F$49+(假设!$C$29-F$49)*1/4))*(1+(F$49+(假设!$C$29-F$49)*2/4))/(1+$B51)^7+$F$19*(1+(F$49+(假设!$C$29-F$49)*0/4))*(1+(F$49+(假设!$C$29-F$49)*1/4))*(1+(F$49+(假设!$C$29-F$49)*2/4))*(1+(F$49+(假设!$C$29-F$49)*3/4))/(1+$B51)^8+$F$19*(1+(F$49+(假设!$C$29-F$49)*0/4))*(1+(F$49+(假设!$C$29-F$49)*1/4))*(1+(F$49+(假设!$C$29-F$49)*2/4))*(1+(F$49+(假设!$C$29-F$49)*3/4))*(1+(F$49+(假设!$C$29-F$49)*4/4))/(1+$B51)^9+$F$19*(1+(F$49+(假设!$C$29-F$49)*0/4))*(1+(F$49+(假设!$C$29-F$49)*1/4))*(1+(F$49+(假设!$C$29-F$49)*2/4))*(1+(F$49+(假设!$C$29-F$49)*3/4))*(1+(F$49+(假设!$C$29-F$49)*4/4))*(1+$C$8)/($B51-$C$8)/(1+$B51)^9+$C$29-$C$30)/$C$32,0) -> 68.065242 | G51: =IFERROR((SUMPRODUCT($C$19:$F$19/(1+$B51)^$C$12:$F$12)+$F$19*(1+(G$49+(假设!$C$29-G$49)*0/4))/(1+$B51)^5+$F$19*(1+(G$49+(假设!$C$29-G$49)*0/4))*(1+(G$49+(假设!$C$29-G$49)*1/4))/(1+$B51)^6+$F$19*(1+(G$49+(假设!$C$29-G$49)*0/4))*(1+(G$49+(假设!$C$29-G$49)*1/4))*(1+(G$49+(假设!$C$29-G$49)*2/4))/(1+$B51)^7+$F$19*(1+(G$49+(假设!$C$29-G$49)*0/4))*(1+(G$49+(假设!$C$29-G$49)*1/4))*(1+(G$49+(假设!$C$29-G$49)*2/4))*(1+(G$49+(假设!$C$29-G$49)*3/4))/(1+$B51)^8+$F$19*(1+(G$49+(假设!$C$29-G$49)*0/4))*(1+(G$49+(假设!$C$29-G$49)*1/4))*(1+(G$49+(假设!$C$29-G$49)*2/4))*(1+(G$49+(假设!$C$29-G$49)*3/4))*(1+(G$49+(假设!$C$29-G$49)*4/4))/(1+$B51)^9+$F$19*(1+(G$49+(假设!$C$29-G$49)*0/4))*(1+(G$49+(假设!$C$29-G$49)*1/4))*(1+(G$49+(假设!$C$29-G$49)*2/4))*(1+(G$49+(假设!$C$29-G$49)*3/4))*(1+(G$49+(假设!$C$29-G$49)*4/4))*(1+$C$8)/($B51-$C$8)/(1+$B51)^9+$C$29-$C$30)/$C$32,0) -> 70.35783
B52: =$C$7+(0) -> 0.089299 | C52: =IFERROR((SUMPRODUCT($C$19:$F$19/(1+$B52)^$C$12:$F$12)+$F$19*(1+(C$49+(假设!$C$29-C$49)*0/4))/(1+$B52)^5+$F$19*(1+(C$49+(假设!$C$29-C$49)*0/4))*(1+(C$49+(假设!$C$29-C$49)*1/4))/(1+$B52)^6+$F$19*(1+(C$49+(假设!$C$29-C$49)*0/4))*(1+(C$49+(假设!$C$29-C$49)*1/4))*(1+(C$49+(假设!$C$29-C$49)*2/4))/(1+$B52)^7+$F$19*(1+(C$49+(假设!$C$29-C$49)*0/4))*(1+(C$49+(假设!$C$29-C$49)*1/4))*(1+(C$49+(假设!$C$29-C$49)*2/4))*(1+(C$49+(假设!$C$29-C$49)*3/4))/(1+$B52)^8+$F$19*(1+(C$49+(假设!$C$29-C$49)*0/4))*(1+(C$49+(假设!$C$29-C$49)*1/4))*(1+(C$49+(假设!$C$29-C$49)*2/4))*(1+(C$49+(假设!$C$29-C$49)*3/4))*(1+(C$49+(假设!$C$29-C$49)*4/4))/(1+$B52)^9+$F$19*(1+(C$49+(假设!$C$29-C$49)*0/4))*(1+(C$49+(假设!$C$29-C$49)*1/4))*(1+(C$49+(假设!$C$29-C$49)*2/4))*(1+(C$49+(假设!$C$29-C$49)*3/4))*(1+(C$49+(假设!$C$29-C$49)*4/4))*(1+$C$8)/($B52-$C$8)/(1+$B52)^9+$C$29-$C$30)/$C$32,0) -> 56.872034 | D52: =IFERROR((SUMPRODUCT($C$19:$F$19/(1+$B52)^$C$12:$F$12)+$F$19*(1+(D$49+(假设!$C$29-D$49)*0/4))/(1+$B52)^5+$F$19*(1+(D$49+(假设!$C$29-D$49)*0/4))*(1+(D$49+(假设!$C$29-D$49)*1/4))/(1+$B52)^6+$F$19*(1+(D$49+(假设!$C$29-D$49)*0/4))*(1+(D$49+(假设!$C$29-D$49)*1/4))*(1+(D$49+(假设!$C$29-D$49)*2/4))/(1+$B52)^7+$F$19*(1+(D$49+(假设!$C$29-D$49)*0/4))*(1+(D$49+(假设!$C$29-D$49)*1/4))*(1+(D$49+(假设!$C$29-D$49)*2/4))*(1+(D$49+(假设!$C$29-D$49)*3/4))/(1+$B52)^8+$F$19*(1+(D$49+(假设!$C$29-D$49)*0/4))*(1+(D$49+(假设!$C$29-D$49)*1/4))*(1+(D$49+(假设!$C$29-D$49)*2/4))*(1+(D$49+(假设!$C$29-D$49)*3/4))*(1+(D$49+(假设!$C$29-D$49)*4/4))/(1+$B52)^9+$F$19*(1+(D$49+(假设!$C$29-D$49)*0/4))*(1+(D$49+(假设!$C$29-D$49)*1/4))*(1+(D$49+(假设!$C$29-D$49)*2/4))*(1+(D$49+(假设!$C$29-D$49)*3/4))*(1+(D$49+(假设!$C$29-D$49)*4/4))*(1+$C$8)/($B52-$C$8)/(1+$B52)^9+$C$29-$C$30)/$C$32,0) -> 58.740949 | E52: =IFERROR((SUMPRODUCT($C$19:$F$19/(1+$B52)^$C$12:$F$12)+$F$19*(1+(E$49+(假设!$C$29-E$49)*0/4))/(1+$B52)^5+$F$19*(1+(E$49+(假设!$C$29-E$49)*0/4))*(1+(E$49+(假设!$C$29-E$49)*1/4))/(1+$B52)^6+$F$19*(1+(E$49+(假设!$C$29-E$49)*0/4))*(1+(E$49+(假设!$C$29-E$49)*1/4))*(1+(E$49+(假设!$C$29-E$49)*2/4))/(1+$B52)^7+$F$19*(1+(E$49+(假设!$C$29-E$49)*0/4))*(1+(E$49+(假设!$C$29-E$49)*1/4))*(1+(E$49+(假设!$C$29-E$49)*2/4))*(1+(E$49+(假设!$C$29-E$49)*3/4))/(1+$B52)^8+$F$19*(1+(E$49+(假设!$C$29-E$49)*0/4))*(1+(E$49+(假设!$C$29-E$49)*1/4))*(1+(E$49+(假设!$C$29-E$49)*2/4))*(1+(E$49+(假设!$C$29-E$49)*3/4))*(1+(E$49+(假设!$C$29-E$49)*4/4))/(1+$B52)^9+$F$19*(1+(E$49+(假设!$C$29-E$49)*0/4))*(1+(E$49+(假设!$C$29-E$49)*1/4))*(1+(E$49+(假设!$C$29-E$49)*2/4))*(1+(E$49+(假设!$C$29-E$49)*3/4))*(1+(E$49+(假设!$C$29-E$49)*4/4))*(1+$C$8)/($B52-$C$8)/(1+$B52)^9+$C$29-$C$30)/$C$32,0) -> 60.66906 | F52: =IFERROR((SUMPRODUCT($C$19:$F$19/(1+$B52)^$C$12:$F$12)+$F$19*(1+(F$49+(假设!$C$29-F$49)*0/4))/(1+$B52)^5+$F$19*(1+(F$49+(假设!$C$29-F$49)*0/4))*(1+(F$49+(假设!$C$29-F$49)*1/4))/(1+$B52)^6+$F$19*(1+(F$49+(假设!$C$29-F$49)*0/4))*(1+(F$49+(假设!$C$29-F$49)*1/4))*(1+(F$49+(假设!$C$29-F$49)*2/4))/(1+$B52)^7+$F$19*(1+(F$49+(假设!$C$29-F$49)*0/4))*(1+(F$49+(假设!$C$29-F$49)*1/4))*(1+(F$49+(假设!$C$29-F$49)*2/4))*(1+(F$49+(假设!$C$29-F$49)*3/4))/(1+$B52)^8+$F$19*(1+(F$49+(假设!$C$29-F$49)*0/4))*(1+(F$49+(假设!$C$29-F$49)*1/4))*(1+(F$49+(假设!$C$29-F$49)*2/4))*(1+(F$49+(假设!$C$29-F$49)*3/4))*(1+(F$49+(假设!$C$29-F$49)*4/4))/(1+$B52)^9+$F$19*(1+(F$49+(假设!$C$29-F$49)*0/4))*(1+(F$49+(假设!$C$29-F$49)*1/4))*(1+(F$49+(假设!$C$29-F$49)*2/4))*(1+(F$49+(假设!$C$29-F$49)*3/4))*(1+(F$49+(假设!$C$29-F$49)*4/4))*(1+$C$8)/($B52-$C$8)/(1+$B52)^9+$C$29-$C$30)/$C$32,0) -> 62.657523 | G52: =IFERROR((SUMPRODUCT($C$19:$F$19/(1+$B52)^$C$12:$F$12)+$F$19*(1+(G$49+(假设!$C$29-G$49)*0/4))/(1+$B52)^5+$F$19*(1+(G$49+(假设!$C$29-G$49)*0/4))*(1+(G$49+(假设!$C$29-G$49)*1/4))/(1+$B52)^6+$F$19*(1+(G$49+(假设!$C$29-G$49)*0/4))*(1+(G$49+(假设!$C$29-G$49)*1/4))*(1+(G$49+(假设!$C$29-G$49)*2/4))/(1+$B52)^7+$F$19*(1+(G$49+(假设!$C$29-G$49)*0/4))*(1+(G$49+(假设!$C$29-G$49)*1/4))*(1+(G$49+(假设!$C$29-G$49)*2/4))*(1+(G$49+(假设!$C$29-G$49)*3/4))/(1+$B52)^8+$F$19*(1+(G$49+(假设!$C$29-G$49)*0/4))*(1+(G$49+(假设!$C$29-G$49)*1/4))*(1+(G$49+(假设!$C$29-G$49)*2/4))*(1+(G$49+(假设!$C$29-G$49)*3/4))*(1+(G$49+(假设!$C$29-G$49)*4/4))/(1+$B52)^9+$F$19*(1+(G$49+(假设!$C$29-G$49)*0/4))*(1+(G$49+(假设!$C$29-G$49)*1/4))*(1+(G$49+(假设!$C$29-G$49)*2/4))*(1+(G$49+(假设!$C$29-G$49)*3/4))*(1+(G$49+(假设!$C$29-G$49)*4/4))*(1+$C$8)/($B52-$C$8)/(1+$B52)^9+$C$29-$C$30)/$C$32,0) -> 64.707504
B53: =$C$7+(0.005) -> 0.094299 | C53: =IFERROR((SUMPRODUCT($C$19:$F$19/(1+$B53)^$C$12:$F$12)+$F$19*(1+(C$49+(假设!$C$29-C$49)*0/4))/(1+$B53)^5+$F$19*(1+(C$49+(假设!$C$29-C$49)*0/4))*(1+(C$49+(假设!$C$29-C$49)*1/4))/(1+$B53)^6+$F$19*(1+(C$49+(假设!$C$29-C$49)*0/4))*(1+(C$49+(假设!$C$29-C$49)*1/4))*(1+(C$49+(假设!$C$29-C$49)*2/4))/(1+$B53)^7+$F$19*(1+(C$49+(假设!$C$29-C$49)*0/4))*(1+(C$49+(假设!$C$29-C$49)*1/4))*(1+(C$49+(假设!$C$29-C$49)*2/4))*(1+(C$49+(假设!$C$29-C$49)*3/4))/(1+$B53)^8+$F$19*(1+(C$49+(假设!$C$29-C$49)*0/4))*(1+(C$49+(假设!$C$29-C$49)*1/4))*(1+(C$49+(假设!$C$29-C$49)*2/4))*(1+(C$49+(假设!$C$29-C$49)*3/4))*(1+(C$49+(假设!$C$29-C$49)*4/4))/(1+$B53)^9+$F$19*(1+(C$49+(假设!$C$29-C$49)*0/4))*(1+(C$49+(假设!$C$29-C$49)*1/4))*(1+(C$49+(假设!$C$29-C$49)*2/4))*(1+(C$49+(假设!$C$29-C$49)*3/4))*(1+(C$49+(假设!$C$29-C$49)*4/4))*(1+$C$8)/($B53-$C$8)/(1+$B53)^9+$C$29-$C$30)/$C$32,0) -> 52.888075 | D53: =IFERROR((SUMPRODUCT($C$19:$F$19/(1+$B53)^$C$12:$F$12)+$F$19*(1+(D$49+(假设!$C$29-D$49)*0/4))/(1+$B53)^5+$F$19*(1+(D$49+(假设!$C$29-D$49)*0/4))*(1+(D$49+(假设!$C$29-D$49)*1/4))/(1+$B53)^6+$F$19*(1+(D$49+(假设!$C$29-D$49)*0/4))*(1+(D$49+(假设!$C$29-D$49)*1/4))*(1+(D$49+(假设!$C$29-D$49)*2/4))/(1+$B53)^7+$F$19*(1+(D$49+(假设!$C$29-D$49)*0/4))*(1+(D$49+(假设!$C$29-D$49)*1/4))*(1+(D$49+(假设!$C$29-D$49)*2/4))*(1+(D$49+(假设!$C$29-D$49)*3/4))/(1+$B53)^8+$F$19*(1+(D$49+(假设!$C$29-D$49)*0/4))*(1+(D$49+(假设!$C$29-D$49)*1/4))*(1+(D$49+(假设!$C$29-D$49)*2/4))*(1+(D$49+(假设!$C$29-D$49)*3/4))*(1+(D$49+(假设!$C$29-D$49)*4/4))/(1+$B53)^9+$F$19*(1+(D$49+(假设!$C$29-D$49)*0/4))*(1+(D$49+(假设!$C$29-D$49)*1/4))*(1+(D$49+(假设!$C$29-D$49)*2/4))*(1+(D$49+(假设!$C$29-D$49)*3/4))*(1+(D$49+(假设!$C$29-D$49)*4/4))*(1+$C$8)/($B53-$C$8)/(1+$B53)^9+$C$29-$C$30)/$C$32,0) -> 54.572012 | E53: =IFERROR((SUMPRODUCT($C$19:$F$19/(1+$B53)^$C$12:$F$12)+$F$19*(1+(E$49+(假设!$C$29-E$49)*0/4))/(1+$B53)^5+$F$19*(1+(E$49+(假设!$C$29-E$49)*0/4))*(1+(E$49+(假设!$C$29-E$49)*1/4))/(1+$B53)^6+$F$19*(1+(E$49+(假设!$C$29-E$49)*0/4))*(1+(E$49+(假设!$C$29-E$49)*1/4))*(1+(E$49+(假设!$C$29-E$49)*2/4))/(1+$B53)^7+$F$19*(1+(E$49+(假设!$C$29-E$49)*0/4))*(1+(E$49+(假设!$C$29-E$49)*1/4))*(1+(E$49+(假设!$C$29-E$49)*2/4))*(1+(E$49+(假设!$C$29-E$49)*3/4))/(1+$B53)^8+$F$19*(1+(E$49+(假设!$C$29-E$49)*0/4))*(1+(E$49+(假设!$C$29-E$49)*1/4))*(1+(E$49+(假设!$C$29-E$49)*2/4))*(1+(E$49+(假设!$C$29-E$49)*3/4))*(1+(E$49+(假设!$C$29-E$49)*4/4))/(1+$B53)^9+$F$19*(1+(E$49+(假设!$C$29-E$49)*0/4))*(1+(E$49+(假设!$C$29-E$49)*1/4))*(1+(E$49+(假设!$C$29-E$49)*2/4))*(1+(E$49+(假设!$C$29-E$49)*3/4))*(1+(E$49+(假设!$C$29-E$49)*4/4))*(1+$C$8)/($B53-$C$8)/(1+$B53)^9+$C$29-$C$30)/$C$32,0) -> 56.309073 | F53: =IFERROR((SUMPRODUCT($C$19:$F$19/(1+$B53)^$C$12:$F$12)+$F$19*(1+(F$49+(假设!$C$29-F$49)*0/4))/(1+$B53)^5+$F$19*(1+(F$49+(假设!$C$29-F$49)*0/4))*(1+(F$49+(假设!$C$29-F$49)*1/4))/(1+$B53)^6+$F$19*(1+(F$49+(假设!$C$29-F$49)*0/4))*(1+(F$49+(假设!$C$29-F$49)*1/4))*(1+(F$49+(假设!$C$29-F$49)*2/4))/(1+$B53)^7+$F$19*(1+(F$49+(假设!$C$29-F$49)*0/4))*(1+(F$49+(假设!$C$29-F$49)*1/4))*(1+(F$49+(假设!$C$29-F$49)*2/4))*(1+(F$49+(假设!$C$29-F$49)*3/4))/(1+$B53)^8+$F$19*(1+(F$49+(假设!$C$29-F$49)*0/4))*(1+(F$49+(假设!$C$29-F$49)*1/4))*(1+(F$49+(假设!$C$29-F$49)*2/4))*(1+(F$49+(假设!$C$29-F$49)*3/4))*(1+(F$49+(假设!$C$29-F$49)*4/4))/(1+$B53)^9+$F$19*(1+(F$49+(假设!$C$29-F$49)*0/4))*(1+(F$49+(假设!$C$29-F$49)*1/4))*(1+(F$49+(假设!$C$29-F$49)*2/4))*(1+(F$49+(假设!$C$29-F$49)*3/4))*(1+(F$49+(假设!$C$29-F$49)*4/4))*(1+$C$8)/($B53-$C$8)/(1+$B53)^9+$C$29-$C$30)/$C$32,0) -> 58.100291 | G53: =IFERROR((SUMPRODUCT($C$19:$F$19/(1+$B53)^$C$12:$F$12)+$F$19*(1+(G$49+(假设!$C$29-G$49)*0/4))/(1+$B53)^5+$F$19*(1+(G$49+(假设!$C$29-G$49)*0/4))*(1+(G$49+(假设!$C$29-G$49)*1/4))/(1+$B53)^6+$F$19*(1+(G$49+(假设!$C$29-G$49)*0/4))*(1+(G$49+(假设!$C$29-G$49)*1/4))*(1+(G$49+(假设!$C$29-G$49)*2/4))/(1+$B53)^7+$F$19*(1+(G$49+(假设!$C$29-G$49)*0/4))*(1+(G$49+(假设!$C$29-G$49)*1/4))*(1+(G$49+(假设!$C$29-G$49)*2/4))*(1+(G$49+(假设!$C$29-G$49)*3/4))/(1+$B53)^8+$F$19*(1+(G$49+(假设!$C$29-G$49)*0/4))*(1+(G$49+(假设!$C$29-G$49)*1/4))*(1+(G$49+(假设!$C$29-G$49)*2/4))*(1+(G$49+(假设!$C$29-G$49)*3/4))*(1+(G$49+(假设!$C$29-G$49)*4/4))/(1+$B53)^9+$F$19*(1+(G$49+(假设!$C$29-G$49)*0/4))*(1+(G$49+(假设!$C$29-G$49)*1/4))*(1+(G$49+(假设!$C$29-G$49)*2/4))*(1+(G$49+(假设!$C$29-G$49)*3/4))*(1+(G$49+(假设!$C$29-G$49)*4/4))*(1+$C$8)/($B53-$C$8)/(1+$B53)^9+$C$29-$C$30)/$C$32,0) -> 59.94671
B54: =$C$7+(0.01) -> 0.099299 | C54: =IFERROR((SUMPRODUCT($C$19:$F$19/(1+$B54)^$C$12:$F$12)+$F$19*(1+(C$49+(假设!$C$29-C$49)*0/4))/(1+$B54)^5+$F$19*(1+(C$49+(假设!$C$29-C$49)*0/4))*(1+(C$49+(假设!$C$29-C$49)*1/4))/(1+$B54)^6+$F$19*(1+(C$49+(假设!$C$29-C$49)*0/4))*(1+(C$49+(假设!$C$29-C$49)*1/4))*(1+(C$49+(假设!$C$29-C$49)*2/4))/(1+$B54)^7+$F$19*(1+(C$49+(假设!$C$29-C$49)*0/4))*(1+(C$49+(假设!$C$29-C$49)*1/4))*(1+(C$49+(假设!$C$29-C$49)*2/4))*(1+(C$49+(假设!$C$29-C$49)*3/4))/(1+$B54)^8+$F$19*(1+(C$49+(假设!$C$29-C$49)*0/4))*(1+(C$49+(假设!$C$29-C$49)*1/4))*(1+(C$49+(假设!$C$29-C$49)*2/4))*(1+(C$49+(假设!$C$29-C$49)*3/4))*(1+(C$49+(假设!$C$29-C$49)*4/4))/(1+$B54)^9+$F$19*(1+(C$49+(假设!$C$29-C$49)*0/4))*(1+(C$49+(假设!$C$29-C$49)*1/4))*(1+(C$49+(假设!$C$29-C$49)*2/4))*(1+(C$49+(假设!$C$29-C$49)*3/4))*(1+(C$49+(假设!$C$29-C$49)*4/4))*(1+$C$8)/($B54-$C$8)/(1+$B54)^9+$C$29-$C$30)/$C$32,0) -> 49.484246 | D54: =IFERROR((SUMPRODUCT($C$19:$F$19/(1+$B54)^$C$12:$F$12)+$F$19*(1+(D$49+(假设!$C$29-D$49)*0/4))/(1+$B54)^5+$F$19*(1+(D$49+(假设!$C$29-D$49)*0/4))*(1+(D$49+(假设!$C$29-D$49)*1/4))/(1+$B54)^6+$F$19*(1+(D$49+(假设!$C$29-D$49)*0/4))*(1+(D$49+(假设!$C$29-D$49)*1/4))*(1+(D$49+(假设!$C$29-D$49)*2/4))/(1+$B54)^7+$F$19*(1+(D$49+(假设!$C$29-D$49)*0/4))*(1+(D$49+(假设!$C$29-D$49)*1/4))*(1+(D$49+(假设!$C$29-D$49)*2/4))*(1+(D$49+(假设!$C$29-D$49)*3/4))/(1+$B54)^8+$F$19*(1+(D$49+(假设!$C$29-D$49)*0/4))*(1+(D$49+(假设!$C$29-D$49)*1/4))*(1+(D$49+(假设!$C$29-D$49)*2/4))*(1+(D$49+(假设!$C$29-D$49)*3/4))*(1+(D$49+(假设!$C$29-D$49)*4/4))/(1+$B54)^9+$F$19*(1+(D$49+(假设!$C$29-D$49)*0/4))*(1+(D$49+(假设!$C$29-D$49)*1/4))*(1+(D$49+(假设!$C$29-D$49)*2/4))*(1+(D$49+(假设!$C$29-D$49)*3/4))*(1+(D$49+(假设!$C$29-D$49)*4/4))*(1+$C$8)/($B54-$C$8)/(1+$B54)^9+$C$29-$C$30)/$C$32,0) -> 51.010942 | E54: =IFERROR((SUMPRODUCT($C$19:$F$19/(1+$B54)^$C$12:$F$12)+$F$19*(1+(E$49+(假设!$C$29-E$49)*0/4))/(1+$B54)^5+$F$19*(1+(E$49+(假设!$C$29-E$49)*0/4))*(1+(E$49+(假设!$C$29-E$49)*1/4))/(1+$B54)^6+$F$19*(1+(E$49+(假设!$C$29-E$49)*0/4))*(1+(E$49+(假设!$C$29-E$49)*1/4))*(1+(E$49+(假设!$C$29-E$49)*2/4))/(1+$B54)^7+$F$19*(1+(E$49+(假设!$C$29-E$49)*0/4))*(1+(E$49+(假设!$C$29-E$49)*1/4))*(1+(E$49+(假设!$C$29-E$49)*2/4))*(1+(E$49+(假设!$C$29-E$49)*3/4))/(1+$B54)^8+$F$19*(1+(E$49+(假设!$C$29-E$49)*0/4))*(1+(E$49+(假设!$C$29-E$49)*1/4))*(1+(E$49+(假设!$C$29-E$49)*2/4))*(1+(E$49+(假设!$C$29-E$49)*3/4))*(1+(E$49+(假设!$C$29-E$49)*4/4))/(1+$B54)^9+$F$19*(1+(E$49+(假设!$C$29-E$49)*0/4))*(1+(E$49+(假设!$C$29-E$49)*1/4))*(1+(E$49+(假设!$C$29-E$49)*2/4))*(1+(E$49+(假设!$C$29-E$49)*3/4))*(1+(E$49+(假设!$C$29-E$49)*4/4))*(1+$C$8)/($B54-$C$8)/(1+$B54)^9+$C$29-$C$30)/$C$32,0) -> 52.585609 | F54: =IFERROR((SUMPRODUCT($C$19:$F$19/(1+$B54)^$C$12:$F$12)+$F$19*(1+(F$49+(假设!$C$29-F$49)*0/4))/(1+$B54)^5+$F$19*(1+(F$49+(假设!$C$29-F$49)*0/4))*(1+(F$49+(假设!$C$29-F$49)*1/4))/(1+$B54)^6+$F$19*(1+(F$49+(假设!$C$29-F$49)*0/4))*(1+(F$49+(假设!$C$29-F$49)*1/4))*(1+(F$49+(假设!$C$29-F$49)*2/4))/(1+$B54)^7+$F$19*(1+(F$49+(假设!$C$29-F$49)*0/4))*(1+(F$49+(假设!$C$29-F$49)*1/4))*(1+(F$49+(假设!$C$29-F$49)*2/4))*(1+(F$49+(假设!$C$29-F$49)*3/4))/(1+$B54)^8+$F$19*(1+(F$49+(假设!$C$29-F$49)*0/4))*(1+(F$49+(假设!$C$29-F$49)*1/4))*(1+(F$49+(假设!$C$29-F$49)*2/4))*(1+(F$49+(假设!$C$29-F$49)*3/4))*(1+(F$49+(假设!$C$29-F$49)*4/4))/(1+$B54)^9+$F$19*(1+(F$49+(假设!$C$29-F$49)*0/4))*(1+(F$49+(假设!$C$29-F$49)*1/4))*(1+(F$49+(假设!$C$29-F$49)*2/4))*(1+(F$49+(假设!$C$29-F$49)*3/4))*(1+(F$49+(假设!$C$29-F$49)*4/4))*(1+$C$8)/($B54-$C$8)/(1+$B54)^9+$C$29-$C$30)/$C$32,0) -> 54.209178 | G54: =IFERROR((SUMPRODUCT($C$19:$F$19/(1+$B54)^$C$12:$F$12)+$F$19*(1+(G$49+(假设!$C$29-G$49)*0/4))/(1+$B54)^5+$F$19*(1+(G$49+(假设!$C$29-G$49)*0/4))*(1+(G$49+(假设!$C$29-G$49)*1/4))/(1+$B54)^6+$F$19*(1+(G$49+(假设!$C$29-G$49)*0/4))*(1+(G$49+(假设!$C$29-G$49)*1/4))*(1+(G$49+(假设!$C$29-G$49)*2/4))/(1+$B54)^7+$F$19*(1+(G$49+(假设!$C$29-G$49)*0/4))*(1+(G$49+(假设!$C$29-G$49)*1/4))*(1+(G$49+(假设!$C$29-G$49)*2/4))*(1+(G$49+(假设!$C$29-G$49)*3/4))/(1+$B54)^8+$F$19*(1+(G$49+(假设!$C$29-G$49)*0/4))*(1+(G$49+(假设!$C$29-G$49)*1/4))*(1+(G$49+(假设!$C$29-G$49)*2/4))*(1+(G$49+(假设!$C$29-G$49)*3/4))*(1+(G$49+(假设!$C$29-G$49)*4/4))/(1+$B54)^9+$F$19*(1+(G$49+(假设!$C$29-G$49)*0/4))*(1+(G$49+(假设!$C$29-G$49)*1/4))*(1+(G$49+(假设!$C$29-G$49)*2/4))*(1+(G$49+(假设!$C$29-G$49)*3/4))*(1+(G$49+(假设!$C$29-G$49)*4/4))*(1+$C$8)/($B54-$C$8)/(1+$B54)^9+$C$29-$C$30)/$C$32,0) -> 55.882587

Sheet 相对估值
A1: 相对估值（PE/PB）与可比公司
A2: 可比公司估值倍数请按最新行情填入黄底单元格（本模型不预填，避免使用过期数据）。
A4: PE估值区间（元/股）
A5: PE倍数 | C5: 2026E | D5: 2027E | E5: 2028E
A6: =假设!$C$31+(假设!$C$32-假设!$C$31)*0/5 -> 30 | C6: =$A6*三表预测!H32 -> 63.772131 | D6: =$A6*三表预测!I32 -> 82.875152 | E6: =$A6*三表预测!J32 -> 91.421152
A7: =假设!$C$31+(假设!$C$32-假设!$C$31)*1/5 -> 35 | C7: =$A7*三表预测!H32 -> 74.40082 | D7: =$A7*三表预测!I32 -> 96.687677 | E7: =$A7*三表预测!J32 -> 106.65801
A8: =假设!$C$31+(假设!$C$32-假设!$C$31)*2/5 -> 40 | C8: =$A8*三表预测!H32 -> 85.029508 | D8: =$A8*三表预测!I32 -> 110.5002 | E8: =$A8*三表预测!J32 -> 121.89487
A9: =假设!$C$31+(假设!$C$32-假设!$C$31)*3/5 -> 45 | C9: =$A9*三表预测!H32 -> 95.658197 | D9: =$A9*三表预测!I32 -> 124.31273 | E9: =$A9*三表预测!J32 -> 137.13173
A10: =假设!$C$31+(假设!$C$32-假设!$C$31)*4/5 -> 50 | C10: =$A10*三表预测!H32 -> 106.28689 | D10: =$A10*三表预测!I32 -> 138.12525 | E10: =$A10*三表预测!J32 -> 152.36859
A11: =假设!$C$31+(假设!$C$32-假设!$C$31)*5/5 -> 55 | C11: =$A11*三表预测!H32 -> 116.91557 | D11: =$A11*三表预测!I32 -> 151.93778 | E11: =$A11*三表预测!J32 -> 167.60544
A12: EPS（模型） | C12: =三表预测!H32 -> 2.1257377 | D12: =三表预测!I32 -> 2.7625051 | E12: =三表预测!J32 -> 3.0473717
A13: 当前股价对应PE | C13: =三表预测!H97 -> 55.745354 | D13: =三表预测!I97 -> 42.895849 | E13: =三表预测!J97 -> 38.885968
A14: 当前股价对应PB | C14: =三表预测!H98 -> 7.6714923 | D14: =三表预测!I98 -> 6.7684077 | E14: =三表预测!J98 -> 6.0325127
A16: 可比公司（请填入最新倍数）
A17: 公司 | B17: 代码 | C17: PE 2026E | D17: PE 2027E | E17: PB（最新） | F17: 备注
A18: 风华高科 | B18: 000636.SZ | F18: MLCC、电阻
A19: 国瓷材料 | B19: 300285.SZ | F19: 电子陶瓷粉体、MLCC介质材料
A20: 天孚通信 | B20: 300394.SZ | F20: 光器件
A21: 村田制作所 | B21: 6981.T | F21: MLCC龙头
A22: 太阳诱电 | B22: 6976.T | F22: MLCC
A23: 京瓷 | B23: 6971.T | F23: 精密陶瓷、电子元件
A24: 三星电机 | B24: 009150.KS | F24: MLCC
A25: 可比公司中位数 | C25: =IFERROR(MEDIAN(C18:C24),0) -> 0 | D25: =IFERROR(MEDIAN(D18:D24),0) -> 0 | E25: =IFERROR(MEDIAN(E18:E24),0) -> 0
A26: 按可比中位数的三环每股价值（元） | C26: =C25*三表预测!H32 -> 0 | D26: =D25*三表预测!I32 -> 0 | E26: =E25*三表预测!H96 -> 0

Sheet SOFC敏感性
A1: SOFC隔膜片敏感性（2027E）
A2: 收入=Bloom电池片层需求（GW）×(1000/单片功率W)×三环份额×单价；需求与单片功率取“假设”当前情景2027E值。
A4: 2027E Bloom电池片层需求（GW） | C4: =假设!I79 -> 2.5
A5: 2027E单片功率（W/片） | C5: =假设!I83 -> 30
A6: SOFC净利率假设（毛利率扣除费用与税） | C6: 0.22
A7: 2027E模型归母净利润 | C7: =三表预测!I29 -> 5460.6668
A9: 2027E SOFC隔膜片收入（百万元）：三环份额（行）× 单价（列）
A10: 份额 \ 单价（元/片） | C10: 16 | D10: 18 | E10: 20 | F10: 22 | G10: 24 | H10: 26
B11: 0.4 | C11: =$C$4*1000/$C$5*$B11*C$10 -> 533.33333 | D11: =$C$4*1000/$C$5*$B11*D$10 -> 600 | E11: =$C$4*1000/$C$5*$B11*E$10 -> 666.66667 | F11: =$C$4*1000/$C$5*$B11*F$10 -> 733.33333 | G11: =$C$4*1000/$C$5*$B11*G$10 -> 800 | H11: =$C$4*1000/$C$5*$B11*H$10 -> 866.66667
B12: 0.5 | C12: =$C$4*1000/$C$5*$B12*C$10 -> 666.66667 | D12: =$C$4*1000/$C$5*$B12*D$10 -> 750 | E12: =$C$4*1000/$C$5*$B12*E$10 -> 833.33333 | F12: =$C$4*1000/$C$5*$B12*F$10 -> 916.66667 | G12: =$C$4*1000/$C$5*$B12*G$10 -> 1000 | H12: =$C$4*1000/$C$5*$B12*H$10 -> 1083.3333
B13: 0.6 | C13: =$C$4*1000/$C$5*$B13*C$10 -> 800 | D13: =$C$4*1000/$C$5*$B13*D$10 -> 900 | E13: =$C$4*1000/$C$5*$B13*E$10 -> 1000 | F13: =$C$4*1000/$C$5*$B13*F$10 -> 1100 | G13: =$C$4*1000/$C$5*$B13*G$10 -> 1200 | H13: =$C$4*1000/$C$5*$B13*H$10 -> 1300
B14: 0.7 | C14: =$C$4*1000/$C$5*$B14*C$10 -> 933.33333 | D14: =$C$4*1000/$C$5*$B14*D$10 -> 1050 | E14: =$C$4*1000/$C$5*$B14*E$10 -> 1166.6667 | F14: =$C$4*1000/$C$5*$B14*F$10 -> 1283.3333 | G14: =$C$4*1000/$C$5*$B14*G$10 -> 1400 | H14: =$C$4*1000/$C$5*$B14*H$10 -> 1516.6667
B15: 0.8 | C15: =$C$4*1000/$C$5*$B15*C$10 -> 1066.6667 | D15: =$C$4*1000/$C$5*$B15*D$10 -> 1200 | E15: =$C$4*1000/$C$5*$B15*E$10 -> 1333.3333 | F15: =$C$4*1000/$C$5*$B15*F$10 -> 1466.6667 | G15: =$C$4*1000/$C$5*$B15*G$10 -> 1600 | H15: =$C$4*1000/$C$5*$B15*H$10 -> 1733.3333
B16: 0.9 | C16: =$C$4*1000/$C$5*$B16*C$10 -> 1200 | D16: =$C$4*1000/$C$5*$B16*D$10 -> 1350 | E16: =$C$4*1000/$C$5*$B16*E$10 -> 1500 | F16: =$C$4*1000/$C$5*$B16*F$10 -> 1650 | G16: =$C$4*1000/$C$5*$B16*G$10 -> 1800 | H16: =$C$4*1000/$C$5*$B16*H$10 -> 1950
A18: SOFC隔膜片净利润占2027E归母净利润比例
A19: 份额 \ 单价（元/片） | C19: 16 | D19: 18 | E19: 20 | F19: 22 | G19: 24 | H19: 26
B20: 0.4 | C20: =IFERROR($C$4*1000/$C$5*$B20*C$19*$C$6/$C$7,0) -> 0.021486997 | D20: =IFERROR($C$4*1000/$C$5*$B20*D$19*$C$6/$C$7,0) -> 0.024172872 | E20: =IFERROR($C$4*1000/$C$5*$B20*E$19*$C$6/$C$7,0) -> 0.026858747 | F20: =IFERROR($C$4*1000/$C$5*$B20*F$19*$C$6/$C$7,0) -> 0.029544621 | G20: =IFERROR($C$4*1000/$C$5*$B20*G$19*$C$6/$C$7,0) -> 0.032230496 | H20: =IFERROR($C$4*1000/$C$5*$B20*H$19*$C$6/$C$7,0) -> 0.034916371
B21: 0.5 | C21: =IFERROR($C$4*1000/$C$5*$B21*C$19*$C$6/$C$7,0) -> 0.026858747 | D21: =IFERROR($C$4*1000/$C$5*$B21*D$19*$C$6/$C$7,0) -> 0.03021609 | E21: =IFERROR($C$4*1000/$C$5*$B21*E$19*$C$6/$C$7,0) -> 0.033573433 | F21: =IFERROR($C$4*1000/$C$5*$B21*F$19*$C$6/$C$7,0) -> 0.036930777 | G21: =IFERROR($C$4*1000/$C$5*$B21*G$19*$C$6/$C$7,0) -> 0.04028812 | H21: =IFERROR($C$4*1000/$C$5*$B21*H$19*$C$6/$C$7,0) -> 0.043645463
B22: 0.6 | C22: =IFERROR($C$4*1000/$C$5*$B22*C$19*$C$6/$C$7,0) -> 0.032230496 | D22: =IFERROR($C$4*1000/$C$5*$B22*D$19*$C$6/$C$7,0) -> 0.036259308 | E22: =IFERROR($C$4*1000/$C$5*$B22*E$19*$C$6/$C$7,0) -> 0.04028812 | F22: =IFERROR($C$4*1000/$C$5*$B22*F$19*$C$6/$C$7,0) -> 0.044316932 | G22: =IFERROR($C$4*1000/$C$5*$B22*G$19*$C$6/$C$7,0) -> 0.048345744 | H22: =IFERROR($C$4*1000/$C$5*$B22*H$19*$C$6/$C$7,0) -> 0.052374556
B23: 0.7 | C23: =IFERROR($C$4*1000/$C$5*$B23*C$19*$C$6/$C$7,0) -> 0.037602245 | D23: =IFERROR($C$4*1000/$C$5*$B23*D$19*$C$6/$C$7,0) -> 0.042302526 | E23: =IFERROR($C$4*1000/$C$5*$B23*E$19*$C$6/$C$7,0) -> 0.047002807 | F23: =IFERROR($C$4*1000/$C$5*$B23*F$19*$C$6/$C$7,0) -> 0.051703087 | G23: =IFERROR($C$4*1000/$C$5*$B23*G$19*$C$6/$C$7,0) -> 0.056403368 | H23: =IFERROR($C$4*1000/$C$5*$B23*H$19*$C$6/$C$7,0) -> 0.061103648
B24: 0.8 | C24: =IFERROR($C$4*1000/$C$5*$B24*C$19*$C$6/$C$7,0) -> 0.042973995 | D24: =IFERROR($C$4*1000/$C$5*$B24*D$19*$C$6/$C$7,0) -> 0.048345744 | E24: =IFERROR($C$4*1000/$C$5*$B24*E$19*$C$6/$C$7,0) -> 0.053717493 | F24: =IFERROR($C$4*1000/$C$5*$B24*F$19*$C$6/$C$7,0) -> 0.059089242 | G24: =IFERROR($C$4*1000/$C$5*$B24*G$19*$C$6/$C$7,0) -> 0.064460992 | H24: =IFERROR($C$4*1000/$C$5*$B24*H$19*$C$6/$C$7,0) -> 0.069832741
B25: 0.9 | C25: =IFERROR($C$4*1000/$C$5*$B25*C$19*$C$6/$C$7,0) -> 0.048345744 | D25: =IFERROR($C$4*1000/$C$5*$B25*D$19*$C$6/$C$7,0) -> 0.054388962 | E25: =IFERROR($C$4*1000/$C$5*$B25*E$19*$C$6/$C$7,0) -> 0.06043218 | F25: =IFERROR($C$4*1000/$C$5*$B25*F$19*$C$6/$C$7,0) -> 0.066475398 | G25: =IFERROR($C$4*1000/$C$5*$B25*G$19*$C$6/$C$7,0) -> 0.072518616 | H25: =IFERROR($C$4*1000/$C$5*$B25*H$19*$C$6/$C$7,0) -> 0.078561834
A27: Bloom需求（GW，行）× 单片功率（W，列）：2027E SOFC收入（份额与单价取当前情景）
A28: GW \ W | C28: 25 | D28: 27.5 | E28: 30 | F28: 32.5 | G28: 35 | H28: 37.5
B29: 1.5 | C29: =$B29*1000/C$28*假设!I87*假设!I91 -> 903 | D29: =$B29*1000/D$28*假设!I87*假设!I91 -> 820.90909 | E29: =$B29*1000/E$28*假设!I87*假设!I91 -> 752.5 | F29: =$B29*1000/F$28*假设!I87*假设!I91 -> 694.61538 | G29: =$B29*1000/G$28*假设!I87*假设!I91 -> 645 | H29: =$B29*1000/H$28*假设!I87*假设!I91 -> 602
B30: 2 | C30: =$B30*1000/C$28*假设!I87*假设!I91 -> 1204 | D30: =$B30*1000/D$28*假设!I87*假设!I91 -> 1094.5455 | E30: =$B30*1000/E$28*假设!I87*假设!I91 -> 1003.3333 | F30: =$B30*1000/F$28*假设!I87*假设!I91 -> 926.15385 | G30: =$B30*1000/G$28*假设!I87*假设!I91 -> 860 | H30: =$B30*1000/H$28*假设!I87*假设!I91 -> 802.66667
B31: 2.5 | C31: =$B31*1000/C$28*假设!I87*假设!I91 -> 1505 | D31: =$B31*1000/D$28*假设!I87*假设!I91 -> 1368.1818 | E31: =$B31*1000/E$28*假设!I87*假设!I91 -> 1254.1667 | F31: =$B31*1000/F$28*假设!I87*假设!I91 -> 1157.6923 | G31: =$B31*1000/G$28*假设!I87*假设!I91 -> 1075 | H31: =$B31*1000/H$28*假设!I87*假设!I91 -> 1003.3333
B32: 3 | C32: =$B32*1000/C$28*假设!I87*假设!I91 -> 1806 | D32: =$B32*1000/D$28*假设!I87*假设!I91 -> 1641.8182 | E32: =$B32*1000/E$28*假设!I87*假设!I91 -> 1505 | F32: =$B32*1000/F$28*假设!I87*假设!I91 -> 1389.2308 | G32: =$B32*1000/G$28*假设!I87*假设!I91 -> 1290 | H32: =$B32*1000/H$28*假设!I87*假设!I91 -> 1204
B33: 3.5 | C33: =$B33*1000/C$28*假设!I87*假设!I91 -> 2107 | D33: =$B33*1000/D$28*假设!I87*假设!I91 -> 1915.4545 | E33: =$B33*1000/E$28*假设!I87*假设!I91 -> 1755.8333 | F33: =$B33*1000/F$28*假设!I87*假设!I91 -> 1620.7692 | G33: =$B33*1000/G$28*假设!I87*假设!I91 -> 1505 | H33: =$B33*1000/H$28*假设!I87*假设!I91 -> 1404.6667
B34: 4 | C34: =$B34*1000/C$28*假设!I87*假设!I91 -> 2408 | D34: =$B34*1000/D$28*假设!I87*假设!I91 -> 2189.0909 | E34: =$B34*1000/E$28*假设!I87*假设!I91 -> 2006.6667 | F34: =$B34*1000/F$28*假设!I87*假设!I91 -> 1852.3077 | G34: =$B34*1000/G$28*假设!I87*假设!I91 -> 1720 | H34: =$B34*1000/H$28*假设!I87*假设!I91 -> 1605.3333

Sheet 一致预期对比
A1: 模型与Wind一致预期对比（仅作参照，不作为模型输入）
A2: 资料来源：Wind盈利预测（截至2026-09-30，12家机构）。
A4: 项目（百万元） | C4: 2026E | D4: 2027E | E4: 2028E
A5: 营业收入（一致预期） | C5: 13140 | D5: 17470 | E5: 20690
A6: 归母净利润（一致预期） | C6: 4198 | D6: 6142 | E6: 7143
A7: EPS（一致预期，元） | C7: 2.1 | D7: 3.08 | E7: 3.58
A8: 营业收入（模型） | C8: =三表预测!H6 -> 13715.092 | D8: =三表预测!I6 -> 17294.044 | E8: =三表预测!J6 -> 19666.727
A9: 归母净利润（模型） | C9: =三表预测!H29 -> 4201.9635 | D9: =三表预测!I29 -> 5460.6668 | E9: =三表预测!J29 -> 6023.7652
A10: EPS（模型，元） | C10: =三表预测!H32 -> 2.1257377 | D10: =三表预测!I32 -> 2.7625051 | E10: =三表预测!J32 -> 3.0473717
A11: 营业收入：模型/一致预期-1 | C11: =IFERROR(C8/C5-1,0) -> 0.043766502 | D11: =IFERROR(D8/D5-1,0) -> -0.010071906 | E11: =IFERROR(E8/E5-1,0) -> -0.049457348
A12: 归母净利润：模型/一致预期-1 | C12: =IFERROR(C9/C6-1,0) -> 0.00094413463 | D12: =IFERROR(D9/D6-1,0) -> -0.11093018 | E12: =IFERROR(E9/E6-1,0) -> -0.15668974
A13: EPS：模型/一致预期-1 | C13: =IFERROR(C10/C7-1,0) -> 0.012256048 | D13: =IFERROR(D10/D7-1,0) -> -0.10308277 | E13: =IFERROR(E10/E7-1,0) -> -0.14877885
A15: 一致预期分布（2026E归母净利润，百万元）
A16: 中值 | C16: 4206
A17: 最大值 | C17: 5503
A18: 最小值 | C18: 3367
A19: 标准差 | C19: 720.8
A20: 预测机构数 | C20: 12

Sheet 季度数据
A1: 三环集团 单季度利润表与利润率
A2: 资料来源：Wind单季度利润表（公司公告值），万元÷100=百万元。增速与利润率为公式。
A4: 项目（百万元） | C4: 2024Q1 | D4: 2024Q2 | E4: 2024Q3 | F4: 2024Q4 | G4: 2025Q1 | H4: 2025Q2 | I4: 2025Q3 | J4: 2025Q4 | K4: 2026Q1 | L4: 2026Q2
A5: 营业收入 | C5: 1563.6153 | D5: 1863.7904 | E5: 1953.374 | F5: 1994.2111 | G5: 1833.141 | H5: 2315.6541 | I5: 2359.5738 | J5: 2498.785 | K5: 2680.9934 | L5: 3742.3384
A6: 营业成本 | C6: 935.946 | D6: 1055.4619 | E6: 1088.1091 | F6: 1125.3467 | G6: 1081.3268 | H6: 1326.0529 | I6: 1335.6835 | J6: 1468.6984 | K6: 1515.058 | L6: 2061.4749
A7: 税金及附加 | C7: 18.8928 | D7: 16.482 | E7: 20.0271 | F7: 23.7726 | G7: 27.3729 | H7: 27.3854 | I7: 25.8937 | J7: 27.1306 | K7: 28.1194 | L7: 32.0799
A8: 销售费用 | C8: 16.5916 | D8: 16.6425 | E8: 17.7552 | F8: 28.4024 | G8: 21.2322 | H8: 20.7534 | I8: 24.9725 | J8: 26.2412 | K8: 22.2371 | L8: 22.5728
A9: 管理费用 | C9: 79.9894 | D9: 89.2862 | E9: 93.4194 | F9: 147.1496 | G9: 93.9391 | H9: 97.5199 | I9: 108.3876 | J9: 181.1035 | K9: 123.0153 | L9: 131.9151
A10: 研发费用 | C10: 127.6636 | D10: 131.9825 | E10: 141.5881 | F10: 181.8381 | G10: 145.6916 | H10: 146.9448 | I10: 148.3194 | J10: 212.4809 | K10: 155.8096 | L10: 184.4559
A11: 财务费用 | C11: -44.9783 | D11: -56.7403 | E11: -4.9306 | F11: -65.8527 | G11: -38.1213 | H11: -25.072 | I11: -38.7991 | J11: -25.7796 | K11: -28.973 | L11: -12.9393
A12: 其他收益 | C12: 64.1002 | D12: 77.6604 | E12: 53.3465 | F12: 109.9897 | G12: 87.1963 | H12: 90.7529 | I12: 87.9912 | J12: 124.2274 | K12: 85.4097 | L12: 53.7199
A13: 营业利润 | C13: 505.5875 | D13: 680.0402 | E13: 655.8087 | F13: 681.2689 | G13: 616.3601 | H13: 810.5954 | I13: 831.3498 | J13: 750.1603 | K13: 911.3291 | L13: 1315.4431
A14: 利润总额 | C14: 507.556 | D14: 675.7373 | E14: 658.3478 | F14: 677.3028 | G14: 618.439 | H14: 808.6791 | I14: 834.7089 | J14: 746.3495 | K14: 907.7421 | L14: 1316.2041
A15: 所得税 | C15: 73.8903 | D15: 82.9915 | E15: 81.0467 | F15: 90.7816 | G15: 85.5439 | H15: 104.4896 | I15: 113.8549 | J15: 87.3079 | K15: 116.937 | L15: 175.0134
A16: 净利润 | C16: 433.6656 | D16: 592.7458 | E16: 577.3011 | F16: 586.5212 | G16: 532.8951 | H16: 704.1895 | I16: 720.8541 | J16: 659.0416 | K16: 790.8051 | L16: 1141.1907
A17: 归母净利润 | C17: 432.979 | D17: 592.5672 | E17: 577.7415 | F17: 587.1617 | G17: 532.6514 | H17: 704.4865 | I17: 721.3812 | J17: 659.8652 | K17: 790.8996 | L17: 1141.2187
A19: 利润率与增速（公式）
A20: 毛利率 | C20: =IFERROR(1-C6/C5,0) -> 0.40142182 | D20: =IFERROR(1-D6/D5,0) -> 0.4337014 | E20: =IFERROR(1-E6/E5,0) -> 0.44295916 | F20: =IFERROR(1-F6/F5,0) -> 0.43569329 | G20: =IFERROR(1-G6/G5,0) -> 0.4101235 | H20: =IFERROR(1-H6/H5,0) -> 0.42735277 | I20: =IFERROR(1-I6/I5,0) -> 0.43393019 | J20: =IFERROR(1-J6/J5,0) -> 0.41223499 | ... L20: =IFERROR(1-L6/L5,0) -> 0.44914792
A21: 期间费用率（销售+管理+研发） | C21: =IFERROR((C8+C9+C10)/C5,0) -> 0.14341418 | D21: =IFERROR((D8+D9+D10)/D5,0) -> 0.12764912 | E21: =IFERROR((E8+E9+E10)/E5,0) -> 0.12939801 | F21: =IFERROR((F8+F9+F10)/F5,0) -> 0.17921378 | G21: =IFERROR((G8+G9+G10)/G5,0) -> 0.14230378 | H21: =IFERROR((H8+H9+H10)/H5,0) -> 0.11453269 | I21: =IFERROR((I8+I9+I10)/I5,0) -> 0.11937728 | J21: =IFERROR((J8+J9+J10)/J5,0) -> 0.16801189 | ... L21: =IFERROR((L8+L9+L10)/L5,0) -> 0.090570056
A22: 营业利润率 | C22: =IFERROR(C13/C5,0) -> 0.3233452 | D22: =IFERROR(D13/D5,0) -> 0.36486946 | E22: =IFERROR(E13/E5,0) -> 0.33573125 | F22: =IFERROR(F13/F5,0) -> 0.34162326 | G22: =IFERROR(G13/G5,0) -> 0.33623169 | H22: =IFERROR(H13/H5,0) -> 0.35005029 | I22: =IFERROR(I13/I5,0) -> 0.35233049 | J22: =IFERROR(J13/J5,0) -> 0.30021002 | ... L22: =IFERROR(L13/L5,0) -> 0.35150298
A23: 归母净利率 | C23: =IFERROR(C17/C5,0) -> 0.2769089 | D23: =IFERROR(D17/D5,0) -> 0.31793661 | E23: =IFERROR(E17/E5,0) -> 0.29576594 | F23: =IFERROR(F17/F5,0) -> 0.29443307 | G23: =IFERROR(G17/G5,0) -> 0.29056761 | H23: =IFERROR(H17/H5,0) -> 0.30422786 | I23: =IFERROR(I17/I5,0) -> 0.30572521 | J23: =IFERROR(J17/J5,0) -> 0.26407442 | ... L23: =IFERROR(L17/L5,0) -> 0.30494802
A24: 所得税实际税率 | C24: =IFERROR(C15/C14,0) -> 0.14558059 | D24: =IFERROR(D15/D14,0) -> 0.12281622 | E24: =IFERROR(E15/E14,0) -> 0.12310621 | F24: =IFERROR(F15/F14,0) -> 0.13403399 | G24: =IFERROR(G15/G14,0) -> 0.13832229 | H24: =IFERROR(H15/H14,0) -> 0.12921021 | I24: =IFERROR(I15/I14,0) -> 0.13640073 | J24: =IFERROR(J15/J14,0) -> 0.11697991 | ... L24: =IFERROR(L15/L14,0) -> 0.13296828
A25: 营业收入同比 | G25: =IFERROR(G5/C5-1,0) -> 0.17237341 | H25: =IFERROR(H5/D5-1,0) -> 0.24244341 | I25: =IFERROR(I5/E5-1,0) -> 0.20794779 | J25: =IFERROR(J5/F5-1,0) -> 0.2530193 | K25: =IFERROR(K5/G5-1,0) -> 0.46251347 | L25: =IFERROR(L5/H5-1,0) -> 0.61610424
A26: 营业收入环比 | D26: =IFERROR(D5/C5-1,0) -> 0.19197503 | E26: =IFERROR(E5/D5-1,0) -> 0.048065276 | F26: =IFERROR(F5/E5-1,0) -> 0.02090593 | G26: =IFERROR(G5/F5-1,0) -> -0.080768831 | H26: =IFERROR(H5/G5-1,0) -> 0.26321658 | I26: =IFERROR(I5/H5-1,0) -> 0.018966434 | J26: =IFERROR(J5/I5-1,0) -> 0.058998451 | K26: =IFERROR(K5/J5-1,0) -> 0.072918799 | L26: =IFERROR(L5/K5-1,0) -> 0.39587751
A27: 归母净利润同比 | G27: =IFERROR(G17/C17-1,0) -> 0.23020146 | H27: =IFERROR(H17/D17-1,0) -> 0.18887191 | I27: =IFERROR(I17/E17-1,0) -> 0.24862278 | J27: =IFERROR(J17/F17-1,0) -> 0.12382194 | K27: =IFERROR(K17/G17-1,0) -> 0.4848353 | L27: =IFERROR(L17/H17-1,0) -> 0.61992984
A28: 归母净利润环比 | D28: =IFERROR(D17/C17-1,0) -> 0.36858185 | E28: =IFERROR(E17/D17-1,0) -> -0.025019441 | F28: =IFERROR(F17/E17-1,0) -> 0.016305216 | G28: =IFERROR(G17/F17-1,0) -> -0.092836948 | H28: =IFERROR(H17/G17-1,0) -> 0.3226033 | I28: =IFERROR(I17/H17-1,0) -> 0.023981581 | J28: =IFERROR(J17/I17-1,0) -> -0.085275302 | K28: =IFERROR(K17/J17-1,0) -> 0.19857753 | L28: =IFERROR(L17/K17-1,0) -> 0.44293751

Sheet 历史利润表
A1: 三环集团 历史利润表（合并）
A2: 资料来源：Wind，公司定期报告（公司公告值）；原始单位万元，已除以100换算为百万元。蓝字为历史数据录入值。
A4: 项目（百万元） | B4: 说明 | C4: 2019A | D4: 2020A | E4: 2021A | F4: 2022A | G4: 2023A | H4: 2024A | I4: 2025A | J4: 2025H1 | K4: 2026H1
A5: 营业总收入 | C5: 2726.4517 | D5: 3993.9746 | E5: 6218.042 | F5: 5149.3869 | G5: 5726.6885 | H5: 7374.9908 | I5: 9007.1539 | J5: 4148.7951 | K5: 6423.3318
A6: 营业收入 | C6: 2726.4517 | D6: 3993.9746 | E6: 6218.042 | F6: 5149.3869 | G6: 5726.6885 | H6: 7374.9908 | I6: 9007.1539 | J6: 4148.7951 | K6: 6423.3318
A7: 营业总成本 | C7: 1900.6297 | D7: 2476.9546 | E7: 4072.253 | F7: 3756.1429 | G7: 4417.8651 | H7: 5183.845 | I7: 6419.3584 | J7: 2925.0258 | K7: 4234.8257
A8: 营业成本 | C8: 1388.9159 | D8: 1952.7752 | E8: 3186.5095 | F8: 2878.3209 | G8: 3445.5299 | H8: 4204.8637 | I8: 5211.7617 | J8: 2407.3798 | K8: 3576.5329
A9: 税金及附加 | C9: 31.8318 | D9: 44.3371 | E9: 58.7828 | F9: 63.2677 | G9: 84.2832 | H9: 79.1745 | I9: 107.7827 | J9: 54.7584 | K9: 60.1994
A10: 销售费用 | C10: 52.3056 | D10: 35.7113 | E10: 51.3154 | F10: 57.308 | G10: 74.3431 | H10: 79.3918 | I10: 93.1993 | J10: 41.9856 | K10: 44.8099
A11: 管理费用 | C11: 238.1567 | D11: 299.4133 | E11: 453.2391 | F11: 479.3491 | G11: 429.4141 | H11: 409.8445 | I11: 480.9502 | J11: 191.459 | K11: 254.9304
A12: 研发费用 | C12: 176.5306 | D12: 239.1121 | E12: 418.5388 | F12: 452.1724 | G12: 545.8062 | H12: 583.0724 | I12: 653.4367 | J12: 292.6364 | K12: 340.2655
A13: 财务费用 | C13: 12.8891 | D13: -94.3944 | E13: -96.1326 | F13: -174.2752 | G13: -161.5113 | H13: -172.5019 | I13: -127.772 | J13: -63.1933 | K13: -41.9124
A14: 其中：利息费用 | C14: 6.6845 | D14: 3.375 | E14: 5.6211 | F14: 8.8993 | G14: 22.4881 | H14: 27.7001 | I14: 20.396 | J14: 10.0906 | K14: 12.6989
A15: 减：利息收入 | C15: 5.2352 | D15: 77.3137 | E15: 103.223 | F15: 154.5883 | G15: 174.943 | H15: 203.5985 | I15: 196.88 | J15: 89.6174 | K15: 98.5122
A16: 加：其他收益 | C16: 92.8579 | D16: 97.5766 | E16: 136.3169 | F16: 218.1716 | G16: 348.6995 | H16: 305.0967 | I16: 390.1677 | J16: 177.9491 | K16: 139.1296
A17: 投资净收益 | C17: 86.0618 | D17: 113.9112 | E17: 74.986 | F17: 97.7236 | G17: 56.5334 | H17: 17.1153 | I17: 41.7054 | J17: 21.9679 | K17: 11.3472
A18: 其中：对联营企业和合营企业的投资收益 | C18: 1.4965 | D18: 3.6266 | E18: -0.1547
A19: 公允价值变动净收益 | F19: 20.0144 | G19: 55.0228 | H19: 49.7733 | I19: 30.4662 | J19: 18.7085 | K19: 20.9291
A20: 资产减值损失 | C20: 0.1154 | D20: -43.9714 | E20: -33.4424 | F20: -70.0966 | G20: -0.9734 | H20: -26.3493 | I20: -26.5942 | J20: -12.3834 | K20: -74.0416
A21: 信用减值损失 | C21: 6.664 | D21: -25.0002 | E21: -25.2766 | F21: 3.6367 | G21: 7.6096 | H21: -12.7345 | I21: -15.445 | J21: -4.2076 | K21: -55.945
A22: 资产处置收益 | C22: -0.1789 | D22: 8.1503 | E22: -3.8453 | F22: -1.2666 | G22: 1.9312 | H22: -1.3421 | I22: 0.3699 | J22: 1.1518 | K22: -3.1531
A23: 营业利润 | C23: 1011.3422 | D23: 1667.6866 | E23: 2294.5276 | F23: 1661.427 | G23: 1777.6465 | H23: 2522.7053 | I23: 3008.4656 | J23: 1426.9555 | K23: 2226.7722
A24: 加：营业外收入 | C24: 6.5768 | D24: 11.3112 | E24: 13.838 | F24: 17.419 | G24: 12.9371 | H24: 14.6536 | I24: 19.903 | J24: 9.2304 | K24: 12.1939
A25: 减：营业外支出 | C25: 1.3356 | D25: 0.3934 | E25: 4.8375 | F25: 12.5283 | G25: 7.7361 | H25: 18.4151 | I25: 20.1922 | J25: 9.0679 | K25: 15.0199
A26: 利润总额 | C26: 1016.5834 | D26: 1678.6044 | E26: 2303.5281 | F26: 1666.3178 | G26: 1782.8476 | H26: 2518.9439 | I26: 3008.1764 | J26: 1427.118 | K26: 2223.9462
A27: 减：所得税 | C27: 142.5086 | D27: 236.9779 | E27: 290.216 | F27: 160.2146 | G27: 199.697 | H27: 328.7101 | I27: 391.1963 | J27: 190.0335 | K27: 291.9504
A28: 净利润 | C28: 874.0748 | D28: 1441.6265 | E28: 2013.312 | F28: 1506.1032 | G28: 1583.1506 | H28: 2190.2338 | I28: 2616.9802 | J28: 1237.0845 | K28: 1931.9958
A29: 持续经营净利润 | C29: 874.0748 | D29: 1441.6265 | E29: 2013.312 | F29: 1506.1032 | G29: 1583.1506 | H29: 2190.2338 | I29: 2616.9802 | J29: 1237.0845 | K29: 1931.9958
A30: 减：少数股东损益 | C30: 2.814 | D30: 2.0639 | E30: 2.5006 | F30: 1.3972 | G30: 2.1646 | H30: -0.2156 | I30: -1.4041 | J30: -0.0534 | K30: -0.1224
A31: 归属于母公司所有者的净利润 | C31: 871.2608 | D31: 1439.5626 | E31: 2010.8114 | F31: 1504.706 | G31: 1580.986 | H31: 2190.4494 | I31: 2618.3843 | J31: 1237.1379 | K31: 1932.1182
... A37: 稀释每股收益 | C37: 0.5 | D37: 0.82 | E37: 1.1 | F37: 0.79 | G37: 0.82 | H37: 1.14 | I37: 1.37 | J37: 0.65 | K37: 1.01

Sheet 历史资产负债表
A1: 三环集团 历史资产负债表（合并）
A2: 资料来源：Wind，公司定期报告（公司公告值）；原始单位万元，已除以100换算为百万元。蓝字为历史数据录入值。
A4: 项目（百万元） | B4: 说明 | C4: 2019A | D4: 2020A | E4: 2021A | F4: 2022A | G4: 2023A | H4: 2024A | I4: 2025A | J4: 2025H1 | K4: 2026H1
A5: 货币资金 | C5: 1078.6418 | D5: 2945.9196 | E5: 5552.412 | F5: 4509.4292 | G5: 2841.6149 | H5: 3062.8452 | I5: 3057.7786 | J5: 5430.1287 | K5: 3825.5415
A6: 交易性金融资产 | C6: 2471.3739 | D6: 2547.0917 | E6: 2693.5949 | F6: 4255.0144 | G6: 3846.7081 | H6: 5053.3869 | I6: 3758.5116 | J6: 2865.6921 | K6: 3256.5671
A7: 应收票据及应收账款 | C7: 874.6517 | D7: 1217.3981 | E7: 2139.811 | F7: 1633.0632 | G7: 2089.1202 | H7: 2513.8265 | I7: 2914.3696 | J7: 2619.3474 | K7: 3830.7259
A8: 应收票据 | C8: 186.3636 | D8: 38.771 | E8: 611.4843 | F8: 435.4813 | G8: 462.5221 | H8: 642.0757 | I8: 754.9216 | J8: 645.5199 | K8: 802.9765
A9: 应收账款 | C9: 688.2881 | D9: 1178.6271 | E9: 1528.3267 | F9: 1197.5819 | G9: 1626.598 | H9: 1871.7507 | I9: 2159.448 | J9: 1973.8276 | K9: 3027.7493
A10: 应收款项融资 | C10: 118.4119 | D10: 519.8569 | E10: 137.0218 | F10: 81.9324 | G10: 170.1508 | H10: 172.5082 | I10: 345.5521 | J10: 185.3687 | K10: 357.0871
A11: 预付款项 | C11: 34.0747 | D11: 50.6405 | E11: 56.4665 | F11: 22.8533 | G11: 45.7734 | H11: 62.2607 | I11: 75.5091 | J11: 65.5243 | K11: 141.655
A12: 其他应收款(合计) | C12: 56.6467 | D12: 167.309 | E12: 151.249 | F12: 83.7475 | G12: 44.234 | H12: 28.6627 | I12: 18.4395 | J12: 20.1296 | K12: 17.1209
A13: 应收股利 | D13: 0
A14: 应收利息 | D14: 8.8488
A15: 其他应收款 | C15: 56.6467 | D15: 158.4602 | E15: 151.249 | F15: 83.7475 | G15: 44.234 | H15: 28.6627 | I15: 18.4395 | J15: 20.1296 | K15: 17.1209
A16: 存货 | C16: 646.8998 | D16: 885.4702 | E16: 1796.5411 | F16: 1885.8512 | G16: 1753.5978 | H16: 2180.7115 | I16: 2391.7224 | J16: 2163.2406 | K16: 2811.0479
A17: 其他流动资产 | C17: 17.5545 | D17: 29.3159 | E17: 259.4314 | F17: 348.8942 | G17: 488.1799 | H17: 527.8337 | I17: 519.6397 | J17: 502.1979 | K17: 469.6768
A18: 流动资产合计 | C18: 5298.255 | D18: 8363.002 | E18: 12786.528 | F18: 12820.785 | G18: 11279.379 | H18: 13602.035 | I18: 13081.523 | J18: 13851.629 | K18: 14709.422
A19: 长期股权投资 | C19: 103.3009 | D19: 100.6275
A20: 其他权益工具投资 | C20: 1.8748 | D20: 2.478 | E20: 2.5805 | F20: 2.7738 | G20: 2.7994 | H20: 2.9601 | I20: 3.1953 | J20: 2.9601 | K20: 3.1953
A21: 投资性房地产 | G21: 127.7244 | H21: 64.7164 | I21: 59.3194 | J21: 61.1679 | K21: 57.471
A22: 固定资产(合计) | C22: 1826.9422 | D22: 2377.2842 | E22: 4312.4233 | F22: 5190.5526 | G22: 5102.6825 | H22: 5733.7872 | I22: 6189.5406 | J22: 5736.3544 | K22: 6088.6838
A23: 固定资产 | C23: 1826.9422 | D23: 2377.2842 | E23: 4312.4233 | F23: 5190.5526 | G23: 5100.7576 | H23: 5733.7872 | I23: 6189.5406 | J23: 5736.3544 | K23: 6088.6838
A24: 固定资产清理 | G24: 1.9249
A25: 在建工程(合计) | C25: 644.1608 | D25: 788.7316 | E25: 725.0642 | F25: 690.5385 | G25: 681.2029 | H25: 593.6648 | I25: 400.1746 | J25: 536.202 | K25: 848.3738
A26: 在建工程 | C26: 644.1608 | D26: 788.7316 | E26: 725.0642 | F26: 690.5385 | G26: 681.2029 | H26: 593.6648 | I26: 400.1746 | J26: 536.202 | K26: 848.3738
A27: 使用权资产 | E27: 9.2459 | F27: 36.5573 | G27: 29.9601 | H27: 24.904 | I27: 20.1651 | J27: 22.5601 | K27: 24.0012
A28: 无形资产 | C28: 326.4268 | D28: 198.8745 | E28: 299.0002 | F28: 363.5942 | G28: 452.4957 | H28: 440.75 | I28: 445.4013 | J28: 438.4908 | K28: 435.7378
A29: 商誉 | C29: 253.7905 | D29: 242.3544 | E29: 218.0344 | F29: 224.171 | G29: 237.3472 | H29: 227.2756 | I29: 248.7115 | J29: 253.7518 | K29: 234.5658
A30: 长期待摊费用 | C30: 15.5597 | D30: 14.6331 | E30: 19.6492 | F30: 24.6772 | G30: 19.0821 | H30: 17.6421 | I30: 10.0005 | J30: 11.8589 | K30: 11.1037
A31: 递延所得税资产 | C31: 44.3924 | D31: 49.3523 | E31: 98.7072 | F31: 187.4023 | G31: 182.164 | H31: 247.2083 | I31: 163.9345 | J31: 222.0775 | K31: 181.5929
A32: 其他非流动资产 | C32: 56.9765 | D32: 209.747 | E32: 148.8167 | F32: 52.3243 | G32: 3712.1273 | H32: 2960.8591 | I32: 5884.1223 | J32: 2960.8195 | K32: 5843.9334
A33: 非流动资产合计 | C33: 3273.4247 | D33: 3984.0826 | E33: 5833.5215 | F33: 6772.5912 | G33: 10547.586 | H33: 10313.768 | I33: 13424.565 | J33: 10246.243 | K33: 13728.659
A34: 资产总计 | C34: 8571.6797 | D34: 12347.085 | E34: 18620.049 | F34: 19593.377 | G34: 21826.965 | H34: 23915.803 | I34: 26506.088 | J34: 24097.872 | K34: 28438.081
A35: 短期借款 | E35: 42.1648 | F35: 151.8424 | G35: 740.5347 | H35: 474.7949 | I35: 539.4178 | J35: 443.2471 | K35: 739.8641
A36: 应付票据及应付账款 | C36: 151.9182 | D36: 442.5423 | E36: 830.1951 | F36: 635.0511 | G36: 980.6995 | H36: 1295.3039 | I36: 1927.9853 | J36: 1290.0362 | K36: 2752.2303
A37: 应付票据 | F37: 27.8661 | G37: 242.5137 | H37: 521.4807 | I37: 1119.1886 | J37: 594.3072 | K37: 1487.9957
A38: 应付账款 | C38: 151.9182 | D38: 442.5423 | E38: 830.1951 | F38: 607.185 | G38: 738.1858 | H38: 773.8232 | I38: 808.7966 | J38: 695.729 | K38: 1264.2346
A39: 预收款项 | C39: 21.634
A40: 合同负债 | D40: 35.7081 | E40: 25.358 | F40: 18.6235 | G40: 22.6123 | H40: 30.7816 | I40: 23.8862 | J40: 30.0577 | K40: 78.3734
A41: 应付职工薪酬 | C41: 100.4094 | D41: 194.3573 | E41: 283.548 | F41: 242.2859 | G41: 267.3971 | H41: 347.7306 | I41: 395.6466 | J41: 167.7551 | K41: 241.0946
A42: 应交税费 | C42: 67.1714 | D42: 77.7808 | E42: 54.9989 | F42: 198.0626 | G42: 157.7104 | H42: 146.4485 | I42: 213.8164 | J42: 123.0478 | K42: 228.3778
A43: 其他应付款(合计) | C43: 118.6857 | D43: 14.8506 | E43: 34.0223 | F43: 54.6813 | G43: 58.1247 | H43: 90.8459 | I43: 114.3282 | J43: 97.5559 | K43: 183.1643
A44: 应付股利 | C44: 2.5765
A45: 其他应付款 | C45: 116.1092 | D45: 14.8506 | E45: 34.0223 | F45: 54.6813 | G45: 58.1247 | H45: 90.8459 | I45: 114.3282 | J45: 97.5559 | K45: 183.1643
A46: 一年内到期的非流动负债 | C46: 19.5388 | E46: 7.7844 | F46: 33.593 | G46: 4.7445 | H46: 4.5523 | I46: 3.2946 | J46: 3.9882 | K46: 4.8332
A47: 其他流动负债 | D47: 4.6183 | E47: 295.9292 | F47: 149.1519 | G47: 168.719 | H47: 203.7941 | I47: 262.1147 | J47: 227.2469 | K47: 197.2194
A48: 流动负债合计 | C48: 479.3574 | D48: 769.8573 | E48: 1574.0006 | F48: 1483.2915 | G48: 2400.5423 | H48: 2594.252 | I48: 3480.4898 | J48: 2382.9348 | K48: 4425.157
A49: 长期借款 | I49: 24.925 | J49: 29.95 | K49: 24.9
A50: 租赁负债 | E50: 1.7371 | F50: 30.6415 | G50: 26.5735 | H50: 22.2459 | I50: 18.7998 | J50: 20.6598 | K50: 21.2371
A51: 长期应付款(合计) | C51: 29.3356 | D51: 28.7048 | E51: 29.3126
A52: 长期应付款 | C52: 29.3356 | D52: 28.7048 | E52: 29.3126
A53: 专项应付款 | D53: 0 | E53: 0
A54: 预计负债 | C54: 0.8032 | D54: 0.7451 | E54: 0.641 | F54: 0.8841 | G54: 2.5309 | H54: 1.2631 | J54: 0.8378
A55: 递延所得税负债 | C55: 60.1878 | D55: 104.8827 | E55: 213.3536 | F55: 242.9296 | G55: 278.5697 | H55: 365.7018 | I55: 286.8605 | J55: 354.6833 | K55: 295.9806
A56: 递延收益-非流动负债 | C56: 402.0755 | D56: 539.3098 | E56: 609.4307 | F56: 732.2181 | G56: 879.648 | H56: 1060.572 | I56: 1031.9704 | J56: 1021.3364 | K56: 1022.2304
A57: 其他非流动负债 | C57: 90 | D57: 90
A58: 非流动负债合计 | C58: 582.4022 | D58: 763.6424 | E58: 854.4751 | F58: 1006.6732 | G58: 1187.3221 | H58: 1449.7828 | I58: 1362.5557 | J58: 1427.4673 | K58: 1364.3481
A59: 负债合计 | C59: 1061.7596 | D59: 1533.4998 | E59: 2428.4757 | F59: 2489.9647 | G59: 3587.8644 | H59: 4044.0348 | I59: 4843.0455 | J59: 3810.4021 | K59: 5789.5051
A60: 实收资本(或股本) | C60: 1743.163 | D60: 1816.906 | E60: 1916.4974 | F60: 1916.4974 | G60: 1916.4974 | H60: 1916.4974 | I60: 1916.4974 | J60: 1916.4974 | K60: 1916.4974
A61: 资本公积 | C61: 384.4055 | D61: 2438.0208 | E61: 6218.2411 | F61: 6218.2411 | G61: 6218.2411 | H61: 6218.2411 | I61: 6218.2411 | J61: 6218.2411 | K61: 6218.2411
A62: 减：库存股 | C62: 106.7257 | I62: 175.4407 | J62: 175.4407 | K62: 175.4407
A63: 其他综合收益 | C63: 11.3846 | D63: -11.2027 | E63: -70.7075 | F63: -52.7573 | G63: -21.0949 | H63: -42.0416 | I63: 34.0112 | J63: 38.3347 | K63: -52.3375
A64: 盈余公积 | C64: 808.0083 | D64: 903.6916 | E64: 1037.3061 | F64: 1131.1383 | G64: 1131.1383 | H64: 1131.1383 | I64: 1131.1383 | J64: 1131.1383 | K64: 1131.1383
A65: 未分配利润 | C65: 4669.6844 | D65: 5665.9892 | E65: 7088.9596 | F65: 7886.5543 | G65: 8988.4159 | H65: 10642.246 | I65: 12534.312 | J65: 11153.066 | K65: 13606.317
A66: 归属于母公司所有者权益合计 | C66: 7509.9201 | D66: 10813.405 | E66: 16190.297 | F66: 17099.674 | G66: 18233.198 | H66: 19866.081 | I66: 21658.759 | J66: 20281.836 | K66: 22644.415
A67: 少数股东权益 | D67: 0.18 | E67: 1.2769 | F67: 3.7382 | G67: 5.9029 | H67: 5.6872 | I67: 4.2831 | J67: 5.6339 | K67: 4.1607
A68: 所有者权益合计 | C68: 7509.9201 | D68: 10813.585 | E68: 16191.574 | F68: 17103.412 | G68: 18239.101 | H68: 19871.768 | I68: 21663.042 | J68: 20287.47 | K68: 22648.576
A69: 负债和所有者权益总计 | C69: 8571.6797 | D69: 12347.085 | E69: 18620.049 | F69: 19593.377 | G69: 21826.965 | H69: 23915.803 | I69: 26506.088 | J69: 24097.872 | K69: 28438.081

Sheet 历史现金流量表
A1: 三环集团 历史现金流量表（合并）
A2: 资料来源：Wind，公司定期报告（公司公告值）；原始单位万元，已除以100换算为百万元。蓝字为历史数据录入值。
A4: 项目（百万元） | B4: 说明 | C4: 2019A | D4: 2020A | E4: 2021A | F4: 2022A | G4: 2023A | H4: 2024A | I4: 2025A | J4: 2025H1 | K4: 2026H1
A5: 销售商品、提供劳务收到的现金 | C5: 3579.8394 | D5: 3658.2067 | E5: 5010.4029 | F5: 5150.8415 | G5: 5049.3661 | H5: 6618.7955 | I5: 8243.4605 | J5: 3916.3724 | K5: 5413.4086
A6: 收到的税费返还 | C6: 30.2336 | D6: 23.2036 | E6: 14.362 | F6: 189.2736 | G6: 140.4832 | H6: 153.0346 | I6: 96.8924 | J6: 8.105 | K6: 51.1513
A7: 收到其他与经营活动有关的现金 | C7: 236.781 | D7: 352.0468 | E7: 408.5564 | F7: 605.9512 | G7: 648.9155 | H7: 603.805 | I7: 461.7296 | J7: 177.3983 | K7: 232.647
A8: 经营活动现金流入小计 | C8: 3846.8541 | D8: 4033.4571 | E8: 5433.3213 | F8: 5946.0662 | G8: 5838.7647 | H8: 7375.6351 | I8: 8802.0825 | J8: 4101.8757 | K8: 5697.2069
A9: 购买商品、接受劳务支付的现金 | C9: 957.2031 | D9: 1481.2912 | E9: 2131.5256 | F9: 1646.5979 | G9: 1747.1491 | H9: 2153.5884 | I9: 2753.8858 | J9: 1344.7955 | K9: 2385.2742
A10: 支付给职工以及为职工支付的现金 | C10: 642.944 | D10: 835.0981 | E10: 1367.2278 | F10: 1478.1609 | G10: 1376.8356 | H10: 1772.4983 | I10: 1992.9064 | J10: 1068.4105 | K10: 1262.4736
A11: 支付的各项税费 | C11: 376.9661 | D11: 406.6268 | E11: 554.7171 | F11: 540.2397 | G11: 766.2418 | H11: 808.898 | I11: 915.9167 | J11: 450.5233 | K11: 566.8132
A12: 支付其他与经营活动有关的现金 | C12: 155.0805 | D12: 135.5401 | E12: 225.5286 | F12: 207.1942 | G12: 229.5702 | H12: 237.5281 | I12: 261.7646 | J12: 110.437 | K12: 185.3264
A13: 经营活动现金流出小计 | C13: 2132.1938 | D13: 2858.5562 | E13: 4278.9991 | F13: 3872.1927 | G13: 4119.7967 | H13: 4972.5128 | I13: 5924.4734 | J13: 2974.1663 | K13: 4399.8873
A14: 经营活动产生的现金流量净额 | C14: 1714.6603 | D14: 1174.9009 | E14: 1154.3222 | F14: 2073.8736 | G14: 1718.968 | H14: 2403.1223 | I14: 2877.6091 | J14: 1127.7094 | K14: 1297.3196
A15: 收回投资收到的现金 | C15: 7058.4501 | D15: 7734.1026 | E15: 13148.951 | F15: 12490.036 | G15: 13435 | H15: 66602.15 | I15: 168585.03 | J15: 100066.18 | K15: 69242.208
A16: 取得投资收益收到的现金 | C16: 82.4918 | D16: 116.5182 | E16: 74.5134 | F16: 96.8132 | G16: 109.8625 | H16: 63.7652 | I16: 267.5621 | J16: 57.9618 | K16: 94.9076
A17: 处置固定资产、无形资产和其他长期资产收回的现金净额 | D17: 17.321 | E17: 4.687 | F17: 61.3832 | G17: 14.3567 | H17: 29.458 | I17: 3.726 | J17: 3.3433 | K17: 3.6919
A18: 收到其他与投资活动有关的现金 | D18: 31.2675
A19: 投资活动现金流入小计 | C19: 7140.9419 | D19: 7899.2092 | E19: 13228.151 | F19: 12648.232 | G19: 13559.219 | H19: 66695.373 | I19: 168856.32 | J19: 100127.49 | K19: 69340.808
A20: 购建固定资产、无形资产和其他长期资产支付的现金 | C20: 578.5731 | D20: 1164.2238 | E20: 1910.3652 | F20: 1124.8091 | G20: 545.8847 | H20: 639.0352 | I20: 580.092 | J20: 207.1667 | K20: 476.371
A21: 投资支付的现金 | C21: 7418.3671 | D21: 7785.7056 | E21: 13194.55 | F21: 15330.15 | G21: 16788.26 | H21: 67410.214 | I21: 169100.42 | J21: 98547.716 | K21: 68544.397
A22: 支付其他与投资活动有关的现金 | H22: 0.0553 | I22: 0.163 | J22: 0.0906 | K22: 0.0626
A23: 投资活动现金流出小计 | C23: 7996.9402 | D23: 8949.9294 | E23: 15104.915 | F23: 16454.959 | G23: 17334.144 | H23: 68049.304 | I23: 169680.68 | J23: 98754.974 | K23: 69020.831
A24: 投资活动产生的现金流量净额 | C24: -855.9983 | D24: -1050.7201 | E24: -1876.7642 | F24: -3806.7269 | G24: -3774.925 | H24: -1353.9311 | I24: -824.3604 | J24: 1372.5114 | K24: 319.9769
A25: 吸收投资收到的现金 | D25: 2153.43 | E25: 3882.12
A26: 其中：子公司吸收少数股东投资收到的现金 | D26: 0.18 | E26: 1.62
A27: 取得借款收到的现金 | C27: 90 | G27: 1104.9694 | H27: 471.927 | I27: 30 | J27: 30 | K27: 110.6774
A28: 收到其他与筹资活动有关的现金 | C28: 24.81
A29: 筹资活动现金流入小计 | C29: 114.81 | D29: 2153.43 | E29: 3882.12 | G29: 1104.9694 | H29: 471.927 | I29: 30 | J29: 30 | K29: 110.6774
A30: 偿还债务支付的现金 | C30: 318.0456 | E30: 90 | G30: 454.8588 | H30: 1122.2695 | I30: 5.025 | K30: 0.025
A31: 分配股利、利润或偿付利息支付的现金 | C31: 442.7123 | D31: 350.151 | E31: 454.2265 | F31: 617.7758 | G31: 489.9347 | H31: 553.6596 | I31: 726.6256 | J31: 726.3767 | K31: 860.9669
A32: 其中：子公司支付给少数股东的股利、利润 | C32: 5.2167 | F32: 4.4966
A33: 支付其他与筹资活动有关的现金 | C33: 28.1973 | D33: 58.4445 | E33: 9.7845 | F33: 11.1512 | G33: 6.2402 | H33: 1.5249 | I33: 192.03 | J33: 176.7303 | K33: 9.8351
A34: 筹资活动现金流出小计 | C34: 788.9552 | D34: 408.5955 | E34: 554.011 | F34: 628.927 | G34: 951.0336 | H34: 1677.4541 | I34: 923.6806 | J34: 903.1069 | K34: 870.827
A35: 筹资活动产生的现金流量净额 | C35: -674.1452 | D35: 1744.8345 | E35: 3328.109 | F35: -628.927 | G35: 153.9358 | H35: -1205.5271 | I35: -893.6806 | J35: -873.1069 | K35: -760.1495
A36: 汇率变动对现金的影响 | C36: 4.628 | D36: -0.6735 | E36: -8.1464 | F36: 9.9994 | G36: 7.436 | H36: -0.4631 | I36: -14.4299 | J36: 13.6897 | K36: -62.0636
A37: 现金及现金等价物净增加额 | C37: 189.1449 | D37: 1868.3418 | E37: 2597.5206 | F37: -2351.781 | G37: -1894.5852 | H37: -156.799 | I37: 1145.1382 | J37: 1640.8036 | K37: 795.0833
A38: 期初现金及现金等价物余额 | C38: 888.4161 | D38: 1077.561 | E38: 2945.9028 | F38: 5543.4234 | G38: 3191.6424 | H38: 1297.0572 | I38: 1140.2582 | J38: 1140.2582 | K38: 2285.3964
A39: 期末现金及现金等价物余额 | C39: 1077.561 | D39: 2945.9028 | E39: 5543.4234 | F39: 3191.6424 | G39: 1297.0572 | H39: 1140.2582 | I39: 2285.3964 | J39: 2781.0618 | K39: 3080.4797
A40: 净利润 | C40: 874.0748 | D40: 1441.6265 | E40: 2013.312 | F40: 1506.1032 | G40: 1583.1506 | H40: 2190.2338 | I40: 2616.9802 | J40: 1237.0845 | K40: 1931.9958
A41: 加：资产减值准备 | C41: -6.7793 | D41: 68.9716 | E41: 58.719 | F41: 66.46 | G41: -6.6362 | H41: 39.0838 | I41: 26.5942 | J41: 16.591 | K41: 74.0416
A42: 信用减值损失 | I42: 15.445 | K42: 55.945
A43: 固定资产折旧、油气资产折耗、生产性生物资产折旧 | C43: 252.3894 | D43: 263.9948 | E43: 364.7864 | F43: 515.7214 | G43: 583.1808 | H43: 632.0889 | I43: 715.1475 | J43: 346.4568 | K43: 391.2897
A44: 无形资产摊销 | C44: 9.7446 | D44: 10.2197 | E44: 7.7336 | F44: 8.7657 | G44: 10.7699 | H44: 12.2777 | I44: 12.2258 | J44: 6.1624 | K44: 6.4267
A45: 使用权资产折旧 | E45: 7.5487 | F45: 10.9972 | G45: 7.3842 | H45: 4.9635 | I45: 4.6801 | J45: 2.3488 | K45: 2.2109
A46: 长期待摊费用摊销 | C46: 3.9655 | D46: 4.8735 | E46: 7.4401 | F46: 8.8908 | G46: 8.0975 | H46: 9.7894 | I46: 12.097 | J46: 6.9988 | K46: 4.3267
A47: 处置固定资产、无形资产和其他长期资产的损失 | C47: 0.1789 | D47: -8.1503 | E47: 3.8453 | F47: 1.2666 | G47: -1.9312 | H47: 1.3421 | I47: -0.3699 | J47: -1.1518 | K47: 3.1531
A48: 固定资产报废损失 | C48: 0.0353 | D48: 0.0083 | E48: 3.8931 | F48: 4.0454 | G48: 3.5321 | H48: 9.4646 | I48: 2.9407 | J48: 3.0454 | K48: 11.5026
A49: 公允价值变动损失 | F49: -20.0144 | G49: -55.0228 | H49: -49.7733 | I49: -30.4662 | J49: -18.7085 | K49: -20.9291
A50: 财务费用 | C50: 6.6845 | D50: 3.375 | E50: 5.6211 | F50: -1.1 | G50: -62.3017 | H50: -90.6263 | I50: -137.6439 | J50: -73.6075 | K50: -26.6906
A51: 投资损失 | C51: -86.0618 | D51: -113.9112 | E51: -74.986 | F51: -97.7236 | G51: -56.5334 | H51: -17.1153 | I51: -41.7054 | J51: -21.9679 | K51: -11.3472
A52: 递延所得税资产减少 | C52: 8.9218 | D52: -4.9599 | E52: -49.3549 | F52: -88.6952 | G52: 5.2383 | H52: -65.0443 | I52: 83.2737 | J52: 25.1308 | K52: -17.6584
A53: 递延所得税负债增加 | C53: 31.1886 | D53: 44.6948 | E53: 108.471 | F53: 29.576 | G53: 35.6401 | H53: 87.1321 | I53: -78.8413 | J53: -11.0185 | K53: 9.1201
A54: 存货的减少 | C54: 40.5921 | D54: -262.409 | E54: -901.4535 | F54: -159.4067 | G54: 131.2799 | H54: -453.463 | I54: -237.605 | J54: 25.2898 | K54: -473.9266
A55: 经营性应收项目的减少 | C55: 672.0659 | D55: -894.4269 | E55: -793.3632 | F55: 623.9934 | G55: -566.1322 | H55: -164.8842 | I55: -575.2987 | J55: -135.9008 | K55: -1074.2823
A56: 经营性应付项目的增加 | C56: -92.34 | D56: 620.9939 | E56: 392.1096 | F56: -335.0064 | G56: 99.2519 | H56: 257.653 | I56: 490.1555 | J56: -279.044 | K56: 432.1415
A57: 间接法-经营活动产生的现金流量净额 | C57: 1714.6603 | D57: 1174.9009 | E57: 1154.3222 | F57: 2073.8736 | G57: 1718.968 | H57: 2403.1223 | I57: 2877.6091 | J57: 1127.7094 | K57: 1297.3196
A58: 现金的期末余额 | C58: 1077.561 | D58: 2945.9028 | E58: 5543.4234 | F58: 3191.6424 | G58: 1297.0572 | H58: 1140.2582 | I58: 2285.3964 | J58: 2781.0618 | K58: 3080.4797
A59: 减：现金的期初余额 | C59: 888.4161 | D59: 1077.561 | E59: 2945.9028 | F59: 5543.4234 | G59: 3191.6424 | H59: 1297.0572 | I59: 1140.2582 | J59: 1140.2582 | K59: 2285.3964
A60: 间接法-现金及现金等价物净增加额 | C60: 189.1449 | D60: 1868.3418 | E60: 2597.5206 | F60: -2351.781 | G60: -1894.5852 | H60: -156.799 | I60: 1145.1382 | J60: 1640.8036 | K60: 795.0833

Sheet 调研要点
A1: 产业链调研与公开信息要点（用于SOFC子模型与Bloom需求假设）
A2: 来源：Third Bridge访谈纪要（2026-04-03、2026-06-11、2026-07-22）及公开资料；访谈观点为专家个人判断，仅作假设参考。
A4: 日期 | B4: 来源 | C4: 要点 | D4: 模型中的用途
A5: 2026-04-03 | B5: Bloom前高级工程经理 | C5: Bloom对外产能指电池片与电堆层；其中约25%-30%用于翻新与现场更换；2026年底电池片与电堆产能约2GW，收入端上限约1.5GW | D5: 电池片层需求与验收量的换算
A6: 2026-04-03 | B6: Bloom前高级工程经理 | C6: 2025年验收约500MW，四季度产能折年约800MW；2026年实际验收约1.25-1.5GW；2027年底收入端产能2.5-3GW；2028-29年电堆产能目标约5GW | D6: Bloom电池片层需求（GW）各情景
A7: 2026-04-03 | B7: Bloom前高级工程经理 | C7: 约两年后推出新一代产品，单位产能对应更多kW；未来两年首次面临电池片与电堆的制造约束 | D7: 单片功率提升假设；份额下降时点
A8: 2026-04-03 | B8: Bloom前高级工程经理 | C8: 系统价格（含激励后）约3,300-3,600美元/kW；部分合约发货即确认验收，现场服务与特种焊接人手是验收瓶颈 | D8: 采购与验收时差（库存）
A9: 2026-06-11 | B9: 三环前业务拓展负责人 | C9: 与Bloom的隔膜片合作十几年，从氧化铝陶瓷开始；隔膜片市场体量小，三环利用富余产能改造设备切入；CoorsTek具备制造能力，日本厂商成本不占优 | D9: 二供进入节奏；第一大客户销售额口径
A10: 2026-06-11 | B10: 三环前业务拓展负责人 | C10: 隔膜片对三环整体营收、利润贡献不大；三环同时自研SOFC电堆，已出货 | D10: SOFC对利润贡献的交叉验证
A11: 2026-06-11 | B11: 三环前业务拓展负责人 | C11: 国内MLCC涨价集中在高容产品，低容不涨；AI服务器高端MLCC使用部分稀土材料 | D11: 电子元件分部增速与毛利率
A12: 2026-07-22 | B12: Bloom前国际业务高级管理人员 | C12: 65kW约用2,000片电池片（约32.5W/片），650kW约2万片；瓶颈在电池片烧结速度，Bloom已在找第二来源 | D12: 单片功率口径；二供
A13: 2026-07-22 | B13: Bloom前国际业务高级管理人员 | C13: SOFC在北美大型数据中心发电中约占10%，2030年前后或升至约20%；数据中心负载波动使反应器温度变化增多 | D13: Bloom需求上限；翻新需求
A14: 2026-07-28 | B14: Bloom二季度业绩公告 | C14: 二季度收入10.65亿美元，同比+166%；2026年收入指引上调至39-42亿美元（中值同比约翻倍） | D14: 2026E Bloom需求约为2025年两倍
A15: 2026-07-29 | B15: 首尔经济新闻 | C15: Amosense已向Bloom交付首批SOFC陶瓷基板，三季度内月产能由20万片扩至60万片 | D15: 二供产能（份额假设）
A16: 2026-08-28 | B16: 三环2026年半年报 | C16: 营收64.23亿元（+54.82%），归母净利19.32亿元（+56.18%）；增长来自MLCC与插芯、套筒等光通信产品；H股共发行80,221,200股 | D16: 2026E收入基数与股本

Sheet 校验
A1: 模型校验（全部应为0）
A2: 任何非零值表示勾稽关系出错。
A4: 校验项 | C4: 2021A | D4: 2022A | E4: 2023A | F4: 2024A | G4: 2025A | H4: 2026E | I4: 2027E | J4: 2028E | K4: 2029E | L4: 2030E
A5: 资产负债表配平（资产-负债-权益） | C5: =ROUND(三表预测!C64,2) -> 0 | D5: =ROUND(三表预测!D64,2) -> 0 | E5: =ROUND(三表预测!E64,2) -> 0 | F5: =ROUND(三表预测!F64,2) -> 0 | G5: =ROUND(三表预测!G64,2) -> 0 | H5: =ROUND(三表预测!H64,2) -> 0 | I5: =ROUND(三表预测!I64,2) -> 0 | J5: =ROUND(三表预测!J64,2) -> 0 | ... L5: =ROUND(三表预测!L64,2) -> 0
A6: 历史资产总计与报告值差异 | C6: =ROUND(三表预测!C65,2) -> 0 | D6: =ROUND(三表预测!D65,2) -> 0 | E6: =ROUND(三表预测!E65,2) -> 0 | F6: =ROUND(三表预测!F65,2) -> 0 | G6: =ROUND(三表预测!G65,2) -> 0
A7: 历史营业利润重算与报告值差异 | C7: =ROUND(三表预测!C39,2) -> 0 | D7: =ROUND(三表预测!D39,2) -> 0 | E7: =ROUND(三表预测!E39,2) -> 0 | F7: =ROUND(三表预测!F39,2) -> 0 | G7: =ROUND(三表预测!G39,2) -> 0
A8: 历史现金净增加额与报告值差异 | C8: =ROUND(三表预测!C84,2) -> 0 | D8: =ROUND(三表预测!D84,2) -> 0 | E8: =ROUND(三表预测!E84,2) -> 0 | F8: =ROUND(三表预测!F84,2) -> 0 | G8: =ROUND(三表预测!G84,2) -> 0
A9: 分部收入合计与利润表收入差异（预测） | H9: =ROUND(分部预测!H27-三表预测!H6,4) -> 0 | I9: =ROUND(分部预测!I27-三表预测!I6,4) -> 0 | J9: =ROUND(分部预测!J27-三表预测!J6,4) -> 0 | K9: =ROUND(分部预测!K27-三表预测!K6,4) -> 0 | L9: =ROUND(分部预测!L27-三表预测!L6,4) -> 0
A10: 分部收入合计与年报差异（2024A/2025A） | F10: =ROUND(分部预测!F27-三表预测!F6,1) -> 0 | G10: =ROUND(分部预测!G27-三表预测!G6,1) -> 0
A11: 现金流量表期末现金与资产负债表货币资金变动差异（预测） | H11: =ROUND((三表预测!H41-三表预测!G41)-三表预测!H82,4) -> 0 | I11: =ROUND((三表预测!I41-三表预测!H41)-三表预测!I82,4) -> 0 | J11: =ROUND((三表预测!J41-三表预测!I41)-三表预测!J82,4) -> 0 | K11: =ROUND((三表预测!K41-三表预测!J41)-三表预测!K82,4) -> 0 | L11: =ROUND((三表预测!L41-三表预测!K41)-三表预测!L82,4) -> 0
A13: 校验汇总（所有校验绝对值之和） | C13: =SUMPRODUCT(ABS(C5:L11)) -> 0
