Workbook

Sheet 封面与摘要
A1: 三环集团（300408.SZ / 06951.HK）详细财务与估值模型
A2: 编制日期：2026-09-30｜单位：百万元人民币（另注明除外）｜数据截至2026年半年报（2026-08-28）
A4: 使用说明
A5: 1. 在“假设”C5切换情景（1=基准，2=乐观，3=悲观）；蓝字为录入值/假设，黑字为本表公式，绿字为跨表链接，灰底为预测列，黄底为关键假设。
A6: 2. 模型链路：假设 → 收入拆解（量价、SOFC子模型）→ 成本拆解（分部毛利率、成本按性质）→ 人员与费用（人数×人均薪酬）→ 资本开支与折旧（在建工程、四类固定资产）→ 营运资金（分项周转天数）→ 融资与资金（利息、权益变动）→ 税务与其他损益（所得税桥）→ 三表预测 → 回报分析 → DCF/相对估值。
A7: 3. 利息收入按期初余额计息、利息费用按平均借款余额，模型无循环引用；货币资金由现金流量表倒挤，资产负债表自动配平。营业成本以分部毛利率为主驱动，生产人工与生产折旧偏离基准标定值的部分直接计入营业成本；DCF第二阶段与永续期按“再投资率=增速÷RONIC”计算FCFF。
A8: 4. “假设”第四节为敏感性冲击单元（默认0）；“敏感性分析”“情景对比”两表为重算引擎写入的静态结果，修改假设后需重跑才会更新；DCF表内的WACC×增长率表与反向DCF为实时公式。
A9: 5. 历史数据：三张报表来自Wind（公司公告值）；附注明细（固定资产变动、成本构成、员工、存货、税率调节等）取自年报/半年报原文，见“披露明细”。
A10: 6. “校验”表汇总应为0；A股股价、汇率、可比公司倍数请按最新行情更新。
A12: 核心输出（随情景自动更新）
A13: 指标 | C13: 2025A | D13: 2026E | E13: 2027E | F13: 2028E | G13: 2029E | H13: 2030E
A14: 营业收入 | C14: =三表预测!G6 -> 9007.1539 | D14: =三表预测!H6 -> 13863.187 | E14: =三表预测!I6 -> 17550.903 | F14: =三表预测!J6 -> 20155.217 | G14: =三表预测!K6 -> 22196.957 | H14: =三表预测!L6 -> 23693.89
A15: 同比 | C15: =三表预测!G7 -> 0.22131053 | D15: =三表预测!H7 -> 0.53913074 | E15: =三表预测!I7 -> 0.26600776 | F15: =三表预测!J7 -> 0.14838634 | G15: =三表预测!K7 -> 0.10130079 | H15: =三表预测!L7 -> 0.067438657
A16: 电子元件 | C16: =收入拆解!G17 -> 3308.0896 | D16: =收入拆解!H17 -> 5983.6724 | E16: =收入拆解!I17 -> 8077.9578 | F16: =收入拆解!J17 -> 9698.3961 | G16: =收入拆解!K17 -> 10862.204 | H16: =收入拆解!L17 -> 11709.456
A17: 通信器件 | C17: =收入拆解!G26 -> 2594.3099 | D17: =收入拆解!H26 -> 3955.5443 | E17: =收入拆解!I26 -> 4936.5193 | F17: =收入拆解!J26 -> 5686.8702 | G17: =收入拆解!K26 -> 6256.1259 | H17: =收入拆解!L26 -> 6735.9708
A18: 电子及陶瓷材料 | C18: =收入拆解!G41 -> 1959.378 | D18: =收入拆解!H41 -> 2525.459 | E18: =收入拆解!I41 -> 3018.5474 | F18: =收入拆解!J41 -> 3136.9255 | G18: =收入拆解!K41 -> 3338.3736 | H18: =收入拆解!L41 -> 3412.4894
A19: 其中SOFC隔膜片（2025A为第一大客户销售额代理） | C19: =收入拆解!G38 -> 330.718 | D19: =收入拆解!H38 -> 652.5 | E19: =收入拆解!I38 -> 920.83333 | F19: =收入拆解!J38 -> 829.44 | G19: =收入拆解!K38 -> 846.28923 | H19: =收入拆解!L38 -> 770.88
A20: 毛利率 | C20: =三表预测!G10 -> 0.4213753 | D20: =三表预测!H10 -> 0.44928717 | E20: =三表预测!I10 -> 0.45214207 | F20: =三表预测!J10 -> 0.44374172 | G20: =三表预测!K10 -> 0.43428588 | H20: =三表预测!L10 -> 0.42888197
A21: 期间费用率（销售+管理+研发） | C21: =人员与费用!G51 -> 0.13629013 | D21: =人员与费用!H51 -> 0.10788538 | E21: =人员与费用!I51 -> 0.10084219 | F21: =人员与费用!J51 -> 0.098670245 | G21: =人员与费用!K51 -> 0.098318583 | H21: =人员与费用!L51 -> 0.099206129
A22: 归母净利润 | C22: =三表预测!G26 -> 2618.3839 | D22: =三表预测!H26 -> 4260.3565 | E22: =三表预测!I26 -> 5632.1372 | F22: =三表预测!J26 -> 6237.7654 | G22: =三表预测!K26 -> 6667.0317 | H22: =三表预测!L26 -> 7002.6492
A23: 同比 | C23: =三表预测!G27 -> 0.1953639 | D23: =三表预测!H27 -> 0.62709392 | E23: =三表预测!I27 -> 0.3219873 | F23: =三表预测!J27 -> 0.10753079 | G23: =三表预测!K27 -> 0.068817316 | H23: =三表预测!L27 -> 0.050339864
A24: EPS（期末流通股本，元） | C24: =三表预测!G29 -> 1.3699036 | D24: =三表预测!H29 -> 2.1552782 | E24: =三表预测!I29 -> 2.8492505 | F24: =三表预测!J29 -> 3.1556326 | G24: =三表预测!K29 -> 3.3727948 | H24: =三表预测!L29 -> 3.5425808
A25: 实际税率 | C25: =税务与其他损益!G28 -> 0.13004434 | D25: =税务与其他损益!H28 -> 0.13252461 | E25: =税务与其他损益!I28 -> 0.13951906 | F25: =税务与其他损益!J28 -> 0.13905344 | G25: =税务与其他损益!K28 -> 0.13843215 | H25: =税务与其他损益!L28 -> 0.13780101
A26: ROE（杜邦，平均） | C26: =回报分析!G8 -> 0.12611169 | D26: =回报分析!H8 -> 0.16421577 | E26: =回报分析!I8 -> 0.17414502 | F26: =回报分析!J8 -> 0.17022453 | G26: =回报分析!K8 -> 0.16206424 | H26: =回报分析!L8 -> 0.15275034
A27: ROIC | C27: =回报分析!G11 -> 0.25480171 | D27: =回报分析!H11 -> 0.37290887 | E27: =回报分析!I11 -> 0.40110246 | F27: =回报分析!J11 -> 0.37370282 | G27: =回报分析!K11 -> 0.35914986 | H27: =回报分析!L11 -> 0.35367001
A28: 资本开支（历史=现金口径；预测=新增投入） | C28: =资本开支与折旧!G11 -> 580.092 | D28: =资本开支与折旧!H11 -> 1787.9753 | E28: =资本开支与折旧!I11 -> 2593.5925 | F28: =资本开支与折旧!J11 -> 2358.5137 | G28: =资本开支与折旧!K11 -> 1918.9354 | H28: =资本开支与折旧!L11 -> 1679.4592
A29: 折旧摊销 | C29: =资本开支与折旧!G91 -> 740.43309 | D29: =资本开支与折旧!H91 -> 813.65692 | E29: =资本开支与折旧!I91 -> 914.99495 | F29: =资本开支与折旧!J91 -> 1060.0309 | G29: =资本开支与折旧!K91 -> 1212.6478 | H29: =资本开支与折旧!L91 -> 1348.2187
A30: 营运资本/收入 | C30: =营运资金!G32 -> 0.36942359 | D30: =营运资金!H32 -> 0.33864913 | E30: =营运资金!I32 -> 0.3425847 | F30: =营运资金!J32 -> 0.34429006 | G30: =营运资金!K32 -> 0.34525345 | H30: =营运资金!L32 -> 0.34495758
A31: 自由现金流（经营现金流-资本开支） | C31: =三表预测!G93 -> 2297.5171 | D31: =三表预测!H93 -> 1878.0406 | E31: =三表预测!I93 -> 2579.2476 | F31: =三表预测!J93 -> 3956.3348 | G31: =三表预测!K93 -> 5180.0314 | H31: =三表预测!L93 -> 6105.2201
A32: 净现金（含一年以上定期存款） | C32: =融资与资金!G43 -> 12080.847 | D32: =融资与资金!H43 -> 18350.22 | E32: =融资与资金!I43 -> 19604.426 | F32: =融资与资金!J43 -> 21788 | G32: =融资与资金!K43 -> 25001.524 | H32: =融资与资金!L43 -> 29004.191
A33: 员工人数（期末） | C33: =人员与费用!G11 -> 17352 | D33: =人员与费用!H11 -> 19628.91 | E33: =人员与费用!I11 -> 21417.099 | F33: =人员与费用!J11 -> 22809.931 | G33: =人员与费用!K11 -> 23893.979 | H33: =人员与费用!L11 -> 24832.667
A34: PE（当前股价，流通股口径） | C34: =回报分析!G16 -> 86.502435 | D34: =回报分析!H16 -> 54.9813 | E34: =回报分析!I16 -> 41.589885 | F34: =回报分析!J16 -> 37.5519 | G34: =回报分析!K16 -> 35.134067 | H34: =回报分析!L16 -> 33.450189
A36: 估值摘要
A37: 当前情景（1基准/2乐观/3悲观） | C37: =假设!$C$5 -> 1
A38: A股股价（元） | C38: =假设!$C$6 -> 118.5
A39: WACC | C39: =DCF估值!$C$7 -> 0.089285
A40: 永续增长率 | C40: =DCF估值!$C$8 -> 0.03
A41: DCF每股价值（元，2026-12-31） | C41: =DCF估值!$C$41 -> 55.033813
A42: DCF每股价值折回当前（元） | C42: =DCF估值!$C$42 -> 53.854647
A43: 相对当前股价空间 | C43: =DCF估值!$C$44 -> -0.5455304
A44: DCF隐含2027E PE | C44: =DCF估值!$C$46 -> 19.510717
A45: 反向DCF：当前股价隐含永续增长率 | C45: =DCF估值!$C$52 -> 0.0735827
A46: 当前股价对应2027E PE | C46: =DCF估值!$C$55 -> 41.589885
A47: PE区间估值（2027E EPS × PE下限/上限，元） | C47: =TEXT(假设!$C$32*三表预测!I29,"0.0")&" - "&TEXT(假设!$C$33*三表预测!I29,"0.0") -> 85.5 - 156.7
A48: 模型校验汇总（应为0） | C48: =校验!C21 -> 0
A50: 工作表地图
A51: 假设 | C51: 情景三组值、敏感性冲击、逐年驱动（带历史参照）
A52: 收入拆解 | C52: 公司量价、电子元件与通信器件量价拆分、SOFC隔膜片子模型、收入增量与地区
A53: 成本拆解 | C53: 分部毛利率与营业成本；营业成本按原材料/人工/折旧/其他制造费用拆分
A54: 人员与费用 | C54: 五类员工人数、人均薪酬、职工薪酬按功能归集；销售/管理/研发费用按性质
A55: 资本开支与折旧 | C55: 维护与扩产资本开支、H股境外项目、在建工程滚动、四类固定资产原值/折旧/净值、无形资产、折旧分摊
A56: 营运资金 | C56: 应收票据/账款/融资、存货三分类与跌价准备、应付票据/账款及其他经营负债、周转天数与现金转换周期
A57: 融资与资金 | C57: 受限资金、理财、定期存款、利息收入与理财收益、借款与利息、所有者权益变动、分红回购、净现金
A58: 税务与其他损益 | C58: 税金及附加、其他收益三分项、减值、所得税桥（法定税率→税率差异→加计扣除→其他）
A59: 股本与每股 | C59: H股发行、回购、库存股、加权股本、分红
A60: 三表预测 | C60: 利润表、资产负债表、现金流量表（间接法）联动
A61: 回报分析 | C61: 杜邦ROE、NOPAT、ROIC与增量ROIC、现金转换、估值倍数
A62: DCF估值 | C62: 三阶段FCFF、反向DCF、两组实时敏感性表
... A65: 披露明细 | C65: 年报/半年报附注原表（固定资产、在建工程、员工、成本构成、存货、税率调节等）
A67: 免责声明：本模型基于公开信息与产业链调研整理，假设具有主观性，不构成任何投资建议。

Sheet 财务汇总
A1: 三环集团（300408.SZ / 06951.HK）财务模型汇总
A2: 单位：百万元人民币（另注明除外）｜年度：2023A-2025A为报告值，2026E-2030E为基准情景（随“假设”C5切换）｜季度：单季报告值｜全部为链接公式
C3: 年度 / Annual | L3: 季度（单季）/ Quarterly
A4: 项目 | C4: 2023A | D4: 2024A | E4: 2025A | F4: 2026E | G4: 2027E | H4: 2028E | I4: 2029E | J4: 2030E | L4: 2025Q1 | M4: 2025Q2 | N4: 2025Q3 | O4: 2025Q4 | P4: 2026Q1 | Q4: 2026Q2
A5: 一、利润表
A6: 营业收入 | C6: =三表预测!E6 -> 5726.6885 | D6: =三表预测!F6 -> 7374.9908 | E6: =三表预测!G6 -> 9007.1539 | F6: =三表预测!H6 -> 13863.187 | G6: =三表预测!I6 -> 17550.903 | H6: =三表预测!J6 -> 20155.217 | I6: =三表预测!K6 -> 22196.957 | J6: =三表预测!L6 -> 23693.89 | L6: =季度数据!G5 -> 1833.141 | M6: =季度数据!H5 -> 2315.6541 | N6: =季度数据!I5 -> 2359.5738 | O6: =季度数据!J5 -> 2498.785 | P6: =季度数据!K5 -> 2680.9934 | Q6: =季度数据!L5 -> 3742.3384
A7: 同比 | C7: =三表预测!E7 -> 0.11211074 | D7: =三表预测!F7 -> 0.28782818 | E7: =三表预测!G7 -> 0.22131053 | F7: =三表预测!H7 -> 0.53913074 | G7: =三表预测!I7 -> 0.26600776 | H7: =三表预测!J7 -> 0.14838634 | I7: =三表预测!K7 -> 0.10130079 | J7: =三表预测!L7 -> 0.067438657 | L7: =IFERROR(季度数据!G5/季度数据!C5-1,0) -> 0.17237341 | M7: =IFERROR(季度数据!H5/季度数据!D5-1,0) -> 0.24244341 | N7: =IFERROR(季度数据!I5/季度数据!E5-1,0) -> 0.20794779 | O7: =IFERROR(季度数据!J5/季度数据!F5-1,0) -> 0.2530193 | P7: =IFERROR(季度数据!K5/季度数据!G5-1,0) -> 0.46251347 | Q7: =IFERROR(季度数据!L5/季度数据!H5-1,0) -> 0.61610424
A8: 毛利 | C8: =三表预测!E9 -> 2281.1586 | D8: =三表预测!F9 -> 3170.1271 | E8: =三表预测!G9 -> 3795.3922 | F8: =三表预测!H9 -> 6228.5523 | G8: =三表预测!I9 -> 7935.5016 | H8: =三表预测!J9 -> 8943.7107 | I8: =三表预测!K9 -> 9639.8248 | J8: =三表预测!L9 -> 10161.882 | L8: =季度数据!G5-季度数据!G6 -> 751.8142 | M8: =季度数据!H5-季度数据!H6 -> 989.6012 | N8: =季度数据!I5-季度数据!I6 -> 1023.8903 | O8: =季度数据!J5-季度数据!J6 -> 1030.0866 | P8: =季度数据!K5-季度数据!K6 -> 1165.9354 | Q8: =季度数据!L5-季度数据!L6 -> 1680.8635
A9: 毛利率 | C9: =三表预测!E10 -> 0.39833817 | D9: =三表预测!F10 -> 0.42984828 | E9: =三表预测!G10 -> 0.4213753 | F9: =三表预测!H10 -> 0.44928717 | G9: =三表预测!I10 -> 0.45214207 | H9: =三表预测!J10 -> 0.44374172 | I9: =三表预测!K10 -> 0.43428588 | J9: =三表预测!L10 -> 0.42888197 | L9: =IFERROR(1-季度数据!G6/季度数据!G5,0) -> 0.4101235 | M9: =IFERROR(1-季度数据!H6/季度数据!H5,0) -> 0.42735277 | N9: =IFERROR(1-季度数据!I6/季度数据!I5,0) -> 0.43393019 | O9: =IFERROR(1-季度数据!J6/季度数据!J5,0) -> 0.41223499 | P9: =IFERROR(1-季度数据!K6/季度数据!K5,0) -> 0.43488932 | Q9: =IFERROR(1-季度数据!L6/季度数据!L5,0) -> 0.44914792
A10: 销售费用 | C10: =三表预测!E12 -> 74.3431 | D10: =三表预测!F12 -> 79.3918 | E10: =三表预测!G12 -> 93.1993 | F10: =三表预测!H12 -> 105.04434 | G10: =三表预测!I12 -> 124.93085 | H10: =三表预测!J12 -> 141.37808 | I10: =三表预测!K12 -> 155.37852 | J10: =三表预测!L12 -> 167.88891 | L10: =季度数据!G8 -> 21.2322 | M10: =季度数据!H8 -> 20.7534 | N10: =季度数据!I8 -> 24.9725 | O10: =季度数据!J8 -> 26.2412 | P10: =季度数据!K8 -> 22.2371 | Q10: =季度数据!L8 -> 22.5728
A11: 管理费用 | C11: =三表预测!E13 -> 429.4141 | D11: =三表预测!F13 -> 409.8445 | E11: =三表预测!G13 -> 480.9502 | F11: =三表预测!H13 -> 609.33009 | G11: =三表预测!I13 -> 700.42727 | H11: =三表预测!J13 -> 776.84113 | I11: =三表预测!K13 -> 848.03725 | J11: =三表预测!L13 -> 907.31969 | L11: =季度数据!G9 -> 93.9391 | M11: =季度数据!H9 -> 97.5199 | N11: =季度数据!I9 -> 108.3876 | O11: =季度数据!J9 -> 181.1035 | P11: =季度数据!K9 -> 123.0153 | Q11: =季度数据!L9 -> 131.9151
A12: 研发费用 | C12: =三表预测!E14 -> 545.8062 | D12: =三表预测!F14 -> 583.0724 | E12: =三表预测!G14 -> 653.4367 | F12: =三表预测!H14 -> 781.26077 | G12: =三表预测!I14 -> 944.5133 | H12: =三表预测!J14 -> 1070.501 | I12: =三表预测!K14 -> 1178.9575 | J12: =三表预测!L14 -> 1275.3705 | L12: =季度数据!G10 -> 145.6916 | M12: =季度数据!H10 -> 146.9448 | N12: =季度数据!I10 -> 148.3194 | O12: =季度数据!J10 -> 212.4809 | P12: =季度数据!K10 -> 155.8096 | Q12: =季度数据!L10 -> 184.4559
A13: 期间费用率 | C13: =IFERROR((三表预测!E12+三表预测!E13+三表预测!E14)/三表预测!E6,0) -> 0.1832758 | D13: =IFERROR((三表预测!F12+三表预测!F13+三表预测!F14)/三表预测!F6,0) -> 0.14539797 | E13: =IFERROR((三表预测!G12+三表预测!G13+三表预测!G14)/三表预测!G6,0) -> 0.13629013 | F13: =IFERROR((三表预测!H12+三表预测!H13+三表预测!H14)/三表预测!H6,0) -> 0.10788538 | G13: =IFERROR((三表预测!I12+三表预测!I13+三表预测!I14)/三表预测!I6,0) -> 0.10084219 | H13: =IFERROR((三表预测!J12+三表预测!J13+三表预测!J14)/三表预测!J6,0) -> 0.098670245 | I13: =IFERROR((三表预测!K12+三表预测!K13+三表预测!K14)/三表预测!K6,0) -> 0.098318583 | J13: =IFERROR((三表预测!L12+三表预测!L13+三表预测!L14)/三表预测!L6,0) -> 0.099206129 | L13: =IFERROR((季度数据!G8+季度数据!G9+季度数据!G10)/季度数据!G5,0) -> 0.14230378 | M13: =IFERROR((季度数据!H8+季度数据!H9+季度数据!H10)/季度数据!H5,0) -> 0.11453269 | N13: =IFERROR((季度数据!I8+季度数据!I9+季度数据!I10)/季度数据!I5,0) -> 0.11937728 | O13: =IFERROR((季度数据!J8+季度数据!J9+季度数据!J10)/季度数据!J5,0) -> 0.16801189 | P13: =IFERROR((季度数据!K8+季度数据!K9+季度数据!K10)/季度数据!K5,0) -> 0.11229494 | Q13: =IFERROR((季度数据!L8+季度数据!L9+季度数据!L10)/季度数据!L5,0) -> 0.090570056
A14: 财务费用（负数为净收益） | C14: =三表预测!E15 -> -161.5113 | D14: =三表预测!F15 -> -172.5019 | E14: =三表预测!G15 -> -127.772 | F14: =三表预测!H15 -> -194.51809 | G14: =三表预测!I15 -> -262.79018 | H14: =三表预测!J15 -> -268.93355 | I14: =三表预测!K15 -> -287.43841 | J14: =三表预测!L15 -> -338.85479 | L14: =季度数据!G11 -> -38.1213 | M14: =季度数据!H11 -> -25.072 | N14: =季度数据!I11 -> -38.7991 | O14: =季度数据!J11 -> -25.7796 | P14: =季度数据!K11 -> -28.973 | Q14: =季度数据!L11 -> -12.9393
A15: 其他收益 | C15: =三表预测!E16 -> 348.6995 | D15: =三表预测!F16 -> 305.0967 | E15: =三表预测!G16 -> 390.1677 | F15: =三表预测!H16 -> 286.29204 | G15: =三表预测!I16 -> 317.12502 | H15: =三表预测!J16 -> 260.62087 | I15: =三表预测!K16 -> 263.78783 | J15: =三表预测!L16 -> 264.77556 | L15: =季度数据!G12 -> 87.1963 | M15: =季度数据!H12 -> 90.7529 | N15: =季度数据!I12 -> 87.9912 | O15: =季度数据!J12 -> 124.2274 | P15: =季度数据!K12 -> 85.4097 | Q15: =季度数据!L12 -> 53.7199
A16: 营业利润 | C16: =三表预测!E20 -> 1777.6464 | D16: =三表预测!F20 -> 2522.7052 | E16: =三表预测!G20 -> 3008.4653 | F16: =三表预测!H20 -> 4914.0391 | G16: =三表预测!I20 -> 6545.3364 | H16: =三表预测!J20 -> 7245.2411 | I16: =三表预测!K20 -> 7738.255 | J16: =三表预测!L20 -> 8121.848 | L16: =季度数据!G13 -> 616.3601 | M16: =季度数据!H13 -> 810.5954 | N16: =季度数据!I13 -> 831.3498 | O16: =季度数据!J13 -> 750.1603 | P16: =季度数据!K13 -> 911.3291 | Q16: =季度数据!L13 -> 1315.4431
A17: 营业利润率 | C17: =IFERROR(三表预测!E20/三表预测!E6,0) -> 0.31041437 | D17: =IFERROR(三表预测!F20/三表预测!F6,0) -> 0.34206215 | E17: =IFERROR(三表预测!G20/三表预测!G6,0) -> 0.33400843 | F17: =IFERROR(三表预测!H20/三表预测!H6,0) -> 0.35446676 | G17: =IFERROR(三表预测!I20/三表预测!I6,0) -> 0.37293445 | H17: =IFERROR(三表预测!J20/三表预测!J6,0) -> 0.35947224 | I17: =IFERROR(三表预测!K20/三表预测!K6,0) -> 0.34861783 | J17: =IFERROR(三表预测!L20/三表预测!L6,0) -> 0.34278239 | L17: =IFERROR(季度数据!G13/季度数据!G5,0) -> 0.33623169 | M17: =IFERROR(季度数据!H13/季度数据!H5,0) -> 0.35005029 | N17: =IFERROR(季度数据!I13/季度数据!I5,0) -> 0.35233049 | O17: =IFERROR(季度数据!J13/季度数据!J5,0) -> 0.30021002 | P17: =IFERROR(季度数据!K13/季度数据!K5,0) -> 0.33992217 | Q17: =IFERROR(季度数据!L13/季度数据!L5,0) -> 0.35150298
A18: 利润总额 | C18: =三表预测!E22 -> 1782.8474 | D18: =三表预测!F22 -> 2518.9437 | E18: =三表预测!G22 -> 3008.1761 | F18: =三表预测!H22 -> 4911.2131 | G18: =三表预测!I22 -> 6545.3364 | H18: =三表预测!J22 -> 7245.2411 | I18: =三表预测!K22 -> 7738.255 | J18: =三表预测!L22 -> 8121.848 | L18: =季度数据!G14 -> 618.439 | M18: =季度数据!H14 -> 808.6791 | N18: =季度数据!I14 -> 834.7089 | O18: =季度数据!J14 -> 746.3495 | P18: =季度数据!K14 -> 907.7421 | Q18: =季度数据!L14 -> 1316.2041
A19: 实际税率 | C19: =税务与其他损益!E28 -> 0.11201013 | D19: =税务与其他损益!F28 -> 0.1304952 | E19: =税务与其他损益!G28 -> 0.13004434 | F19: =税务与其他损益!H28 -> 0.13252461 | G19: =税务与其他损益!I28 -> 0.13951906 | H19: =税务与其他损益!J28 -> 0.13905344 | I19: =税务与其他损益!K28 -> 0.13843215 | J19: =税务与其他损益!L28 -> 0.13780101 | L19: =IFERROR(季度数据!G15/季度数据!G14,0) -> 0.13832229 | M19: =IFERROR(季度数据!H15/季度数据!H14,0) -> 0.12921021 | N19: =IFERROR(季度数据!I15/季度数据!I14,0) -> 0.13640073 | O19: =IFERROR(季度数据!J15/季度数据!J14,0) -> 0.11697991 | P19: =IFERROR(季度数据!K15/季度数据!K14,0) -> 0.12882183 | Q19: =IFERROR(季度数据!L15/季度数据!L14,0) -> 0.13296828
A20: 归母净利润 | C20: =三表预测!E26 -> 1580.9858 | D20: =三表预测!F26 -> 2190.4492 | E20: =三表预测!G26 -> 2618.3839 | F20: =三表预测!H26 -> 4260.3565 | G20: =三表预测!I26 -> 5632.1372 | H20: =三表预测!J26 -> 6237.7654 | I20: =三表预测!K26 -> 6667.0317 | J20: =三表预测!L26 -> 7002.6492 | L20: =季度数据!G17 -> 532.6514 | M20: =季度数据!H17 -> 704.4865 | N20: =季度数据!I17 -> 721.3812 | O20: =季度数据!J17 -> 659.8652 | P20: =季度数据!K17 -> 790.8996 | Q20: =季度数据!L17 -> 1141.2187
A21: 同比 | C21: =三表预测!E27 -> 0.050694156 | D21: =三表预测!F27 -> 0.38549581 | E21: =三表预测!G27 -> 0.1953639 | F21: =三表预测!H27 -> 0.62709392 | G21: =三表预测!I27 -> 0.3219873 | H21: =三表预测!J27 -> 0.10753079 | I21: =三表预测!K27 -> 0.068817316 | J21: =三表预测!L27 -> 0.050339864 | L21: =IFERROR(季度数据!G17/季度数据!C17-1,0) -> 0.23020146 | M21: =IFERROR(季度数据!H17/季度数据!D17-1,0) -> 0.18887191 | N21: =IFERROR(季度数据!I17/季度数据!E17-1,0) -> 0.24862278 | O21: =IFERROR(季度数据!J17/季度数据!F17-1,0) -> 0.12382194 | P21: =IFERROR(季度数据!K17/季度数据!G17-1,0) -> 0.4848353 | Q21: =IFERROR(季度数据!L17/季度数据!H17-1,0) -> 0.61992984
A22: 归母净利率 | C22: =三表预测!E28 -> 0.2760733 | D22: =三表预测!F28 -> 0.29701043 | E22: =三表预测!G28 -> 0.29070047 | F22: =三表预测!H28 -> 0.30731436 | G22: =三表预测!I28 -> 0.32090299 | H22: =三表预测!J28 -> 0.30948639 | I22: =三表预测!K28 -> 0.30035792 | J22: =三表预测!L28 -> 0.29554663 | L22: =IFERROR(季度数据!G17/季度数据!G5,0) -> 0.29056761 | M22: =IFERROR(季度数据!H17/季度数据!H5,0) -> 0.30422786 | N22: =IFERROR(季度数据!I17/季度数据!I5,0) -> 0.30572521 | O22: =IFERROR(季度数据!J17/季度数据!J5,0) -> 0.26407442 | P22: =IFERROR(季度数据!K17/季度数据!K5,0) -> 0.29500244 | Q22: =IFERROR(季度数据!L17/季度数据!L5,0) -> 0.30494802
A23: EPS（元，期末流通股本） | C23: =三表预测!E29 -> 0.82493502 | D23: =三表预测!F29 -> 1.142944 | E23: =三表预测!G29 -> 1.3699036 | F23: =三表预测!H29 -> 2.1552782 | G23: =三表预测!I29 -> 2.8492505 | H23: =三表预测!J29 -> 3.1556326 | I23: =三表预测!K29 -> 3.3727948 | J23: =三表预测!L29 -> 3.5425808
A24: EBITDA | C24: =三表预测!E33 -> 2123.0677 | D24: =三表预测!F33 -> 2931.1984 | E24: =三表预测!G33 -> 3500.2428 | F24: =三表预测!H33 -> 5413.0418 | G24: =三表预测!I33 -> 7131.1635 | H24: =三表预测!J33 -> 7969.9608 | I24: =三表预测!K33 -> 8597.0867 | J24: =三表预测!L33 -> 9064.8342
A25: EBITDA利润率 | C25: =三表预测!E34 -> 0.37073218 | D25: =三表预测!F34 -> 0.39745113 | E25: =三表预测!G34 -> 0.38860697 | F25: =三表预测!H34 -> 0.39046156 | G25: =三表预测!I34 -> 0.4063132 | H25: =三表预测!J34 -> 0.39542917 | I25: =三表预测!K34 -> 0.38730925 | J25: =三表预测!L34 -> 0.3825811
A26: 二、业务经营
A27: 电子元件收入 | D27: =收入拆解!F17 -> 2298.159 | E27: =收入拆解!G17 -> 3308.0896 | F27: =收入拆解!H17 -> 5983.6724 | G27: =收入拆解!I17 -> 8077.9578 | H27: =收入拆解!J17 -> 9698.3961 | I27: =收入拆解!K17 -> 10862.204 | J27: =收入拆解!L17 -> 11709.456
A28: 通信器件收入 | D28: =收入拆解!F26 -> 2305.9847 | E28: =收入拆解!G26 -> 2594.3099 | F28: =收入拆解!H26 -> 3955.5443 | G28: =收入拆解!I26 -> 4936.5193 | H28: =收入拆解!J26 -> 5686.8702 | I28: =收入拆解!K26 -> 6256.1259 | J28: =收入拆解!L26 -> 6735.9708
A29: 电子及陶瓷材料收入 | D29: =收入拆解!F41 -> 1677.2328 | E29: =收入拆解!G41 -> 1959.378 | F29: =收入拆解!H41 -> 2525.459 | G29: =收入拆解!I41 -> 3018.5474 | H29: =收入拆解!J41 -> 3136.9255 | I29: =收入拆解!K41 -> 3338.3736 | J29: =收入拆解!L41 -> 3412.4894
A30: 其中SOFC隔膜片（历史为第一大客户代理） | C30: =收入拆解!E38 -> 449.31873 | D30: =收入拆解!F38 -> 323.86965 | E30: =收入拆解!G38 -> 330.718 | F30: =收入拆解!H38 -> 652.5 | G30: =收入拆解!I38 -> 920.83333 | H30: =收入拆解!J38 -> 829.44 | I30: =收入拆解!K38 -> 846.28923 | J30: =收入拆解!L38 -> 770.88
A31: 设备组件收入 | D31: =收入拆解!F43 -> 536.82473 | E31: =收入拆解!G43 -> 601.75341 | F31: =收入拆解!H43 -> 692.01642 | G31: =收入拆解!I43 -> 775.05839 | H31: =收入拆解!J43 -> 852.56423 | I31: =收入拆解!K43 -> 920.76937 | J31: =收入拆解!L43 -> 976.01553
A32: 其他主营及其他业务收入 | D32: =收入拆解!F44+收入拆解!F45 -> 556.78962 | E32: =收入拆解!G44+收入拆解!G45 -> 543.62299 | F32: =收入拆解!H44+收入拆解!H45 -> 706.49528 | G32: =收入拆解!I44+收入拆解!I45 -> 742.82005 | H32: =收入拆解!J44+收入拆解!J45 -> 780.46105 | I32: =收入拆解!K44+收入拆解!K45 -> 819.4841 | J32: =收入拆解!L44+收入拆解!L45 -> 859.95831
A33: 电子、通信元件及材料（半年报口径） | D33: =收入拆解!F17+收入拆解!F26+收入拆解!F41+收入拆解!F43 -> 6818.2012 | E33: =收入拆解!G17+收入拆解!G26+收入拆解!G41+收入拆解!G43 -> 8463.5309 | F33: =收入拆解!H17+收入拆解!H26+收入拆解!H41+收入拆解!H43 -> 13156.692 | G33: =收入拆解!I17+收入拆解!I26+收入拆解!I41+收入拆解!I43 -> 16808.083 | H33: =收入拆解!J17+收入拆解!J26+收入拆解!J41+收入拆解!J43 -> 19374.756 | I33: =收入拆解!K17+收入拆解!K26+收入拆解!K41+收入拆解!K43 -> 21377.473 | J33: =收入拆解!L17+收入拆解!L26+收入拆解!L41+收入拆解!L43 -> 22833.931
A34: 销售量（亿只/片，公司口径） | C34: =收入拆解!E6 -> 2872.5609 | D34: =收入拆解!F6 -> 3816.1069 | E34: =收入拆解!G6 -> 5329.9092
A35: 员工人数（期末） | C35: =人员与费用!E11 -> 13501 | D35: =人员与费用!F11 -> 15515 | E35: =人员与费用!G11 -> 17352 | F35: =人员与费用!H11 -> 19628.91 | G35: =人员与费用!I11 -> 21417.099 | H35: =人员与费用!J11 -> 22809.931 | I35: =人员与费用!K11 -> 23893.979 | J35: =人员与费用!L11 -> 24832.667
A36: 人均薪酬（万元） | D36: =人员与费用!F22 -> 12.928528 | E36: =人员与费用!G22 -> 12.79326 | F36: =人员与费用!H22 -> 13.432923 | G36: =人员与费用!I22 -> 14.104569 | H36: =人员与费用!J22 -> 14.739274 | I36: =人员与费用!K22 -> 15.328845 | J36: =人员与费用!L22 -> 15.941999
A37: 资本开支 | C37: =资本开支与折旧!E11 -> 545.8847 | D37: =资本开支与折旧!F11 -> 639.0352 | E37: =资本开支与折旧!G11 -> 580.092 | F37: =资本开支与折旧!H11 -> 1787.9753 | G37: =资本开支与折旧!I11 -> 2593.5925 | H37: =资本开支与折旧!J11 -> 2358.5137 | I37: =资本开支与折旧!K11 -> 1918.9354 | J37: =资本开支与折旧!L11 -> 1679.4592 | L37: =季度数据!G19 -> 98.8266 | M37: =季度数据!H19 -> 108.3401 | N37: =季度数据!I19 -> 166.7533 | O37: =季度数据!J19 -> 206.172 | P37: =季度数据!K19 -> 188.4361 | Q37: =季度数据!L19 -> 287.9349
A38: 折旧与摊销 | C38: =资本开支与折旧!E91 -> 609.43241 | D38: =资本开支与折旧!F91 -> 651.2802 | E38: =资本开支与折旧!G91 -> 740.43309 | F38: =资本开支与折旧!H91 -> 813.65692 | G38: =资本开支与折旧!I91 -> 914.99495 | H38: =资本开支与折旧!J91 -> 1060.0309 | I38: =资本开支与折旧!K91 -> 1212.6478 | J38: =资本开支与折旧!L91 -> 1348.2187
A39: 应收周转天数（票据+账款+融资） | C39: =营运资金!E33 -> 143.99838 | D39: =营运资金!F33 -> 132.95096 | E39: =营运资金!G33 -> 132.10293 | F39: =营运资金!H33 -> 128 | G39: =营运资金!I33 -> 128 | H39: =营运资金!J33 -> 128 | I39: =营运资金!K33 -> 128 | J39: =营运资金!L33 -> 128
A40: 存货周转天数 | C40: =营运资金!E34 -> 185.76626 | D40: =营运资金!F34 -> 189.29501 | E40: =营运资金!G34 -> 167.50165 | F40: =营运资金!H34 -> 156.10015 | G40: =营运资金!I34 -> 157.07956 | H40: =营运资金!J34 -> 157.38008 | I40: =营运资金!K34 -> 157.47553 | J40: =营运资金!L34 -> 157.33805
A41: 应付周转天数（票据+账款） | C41: =营运资金!E35 -> 103.88977 | D41: =营运资金!F35 -> 112.43787 | E41: =营运资金!G35 -> 135.02432 | F41: =营运资金!H35 -> 135 | G41: =营运资金!I35 -> 135 | H41: =营运资金!J35 -> 135 | I41: =营运资金!K35 -> 135 | J41: =营运资金!L35 -> 135
A42: 现金转换周期 | C42: =营运资金!E36 -> 225.87487 | D42: =营运资金!F36 -> 209.8081 | E42: =营运资金!G36 -> 164.58025 | F42: =营运资金!H36 -> 149.10015 | G42: =营运资金!I36 -> 150.07956 | H42: =营运资金!J36 -> 150.38008 | I42: =营运资金!K36 -> 150.47553 | J42: =营运资金!L36 -> 150.33805
A43: 三、资产负债表（季度列仅半年末与年末）
A44: 货币资金 | C44: =三表预测!E37 -> 2841.6149 | D44: =三表预测!F37 -> 3062.8452 | E44: =三表预测!G37 -> 3057.7786 | F44: =三表预测!H37 -> 9327.1517 | G44: =三表预测!I37 -> 10581.358 | H44: =三表预测!J37 -> 12764.932 | I44: =三表预测!K37 -> 15978.456 | J44: =三表预测!L37 -> 19981.123 | M44: =N(历史资产负债表!J5) -> 5430.1287 | O44: =三表预测!G37 -> 3057.7786 | Q44: =N(历史资产负债表!K5) -> 3825.5415
A45: 交易性金融资产（理财） | C45: =三表预测!E38 -> 3846.7081 | D45: =三表预测!F38 -> 5053.3869 | E45: =三表预测!G38 -> 3758.5116 | F45: =三表预测!H38 -> 3758.5116 | G45: =三表预测!I38 -> 3758.5116 | H45: =三表预测!J38 -> 3758.5116 | I45: =三表预测!K38 -> 3758.5116 | J45: =三表预测!L38 -> 3758.5116 | M45: =N(历史资产负债表!J6) -> 2865.6921 | O45: =三表预测!G38 -> 3758.5116 | Q45: =N(历史资产负债表!K6) -> 3256.5671
A46: 一年以上定期存款及大额存单 | C46: =融资与资金!E10 -> 3590.7033 | D46: =融资与资金!F10 -> 2930.2505 | E46: =融资与资金!G10 -> 5850.9937 | F46: =融资与资金!H10 -> 5850.9937 | G46: =融资与资金!I10 -> 5850.9937 | H46: =融资与资金!J10 -> 5850.9937 | I46: =融资与资金!K10 -> 5850.9937 | J46: =融资与资金!L10 -> 5850.9937 | M46: 2925.9402 | O46: =融资与资金!G10 -> 5850.9937 | Q46: 5693.1376
A47: 应收票据、账款及应收款项融资 | C47: =三表预测!E39+三表预测!E40+三表预测!E41 -> 2259.2709 | D47: =三表预测!F39+三表预测!F40+三表预测!F41 -> 2686.3346 | E47: =三表预测!G39+三表预测!G40+三表预测!G41 -> 3259.9217 | F47: =三表预测!H39+三表预测!H40+三表预测!H41 -> 4861.6109 | G47: =三表预测!I39+三表预测!I40+三表预测!I41 -> 6154.8372 | H47: =三表预测!J39+三表预测!J40+三表预测!J41 -> 7068.1309 | I47: =三表预测!K39+三表预测!K40+三表预测!K41 -> 7784.1382 | J47: =三表预测!L39+三表预测!L40+三表预测!L41 -> 8309.09 | M47: =N(历史资产负债表!J8)+N(历史资产负债表!J9)+N(历史资产负债表!J10) -> 2804.7162 | O47: =三表预测!G39+三表预测!G40+三表预测!G41 -> 3259.9217 | Q47: =N(历史资产负债表!K8)+N(历史资产负债表!K9)+N(历史资产负债表!K10) -> 4187.8129
A48: 存货 | C48: =三表预测!E44 -> 1753.5978 | D48: =三表预测!F44 -> 2180.7115 | E48: =三表预测!G44 -> 2391.7224 | F48: =三表预测!H44 -> 3265.117 | G48: =三表预测!I44 -> 4138.0358 | H48: =三表预测!J44 -> 4834.1584 | I48: =三表预测!K44 -> 5417.6464 | J48: =三表预测!L44 -> 5833.1498 | M48: =N(历史资产负债表!J16) -> 2163.2406 | O48: =三表预测!G44 -> 2391.7224 | Q48: =N(历史资产负债表!K16) -> 2811.0479
A49: 固定资产及在建工程 | C49: =三表预测!E47 -> 5783.8854 | D49: =三表预测!F47 -> 6327.452 | E49: =三表预测!G47 -> 6589.7152 | F49: =三表预测!H47 -> 7506.5027 | G49: =三表预测!I47 -> 9145.1311 | H49: =三表预测!J47 -> 10404.481 | I49: =三表预测!K47 -> 11071.028 | J49: =三表预测!L47 -> 11357.132 | M49: =N(历史资产负债表!J22)+N(历史资产负债表!J25) -> 6272.5564 | O49: =三表预测!G47 -> 6589.7152 | Q49: =N(历史资产负债表!K22)+N(历史资产负债表!K25) -> 6937.0576
A50: 资产总计 | C50: =三表预测!E54 -> 21826.965 | D50: =三表预测!F54 -> 23915.803 | E50: =三表预测!G54 -> 26506.088 | F50: =三表预测!H54 -> 36274.471 | G50: =三表预测!I54 -> 41535.498 | H50: =三表预测!J54 -> 46732.423 | I50: =三表预测!K54 -> 52023.435 | J50: =三表预测!L54 -> 57335.078 | M50: =N(历史资产负债表!J34) -> 24097.872 | O50: =三表预测!G54 -> 26506.088 | Q50: =N(历史资产负债表!K34) -> 28438.081
A51: 有息负债 | C51: =融资与资金!E23 -> 745.2792 | D51: =融资与资金!F23 -> 479.3472 | E51: =融资与资金!G23 -> 567.6374 | F51: =融资与资金!H23 -> 567.6374 | G51: =融资与资金!I23 -> 567.6374 | H51: =融资与资金!J23 -> 567.6374 | I51: =融资与资金!K23 -> 567.6374 | J51: =融资与资金!L23 -> 567.6374 | M51: =N(历史资产负债表!J35)+N(历史资产负债表!J49)+N(历史资产负债表!J46) -> 477.1853 | O51: =融资与资金!G23 -> 567.6374 | Q51: =N(历史资产负债表!K35)+N(历史资产负债表!K49)+N(历史资产负债表!K46) -> 769.5973
A52: 负债合计 | C52: =三表预测!E66 -> 3587.8643 | D52: =三表预测!F66 -> 4044.0346 | E52: =三表预测!G66 -> 4843.0454 | F52: =三表预测!H66 -> 6041.6477 | G52: =三表预测!I66 -> 7076.4546 | H52: =三表预测!J66 -> 7894.2198 | I52: =三表预测!K66 -> 8576.6631 | J52: =三表预测!L66 -> 9085.7766 | M52: =N(历史资产负债表!J59) -> 3810.4021 | O52: =三表预测!G66 -> 4843.0454 | Q52: =N(历史资产负债表!K59) -> 5789.5051
A53: 归母所有者权益 | C53: =三表预测!E67 -> 18233.198 | D53: =三表预测!F67 -> 19866.081 | E53: =三表预测!G67 -> 21658.759 | F53: =三表预测!H67 -> 30228.541 | G53: =三表预测!I67 -> 34454.76 | H53: =三表预测!J67 -> 38833.92 | I53: =三表预测!K67 -> 43442.489 | J53: =三表预测!L67 -> 48245.018 | M53: =N(历史资产负债表!J66) -> 20281.836 | O53: =三表预测!G67 -> 21658.759 | Q53: =N(历史资产负债表!K66) -> 22644.415
A54: 净现金（含一年以上定期存款） | C54: =融资与资金!E43 -> 9507.1736 | D54: =融资与资金!F43 -> 10544.889 | E54: =融资与资金!G43 -> 12080.847 | F54: =融资与资金!H43 -> 18350.22 | G54: =融资与资金!I43 -> 19604.426 | H54: =融资与资金!J43 -> 21788 | I54: =融资与资金!K43 -> 25001.524 | J54: =融资与资金!L43 -> 29004.191 | M54: =M44+M45+M46-M51-N(N(历史资产负债表!J50)) -> 10723.916 | O54: =融资与资金!G43 -> 12080.847 | Q54: =Q44+Q45+Q46-Q51-N(N(历史资产负债表!K50)) -> 11984.412
A55: 资产负债率 | C55: =IFERROR(C52/C50,0) -> 0.16437761 | D55: =IFERROR(D52/D50,0) -> 0.16909466 | E55: =IFERROR(E52/E50,0) -> 0.18271446 | F55: =IFERROR(F52/F50,0) -> 0.16655371 | G55: =IFERROR(G52/G50,0) -> 0.17037125 | H55: =IFERROR(H52/H50,0) -> 0.16892383 | I55: =IFERROR(I52/I50,0) -> 0.16486153 | J55: =IFERROR(J52/J50,0) -> 0.15846803 | M55: =IFERROR(M52/M50,0) -> 0.15812193 | O55: =IFERROR(O52/O50,0) -> 0.18271446 | Q55: =IFERROR(Q52/Q50,0) -> 0.20358283
A56: 四、现金流量
A57: 经营活动现金流量净额 | C57: =三表预测!E79 -> 1718.968 | D57: =三表预测!F79 -> 2403.1223 | E57: =三表预测!G79 -> 2877.6091 | F57: =三表预测!H79 -> 3666.0159 | G57: =三表预测!I79 -> 5172.8401 | H57: =三表预测!J79 -> 6314.8486 | I57: =三表预测!K79 -> 7098.9668 | J57: =三表预测!L79 -> 7784.6793 | L57: =季度数据!G18 -> 242.589 | M57: =季度数据!H18 -> 885.1204 | N57: =季度数据!I18 -> 862.7469 | O57: =季度数据!J18 -> 887.1527 | P57: =季度数据!K18 -> 156.6853 | Q57: =季度数据!L18 -> 1140.6343
A58: 资本开支（流出为负） | C58: =三表预测!E80 -> -545.8847 | D58: =三表预测!F80 -> -639.0352 | E58: =三表预测!G80 -> -580.092 | F58: =三表预测!H80 -> -1787.9753 | G58: =三表预测!I80 -> -2593.5925 | H58: =三表预测!J80 -> -2358.5137 | I58: =三表预测!K80 -> -1918.9354 | J58: =三表预测!L80 -> -1679.4592 | L58: =-季度数据!G19 -> -98.8266 | M58: =-季度数据!H19 -> -108.3401 | N58: =-季度数据!I19 -> -166.7533 | O58: =-季度数据!J19 -> -206.172 | P58: =-季度数据!K19 -> -188.4361 | Q58: =-季度数据!L19 -> -287.9349
A59: 自由现金流（经营现金流-资本开支） | C59: =C57+C58 -> 1173.0833 | D59: =D57+D58 -> 1764.0871 | E59: =E57+E58 -> 2297.5171 | F59: =F57+F58 -> 1878.0406 | G59: =G57+G58 -> 2579.2476 | H59: =H57+H58 -> 3956.3348 | I59: =I57+I58 -> 5180.0314 | J59: =J57+J58 -> 6105.2201 | L59: =L57+L58 -> 143.7624 | M59: =M57+M58 -> 776.7803 | N59: =N57+N58 -> 695.9936 | O59: =O57+O58 -> 680.9807 | P59: =P57+P58 -> -31.7508 | Q59: =Q57+Q58 -> 852.6994
A60: 现金分红（历史含利息支付） | C60: =-三表预测!E85 -> 489.9347 | D60: =-三表预测!F85 -> 553.6596 | E60: =-三表预测!G85 -> 726.6256 | F60: =-三表预测!H85 -> 860.11 | G60: =-三表预测!I85 -> 1405.9177 | H60: =-三表预测!J85 -> 1858.6053 | I60: =-三表预测!K85 -> 2058.4626 | J60: =-三表预测!L85 -> 2200.1205 | L60: =季度数据!G20 -> 0 | M60: =季度数据!H20 -> 726.3767 | N60: =季度数据!I20 -> 0.1353 | O60: =季度数据!J20 -> 0.1137 | P60: =季度数据!K20 -> 0.1622 | Q60: =季度数据!L20 -> 860.8047
A61: 股份回购 | C61: =-三表预测!E86 -> 0 | D61: =-三表预测!F86 -> 0 | E61: =-三表预测!G86 -> 175.44073 | F61: =-三表预测!H86 -> 1644.66 | G61: =-三表预测!I86 -> 0 | H61: =-三表预测!J86 -> 0 | I61: =-三表预测!K86 -> 0 | J61: =-三表预测!L86 -> 0
A62: 五、关键指标
A63: ROE（平均权益） | C63: =回报分析!E8 -> 0.089490933 | D63: =回报分析!F8 -> 0.11498639 | E63: =回报分析!G8 -> 0.12611169 | F63: =回报分析!H8 -> 0.16421577 | G63: =回报分析!I8 -> 0.17414502 | H63: =回报分析!J8 -> 0.17022453 | I63: =回报分析!K8 -> 0.16206424 | J63: =回报分析!L8 -> 0.15275034
A64: ROIC | C64: =回报分析!E11 -> 0.15708236 | D64: =回报分析!F11 -> 0.22141341 | E64: =回报分析!G11 -> 0.25480171 | F64: =回报分析!H11 -> 0.37290887 | G64: =回报分析!I11 -> 0.40110246 | H64: =回报分析!J11 -> 0.37370282 | I64: =回报分析!K11 -> 0.35914986 | J64: =回报分析!L11 -> 0.35367001
A65: 每股净资产（元） | C65: =IFERROR(三表预测!E67/股本与每股!E12,0) -> 9.513813 | D65: =IFERROR(三表预测!F67/股本与每股!F12,0) -> 10.365827 | E65: =IFERROR(三表预测!G67/股本与每股!G12,0) -> 11.331575 | F65: =IFERROR(三表预测!H67/股本与每股!H12,0) -> 15.292362 | G65: =IFERROR(三表预测!I67/股本与每股!I12,0) -> 17.430371 | H65: =IFERROR(三表预测!J67/股本与每股!J12,0) -> 19.645751 | I65: =IFERROR(三表预测!K67/股本与每股!K12,0) -> 21.977187 | J65: =IFERROR(三表预测!L67/股本与每股!L12,0) -> 24.406746
A66: 每股股利（元，当年派发） | E66: =股本与每股!G15 -> 0.38 | F66: =股本与每股!H15 -> 0.44999811 | G66: =股本与每股!I15 -> 0.71124182 | H66: =股本与每股!J15 -> 0.94025266 | I66: =股本与每股!K15 -> 1.0413588 | J66: =股本与每股!L15 -> 1.1130223
A67: PE（当前股价） | C67: =回报分析!E16 -> 143.64768 | D67: =回报分析!F16 -> 103.67962 | E67: =回报分析!G16 -> 86.502435 | F67: =回报分析!H16 -> 54.9813 | G67: =回报分析!I16 -> 41.589885 | H67: =回报分析!J16 -> 37.5519 | I67: =回报分析!K16 -> 35.134067 | J67: =回报分析!L16 -> 33.450189
A68: PB（当前股价） | C68: =回报分析!E17 -> 12.455574 | D68: =回报分析!F17 -> 11.431794 | E68: =回报分析!G17 -> 10.457505 | F68: =回报分析!H17 -> 7.7489662 | G68: =回报分析!I17 -> 6.7984783 | H68: =回报分析!J17 -> 6.0318386 | I68: =回报分析!K17 -> 5.3919548 | J68: =回报分析!L17 -> 4.8552151
A69: EV/EBITDA（当前股价） | F69: =回报分析!H18 -> 39.883254 | G69: =回报分析!I18 -> 30.274123 | H69: =回报分析!J18 -> 27.087928 | I69: =回报分析!K18 -> 25.111963 | J69: =回报分析!L18 -> 23.81618
A71: 注：季度资产负债表仅在半年末（2025Q2、2026Q2）与年末（2025Q4=2025A）可得；季度“资本开支”为购建长期资产支付的现金。
A72: “电子、通信元件及材料”为2026年半年报口径（电子元件+通信器件+电子及陶瓷材料+设备组件），2026H1为6,080.7（同比+55.0%）；季度分部收入未披露。

Sheet Summary_EN
A1: Sanhuan Group (CCTC, 300408.SZ / 06951.HK) - Financial model summary
A2: RMB mn unless stated | Annual: 2023A-2025A reported, 2026E-2030E model (scenario per 假设!C5) | Quarterly: single-quarter reported | All cells are live links
C3: Annual | L3: Quarterly (single quarter)
A4: Item | C4: 2023A | D4: 2024A | E4: 2025A | F4: 2026E | G4: 2027E | H4: 2028E | I4: 2029E | J4: 2030E | L4: 2025Q1 | M4: 2025Q2 | N4: 2025Q3 | O4: 2025Q4 | P4: 2026Q1 | Q4: 2026Q2
A5: I. Income statement
A6: Revenue | C6: =三表预测!E6 -> 5726.6885 | D6: =三表预测!F6 -> 7374.9908 | E6: =三表预测!G6 -> 9007.1539 | F6: =三表预测!H6 -> 13863.187 | G6: =三表预测!I6 -> 17550.903 | H6: =三表预测!J6 -> 20155.217 | I6: =三表预测!K6 -> 22196.957 | J6: =三表预测!L6 -> 23693.89 | L6: =季度数据!G5 -> 1833.141 | M6: =季度数据!H5 -> 2315.6541 | N6: =季度数据!I5 -> 2359.5738 | O6: =季度数据!J5 -> 2498.785 | P6: =季度数据!K5 -> 2680.9934 | Q6: =季度数据!L5 -> 3742.3384
A7: YoY | C7: =三表预测!E7 -> 0.11211074 | D7: =三表预测!F7 -> 0.28782818 | E7: =三表预测!G7 -> 0.22131053 | F7: =三表预测!H7 -> 0.53913074 | G7: =三表预测!I7 -> 0.26600776 | H7: =三表预测!J7 -> 0.14838634 | I7: =三表预测!K7 -> 0.10130079 | J7: =三表预测!L7 -> 0.067438657 | L7: =IFERROR(季度数据!G5/季度数据!C5-1,0) -> 0.17237341 | M7: =IFERROR(季度数据!H5/季度数据!D5-1,0) -> 0.24244341 | N7: =IFERROR(季度数据!I5/季度数据!E5-1,0) -> 0.20794779 | O7: =IFERROR(季度数据!J5/季度数据!F5-1,0) -> 0.2530193 | P7: =IFERROR(季度数据!K5/季度数据!G5-1,0) -> 0.46251347 | Q7: =IFERROR(季度数据!L5/季度数据!H5-1,0) -> 0.61610424
A8: Gross profit | C8: =三表预测!E9 -> 2281.1586 | D8: =三表预测!F9 -> 3170.1271 | E8: =三表预测!G9 -> 3795.3922 | F8: =三表预测!H9 -> 6228.5523 | G8: =三表预测!I9 -> 7935.5016 | H8: =三表预测!J9 -> 8943.7107 | I8: =三表预测!K9 -> 9639.8248 | J8: =三表预测!L9 -> 10161.882 | L8: =季度数据!G5-季度数据!G6 -> 751.8142 | M8: =季度数据!H5-季度数据!H6 -> 989.6012 | N8: =季度数据!I5-季度数据!I6 -> 1023.8903 | O8: =季度数据!J5-季度数据!J6 -> 1030.0866 | P8: =季度数据!K5-季度数据!K6 -> 1165.9354 | Q8: =季度数据!L5-季度数据!L6 -> 1680.8635
A9: Gross margin | C9: =三表预测!E10 -> 0.39833817 | D9: =三表预测!F10 -> 0.42984828 | E9: =三表预测!G10 -> 0.4213753 | F9: =三表预测!H10 -> 0.44928717 | G9: =三表预测!I10 -> 0.45214207 | H9: =三表预测!J10 -> 0.44374172 | I9: =三表预测!K10 -> 0.43428588 | J9: =三表预测!L10 -> 0.42888197 | L9: =IFERROR(1-季度数据!G6/季度数据!G5,0) -> 0.4101235 | M9: =IFERROR(1-季度数据!H6/季度数据!H5,0) -> 0.42735277 | N9: =IFERROR(1-季度数据!I6/季度数据!I5,0) -> 0.43393019 | O9: =IFERROR(1-季度数据!J6/季度数据!J5,0) -> 0.41223499 | P9: =IFERROR(1-季度数据!K6/季度数据!K5,0) -> 0.43488932 | Q9: =IFERROR(1-季度数据!L6/季度数据!L5,0) -> 0.44914792
A10: Selling expenses | C10: =三表预测!E12 -> 74.3431 | D10: =三表预测!F12 -> 79.3918 | E10: =三表预测!G12 -> 93.1993 | F10: =三表预测!H12 -> 105.04434 | G10: =三表预测!I12 -> 124.93085 | H10: =三表预测!J12 -> 141.37808 | I10: =三表预测!K12 -> 155.37852 | J10: =三表预测!L12 -> 167.88891 | L10: =季度数据!G8 -> 21.2322 | M10: =季度数据!H8 -> 20.7534 | N10: =季度数据!I8 -> 24.9725 | O10: =季度数据!J8 -> 26.2412 | P10: =季度数据!K8 -> 22.2371 | Q10: =季度数据!L8 -> 22.5728
A11: G&A expenses | C11: =三表预测!E13 -> 429.4141 | D11: =三表预测!F13 -> 409.8445 | E11: =三表预测!G13 -> 480.9502 | F11: =三表预测!H13 -> 609.33009 | G11: =三表预测!I13 -> 700.42727 | H11: =三表预测!J13 -> 776.84113 | I11: =三表预测!K13 -> 848.03725 | J11: =三表预测!L13 -> 907.31969 | L11: =季度数据!G9 -> 93.9391 | M11: =季度数据!H9 -> 97.5199 | N11: =季度数据!I9 -> 108.3876 | O11: =季度数据!J9 -> 181.1035 | P11: =季度数据!K9 -> 123.0153 | Q11: =季度数据!L9 -> 131.9151
A12: R&D expenses | C12: =三表预测!E14 -> 545.8062 | D12: =三表预测!F14 -> 583.0724 | E12: =三表预测!G14 -> 653.4367 | F12: =三表预测!H14 -> 781.26077 | G12: =三表预测!I14 -> 944.5133 | H12: =三表预测!J14 -> 1070.501 | I12: =三表预测!K14 -> 1178.9575 | J12: =三表预测!L14 -> 1275.3705 | L12: =季度数据!G10 -> 145.6916 | M12: =季度数据!H10 -> 146.9448 | N12: =季度数据!I10 -> 148.3194 | O12: =季度数据!J10 -> 212.4809 | P12: =季度数据!K10 -> 155.8096 | Q12: =季度数据!L10 -> 184.4559
A13: Opex / revenue | C13: =IFERROR((三表预测!E12+三表预测!E13+三表预测!E14)/三表预测!E6,0) -> 0.1832758 | D13: =IFERROR((三表预测!F12+三表预测!F13+三表预测!F14)/三表预测!F6,0) -> 0.14539797 | E13: =IFERROR((三表预测!G12+三表预测!G13+三表预测!G14)/三表预测!G6,0) -> 0.13629013 | F13: =IFERROR((三表预测!H12+三表预测!H13+三表预测!H14)/三表预测!H6,0) -> 0.10788538 | G13: =IFERROR((三表预测!I12+三表预测!I13+三表预测!I14)/三表预测!I6,0) -> 0.10084219 | H13: =IFERROR((三表预测!J12+三表预测!J13+三表预测!J14)/三表预测!J6,0) -> 0.098670245 | I13: =IFERROR((三表预测!K12+三表预测!K13+三表预测!K14)/三表预测!K6,0) -> 0.098318583 | J13: =IFERROR((三表预测!L12+三表预测!L13+三表预测!L14)/三表预测!L6,0) -> 0.099206129 | L13: =IFERROR((季度数据!G8+季度数据!G9+季度数据!G10)/季度数据!G5,0) -> 0.14230378 | M13: =IFERROR((季度数据!H8+季度数据!H9+季度数据!H10)/季度数据!H5,0) -> 0.11453269 | N13: =IFERROR((季度数据!I8+季度数据!I9+季度数据!I10)/季度数据!I5,0) -> 0.11937728 | O13: =IFERROR((季度数据!J8+季度数据!J9+季度数据!J10)/季度数据!J5,0) -> 0.16801189 | P13: =IFERROR((季度数据!K8+季度数据!K9+季度数据!K10)/季度数据!K5,0) -> 0.11229494 | Q13: =IFERROR((季度数据!L8+季度数据!L9+季度数据!L10)/季度数据!L5,0) -> 0.090570056
A14: Net finance cost (negative = income) | C14: =三表预测!E15 -> -161.5113 | D14: =三表预测!F15 -> -172.5019 | E14: =三表预测!G15 -> -127.772 | F14: =三表预测!H15 -> -194.51809 | G14: =三表预测!I15 -> -262.79018 | H14: =三表预测!J15 -> -268.93355 | I14: =三表预测!K15 -> -287.43841 | J14: =三表预测!L15 -> -338.85479 | L14: =季度数据!G11 -> -38.1213 | M14: =季度数据!H11 -> -25.072 | N14: =季度数据!I11 -> -38.7991 | O14: =季度数据!J11 -> -25.7796 | P14: =季度数据!K11 -> -28.973 | Q14: =季度数据!L11 -> -12.9393
A15: Other income | C15: =三表预测!E16 -> 348.6995 | D15: =三表预测!F16 -> 305.0967 | E15: =三表预测!G16 -> 390.1677 | F15: =三表预测!H16 -> 286.29204 | G15: =三表预测!I16 -> 317.12502 | H15: =三表预测!J16 -> 260.62087 | I15: =三表预测!K16 -> 263.78783 | J15: =三表预测!L16 -> 264.77556 | L15: =季度数据!G12 -> 87.1963 | M15: =季度数据!H12 -> 90.7529 | N15: =季度数据!I12 -> 87.9912 | O15: =季度数据!J12 -> 124.2274 | P15: =季度数据!K12 -> 85.4097 | Q15: =季度数据!L12 -> 53.7199
A16: Operating profit | C16: =三表预测!E20 -> 1777.6464 | D16: =三表预测!F20 -> 2522.7052 | E16: =三表预测!G20 -> 3008.4653 | F16: =三表预测!H20 -> 4914.0391 | G16: =三表预测!I20 -> 6545.3364 | H16: =三表预测!J20 -> 7245.2411 | I16: =三表预测!K20 -> 7738.255 | J16: =三表预测!L20 -> 8121.848 | L16: =季度数据!G13 -> 616.3601 | M16: =季度数据!H13 -> 810.5954 | N16: =季度数据!I13 -> 831.3498 | O16: =季度数据!J13 -> 750.1603 | P16: =季度数据!K13 -> 911.3291 | Q16: =季度数据!L13 -> 1315.4431
A17: Operating margin | C17: =IFERROR(三表预测!E20/三表预测!E6,0) -> 0.31041437 | D17: =IFERROR(三表预测!F20/三表预测!F6,0) -> 0.34206215 | E17: =IFERROR(三表预测!G20/三表预测!G6,0) -> 0.33400843 | F17: =IFERROR(三表预测!H20/三表预测!H6,0) -> 0.35446676 | G17: =IFERROR(三表预测!I20/三表预测!I6,0) -> 0.37293445 | H17: =IFERROR(三表预测!J20/三表预测!J6,0) -> 0.35947224 | I17: =IFERROR(三表预测!K20/三表预测!K6,0) -> 0.34861783 | J17: =IFERROR(三表预测!L20/三表预测!L6,0) -> 0.34278239 | L17: =IFERROR(季度数据!G13/季度数据!G5,0) -> 0.33623169 | M17: =IFERROR(季度数据!H13/季度数据!H5,0) -> 0.35005029 | N17: =IFERROR(季度数据!I13/季度数据!I5,0) -> 0.35233049 | O17: =IFERROR(季度数据!J13/季度数据!J5,0) -> 0.30021002 | P17: =IFERROR(季度数据!K13/季度数据!K5,0) -> 0.33992217 | Q17: =IFERROR(季度数据!L13/季度数据!L5,0) -> 0.35150298
A18: Profit before tax | C18: =三表预测!E22 -> 1782.8474 | D18: =三表预测!F22 -> 2518.9437 | E18: =三表预测!G22 -> 3008.1761 | F18: =三表预测!H22 -> 4911.2131 | G18: =三表预测!I22 -> 6545.3364 | H18: =三表预测!J22 -> 7245.2411 | I18: =三表预测!K22 -> 7738.255 | J18: =三表预测!L22 -> 8121.848 | L18: =季度数据!G14 -> 618.439 | M18: =季度数据!H14 -> 808.6791 | N18: =季度数据!I14 -> 834.7089 | O18: =季度数据!J14 -> 746.3495 | P18: =季度数据!K14 -> 907.7421 | Q18: =季度数据!L14 -> 1316.2041
A19: Effective tax rate | C19: =税务与其他损益!E28 -> 0.11201013 | D19: =税务与其他损益!F28 -> 0.1304952 | E19: =税务与其他损益!G28 -> 0.13004434 | F19: =税务与其他损益!H28 -> 0.13252461 | G19: =税务与其他损益!I28 -> 0.13951906 | H19: =税务与其他损益!J28 -> 0.13905344 | I19: =税务与其他损益!K28 -> 0.13843215 | J19: =税务与其他损益!L28 -> 0.13780101 | L19: =IFERROR(季度数据!G15/季度数据!G14,0) -> 0.13832229 | M19: =IFERROR(季度数据!H15/季度数据!H14,0) -> 0.12921021 | N19: =IFERROR(季度数据!I15/季度数据!I14,0) -> 0.13640073 | O19: =IFERROR(季度数据!J15/季度数据!J14,0) -> 0.11697991 | P19: =IFERROR(季度数据!K15/季度数据!K14,0) -> 0.12882183 | Q19: =IFERROR(季度数据!L15/季度数据!L14,0) -> 0.13296828
A20: Net profit attributable | C20: =三表预测!E26 -> 1580.9858 | D20: =三表预测!F26 -> 2190.4492 | E20: =三表预测!G26 -> 2618.3839 | F20: =三表预测!H26 -> 4260.3565 | G20: =三表预测!I26 -> 5632.1372 | H20: =三表预测!J26 -> 6237.7654 | I20: =三表预测!K26 -> 6667.0317 | J20: =三表预测!L26 -> 7002.6492 | L20: =季度数据!G17 -> 532.6514 | M20: =季度数据!H17 -> 704.4865 | N20: =季度数据!I17 -> 721.3812 | O20: =季度数据!J17 -> 659.8652 | P20: =季度数据!K17 -> 790.8996 | Q20: =季度数据!L17 -> 1141.2187
A21: YoY | C21: =三表预测!E27 -> 0.050694156 | D21: =三表预测!F27 -> 0.38549581 | E21: =三表预测!G27 -> 0.1953639 | F21: =三表预测!H27 -> 0.62709392 | G21: =三表预测!I27 -> 0.3219873 | H21: =三表预测!J27 -> 0.10753079 | I21: =三表预测!K27 -> 0.068817316 | J21: =三表预测!L27 -> 0.050339864 | L21: =IFERROR(季度数据!G17/季度数据!C17-1,0) -> 0.23020146 | M21: =IFERROR(季度数据!H17/季度数据!D17-1,0) -> 0.18887191 | N21: =IFERROR(季度数据!I17/季度数据!E17-1,0) -> 0.24862278 | O21: =IFERROR(季度数据!J17/季度数据!F17-1,0) -> 0.12382194 | P21: =IFERROR(季度数据!K17/季度数据!G17-1,0) -> 0.4848353 | Q21: =IFERROR(季度数据!L17/季度数据!H17-1,0) -> 0.61992984
A22: Net margin | C22: =三表预测!E28 -> 0.2760733 | D22: =三表预测!F28 -> 0.29701043 | E22: =三表预测!G28 -> 0.29070047 | F22: =三表预测!H28 -> 0.30731436 | G22: =三表预测!I28 -> 0.32090299 | H22: =三表预测!J28 -> 0.30948639 | I22: =三表预测!K28 -> 0.30035792 | J22: =三表预测!L28 -> 0.29554663 | L22: =IFERROR(季度数据!G17/季度数据!G5,0) -> 0.29056761 | M22: =IFERROR(季度数据!H17/季度数据!H5,0) -> 0.30422786 | N22: =IFERROR(季度数据!I17/季度数据!I5,0) -> 0.30572521 | O22: =IFERROR(季度数据!J17/季度数据!J5,0) -> 0.26407442 | P22: =IFERROR(季度数据!K17/季度数据!K5,0) -> 0.29500244 | Q22: =IFERROR(季度数据!L17/季度数据!L5,0) -> 0.30494802
A23: EPS (RMB, period-end shares) | C23: =三表预测!E29 -> 0.82493502 | D23: =三表预测!F29 -> 1.142944 | E23: =三表预测!G29 -> 1.3699036 | F23: =三表预测!H29 -> 2.1552782 | G23: =三表预测!I29 -> 2.8492505 | H23: =三表预测!J29 -> 3.1556326 | I23: =三表预测!K29 -> 3.3727948 | J23: =三表预测!L29 -> 3.5425808
A24: EBITDA | C24: =三表预测!E33 -> 2123.0677 | D24: =三表预测!F33 -> 2931.1984 | E24: =三表预测!G33 -> 3500.2428 | F24: =三表预测!H33 -> 5413.0418 | G24: =三表预测!I33 -> 7131.1635 | H24: =三表预测!J33 -> 7969.9608 | I24: =三表预测!K33 -> 8597.0867 | J24: =三表预测!L33 -> 9064.8342
A25: EBITDA margin | C25: =三表预测!E34 -> 0.37073218 | D25: =三表预测!F34 -> 0.39745113 | E25: =三表预测!G34 -> 0.38860697 | F25: =三表预测!H34 -> 0.39046156 | G25: =三表预测!I34 -> 0.4063132 | H25: =三表预测!J34 -> 0.39542917 | I25: =三表预测!K34 -> 0.38730925 | J25: =三表预测!L34 -> 0.3825811
A26: II. Operations
A27: Electronic components revenue | D27: =收入拆解!F17 -> 2298.159 | E27: =收入拆解!G17 -> 3308.0896 | F27: =收入拆解!H17 -> 5983.6724 | G27: =收入拆解!I17 -> 8077.9578 | H27: =收入拆解!J17 -> 9698.3961 | I27: =收入拆解!K17 -> 10862.204 | J27: =收入拆解!L17 -> 11709.456
A28: Communication components revenue | D28: =收入拆解!F26 -> 2305.9847 | E28: =收入拆解!G26 -> 2594.3099 | F28: =收入拆解!H26 -> 3955.5443 | G28: =收入拆解!I26 -> 4936.5193 | H28: =收入拆解!J26 -> 5686.8702 | I28: =收入拆解!K26 -> 6256.1259 | J28: =收入拆解!L26 -> 6735.9708
A29: Electronic & ceramic materials revenue | D29: =收入拆解!F41 -> 1677.2328 | E29: =收入拆解!G41 -> 1959.378 | F29: =收入拆解!H41 -> 2525.459 | G29: =收入拆解!I41 -> 3018.5474 | H29: =收入拆解!J41 -> 3136.9255 | I29: =收入拆解!K41 -> 3338.3736 | J29: =收入拆解!L41 -> 3412.4894
A30: of which SOFC separators (hist.: top-customer proxy) | C30: =收入拆解!E38 -> 449.31873 | D30: =收入拆解!F38 -> 323.86965 | E30: =收入拆解!G38 -> 330.718 | F30: =收入拆解!H38 -> 652.5 | G30: =收入拆解!I38 -> 920.83333 | H30: =收入拆解!J38 -> 829.44 | I30: =收入拆解!K38 -> 846.28923 | J30: =收入拆解!L38 -> 770.88
A31: Equipment components revenue | D31: =收入拆解!F43 -> 536.82473 | E31: =收入拆解!G43 -> 601.75341 | F31: =收入拆解!H43 -> 692.01642 | G31: =收入拆解!I43 -> 775.05839 | H31: =收入拆解!J43 -> 852.56423 | I31: =收入拆解!K43 -> 920.76937 | J31: =收入拆解!L43 -> 976.01553
A32: Other revenue | D32: =收入拆解!F44+收入拆解!F45 -> 556.78962 | E32: =收入拆解!G44+收入拆解!G45 -> 543.62299 | F32: =收入拆解!H44+收入拆解!H45 -> 706.49528 | G32: =收入拆解!I44+收入拆解!I45 -> 742.82005 | H32: =收入拆解!J44+收入拆解!J45 -> 780.46105 | I32: =收入拆解!K44+收入拆解!K45 -> 819.4841 | J32: =收入拆解!L44+收入拆解!L45 -> 859.95831
A33: Core components & materials (interim basis) | D33: =收入拆解!F17+收入拆解!F26+收入拆解!F41+收入拆解!F43 -> 6818.2012 | E33: =收入拆解!G17+收入拆解!G26+收入拆解!G41+收入拆解!G43 -> 8463.5309 | F33: =收入拆解!H17+收入拆解!H26+收入拆解!H41+收入拆解!H43 -> 13156.692 | G33: =收入拆解!I17+收入拆解!I26+收入拆解!I41+收入拆解!I43 -> 16808.083 | H33: =收入拆解!J17+收入拆解!J26+收入拆解!J41+收入拆解!J43 -> 19374.756 | I33: =收入拆解!K17+收入拆解!K26+收入拆解!K41+收入拆解!K43 -> 21377.473 | J33: =收入拆解!L17+收入拆解!L26+收入拆解!L41+收入拆解!L43 -> 22833.931
A34: Sales volume (100 mn units, company basis) | C34: =收入拆解!E6 -> 2872.5609 | D34: =收入拆解!F6 -> 3816.1069 | E34: =收入拆解!G6 -> 5329.9092
A35: Headcount (period-end) | C35: =人员与费用!E11 -> 13501 | D35: =人员与费用!F11 -> 15515 | E35: =人员与费用!G11 -> 17352 | F35: =人员与费用!H11 -> 19628.91 | G35: =人员与费用!I11 -> 21417.099 | H35: =人员与费用!J11 -> 22809.931 | I35: =人员与费用!K11 -> 23893.979 | J35: =人员与费用!L11 -> 24832.667
A36: Pay per employee (RMB 10k) | D36: =人员与费用!F22 -> 12.928528 | E36: =人员与费用!G22 -> 12.79326 | F36: =人员与费用!H22 -> 13.432923 | G36: =人员与费用!I22 -> 14.104569 | H36: =人员与费用!J22 -> 14.739274 | I36: =人员与费用!K22 -> 15.328845 | J36: =人员与费用!L22 -> 15.941999
A37: Capex | C37: =资本开支与折旧!E11 -> 545.8847 | D37: =资本开支与折旧!F11 -> 639.0352 | E37: =资本开支与折旧!G11 -> 580.092 | F37: =资本开支与折旧!H11 -> 1787.9753 | G37: =资本开支与折旧!I11 -> 2593.5925 | H37: =资本开支与折旧!J11 -> 2358.5137 | I37: =资本开支与折旧!K11 -> 1918.9354 | J37: =资本开支与折旧!L11 -> 1679.4592 | L37: =季度数据!G19 -> 98.8266 | M37: =季度数据!H19 -> 108.3401 | N37: =季度数据!I19 -> 166.7533 | O37: =季度数据!J19 -> 206.172 | P37: =季度数据!K19 -> 188.4361 | Q37: =季度数据!L19 -> 287.9349
A38: D&A | C38: =资本开支与折旧!E91 -> 609.43241 | D38: =资本开支与折旧!F91 -> 651.2802 | E38: =资本开支与折旧!G91 -> 740.43309 | F38: =资本开支与折旧!H91 -> 813.65692 | G38: =资本开支与折旧!I91 -> 914.99495 | H38: =资本开支与折旧!J91 -> 1060.0309 | I38: =资本开支与折旧!K91 -> 1212.6478 | J38: =资本开支与折旧!L91 -> 1348.2187
A39: Receivable days | C39: =营运资金!E33 -> 143.99838 | D39: =营运资金!F33 -> 132.95096 | E39: =营运资金!G33 -> 132.10293 | F39: =营运资金!H33 -> 128 | G39: =营运资金!I33 -> 128 | H39: =营运资金!J33 -> 128 | I39: =营运资金!K33 -> 128 | J39: =营运资金!L33 -> 128
A40: Inventory days | C40: =营运资金!E34 -> 185.76626 | D40: =营运资金!F34 -> 189.29501 | E40: =营运资金!G34 -> 167.50165 | F40: =营运资金!H34 -> 156.10015 | G40: =营运资金!I34 -> 157.07956 | H40: =营运资金!J34 -> 157.38008 | I40: =营运资金!K34 -> 157.47553 | J40: =营运资金!L34 -> 157.33805
A41: Payable days | C41: =营运资金!E35 -> 103.88977 | D41: =营运资金!F35 -> 112.43787 | E41: =营运资金!G35 -> 135.02432 | F41: =营运资金!H35 -> 135 | G41: =营运资金!I35 -> 135 | H41: =营运资金!J35 -> 135 | I41: =营运资金!K35 -> 135 | J41: =营运资金!L35 -> 135
A42: Cash conversion cycle (days) | C42: =营运资金!E36 -> 225.87487 | D42: =营运资金!F36 -> 209.8081 | E42: =营运资金!G36 -> 164.58025 | F42: =营运资金!H36 -> 149.10015 | G42: =营运资金!I36 -> 150.07956 | H42: =营运资金!J36 -> 150.38008 | I42: =营运资金!K36 -> 150.47553 | J42: =营运资金!L36 -> 150.33805
A43: III. Balance sheet (quarterly: half-year and year-ends only)
A44: Cash | C44: =三表预测!E37 -> 2841.6149 | D44: =三表预测!F37 -> 3062.8452 | E44: =三表预测!G37 -> 3057.7786 | F44: =三表预测!H37 -> 9327.1517 | G44: =三表预测!I37 -> 10581.358 | H44: =三表预测!J37 -> 12764.932 | I44: =三表预测!K37 -> 15978.456 | J44: =三表预测!L37 -> 19981.123 | M44: =N(历史资产负债表!J5) -> 5430.1287 | O44: =三表预测!G37 -> 3057.7786 | Q44: =N(历史资产负债表!K5) -> 3825.5415
A45: Wealth-management products | C45: =三表预测!E38 -> 3846.7081 | D45: =三表预测!F38 -> 5053.3869 | E45: =三表预测!G38 -> 3758.5116 | F45: =三表预测!H38 -> 3758.5116 | G45: =三表预测!I38 -> 3758.5116 | H45: =三表预测!J38 -> 3758.5116 | I45: =三表预测!K38 -> 3758.5116 | J45: =三表预测!L38 -> 3758.5116 | M45: =N(历史资产负债表!J6) -> 2865.6921 | O45: =三表预测!G38 -> 3758.5116 | Q45: =N(历史资产负债表!K6) -> 3256.5671
A46: Deposits over one year | C46: =融资与资金!E10 -> 3590.7033 | D46: =融资与资金!F10 -> 2930.2505 | E46: =融资与资金!G10 -> 5850.9937 | F46: =融资与资金!H10 -> 5850.9937 | G46: =融资与资金!I10 -> 5850.9937 | H46: =融资与资金!J10 -> 5850.9937 | I46: =融资与资金!K10 -> 5850.9937 | J46: =融资与资金!L10 -> 5850.9937 | M46: 2925.9402 | O46: =融资与资金!G10 -> 5850.9937 | Q46: 5693.1376
A47: Notes, accounts receivable & receivables financing | C47: =三表预测!E39+三表预测!E40+三表预测!E41 -> 2259.2709 | D47: =三表预测!F39+三表预测!F40+三表预测!F41 -> 2686.3346 | E47: =三表预测!G39+三表预测!G40+三表预测!G41 -> 3259.9217 | F47: =三表预测!H39+三表预测!H40+三表预测!H41 -> 4861.6109 | G47: =三表预测!I39+三表预测!I40+三表预测!I41 -> 6154.8372 | H47: =三表预测!J39+三表预测!J40+三表预测!J41 -> 7068.1309 | I47: =三表预测!K39+三表预测!K40+三表预测!K41 -> 7784.1382 | J47: =三表预测!L39+三表预测!L40+三表预测!L41 -> 8309.09 | M47: =N(历史资产负债表!J8)+N(历史资产负债表!J9)+N(历史资产负债表!J10) -> 2804.7162 | O47: =三表预测!G39+三表预测!G40+三表预测!G41 -> 3259.9217 | Q47: =N(历史资产负债表!K8)+N(历史资产负债表!K9)+N(历史资产负债表!K10) -> 4187.8129
A48: Inventories | C48: =三表预测!E44 -> 1753.5978 | D48: =三表预测!F44 -> 2180.7115 | E48: =三表预测!G44 -> 2391.7224 | F48: =三表预测!H44 -> 3265.117 | G48: =三表预测!I44 -> 4138.0358 | H48: =三表预测!J44 -> 4834.1584 | I48: =三表预测!K44 -> 5417.6464 | J48: =三表预测!L44 -> 5833.1498 | M48: =N(历史资产负债表!J16) -> 2163.2406 | O48: =三表预测!G44 -> 2391.7224 | Q48: =N(历史资产负债表!K16) -> 2811.0479
A49: PP&E incl. construction in progress | C49: =三表预测!E47 -> 5783.8854 | D49: =三表预测!F47 -> 6327.452 | E49: =三表预测!G47 -> 6589.7152 | F49: =三表预测!H47 -> 7506.5027 | G49: =三表预测!I47 -> 9145.1311 | H49: =三表预测!J47 -> 10404.481 | I49: =三表预测!K47 -> 11071.028 | J49: =三表预测!L47 -> 11357.132 | M49: =N(历史资产负债表!J22)+N(历史资产负债表!J25) -> 6272.5564 | O49: =三表预测!G47 -> 6589.7152 | Q49: =N(历史资产负债表!K22)+N(历史资产负债表!K25) -> 6937.0576
A50: Total assets | C50: =三表预测!E54 -> 21826.965 | D50: =三表预测!F54 -> 23915.803 | E50: =三表预测!G54 -> 26506.088 | F50: =三表预测!H54 -> 36274.471 | G50: =三表预测!I54 -> 41535.498 | H50: =三表预测!J54 -> 46732.423 | I50: =三表预测!K54 -> 52023.435 | J50: =三表预测!L54 -> 57335.078 | M50: =N(历史资产负债表!J34) -> 24097.872 | O50: =三表预测!G54 -> 26506.088 | Q50: =N(历史资产负债表!K34) -> 28438.081
A51: Interest-bearing debt | C51: =融资与资金!E23 -> 745.2792 | D51: =融资与资金!F23 -> 479.3472 | E51: =融资与资金!G23 -> 567.6374 | F51: =融资与资金!H23 -> 567.6374 | G51: =融资与资金!I23 -> 567.6374 | H51: =融资与资金!J23 -> 567.6374 | I51: =融资与资金!K23 -> 567.6374 | J51: =融资与资金!L23 -> 567.6374 | M51: =N(历史资产负债表!J35)+N(历史资产负债表!J49)+N(历史资产负债表!J46) -> 477.1853 | O51: =融资与资金!G23 -> 567.6374 | Q51: =N(历史资产负债表!K35)+N(历史资产负债表!K49)+N(历史资产负债表!K46) -> 769.5973
A52: Total liabilities | C52: =三表预测!E66 -> 3587.8643 | D52: =三表预测!F66 -> 4044.0346 | E52: =三表预测!G66 -> 4843.0454 | F52: =三表预测!H66 -> 6041.6477 | G52: =三表预测!I66 -> 7076.4546 | H52: =三表预测!J66 -> 7894.2198 | I52: =三表预测!K66 -> 8576.6631 | J52: =三表预测!L66 -> 9085.7766 | M52: =N(历史资产负债表!J59) -> 3810.4021 | O52: =三表预测!G66 -> 4843.0454 | Q52: =N(历史资产负债表!K59) -> 5789.5051
A53: Shareholders' equity | C53: =三表预测!E67 -> 18233.198 | D53: =三表预测!F67 -> 19866.081 | E53: =三表预测!G67 -> 21658.759 | F53: =三表预测!H67 -> 30228.541 | G53: =三表预测!I67 -> 34454.76 | H53: =三表预测!J67 -> 38833.92 | I53: =三表预测!K67 -> 43442.489 | J53: =三表预测!L67 -> 48245.018 | M53: =N(历史资产负债表!J66) -> 20281.836 | O53: =三表预测!G67 -> 21658.759 | Q53: =N(历史资产负债表!K66) -> 22644.415
A54: Net cash (incl. deposits over one year) | C54: =融资与资金!E43 -> 9507.1736 | D54: =融资与资金!F43 -> 10544.889 | E54: =融资与资金!G43 -> 12080.847 | F54: =融资与资金!H43 -> 18350.22 | G54: =融资与资金!I43 -> 19604.426 | H54: =融资与资金!J43 -> 21788 | I54: =融资与资金!K43 -> 25001.524 | J54: =融资与资金!L43 -> 29004.191 | M54: =M44+M45+M46-M51-N(N(历史资产负债表!J50)) -> 10723.916 | O54: =融资与资金!G43 -> 12080.847 | Q54: =Q44+Q45+Q46-Q51-N(N(历史资产负债表!K50)) -> 11984.412
A55: Liabilities / assets | C55: =IFERROR(C52/C50,0) -> 0.16437761 | D55: =IFERROR(D52/D50,0) -> 0.16909466 | E55: =IFERROR(E52/E50,0) -> 0.18271446 | F55: =IFERROR(F52/F50,0) -> 0.16655371 | G55: =IFERROR(G52/G50,0) -> 0.17037125 | H55: =IFERROR(H52/H50,0) -> 0.16892383 | I55: =IFERROR(I52/I50,0) -> 0.16486153 | J55: =IFERROR(J52/J50,0) -> 0.15846803 | M55: =IFERROR(M52/M50,0) -> 0.15812193 | O55: =IFERROR(O52/O50,0) -> 0.18271446 | Q55: =IFERROR(Q52/Q50,0) -> 0.20358283
A56: IV. Cash flow
A57: Operating cash flow | C57: =三表预测!E79 -> 1718.968 | D57: =三表预测!F79 -> 2403.1223 | E57: =三表预测!G79 -> 2877.6091 | F57: =三表预测!H79 -> 3666.0159 | G57: =三表预测!I79 -> 5172.8401 | H57: =三表预测!J79 -> 6314.8486 | I57: =三表预测!K79 -> 7098.9668 | J57: =三表预测!L79 -> 7784.6793 | L57: =季度数据!G18 -> 242.589 | M57: =季度数据!H18 -> 885.1204 | N57: =季度数据!I18 -> 862.7469 | O57: =季度数据!J18 -> 887.1527 | P57: =季度数据!K18 -> 156.6853 | Q57: =季度数据!L18 -> 1140.6343
A58: Capex (outflow negative) | C58: =三表预测!E80 -> -545.8847 | D58: =三表预测!F80 -> -639.0352 | E58: =三表预测!G80 -> -580.092 | F58: =三表预测!H80 -> -1787.9753 | G58: =三表预测!I80 -> -2593.5925 | H58: =三表预测!J80 -> -2358.5137 | I58: =三表预测!K80 -> -1918.9354 | J58: =三表预测!L80 -> -1679.4592 | L58: =-季度数据!G19 -> -98.8266 | M58: =-季度数据!H19 -> -108.3401 | N58: =-季度数据!I19 -> -166.7533 | O58: =-季度数据!J19 -> -206.172 | P58: =-季度数据!K19 -> -188.4361 | Q58: =-季度数据!L19 -> -287.9349
A59: Free cash flow (OCF - capex) | C59: =C57+C58 -> 1173.0833 | D59: =D57+D58 -> 1764.0871 | E59: =E57+E58 -> 2297.5171 | F59: =F57+F58 -> 1878.0406 | G59: =G57+G58 -> 2579.2476 | H59: =H57+H58 -> 3956.3348 | I59: =I57+I58 -> 5180.0314 | J59: =J57+J58 -> 6105.2201 | L59: =L57+L58 -> 143.7624 | M59: =M57+M58 -> 776.7803 | N59: =N57+N58 -> 695.9936 | O59: =O57+O58 -> 680.9807 | P59: =P57+P58 -> -31.7508 | Q59: =Q57+Q58 -> 852.6994
A60: Dividends paid (hist. incl. interest) | C60: =-三表预测!E85 -> 489.9347 | D60: =-三表预测!F85 -> 553.6596 | E60: =-三表预测!G85 -> 726.6256 | F60: =-三表预测!H85 -> 860.11 | G60: =-三表预测!I85 -> 1405.9177 | H60: =-三表预测!J85 -> 1858.6053 | I60: =-三表预测!K85 -> 2058.4626 | J60: =-三表预测!L85 -> 2200.1205 | L60: =季度数据!G20 -> 0 | M60: =季度数据!H20 -> 726.3767 | N60: =季度数据!I20 -> 0.1353 | O60: =季度数据!J20 -> 0.1137 | P60: =季度数据!K20 -> 0.1622 | Q60: =季度数据!L20 -> 860.8047
A61: Share buybacks | C61: =-三表预测!E86 -> 0 | D61: =-三表预测!F86 -> 0 | E61: =-三表预测!G86 -> 175.44073 | F61: =-三表预测!H86 -> 1644.66 | G61: =-三表预测!I86 -> 0 | H61: =-三表预测!J86 -> 0 | I61: =-三表预测!K86 -> 0 | J61: =-三表预测!L86 -> 0
A62: V. Key metrics
A63: ROE (average equity) | C63: =回报分析!E8 -> 0.089490933 | D63: =回报分析!F8 -> 0.11498639 | E63: =回报分析!G8 -> 0.12611169 | F63: =回报分析!H8 -> 0.16421577 | G63: =回报分析!I8 -> 0.17414502 | H63: =回报分析!J8 -> 0.17022453 | I63: =回报分析!K8 -> 0.16206424 | J63: =回报分析!L8 -> 0.15275034
A64: ROIC | C64: =回报分析!E11 -> 0.15708236 | D64: =回报分析!F11 -> 0.22141341 | E64: =回报分析!G11 -> 0.25480171 | F64: =回报分析!H11 -> 0.37290887 | G64: =回报分析!I11 -> 0.40110246 | H64: =回报分析!J11 -> 0.37370282 | I64: =回报分析!K11 -> 0.35914986 | J64: =回报分析!L11 -> 0.35367001
A65: Book value per share (RMB) | C65: =IFERROR(三表预测!E67/股本与每股!E12,0) -> 9.513813 | D65: =IFERROR(三表预测!F67/股本与每股!F12,0) -> 10.365827 | E65: =IFERROR(三表预测!G67/股本与每股!G12,0) -> 11.331575 | F65: =IFERROR(三表预测!H67/股本与每股!H12,0) -> 15.292362 | G65: =IFERROR(三表预测!I67/股本与每股!I12,0) -> 17.430371 | H65: =IFERROR(三表预测!J67/股本与每股!J12,0) -> 19.645751 | I65: =IFERROR(三表预测!K67/股本与每股!K12,0) -> 21.977187 | J65: =IFERROR(三表预测!L67/股本与每股!L12,0) -> 24.406746
A66: DPS paid in year (RMB) | E66: =股本与每股!G15 -> 0.38 | F66: =股本与每股!H15 -> 0.44999811 | G66: =股本与每股!I15 -> 0.71124182 | H66: =股本与每股!J15 -> 0.94025266 | I66: =股本与每股!K15 -> 1.0413588 | J66: =股本与每股!L15 -> 1.1130223
A67: P/E (current price) | C67: =回报分析!E16 -> 143.64768 | D67: =回报分析!F16 -> 103.67962 | E67: =回报分析!G16 -> 86.502435 | F67: =回报分析!H16 -> 54.9813 | G67: =回报分析!I16 -> 41.589885 | H67: =回报分析!J16 -> 37.5519 | I67: =回报分析!K16 -> 35.134067 | J67: =回报分析!L16 -> 33.450189
A68: P/B (current price) | C68: =回报分析!E17 -> 12.455574 | D68: =回报分析!F17 -> 11.431794 | E68: =回报分析!G17 -> 10.457505 | F68: =回报分析!H17 -> 7.7489662 | G68: =回报分析!I17 -> 6.7984783 | H68: =回报分析!J17 -> 6.0318386 | I68: =回报分析!K17 -> 5.3919548 | J68: =回报分析!L17 -> 4.8552151
A69: EV/EBITDA (current price) | F69: =回报分析!H18 -> 39.883254 | G69: =回报分析!I18 -> 30.274123 | H69: =回报分析!J18 -> 27.087928 | I69: =回报分析!K18 -> 25.111963 | J69: =回报分析!L18 -> 23.81618
A71: Note: quarterly balance-sheet data are available only at half-year ends (2025Q2, 2026Q2) and year-end (2025Q4 = 2025A); quarterly capex is cash paid for long-term assets.
A72: 'Core components & materials' follows the 2026 interim-report basis (electronic + communication components + materials + equipment); 2026H1 was 6,080.7 (+55.0% YoY). Quarterly segment revenue is not disclosed.

Sheet 假设
A1: 核心假设（蓝字可改；黄底为关键假设；情景切换在C5）
A2: 单位：百万元人民币，另注明除外。逐年假设列与各明细表对齐（C:G=2021A-2025A历史参照，H:L=2026E-2030E）。“采用值”行=情景值+敏感性冲击，模型只引用采用值。
A4: 一、情景、市场与股本参数
A5: 情景选择（1=基准，2=乐观，3=悲观） | C5: 1 | D5: 修改此格切换全模型情景
A6: A股股价（元/股） | C6: 118.5 | D6: Wind一致预期表2026-09-30：2026E PE 56.42×EPS 2.10倒算；请按最新行情更新
A7: H股发行价（港元/股） | C7: 100.3 | D7: H股配售结果：发行价100.30港元（2026-07-09上市）
A8: 港元兑人民币（HKD/CNY） | C8: 0.8686 | D8: 2026年半年报外币折算汇率（2026-06-30）0.86855；H股于2026-07-09上市，请按实际结汇汇率更新
A9: H股发行股数（股，含部分行使超额配股权） | C9: 80221200 | D9: 2026年半年报：首次发行71,364,300股+超额配股8,856,900股=80,221,200股
A10: H股发行费用率 | C10: 0.025 | D10: 假设值（上市费用、承销佣金）；2025年及2026H1已付上市费用合计约18.2百万元
A11: H股2026年加权在外天数 | C11: 172 | D11: 71,364,300股自2026-07-09（175天）、8,856,900股自2026-08-05（148天）加权
A12: H股募资投向境外新建扩建项目比例 | C12: 0.412 | D12: H股招股章程：约41.2%投向泰国、德国新建扩建（燃料电池扩建、高精度压电微点胶、数据中心电子元件、通信器件）
A13: 2026年第一期回购股数（股） | C13: 8547300 | D13: 2026年半年报：董事会2026-07-20批准，截至2026-07-30实施完毕
A14: 2026年第一期回购金额 | C14: 894.66 | D14: 2026年半年报：成交总金额894,661,561.03元（不含交易费用）
A15: 2026年第二期回购金额（下限5亿、上限10亿，取中值） | C15: 750 | D15: 董事会2026-07-30批准，进行中；中值为假设
A16: 2026年第一期回购完成后至年末月数（加权股本用） | C16: 5 | D16: 2026-07-30完成，至12-31约5个月
... A20: 少数股东损益占净利润比例 | C20: 0 | D20: 历史接近0（2025年-1.4百万元）
A22: 二、估值参数
A23: 无风险利率 | C23: 0.019 | D23: 假设：中国10年期国债收益率约1.8%-1.9%
A24: Beta | C24: 1.1 | D24: 假设值
A25: 股权风险溢价 | C25: 0.065 | D25: 假设值
A26: 税前债务成本 | C26: 0.035 | D26: 2025年利息费用20.4/平均有息负债约507（约4.0%），取3.5%
A27: 目标债务占比 D/(D+E) | C27: 0.02 | D27: 公司净现金，取2%
A28: 永续增长率 | C28: 0.03 | D28: 假设值
A29: 第二阶段起点增速溢价（相对2030E收入增速） | C29: 0 | D29: 第二阶段（2031E-2035E）起点增速=MAX(永续增速, 2030E收入增速)+本溢价，线性递减至终点；FCFF=NOPAT×(1-增速÷RONIC)。默认0，即假设2030年后不再提速
A30: 第二阶段增速终点（2035E） | C30: 0.04 | D30: 不高于起点、不低于永续增速
A31: 新增投资资本回报率（RONIC，第二阶段与永续期） | C31: 0.25 | D31: 再投资率=增速÷RONIC（价值驱动公式）；2025A ROIC约25.9%（含H股前口径），2026E-2030E约37%-40%
A32: 相对估值：PE下限 | C32: 30 | D32: 可调
A33: 相对估值：PE上限 | C33: 55 | D33: 可调
A35: 三、税务与费用分摊参数
A36: 法定适用税率（高新技术企业） | C36: 0.15 | D36: 母公司及深圳、南充、德阳、苏州子公司为高新技术企业，成都、红河适用西部大开发，均为15%；母公司与南充的高新证书2025-12-31到期，2026H1暂按15%预缴，待复审（风险点）
A37: 研发费用加计扣除比例 | C37: 1 | D37: 财税〔2023〕7号：自2023年起按100%加计扣除
A38: 折旧摊销计入营业成本比例 | C38: 0.842 | D38: 2025A：折旧摊销740.4中，研发37.3（5.0%）、管理79.8（10.8%）、销售未单列；其余计入生产成本（倒挤）
A39: 折旧摊销计入研发费用比例 | C39: 0.05 | D39: 2025A研发费用折旧摊销37.3/740.4
A40: 折旧摊销计入销售费用比例 | C40: 0 | D40: 销售费用附注未单列折旧摊销
A42: 四、敏感性冲击（默认0；情景值之上叠加，用于龙卷风图与二维敏感性）
A43: 电子元件销量增速冲击（pp，逐年叠加） | C43: 0 | D43: 敏感性分析用；正常使用保持0
A44: 电子元件单价变动冲击（pp，逐年叠加） | C44: 0 | D44: 敏感性分析用；正常使用保持0
A45: 通信器件销量增速冲击（pp） | C45: 0 | D45: 敏感性分析用；正常使用保持0
A46: 通信器件单价变动冲击（pp） | C46: 0 | D46: 敏感性分析用；正常使用保持0
A47: 其他电子及陶瓷材料增速冲击（pp） | C47: 0 | D47: 敏感性分析用；正常使用保持0
A48: 全部分部毛利率冲击（pp） | C48: 0 | D48: 敏感性分析用；正常使用保持0
A49: Bloom电池片层需求冲击（%，乘数） | C49: 0 | D49: 敏感性分析用；正常使用保持0
A50: 三环隔膜片份额冲击（pp） | C50: 0 | D50: 敏感性分析用；正常使用保持0
A51: 隔膜片单价冲击（%，乘数） | C51: 0 | D51: 敏感性分析用；正常使用保持0
A52: 人均薪酬增速冲击（pp） | C52: 0 | D52: 敏感性分析用；正常使用保持0
A53: 员工人数增速冲击（pp） | C53: 0 | D53: 敏感性分析用；正常使用保持0
A54: 管理费用其他项占收入冲击（pp） | C54: 0 | D54: 敏感性分析用；正常使用保持0
... A61: 2026E权重（上半年已实现，只对下半年生效） | C61: 0.5 | D61: 2026E列的敏感性冲击与乐观/悲观情景相对基准的差额均乘以该权重（周转天数冲击作用于年末余额，不加权）；2027E起全额生效
A63: 逐年假设 | B63: 单位 | C63: 2021A | D63: 2022A | E63: 2023A | F63: 2024A | G63: 2025A | H63: 2026E | I63: 2027E | J63: 2028E | K63: 2029E | L63: 2030E | M63: 来源/说明
A64: 五、收入：量价拆分（电子元件=MLCC、陶瓷封装基座、电阻等；通信器件=插芯、套筒等光通信产品）
A65: 电子元件 销量增速—基准 | B65: % | H65: 0.52 | I65: 0.25 | J65: 0.16 | K65: 0.12 | L65: 0.1
A66: 电子元件 销量增速—乐观 | B66: % | H66: 0.58 | I66: 0.3 | J66: 0.2 | K66: 0.15 | L66: 0.12
A67: 电子元件 销量增速—悲观 | B67: % | H67: 0.46 | I67: 0.15 | J67: 0.1 | K67: 0.08 | L67: 0.06
A68: 电子元件 销量增速（采用值） | B68: % | H68: =(H65+(CHOOSE($C$5,H65,H66,H67)-H65)*$C$61)+$C$43*$C$61 -> 0.52 | I68: =CHOOSE($C$5,I65,I66,I67)+$C$43 -> 0.25 | J68: =CHOOSE($C$5,J65,J66,J67)+$C$43 -> 0.16 | K68: =CHOOSE($C$5,K65,K66,K67)+$C$43 -> 0.12 | L68: =CHOOSE($C$5,L65,L66,L67)+$C$43 -> 0.1 | M68: 公司口径销量（万只）2025A +39.7%、2024A +32.9%；2026H1“电子、通信元件及材料”+55%（可比口径），2026Q2单季收入3,742；2026E按下半年/上半年约1.16倍（2024-2025年为1.15-1.17倍）标定
A69: 电子元件 单价变动—基准 | B69: % | H69: 0.19 | I69: 0.08 | J69: 0.035 | K69: 0 | L69: -0.02
A70: 电子元件 单价变动—乐观 | B70: % | H70: 0.22 | I70: 0.115 | J70: 0.04 | K70: 0 | L70: -0.02
A71: 电子元件 单价变动—悲观 | B71: % | H71: 0.15 | I71: 0.045 | J71: 0 | K71: -0.02 | L71: -0.02
A72: 电子元件 单价变动（采用值） | B72: % | H72: =(H69+(CHOOSE($C$5,H69,H70,H71)-H69)*$C$61)+$C$44*$C$61 -> 0.19 | I72: =CHOOSE($C$5,I69,I70,I71)+$C$44 -> 0.08 | J72: =CHOOSE($C$5,J69,J70,J71)+$C$44 -> 0.035 | K72: =CHOOSE($C$5,K69,K70,K71)+$C$44 -> 0 | L72: =CHOOSE($C$5,L69,L70,L71)+$C$44 -> -0.02 | M72: 产业链调研（2026-06-11）：国内MLCC涨价集中在高容产品，低容不涨；结构升级带来均价上行
A73: 通信器件 销量增速—基准 | B73: % | H73: 0.58 | I73: 0.3 | J73: 0.2 | K73: 0.14 | L73: 0.11
A74: 通信器件 销量增速—乐观 | B74: % | H74: 0.65 | I74: 0.4 | J74: 0.24 | K74: 0.16 | L74: 0.13
A75: 通信器件 销量增速—悲观 | B75: % | H75: 0.5 | I75: 0.17 | J75: 0.13 | K75: 0.095 | L75: 0.08
A76: 通信器件 销量增速（采用值） | B76: % | H76: =(H73+(CHOOSE($C$5,H73,H74,H75)-H73)*$C$61)+$C$45*$C$61 -> 0.58 | I76: =CHOOSE($C$5,I73,I74,I75)+$C$45 -> 0.3 | J76: =CHOOSE($C$5,J73,J74,J75)+$C$45 -> 0.2 | K76: =CHOOSE($C$5,K73,K74,K75)+$C$45 -> 0.14 | L76: =CHOOSE($C$5,L73,L74,L75)+$C$45 -> 0.11 | M76: 2025A通信器件收入+12.5%；2026H1插芯、套筒等光通信产品随数据中心光模块需求快速增长
A77: 通信器件 单价变动—基准 | B77: % | H77: -0.035 | I77: -0.04 | J77: -0.04 | K77: -0.035 | L77: -0.03
A78: 通信器件 单价变动—乐观 | B78: % | H78: -0.03 | I78: -0.035 | J78: -0.03 | K78: -0.035 | L78: -0.025
A79: 通信器件 单价变动—悲观 | B79: % | H79: -0.04 | I79: -0.045 | J79: -0.045 | K79: -0.04 | L79: -0.035
A80: 通信器件 单价变动（采用值） | B80: % | H80: =(H77+(CHOOSE($C$5,H77,H78,H79)-H77)*$C$61)+$C$46*$C$61 -> -0.035 | I80: =CHOOSE($C$5,I77,I78,I79)+$C$46 -> -0.04 | J80: =CHOOSE($C$5,J77,J78,J79)+$C$46 -> -0.04 | K80: =CHOOSE($C$5,K77,K78,K79)+$C$46 -> -0.035 | L80: =CHOOSE($C$5,L77,L78,L79)+$C$46 -> -0.03 | M80: 成熟光无源器件年降价3%-5%为行业惯例（假设）
A81: 其他电子及陶瓷材料（不含SOFC）增速—基准 | B81: % | H81: 0.15 | I81: 0.12 | J81: 0.1 | K81: 0.08 | L81: 0.06
A82: 其他电子及陶瓷材料（不含SOFC）增速—乐观 | B82: % | H82: 0.2 | I82: 0.15 | J82: 0.12 | K82: 0.1 | L82: 0.08
A83: 其他电子及陶瓷材料（不含SOFC）增速—悲观 | B83: % | H83: 0.08 | I83: 0.06 | J83: 0.05 | K83: 0.04 | L83: 0.03
A84: 其他电子及陶瓷材料（不含SOFC）增速（采用值） | B84: % | H84: =(H81+(CHOOSE($C$5,H81,H82,H83)-H81)*$C$61)+$C$47*$C$61 -> 0.15 | I84: =CHOOSE($C$5,I81,I82,I83)+$C$47 -> 0.12 | J84: =CHOOSE($C$5,J81,J82,J83)+$C$47 -> 0.1 | K84: =CHOOSE($C$5,K81,K82,K83)+$C$47 -> 0.08 | L84: =CHOOSE($C$5,L81,L82,L83)+$C$47 -> 0.06 | M84: 2025A分部整体+16.8%（含SOFC隔膜片）
A85: 设备组件 收入增速—基准 | B85: % | H85: 0.15 | I85: 0.12 | J85: 0.1 | K85: 0.08 | L85: 0.06
A86: 设备组件 收入增速—乐观 | B86: % | H86: 0.2 | I86: 0.15 | J86: 0.12 | K86: 0.1 | L86: 0.08
A87: 设备组件 收入增速—悲观 | B87: % | H87: 0.08 | I87: 0.06 | J87: 0.05 | K87: 0.04 | L87: 0.03
A88: 设备组件 收入增速（采用值） | B88: % | H88: =(H85+(CHOOSE($C$5,H85,H86,H87)-H85)*$C$61) -> 0.15 | I88: =CHOOSE($C$5,I85,I86,I87) -> 0.12 | J88: =CHOOSE($C$5,J85,J86,J87) -> 0.1 | K88: =CHOOSE($C$5,K85,K86,K87) -> 0.08 | L88: =CHOOSE($C$5,L85,L86,L87) -> 0.06 | M88: 2025A +12.1%
A89: 其他主营 收入增速—基准 | B89: % | H89: 0.3 | I89: 0.05 | J89: 0.05 | K89: 0.05 | L89: 0.05
A90: 其他主营 收入增速—乐观 | B90: % | H90: 0.35 | I90: 0.08 | J90: 0.08 | K90: 0.08 | L90: 0.08
A91: 其他主营 收入增速—悲观 | B91: % | H91: 0.2 | I91: 0 | J91: 0 | K91: 0 | L91: 0
A92: 其他主营 收入增速（采用值） | B92: % | H92: =(H89+(CHOOSE($C$5,H89,H90,H91)-H89)*$C$61) -> 0.3 | I92: =CHOOSE($C$5,I89,I90,I91) -> 0.05 | J92: =CHOOSE($C$5,J89,J90,J91) -> 0.05 | K92: =CHOOSE($C$5,K89,K90,K91) -> 0.05 | L92: =CHOOSE($C$5,L89,L90,L91) -> 0.05 | M92: 2025A -9.6%。2026H1半年报“其他”（其他主营+其他业务）342.6，对2025H1可比约225.0增长约52%（新口径下设备组件已并入主营大类）
A93: 其他业务 收入—基准 | B93: 百万元 | H93: 180 | I93: 190 | J93: 200 | K93: 210 | L93: 220
A94: 其他业务 收入—乐观 | B94: 百万元 | H94: 200 | I94: 220 | J94: 240 | K94: 260 | L94: 280
A95: 其他业务 收入—悲观 | B95: 百万元 | H95: 150 | I95: 150 | J95: 150 | K95: 150 | L95: 150
A96: 其他业务 收入（采用值） | B96: 百万元 | F96: =收入拆解!F45 -> 108.85815 | G96: =收入拆解!G45 -> 138.62662 | H96: =(H93+(CHOOSE($C$5,H93,H94,H95)-H93)*$C$61) -> 180 | I96: =CHOOSE($C$5,I93,I94,I95) -> 190 | J96: =CHOOSE($C$5,J93,J94,J95) -> 200 | K96: =CHOOSE($C$5,K93,K94,K95) -> 210 | L96: =CHOOSE($C$5,L93,L94,L95) -> 220 | M96: 2025A 138.6（2024A 108.9）；按“其他”合计约+30%推算
A97: 境外收入占比 | B97: % | D97: =收入拆解!D63 -> 0.2112 | E97: =收入拆解!E63 -> 0.2011 | F97: =收入拆解!F63 -> 0.179 | G97: =收入拆解!G63 -> 0.174 | H97: 0.18 | I97: 0.19 | J97: 0.2 | K97: 0.2 | L97: 0.2 | M97: 年报2022-2023A为21.1%/20.1%；2024年起年报不再披露地区拆分，2024-2025A取H股招股章程17.9%/17.4%（口径略异）；泰国工厂投产后海外占比回升（假设）
A98: 六、SOFC隔膜片子模型（Bloom电池片层需求×每GW片数×三环份额×单价；2025A以三环第一大客户销售额330.7百万元为代理）
A99: Bloom电池片层需求—基准 | B99: GW | H99: 1.45 | I99: 2.5 | J99: 3.2 | K99: 3.8 | L99: 4.4
A100: Bloom电池片层需求—乐观 | B100: GW | H100: 1.6 | I100: 3 | J100: 4 | K100: 4.8 | L100: 5.5
A101: Bloom电池片层需求—悲观 | B101: GW | H101: 1.3 | I101: 2 | J101: 2.4 | K101: 2.8 | L101: 3.2
A102: Bloom电池片层需求（采用值） | B102: GW | G102: 0.725 | H102: =(H99+(CHOOSE($C$5,H99,H100,H101)-H99)*$C$61)*(1+$C$49*$C$61) -> 1.45 | I102: =CHOOSE($C$5,I99,I100,I101)*(1+$C$49) -> 2.5 | J102: =CHOOSE($C$5,J99,J100,J101)*(1+$C$49) -> 3.2 | K102: =CHOOSE($C$5,K99,K100,K101)*(1+$C$49) -> 3.8 | L102: =CHOOSE($C$5,L99,L100,L101)*(1+$C$49) -> 4.4 | M102: 2025A约0.65-0.8GW（验收约500MW+约25%-30%翻新）；Bloom 2026年收入指引39-42亿美元；产业链调研：电堆产能2028-29年约5GW
A103: 单片功率—基准 | B103: W/片 | H103: 30 | I103: 30 | J103: 32.5 | K103: 32.5 | L103: 35
A104: 单片功率—乐观 | B104: W/片 | H104: 27.5 | I104: 25 | J104: 30 | K104: 30 | L104: 32.5
A105: 单片功率—悲观 | B105: W/片 | H105: 32.5 | I105: 32.5 | J105: 35 | K105: 35 | L105: 37.5
A106: 单片功率（采用值） | B106: W/片 | H106: =(H103+(CHOOSE($C$5,H103,H104,H105)-H103)*$C$61) -> 30 | I106: =CHOOSE($C$5,I103,I104,I105) -> 30 | J106: =CHOOSE($C$5,J103,J104,J105) -> 32.5 | K106: =CHOOSE($C$5,K103,K104,K105) -> 32.5 | L106: =CHOOSE($C$5,L103,L104,L105) -> 35 | M106: Hunterbrook转引Bloom 2021年材料约25W/片；产业链调研约65kW对应2,000片即32.5W/片；新一代产品提高单片功率
A107: 三环份额—基准 | B107: % | H107: 0.75 | I107: 0.65 | J107: 0.52 | K107: 0.47 | L107: 0.42
A108: 三环份额—乐观 | B108: % | H108: 0.85 | I108: 0.78 | J108: 0.68 | K108: 0.62 | L108: 0.57
A109: 三环份额—悲观 | B109: % | H109: 0.7 | I109: 0.52 | J109: 0.38 | K109: 0.33 | L109: 0.28
A110: 三环份额（采用值） | B110: % | H110: =(H107+(CHOOSE($C$5,H107,H108,H109)-H107)*$C$61)+$C$50*$C$61 -> 0.75 | I110: =CHOOSE($C$5,I107,I108,I109)+$C$50 -> 0.65 | J110: =CHOOSE($C$5,J107,J108,J109)+$C$50 -> 0.52 | K110: =CHOOSE($C$5,K107,K108,K109)+$C$50 -> 0.47 | L110: =CHOOSE($C$5,L107,L108,L109)+$C$50 -> 0.42 | M110: 二供Amosense 2026年三季度月产能扩至60万片；2028年前后美国受禁外国实体（PFE）规则门槛升至50%
A111: 单价—基准 | B111: 元/片 | H111: 18 | I111: 17 | J111: 16.2 | K111: 15.4 | L111: 14.6
A112: 单价—乐观 | B112: 元/片 | H112: 19.5 | I112: 18.5 | J112: 17.8 | K112: 17 | L112: 16.2
A113: 单价—悲观 | B113: 元/片 | H113: 16.5 | I113: 15.5 | J113: 14.5 | K113: 13.8 | L113: 13
A114: 单价（采用值） | B114: 元/片 | H114: =(H111+(CHOOSE($C$5,H111,H112,H113)-H111)*$C$61)*(1+$C$51*$C$61) -> 18 | I114: =CHOOSE($C$5,I111,I112,I113)*(1+$C$51) -> 17 | J114: =CHOOSE($C$5,J111,J112,J113)*(1+$C$51) -> 16.2 | K114: =CHOOSE($C$5,K111,K112,K113)*(1+$C$51) -> 15.4 | L114: =CHOOSE($C$5,L111,L112,L113)*(1+$C$51) -> 14.6 | M114: 2025A校准：330.7÷(0.725GW×33.3百万片/GW)=13.7元/片（单价×份额），按份额75%-80%推算单价约17-18元；市场流传2023年25-30元。基准2026E每GW价值量（含份额）约450百万元，与2025A约456持平
...

Sheet 收入拆解
A1: 收入拆解：量价、分部与SOFC隔膜片子模型
A2: 分部口径：2024A-2025A为2025年年报新四分部口径（与H股招股章程一致）；量价拆分为假设驱动（公司未按分部披露销量）。
A4: 项目（百万元，另注明除外） | B4: 单位 | C4: 2021A | D4: 2022A | E4: 2023A | F4: 2024A | G4: 2025A | H4: 2026E | I4: 2027E | J4: 2028E | K4: 2029E | L4: 2030E | M4: 来源/说明
A5: A. 公司口径量价（年报“产销量”，万只/万片÷1万=亿只/片）
A6: 销售量 | B6: 亿只/片 | D6: 1593.2022 | E6: 2872.5609 | F6: 3816.1069 | G6: 5329.9092 | M6: 年报“产销量情况分析”（单位万只/万片）
A7: 生产量 | B7: 亿只/片 | D7: 1848.4198 | E7: 2827.2912 | F7: 4078.6015 | G7: 5623.279
A8: 库存量 | B8: 亿只/片 | D8: 808.39338 | E8: 763.12371 | F8: 1025.6183 | G8: 1318.988
A9: 综合单价（营业收入÷销售量） | B9: 元/千只 | D9: =IFERROR(三表预测!D6*10/D6,0) -> 32.320988 | E9: =IFERROR(三表预测!E6*10/E6,0) -> 19.93583 | F9: =IFERROR(三表预测!F6*10/F6,0) -> 19.325954 | G9: =IFERROR(三表预测!G6*10/G6,0) -> 16.899263 | M9: 综合单价受产品结构影响大（MLCC小尺寸占量大、单价低），仅作趋势参考
A10: 销售量同比 | B10: % | E10: =IFERROR(E6/D6-1,0) -> 0.8030109 | F10: =IFERROR(F6/E6-1,0) -> 0.32846859 | G10: =IFERROR(G6/F6-1,0) -> 0.39668761
A11: 综合单价同比 | B11: % | E11: =IFERROR(E9/D9-1,0) -> -0.38319244 | F11: =IFERROR(F9/E9-1,0) -> -0.030591925 | G11: =IFERROR(G9/F9-1,0) -> -0.12556644
A12: 电子元件（MLCC、陶瓷封装基座、电阻等）
A13: 销量增速（假设） | B13: % | H13: =假设!H68 -> 0.52 | I13: =假设!I68 -> 0.25 | J13: =假设!J68 -> 0.16 | K13: =假设!K68 -> 0.12 | L13: =假设!L68 -> 0.1
A14: 单价变动（假设） | B14: % | H14: =假设!H72 -> 0.19 | I14: =假设!I72 -> 0.08 | J14: =假设!J72 -> 0.035 | K14: =假设!K72 -> 0 | L14: =假设!L72 -> -0.02
A15: 销量指数（2025A=100） | G15: 100 | H15: =G15*(1+H13) -> 152 | I15: =H15*(1+I13) -> 190 | J15: =I15*(1+J13) -> 220.4 | K15: =J15*(1+K13) -> 246.848 | L15: =K15*(1+L13) -> 271.5328
A16: 单价指数（2025A=100） | G16: 100 | H16: =G16*(1+H14) -> 119 | I16: =H16*(1+I14) -> 128.52 | J16: =I16*(1+J14) -> 133.0182 | K16: =J16*(1+K14) -> 133.0182 | L16: =K16*(1+L14) -> 130.35784
A17: 电子元件（MLCC、陶瓷封装基座、电阻等）收入 | B17: 百万元 | F17: 2298.159 | G17: 3308.0896 | H17: =G17*(1+H13)*(1+H14) -> 5983.6724 | I17: =H17*(1+I13)*(1+I14) -> 8077.9578 | J17: =I17*(1+J13)*(1+J14) -> 9698.3961 | K17: =J17*(1+K13)*(1+K14) -> 10862.204 | L17: =K17*(1+L13)*(1+L14) -> 11709.456 | M17: 2025年年报：电子元件3,308,089,586.22元（2024年2,298,159,034.08元）
A18: 其中：量的贡献 | B18: 百万元 | H18: =G17*H13 -> 1720.2066 | I18: =H17*I13 -> 1495.9181 | J18: =I17*J13 -> 1292.4732 | K18: =J17*K13 -> 1163.8075 | L18: =K17*L13 -> 1086.2204
A19: 其中：价的贡献 | B19: 百万元 | H19: =G17*(1+H13)*H14 -> 955.37627 | I19: =H17*(1+I13)*I14 -> 598.36724 | J19: =I17*(1+J13)*J14 -> 327.96509 | K19: =J17*(1+K13)*K14 -> 0 | L19: =K17*(1+L13)*L14 -> -238.96848
A20: 同比 | B20: % | G20: =IFERROR(G17/F17-1,0) -> 0.43945199 | H20: =IFERROR(H17/G17-1,0) -> 0.8088 | I20: =IFERROR(I17/H17-1,0) -> 0.35 | J20: =IFERROR(J17/I17-1,0) -> 0.2006 | K20: =IFERROR(K17/J17-1,0) -> 0.12 | L20: =IFERROR(L17/K17-1,0) -> 0.078
A21: 通信器件（陶瓷插芯、套筒等光通信产品）
A22: 销量增速（假设） | B22: % | H22: =假设!H76 -> 0.58 | I22: =假设!I76 -> 0.3 | J22: =假设!J76 -> 0.2 | K22: =假设!K76 -> 0.14 | L22: =假设!L76 -> 0.11
A23: 单价变动（假设） | B23: % | H23: =假设!H80 -> -0.035 | I23: =假设!I80 -> -0.04 | J23: =假设!J80 -> -0.04 | K23: =假设!K80 -> -0.035 | L23: =假设!L80 -> -0.03
A24: 销量指数（2025A=100） | G24: 100 | H24: =G24*(1+H22) -> 158 | I24: =H24*(1+I22) -> 205.4 | J24: =I24*(1+J22) -> 246.48 | K24: =J24*(1+K22) -> 280.9872 | L24: =K24*(1+L22) -> 311.89579
A25: 单价指数（2025A=100） | G25: 100 | H25: =G25*(1+H23) -> 96.5 | I25: =H25*(1+I23) -> 92.64 | J25: =I25*(1+J23) -> 88.9344 | K25: =J25*(1+K23) -> 85.821696 | L25: =K25*(1+L23) -> 83.247045
A26: 通信器件（陶瓷插芯、套筒等光通信产品）收入 | B26: 百万元 | F26: 2305.9847 | G26: 2594.3099 | H26: =G26*(1+H22)*(1+H23) -> 3955.5443 | I26: =H26*(1+I22)*(1+I23) -> 4936.5193 | J26: =I26*(1+J22)*(1+J23) -> 5686.8702 | K26: =J26*(1+K22)*(1+K23) -> 6256.1259 | L26: =K26*(1+L22)*(1+L23) -> 6735.9708 | M26: 2025年年报：通信器件2,594,309,892.31元（2024年2,305,984,655.76元）
A27: 其中：量的贡献 | B27: 百万元 | H27: =G26*H22 -> 1504.6997 | I27: =H26*I22 -> 1186.6633 | J27: =I26*J22 -> 987.30386 | K27: =J26*K22 -> 796.16183 | L27: =K26*L22 -> 688.17385
A28: 其中：价的贡献 | B28: 百万元 | H28: =G26*(1+H22)*H23 -> -143.46534 | I28: =H26*(1+I22)*I23 -> -205.6883 | J28: =I26*(1+J22)*J23 -> -236.95293 | K28: =J26*(1+K22)*K23 -> -226.90612 | L28: =K26*(1+L22)*L23 -> -208.32899
A29: 同比 | B29: % | G29: =IFERROR(G26/F26-1,0) -> 0.12503346 | H29: =IFERROR(H26/G26-1,0) -> 0.5247 | I29: =IFERROR(I26/H26-1,0) -> 0.248 | J29: =IFERROR(J26/I26-1,0) -> 0.152 | K29: =IFERROR(K26/J26-1,0) -> 0.1001 | L29: =IFERROR(L26/K26-1,0) -> 0.0767
A30: 电子及陶瓷材料（陶瓷基片/基板、电子浆料、SOFC隔膜片等）
A31: Bloom电池片层需求 | B31: GW | G31: =假设!G102 -> 0.725 | H31: =假设!H102 -> 1.45 | I31: =假设!I102 -> 2.5 | J31: =假设!J102 -> 3.2 | K31: =假设!K102 -> 3.8 | L31: =假设!L102 -> 4.4 | M31: 见“假设”SOFC子模型
A32: 单片功率 | B32: W/片 | H32: =假设!H106 -> 30 | I32: =假设!I106 -> 30 | J32: =假设!J106 -> 32.5 | K32: =假设!K106 -> 32.5 | L32: =假设!L106 -> 35
A33: 每GW隔膜片需求 | B33: 百万片/GW | H33: =IFERROR(1000/H32,0) -> 33.333333 | I33: =IFERROR(1000/I32,0) -> 33.333333 | J33: =IFERROR(1000/J32,0) -> 30.769231 | K33: =IFERROR(1000/K32,0) -> 30.769231 | L33: =IFERROR(1000/L32,0) -> 28.571429
A34: Bloom隔膜片需求 | B34: 百万片 | H34: =H31*H33 -> 48.333333 | I34: =I31*I33 -> 83.333333 | J34: =J31*J33 -> 98.461538 | K34: =K31*K33 -> 116.92308 | L34: =L31*L33 -> 125.71429
A35: 三环份额 | B35: % | H35: =假设!H110 -> 0.75 | I35: =假设!I110 -> 0.65 | J35: =假设!J110 -> 0.52 | K35: =假设!K110 -> 0.47 | L35: =假设!L110 -> 0.42
A36: 三环隔膜片出货 | B36: 百万片 | H36: =H34*H35 -> 36.25 | I36: =I34*I35 -> 54.166667 | J36: =J34*J35 -> 51.2 | K36: =K34*K35 -> 54.953846 | L36: =L34*L35 -> 52.8
A37: 单价 | B37: 元/片 | H37: =假设!H114 -> 18 | I37: =假设!I114 -> 17 | J37: =假设!J114 -> 16.2 | K37: =假设!K114 -> 15.4 | L37: =假设!L114 -> 14.6
A38: SOFC隔膜片收入 | B38: 百万元 | E38: 449.31873 | F38: 323.86965 | G38: 330.718 | H38: =H36*H37 -> 652.5 | I38: =I36*I37 -> 920.83333 | J38: =J36*J37 -> 829.44 | K38: =K36*K37 -> 846.28923 | L38: =L36*L37 -> 770.88 | M38: 历史为年报前五大客户“客户1”销售额（2023A 449,318,727.96元；2024A 323,869,648.00元；2025A 330,717,999.78元），市场普遍对应Bloom
A39: 每GW隔膜片价值量（100%份额） | B39: 百万元/GW | H39: =H33*H37 -> 600 | I39: =I33*I37 -> 566.66667 | J39: =J33*J37 -> 498.46154 | K39: =K33*K37 -> 473.84615 | L39: =L33*L37 -> 417.14286
A40: 其他电子及陶瓷材料（不含SOFC） | B40: 百万元 | F40: =F41-F38 -> 1353.3631 | G40: =G41-G38 -> 1628.66 | H40: =G40*(1+假设!H84) -> 1872.959 | I40: =H40*(1+假设!I84) -> 2097.7141 | J40: =I40*(1+假设!J84) -> 2307.4855 | K40: =J40*(1+假设!K84) -> 2492.0844 | L40: =K40*(1+假设!L84) -> 2641.6094
A41: 电子及陶瓷材料收入 | B41: 百万元 | F41: 1677.2328 | G41: 1959.378 | H41: =H40+H38 -> 2525.459 | I41: =I40+I38 -> 3018.5474 | J41: =J40+J38 -> 3136.9255 | K41: =K40+K38 -> 3338.3736 | L41: =L40+L38 -> 3412.4894 | M41: 2025年年报：电子及陶瓷材料1,959,378,016.92元（2024年1,677,232,780.51元）
A42: 设备组件、其他主营与其他业务
A43: 设备组件收入 | B43: 百万元 | F43: 536.82473 | G43: 601.75341 | H43: =G43*(1+假设!H88) -> 692.01642 | I43: =H43*(1+假设!I88) -> 775.05839 | J43: =I43*(1+假设!J88) -> 852.56423 | K43: =J43*(1+假设!K88) -> 920.76937 | L43: =K43*(1+假设!L88) -> 976.01553 | M43: 2025年年报：601,753,409.61元（2024年536,824,729.50元）
A44: 其他主营收入 | B44: 百万元 | F44: 447.93147 | G44: 404.99637 | H44: =G44*(1+假设!H92) -> 526.49528 | I44: =H44*(1+假设!I92) -> 552.82005 | J44: =I44*(1+假设!J92) -> 580.46105 | K44: =J44*(1+假设!K92) -> 609.4841 | L44: =K44*(1+假设!L92) -> 639.95831 | M44: 2025年年报：404,996,373.28元（2024年447,931,467.25元）
A45: 其他业务收入 | B45: 百万元 | F45: 108.85815 | G45: 138.62662 | H45: =假设!H96 -> 180 | I45: =假设!I96 -> 190 | J45: =假设!J96 -> 200 | K45: =假设!K96 -> 210 | L45: =假设!L96 -> 220 | M45: 2025年年报：138,626,615.77元；2026H1半年报“其他”342.6为其他主营+其他业务合计（新口径下设备组件并入“电子、通信元件及材料”）
A46: 合计与结构
A47: 营业收入合计 | B47: 百万元 | F47: =F17+F26+F41+F43+F44+F45 -> 7374.9908 | G47: =G17+G26+G41+G43+G44+G45 -> 9007.1539 | H47: =H17+H26+H41+H43+H44+H45 -> 13863.187 | I47: =I17+I26+I41+I43+I44+I45 -> 17550.903 | J47: =J17+J26+J41+J43+J44+J45 -> 20155.217 | K47: =K17+K26+K41+K43+K44+K45 -> 22196.957 | L47: =L17+L26+L41+L43+L44+L45 -> 23693.89
A48: 同比 | B48: % | G48: =IFERROR(G47/F47-1,0) -> 0.22131052 | H48: =IFERROR(H47/G47-1,0) -> 0.53913074 | I48: =IFERROR(I47/H47-1,0) -> 0.26600776 | J48: =IFERROR(J47/I47-1,0) -> 0.14838634 | K48: =IFERROR(K47/J47-1,0) -> 0.10130079 | L48: =IFERROR(L47/K47-1,0) -> 0.067438657
A49: 电子元件占比 | B49: % | F49: =IFERROR(F17/F47,0) -> 0.31161517 | G49: =IFERROR(G17/G47,0) -> 0.36727357 | H49: =IFERROR(H17/H47,0) -> 0.43162314 | I49: =IFERROR(I17/I47,0) -> 0.46025882 | J49: =IFERROR(J17/J47,0) -> 0.4811854 | K49: =IFERROR(K17/K47,0) -> 0.48935554 | L49: =IFERROR(L17/L47,0) -> 0.49419727
A50: 通信器件占比 | B50: % | F50: =IFERROR(F26/F47,0) -> 0.31267627 | G50: =IFERROR(G26/G47,0) -> 0.28802771 | H50: =IFERROR(H26/H47,0) -> 0.28532719 | I50: =IFERROR(I26/I47,0) -> 0.28126868 | J50: =IFERROR(J26/J47,0) -> 0.28215376 | K50: =IFERROR(K26/K47,0) -> 0.28184611 | L50: =IFERROR(L26/L47,0) -> 0.28429147
A51: 电子及陶瓷材料占比 | B51: % | F51: =IFERROR(F41/F47,0) -> 0.22742168 | G51: =IFERROR(G41/G47,0) -> 0.21753575 | H51: =IFERROR(H41/H47,0) -> 0.18217016 | I51: =IFERROR(I41/I47,0) -> 0.17198816 | J51: =IFERROR(J41/J47,0) -> 0.15563839 | K51: =IFERROR(K41/K47,0) -> 0.15039781 | L51: =IFERROR(L41/L47,0) -> 0.14402403
A52: 其中SOFC隔膜片占比 | B52: % | F52: =IFERROR(F38/F47,0) -> 0.043914583 | G52: =IFERROR(G38/G47,0) -> 0.036717259 | H52: =IFERROR(H38/H47,0) -> 0.047067098 | I52: =IFERROR(I38/I47,0) -> 0.052466436 | J52: =IFERROR(J38/J47,0) -> 0.04115262 | K52: =IFERROR(K38/K47,0) -> 0.038126363 | L52: =IFERROR(L38/L47,0) -> 0.032534971
A53: 设备组件占比 | B53: % | F53: =IFERROR(F43/F47,0) -> 0.072789884 | G53: =IFERROR(G43/G47,0) -> 0.066808386 | H53: =IFERROR(H43/H47,0) -> 0.049917555 | I53: =IFERROR(I43/I47,0) -> 0.044160599 | J53: =IFERROR(J43/J47,0) -> 0.042299928 | K53: =IFERROR(K43/K47,0) -> 0.041481784 | L53: =IFERROR(L43/L47,0) -> 0.04119271
A54: 收入增量拆解（同比增加额，百万元）
A55: 电子元件 | B55: 百万元 | G55: =G17-F17 -> 1009.9306 | H55: =H17-G17 -> 2675.5829 | I55: =I17-H17 -> 2094.2854 | J55: =J17-I17 -> 1620.4383 | K55: =K17-J17 -> 1163.8075 | L55: =L17-K17 -> 847.25189
A56: 通信器件 | B56: 百万元 | G56: =G26-F26 -> 288.32524 | H56: =H26-G26 -> 1361.2344 | I56: =I26-H26 -> 980.97498 | J56: =J26-I26 -> 750.35093 | K56: =K26-J26 -> 569.25571 | L56: =L26-K26 -> 479.84486
A57: 电子及陶瓷材料 | B57: 百万元 | G57: =G41-F41 -> 282.14524 | H57: =H41-G41 -> 566.081 | I57: =I41-H41 -> 493.08842 | J57: =J41-I41 -> 118.37808 | K57: =K41-J41 -> 201.44807 | L57: =L41-K41 -> 74.115831
A58: 设备组件 | B58: 百万元 | G58: =G43-F43 -> 64.92868 | H58: =H43-G43 -> 90.263012 | I58: =I43-H43 -> 83.041971 | J58: =J43-I43 -> 77.505839 | K58: =K43-J43 -> 68.205139 | L58: =L43-K43 -> 55.246162
A59: 其他主营 | B59: 百万元 | G59: =G44-F44 -> -42.935094 | H59: =H44-G44 -> 121.49891 | I59: =I44-H44 -> 26.324764 | J59: =J44-I44 -> 27.641002 | K59: =K44-J44 -> 29.023053 | L59: =L44-K44 -> 30.474205
A60: 其他业务 | B60: 百万元 | G60: =G45-F45 -> 29.768462 | H60: =H45-G45 -> 41.373384 | I60: =I45-H45 -> 10 | J60: =J45-I45 -> 10 | K60: =K45-J45 -> 10 | L60: =L45-K45 -> 10
A61: 合计 | B61: 百万元 | G61: =SUM(G55:G60) -> 1632.1631 | H61: =SUM(H55:H60) -> 4856.0336 | I61: =SUM(I55:I60) -> 3687.7155 | J61: =SUM(J55:J60) -> 2604.3142 | K61: =SUM(K55:K60) -> 2041.7395 | L61: =SUM(L55:L60) -> 1496.9329
A62: 地区结构
A63: 境外收入占比 | B63: % | D63: 0.2112 | E63: 0.2011 | F63: 0.179 | G63: 0.174 | H63: =假设!H97 -> 0.18 | I63: =假设!I97 -> 0.19 | J63: =假设!J97 -> 0.2 | K63: =假设!K97 -> 0.2 | L63: =假设!L97 -> 0.2 | M63: 年报“营业收入构成-分地区”；H股招股章程：2023-2025年海外收入占比20.3%/17.9%/17.4%
A64: 境外收入 | B64: 百万元 | H64: =H47*H63 -> 2495.3737 | I64: =I47*I63 -> 3334.6716 | J64: =J47*J63 -> 4031.0434 | K64: =K47*K63 -> 4439.3913 | L64: =L47*L63 -> 4738.7779
A65: 境内收入 | B65: 百万元 | H65: =H47-H64 -> 11367.814 | I65: =I47-I64 -> 14216.231 | J65: =J47-J64 -> 16124.174 | K65: =K47-K64 -> 17757.565 | L65: =L47-L64 -> 18955.112
A66: 半年度校验（2026H1半年报新口径：电子、通信元件及材料=电子元件+通信器件+电子及陶瓷材料+设备组件；其他=其他主营+其他业务）
A67: 2026H1 电子、通信元件及材料（实际） | B67: 百万元 | H67: 6080.7434 | M67: 2026年半年报：6,080,743,358.96元，同比+54.97%（对应2025H1可比基数约3,923.8）
A68: 2026H1 其他（实际） | B68: 百万元 | H68: =H71-H67 -> 342.58844
A69: 2026E隐含下半年 电子、通信元件及材料 | B69: 百万元 | H69: =H17+H26+H41+H43-H67 -> 7075.9488
A70: 2026E隐含下半年 其他 | B70: 百万元 | H70: =H44+H45-H68 -> 363.90684 | M70: 2025年可比：上半年约225.0、全年543.6（其他主营405.0+其他业务138.6）
A71: 2026H1营业收入（半年报） | B71: 百万元 | H71: =历史利润表!K6 -> 6423.3318
A72: 2026E隐含下半年收入 | B72: 百万元 | H72: =H47-H71 -> 7439.8557
A73: 2026E下半年/上半年 | B73: x | H73: =IFERROR(H72/H71,0) -> 1.1582549 | M73: 参照：2025年下半年/上半年约1.17x；2026Q2单季收入3,742百万元

Sheet 成本拆解
A1: 成本拆解：分部毛利率与营业成本按性质
A2: 分部毛利率为主驱动（生产人工与生产折旧偏离标定值的部分另行计入）；按性质拆分时人工来自人员模型、折旧来自资本开支模型、其他制造费用按占收入比例假设，原材料为倒挤项。
A4: 项目（百万元，另注明除外） | B4: 单位 | C4: 2021A | D4: 2022A | E4: 2023A | F4: 2024A | G4: 2025A | H4: 2026E | I4: 2027E | J4: 2028E | K4: 2029E | L4: 2030E | M4: 来源/说明
A5: A. 分部毛利率（采用值，含敏感性冲击）
A6: 电子元件 毛利率 | B6: % | F6: 0.4437 | G6: 0.423 | H6: =假设!H119 -> 0.46 | I6: =假设!I119 -> 0.47 | J6: =假设!J119 -> 0.46 | K6: =假设!K119 -> 0.45 | L6: =假设!L119 -> 0.44 | M6: 2025年年报分产品毛利率及同比增减倒推；设备组件/其他主营/其他业务按Wind主营构成
A7: 通信器件 毛利率 | B7: % | F7: 0.4393 | G7: 0.4436 | H7: =假设!H123 -> 0.46 | I7: =假设!I123 -> 0.46 | J7: =假设!J123 -> 0.45 | K7: =假设!K123 -> 0.44 | L7: =假设!L123 -> 0.44 | M7: 2025年年报分产品毛利率及同比增减倒推；设备组件/其他主营/其他业务按Wind主营构成
A8: 其他电子及陶瓷材料 毛利率 | B8: % | H8: =假设!H127 -> 0.38 | I8: =假设!I127 -> 0.38 | J8: =假设!J127 -> 0.38 | K8: =假设!K127 -> 0.37 | L8: =假设!L127 -> 0.37
A9: SOFC隔膜片 毛利率 | B9: % | H9: =假设!H131 -> 0.4 | I9: =假设!I131 -> 0.4 | J9: =假设!J131 -> 0.39 | K9: =假设!K131 -> 0.38 | L9: =假设!L131 -> 0.38
A10: 设备组件 毛利率 | B10: % | G10: 0.5846 | H10: =假设!H135 -> 0.58 | I10: =假设!I135 -> 0.58 | J10: =假设!J135 -> 0.57 | K10: =假设!K135 -> 0.57 | L10: =假设!L135 -> 0.56 | M10: 2025年年报分产品毛利率及同比增减倒推；设备组件/其他主营/其他业务按Wind主营构成
A11: 其他主营 毛利率 | B11: % | G11: 0.0911 | H11: =假设!H137 -> 0.28 | I11: =假设!I137 -> 0.2 | J11: =假设!J137 -> 0.15 | K11: =假设!K137 -> 0.12 | L11: =假设!L137 -> 0.1
A12: 其他业务 毛利率 | B12: % | G12: 0.7957 | H12: =假设!H139 -> 0.75 | I12: =假设!I139 -> 0.75 | J12: =假设!J139 -> 0.75 | K12: =假设!K139 -> 0.75 | L12: =假设!L139 -> 0.75
A13: 电子及陶瓷材料（分部合计）毛利率 | B13: % | F13: 0.4057 | G13: 0.3809 | H13: =IFERROR(1-H22/收入拆解!H41,0) -> 0.38516738 | I13: =IFERROR(1-I22/收入拆解!I41,0) -> 0.38610117 | J13: =IFERROR(1-J22/收入拆解!J41,0) -> 0.38264412 | K13: =IFERROR(1-K22/收入拆解!K41,0) -> 0.37253503 | L13: =IFERROR(1-L22/收入拆解!L41,0) -> 0.372259
A14: B. 分部营业成本
A15: 电子元件 营业成本 | B15: 百万元 | G15: 1908.6416 | H15: =收入拆解!H17*(1-H6) -> 3231.1831 | I15: =收入拆解!I17*(1-I6) -> 4281.3176 | J15: =收入拆解!J17*(1-J6) -> 5237.1339 | K15: =收入拆解!K17*(1-K6) -> 5974.212 | L15: =收入拆解!L17*(1-L6) -> 6557.2951
A16: 通信器件 营业成本 | B16: 百万元 | G16: 1443.6034 | H16: =收入拆解!H26*(1-H7) -> 2135.9939 | I16: =收入拆解!I26*(1-I7) -> 2665.7204 | J16: =收入拆解!J26*(1-J7) -> 3127.7786 | K16: =收入拆解!K26*(1-K7) -> 3503.4305 | L16: =收入拆解!L26*(1-L7) -> 3772.1436
A17: 其他电子及陶瓷材料 营业成本 | B17: 百万元 | H17: =收入拆解!H40*(1-H8) -> 1161.2346 | I17: =收入拆解!I40*(1-I8) -> 1300.5827 | J17: =收入拆解!J40*(1-J8) -> 1430.641 | K17: =收入拆解!K40*(1-K8) -> 1570.0131 | L17: =收入拆解!L40*(1-L8) -> 1664.2139
A18: SOFC隔膜片 营业成本 | B18: 百万元 | H18: =收入拆解!H38*(1-H9) -> 391.5 | I18: =收入拆解!I38*(1-I9) -> 552.5 | J18: =收入拆解!J38*(1-J9) -> 505.9584 | K18: =收入拆解!K38*(1-K9) -> 524.69932 | L18: =收入拆解!L38*(1-L9) -> 477.9456
A19: 设备组件 营业成本 | B19: 百万元 | G19: 249.9511 | H19: =收入拆解!H43*(1-H10) -> 290.6469 | I19: =收入拆解!I43*(1-I10) -> 325.52452 | J19: =收入拆解!J43*(1-J10) -> 366.60262 | K19: =收入拆解!K43*(1-K10) -> 395.93083 | L19: =收入拆解!L43*(1-L10) -> 429.44683
A20: 其他主营 营业成本 | B20: 百万元 | G20: 368.116 | H20: =收入拆解!H44*(1-H11) -> 379.07661 | I20: =收入拆解!I44*(1-I11) -> 442.25604 | J20: =收入拆解!J44*(1-J11) -> 493.39189 | K20: =收入拆解!K44*(1-K11) -> 536.34601 | L20: =收入拆解!L44*(1-L11) -> 575.96248
A21: 其他业务 营业成本 | B21: 百万元 | G21: 28.3312 | H21: =收入拆解!H45*(1-H12) -> 45 | I21: =收入拆解!I45*(1-I12) -> 47.5 | J21: =收入拆解!J45*(1-J12) -> 50 | K21: =收入拆解!K45*(1-K12) -> 52.5 | L21: =收入拆解!L45*(1-L12) -> 55
A22: 电子及陶瓷材料 营业成本（合计） | B22: 百万元 | G22: 1213.1183 | H22: =H17+H18 -> 1552.7346 | I22: =I17+I18 -> 1853.0827 | J22: =J17+J18 -> 1936.5994 | K22: =K17+K18 -> 2094.7125 | L22: =L17+L18 -> 2142.1595
A23: 分部营业成本小计（按毛利率假设） | B23: 百万元 | G23: =G15+G16+G22+G19+G20+G21 -> 5211.7617 | H23: =H15+H16+H22+H19+H20+H21 -> 7634.6351 | I23: =I15+I16+I22+I19+I20+I21 -> 9615.4014 | J23: =J15+J16+J22+J19+J20+J21 -> 11211.506 | K23: =K15+K16+K22+K19+K20+K21 -> 12557.132 | L23: =L15+L16+L22+L19+L20+L21 -> 13532.008
A24: 加：生产人工偏离标定值 | B24: 百万元 | H24: =H33-假设!H141 -> -1.9376444e-07 | I24: =I33-假设!I141 -> 3.3300057e-07 | J24: =J33-假设!J141 -> -2.489669e-07 | K24: =K33-假设!K141 -> 4.1479325e-07 | L24: =L33-假设!L141 -> -1.6101376e-07 | M24: 人数或人均薪酬假设偏离标定值时，差额直接计入营业成本（基准情景为0）
A25: 加：生产折旧摊销偏离标定值 | B25: 百万元 | H25: =H35-假设!H142 -> 1.4353236e-07 | I25: =I35-假设!I142 -> -4.5915544e-07 | J25: =J35-假设!J142 -> 3.3833021e-07 | K25: =K35-假设!K142 -> 4.5630316e-07 | L25: =L35-假设!L142 -> -4.341307e-07 | M25: 资本开支、折旧率或情景变化引起的生产折旧差额直接计入营业成本（基准情景为0）
A26: 营业成本合计 | B26: 百万元 | C26: =历史利润表!E8 -> 3186.5095 | D26: =历史利润表!F8 -> 2878.3209 | E26: =历史利润表!G8 -> 3445.5299 | F26: =历史利润表!H8 -> 4204.8637 | G26: =历史利润表!I8 -> 5211.7617 | H26: =H23+H24+H25 -> 7634.6351 | I26: =I23+I24+I25 -> 9615.4014 | J26: =J23+J24+J25 -> 11211.506 | K26: =K23+K24+K25 -> 12557.132 | L26: =L23+L24+L25 -> 13532.008
A27: 毛利合计 | B27: 百万元 | C27: =历史利润表!E6-历史利润表!E8 -> 3031.5325 | D27: =历史利润表!F6-历史利润表!F8 -> 2271.066 | E27: =历史利润表!G6-历史利润表!G8 -> 2281.1586 | F27: =收入拆解!F47-F26 -> 3170.1271 | G27: =收入拆解!G47-G26 -> 3795.3922 | H27: =收入拆解!H47-H26 -> 6228.5523 | I27: =收入拆解!I47-I26 -> 7935.5016 | J27: =收入拆解!J47-J26 -> 8943.7107 | K27: =收入拆解!K47-K26 -> 9639.8248 | L27: =收入拆解!L47-L26 -> 10161.882
A28: 综合毛利率 | B28: % | C28: =IFERROR(C27/历史利润表!E6,0) -> 0.48753812 | D28: =IFERROR(D27/历史利润表!F6,0) -> 0.44103619 | E28: =IFERROR(E27/历史利润表!G6,0) -> 0.39833817 | F28: =IFERROR(F27/历史利润表!H6,0) -> 0.42984828 | G28: =IFERROR(G27/历史利润表!I6,0) -> 0.4213753 | H28: =IFERROR(H27/收入拆解!H47,0) -> 0.44928717 | I28: =IFERROR(I27/收入拆解!I47,0) -> 0.45214207 | J28: =IFERROR(J27/收入拆解!J47,0) -> 0.44374172 | K28: =IFERROR(K27/收入拆解!K47,0) -> 0.43428588 | L28: =IFERROR(L27/收入拆解!L47,0) -> 0.42888197
A29: SOFC隔膜片毛利 | B29: 百万元 | H29: =收入拆解!H38-H18 -> 261 | I29: =收入拆解!I38-I18 -> 368.33333 | J29: =收入拆解!J38-J18 -> 323.4816 | K29: =收入拆解!K38-K18 -> 321.58991 | L29: =收入拆解!L38-L18 -> 292.9344
A30: SOFC毛利占公司毛利 | B30: % | H30: =IFERROR(H29/H27,0) -> 0.041903798 | I30: =IFERROR(I29/I27,0) -> 0.046415885 | J30: =IFERROR(J29/J27,0) -> 0.036168612 | K30: =IFERROR(K29/K27,0) -> 0.033360555 | L30: =IFERROR(L29/L27,0) -> 0.028826786
A31: C. 营业成本按性质（人工来自人员模型、生产折旧来自资本开支模型、其他制造费用按假设，原材料为倒挤项）
A32: 原材料（预测为倒挤：营业成本-人工-生产折旧-其他制造费用） | B32: 百万元 | D32: 1542.6735 | E32: 1972.6116 | F32: 2489.6812 | G32: 3315.2286 | H32: =H26-H33-H34 -> 5307.8759 | I32: =I26-I33-I34 -> 6880.1563 | J32: =J26-J33-J34 -> 8092.0546 | K32: =K26-K33-K34 -> 9088.1169 | L32: =L26-L33-L34 -> 9755.1192 | M32: 年报“营业成本构成”（工业）
A33: 人工费用 | B33: 百万元 | D33: 657.55686 | E33: 673.31081 | F33: 879.76224 | G33: 955.38895 | H33: =人员与费用!H25 -> 1128.7221 | I33: =人员与费用!I25 -> 1315.4359 | J33: =人员与费用!J25 -> 1481.1629 | K33: =人员与费用!K25 -> 1626.6781 | L33: =人员与费用!L25 -> 1765.0143
A34: 制造费用 | B34: 百万元 | D34: 678.09057 | E34: 799.60748 | F34: 835.42027 | G34: 941.14411 | H34: =H35+H36 -> 1198.0371 | I34: =I35+I36 -> 1419.8092 | J34: =J35+J36 -> 1638.289 | K34: =K35+K36 -> 1842.3369 | L34: =L35+L36 -> 2011.8741
A35: 其中：生产用折旧摊销 | B35: 百万元 | E35: =资本开支与折旧!E91*假设!$C$38 -> 513.14209 | F35: =资本开支与折旧!F91*假设!$C$38 -> 548.37793 | G35: =资本开支与折旧!G91*假设!$C$38 -> 623.44466 | H35: =资本开支与折旧!H93 -> 685.09913 | I35: =资本开支与折旧!I93 -> 770.42575 | J35: =资本开支与折旧!J93 -> 892.54598 | K35: =资本开支与折旧!K93 -> 1021.0495 | L35: =资本开支与折旧!L93 -> 1135.2002 | M35: 历史按折旧摊销总额×生产分摊比例估算
A36: 其中：能源、辅料及其他制造费用 | B36: 百万元 | E36: =E34-E35 -> 286.46539 | F36: =F34-F35 -> 287.04235 | G36: =G34-G35 -> 317.69945 | H36: =收入拆解!H47*假设!H140 -> 512.93794 | I36: =收入拆解!I47*假设!I140 -> 649.38341 | J36: =收入拆解!J47*假设!J140 -> 745.74303 | K36: =收入拆解!K47*假设!K140 -> 821.2874 | L36: =收入拆解!L47*假设!L140 -> 876.67391
A37: 校验：性质合计-营业成本 | B37: 百万元 | E37: =ROUND(E32+E33+E34-E26,1) -> 0 | F37: =ROUND(F32+F33+F34-F26,1) -> 0 | G37: =ROUND(G32+G33+G34-G26,1) -> 0 | H37: =ROUND(H32+H33+H34-H26,4) -> 0 | I37: =ROUND(I32+I33+I34-I26,4) -> 0 | J37: =ROUND(J32+J33+J34-J26,4) -> 0 | K37: =ROUND(K32+K33+K34-K26,4) -> 0 | L37: =ROUND(L32+L33+L34-L26,4) -> 0
A38: 原材料占营业成本（预测为结果，对照历史53.6%-63.6%） | B38: % | E38: =IFERROR(E32/E26,0) -> 0.57251327 | F38: =IFERROR(F32/F26,0) -> 0.59209558 | G38: =IFERROR(G32/G26,0) -> 0.63610517 | H38: =IFERROR(H32/H26,0) -> 0.69523636 | I38: =IFERROR(I32/I26,0) -> 0.71553501 | J38: =IFERROR(J32/J26,0) -> 0.72176336 | K38: =IFERROR(K32/K26,0) -> 0.72374146 | L38: =IFERROR(L32/L26,0) -> 0.72089224
A39: 人工占营业成本 | B39: % | E39: =IFERROR(E33/E26,0) -> 0.19541575 | F39: =IFERROR(F33/F26,0) -> 0.20922491 | G39: =IFERROR(G33/G26,0) -> 0.18331401 | H39: =IFERROR(H33/H26,0) -> 0.14784232 | I39: =IFERROR(I33/I26,0) -> 0.13680509 | J39: =IFERROR(J33/J26,0) -> 0.13211096 | K39: =IFERROR(K33/K26,0) -> 0.12954217 | L39: =IFERROR(L33/L26,0) -> 0.13043255
A40: 制造费用占营业成本 | B40: % | E40: =IFERROR(E34/E26,0) -> 0.23207097 | F40: =IFERROR(F34/F26,0) -> 0.19867951 | G40: =IFERROR(G34/G26,0) -> 0.1805808 | H40: =IFERROR(H34/H26,0) -> 0.15692133 | I40: =IFERROR(I34/I26,0) -> 0.1476599 | J40: =IFERROR(J34/J26,0) -> 0.14612568 | K40: =IFERROR(K34/K26,0) -> 0.14671638 | L40: =IFERROR(L34/L26,0) -> 0.14867521
A41: 其他制造费用占收入 | B41: % | E41: =IFERROR(E36/历史利润表!G6,0) -> 0.05002287 | F41: =IFERROR(F36/历史利润表!H6,0) -> 0.038921045 | G41: =IFERROR(G36/历史利润表!I6,0) -> 0.035271903 | H41: =IFERROR(H36/收入拆解!H47,0) -> 0.037 | I41: =IFERROR(I36/收入拆解!I47,0) -> 0.037 | J41: =IFERROR(J36/收入拆解!J47,0) -> 0.037 | K41: =IFERROR(K36/收入拆解!K47,0) -> 0.037 | L41: =IFERROR(L36/收入拆解!L47,0) -> 0.037 | M41: 预测为假设驱动（见“假设”）
A42: 原材料占收入 | B42: % | E42: =IFERROR(E32/历史利润表!G6,0) -> 0.34445938 | F42: =IFERROR(F32/历史利润表!H6,0) -> 0.33758431 | G42: =IFERROR(G32/历史利润表!I6,0) -> 0.36806616 | H42: =IFERROR(H32/收入拆解!H47,0) -> 0.38287558 | I42: =IFERROR(I32/收入拆解!I47,0) -> 0.39201153 | J42: =IFERROR(J32/收入拆解!J47,0) -> 0.40148685 | K42: =IFERROR(K32/收入拆解!K47,0) -> 0.40943076 | L42: =IFERROR(L32/收入拆解!L47,0) -> 0.41171456

Sheet 人员与费用
A1: 人员与期间费用：人数×人均薪酬驱动
A2: 员工人数与专业构成来自年报“公司员工情况”；职工薪酬总额取“应付职工薪酬”本期增加；费用按性质拆分来自财务报表附注。
A4: 项目（百万元，另注明除外） | B4: 单位 | C4: 2021A | D4: 2022A | E4: 2023A | F4: 2024A | G4: 2025A | H4: 2026E | I4: 2027E | J4: 2028E | K4: 2029E | L4: 2030E | M4: 来源/说明
A5: A. 员工人数（期末，人）
A6: 生产人员 | B6: 人 | E6: 9657 | F6: 10438 | G6: 13906 | H6: =G6*(1+假设!H145) -> 15991.9 | I6: =H6*(1+假设!I145) -> 17591.09 | J6: =I6*(1+假设!J145) -> 18822.466 | K6: =J6*(1+假设!K145) -> 19763.59 | L6: =K6*(1+假设!L145) -> 20554.133
A7: 销售人员 | B7: 人 | E7: 211 | F7: 188 | G7: 208 | H7: =G7*(1+假设!H147) -> 218.4 | I7: =H7*(1+假设!I147) -> 229.32 | J7: =I7*(1+假设!J147) -> 238.4928 | K7: =J7*(1+假设!K147) -> 245.64758 | L7: =K7*(1+假设!L147) -> 253.01701
A8: 技术人员 | B8: 人 | E8: 2675 | F8: 3918 | G8: 1975 | H8: =G8*(1+假设!H149) -> 2093.5 | I8: =H8*(1+假设!I149) -> 2219.11 | J8: =I8*(1+假设!J149) -> 2330.0655 | K8: =J8*(1+假设!K149) -> 2423.2681 | L8: =K8*(1+假设!L149) -> 2520.1988
A9: 财务人员 | B9: 人 | E9: 50 | F9: 44 | G9: 52 | H9: =G9*(1+假设!H151) -> 53.56 | I9: =H9*(1+假设!I151) -> 55.1668 | J9: =I9*(1+假设!J151) -> 56.821804 | K9: =J9*(1+假设!K151) -> 58.526458 | L9: =K9*(1+假设!L151) -> 60.282252
A10: 行政人员 | B10: 人 | E10: 908 | F10: 927 | G10: 1211 | H10: =G10*(1+假设!H153) -> 1271.55 | I10: =H10*(1+假设!I153) -> 1322.412 | J10: =I10*(1+假设!J153) -> 1362.0844 | K10: =J10*(1+假设!K153) -> 1402.9469 | L10: =K10*(1+假设!L153) -> 1445.0353
A11: 员工合计 | B11: 人 | E11: =SUM(E6:E10) -> 13501 | F11: =SUM(F6:F10) -> 15515 | G11: =SUM(G6:G10) -> 17352 | H11: =SUM(H6:H10) -> 19628.91 | I11: =SUM(I6:I10) -> 21417.099 | J11: =SUM(J6:J10) -> 22809.931 | K11: =SUM(K6:K10) -> 23893.979 | L11: =SUM(L6:L10) -> 24832.667
A12: 员工合计同比 | B12: % | F12: =IFERROR(F11/E11-1,0) -> 0.14917414 | G12: =IFERROR(G11/F11-1,0) -> 0.11840155 | H12: =IFERROR(H11/G11-1,0) -> 0.13121888 | I12: =IFERROR(I11/H11-1,0) -> 0.09109975 | J12: =IFERROR(J11/I11-1,0) -> 0.065033643 | K12: =IFERROR(K11/J11-1,0) -> 0.047525261 | L12: =IFERROR(L11/K11-1,0) -> 0.039285543
A13: 人均营业收入 | B13: 万元/人 | F13: =IFERROR(历史利润表!H6*100/AVERAGE(E11,F11),0) -> 50.833959 | G13: =IFERROR(历史利润表!I6*100/AVERAGE(F11,G11),0) -> 54.809711 | H13: =IFERROR(收入拆解!H47*100/AVERAGE(G11,H11),0) -> 74.974831 | I13: =IFERROR(收入拆解!I47*100/AVERAGE(H11,I11),0) -> 85.518195 | J13: =IFERROR(收入拆解!J47*100/AVERAGE(I11,J11),0) -> 91.14434 | K13: =IFERROR(收入拆解!K47*100/AVERAGE(J11,K11),0) -> 95.053955 | L13: =IFERROR(收入拆解!L47*100/AVERAGE(K11,L11),0) -> 97.252292
A14: 生产人员（平均） | B14: 人 | F14: =AVERAGE(E6,F6) -> 10047.5 | G14: =AVERAGE(F6,G6) -> 12172 | H14: =AVERAGE(G6,H6) -> 14948.95 | I14: =AVERAGE(H6,I6) -> 16791.495 | J14: =AVERAGE(I6,J6) -> 18206.778 | K14: =AVERAGE(J6,K6) -> 19293.028 | L14: =AVERAGE(K6,L6) -> 20158.861
A15: 销售人员（平均） | B15: 人 | F15: =AVERAGE(E7,F7) -> 199.5 | G15: =AVERAGE(F7,G7) -> 198 | H15: =AVERAGE(G7,H7) -> 213.2 | I15: =AVERAGE(H7,I7) -> 223.86 | J15: =AVERAGE(I7,J7) -> 233.9064 | K15: =AVERAGE(J7,K7) -> 242.07019 | L15: =AVERAGE(K7,L7) -> 249.3323
A16: 技术人员（平均） | B16: 人 | F16: =AVERAGE(E8,F8) -> 3296.5 | G16: =AVERAGE(F8,G8) -> 2946.5 | H16: =AVERAGE(G8,H8) -> 2034.25 | I16: =AVERAGE(H8,I8) -> 2156.305 | J16: =AVERAGE(I8,J8) -> 2274.5878 | K16: =AVERAGE(J8,K8) -> 2376.6668 | L16: =AVERAGE(K8,L8) -> 2471.7335
A17: 财务人员（平均） | B17: 人 | F17: =AVERAGE(E9,F9) -> 47 | G17: =AVERAGE(F9,G9) -> 48 | H17: =AVERAGE(G9,H9) -> 52.78 | I17: =AVERAGE(H9,I9) -> 54.3634 | J17: =AVERAGE(I9,J9) -> 55.994302 | K17: =AVERAGE(J9,K9) -> 57.674131 | L17: =AVERAGE(K9,L9) -> 59.404355
A18: 行政人员（平均） | B18: 人 | F18: =AVERAGE(E10,F10) -> 917.5 | G18: =AVERAGE(F10,G10) -> 1069 | H18: =AVERAGE(G10,H10) -> 1241.275 | I18: =AVERAGE(H10,I10) -> 1296.981 | J18: =AVERAGE(I10,J10) -> 1342.2482 | K18: =AVERAGE(J10,K10) -> 1382.5156 | L18: =AVERAGE(K10,L10) -> 1423.9911
A19: 平均员工合计 | B19: 人 | F19: =SUM(F14:F18) -> 14508 | G19: =SUM(G14:G18) -> 16433.5 | H19: =SUM(H14:H18) -> 18490.455 | I19: =SUM(I14:I18) -> 20523.004 | J19: =SUM(J14:J18) -> 22113.515 | K19: =SUM(K14:K18) -> 23351.955 | L19: =SUM(L14:L18) -> 24363.323
A20: B. 职工薪酬总额与人均
A21: 职工薪酬总额 | B21: 百万元 | E21: 1427.965 | F21: 1875.6708 | G21: 2102.3803 | H21: =H22*H19/100 -> 2483.8085 | I21: =I22*I19/100 -> 2894.6812 | J21: =J22*J19/100 -> 3259.3716 | K21: =K22*K19/100 -> 3579.585 | L21: =L22*L19/100 -> 3884.0007 | M21: 应付职工薪酬“本期增加”（短期薪酬+离职后福利）
A22: 人均薪酬 | B22: 万元/人 | F22: =IFERROR(F21*100/F19,0) -> 12.928528 | G22: =IFERROR(G21*100/G19,0) -> 12.79326 | H22: =G22*(1+假设!H155) -> 13.432923 | I22: =H22*(1+假设!I155) -> 14.104569 | J22: =I22*(1+假设!J155) -> 14.739274 | K22: =J22*(1+假设!K155) -> 15.328845 | L22: =K22*(1+假设!L155) -> 15.941999
A23: 人均薪酬同比 | B23: % | G23: =IFERROR(G22/F22-1,0) -> -0.01046275 | H23: =假设!H155 -> 0.05 | I23: =假设!I155 -> 0.05 | J23: =假设!J155 -> 0.045 | K23: =假设!K155 -> 0.04 | L23: =假设!L155 -> 0.04
A24: C. 职工薪酬按功能归集（上年×平均总人数变动×(1+人均薪酬增速)；2025年技术人员由3,918人降至1,975人、生产人员增加3,468人，为口径调整）
A25: 计入营业成本的人工 | B25: 百万元 | D25: 657.55686 | E25: 673.31081 | F25: 879.76224 | G25: 955.38895 | H25: =G25*IFERROR((H14+H15+H16+H17+H18)/(G14+G15+G16+G17+G18),1)*(1+假设!H155) -> 1128.7221 | I25: =H25*IFERROR((I14+I15+I16+I17+I18)/(H14+H15+H16+H17+H18),1)*(1+假设!I155) -> 1315.4359 | J25: =I25*IFERROR((J14+J15+J16+J17+J18)/(I14+I15+I16+I17+I18),1)*(1+假设!J155) -> 1481.1629 | K25: =J25*IFERROR((K14+K15+K16+K17+K18)/(J14+J15+J16+J17+J18),1)*(1+假设!K155) -> 1626.6781 | L25: =K25*IFERROR((L14+L15+L16+L17+L18)/(K14+K15+K16+K17+K18),1)*(1+假设!L155) -> 1765.0143
A26: 研发费用-职工薪酬 | B26: 百万元 | D26: 291.7834 | E26: 365.28506 | F26: 451.13867 | G26: 474.30486 | H26: =G26*IFERROR((H14+H15+H16+H17+H18)/(G14+G15+G16+G17+G18),1)*(1+假设!H155) -> 560.35649 | I26: =H26*IFERROR((I14+I15+I16+I17+I18)/(H14+H15+H16+H17+H18),1)*(1+假设!I155) -> 653.05092 | J26: =I26*IFERROR((J14+J15+J16+J17+J18)/(I14+I15+I16+I17+I18),1)*(1+假设!J155) -> 735.32642 | K26: =J26*IFERROR((K14+K15+K16+K17+K18)/(J14+J15+J16+J17+J18),1)*(1+假设!K155) -> 807.56776 | L26: =K26*IFERROR((L14+L15+L16+L17+L18)/(K14+K15+K16+K17+K18),1)*(1+假设!L155) -> 876.24508
A27: 管理费用-职工薪酬 | B27: 百万元 | D27: 318.43783 | E27: 267.22089 | F27: 218.7219 | G27: 271.23044 | H27: =G27*IFERROR((H14+H15+H16+H17+H18)/(G14+G15+G16+G17+G18),1)*(1+假设!H155) -> 320.43892 | I27: =H27*IFERROR((I14+I15+I16+I17+I18)/(H14+H15+H16+H17+H18),1)*(1+假设!I155) -> 373.44608 | J27: =I27*IFERROR((J14+J15+J16+J17+J18)/(I14+I15+I16+I17+I18),1)*(1+假设!J155) -> 420.49519 | K27: =J27*IFERROR((K14+K15+K16+K17+K18)/(J14+J15+J16+J17+J18),1)*(1+假设!K155) -> 461.80628 | L27: =K27*IFERROR((L14+L15+L16+L17+L18)/(K14+K15+K16+K17+K18),1)*(1+假设!L155) -> 501.07929
A28: 销售费用-职工薪酬 | B28: 百万元 | D28: 46.110385 | E28: 54.158358 | F28: 59.992823 | G28: 67.791417 | H28: =G28*IFERROR((H14+H15+H16+H17+H18)/(G14+G15+G16+G17+G18),1)*(1+假设!H155) -> 80.090599 | I28: =H28*IFERROR((I14+I15+I16+I17+I18)/(H14+H15+H16+H17+H18),1)*(1+假设!I155) -> 93.339223 | J28: =I28*IFERROR((J14+J15+J16+J17+J18)/(I14+I15+I16+I17+I18),1)*(1+假设!J155) -> 105.09869 | K28: =J28*IFERROR((K14+K15+K16+K17+K18)/(J14+J15+J16+J17+J18),1)*(1+假设!K155) -> 115.424 | L28: =K28*IFERROR((L14+L15+L16+L17+L18)/(K14+K15+K16+K17+K18),1)*(1+假设!L155) -> 125.2399
A29: 其他职工薪酬（计入在建工程、存货等，倒挤） | B29: 百万元 | E29: =E21-E25-E26-E27-E28 -> 67.989882 | F29: =F21-F25-F26-F27-F28 -> 266.05513 | G29: =G21-G25-G26-G27-G28 -> 333.66463 | H29: =H21-H25-H26-H27-H28 -> 394.20035 | I29: =I21-I25-I26-I27-I28 -> 459.40915 | J29: =J21-J25-J26-J27-J28 -> 517.28844 | K29: =K21-K25-K26-K27-K28 -> 568.10888 | L29: =L21-L25-L26-L27-L28 -> 616.42209 | M29: 倒挤项，反映薪酬在成本与费用之间的归集差异及存货中尚未结转的人工
A30: D. 销售费用
A31: 职工薪酬 | B31: 百万元 | D31: =D28 -> 46.110385 | E31: =E28 -> 54.158358 | F31: =F28 -> 59.992823 | G31: =G28 -> 67.791417 | H31: =H28 -> 80.090599 | I31: =I28 -> 93.339223 | J31: =J28 -> 105.09869 | K31: =K28 -> 115.424 | L31: =L28 -> 125.2399
A32: 折旧与摊销 | B32: 百万元 | H32: =资本开支与折旧!H95 -> 0 | I32: =资本开支与折旧!I95 -> 0 | J32: =资本开支与折旧!J95 -> 0 | K32: =资本开支与折旧!K95 -> 0 | L32: =资本开支与折旧!L95 -> 0
A33: 其他 | B33: 百万元 | D33: =历史利润表!F10-D31-D32 -> 11.197615 | E33: =历史利润表!G10-E31-E32 -> 20.184742 | F33: =历史利润表!H10-F31-F32 -> 19.398977 | G33: =历史利润表!I10-G31-G32 -> 25.407883 | H33: =收入拆解!H47*假设!H157 -> 24.953737 | I33: =收入拆解!I47*假设!I157 -> 31.591625 | J33: =收入拆解!J47*假设!J157 -> 36.279391 | K33: =收入拆解!K47*假设!K157 -> 39.954522 | L33: =收入拆解!L47*假设!L157 -> 42.649001
A34: 销售费用合计 | B34: 百万元 | C34: =历史利润表!E10 -> 51.3154 | D34: =历史利润表!F10 -> 57.308 | E34: =历史利润表!G10 -> 74.3431 | F34: =历史利润表!H10 -> 79.3918 | G34: =历史利润表!I10 -> 93.1993 | H34: =H31+H32+H33 -> 105.04434 | I34: =I31+I32+I33 -> 124.93085 | J34: =J31+J32+J33 -> 141.37808 | K34: =K31+K32+K33 -> 155.37852 | L34: =L31+L32+L33 -> 167.88891
A35: 销售费用率 | B35: % | C35: =IFERROR(C34/历史利润表!E6,0) -> 0.0082526622 | D35: =IFERROR(D34/历史利润表!F6,0) -> 0.011129092 | E35: =IFERROR(E34/历史利润表!G6,0) -> 0.012981866 | F35: =IFERROR(F34/历史利润表!H6,0) -> 0.010765003 | G35: =IFERROR(G34/历史利润表!I6,0) -> 0.010347253 | H35: =IFERROR(H34/收入拆解!H47,0) -> 0.0075772139 | I35: =IFERROR(I34/收入拆解!I47,0) -> 0.0071182006 | J35: =IFERROR(J34/收入拆解!J47,0) -> 0.0070144658 | K35: =IFERROR(K34/收入拆解!K47,0) -> 0.006999992 | L35: =IFERROR(L34/收入拆解!L47,0) -> 0.0070857469
A36: E. 管理费用
A37: 职工薪酬 | B37: 百万元 | D37: =D27 -> 318.43783 | E37: =E27 -> 267.22089 | F37: =F27 -> 218.7219 | G37: =G27 -> 271.23044 | H37: =H27 -> 320.43892 | I37: =I27 -> 373.44608 | J37: =J27 -> 420.49519 | K37: =K27 -> 461.80628 | L37: =L27 -> 501.07929
A38: 折旧与摊销 | B38: 百万元 | D38: 43.384565 | E38: 52.321879 | F38: 69.846522 | G38: 79.79976 | H38: =资本开支与折旧!H96 -> 87.874948 | I38: =资本开支与折旧!I96 -> 98.819455 | J38: =资本开支与折旧!J96 -> 114.48333 | K38: =资本开支与折旧!K96 -> 130.96597 | L38: =资本开支与折旧!L96 -> 145.60762
A39: 其他 | B39: 百万元 | D39: =历史利润表!F11-D37-D38 -> 117.52671 | E39: =历史利润表!G11-E37-E38 -> 109.87133 | F39: =历史利润表!H11-F37-F38 -> 121.27607 | G39: =历史利润表!I11-G37-G38 -> 129.92 | H39: =收入拆解!H47*假设!H159 -> 201.01622 | I39: =收入拆解!I47*假设!I159 -> 228.16174 | J39: =收入拆解!J47*假设!J159 -> 241.86261 | K39: =收入拆解!K47*假设!K159 -> 255.265 | L39: =收入拆解!L47*假设!L159 -> 260.63279
A40: 管理费用合计 | B40: 百万元 | C40: =历史利润表!E11 -> 453.2391 | D40: =历史利润表!F11 -> 479.3491 | E40: =历史利润表!G11 -> 429.4141 | F40: =历史利润表!H11 -> 409.8445 | G40: =历史利润表!I11 -> 480.9502 | H40: =H37+H38+H39 -> 609.33009 | I40: =I37+I38+I39 -> 700.42727 | J40: =J37+J38+J39 -> 776.84113 | K40: =K37+K38+K39 -> 848.03725 | L40: =L37+L38+L39 -> 907.31969
A41: 管理费用率 | B41: % | C41: =IFERROR(C40/历史利润表!E6,0) -> 0.072890968 | D41: =IFERROR(D40/历史利润表!F6,0) -> 0.093088577 | E41: =IFERROR(E40/历史利润表!G6,0) -> 0.074984714 | F41: =IFERROR(F40/历史利润表!H6,0) -> 0.055572205 | G41: =IFERROR(G40/历史利润表!I6,0) -> 0.053396467 | H41: =IFERROR(H40/收入拆解!H47,0) -> 0.043953102 | I41: =IFERROR(I40/收入拆解!I47,0) -> 0.039908333 | J41: =IFERROR(J40/收入拆解!J47,0) -> 0.03854293 | K41: =IFERROR(K40/收入拆解!K47,0) -> 0.038205114 | L41: =IFERROR(L40/收入拆解!L47,0) -> 0.038293404
A42: F. 研发费用
A43: 职工薪酬 | B43: 百万元 | D43: =D26 -> 291.7834 | E43: =E26 -> 365.28506 | F43: =F26 -> 451.13867 | G43: =G26 -> 474.30486 | H43: =H26 -> 560.35649 | I43: =I26 -> 653.05092 | J43: =J26 -> 735.32642 | K43: =K26 -> 807.56776 | L43: =L26 -> 876.24508
A44: 折旧与摊销 | B44: 百万元 | D44: 21.055212 | E44: 35.140623 | F44: 40.153356 | G44: 37.257676 | H44: =资本开支与折旧!H94 -> 40.682846 | I44: =资本开支与折旧!I94 -> 45.749748 | J44: =资本开支与折旧!J94 -> 53.001543 | K44: =资本开支与折旧!K94 -> 60.632392 | L44: =资本开支与折旧!L94 -> 67.410936
A45: 直接投入/材料 | B45: 百万元 | D45: 134.8229 | E45: 138.17461 | F45: 77.627928 | G45: 116.93566 | H45: =收入拆解!H47*假设!H160 -> 152.49506 | I45: =收入拆解!I47*假设!I160 -> 210.61084 | J45: =收入拆解!J47*假设!J160 -> 241.86261 | K45: =收入拆解!K47*假设!K160 -> 266.36348 | L45: =收入拆解!L47*假设!L160 -> 284.32668
A46: 其他 | B46: 百万元 | D46: =历史利润表!F12-D43-D44-D45 -> 4.51089 | E46: =历史利润表!G12-E43-E44-E45 -> 7.2059 | F46: =历史利润表!H12-F43-F44-F45 -> 14.152441 | G46: =历史利润表!I12-G43-G44-G45 -> 24.938506 | H46: =收入拆解!H47*假设!H161 -> 27.726375 | I46: =收入拆解!I47*假设!I161 -> 35.101806 | J46: =收入拆解!J47*假设!J161 -> 40.310434 | K46: =收入拆解!K47*假设!K161 -> 44.393913 | L46: =收入拆解!L47*假设!L161 -> 47.387779
A47: 研发费用合计 | B47: 百万元 | C47: =历史利润表!E12 -> 418.5388 | D47: =历史利润表!F12 -> 452.1724 | E47: =历史利润表!G12 -> 545.8062 | F47: =历史利润表!H12 -> 583.0724 | G47: =历史利润表!I12 -> 653.4367 | H47: =H43+H44+H45+H46 -> 781.26077 | I47: =I43+I44+I45+I46 -> 944.5133 | J47: =J43+J44+J45+J46 -> 1070.501 | K47: =K43+K44+K45+K46 -> 1178.9575 | L47: =L43+L44+L45+L46 -> 1275.3705
A48: 研发费用率 | B48: % | C48: =IFERROR(C47/历史利润表!E6,0) -> 0.067310385 | D48: =IFERROR(D47/历史利润表!F6,0) -> 0.08781092 | E48: =IFERROR(E47/历史利润表!G6,0) -> 0.095309218 | F48: =IFERROR(F47/历史利润表!H6,0) -> 0.079060763 | G48: =IFERROR(G47/历史利润表!I6,0) -> 0.072546412 | H48: =IFERROR(H47/收入拆解!H47,0) -> 0.056355061 | I48: =IFERROR(I47/收入拆解!I47,0) -> 0.053815653 | J48: =IFERROR(J47/收入拆解!J47,0) -> 0.053112849 | K48: =IFERROR(K47/收入拆解!K47,0) -> 0.053113477 | L48: =IFERROR(L47/收入拆解!L47,0) -> 0.053826978
A49: G. 期间费用合计
A50: 销售+管理+研发 | B50: 百万元 | C50: =C34+C40+C47 -> 923.0933 | D50: =D34+D40+D47 -> 988.8295 | E50: =E34+E40+E47 -> 1049.5634 | F50: =F34+F40+F47 -> 1072.3087 | G50: =G34+G40+G47 -> 1227.5862 | H50: =H34+H40+H47 -> 1495.6352 | I50: =I34+I40+I47 -> 1769.8714 | J50: =J34+J40+J47 -> 1988.7202 | ... L50: =L34+L40+L47 -> 2350.5791
A51: 期间费用率 | B51: % | C51: =IFERROR(C50/历史利润表!E6,0) -> 0.14845401 | D51: =IFERROR(D50/历史利润表!F6,0) -> 0.19202859 | E51: =IFERROR(E50/历史利润表!G6,0) -> 0.1832758 | F51: =IFERROR(F50/历史利润表!H6,0) -> 0.14539797 | G51: =IFERROR(G50/历史利润表!I6,0) -> 0.13629013 | H51: =IFERROR(H50/收入拆解!H47,0) -> 0.10788538 | I51: =IFERROR(I50/收入拆解!I47,0) -> 0.10084219 | J51: =IFERROR(J50/收入拆解!J47,0) -> 0.098670245 | K51: =IFERROR(K50/收入拆解!K47,0) -> 0.098318583 | L51: =IFERROR(L50/收入拆解!L47,0) -> 0.099206129
A52: 职工薪酬总额/收入 | B52: % | E52: =IFERROR(E21/历史利润表!G6,0) -> 0.24935266 | F52: =IFERROR(F21/历史利润表!H6,0) -> 0.25432856 | G52: =IFERROR(G21/历史利润表!I6,0) -> 0.23341228 | H52: =IFERROR(H21/收入拆解!H47,0) -> 0.17916576 | I52: =IFERROR(I21/收入拆解!I47,0) -> 0.16493062 | J52: =IFERROR(J21/收入拆解!J47,0) -> 0.16171354 | K52: =IFERROR(K21/收入拆解!K47,0) -> 0.16126467 | L52: =IFERROR(L21/收入拆解!L47,0) -> 0.16392415

Sheet 资本开支与折旧
A1: 资本开支、在建工程与固定资产折旧（按资产类别）
A2: 固定资产变动表来自年报附注（合并）；预测：新增资产按类别结构分配，折旧=（期初原值+50%新增-50%处置）×类别年折旧率。
A4: 项目（百万元，另注明除外） | B4: 单位 | C4: 2021A | D4: 2022A | E4: 2023A | F4: 2024A | G4: 2025A | H4: 2026E | I4: 2027E | J4: 2028E | K4: 2029E | L4: 2030E | M4: 来源/说明
A5: A. 资本开支计划
A6: 维护性资本开支（上年固定资产折旧×维护比例） | B6: 百万元 | H6: =G78*假设!H163 -> 426.85811 | I6: =H78*假设!I163 -> 470.98562 | J6: =I78*假设!J163 -> 531.27928 | K6: =J78*假设!K163 -> 617.81814 | L6: =K78*假设!L163 -> 709.08675
A7: 国内扩产（MLCC高容、光通信、陶瓷材料等） | B7: 百万元 | H7: =假设!H167 -> 900 | I7: =假设!I167 -> 1100 | J7: =假设!J167 -> 950 | K7: =假设!K167 -> 850 | L7: =假设!L167 -> 800
A8: H股募资中境外新建扩建项目资金池 | B8: 百万元 | H8: =股本与每股!$H$7*假设!$C$12 -> 2807.4481 | M8: H股招股章程：所得款项净额约41.2%投向泰国、德国新建扩建项目（燃料电池扩建、高精度压电微点胶、数据中心电子元件、通信器件）
A9: H股境外项目（泰国、德国） | B9: 百万元 | H9: =$H8*假设!H168 -> 421.11722 | I9: =$H8*假设!I168 -> 982.60685 | J9: =$H8*假设!J168 -> 842.23444 | K9: =$H8*假设!K168 -> 421.11722 | L9: =$H8*假设!L168 -> 140.37241
A10: 土地使用权、软件及长期待摊 | B10: 百万元 | H10: =假设!H169 -> 40 | I10: =假设!I169 -> 40 | J10: =假设!J169 -> 35 | K10: =假设!K169 -> 30 | L10: =假设!L169 -> 30
A11: 资本开支合计（历史=购建长期资产支付的现金；预测=当年新增长期资产投入，假设当期付现） | B11: 百万元 | C11: =历史现金流量表!E20 -> 1910.3652 | D11: =历史现金流量表!F20 -> 1124.8091 | E11: =历史现金流量表!G20 -> 545.8847 | F11: =历史现金流量表!H20 -> 639.0352 | G11: =历史现金流量表!I20 -> 580.092 | H11: =(H6+H7+H9+H10)*(1+假设!$C$56*假设!$C$61) -> 1787.9753 | I11: =(I6+I7+I9+I10)*(1+假设!$C$56) -> 2593.5925 | J11: =(J6+J7+J9+J10)*(1+假设!$C$56) -> 2358.5137 | K11: =(K6+K7+K9+K10)*(1+假设!$C$56) -> 1918.9354 | L11: =(L6+L7+L9+L10)*(1+假设!$C$56) -> 1679.4592
A12: 其中：投入在建工程（历史为权责口径的在建工程增加，与上行现金口径不勾稽） | B12: 百万元 | E12: =E18 -> 497.60518 | F12: =F18 -> 1000.027 | G12: =G18 -> 452.25401 | H12: =(H11-H10)*假设!H170 -> 1310.9815 | I12: =(I11-I10)*假设!I170 -> 1915.1944 | J12: =(J11-J10)*假设!J170 -> 1626.4596 | K12: =(K11-K10)*假设!K170 -> 1227.808 | L12: =(L11-L10)*假设!L170 -> 989.6755
A13: 其中：直接购置固定资产（历史为权责口径） | B13: 百万元 | E13: 146.59025 | F13: 98.255611 | G13: 528.81031 | H13: =H11-H10-H12 -> 436.99383 | I13: =I11-I10-I12 -> 638.39812 | J13: =J11-J10-J12 -> 697.05412 | K13: =K11-K10-K12 -> 661.12738 | L13: =L11-L10-L12 -> 659.78366
A14: 资本开支/收入 | B14: % | C14: =IFERROR(C11/历史利润表!E6,0) -> 0.30722938 | D14: =IFERROR(D11/历史利润表!F6,0) -> 0.21843554 | E14: =IFERROR(E11/历史利润表!G6,0) -> 0.095322925 | F14: =IFERROR(F11/历史利润表!H6,0) -> 0.086648949 | G14: =IFERROR(G11/历史利润表!I6,0) -> 0.064403474 | H14: =IFERROR(H11/收入拆解!H47,0) -> 0.12897289 | I14: =IFERROR(I11/收入拆解!I47,0) -> 0.14777544 | J14: =IFERROR(J11/收入拆解!J47,0) -> 0.11701753 | K14: =IFERROR(K11/收入拆解!K47,0) -> 0.086450381 | L14: =IFERROR(L11/收入拆解!L47,0) -> 0.070881531
A15: 资本开支/折旧摊销 | B15: x | C15: =IFERROR(C11/C91,0) -> 4.9298628 | D15: =IFERROR(D11/D91,0) -> 2.0662391 | E15: =IFERROR(E11/E91,0) -> 0.89572641 | F15: =IFERROR(F11/F91,0) -> 0.98119857 | G15: =IFERROR(G11/G91,0) -> 0.78344959 | H15: =IFERROR(H11/H91,0) -> 2.1974561 | I15: =IFERROR(I11/I91,0) -> 2.8345429 | J15: =IFERROR(J11/J91,0) -> 2.2249482 | ... L15: =IFERROR(L11/L91,0) -> 1.2456875
A16: B. 在建工程
A17: 期初余额 | B17: 百万元 | D17: =历史资产负债表!E25 -> 725.0642 | E17: =历史资产负债表!F25 -> 690.5385 | F17: =历史资产负债表!G25 -> 681.2029 | G17: =历史资产负债表!H25 -> 593.6648 | H17: =G20 -> 400.1746 | I17: =H20 -> 1037.7394 | J17: =I20 -> 1651.9579 | K17: =J20 -> 1634.1091 | L17: =K20 -> 1349.6983
A18: 本期增加（资本开支投入） | B18: 百万元 | E18: =E20-E17+E19 -> 497.60518 | F18: =F20-F17+F19 -> 1000.027 | G18: =G20-G17+G19 -> 452.25401 | H18: =H12 -> 1310.9815 | I18: =I12 -> 1915.1944 | J18: =J12 -> 1626.4596 | K18: =K12 -> 1227.808 | L18: =L12 -> 989.6755
A19: 转入固定资产 | B19: 百万元 | E19: 506.94078 | F19: 1087.5651 | G19: 645.74422 | H19: =H17*假设!H171+H18*假设!H172 -> 673.41667 | I19: =I17*假设!I171+I18*假设!I172 -> 1300.9759 | J19: =J17*假设!J171+J18*假设!J172 -> 1644.3084 | K19: =K17*假设!K171+K18*假设!K172 -> 1512.2188 | L19: =L17*假设!L171+L18*假设!L172 -> 1241.6915
A20: 期末余额 | B20: 百万元 | C20: =历史资产负债表!E25 -> 725.0642 | D20: =历史资产负债表!F25 -> 690.5385 | E20: =历史资产负债表!G25 -> 681.2029 | F20: =历史资产负债表!H25 -> 593.6648 | G20: =历史资产负债表!I25 -> 400.1746 | H20: =H17+H18-H19 -> 1037.7394 | I20: =I17+I18-I19 -> 1651.9579 | J20: =J17+J18-J19 -> 1634.1091 | K20: =K17+K18-K19 -> 1349.6983 | L20: =L17+L18-L19 -> 1097.6823
A21: 转固率（转入/（期初+增加）） | B21: % | E21: =IFERROR(E19/(E17+E18),0) -> 0.42666622 | F21: =IFERROR(F19/(F17+F18),0) -> 0.64688661 | G21: =IFERROR(G19/(G17+G18),0) -> 0.6173942 | H21: =IFERROR(H19/(H17+H18),0) -> 0.39354485 | I21: =IFERROR(I19/(I17+I18),0) -> 0.44057063 | J21: =IFERROR(J19/(J17+J18),0) -> 0.50155552 | K21: =IFERROR(K19/(K17+K18),0) -> 0.52839363 | L21: =IFERROR(L19/(L17+L18),0) -> 0.53077942
A22: C. 固定资产（按类别，原值/累计折旧）
A23: 房屋及建筑物 | C23: 2021A | D23: 2022A | E23: 2023A | F23: 2024A | G23: 2025A | H23: 2026E | I23: 2027E | J23: 2028E | K23: 2029E | L23: 2030E
A24: 原值期初 | B24: 百万元 | E24: 2027.6042 | F24: 2321.74 | G24: 2736.048 | H24: =G27 -> 3077.8211 | I24: =H27 -> 3401.7108 | J24: =I27 -> 4012.1053 | K24: =J27 -> 4702.4778 | L24: =K27 -> 5296.9073
A25: 本期新增（在建转入+购置+其他） | B25: 百万元 | E25: 434.42843 | F25: 450.08207 | G25: 341.77307 | H25: =(H19+H13)*假设!H173 -> 333.12315 | I25: =(I19+I13)*假设!I173 -> 620.59969 | J25: =(J19+J13)*假设!J173 -> 702.40875 | K25: =(K19+K13)*假设!K173 -> 608.53692 | L25: =(L19+L13)*假设!L173 -> 475.36878
A26: 本期减少（处置报废及其他） | B26: 百万元 | E26: 140.29264 | F26: 35.774012 | G26: 0 | H26: =H24*假设!H179 -> 9.2334633 | I26: =I24*假设!I179 -> 10.205132 | J26: =J24*假设!J179 -> 12.036316 | K26: =K24*假设!K179 -> 14.107433 | L26: =L24*假设!L179 -> 15.890722
A27: 原值期末 | B27: 百万元 | D27: 2027.6042 | E27: 2321.74 | F27: 2736.048 | G27: 3077.8211 | H27: =H24+H25-H26 -> 3401.7108 | I27: =I24+I25-I26 -> 4012.1053 | J27: =J24+J25-J26 -> 4702.4778 | K27: =K24+K25-K26 -> 5296.9073 | L27: =L24+L25-L26 -> 5756.3853
A28: 本期折旧 | B28: 百万元 | E28: 101.18511 | F28: 124.75704 | G28: 140.19385 | H28: =(H24+0.5*H25-0.5*H26)*假设!H178 -> 155.50876 | I28: =(I24+0.5*I25-0.5*I26)*假设!I178 -> 177.93159 | J28: =(J24+0.5*J25-0.5*J26)*假设!J178 -> 209.14999 | K28: =(K24+0.5*K25-0.5*K26)*假设!K178 -> 239.98524 | L28: =(L24+0.5*L25-0.5*L26)*假设!L178 -> 265.27902
A29: 折旧率（折旧/平均原值） | B29: % | E29: =IFERROR(E28/(E24+0.5*E25-0.5*E26),0) -> 0.046528904 | F29: =IFERROR(F28/(F24+0.5*F25-0.5*F26),0) -> 0.049332647 | G29: =IFERROR(G28/(G24+0.5*G25-0.5*G26),0) -> 0.048227383 | H29: =假设!H178 -> 0.048 | I29: =假设!I178 -> 0.048 | J29: =假设!J178 -> 0.048 | K29: =假设!K178 -> 0.048 | L29: =假设!L178 -> 0.048
A30: 累计折旧期初 | B30: 百万元 | E30: 388.90767 | F30: 479.50435 | G30: 581.8431 | H30: =G32 -> 723.24495 | I30: =H32 -> 872.29029 | J30: =I32 -> 1043.0783 | K30: =J32 -> 1243.8029 | L30: =K32 -> 1473.9129
A31: 累计折旧减少（处置及其他） | B31: 百万元 | E31: 10.588428 | F31: 22.418288 | G31: -1.208007 | H31: =H26*假设!H180 -> 6.4634243 | I31: =I26*假设!I180 -> 7.1435926 | J31: =J26*假设!J180 -> 8.4254212 | K31: =K26*假设!K180 -> 9.8752033 | L31: =L26*假设!L180 -> 11.123505
A32: 累计折旧期末 | B32: 百万元 | D32: 388.90767 | E32: 479.50435 | F32: 581.8431 | G32: 723.24495 | H32: =H30+H28-H31 -> 872.29029 | I32: =I30+I28-I31 -> 1043.0783 | J32: =J30+J28-J31 -> 1243.8029 | K32: =K30+K28-K31 -> 1473.9129 | L32: =L30+L28-L31 -> 1728.0684
A33: 账面净值（未扣减值） | B33: 百万元 | D33: =D27-D32 -> 1638.6965 | E33: =E27-E32 -> 1842.2356 | F33: =F27-F32 -> 2154.2049 | G33: =G27-G32 -> 2354.5761 | H33: =H27-H32 -> 2529.4205 | I33: =I27-I32 -> 2969.027 | J33: =J27-J32 -> 3458.6749 | K33: =K27-K32 -> 3822.9944 | L33: =L27-L32 -> 4028.3169
A34: 净值/原值（新旧程度） | B34: % | D34: =IFERROR(D33/D27,0) -> 0.8081935 | E34: =IFERROR(E33/E27,0) -> 0.79347198 | F34: =IFERROR(F33/F27,0) -> 0.78734178 | G34: =IFERROR(G33/G27,0) -> 0.76501397 | H34: =IFERROR(H33/H27,0) -> 0.74357306 | I34: =IFERROR(I33/I27,0) -> 0.74001722 | J34: =IFERROR(J33/J27,0) -> 0.73550053 | K34: =IFERROR(K33/K27,0) -> 0.72174085 | L34: =IFERROR(L33/L27,0) -> 0.69979973
A35: 机器设备 | C35: 2021A | D35: 2022A | E35: 2023A | F35: 2024A | G35: 2025A | H35: 2026E | I35: 2027E | J35: 2028E | K35: 2029E | L35: 2030E
A36: 原值期初 | B36: 百万元 | E36: 5551.7772 | F36: 5649.3638 | G36: 6350.3628 | H36: =G39 -> 7000.6243 | I36: =H39 -> 7584.0694 | J36: =I39 -> 8633.9328 | K36: =J39 -> 9956.0686 | L36: =K39 -> 11197.669
A37: 本期新增（在建转入+购置+其他） | B37: 百万元 | E37: 211.3066 | F37: 804.91709 | G37: 733.841 | H37: =(H19+H13)*假设!H174 -> 688.45451 | I37: =(I19+I13)*假设!I174 -> 1163.6244 | J37: =(J19+J13)*假设!J174 -> 1451.6448 | K37: =(K19+K13)*假设!K174 -> 1390.9415 | L37: =(L19+L13)*假设!L174 -> 1273.9883
A38: 本期减少（处置报废及其他） | B38: 百万元 | E38: 113.71996 | F38: 103.91809 | G38: 83.579561 | H38: =H36*假设!H183 -> 105.00936 | I38: =I36*假设!I183 -> 113.76104 | J38: =J36*假设!J183 -> 129.50899 | K38: =K36*假设!K183 -> 149.34103 | L38: =L36*假设!L183 -> 167.96504
A39: 原值期末 | B39: 百万元 | D39: 5551.7772 | E39: 5649.3638 | F39: 6350.3628 | G39: 7000.6243 | H39: =H36+H37-H38 -> 7584.0694 | I39: =I36+I37-I38 -> 8633.9328 | J39: =J36+J37-J38 -> 9956.0686 | K39: =K36+K37-K38 -> 11197.669 | L39: =L36+L37-L38 -> 12303.692
A40: 本期折旧 | B40: 百万元 | E40: 463.05371 | F40: 478.11345 | G40: 541.97172 | H40: =(H36+0.5*H37-0.5*H38)*假设!H182 -> 590.68009 | I40: =(I36+0.5*I37-0.5*I38)*假设!I182 -> 656.82909 | J40: =(J36+0.5*J37-0.5*J38)*假设!J182 -> 752.89506 | K40: =(K36+0.5*K37-0.5*K38)*假设!K182 -> 856.72637 | L40: =(L36+0.5*L37-0.5*L38)*假设!L182 -> 951.80514
A41: 折旧率（折旧/平均原值） | B41: % | E41: =IFERROR(E40/(E36+0.5*E37-0.5*E38),0) -> 0.082679739 | F41: =IFERROR(F40/(F36+0.5*F37-0.5*F38),0) -> 0.079687391 | G41: =IFERROR(G40/(G36+0.5*G37-0.5*G38),0) -> 0.081188262 | H41: =假设!H182 -> 0.081 | I41: =假设!I182 -> 0.081 | J41: =假设!J182 -> 0.081 | K41: =假设!K182 -> 0.081 | L41: =假设!L182 -> 0.081
A42: 累计折旧期初 | B42: 百万元 | E42: 2092.9064 | F42: 2476.8094 | G42: 2866.9338 | H42: =G44 -> 3343.804 | I42: =H44 -> 3850.4766 | J42: =I44 -> 4416.2969 | K42: =J44 -> 5065.5848 | L42: =K44 -> 5802.8383
A43: 累计折旧减少（处置及其他） | B43: 百万元 | E43: 79.150714 | F43: 87.989039 | G43: 65.101462 | H43: =H38*假设!H184 -> 84.007491 | I43: =I38*假设!I184 -> 91.008833 | J43: =J38*假设!J184 -> 103.60719 | K43: =K38*假设!K184 -> 119.47282 | L43: =L38*假设!L184 -> 134.37203
A44: 累计折旧期末 | B44: 百万元 | D44: 2092.9064 | E44: 2476.8094 | F44: 2866.9338 | G44: 3343.804 | H44: =H42+H40-H43 -> 3850.4766 | I44: =I42+I40-I43 -> 4416.2969 | J44: =J42+J40-J43 -> 5065.5848 | K44: =K42+K40-K43 -> 5802.8383 | L44: =L42+L40-L43 -> 6620.2714
A45: 账面净值（未扣减值） | B45: 百万元 | D45: =D39-D44 -> 3458.8708 | E45: =E39-E44 -> 3172.5545 | F45: =F39-F44 -> 3483.4291 | G45: =G39-G44 -> 3656.8202 | H45: =H39-H44 -> 3733.5928 | I45: =I39-I44 -> 4217.6359 | J45: =J39-J44 -> 4890.4838 | K45: =K39-K44 -> 5394.8308 | L45: =L39-L44 -> 5683.421
A46: 净值/原值（新旧程度） | B46: % | D46: =IFERROR(D45/D39,0) -> 0.62302047 | E46: =IFERROR(E45/E39,0) -> 0.5615773 | F46: =IFERROR(F45/F39,0) -> 0.54854016 | G46: =IFERROR(G45/G39,0) -> 0.52235631 | H46: =IFERROR(H45/H39,0) -> 0.49229412 | I46: =IFERROR(I45/I39,0) -> 0.48849534 | J46: =IFERROR(J45/J39,0) -> 0.49120632 | K46: =IFERROR(K45/K39,0) -> 0.48178159 | L46: =IFERROR(L45/L39,0) -> 0.46192808
A47: 运输设备 | C47: 2021A | D47: 2022A | E47: 2023A | F47: 2024A | G47: 2025A | H47: 2026E | I47: 2027E | J47: 2028E | K47: 2029E | L47: 2030E
A48: 原值期初 | B48: 百万元 | E48: 47.974716 | F48: 48.942447 | G48: 44.624967 | H48: =G51 -> 41.13057 | I48: =H51 -> 40.348745 | J48: =I51 -> 42.131992 | K48: =J51 -> 44.94288 | L48: =K51 -> 46.968631
A49: 本期新增（在建转入+购置+其他） | B49: 百万元 | E49: 3.479764 | F49: 1.921547 | G49: 2.30162 | H49: =(H19+H13)*假设!H175 -> 3.3312315 | I49: =(I19+I13)*假设!I175 -> 5.8181221 | J49: =(J19+J13)*假设!J175 -> 7.0240875 | K49: =(K19+K13)*假设!K175 -> 6.5200384 | L49: =(L19+L13)*假设!L175 -> 5.7044254
A50: 本期减少（处置报废及其他） | B50: 百万元 | E50: 2.512032 | F50: 6.239027 | G50: 5.796017 | H50: =H48*假设!H187 -> 4.113057 | I50: =I48*假设!I187 -> 4.0348745 | J50: =J48*假设!J187 -> 4.2131992 | K50: =K48*假设!K187 -> 4.494288 | L50: =L48*假设!L187 -> 4.6968631
A51: 原值期末 | B51: 百万元 | D51: 47.974716 | E51: 48.942447 | F51: 44.624967 | G51: 41.13057 | H51: =H48+H49-H50 -> 40.348745 | I51: =I48+I49-I50 -> 42.131992 | J51: =J48+J49-J50 -> 44.94288 | K51: =K48+K49-K50 -> 46.968631 | L51: =L48+L49-L50 -> 47.976193
A52: 本期折旧 | B52: 百万元 | E52: 4.640892 | F52: 4.597469 | G52: 4.021179 | H52: =(H48+0.5*H49-0.5*H50)*假设!H186 -> 3.9110071 | I52: =(I48+0.5*I49-0.5*I50)*假设!I186 -> 3.9590754 | J52: =(J48+0.5*J49-0.5*J50)*假设!J186 -> 4.1795939 | K52: =(K48+0.5*K49-0.5*K50)*假设!K186 -> 4.4117525 | L52: =(L48+0.5*L49-0.5*L50)*假设!L186 -> 4.5573515
A53: 折旧率（折旧/平均原值） | B53: % | E53: =IFERROR(E52/(E48+0.5*E49-0.5*E50),0) -> 0.095770281 | F53: =IFERROR(F52/(F48+0.5*F49-0.5*F50),0) -> 0.098270729 | G53: =IFERROR(G52/(G48+0.5*G49-0.5*G50),0) -> 0.093782376 | H53: =假设!H186 -> 0.096 | I53: =假设!I186 -> 0.096 | J53: =假设!J186 -> 0.096 | K53: =假设!K186 -> 0.096 | L53: =假设!L186 -> 0.096
A54: 累计折旧期初 | B54: 百万元 | E54: 25.153365 | F54: 28.295518 | G54: 27.486288 | H54: =G56 -> 26.251633 | I54: =H56 -> 26.54315 | J54: =I56 -> 26.951536 | K54: =J56 -> 27.423514 | L54: =K56 -> 27.880293
A55: 累计折旧减少（处置及其他） | B55: 百万元 | E55: 1.498738 | F55: 5.406699 | G55: 5.255834 | H55: =H50*假设!H188 -> 3.6194902 | I55: =I50*假设!I188 -> 3.5506895 | J55: =J50*假设!J188 -> 3.7076153 | K55: =K50*假设!K188 -> 3.9549735 | L55: =L50*假设!L188 -> 4.1332395
A56: 累计折旧期末 | B56: 百万元 | D56: 25.153365 | E56: 28.295518 | F56: 27.486288 | G56: 26.251633 | H56: =H54+H52-H55 -> 26.54315 | I56: =I54+I52-I55 -> 26.951536 | J56: =J54+J52-J55 -> 27.423514 | K56: =K54+K52-K55 -> 27.880293 | L56: =L54+L52-L55 -> 28.304405
A57: 账面净值（未扣减值） | B57: 百万元 | D57: =D51-D56 -> 22.821351 | E57: =E51-E56 -> 20.646929 | F57: =F51-F56 -> 17.138679 | G57: =G51-G56 -> 14.878937 | H57: =H51-H56 -> 13.805595 | I57: =I51-I56 -> 15.180456 | J57: =J51-J56 -> 17.519366 | K57: =K51-K56 -> 19.088337 | L57: =L51-L56 -> 19.671788
A58: 净值/原值（新旧程度） | B58: % | D58: =IFERROR(D57/D51,0) -> 0.47569539 | E58: =IFERROR(E57/E51,0) -> 0.4218614 | F58: =IFERROR(F57/F51,0) -> 0.38406032 | G58: =IFERROR(G57/G51,0) -> 0.36174886 | H58: =IFERROR(H57/H51,0) -> 0.34215673 | I58: =IFERROR(I57/I51,0) -> 0.36030711 | J58: =IFERROR(J57/J51,0) -> 0.38981405 | K58: =IFERROR(K57/K51,0) -> 0.40640609 | L58: =IFERROR(L57/L51,0) -> 0.41003228
A59: 电子设备及其他 | C59: 2021A | D59: 2022A | E59: 2023A | F59: 2024A | G59: 2025A | H59: 2026E | I59: 2027E | J59: 2028E | K59: 2029E | L59: 2030E
A60: 原值期初 | B60: 百万元 | E60: 156.85088 | F60: 163.57725 | G60: 169.83727 | H60: =G63 -> 278.48244 | I60: =H63 -> 355.62958 | J60: =I63 -> 494.29249 | K60: =J63 -> 659.74863 | L60: =K63 -> 807.30382
A61: 本期新增（在建转入+购置+其他） | B61: 百万元 | E61: 10.706695 | F61: 30.189694 | G61: 110.72183 | H61: =(H19+H13)*假设!H176 -> 85.501609 | I61: =(I19+I13)*假设!I176 -> 149.3318 | J61: =(J19+J13)*假设!J176 -> 180.28491 | K61: =(K19+K13)*假设!K176 -> 167.34765 | L61: =(L19+L13)*假设!L176 -> 146.41359
A62: 本期减少（处置报废及其他） | B62: 百万元 | E62: 3.980323 | F62: 23.929668 | G62: 2.076656 | H62: =H60*假设!H191 -> 8.3544733 | I62: =I60*假设!I191 -> 10.668887 | J62: =J60*假设!J191 -> 14.828775 | K62: =K60*假设!K191 -> 19.792459 | L62: =L60*假设!L191 -> 24.219115
A63: 原值期末 | B63: 百万元 | D63: 156.85088 | E63: 163.57725 | F63: 169.83727 | G63: 278.48244 | H63: =H60+H61-H62 -> 355.62958 | I63: =I60+I61-I62 -> 494.29249 | J63: =J60+J61-J62 -> 659.74863 | K63: =K60+K61-K62 -> 807.30382 | L63: =L60+L61-L62 -> 929.49829
A64: 本期折旧 | B64: 百万元 | E64: 14.301098 | F64: 16.781641 | G64: 25.243439 | H64: =(H60+0.5*H61-0.5*H62)*假设!H190 -> 34.876161 | I64: =(I60+0.5*I61-0.5*I62)*假设!I190 -> 46.745714 | J64: =(J60+0.5*J61-0.5*J62)*假设!J190 -> 63.472262 | K64: =(K60+0.5*K61-0.5*K62)*假设!K190 -> 80.687885 | L64: =(L60+0.5*L61-0.5*L62)*假设!L190 -> 95.524117
A65: 折旧率（折旧/平均原值） | B65: % | E65: =IFERROR(E64/(E60+0.5*E61-0.5*E62),0) -> 0.089262439 | F65: =IFERROR(F64/(F60+0.5*F61-0.5*F62),0) -> 0.10066533 | G65: =IFERROR(G64/(G60+0.5*G61-0.5*G62),0) -> 0.11261356 | H65: =假设!H190 -> 0.11 | I65: =假设!I190 -> 0.11 | J65: =假设!J190 -> 0.11 | K65: =假设!K190 -> 0.11 | L65: =假设!L190 -> 0.11
A66: 累计折旧期初 | B66: 百万元 | E66: 65.396865 | F66: 77.896045 | G66: 71.175755 | H66: =G68 -> 95.756225 | I66: =H68 -> 124.78425 | J66: =I68 -> 164.06175 | K66: =J68 -> 217.15387 | L66: =K68 -> 283.98703
A67: 累计折旧减少（处置及其他） | B67: 百万元 | E67: 1.801918 | F67: 23.501931 | G67: 0.662968 | H67: =H62*假设!H192 -> 5.8481313 | I67: =I62*假设!I192 -> 7.4682212 | J67: =J62*假设!J192 -> 10.380142 | K67: =K62*假设!K192 -> 13.854721 | L67: =L62*假设!L192 -> 16.95338
A68: 累计折旧期末 | B68: 百万元 | D68: 65.396865 | E68: 77.896045 | F68: 71.175755 | G68: 95.756225 | H68: =H66+H64-H67 -> 124.78425 | I68: =I66+I64-I67 -> 164.06175 | J68: =J66+J64-J67 -> 217.15387 | K68: =K66+K64-K67 -> 283.98703 | L68: =L66+L64-L67 -> 362.55777
A69: 账面净值（未扣减值） | B69: 百万元 | D69: =D63-D68 -> 91.454011 | E69: =E63-E68 -> 85.681202 | F69: =F63-F68 -> 98.661519 | G69: =G63-G68 -> 182.72622 | H69: =H63-H68 -> 230.84532 | I69: =I63-I68 -> 330.23074 | J69: =J63-J68 -> 442.59476 | K69: =K63-K68 -> 523.31679 | L69: =L63-L68 -> 566.94053
A70: 净值/原值（新旧程度） | B70: % | D70: =IFERROR(D69/D63,0) -> 0.58306344 | E70: =IFERROR(E69/E63,0) -> 0.52379658 | F70: =IFERROR(F69/F63,0) -> 0.58091794 | G70: =IFERROR(G69/G63,0) -> 0.65614987 | H70: =IFERROR(H69/H63,0) -> 0.64911733 | I70: =IFERROR(I69/I63,0) -> 0.66808772 | J70: =IFERROR(J69/J63,0) -> 0.67085363 | K70: =IFERROR(K69/K63,0) -> 0.64822781 | L70: =IFERROR(L69/L63,0) -> 0.60994252
A71: D. 固定资产合计
A72: 固定资产原值 | B72: 百万元 | D72: =D27+D39+D51+D63 -> 7784.207 | E72: =E27+E39+E51+E63 -> 8183.6235 | F72: =F27+F39+F51+F63 -> 9300.8731 | G72: =G27+G39+G51+G63 -> 10398.058 | H72: =H27+H39+H51+H63 -> 11381.759 | I72: =I27+I39+I51+I63 -> 13182.463 | J72: =J27+J39+J51+J63 -> 15363.238 | K72: =K27+K39+K51+K63 -> 17348.849 | L72: =L27+L39+L51+L63 -> 19037.552
A73: 累计折旧 | B73: 百万元 | D73: =D32+D44+D56+D68 -> 2572.3643 | E73: =E32+E44+E56+E68 -> 3062.5053 | F73: =F32+F44+F56+F68 -> 3547.4389 | G73: =G32+G44+G56+G68 -> 4189.0568 | H73: =H32+H44+H56+H68 -> 4874.0943 | I73: =I32+I44+I56+I68 -> 5650.3885 | J73: =J32+J44+J56+J68 -> 6553.965 | K73: =K32+K44+K56+K68 -> 7588.6185 | L73: =L32+L44+L56+L68 -> 8739.202
A74: 减值准备 | B74: 百万元 | D74: 21.29009 | E74: 20.360676 | F74: 19.647001 | G74: 19.460897 | H74: =G74-税务与其他损益!H17 -> 38.900897 | I74: =H74-税务与其他损益!I17 -> 38.900897 | J74: =I74-税务与其他损益!J17 -> 38.900897 | K74: =J74-税务与其他损益!K17 -> 38.900897 | L74: =K74-税务与其他损益!L17 -> 38.900897 | M74: 加上当年固定资产减值损失（见税务与其他损益）
A75: 固定资产清理 | B75: 百万元 | E75: 1.924903 | M75: 仅2023年末有余额1.92
A76: 固定资产账面价值（含清理） | B76: 百万元 | C76: =历史资产负债表!E22 -> 4312.4233 | D76: =历史资产负债表!F22 -> 5190.5526 | E76: =历史资产负债表!G22 -> 5102.6825 | F76: =历史资产负债表!H22 -> 5733.7872 | G76: =历史资产负债表!I22 -> 6189.5406 | H76: =H72-H73-H74 -> 6468.7633 | I76: =I72-I73-I74 -> 7493.1733 | J76: =J72-J73-J74 -> 8770.372 | K76: =K72-K73-K74 -> 9721.3294 | L76: =L72-L73-L74 -> 10259.449
A77: 校验：类别合计-资产负债表（历史） | B77: 百万元 | D77: =ROUND(D72-D73-D74+N(D75)-D76,1) -> 0 | E77: =ROUND(E72-E73-E74+N(E75)-E76,1) -> 0 | F77: =ROUND(F72-F73-F74+N(F75)-F76,1) -> 0 | G77: =ROUND(G72-G73-G74+N(G75)-G76,1) -> 0
A78: 固定资产折旧合计 | B78: 百万元 | C78: =历史现金流量表!E43 -> 364.7864 | D78: =历史现金流量表!F43 -> 515.7214 | E78: =E28+E40+E52+E64 -> 583.18081 | F78: =F28+F40+F52+F64 -> 624.2496 | G78: =G28+G40+G52+G64 -> 711.43019 | H78: =H28+H40+H52+H64 -> 784.97603 | I78: =I28+I40+I52+I64 -> 885.46547 | J78: =J28+J40+J52+J64 -> 1029.6969 | K78: =K28+K40+K52+K64 -> 1181.8113 | L78: =L28+L40+L52+L64 -> 1317.1656
A79: 处置资产账面净值（假设按账面价值收回现金） | B79: 百万元 | H79: =(H26-H31)+(H38-H43)+(H50-H55)+(H62-H67) -> 26.771821 | I79: =(I26-I31)+(I38-I43)+(I50-I55)+(I62-I67) -> 29.498599 | J79: =(J26-J31)+(J38-J43)+(J50-J55)+(J62-J67) -> 34.46691 | K79: =(K26-K31)+(K38-K43)+(K50-K55)+(K62-K67) -> 40.577488 | L79: =(L26-L31)+(L38-L43)+(L50-L55)+(L62-L67) -> 46.189582
A80: 固定资产+在建工程 | B80: 百万元 | C80: =C76+C20 -> 5037.4875 | D80: =D76+D20 -> 5881.0911 | E80: =E76+E20 -> 5783.8854 | F80: =F76+F20 -> 6327.452 | G80: =G76+G20 -> 6589.7152 | H80: =H76+H20 -> 7506.5027 | I80: =I76+I20 -> 9145.1311 | J80: =J76+J20 -> 10404.481 | ... L80: =L76+L20 -> 11357.132
A81: 固定资产周转率（收入/平均原值） | B81: x | E81: =IFERROR(历史利润表!G6/AVERAGE(E72,D72),0) -> 0.71727822 | F81: =IFERROR(历史利润表!H6/AVERAGE(F72,E72),0) -> 0.84360345 | G81: =IFERROR(历史利润表!I6/AVERAGE(G72,F72),0) -> 0.91448147 | H81: =IFERROR(收入拆解!H47/AVERAGE(H72,G72),0) -> 1.2730307 | I81: =IFERROR(收入拆解!I47/AVERAGE(I72,H72),0) -> 1.428981 | J81: =IFERROR(收入拆解!J47/AVERAGE(J72,I72),0) -> 1.4121368 | K81: =IFERROR(收入拆解!K47/AVERAGE(K72,J72),0) -> 1.3571104 | L81: =IFERROR(收入拆解!L47/AVERAGE(L72,K72),0) -> 1.3023486
A82: E. 无形资产、使用权资产及其他长期资产
A83: 无形资产及长期待摊期初 | B83: 百万元 | D83: =C86 -> 318.6494 | E83: =D86 -> 388.2714 | F83: =E86 -> 471.5778 | G83: =F86 -> 458.3921 | H83: =G86 -> 455.4018 | I83: =H86 -> 471.72091 | J83: =I86 -> 487.19142 | K83: =J86 -> 496.85747 | L83: =K86 -> 501.02088
A84: 本期增加（资本开支） | B84: 百万元 | H84: =H10 -> 40 | I84: =I10 -> 40 | J84: =J10 -> 35 | K84: =K10 -> 30 | L84: =L10 -> 30
A85: 本期摊销 | B85: 百万元 | C85: =历史现金流量表!E44+历史现金流量表!E46 -> 15.1737 | D85: =历史现金流量表!F44+历史现金流量表!F46 -> 17.6565 | E85: =历史现金流量表!G44+历史现金流量表!G46 -> 18.8674 | F85: =历史现金流量表!H44+历史现金流量表!H46 -> 22.0671 | G85: =历史现金流量表!I44+历史现金流量表!I46 -> 24.3228 | H85: =H83*假设!H193 -> 23.680894 | I85: =I83*假设!I193 -> 24.529487 | J85: =J83*假设!J193 -> 25.333954 | K85: =K83*假设!K193 -> 25.836588 | L85: =L83*假设!L193 -> 26.053086
A86: 无形资产及长期待摊期末 | B86: 百万元 | C86: =历史资产负债表!E28+N(历史资产负债表!E30) -> 318.6494 | D86: =历史资产负债表!F28+N(历史资产负债表!F30) -> 388.2714 | E86: =历史资产负债表!G28+N(历史资产负债表!G30) -> 471.5778 | F86: =历史资产负债表!H28+N(历史资产负债表!H30) -> 458.3921 | G86: =历史资产负债表!I28+N(历史资产负债表!I30) -> 455.4018 | H86: =H83+H84-H85 -> 471.72091 | I86: =I83+I84-I85 -> 487.19142 | J86: =J83+J84-J85 -> 496.85747 | K86: =K83+K84-K85 -> 501.02088 | L86: =L83+L84-L85 -> 504.96779
A87: 使用权资产（假设续租维持不变） | B87: 百万元 | C87: =N(历史资产负债表!E27) -> 9.2459 | D87: =N(历史资产负债表!F27) -> 36.5573 | E87: =N(历史资产负债表!G27) -> 29.9601 | F87: =N(历史资产负债表!H27) -> 24.904 | G87: =N(历史资产负债表!I27) -> 20.1651 | H87: =G87 -> 20.1651 | I87: =H87 -> 20.1651 | J87: =I87 -> 20.1651 | K87: =J87 -> 20.1651 | L87: =K87 -> 20.1651
A88: 使用权资产折旧 | B88: 百万元 | C88: =N(历史现金流量表!E45) -> 7.5487 | D88: =N(历史现金流量表!F45) -> 10.9972 | E88: =N(历史现金流量表!G45) -> 7.3842 | F88: =N(历史现金流量表!H45) -> 4.9635 | G88: =N(历史现金流量表!I45) -> 4.6801 | H88: =假设!H194 -> 5 | I88: =假设!I194 -> 5 | J88: =假设!J194 -> 5 | K88: =假设!K194 -> 5 | L88: =假设!L194 -> 5
A89: 商誉、投资性房地产及股权投资（维持不变） | B89: 百万元 | C89: =N(历史资产负债表!E19)+N(历史资产负债表!E20)+N(历史资产负债表!E21)+N(历史资产负债表!E29) -> 220.6149 | D89: =N(历史资产负债表!F19)+N(历史资产负债表!F20)+N(历史资产负债表!F21)+N(历史资产负债表!F29) -> 226.9448 | E89: =N(历史资产负债表!G19)+N(历史资产负债表!G20)+N(历史资产负债表!G21)+N(历史资产负债表!G29) -> 367.871 | F89: =N(历史资产负债表!H19)+N(历史资产负债表!H20)+N(历史资产负债表!H21)+N(历史资产负债表!H29) -> 294.9521 | G89: =N(历史资产负债表!I19)+N(历史资产负债表!I20)+N(历史资产负债表!I21)+N(历史资产负债表!I29) -> 311.2262 | H89: =G89 -> 311.2262 | I89: =H89 -> 311.2262 | J89: =I89 -> 311.2262 | K89: =J89 -> 311.2262 | L89: =K89 -> 311.2262
A90: F. 折旧摊销汇总与分摊
A91: 折旧摊销合计 | B91: 百万元 | C91: =C78+C85+C88 -> 387.5088 | D91: =D78+D85+D88 -> 544.3751 | E91: =E78+E85+E88 -> 609.43241 | F91: =F78+F85+F88 -> 651.2802 | G91: =G78+G85+G88 -> 740.43309 | H91: =H78+H85+H88 -> 813.65692 | I91: =I78+I85+I88 -> 914.99495 | J91: =J78+J85+J88 -> 1060.0309 | ... L91: =L78+L85+L88 -> 1348.2187
A92: 折旧摊销/收入 | B92: % | C92: =IFERROR(C91/历史利润表!E6,0) -> 0.062320068 | D92: =IFERROR(D91/历史利润表!F6,0) -> 0.10571649 | E92: =IFERROR(E91/历史利润表!G6,0) -> 0.10641969 | F92: =IFERROR(F91/历史利润表!H6,0) -> 0.08830929 | G92: =IFERROR(G91/历史利润表!I6,0) -> 0.082205 | H92: =IFERROR(H91/收入拆解!H47,0) -> 0.058691908 | I92: =IFERROR(I91/收入拆解!I47,0) -> 0.052133782 | J92: =IFERROR(J91/收入拆解!J47,0) -> 0.052593373 | K92: =IFERROR(K91/收入拆解!K47,0) -> 0.054631266 | L92: =IFERROR(L91/收入拆解!L47,0) -> 0.056901536
A93: 计入营业成本 | B93: 百万元 | H93: =H91*假设!$C$38 -> 685.09913 | I93: =I91*假设!$C$38 -> 770.42575 | J93: =J91*假设!$C$38 -> 892.54598 | K93: =K91*假设!$C$38 -> 1021.0495 | L93: =L91*假设!$C$38 -> 1135.2002
A94: 计入研发费用 | B94: 百万元 | H94: =H91*假设!$C$39 -> 40.682846 | I94: =I91*假设!$C$39 -> 45.749748 | J94: =J91*假设!$C$39 -> 53.001543 | K94: =K91*假设!$C$39 -> 60.632392 | L94: =L91*假设!$C$39 -> 67.410936
A95: 计入销售费用 | B95: 百万元 | H95: =H91*假设!$C$40 -> 0 | I95: =I91*假设!$C$40 -> 0 | J95: =J91*假设!$C$40 -> 0 | K95: =K91*假设!$C$40 -> 0 | L95: =L91*假设!$C$40 -> 0
A96: 计入管理费用（倒挤） | B96: 百万元 | H96: =H91-H93-H94-H95 -> 87.874948 | I96: =I91-I93-I94-I95 -> 98.819455 | J96: =J91-J93-J94-J95 -> 114.48333 | K96: =K91-K93-K94-K95 -> 130.96597 | L96: =L91-L93-L94-L95 -> 145.60762

Sheet 营运资金
A1: 营运资金明细（周转天数驱动）
A2: 历史取Wind资产负债表；存货分类来自年报附注。周转天数按期末余额计算。
A4: 项目（百万元，另注明除外） | B4: 单位 | C4: 2021A | D4: 2022A | E4: 2023A | F4: 2024A | G4: 2025A | H4: 2026E | I4: 2027E | J4: 2028E | K4: 2029E | L4: 2030E | M4: 来源/说明
A5: A. 经营性流动资产
A6: 应收票据 | B6: 百万元 | C6: =N(历史资产负债表!E8) -> 611.4843 | D6: =N(历史资产负债表!F8) -> 435.4813 | E6: =N(历史资产负债表!G8) -> 462.5221 | F6: =N(历史资产负债表!H8) -> 642.0757 | G6: =N(历史资产负债表!I8) -> 754.9216 | H6: =收入拆解!H47*假设!H196/365 -> 1063.4774 | I6: =收入拆解!I47*假设!I196/365 -> 1346.3706 | J6: =收入拆解!J47*假设!J196/365 -> 1546.1536 | K6: =收入拆解!K47*假设!K196/365 -> 1702.7802 | L6: =收入拆解!L47*假设!L196/365 -> 1817.6134
A7: 应收账款 | B7: 百万元 | C7: =N(历史资产负债表!E9) -> 1528.3267 | D7: =N(历史资产负债表!F9) -> 1197.5819 | E7: =N(历史资产负债表!G9) -> 1626.598 | F7: =N(历史资产负债表!H9) -> 1871.7507 | G7: =N(历史资产负债表!I9) -> 2159.448 | H7: =收入拆解!H47*(假设!H197+假设!$C$58)/365 -> 3342.3575 | I7: =收入拆解!I47*(假设!I197+假设!$C$58)/365 -> 4231.4506 | J7: =收入拆解!J47*(假设!J197+假设!$C$58)/365 -> 4859.34 | K7: =收入拆解!K47*(假设!K197+假设!$C$58)/365 -> 5351.595 | L7: =收入拆解!L47*(假设!L197+假设!$C$58)/365 -> 5712.4994
A8: 应收款项融资 | B8: 百万元 | C8: =N(历史资产负债表!E10) -> 137.0218 | D8: =N(历史资产负债表!F10) -> 81.9324 | E8: =N(历史资产负债表!G10) -> 170.1508 | F8: =N(历史资产负债表!H10) -> 172.5082 | G8: =N(历史资产负债表!I10) -> 345.5521 | H8: =收入拆解!H47*假设!H198/365 -> 455.77603 | I8: =收入拆解!I47*假设!I198/365 -> 577.01599 | J8: =收入拆解!J47*假设!J198/365 -> 662.63728 | K8: =收入拆解!K47*假设!K198/365 -> 729.76296 | L8: =收入拆解!L47*假设!L198/365 -> 778.97719
A9: 预付款项 | B9: 百万元 | C9: =N(历史资产负债表!E11) -> 56.4665 | D9: =N(历史资产负债表!F11) -> 22.8533 | E9: =N(历史资产负债表!G11) -> 45.7734 | F9: =N(历史资产负债表!H11) -> 62.2607 | G9: =N(历史资产负债表!I11) -> 75.5091 | H9: =成本拆解!H26*假设!H206 -> 122.15416 | I9: =成本拆解!I26*假设!I206 -> 153.84642 | J9: =成本拆解!J26*假设!J206 -> 179.3841 | K9: =成本拆解!K26*假设!K206 -> 200.91411 | L9: =成本拆解!L26*假设!L206 -> 216.51212
A10: 其他应收款 | B10: 百万元 | C10: =N(历史资产负债表!E12) -> 151.249 | D10: =N(历史资产负债表!F12) -> 83.7475 | E10: =N(历史资产负债表!G12) -> 44.234 | F10: =N(历史资产负债表!H12) -> 28.6627 | G10: =N(历史资产负债表!I12) -> 18.4395 | H10: =收入拆解!H47*假设!H207 -> 27.726375 | I10: =收入拆解!I47*假设!I207 -> 35.101806 | J10: =收入拆解!J47*假设!J207 -> 40.310434 | K10: =收入拆解!K47*假设!K207 -> 44.393913 | L10: =收入拆解!L47*假设!L207 -> 47.387779
A11: 存货-原材料（账面余额） | B11: 百万元 | E11: 440.46508 | F11: 343.24703 | G11: 406.8243 | H11: =成本拆解!H32*假设!H199/365 -> 727.10629 | I11: =成本拆解!I32*假设!I199/365 -> 942.48717 | J11: =成本拆解!J32*假设!J199/365 -> 1108.5006 | K11: =成本拆解!K32*假设!K199/365 -> 1244.9475 | L11: =成本拆解!L32*假设!L199/365 -> 1336.3177
A12: 存货-在产品及半成品（账面余额） | B12: 百万元 | E12: 749.32512 | F12: 1071.3703 | G12: 1164.7038 | H12: =成本拆解!H26*假设!H200/365 -> 1506.0102 | I12: =成本拆解!I26*假设!I200/365 -> 1896.7367 | J12: =成本拆解!J26*假设!J200/365 -> 2211.5848 | K12: =成本拆解!K26*假设!K200/365 -> 2477.0233 | L12: =成本拆解!L26*假设!L200/365 -> 2669.3275
A13: 存货-库存商品及发出商品（账面余额） | B13: 百万元 | E13: 611.84643 | F13: 840.48232 | G13: 889.9892 | H13: =成本拆解!H26*(假设!H201+假设!$C$58)/365 -> 1150.4245 | I13: =成本拆解!I26*(假设!I201+假设!$C$58)/365 -> 1448.8961 | J13: =成本拆解!J26*(假设!J201+假设!$C$58)/365 -> 1689.4051 | K13: =成本拆解!K26*(假设!K201+假设!$C$58)/365 -> 1892.1706 | L13: =成本拆解!L26*(假设!L201+假设!$C$58)/365 -> 2039.0696
A14: 存货-其他（周转材料、委托加工等） | B14: 百万元 | E14: 0 | F14: 0 | G14: 0 | H14: =成本拆解!H26*假设!H204 -> 0 | I14: =成本拆解!I26*假设!I204 -> 0 | J14: =成本拆解!J26*假设!J204 -> 0 | K14: =成本拆解!K26*假设!K204 -> 0 | L14: =成本拆解!L26*假设!L204 -> 0
A15: 存货跌价准备 | B15: 百万元 | E15: 48.038827 | F15: 74.388147 | G15: 69.794879 | H15: =(H11+H12+H13+H14)*假设!H205 -> 118.42393 | I15: =(I11+I12+I13+I14)*假设!I205 -> 150.0842 | J15: =(J11+J12+J13+J14)*假设!J205 -> 175.33217 | K15: =(K11+K12+K13+K14)*假设!K205 -> 196.49495 | L15: =(L11+L12+L13+L14)*假设!L205 -> 211.56502
A16: 存货（账面价值） | B16: 百万元 | C16: =N(历史资产负债表!E16) -> 1796.5411 | D16: =N(历史资产负债表!F16) -> 1885.8512 | E16: =N(历史资产负债表!G16) -> 1753.5978 | F16: =N(历史资产负债表!H16) -> 2180.7115 | G16: =N(历史资产负债表!I16) -> 2391.7224 | H16: =H11+H12+H13+H14-H15 -> 3265.117 | I16: =I11+I12+I13+I14-I15 -> 4138.0358 | J16: =J11+J12+J13+J14-J15 -> 4834.1584 | K16: =K11+K12+K13+K14-K15 -> 5417.6464 | L16: =L11+L12+L13+L14-L15 -> 5833.1498
A17: 校验：分类合计-资产负债表（历史） | B17: 百万元 | E17: =ROUND(E11+E12+E13+E14-E15-E16,1) -> 0 | F17: =ROUND(F11+F12+F13+F14-F15-F16,1) -> 0 | G17: =ROUND(G11+G12+G13+G14-G15-G16,1) -> 0
A18: 其他流动资产 | B18: 百万元 | C18: =N(历史资产负债表!E17) -> 259.4314 | D18: =N(历史资产负债表!F17) -> 348.8942 | E18: =N(历史资产负债表!G17) -> 488.1799 | F18: =N(历史资产负债表!H17) -> 527.8337 | G18: =N(历史资产负债表!I17) -> 519.6397 | H18: =收入拆解!H47*假设!H208 -> 554.5275 | I18: =收入拆解!I47*假设!I208 -> 702.03612 | J18: =收入拆解!J47*假设!J208 -> 806.20869 | K18: =收入拆解!K47*假设!K208 -> 887.87827 | L18: =收入拆解!L47*假设!L208 -> 947.75558
A19: 经营性流动资产合计 | B19: 百万元 | C19: =C6+C7+C8+C9+C10+C16+C18 -> 4540.5208 | D19: =D6+D7+D8+D9+D10+D16+D18 -> 4056.3418 | E19: =E6+E7+E8+E9+E10+E16+E18 -> 4591.056 | F19: =F6+F7+F8+F9+F10+F16+F18 -> 5485.8032 | G19: =G6+G7+G8+G9+G10+G16+G18 -> 6265.2324 | H19: =H6+H7+H8+H9+H10+H16+H18 -> 8831.136 | I19: =I6+I7+I8+I9+I10+I16+I18 -> 11183.857 | J19: =J6+J7+J8+J9+J10+J16+J18 -> 12928.193 | ... L19: =L6+L7+L8+L9+L10+L16+L18 -> 15353.895
A20: B. 经营性流动负债
A21: 应付票据 | B21: 百万元 | C21: =N(历史资产负债表!E37) -> 0 | D21: =N(历史资产负债表!F37) -> 27.8661 | E21: =N(历史资产负债表!G37) -> 242.5137 | F21: =N(历史资产负债表!H37) -> 521.4807 | G21: =N(历史资产负债表!I37) -> 1119.1886 | H21: =成本拆解!H26*假设!H202/365 -> 1568.7606 | I21: =成本拆解!I26*假设!I202/365 -> 1975.7674 | J21: =成本拆解!J26*假设!J202/365 -> 2303.7342 | K21: =成本拆解!K26*假设!K202/365 -> 2580.2326 | L21: =成本拆解!L26*假设!L202/365 -> 2780.5495
A22: 应付账款 | B22: 百万元 | C22: =N(历史资产负债表!E38) -> 830.1951 | D22: =N(历史资产负债表!F38) -> 607.185 | E22: =N(历史资产负债表!G38) -> 738.1858 | F22: =N(历史资产负债表!H38) -> 773.8232 | G22: =N(历史资产负债表!I38) -> 808.7966 | H22: =成本拆解!H26*假设!H203/365 -> 1255.0085 | I22: =成本拆解!I26*假设!I203/365 -> 1580.6139 | J22: =成本拆解!J26*假设!J203/365 -> 1842.9874 | K22: =成本拆解!K26*假设!K203/365 -> 2064.1861 | L22: =成本拆解!L26*假设!L203/365 -> 2224.4396
A23: 合同负债及预收款项 | B23: 百万元 | C23: =N(历史资产负债表!E39)+N(历史资产负债表!E40) -> 25.358 | D23: =N(历史资产负债表!F39)+N(历史资产负债表!F40) -> 18.6235 | E23: =N(历史资产负债表!G39)+N(历史资产负债表!G40) -> 22.6123 | F23: =N(历史资产负债表!H39)+N(历史资产负债表!H40) -> 30.7816 | G23: =N(历史资产负债表!I39)+N(历史资产负债表!I40) -> 23.8862 | H23: =收入拆解!H47*假设!H209 -> 55.45275 | I23: =收入拆解!I47*假设!I209 -> 70.203612 | J23: =收入拆解!J47*假设!J209 -> 80.620869 | K23: =收入拆解!K47*假设!K209 -> 88.787827 | L23: =收入拆解!L47*假设!L209 -> 94.775558
A24: 应付职工薪酬 | B24: 百万元 | C24: =N(历史资产负债表!E41) -> 283.548 | D24: =N(历史资产负债表!F41) -> 242.2859 | E24: =N(历史资产负债表!G41) -> 267.3971 | F24: =N(历史资产负债表!H41) -> 347.7306 | G24: =N(历史资产负债表!I41) -> 395.6466 | H24: =人员与费用!H21*假设!H210 -> 466.956 | I24: =人员与费用!I21*假设!I210 -> 544.20007 | J24: =人员与费用!J21*假设!J210 -> 612.76186 | K24: =人员与费用!K21*假设!K210 -> 672.96198 | L24: =人员与费用!L21*假设!L210 -> 730.19212
A25: 应交税费 | B25: 百万元 | C25: =N(历史资产负债表!E42) -> 54.9989 | D25: =N(历史资产负债表!F42) -> 198.0626 | E25: =N(历史资产负债表!G42) -> 157.7104 | F25: =N(历史资产负债表!H42) -> 146.4485 | G25: =N(历史资产负债表!I42) -> 213.8164 | H25: =收入拆解!H47*假设!H211 -> 291.12694 | I25: =收入拆解!I47*假设!I211 -> 368.56896 | J25: =收入拆解!J47*假设!J211 -> 423.25956 | K25: =收入拆解!K47*假设!K211 -> 466.13609 | L25: =收入拆解!L47*假设!L211 -> 497.57168
A26: 其他应付款 | B26: 百万元 | C26: =N(历史资产负债表!E43) -> 34.0223 | D26: =N(历史资产负债表!F43) -> 54.6813 | E26: =N(历史资产负债表!G43) -> 58.1247 | F26: =N(历史资产负债表!H43) -> 90.8459 | G26: =N(历史资产负债表!I43) -> 114.3282 | H26: =收入拆解!H47*假设!H212 -> 180.22144 | I26: =收入拆解!I47*假设!I212 -> 228.16174 | J26: =收入拆解!J47*假设!J212 -> 262.01782 | K26: =收入拆解!K47*假设!K212 -> 288.56044 | L26: =收入拆解!L47*假设!L212 -> 308.02056
A27: 其他流动负债 | B27: 百万元 | C27: =N(历史资产负债表!E47) -> 295.9292 | D27: =N(历史资产负债表!F47) -> 149.1519 | E27: =N(历史资产负债表!G47) -> 168.719 | F27: =N(历史资产负债表!H47) -> 203.7941 | G27: =N(历史资产负债表!I47) -> 262.1147 | H27: =收入拆解!H47*假设!H213 -> 318.85331 | I27: =收入拆解!I47*假设!I213 -> 403.67077 | J27: =收入拆解!J47*假设!J213 -> 463.56999 | K27: =收入拆解!K47*假设!K213 -> 510.53 | L27: =收入拆解!L47*假设!L213 -> 544.95946
A28: 经营性流动负债合计 | B28: 百万元 | C28: =C21+C22+C23+C24+C25+C26+C27 -> 1524.0515 | D28: =D21+D22+D23+D24+D25+D26+D27 -> 1297.8563 | E28: =E21+E22+E23+E24+E25+E26+E27 -> 1655.263 | F28: =F21+F22+F23+F24+F25+F26+F27 -> 2114.9046 | G28: =G21+G22+G23+G24+G25+G26+G27 -> 2937.7773 | H28: =H21+H22+H23+H24+H25+H26+H27 -> 4136.3796 | I28: =I21+I22+I23+I24+I25+I26+I27 -> 5171.1865 | J28: =J21+J22+J23+J24+J25+J26+J27 -> 5988.9517 | ... L28: =L21+L22+L23+L24+L25+L26+L27 -> 7180.5085
A29: C. 营运资本与周转
A30: 营运资本（经营性流动资产-经营性流动负债） | B30: 百万元 | C30: =C19-C28 -> 3016.4693 | D30: =D19-D28 -> 2758.4855 | E30: =E19-E28 -> 2935.793 | F30: =F19-F28 -> 3370.8986 | G30: =G19-G28 -> 3327.4551 | H30: =H19-H28 -> 4694.7564 | I30: =I19-I28 -> 6012.6708 | J30: =J19-J28 -> 6939.2409 | ... L30: =L19-L28 -> 8173.3869
A31: 营运资本增加 | B31: 百万元 | D31: =D30-C30 -> -257.9838 | E31: =E30-D30 -> 177.3075 | F31: =F30-E30 -> 435.1056 | G31: =G30-F30 -> -43.4435 | H31: =H30-G30 -> 1367.3013 | I31: =I30-H30 -> 1317.9144 | J31: =J30-I30 -> 926.57003 | K31: =K30-J30 -> 724.33507 | L31: =L30-K30 -> 509.81094
A32: 营运资本/收入 | B32: % | C32: =IFERROR(C30/历史利润表!E6,0) -> 0.48511562 | D32: =IFERROR(D30/历史利润表!F6,0) -> 0.53569203 | E32: =IFERROR(E30/历史利润表!G6,0) -> 0.51265107 | F32: =IFERROR(F30/历史利润表!H6,0) -> 0.45707157 | G32: =IFERROR(G30/历史利润表!I6,0) -> 0.36942359 | H32: =IFERROR(H30/收入拆解!H47,0) -> 0.33864913 | I32: =IFERROR(I30/收入拆解!I47,0) -> 0.3425847 | J32: =IFERROR(J30/收入拆解!J47,0) -> 0.34429006 | K32: =IFERROR(K30/收入拆解!K47,0) -> 0.34525345 | L32: =IFERROR(L30/收入拆解!L47,0) -> 0.34495758
A33: 应收周转天数（应收票据+账款+融资） | B33: 天 | C33: =IFERROR((C6+C7+C8)/历史利润表!E6*365,0) -> 133.65043 | D33: =IFERROR((D6+D7+D8)/历史利润表!F6*365,0) -> 121.5627 | E33: =IFERROR((E6+E7+E8)/历史利润表!G6*365,0) -> 143.99838 | F33: =IFERROR((F6+F7+F8)/历史利润表!H6*365,0) -> 132.95096 | G33: =IFERROR((G6+G7+G8)/历史利润表!I6*365,0) -> 132.10293 | H33: =IFERROR((H6+H7+H8)/收入拆解!H47*365,0) -> 128 | I33: =IFERROR((I6+I7+I8)/收入拆解!I47*365,0) -> 128 | J33: =IFERROR((J6+J7+J8)/收入拆解!J47*365,0) -> 128 | K33: =IFERROR((K6+K7+K8)/收入拆解!K47*365,0) -> 128 | L33: =IFERROR((L6+L7+L8)/收入拆解!L47*365,0) -> 128
A34: 存货周转天数 | B34: 天 | C34: =IFERROR(C16/历史利润表!E8*365,0) -> 205.78552 | D34: =IFERROR(D16/历史利润表!F8*365,0) -> 239.14487 | E34: =IFERROR(E16/历史利润表!G8*365,0) -> 185.76626 | F34: =IFERROR(F16/历史利润表!H8*365,0) -> 189.29501 | G34: =IFERROR(G16/历史利润表!I8*365,0) -> 167.50165 | H34: =IFERROR(H16/成本拆解!H26*365,0) -> 156.10015 | I34: =IFERROR(I16/成本拆解!I26*365,0) -> 157.07956 | J34: =IFERROR(J16/成本拆解!J26*365,0) -> 157.38008 | K34: =IFERROR(K16/成本拆解!K26*365,0) -> 157.47553 | L34: =IFERROR(L16/成本拆解!L26*365,0) -> 157.33805
A35: 应付周转天数（应付票据+账款） | B35: 天 | C35: =IFERROR((C21+C22)/历史利润表!E8*365,0) -> 95.095028 | D35: =IFERROR((D21+D22)/历史利润表!F8*365,0) -> 80.530858 | E35: =IFERROR((E21+E22)/历史利润表!G8*365,0) -> 103.88977 | F35: =IFERROR((F21+F22)/历史利润表!H8*365,0) -> 112.43787 | G35: =IFERROR((G21+G22)/历史利润表!I8*365,0) -> 135.02432 | H35: =IFERROR((H21+H22)/成本拆解!H26*365,0) -> 135 | I35: =IFERROR((I21+I22)/成本拆解!I26*365,0) -> 135 | J35: =IFERROR((J21+J22)/成本拆解!J26*365,0) -> 135 | K35: =IFERROR((K21+K22)/成本拆解!K26*365,0) -> 135 | L35: =IFERROR((L21+L22)/成本拆解!L26*365,0) -> 135
A36: 现金转换周期 | B36: 天 | C36: =C33+C34-C35 -> 244.34092 | D36: =D33+D34-D35 -> 280.17672 | E36: =E33+E34-E35 -> 225.87487 | F36: =F33+F34-F35 -> 209.8081 | G36: =G33+G34-G35 -> 164.58025 | H36: =H33+H34-H35 -> 149.10015 | I36: =I33+I34-I35 -> 150.07956 | J36: =J33+J34-J35 -> 150.38008 | ... L36: =L33+L34-L35 -> 150.33805
A37: 应收账款天数 | B37: 天 | C37: =IFERROR(C7/历史利润表!E6*365,0) -> 89.713007 | D37: =IFERROR(D7/历史利润表!F6*365,0) -> 84.887269 | E37: =IFERROR(E7/历史利润表!G6*365,0) -> 103.67392 | F37: =IFERROR(F7/历史利润表!H6*365,0) -> 92.635913 | G37: =IFERROR(G7/历史利润表!I6*365,0) -> 87.508055 | H37: =IFERROR(H7/收入拆解!H47*365,0) -> 88 | I37: =IFERROR(I7/收入拆解!I47*365,0) -> 88 | J37: =IFERROR(J7/收入拆解!J47*365,0) -> 88 | K37: =IFERROR(K7/收入拆解!K47*365,0) -> 88 | L37: =IFERROR(L7/收入拆解!L47*365,0) -> 88
A38: 应收票据天数 | B38: 天 | C38: =IFERROR(C6/历史利润表!E6*365,0) -> 35.89422 | D38: =IFERROR(D6/历史利润表!F6*365,0) -> 30.867883 | E38: =IFERROR(E6/历史利润表!G6*365,0) -> 29.479614 | F38: =IFERROR(F6/历史利润表!H6*365,0) -> 31.777345 | G38: =IFERROR(G6/历史利润表!I6*365,0) -> 30.591948 | H38: =IFERROR(H6/收入拆解!H47*365,0) -> 28 | I38: =IFERROR(I6/收入拆解!I47*365,0) -> 28 | J38: =IFERROR(J6/收入拆解!J47*365,0) -> 28 | K38: =IFERROR(K6/收入拆解!K47*365,0) -> 28 | L38: =IFERROR(L6/收入拆解!L47*365,0) -> 28
A39: 应收款项融资天数 | B39: 天 | C39: =IFERROR(C8/历史利润表!E6*365,0) -> 8.0432003 | D39: =IFERROR(D8/历史利润表!F6*365,0) -> 5.8075508 | E39: =IFERROR(E8/历史利润表!G6*365,0) -> 10.844844 | F39: =IFERROR(F8/历史利润表!H6*365,0) -> 8.5377046 | G39: =IFERROR(G8/历史利润表!I6*365,0) -> 14.002927 | H39: =IFERROR(H8/收入拆解!H47*365,0) -> 12 | I39: =IFERROR(I8/收入拆解!I47*365,0) -> 12 | J39: =IFERROR(J8/收入拆解!J47*365,0) -> 12 | K39: =IFERROR(K8/收入拆解!K47*365,0) -> 12 | L39: =IFERROR(L8/收入拆解!L47*365,0) -> 12
A40: 原材料天数（按原材料成本） | B40: 天 | E40: =IFERROR(E11/成本拆解!E32*365,0) -> 81.500969 | F40: =IFERROR(F11/成本拆解!F32*365,0) -> 50.321771 | G40: =IFERROR(G11/成本拆解!G32*365,0) -> 44.790537 | H40: =IFERROR(H11/成本拆解!H32*365,0) -> 50 | I40: =IFERROR(I11/成本拆解!I32*365,0) -> 50 | J40: =IFERROR(J11/成本拆解!J32*365,0) -> 50 | K40: =IFERROR(K11/成本拆解!K32*365,0) -> 50 | L40: =IFERROR(L11/成本拆解!L32*365,0) -> 50
A41: 在产品及半成品天数 | B41: 天 | E41: =IFERROR(E12/历史利润表!G8*365,0) -> 79.379276 | F41: =IFERROR(F12/历史利润表!H8*365,0) -> 92.999484 | G41: =IFERROR(G12/历史利润表!I8*365,0) -> 81.568747 | H41: =IFERROR(H12/成本拆解!H26*365,0) -> 72 | I41: =IFERROR(I12/成本拆解!I26*365,0) -> 72 | J41: =IFERROR(J12/成本拆解!J26*365,0) -> 72 | K41: =IFERROR(K12/成本拆解!K26*365,0) -> 72 | L41: =IFERROR(L12/成本拆解!L26*365,0) -> 72
A42: 库存商品及发出商品天数 | B42: 天 | E42: =IFERROR(E13/历史利润表!G8*365,0) -> 64.815559 | F42: =IFERROR(F13/历史利润表!H8*365,0) -> 72.957429 | G42: =IFERROR(G13/历史利润表!I8*365,0) -> 62.329415 | H42: =IFERROR(H13/成本拆解!H26*365,0) -> 55 | I42: =IFERROR(I13/成本拆解!I26*365,0) -> 55 | J42: =IFERROR(J13/成本拆解!J26*365,0) -> 55 | K42: =IFERROR(K13/成本拆解!K26*365,0) -> 55 | L42: =IFERROR(L13/成本拆解!L26*365,0) -> 55
A43: 应付票据天数 | B43: 天 | C43: =IFERROR(C21/历史利润表!E8*365,0) -> 0 | D43: =IFERROR(D21/历史利润表!F8*365,0) -> 3.5337014 | E43: =IFERROR(E21/历史利润表!G8*365,0) -> 25.690533 | F43: =IFERROR(F21/历史利润表!H8*365,0) -> 45.266736 | G43: =IFERROR(G21/历史利润表!I8*365,0) -> 78.381143 | H43: =IFERROR(H21/成本拆解!H26*365,0) -> 75 | I43: =IFERROR(I21/成本拆解!I26*365,0) -> 75 | J43: =IFERROR(J21/成本拆解!J26*365,0) -> 75 | K43: =IFERROR(K21/成本拆解!K26*365,0) -> 75 | L43: =IFERROR(L21/成本拆解!L26*365,0) -> 75
A44: 应付账款天数 | B44: 天 | C44: =IFERROR(C22/历史利润表!E8*365,0) -> 95.095028 | D44: =IFERROR(D22/历史利润表!F8*365,0) -> 76.997157 | E44: =IFERROR(E22/历史利润表!G8*365,0) -> 78.199239 | F44: =IFERROR(F22/历史利润表!H8*365,0) -> 67.171135 | G44: =IFERROR(G22/历史利润表!I8*365,0) -> 56.643181 | H44: =IFERROR(H22/成本拆解!H26*365,0) -> 60 | I44: =IFERROR(I22/成本拆解!I26*365,0) -> 60 | J44: =IFERROR(J22/成本拆解!J26*365,0) -> 60 | K44: =IFERROR(K22/成本拆解!K26*365,0) -> 60 | L44: =IFERROR(L22/成本拆解!L26*365,0) -> 60
A45: 存货跌价准备/存货余额 | B45: % | E45: =IFERROR(E15/(E11+E12+E13+E14),0) -> 0.026663993 | F45: =IFERROR(F15/(F11+F12+F13+F14),0) -> 0.032986634 | G45: =IFERROR(G15/(G11+G12+G13+G14),0) -> 0.028354414 | H45: =假设!H205 -> 0.035 | I45: =假设!I205 -> 0.035 | J45: =假设!J205 -> 0.035 | K45: =假设!K205 -> 0.035 | L45: =假设!L205 -> 0.035

Sheet 融资与资金
A1: 融资、资金与权益（利息按期初/平均余额，无循环引用）
A2: 货币资金由“三表预测”现金流倒挤；利息收入按期初余额计息以避免循环；有息负债按假设的净借款变动滚动。
A4: 项目（百万元，另注明除外） | B4: 单位 | C4: 2021A | D4: 2022A | E4: 2023A | F4: 2024A | G4: 2025A | H4: 2026E | I4: 2027E | J4: 2028E | K4: 2029E | L4: 2030E | M4: 来源/说明
A5: A. 货币资金、理财与定期存款
A6: 货币资金 | B6: 百万元 | C6: =历史资产负债表!E5 -> 5552.412 | D6: =历史资产负债表!F5 -> 4509.4292 | E6: =历史资产负债表!G5 -> 2841.6149 | F6: =历史资产负债表!H5 -> 3062.8452 | G6: =历史资产负债表!I5 -> 3057.7786 | H6: =三表预测!H37 -> 9327.1517 | I6: =三表预测!I37 -> 10581.358 | J6: =三表预测!J37 -> 12764.932 | K6: =三表预测!K37 -> 15978.456 | L6: =三表预测!L37 -> 19981.123
A7: 其中：受限资金 | B7: 百万元 | D7: 1.917512 | E7: 2.03805 | F7: 25.824951 | G7: 0.017313 | H7: =G7 -> 0.017313 | I7: =H7 -> 0.017313 | J7: =I7 -> 0.017313 | K7: =J7 -> 0.017313 | L7: =K7 -> 0.017313 | M7: 年报货币资金附注：使用受限的货币资金（票据保证金等）
A8: 其中：可自由使用 | B8: 百万元 | D8: =D6-D7 -> 4507.5117 | E8: =E6-E7 -> 2839.5768 | F8: =F6-F7 -> 3037.0202 | G8: =G6-G7 -> 3057.7613 | H8: =H6-H7 -> 9327.1344 | I8: =I6-I7 -> 10581.341 | J8: =J6-J7 -> 12764.915 | K8: =K6-K7 -> 15978.439 | L8: =L6-L7 -> 19981.106
A9: 交易性金融资产（银行理财、结构性存款） | B9: 百万元 | C9: =历史资产负债表!E6 -> 2693.5949 | D9: =历史资产负债表!F6 -> 4255.0144 | E9: =历史资产负债表!G6 -> 3846.7081 | F9: =历史资产负债表!H6 -> 5053.3869 | G9: =历史资产负债表!I6 -> 3758.5116 | H9: =G9+假设!H221 -> 3758.5116 | I9: =H9+假设!I221 -> 3758.5116 | J9: =I9+假设!J221 -> 3758.5116 | K9: =J9+假设!K221 -> 3758.5116 | L9: =K9+假设!L221 -> 3758.5116
A10: 其他非流动资产-定期存款/大额存单 | B10: 百万元 | D10: 0 | E10: 3590.7033 | F10: 2930.2505 | G10: 5850.9937 | H10: =G10+假设!H222 -> 5850.9937 | I10: =H10+假设!I222 -> 5850.9937 | J10: =I10+假设!J222 -> 5850.9937 | K10: =J10+假设!K222 -> 5850.9937 | L10: =K10+假设!L222 -> 5850.9937
A11: 其他非流动资产-预付工程设备款及其他 | B11: 百万元 | D11: =历史资产负债表!F32-D10 -> 52.3243 | E11: =历史资产负债表!G32-E10 -> 121.42397 | F11: =历史资产负债表!H32-F10 -> 30.608608 | G11: =历史资产负债表!I32-G10 -> 33.128604 | H11: =G11 -> 33.128604 | I11: =H11 -> 33.128604 | J11: =I11 -> 33.128604 | K11: =J11 -> 33.128604 | L11: =K11 -> 33.128604
A12: 其他非流动资产合计 | B12: 百万元 | C12: =历史资产负债表!E32 -> 148.8167 | D12: =历史资产负债表!F32 -> 52.3243 | E12: =历史资产负债表!G32 -> 3712.1273 | F12: =历史资产负债表!H32 -> 2960.8591 | G12: =历史资产负债表!I32 -> 5884.1223 | H12: =H10+H11 -> 5884.1223 | I12: =I10+I11 -> 5884.1223 | J12: =J10+J11 -> 5884.1223 | K12: =K10+K11 -> 5884.1223 | L12: =L10+L11 -> 5884.1223
A13: B. 利息收入与理财收益
A14: 活期及短期存款利息 | B14: 百万元 | H14: =G8*假设!H216 -> 67.270748 | I14: =H8*假设!I216 -> 167.88842 | J14: =I8*假设!J216 -> 179.88279 | K14: =J8*假设!K216 -> 204.23864 | L14: =K8*假设!L216 -> 255.65502
A15: 定期存款/大额存单利息 | B15: 百万元 | H15: =G10*假设!H218 -> 134.57286 | I15: =H10*假设!I218 -> 122.87087 | J15: =I10*假设!J218 -> 117.01987 | K15: =J10*假设!K218 -> 111.16888 | L15: =K10*假设!L218 -> 111.16888
A16: H股募资款当年利息（按在外天数） | B16: 百万元 | H16: =股本与每股!H7*假设!H216*假设!$C$11/365 -> 70.643595 | I16: =股本与每股!I7*假设!I216*假设!$C$11/365 -> 0 | J16: =股本与每股!J7*假设!J216*假设!$C$11/365 -> 0 | K16: =股本与每股!K7*假设!K216*假设!$C$11/365 -> 0 | L16: =股本与每股!L7*假设!L216*假设!$C$11/365 -> 0
A17: 利息收入合计 | B17: 百万元 | C17: =历史利润表!E15 -> 103.223 | D17: =历史利润表!F15 -> 154.5883 | E17: =历史利润表!G15 -> 174.943 | F17: =历史利润表!H15 -> 203.5985 | G17: =历史利润表!I15 -> 196.88 | H17: =H14+H15+H16 -> 272.4872 | I17: =I14+I15+I16 -> 290.75929 | J17: =J14+J15+J16 -> 296.90267 | K17: =K14+K15+K16 -> 315.40752 | L17: =L14+L15+L16 -> 366.8239
A18: 综合利息收益率（利息收入/期初货币资金+其他非流动资产） | B18: % | D18: =IFERROR(D17/(C6+C12),0) -> 0.027114909 | E18: =IFERROR(E17/(D6+D12),0) -> 0.038349946 | F18: =IFERROR(F17/(E6+E12),0) -> 0.031065992 | G18: =IFERROR(G17/(F6+F12),0) -> 0.032684207 | H18: =IFERROR(H17/(G6+G12),0) -> 0.030473073 | I18: =IFERROR(I17/(H6+H12),0) -> 0.019114723 | J18: =IFERROR(J17/(I6+I12),0) -> 0.018031825 | K18: =IFERROR(K17/(J6+J12),0) -> 0.016912789 | L18: =IFERROR(L17/(K6+K12),0) -> 0.01677862
A19: 投资收益+公允价值变动收益 | B19: 百万元 | C19: =N(历史利润表!E17)+N(历史利润表!E19) -> 74.986 | D19: =N(历史利润表!F17)+N(历史利润表!F19) -> 117.738 | E19: =N(历史利润表!G17)+N(历史利润表!G19) -> 111.5562 | F19: =N(历史利润表!H17)+N(历史利润表!H19) -> 66.8886 | G19: =N(历史利润表!I17)+N(历史利润表!I19) -> 72.1716 | H19: =G9*假设!H220 -> 60.136186 | I19: =H9*假设!I220 -> 56.377674 | J19: =I9*假设!J220 -> 56.377674 | K19: =J9*假设!K220 -> 56.377674 | L19: =K9*假设!L220 -> 56.377674
A20: C. 有息负债与利息支出
A21: 短期借款 | B21: 百万元 | C21: =N(历史资产负债表!E35) -> 42.1648 | D21: =N(历史资产负债表!F35) -> 151.8424 | E21: =N(历史资产负债表!G35) -> 740.5347 | F21: =N(历史资产负债表!H35) -> 474.7949 | G21: =N(历史资产负债表!I35) -> 539.4178 | H21: =G21+假设!H223 -> 539.4178 | I21: =H21+假设!I223 -> 539.4178 | J21: =I21+假设!J223 -> 539.4178 | K21: =J21+假设!K223 -> 539.4178 | L21: =K21+假设!L223 -> 539.4178
A22: 长期借款（含一年内到期） | B22: 百万元 | C22: =N(历史资产负债表!E49)+N(历史资产负债表!E46) -> 7.7844 | D22: =N(历史资产负债表!F49)+N(历史资产负债表!F46) -> 33.593 | E22: =N(历史资产负债表!G49)+N(历史资产负债表!G46) -> 4.7445 | F22: =N(历史资产负债表!H49)+N(历史资产负债表!H46) -> 4.5523 | G22: =N(历史资产负债表!I49)+N(历史资产负债表!I46) -> 28.2196 | H22: =G22+假设!H224 -> 28.2196 | I22: =H22+假设!I224 -> 28.2196 | J22: =I22+假设!J224 -> 28.2196 | K22: =J22+假设!K224 -> 28.2196 | L22: =K22+假设!L224 -> 28.2196
A23: 有息负债合计 | B23: 百万元 | C23: =C21+C22 -> 49.9492 | D23: =D21+D22 -> 185.4354 | E23: =E21+E22 -> 745.2792 | F23: =F21+F22 -> 479.3472 | G23: =G21+G22 -> 567.6374 | H23: =H21+H22 -> 567.6374 | I23: =I21+I22 -> 567.6374 | J23: =J21+J22 -> 567.6374 | ... L23: =L21+L22 -> 567.6374
A24: 租赁负债（假设维持不变） | B24: 百万元 | C24: =N(历史资产负债表!E50) -> 1.7371 | D24: =N(历史资产负债表!F50) -> 30.6415 | E24: =N(历史资产负债表!G50) -> 26.5735 | F24: =N(历史资产负债表!H50) -> 22.2459 | G24: =N(历史资产负债表!I50) -> 18.7998 | H24: =G24 -> 18.7998 | I24: =H24 -> 18.7998 | J24: =I24 -> 18.7998 | K24: =J24 -> 18.7998 | L24: =K24 -> 18.7998
A25: 利息费用 | B25: 百万元 | C25: =历史利润表!E14 -> 5.6211 | D25: =历史利润表!F14 -> 8.8993 | E25: =历史利润表!G14 -> 22.4881 | F25: =历史利润表!H14 -> 27.7001 | G25: =历史利润表!I14 -> 20.396 | H25: =AVERAGE(G21,H21)*假设!H225+AVERAGE(G22,H22)*假设!H226+H24*假设!H227 -> 17.969112 | I25: =AVERAGE(H21,I21)*假设!I225+AVERAGE(H22,I22)*假设!I226+I24*假设!I227 -> 17.969112 | J25: =AVERAGE(I21,J21)*假设!J225+AVERAGE(I22,J22)*假设!J226+J24*假设!J227 -> 17.969112 | K25: =AVERAGE(J21,K21)*假设!K225+AVERAGE(J22,K22)*假设!K226+K24*假设!K227 -> 17.969112 | L25: =AVERAGE(K21,L21)*假设!L225+AVERAGE(K22,L22)*假设!L226+L24*假设!L227 -> 17.969112
A26: 平均借款成本（利息费用/平均有息负债+租赁负债） | B26: % | D26: =IFERROR(D25/AVERAGE(C23+C24,D23+D24),0) -> 0.06647142 | E26: =IFERROR(E25/AVERAGE(D23+D24,E23+E24),0) -> 0.045525714 | F26: =IFERROR(F25/AVERAGE(E23+E24,F23+F24),0) -> 0.043504168 | G26: =IFERROR(G25/AVERAGE(F23+F24,G23+G24),0) -> 0.037491603 | H26: =IFERROR(H25/AVERAGE(G23+G24,H23+H24),0) -> 0.030641153 | I26: =IFERROR(I25/AVERAGE(H23+H24,I23+I24),0) -> 0.030641153 | J26: =IFERROR(J25/AVERAGE(I23+I24,J23+J24),0) -> 0.030641153 | K26: =IFERROR(K25/AVERAGE(J23+J24,K23+K24),0) -> 0.030641153 | L26: =IFERROR(L25/AVERAGE(K23+K24,L23+L24),0) -> 0.030641153
A27: 汇兑损益、手续费及其他 | B27: 百万元 | C27: =历史利润表!E13-C25+C17 -> 1.4693 | D27: =历史利润表!F13-D25+D17 -> -28.5862 | E27: =历史利润表!G13-E25+E17 -> -9.0564 | F27: =历史利润表!H13-F25+F17 -> 3.3965 | G27: =历史利润表!I13-G25+G17 -> 48.712 | H27: =假设!H228 -> 60 | I27: =假设!I228 -> 10 | J27: =假设!J228 -> 10 | K27: =假设!K228 -> 10 | L27: =假设!L228 -> 10 | M27: 历史倒挤：财务费用-利息费用+利息收入（主要为汇兑损益）；2026H1受汇率影响汇兑损失增加
A28: 财务费用（负数为净收益） | B28: 百万元 | C28: =历史利润表!E13 -> -96.1326 | D28: =历史利润表!F13 -> -174.2752 | E28: =历史利润表!G13 -> -161.5113 | F28: =历史利润表!H13 -> -172.5019 | G28: =历史利润表!I13 -> -127.772 | H28: =H25-H17+H27 -> -194.51809 | I28: =I25-I17+I27 -> -262.79018 | J28: =J25-J17+J27 -> -268.93355 | K28: =K25-K17+K27 -> -287.43841 | L28: =L25-L17+L27 -> -338.85479
A29: D. 所有者权益变动
A30: 股本 | B30: 百万元 | C30: =历史资产负债表!E60 -> 1916.4974 | D30: =历史资产负债表!F60 -> 1916.4974 | E30: =历史资产负债表!G60 -> 1916.4974 | F30: =历史资产负债表!H60 -> 1916.4974 | G30: =历史资产负债表!I60 -> 1916.4974 | H30: =G30+股本与每股!H5 -> 1996.7186 | I30: =H30+股本与每股!I5 -> 1996.7186 | J30: =I30+股本与每股!J5 -> 1996.7186 | K30: =J30+股本与每股!K5 -> 1996.7186 | L30: =K30+股本与每股!L5 -> 1996.7186
A31: 资本公积 | B31: 百万元 | C31: =历史资产负债表!E61 -> 6218.2411 | D31: =历史资产负债表!F61 -> 6218.2411 | E31: =历史资产负债表!G61 -> 6218.2411 | F31: =历史资产负债表!H61 -> 6218.2411 | G31: =历史资产负债表!I61 -> 6218.2411 | H31: =G31+股本与每股!H7-股本与每股!H5 -> 12952.214 | I31: =H31+股本与每股!I7-股本与每股!I5 -> 12952.214 | J31: =I31+股本与每股!J7-股本与每股!J5 -> 12952.214 | K31: =J31+股本与每股!K7-股本与每股!K5 -> 12952.214 | L31: =K31+股本与每股!L7-股本与每股!L5 -> 12952.214
A32: 减：库存股 | B32: 百万元 | C32: =N(历史资产负债表!E62) -> 0 | D32: =N(历史资产负债表!F62) -> 0 | E32: =N(历史资产负债表!G62) -> 0 | F32: =N(历史资产负债表!H62) -> 0 | G32: =N(历史资产负债表!I62) -> 175.4407 | H32: =G32+股本与每股!H9 -> 1820.1007 | I32: =H32+股本与每股!I9 -> 1820.1007 | J32: =I32+股本与每股!J9 -> 1820.1007 | K32: =J32+股本与每股!K9 -> 1820.1007 | L32: =K32+股本与每股!L9 -> 1820.1007
A33: 其他综合收益（假设不变） | B33: 百万元 | C33: =历史资产负债表!E63 -> -70.7075 | D33: =历史资产负债表!F63 -> -52.7573 | E33: =历史资产负债表!G63 -> -21.0949 | F33: =历史资产负债表!H63 -> -42.0416 | G33: =历史资产负债表!I63 -> 34.0112 | H33: =G33 -> 34.0112 | I33: =H33 -> 34.0112 | J33: =I33 -> 34.0112 | K33: =J33 -> 34.0112 | L33: =K33 -> 34.0112
A34: 盈余公积 | B34: 百万元 | C34: =历史资产负债表!E64 -> 1037.3061 | D34: =历史资产负债表!F64 -> 1131.1383 | E34: =历史资产负债表!G64 -> 1131.1383 | F34: =历史资产负债表!H64 -> 1131.1383 | G34: =历史资产负债表!I64 -> 1131.1383 | H34: =G34 -> 1131.1383 | I34: =H34 -> 1131.1383 | J34: =I34 -> 1131.1383 | K34: =J34 -> 1131.1383 | L34: =K34 -> 1131.1383 | M34: 2025年末盈余公积1,131.1百万元已超过股本50%（958.2），母公司可不再提取法定盈余公积；故预测维持不变
A35: 未分配利润 | B35: 百万元 | C35: =历史资产负债表!E65 -> 7088.9596 | D35: =历史资产负债表!F65 -> 7886.5543 | E35: =历史资产负债表!G65 -> 8988.4159 | F35: =历史资产负债表!H65 -> 10642.246 | G35: =历史资产负债表!I65 -> 12534.312 | H35: =G35+三表预测!H26-股本与每股!H14 -> 15934.559 | I35: =H35+三表预测!I26-股本与每股!I14 -> 20160.778 | J35: =I35+三表预测!J26-股本与每股!J14 -> 24539.938 | K35: =J35+三表预测!K26-股本与每股!K14 -> 29148.508 | L35: =K35+三表预测!L26-股本与每股!L14 -> 33951.036
A36: 归母所有者权益 | B36: 百万元 | C36: =历史资产负债表!E66 -> 16190.297 | D36: =历史资产负债表!F66 -> 17099.674 | E36: =历史资产负债表!G66 -> 18233.198 | F36: =历史资产负债表!H66 -> 19866.081 | G36: =历史资产负债表!I66 -> 21658.759 | H36: =H30+H31-H32+H33+H34+H35 -> 30228.541 | I36: =I30+I31-I32+I33+I34+I35 -> 34454.76 | J36: =J30+J31-J32+J33+J34+J35 -> 38833.92 | K36: =K30+K31-K32+K33+K34+K35 -> 43442.489 | L36: =L30+L31-L32+L33+L34+L35 -> 48245.018
A37: 校验：权益明细合计-报告值（历史） | B37: 百万元 | C37: =ROUND(C30+C31-C32+C33+C34+C35-C36,1) -> 0 | D37: =ROUND(D30+D31-D32+D33+D34+D35-D36,1) -> 0 | E37: =ROUND(E30+E31-E32+E33+E34+E35-E36,1) -> 0 | F37: =ROUND(F30+F31-F32+F33+F34+F35-F36,1) -> 0 | G37: =ROUND(G30+G31-G32+G33+G34+G35-G36,1) -> 0
A38: E. 分红、回购与杠杆
A39: 当年派发现金股利 | B39: 百万元 | G39: =股本与每股!G14 -> 726.31816 | H39: =股本与每股!H14 -> 860.11 | I39: =股本与每股!I14 -> 1405.9177 | J39: =股本与每股!J14 -> 1858.6053 | K39: =股本与每股!K14 -> 2058.4626 | L39: =股本与每股!L14 -> 2200.1205
A40: 每股股利（按派息时流通股） | B40: 元/股 | H40: =IFERROR(H39/股本与每股!G12,0) -> 0.44999811 | I40: =IFERROR(I39/股本与每股!H12,0) -> 0.71124182 | J40: =IFERROR(J39/股本与每股!I12,0) -> 0.94025266 | K40: =IFERROR(K39/股本与每股!J12,0) -> 1.0413588 | L40: =IFERROR(L39/股本与每股!K12,0) -> 1.1130223
A41: 股息率（当前股价） | B41: % | H41: =IFERROR(H40/假设!$C$6,0) -> 0.0037974524 | I41: =IFERROR(I40/假设!$C$6,0) -> 0.0060020407 | J41: =IFERROR(J40/假设!$C$6,0) -> 0.0079346216 | K41: =IFERROR(K40/假设!$C$6,0) -> 0.0087878377 | L41: =IFERROR(L40/假设!$C$6,0) -> 0.0093925932
A42: 股份回购 | B42: 百万元 | H42: =股本与每股!H9 -> 1644.66 | I42: =股本与每股!I9 -> 0 | J42: =股本与每股!J9 -> 0 | K42: =股本与每股!K9 -> 0 | L42: =股本与每股!L9 -> 0
A43: 净现金（货币资金+理财+一年以上定期存款-有息负债-租赁负债） | B43: 百万元 | C43: =C6+C9+N(C10)-C23-C24 -> 8194.3206 | D43: =D6+D9+N(D10)-D23-D24 -> 8548.3667 | E43: =E6+E9+N(E10)-E23-E24 -> 9507.1736 | F43: =F6+F9+N(F10)-F23-F24 -> 10544.889 | G43: =G6+G9+N(G10)-G23-G24 -> 12080.847 | H43: =H6+H9+H10-H23-H24 -> 18350.22 | I43: =I6+I9+I10-I23-I24 -> 19604.426 | J43: =J6+J9+J10-J23-J24 -> 21788 | K43: =K6+K9+K10-K23-K24 -> 25001.524 | L43: =L6+L9+L10-L23-L24 -> 29004.191 | M43: 一年以上定期存款及大额存单列示于其他非流动资产（年报附注），视同现金；2021A未拆分，按0计
A44: 利息保障倍数（EBIT/利息费用） | B44: x | C44: =IFERROR(三表预测!C31/C25,0) -> 377.49545 | D44: =IFERROR(三表预测!D31/D25,0) -> 157.09102 | E44: =IFERROR(三表预测!E31/E25,0) -> 67.308279 | F44: =IFERROR(三表预测!F31/F25,0) -> 82.307219 | G44: =IFERROR(三表预测!G31/G25,0) -> 135.31132 | H44: =IFERROR(三表预测!H31/H25,0) -> 255.96061 | I44: =IFERROR(三表预测!I31/I25,0) -> 345.93633 | J44: =IFERROR(三表预测!J31/J25,0) -> 384.54487 | ... L44: =IFERROR(三表预测!L31/L25,0) -> 429.43778
A45: 有息负债/归母权益 | B45: % | C45: =IFERROR(C23/C36,0) -> 0.0030851319 | D45: =IFERROR(D23/D36,0) -> 0.010844382 | E45: =IFERROR(E23/E36,0) -> 0.040874849 | F45: =IFERROR(F23/F36,0) -> 0.024128926 | G45: =IFERROR(G23/G36,0) -> 0.026208214 | H45: =IFERROR(H23/H36,0) -> 0.018778194 | I45: =IFERROR(I23/I36,0) -> 0.016474861 | J45: =IFERROR(J23/J36,0) -> 0.014617051 | ... L45: =IFERROR(L23/L36,0) -> 0.011765721

Sheet 税务与其他损益
A1: 税金、其他收益、减值与所得税桥
A2: 所得税：法定15%（高新技术企业）为起点，叠加子公司税率差异、研发费用加计扣除与其他调整。
A4: 项目（百万元，另注明除外） | B4: 单位 | C4: 2021A | D4: 2022A | E4: 2023A | F4: 2024A | G4: 2025A | H4: 2026E | I4: 2027E | J4: 2028E | K4: 2029E | L4: 2030E | M4: 来源/说明
A5: A. 税金及附加
A6: 税金及附加 | B6: 百万元 | C6: =历史利润表!E9 -> 58.7828 | D6: =历史利润表!F9 -> 63.2677 | E6: =历史利润表!G9 -> 84.2832 | F6: =历史利润表!H9 -> 79.1745 | G6: =历史利润表!I9 -> 107.7827 | H6: =收入拆解!H47*假设!H231 -> 138.63187 | I6: =收入拆解!I47*假设!I231 -> 175.50903 | J6: =收入拆解!J47*假设!J231 -> 201.55217 | K6: =收入拆解!K47*假设!K231 -> 221.96957 | L6: =收入拆解!L47*假设!L231 -> 236.9389
A7: 占收入 | B7: % | C7: =IFERROR(C6/历史利润表!E6,0) -> 0.0094535868 | D7: =IFERROR(D6/历史利润表!F6,0) -> 0.012286453 | E7: =IFERROR(E6/历史利润表!G6,0) -> 0.014717616 | F7: =IFERROR(F6/历史利润表!H6,0) -> 0.010735539 | G7: =IFERROR(G6/历史利润表!I6,0) -> 0.011966344 | H7: =IFERROR(H6/收入拆解!H47,0) -> 0.01 | I7: =IFERROR(I6/收入拆解!I47,0) -> 0.01 | J7: =IFERROR(J6/收入拆解!J47,0) -> 0.01 | K7: =IFERROR(K6/收入拆解!K47,0) -> 0.01 | L7: =IFERROR(L6/收入拆解!L47,0) -> 0.01
A8: B. 其他收益
A9: 与资产相关的政府补助摊销（递延收益转入） | B9: 百万元 | D9: 108.67066 | E9: 171.18011 | F9: 170.45451 | G9: 152.17329 | H9: =假设!H232 -> 190 | I9: =假设!I232 -> 185 | J9: =假设!J232 -> 180 | K9: =假设!K232 -> 175 | L9: =假设!L232 -> 170
A10: 增值税加计抵减 | B10: 百万元 | E10: 46.131557 | F10: 63.001737 | G10: 27.468772 | H10: =成本拆解!H32*假设!H233 -> 47.770883 | I10: =成本拆解!I32*假设!I233 -> 61.921407 | J10: =成本拆解!J32*假设!J233 -> 0 | K10: =成本拆解!K32*假设!K233 -> 0 | L10: =成本拆解!L32*假设!L233 -> 0 | M10: 先进制造业企业按当期可抵扣进项税额加计5%抵减（政策期至2027年底），按原材料成本比例近似
A11: 与收益相关的政府补助及其他 | B11: 百万元 | E11: =E12-N(E9)-N(E10) -> 131.38784 | F11: =F12-N(F9)-N(F10) -> 71.640454 | G11: =G12-N(G9)-N(G10) -> 210.52564 | H11: =收入拆解!H47*假设!H235 -> 48.521156 | I11: =收入拆解!I47*假设!I235 -> 70.203612 | J11: =收入拆解!J47*假设!J235 -> 80.620869 | K11: =收入拆解!K47*假设!K235 -> 88.787827 | L11: =收入拆解!L47*假设!L235 -> 94.775558
A12: 其他收益合计 | B12: 百万元 | C12: =历史利润表!E16 -> 136.3169 | D12: =历史利润表!F16 -> 218.1716 | E12: =历史利润表!G16 -> 348.6995 | F12: =历史利润表!H16 -> 305.0967 | G12: =历史利润表!I16 -> 390.1677 | H12: =H9+H10+H11 -> 286.29204 | I12: =I9+I10+I11 -> 317.12502 | J12: =J9+J10+J11 -> 260.62087 | K12: =K9+K10+K11 -> 263.78783 | L12: =L9+L10+L11 -> 264.77556
A13: 占收入 | B13: % | C13: =IFERROR(C12/历史利润表!E6,0) -> 0.021922801 | D13: =IFERROR(D12/历史利润表!F6,0) -> 0.042368461 | E13: =IFERROR(E12/历史利润表!G6,0) -> 0.060890251 | F13: =IFERROR(F12/历史利润表!H6,0) -> 0.041369096 | G13: =IFERROR(G12/历史利润表!I6,0) -> 0.043317535 | H13: =IFERROR(H12/收入拆解!H47,0) -> 0.020651242 | I13: =IFERROR(I12/收入拆解!I47,0) -> 0.018068872 | J13: =IFERROR(J12/收入拆解!J47,0) -> 0.01293069 | K13: =IFERROR(K12/收入拆解!K47,0) -> 0.011883964 | L13: =IFERROR(L12/收入拆解!L47,0) -> 0.011174846
A14: C. 减值损失（负数为损失）
A15: 资产减值损失-存货跌价（历史=资产减值损失合计） | B15: 百万元 | C15: =N(历史利润表!E20) -> -33.4424 | D15: =N(历史利润表!F20) -> -70.0966 | E15: =N(历史利润表!G20) -> -0.9734 | F15: =N(历史利润表!H20) -> -26.3493 | G15: =N(历史利润表!I20) -> -26.5942 | H15: =-(营运资金!H11+营运资金!H12+营运资金!H13+营运资金!H14)*假设!H236 -> -115.04039 | I15: =-(营运资金!I11+营运资金!I12+营运资金!I13+营运资金!I14)*假设!I236 -> -51.45744 | J15: =-(营运资金!J11+营运资金!J12+营运资金!J13+营运资金!J14)*假设!J236 -> -60.113887 | K15: =-(营运资金!K11+营运资金!K12+营运资金!K13+营运资金!K14)*假设!K236 -> -67.369696 | L15: =-(营运资金!L11+营运资金!L12+营运资金!L13+营运资金!L14)*假设!L236 -> -72.536578
A16: 信用减值损失 | B16: 百万元 | C16: =N(历史利润表!E21) -> -25.2766 | D16: =N(历史利润表!F21) -> 3.6367 | E16: =N(历史利润表!G21) -> 7.6096 | F16: =N(历史利润表!H21) -> -12.7345 | G16: =N(历史利润表!I21) -> -15.445 | H16: =-营运资金!H7*假设!H237 -> -83.558938 | I16: =-营运资金!I7*假设!I237 -> -29.620154 | J16: =-营运资金!J7*假设!J237 -> -34.01538 | K16: =-营运资金!K7*假设!K237 -> -37.461165 | L16: =-营运资金!L7*假设!L237 -> -39.987496
A17: 固定资产减值损失 | B17: 百万元 | H17: =-假设!H238 -> -19.44 | I17: =-假设!I238 -> 0 | J17: =-假设!J238 -> 0 | K17: =-假设!K238 -> 0 | L17: =-假设!L238 -> 0 | M17: 2026H1计提19.44；历史各期无（历史列含于资产减值损失）
A18: 减值损失合计 | B18: 百万元 | C18: =C15+C16 -> -58.719 | D18: =D15+D16 -> -66.4599 | E18: =E15+E16 -> 6.6362 | F18: =F15+F16 -> -39.0838 | G18: =G15+G16 -> -42.0392 | H18: =H15+H16+H17 -> -218.03933 | I18: =I15+I16+I17 -> -81.077594 | J18: =J15+J16+J17 -> -94.129267 | K18: =K15+K16+K17 -> -104.83086 | L18: =L15+L16+L17 -> -112.52407
A19: 资产处置收益 | B19: 百万元 | C19: =N(历史利润表!E22) -> -3.8453 | D19: =N(历史利润表!F22) -> -1.2666 | E19: =N(历史利润表!G22) -> 1.9312 | F19: =N(历史利润表!H22) -> -1.3421 | G19: =N(历史利润表!I22) -> 0.3699 | H19: =N(历史利润表!K22) -> -3.1531 | I19: =0 -> 0 | J19: =0 -> 0 | K19: =0 -> 0 | L19: =0 -> 0 | M19: 2026E取2026H1实际值（下半年假设为0）；2027E起为0
A20: 营业外收支净额 | B20: 百万元 | C20: =历史利润表!E24-历史利润表!E25 -> 9.0005 | D20: =历史利润表!F24-历史利润表!F25 -> 4.8907 | E20: =历史利润表!G24-历史利润表!G25 -> 5.201 | F20: =历史利润表!H24-历史利润表!H25 -> -3.7615 | G20: =历史利润表!I24-历史利润表!I25 -> -0.2892 | H20: =历史利润表!K24-历史利润表!K25 -> -2.826 | I20: =0 -> 0 | J20: =0 -> 0 | K20: =0 -> 0 | L20: =0 -> 0 | M20: 同上
A21: D. 所得税桥
A22: 利润总额 | B22: 百万元 | C22: =历史利润表!E26 -> 2303.5281 | D22: =历史利润表!F26 -> 1666.3178 | E22: =历史利润表!G26 -> 1782.8476 | F22: =历史利润表!H26 -> 2518.9439 | G22: =历史利润表!I26 -> 3008.1764 | H22: =三表预测!H22 -> 4911.2131 | I22: =三表预测!I22 -> 6545.3364 | J22: =三表预测!J22 -> 7245.2411 | K22: =三表预测!K22 -> 7738.255 | L22: =三表预测!L22 -> 8121.848
A23: 按法定适用税率计算的所得税 | B23: 百万元 | E23: =E22*假设!$C$36 -> 267.42714 | F23: =F22*假设!$C$36 -> 377.84159 | G23: =G22*假设!$C$36 -> 451.22646 | H23: =H22*假设!$C$36 -> 736.68197 | I23: =I22*假设!$C$36 -> 981.80046 | J23: =J22*假设!$C$36 -> 1086.7862 | K23: =K22*假设!$C$36 -> 1160.7382 | L23: =L22*假设!$C$36 -> 1218.2772
A24: 子公司适用不同税率的影响 | B24: 百万元 | E24: 13.234393 | F24: 15.321301 | G24: 20.77772 | H24: =H22*假设!H239 -> 34.378492 | I24: =I22*假设!I239 -> 45.817355 | J24: =J22*假设!J239 -> 50.716688 | K24: =K22*假设!K239 -> 54.167785 | L24: =L22*假设!L239 -> 56.852936
A25: 研发费用加计扣除的影响 | B25: 百万元 | E25: -81.014715 | F25: -76.17924 | G25: -89.649014 | H25: =-人员与费用!H47*假设!H240*假设!$C$37*假设!$C$36 -> -105.4702 | I25: =-人员与费用!I47*假设!I240*假设!$C$37*假设!$C$36 -> -127.5093 | J25: =-人员与费用!J47*假设!J240*假设!$C$37*假设!$C$36 -> -144.51764 | K25: =-人员与费用!K47*假设!K240*假设!$C$37*假设!$C$36 -> -159.15927 | L25: =-人员与费用!L47*假设!L240*假设!$C$37*假设!$C$36 -> -172.17501
A26: 其他调整（不可抵扣、以前年度、非应税等） | B26: 百万元 | E26: =E27-E23-N(E24)-N(E25) -> 0.050182 | F26: =F27-F23-N(F24)-N(F25) -> 11.726454 | G26: =G27-G23-N(G24)-N(G25) -> 8.841134 | H26: =H22*(假设!H241+假设!$C$60*假设!$C$61) -> -14.733639 | I26: =I22*(假设!I241+假设!$C$60) -> 13.090673 | J26: =J22*(假设!J241+假设!$C$60) -> 14.490482 | K26: =K22*(假设!K241+假设!$C$60) -> 15.47651 | L26: =L22*(假设!L241+假设!$C$60) -> 16.243696
A27: 所得税费用 | B27: 百万元 | C27: =历史利润表!E27 -> 290.216 | D27: =历史利润表!F27 -> 160.2146 | E27: =历史利润表!G27 -> 199.697 | F27: =历史利润表!H27 -> 328.7101 | G27: =历史利润表!I27 -> 391.1963 | H27: =H23+H24+H25+H26 -> 650.85662 | I27: =I23+I24+I25+I26 -> 913.19919 | J27: =J23+J24+J25+J26 -> 1007.4757 | K27: =K23+K24+K25+K26 -> 1071.2233 | L27: =L23+L24+L25+L26 -> 1119.1988
A28: 实际税率 | B28: % | C28: =IFERROR(C27/C22,0) -> 0.12598761 | D28: =IFERROR(D27/D22,0) -> 0.096148886 | E28: =IFERROR(E27/E22,0) -> 0.11201013 | F28: =IFERROR(F27/F22,0) -> 0.1304952 | G28: =IFERROR(G27/G22,0) -> 0.13004434 | H28: =IFERROR(H27/H22,0) -> 0.13252461 | I28: =IFERROR(I27/I22,0) -> 0.13951906 | J28: =IFERROR(J27/J22,0) -> 0.13905344 | ... L28: =IFERROR(L27/L22,0) -> 0.13780101
A29: 税率差异对税率的影响 | B29: pp | E29: =IFERROR(N(E24)/E22,0) -> 0.0074231768 | F29: =IFERROR(N(F24)/F22,0) -> 0.0060824304 | G29: =IFERROR(N(G24)/G22,0) -> 0.0069070816 | H29: =IFERROR(H24/H22,0) -> 0.007 | I29: =IFERROR(I24/I22,0) -> 0.007 | J29: =IFERROR(J24/J22,0) -> 0.007 | K29: =IFERROR(K24/K22,0) -> 0.007 | L29: =IFERROR(L24/L22,0) -> 0.007
A30: 加计扣除对税率的影响 | B30: pp | E30: =IFERROR(N(E25)/E22,0) -> -0.045441189 | F30: =IFERROR(N(F25)/F22,0) -> -0.030242531 | G30: =IFERROR(N(G25)/G22,0) -> -0.029801781 | H30: =IFERROR(H25/H22,0) -> -0.021475387 | I30: =IFERROR(I25/I22,0) -> -0.019480938 | J30: =IFERROR(J25/J22,0) -> -0.01994656 | K30: =IFERROR(K25/K22,0) -> -0.02056785 | L30: =IFERROR(L25/L22,0) -> -0.021198995
A31: 其他调整对税率的影响 | B31: pp | E31: =IFERROR(N(E26)/E22,0) -> 2.8147106e-05 | F31: =IFERROR(N(F26)/F22,0) -> 0.0046553057 | G31: =IFERROR(N(G26)/G22,0) -> 0.0029390344 | H31: =IFERROR(H26/H22,0) -> -0.003 | I31: =IFERROR(I26/I22,0) -> 0.002 | J31: =IFERROR(J26/J22,0) -> 0.002 | K31: =IFERROR(K26/K22,0) -> 0.002 | L31: =IFERROR(L26/L22,0) -> 0.002

Sheet 股本与每股
A1: 股本、库存股、H股募资与分红
A2: 期末流通股本=总股本-库存股，用于EPS、每股净资产与市场倍数；DCF每股价值按含库存股的总股本（全面摊薄）。H股于2026-07-09上市。
A4: 项目（百万元，另注明除外） | B4: 单位 | C4: 2021A | D4: 2022A | E4: 2023A | F4: 2024A | G4: 2025A | H4: 2026E | I4: 2027E | J4: 2028E | K4: 2029E | L4: 2030E | M4: 来源/说明
A5: H股新发股数 | B5: 百万股 | H5: =假设!$C$9/1000000 -> 80.2212 | I5: 0 | J5: 0 | K5: 0 | L5: 0
A6: H股募资总额 | B6: 百万元 | H6: =假设!$C$9*假设!$C$7*假设!$C$8/1000000 -> 6988.9175 | I6: 0 | J6: 0 | K6: 0 | L6: 0
A7: H股募资净额 | B7: 百万元 | H7: =H6*(1-假设!$C$10) -> 6814.1945 | I7: 0 | J7: 0 | K7: 0 | L7: 0
A8: 期末总股本 | B8: 百万股 | C8: 1916.4974 | D8: 1916.4974 | E8: 1916.4974 | F8: 1916.4974 | G8: 1916.4974 | H8: =G8+H5 -> 1996.7186 | I8: =H8+I5 -> 1996.7186 | J8: =I8+J5 -> 1996.7186 | K8: =J8+K5 -> 1996.7186 | L8: =K8+L5 -> 1996.7186
A9: 当年回购金额 | B9: 百万元 | G9: 175.44073 | H9: =假设!$C$14+假设!$C$15 -> 1644.66 | I9: =假设!I229 -> 0 | J9: =假设!J229 -> 0 | K9: =假设!K229 -> 0 | L9: =假设!L229 -> 0
A10: 当年回购股数 | B10: 百万股 | G10: 5.1338 | H10: =假设!$C$13/1000000+IFERROR(假设!$C$15/假设!$C$6,0) -> 14.876414 | I10: =IFERROR(I9/假设!$C$6,0) -> 0 | J10: =IFERROR(J9/假设!$C$6,0) -> 0 | K10: =IFERROR(K9/假设!$C$6,0) -> 0 | L10: =IFERROR(L9/假设!$C$6,0) -> 0
A11: 期末库存股 | B11: 百万股 | C11: 0 | D11: 0 | E11: 0 | F11: 0 | G11: 5.1338 | H11: =G11+H10 -> 20.010214 | I11: =H11+I10 -> 20.010214 | J11: =I11+J10 -> 20.010214 | K11: =J11+K10 -> 20.010214 | L11: =K11+L10 -> 20.010214
A12: 期末流通股本（扣除库存股） | B12: 百万股 | C12: =C8-C11 -> 1916.4974 | D12: =D8-D11 -> 1916.4974 | E12: =E8-E11 -> 1916.4974 | F12: =F8-F11 -> 1916.4974 | G12: =G8-G11 -> 1911.3636 | H12: =H8-H11 -> 1976.7084 | I12: =I8-I11 -> 1976.7084 | J12: =J8-J11 -> 1976.7084 | ... L12: =L8-L11 -> 1976.7084
A13: 加权平均股本（历史=归母净利润÷报告基本每股收益；预测H股按上市后天数加权） | B13: 百万股 | C13: =IFERROR(三表预测!C26/历史利润表!E36,C12) -> 1828.0105 | D13: =IFERROR(三表预测!D26/历史利润表!F36,D12) -> 1904.6911 | E13: =IFERROR(三表预测!E26/历史利润表!G36,E12) -> 1928.0315 | F13: =IFERROR(三表预测!F26/历史利润表!H36,F12) -> 1921.4467 | G13: =IFERROR(三表预测!G26/历史利润表!I36,G12) -> 1911.2291 | H13: =G12+H5*假设!$C$11/365-假设!$C$13/1000000*假设!$C$16/12 -> 1945.6051 | I13: =AVERAGE(H12,I12) -> 1976.7084 | J13: =AVERAGE(I12,J12) -> 1976.7084 | K13: =AVERAGE(J12,K12) -> 1976.7084 | L13: =AVERAGE(K12,L12) -> 1976.7084
A14: 当年派发现金股利 | B14: 百万元 | G14: 726.31816 | H14: =假设!$C$18 -> 860.11 | I14: =假设!$C$19*三表预测!H26 -> 1405.9177 | J14: =假设!$C$19*三表预测!I26 -> 1858.6053 | K14: =假设!$C$19*三表预测!J26 -> 2058.4626 | L14: =假设!$C$19*三表预测!K26 -> 2200.1205
A15: 对应每股股利 | B15: 元/股 | G15: 0.38 | H15: =IFERROR(H14/G12,0) -> 0.44999811 | I15: =IFERROR(I14/H12,0) -> 0.71124182 | J15: =IFERROR(J14/I12,0) -> 0.94025266 | K15: =IFERROR(K14/J12,0) -> 1.0413588 | L15: =IFERROR(L14/K12,0) -> 1.1130223

Sheet 三表预测
A1: 三表联动预测（利润表、资产负债表、现金流量表）
A2: 2021A-2025A链接历史报表；2026E-2030E链接各明细模块。货币资金由现金流量表倒挤，资产负债表自动配平。
A4: 项目（百万元，另注明除外） | B4: 单位 | C4: 2021A | D4: 2022A | E4: 2023A | F4: 2024A | G4: 2025A | H4: 2026E | I4: 2027E | J4: 2028E | K4: 2029E | L4: 2030E | M4: 来源/说明
A5: 利润表
A6: 营业收入 | C6: =历史利润表!E6 -> 6218.042 | D6: =历史利润表!F6 -> 5149.3869 | E6: =历史利润表!G6 -> 5726.6885 | F6: =历史利润表!H6 -> 7374.9908 | G6: =历史利润表!I6 -> 9007.1539 | H6: =收入拆解!H47 -> 13863.187 | I6: =收入拆解!I47 -> 17550.903 | J6: =收入拆解!J47 -> 20155.217 | K6: =收入拆解!K47 -> 22196.957 | L6: =收入拆解!L47 -> 23693.89
A7: 同比 | B7: % | D7: =IFERROR(D6/C6-1,0) -> -0.1718636 | E7: =IFERROR(E6/D6-1,0) -> 0.11211074 | F7: =IFERROR(F6/E6-1,0) -> 0.28782818 | G7: =IFERROR(G6/F6-1,0) -> 0.22131053 | H7: =IFERROR(H6/G6-1,0) -> 0.53913074 | I7: =IFERROR(I6/H6-1,0) -> 0.26600776 | J7: =IFERROR(J6/I6-1,0) -> 0.14838634 | K7: =IFERROR(K6/J6-1,0) -> 0.10130079 | L7: =IFERROR(L6/K6-1,0) -> 0.067438657
A8: 营业成本 | C8: =历史利润表!E8 -> 3186.5095 | D8: =历史利润表!F8 -> 2878.3209 | E8: =历史利润表!G8 -> 3445.5299 | F8: =历史利润表!H8 -> 4204.8637 | G8: =历史利润表!I8 -> 5211.7617 | H8: =成本拆解!H26 -> 7634.6351 | I8: =成本拆解!I26 -> 9615.4014 | J8: =成本拆解!J26 -> 11211.506 | K8: =成本拆解!K26 -> 12557.132 | L8: =成本拆解!L26 -> 13532.008
A9: 毛利 | C9: =C6-C8 -> 3031.5325 | D9: =D6-D8 -> 2271.066 | E9: =E6-E8 -> 2281.1586 | F9: =F6-F8 -> 3170.1271 | G9: =G6-G8 -> 3795.3922 | H9: =H6-H8 -> 6228.5523 | I9: =I6-I8 -> 7935.5016 | J9: =J6-J8 -> 8943.7107 | ... L9: =L6-L8 -> 10161.882
A10: 毛利率 | B10: % | C10: =IFERROR(C9/C6,0) -> 0.48753812 | D10: =IFERROR(D9/D6,0) -> 0.44103619 | E10: =IFERROR(E9/E6,0) -> 0.39833817 | F10: =IFERROR(F9/F6,0) -> 0.42984828 | G10: =IFERROR(G9/G6,0) -> 0.4213753 | H10: =IFERROR(H9/H6,0) -> 0.44928717 | I10: =IFERROR(I9/I6,0) -> 0.45214207 | J10: =IFERROR(J9/J6,0) -> 0.44374172 | ... L10: =IFERROR(L9/L6,0) -> 0.42888197
A11: 税金及附加 | C11: =历史利润表!E9 -> 58.7828 | D11: =历史利润表!F9 -> 63.2677 | E11: =历史利润表!G9 -> 84.2832 | F11: =历史利润表!H9 -> 79.1745 | G11: =历史利润表!I9 -> 107.7827 | H11: =税务与其他损益!H6 -> 138.63187 | I11: =税务与其他损益!I6 -> 175.50903 | J11: =税务与其他损益!J6 -> 201.55217 | K11: =税务与其他损益!K6 -> 221.96957 | L11: =税务与其他损益!L6 -> 236.9389
A12: 销售费用 | C12: =历史利润表!E10 -> 51.3154 | D12: =历史利润表!F10 -> 57.308 | E12: =历史利润表!G10 -> 74.3431 | F12: =历史利润表!H10 -> 79.3918 | G12: =历史利润表!I10 -> 93.1993 | H12: =人员与费用!H34 -> 105.04434 | I12: =人员与费用!I34 -> 124.93085 | J12: =人员与费用!J34 -> 141.37808 | K12: =人员与费用!K34 -> 155.37852 | L12: =人员与费用!L34 -> 167.88891
A13: 管理费用 | C13: =历史利润表!E11 -> 453.2391 | D13: =历史利润表!F11 -> 479.3491 | E13: =历史利润表!G11 -> 429.4141 | F13: =历史利润表!H11 -> 409.8445 | G13: =历史利润表!I11 -> 480.9502 | H13: =人员与费用!H40 -> 609.33009 | I13: =人员与费用!I40 -> 700.42727 | J13: =人员与费用!J40 -> 776.84113 | K13: =人员与费用!K40 -> 848.03725 | L13: =人员与费用!L40 -> 907.31969
A14: 研发费用 | C14: =历史利润表!E12 -> 418.5388 | D14: =历史利润表!F12 -> 452.1724 | E14: =历史利润表!G12 -> 545.8062 | F14: =历史利润表!H12 -> 583.0724 | G14: =历史利润表!I12 -> 653.4367 | H14: =人员与费用!H47 -> 781.26077 | I14: =人员与费用!I47 -> 944.5133 | J14: =人员与费用!J47 -> 1070.501 | K14: =人员与费用!K47 -> 1178.9575 | L14: =人员与费用!L47 -> 1275.3705
A15: 财务费用（负数为净收益） | C15: =历史利润表!E13 -> -96.1326 | D15: =历史利润表!F13 -> -174.2752 | E15: =历史利润表!G13 -> -161.5113 | F15: =历史利润表!H13 -> -172.5019 | G15: =历史利润表!I13 -> -127.772 | H15: =融资与资金!H28 -> -194.51809 | I15: =融资与资金!I28 -> -262.79018 | J15: =融资与资金!J28 -> -268.93355 | K15: =融资与资金!K28 -> -287.43841 | L15: =融资与资金!L28 -> -338.85479
A16: 其他收益 | C16: =历史利润表!E16 -> 136.3169 | D16: =历史利润表!F16 -> 218.1716 | E16: =历史利润表!G16 -> 348.6995 | F16: =历史利润表!H16 -> 305.0967 | G16: =历史利润表!I16 -> 390.1677 | H16: =税务与其他损益!H12 -> 286.29204 | I16: =税务与其他损益!I12 -> 317.12502 | J16: =税务与其他损益!J12 -> 260.62087 | K16: =税务与其他损益!K12 -> 263.78783 | L16: =税务与其他损益!L12 -> 264.77556
A17: 投资收益+公允价值变动 | C17: =N(历史利润表!E17)+N(历史利润表!E19) -> 74.986 | D17: =N(历史利润表!F17)+N(历史利润表!F19) -> 117.738 | E17: =N(历史利润表!G17)+N(历史利润表!G19) -> 111.5562 | F17: =N(历史利润表!H17)+N(历史利润表!H19) -> 66.8886 | G17: =N(历史利润表!I17)+N(历史利润表!I19) -> 72.1716 | H17: =融资与资金!H19 -> 60.136186 | I17: =融资与资金!I19 -> 56.377674 | J17: =融资与资金!J19 -> 56.377674 | K17: =融资与资金!K19 -> 56.377674 | L17: =融资与资金!L19 -> 56.377674
A18: 资产及信用减值损失 | C18: =N(历史利润表!E20)+N(历史利润表!E21) -> -58.719 | D18: =N(历史利润表!F20)+N(历史利润表!F21) -> -66.4599 | E18: =N(历史利润表!G20)+N(历史利润表!G21) -> 6.6362 | F18: =N(历史利润表!H20)+N(历史利润表!H21) -> -39.0838 | G18: =N(历史利润表!I20)+N(历史利润表!I21) -> -42.0392 | H18: =税务与其他损益!H18 -> -218.03933 | I18: =税务与其他损益!I18 -> -81.077594 | J18: =税务与其他损益!J18 -> -94.129267 | K18: =税务与其他损益!K18 -> -104.83086 | L18: =税务与其他损益!L18 -> -112.52407
A19: 资产处置收益 | C19: =N(历史利润表!E22) -> -3.8453 | D19: =N(历史利润表!F22) -> -1.2666 | E19: =N(历史利润表!G22) -> 1.9312 | F19: =N(历史利润表!H22) -> -1.3421 | G19: =N(历史利润表!I22) -> 0.3699 | H19: =税务与其他损益!H19 -> -3.1531 | I19: =税务与其他损益!I19 -> 0 | J19: =税务与其他损益!J19 -> 0 | K19: =税务与其他损益!K19 -> 0 | L19: =税务与其他损益!L19 -> 0
A20: 营业利润 | C20: =C9-C11-C12-C13-C14-C15+C16+C17+C18+C19 -> 2294.5276 | D20: =D9-D11-D12-D13-D14-D15+D16+D17+D18+D19 -> 1661.4271 | E20: =E9-E11-E12-E13-E14-E15+E16+E17+E18+E19 -> 1777.6464 | F20: =F9-F11-F12-F13-F14-F15+F16+F17+F18+F19 -> 2522.7052 | G20: =G9-G11-G12-G13-G14-G15+G16+G17+G18+G19 -> 3008.4653 | H20: =H9-H11-H12-H13-H14-H15+H16+H17+H18+H19 -> 4914.0391 | I20: =I9-I11-I12-I13-I14-I15+I16+I17+I18+I19 -> 6545.3364 | J20: =J9-J11-J12-J13-J14-J15+J16+J17+J18+J19 -> 7245.2411 | ... L20: =L9-L11-L12-L13-L14-L15+L16+L17+L18+L19 -> 8121.848
A21: 营业外收支净额 | C21: =历史利润表!E24-历史利润表!E25 -> 9.0005 | D21: =历史利润表!F24-历史利润表!F25 -> 4.8907 | E21: =历史利润表!G24-历史利润表!G25 -> 5.201 | F21: =历史利润表!H24-历史利润表!H25 -> -3.7615 | G21: =历史利润表!I24-历史利润表!I25 -> -0.2892 | H21: =税务与其他损益!H20 -> -2.826 | I21: =税务与其他损益!I20 -> 0 | J21: =税务与其他损益!J20 -> 0 | K21: =税务与其他损益!K20 -> 0 | L21: =税务与其他损益!L20 -> 0
A22: 利润总额 | C22: =C20+C21 -> 2303.5281 | D22: =D20+D21 -> 1666.3178 | E22: =E20+E21 -> 1782.8474 | F22: =F20+F21 -> 2518.9437 | G22: =G20+G21 -> 3008.1761 | H22: =H20+H21 -> 4911.2131 | I22: =I20+I21 -> 6545.3364 | J22: =J20+J21 -> 7245.2411 | ... L22: =L20+L21 -> 8121.848
A23: 所得税 | C23: =历史利润表!E27 -> 290.216 | D23: =历史利润表!F27 -> 160.2146 | E23: =历史利润表!G27 -> 199.697 | F23: =历史利润表!H27 -> 328.7101 | G23: =历史利润表!I27 -> 391.1963 | H23: =税务与其他损益!H27 -> 650.85662 | I23: =税务与其他损益!I27 -> 913.19919 | J23: =税务与其他损益!J27 -> 1007.4757 | K23: =税务与其他损益!K27 -> 1071.2233 | L23: =税务与其他损益!L27 -> 1119.1988
A24: 净利润 | C24: =C22-C23 -> 2013.3121 | D24: =D22-D23 -> 1506.1032 | E24: =E22-E23 -> 1583.1504 | F24: =F22-F23 -> 2190.2336 | G24: =G22-G23 -> 2616.9798 | H24: =H22-H23 -> 4260.3565 | I24: =I22-I23 -> 5632.1372 | J24: =J22-J23 -> 6237.7654 | ... L24: =L22-L23 -> 7002.6492
A25: 少数股东损益 | C25: =历史利润表!E30 -> 2.5006 | D25: =历史利润表!F30 -> 1.3972 | E25: =历史利润表!G30 -> 2.1646 | F25: =历史利润表!H30 -> -0.2156 | G25: =历史利润表!I30 -> -1.4041 | H25: =H24*假设!$C$20 -> 0 | I25: =I24*假设!$C$20 -> 0 | J25: =J24*假设!$C$20 -> 0 | K25: =K24*假设!$C$20 -> 0 | L25: =L24*假设!$C$20 -> 0
A26: 归母净利润 | C26: =C24-C25 -> 2010.8115 | D26: =D24-D25 -> 1504.706 | E26: =E24-E25 -> 1580.9858 | F26: =F24-F25 -> 2190.4492 | G26: =G24-G25 -> 2618.3839 | H26: =H24-H25 -> 4260.3565 | I26: =I24-I25 -> 5632.1372 | J26: =J24-J25 -> 6237.7654 | ... L26: =L24-L25 -> 7002.6492
A27: 同比 | B27: % | D27: =IFERROR(D26/C26-1,0) -> -0.25169217 | E27: =IFERROR(E26/D26-1,0) -> 0.050694156 | F27: =IFERROR(F26/E26-1,0) -> 0.38549581 | G27: =IFERROR(G26/F26-1,0) -> 0.1953639 | H27: =IFERROR(H26/G26-1,0) -> 0.62709392 | I27: =IFERROR(I26/H26-1,0) -> 0.3219873 | J27: =IFERROR(J26/I26-1,0) -> 0.10753079 | K27: =IFERROR(K26/J26-1,0) -> 0.068817316 | L27: =IFERROR(L26/K26-1,0) -> 0.050339864
A28: 归母净利率 | B28: % | C28: =IFERROR(C26/C6,0) -> 0.32338339 | D28: =IFERROR(D26/D6,0) -> 0.29221071 | E28: =IFERROR(E26/E6,0) -> 0.2760733 | F28: =IFERROR(F26/F6,0) -> 0.29701043 | G28: =IFERROR(G26/G6,0) -> 0.29070047 | H28: =IFERROR(H26/H6,0) -> 0.30731436 | I28: =IFERROR(I26/I6,0) -> 0.32090299 | J28: =IFERROR(J26/J6,0) -> 0.30948639 | ... L28: =IFERROR(L26/L6,0) -> 0.29554663
A29: EPS（按期末流通股本，扣除库存股，元） | B29: 元 | C29: =IFERROR(C26/股本与每股!C12,0) -> 1.0492117 | D29: =IFERROR(D26/股本与每股!D12,0) -> 0.78513335 | E29: =IFERROR(E26/股本与每股!E12,0) -> 0.82493502 | F29: =IFERROR(F26/股本与每股!F12,0) -> 1.142944 | G29: =IFERROR(G26/股本与每股!G12,0) -> 1.3699036 | H29: =IFERROR(H26/股本与每股!H12,0) -> 2.1552782 | I29: =IFERROR(I26/股本与每股!I12,0) -> 2.8492505 | J29: =IFERROR(J26/股本与每股!J12,0) -> 3.1556326 | ... L29: =IFERROR(L26/股本与每股!L12,0) -> 3.5425808
A30: EPS（加权平均股本，元；历史=报告基本每股收益） | B30: 元 | C30: =历史利润表!E36 -> 1.1 | D30: =历史利润表!F36 -> 0.79 | E30: =历史利润表!G36 -> 0.82 | F30: =历史利润表!H36 -> 1.14 | G30: =历史利润表!I36 -> 1.37 | H30: =IFERROR(H26/股本与每股!H13,0) -> 2.1897335 | I30: =IFERROR(I26/股本与每股!I13,0) -> 2.8492505 | J30: =IFERROR(J26/股本与每股!J13,0) -> 3.1556326 | K30: =IFERROR(K26/股本与每股!K13,0) -> 3.3727948 | L30: =IFERROR(L26/股本与每股!L13,0) -> 3.5425808
A31: EBIT（剔除利息收支与理财收益；汇兑损益与手续费保留） | C31: =C20+C15-融资与资金!C27-C17 -> 2121.9397 | D31: =D20+D15-融资与资金!D27-D17 -> 1398.0001 | E31: =E20+E15-融资与资金!E27-E17 -> 1513.6353 | F31: =F20+F15-融资与资金!F27-F17 -> 2279.9182 | G31: =G20+G15-融资与资金!G27-G17 -> 2759.8097 | H31: =H20+H15-融资与资金!H27-H17 -> 4599.3849 | I31: =I20+I15-融资与资金!I27-I17 -> 6216.1686 | J31: =J20+J15-融资与资金!J27-J17 -> 6909.9299 | ... L31: =L20+L15-融资与资金!L27-L17 -> 7716.6155
A32: 折旧与摊销 | C32: =资本开支与折旧!C91 -> 387.5088 | D32: =资本开支与折旧!D91 -> 544.3751 | E32: =资本开支与折旧!E91 -> 609.43241 | F32: =资本开支与折旧!F91 -> 651.2802 | G32: =资本开支与折旧!G91 -> 740.43309 | H32: =资本开支与折旧!H91 -> 813.65692 | I32: =资本开支与折旧!I91 -> 914.99495 | J32: =资本开支与折旧!J91 -> 1060.0309 | ... L32: =资本开支与折旧!L91 -> 1348.2187
A33: EBITDA | C33: =C31+C32 -> 2509.4485 | D33: =D31+D32 -> 1942.3752 | E33: =E31+E32 -> 2123.0677 | F33: =F31+F32 -> 2931.1984 | G33: =G31+G32 -> 3500.2428 | H33: =H31+H32 -> 5413.0418 | I33: =I31+I32 -> 7131.1635 | J33: =J31+J32 -> 7969.9608 | ... L33: =L31+L32 -> 9064.8342
A34: EBITDA利润率 | B34: % | C34: =IFERROR(C33/C6,0) -> 0.40357535 | D34: =IFERROR(D33/D6,0) -> 0.37720514 | E34: =IFERROR(E33/E6,0) -> 0.37073218 | F34: =IFERROR(F33/F6,0) -> 0.39745113 | G34: =IFERROR(G33/G6,0) -> 0.38860697 | H34: =IFERROR(H33/H6,0) -> 0.39046156 | I34: =IFERROR(I33/I6,0) -> 0.4063132 | J34: =IFERROR(J33/J6,0) -> 0.39542917 | ... L34: =IFERROR(L33/L6,0) -> 0.3825811
A35: 校验：营业利润-报告值（历史） | C35: =ROUND(C20-历史利润表!E23,2) -> 0 | D35: =ROUND(D20-历史利润表!F23,2) -> 0 | E35: =ROUND(E20-历史利润表!G23,2) -> 0 | F35: =ROUND(F20-历史利润表!H23,2) -> 0 | G35: =ROUND(G20-历史利润表!I23,2) -> 0
A36: 资产负债表
A37: 货币资金 | C37: =N(历史资产负债表!E5) -> 5552.412 | D37: =N(历史资产负债表!F5) -> 4509.4292 | E37: =N(历史资产负债表!G5) -> 2841.6149 | F37: =N(历史资产负债表!H5) -> 3062.8452 | G37: =N(历史资产负债表!I5) -> 3057.7786 | H37: =G37+H92 -> 9327.1517 | I37: =H37+I92 -> 10581.358 | J37: =I37+J92 -> 12764.932 | K37: =J37+K92 -> 15978.456 | L37: =K37+L92 -> 19981.123
A38: 交易性金融资产 | C38: =N(历史资产负债表!E6) -> 2693.5949 | D38: =N(历史资产负债表!F6) -> 4255.0144 | E38: =N(历史资产负债表!G6) -> 3846.7081 | F38: =N(历史资产负债表!H6) -> 5053.3869 | G38: =N(历史资产负债表!I6) -> 3758.5116 | H38: =融资与资金!H9 -> 3758.5116 | I38: =融资与资金!I9 -> 3758.5116 | J38: =融资与资金!J9 -> 3758.5116 | K38: =融资与资金!K9 -> 3758.5116 | L38: =融资与资金!L9 -> 3758.5116
A39: 应收票据 | C39: =N(历史资产负债表!E8) -> 611.4843 | D39: =N(历史资产负债表!F8) -> 435.4813 | E39: =N(历史资产负债表!G8) -> 462.5221 | F39: =N(历史资产负债表!H8) -> 642.0757 | G39: =N(历史资产负债表!I8) -> 754.9216 | H39: =营运资金!H6 -> 1063.4774 | I39: =营运资金!I6 -> 1346.3706 | J39: =营运资金!J6 -> 1546.1536 | K39: =营运资金!K6 -> 1702.7802 | L39: =营运资金!L6 -> 1817.6134
A40: 应收账款 | C40: =N(历史资产负债表!E9) -> 1528.3267 | D40: =N(历史资产负债表!F9) -> 1197.5819 | E40: =N(历史资产负债表!G9) -> 1626.598 | F40: =N(历史资产负债表!H9) -> 1871.7507 | G40: =N(历史资产负债表!I9) -> 2159.448 | H40: =营运资金!H7 -> 3342.3575 | I40: =营运资金!I7 -> 4231.4506 | J40: =营运资金!J7 -> 4859.34 | K40: =营运资金!K7 -> 5351.595 | L40: =营运资金!L7 -> 5712.4994
A41: 应收款项融资 | C41: =N(历史资产负债表!E10) -> 137.0218 | D41: =N(历史资产负债表!F10) -> 81.9324 | E41: =N(历史资产负债表!G10) -> 170.1508 | F41: =N(历史资产负债表!H10) -> 172.5082 | G41: =N(历史资产负债表!I10) -> 345.5521 | H41: =营运资金!H8 -> 455.77603 | I41: =营运资金!I8 -> 577.01599 | J41: =营运资金!J8 -> 662.63728 | K41: =营运资金!K8 -> 729.76296 | L41: =营运资金!L8 -> 778.97719
A42: 预付款项 | C42: =N(历史资产负债表!E11) -> 56.4665 | D42: =N(历史资产负债表!F11) -> 22.8533 | E42: =N(历史资产负债表!G11) -> 45.7734 | F42: =N(历史资产负债表!H11) -> 62.2607 | G42: =N(历史资产负债表!I11) -> 75.5091 | H42: =营运资金!H9 -> 122.15416 | I42: =营运资金!I9 -> 153.84642 | J42: =营运资金!J9 -> 179.3841 | K42: =营运资金!K9 -> 200.91411 | L42: =营运资金!L9 -> 216.51212
A43: 其他应收款 | C43: =N(历史资产负债表!E12) -> 151.249 | D43: =N(历史资产负债表!F12) -> 83.7475 | E43: =N(历史资产负债表!G12) -> 44.234 | F43: =N(历史资产负债表!H12) -> 28.6627 | G43: =N(历史资产负债表!I12) -> 18.4395 | H43: =营运资金!H10 -> 27.726375 | I43: =营运资金!I10 -> 35.101806 | J43: =营运资金!J10 -> 40.310434 | K43: =营运资金!K10 -> 44.393913 | L43: =营运资金!L10 -> 47.387779
A44: 存货 | C44: =N(历史资产负债表!E16) -> 1796.5411 | D44: =N(历史资产负债表!F16) -> 1885.8512 | E44: =N(历史资产负债表!G16) -> 1753.5978 | F44: =N(历史资产负债表!H16) -> 2180.7115 | G44: =N(历史资产负债表!I16) -> 2391.7224 | H44: =营运资金!H16 -> 3265.117 | I44: =营运资金!I16 -> 4138.0358 | J44: =营运资金!J16 -> 4834.1584 | K44: =营运资金!K16 -> 5417.6464 | L44: =营运资金!L16 -> 5833.1498
A45: 其他流动资产 | C45: =N(历史资产负债表!E17) -> 259.4314 | D45: =N(历史资产负债表!F17) -> 348.8942 | E45: =N(历史资产负债表!G17) -> 488.1799 | F45: =N(历史资产负债表!H17) -> 527.8337 | G45: =N(历史资产负债表!I17) -> 519.6397 | H45: =营运资金!H18 -> 554.5275 | I45: =营运资金!I18 -> 702.03612 | J45: =营运资金!J18 -> 806.20869 | K45: =营运资金!K18 -> 887.87827 | L45: =营运资金!L18 -> 947.75558
A46: 流动资产合计 | C46: =SUM(C37:C45) -> 12786.528 | D46: =SUM(D37:D45) -> 12820.785 | E46: =SUM(E37:E45) -> 11279.379 | F46: =SUM(F37:F45) -> 13602.035 | G46: =SUM(G37:G45) -> 13081.523 | H46: =SUM(H37:H45) -> 21916.799 | I46: =SUM(I37:I45) -> 25523.727 | J46: =SUM(J37:J45) -> 29451.636 | ... L46: =SUM(L37:L45) -> 39093.53
A47: 固定资产+在建工程 | C47: =N(历史资产负债表!E22)+N(历史资产负债表!E25) -> 5037.4875 | D47: =N(历史资产负债表!F22)+N(历史资产负债表!F25) -> 5881.0911 | E47: =N(历史资产负债表!G22)+N(历史资产负债表!G25) -> 5783.8854 | F47: =N(历史资产负债表!H22)+N(历史资产负债表!H25) -> 6327.452 | G47: =N(历史资产负债表!I22)+N(历史资产负债表!I25) -> 6589.7152 | H47: =资本开支与折旧!H80 -> 7506.5027 | I47: =资本开支与折旧!I80 -> 9145.1311 | J47: =资本开支与折旧!J80 -> 10404.481 | K47: =资本开支与折旧!K80 -> 11071.028 | L47: =资本开支与折旧!L80 -> 11357.132
A48: 无形资产及长期待摊费用 | C48: =N(历史资产负债表!E28)+N(历史资产负债表!E30) -> 318.6494 | D48: =N(历史资产负债表!F28)+N(历史资产负债表!F30) -> 388.2714 | E48: =N(历史资产负债表!G28)+N(历史资产负债表!G30) -> 471.5778 | F48: =N(历史资产负债表!H28)+N(历史资产负债表!H30) -> 458.3921 | G48: =N(历史资产负债表!I28)+N(历史资产负债表!I30) -> 455.4018 | H48: =资本开支与折旧!H86 -> 471.72091 | I48: =资本开支与折旧!I86 -> 487.19142 | J48: =资本开支与折旧!J86 -> 496.85747 | K48: =资本开支与折旧!K86 -> 501.02088 | L48: =资本开支与折旧!L86 -> 504.96779
A49: 使用权资产 | C49: =N(历史资产负债表!E27) -> 9.2459 | D49: =N(历史资产负债表!F27) -> 36.5573 | E49: =N(历史资产负债表!G27) -> 29.9601 | F49: =N(历史资产负债表!H27) -> 24.904 | G49: =N(历史资产负债表!I27) -> 20.1651 | H49: =资本开支与折旧!H87 -> 20.1651 | I49: =资本开支与折旧!I87 -> 20.1651 | J49: =资本开支与折旧!J87 -> 20.1651 | K49: =资本开支与折旧!K87 -> 20.1651 | L49: =资本开支与折旧!L87 -> 20.1651
A50: 商誉、投资性房地产及股权投资 | C50: =N(历史资产负债表!E19)+N(历史资产负债表!E20)+N(历史资产负债表!E21)+N(历史资产负债表!E29) -> 220.6149 | D50: =N(历史资产负债表!F19)+N(历史资产负债表!F20)+N(历史资产负债表!F21)+N(历史资产负债表!F29) -> 226.9448 | E50: =N(历史资产负债表!G19)+N(历史资产负债表!G20)+N(历史资产负债表!G21)+N(历史资产负债表!G29) -> 367.871 | F50: =N(历史资产负债表!H19)+N(历史资产负债表!H20)+N(历史资产负债表!H21)+N(历史资产负债表!H29) -> 294.9521 | G50: =N(历史资产负债表!I19)+N(历史资产负债表!I20)+N(历史资产负债表!I21)+N(历史资产负债表!I29) -> 311.2262 | H50: =资本开支与折旧!H89 -> 311.2262 | I50: =资本开支与折旧!I89 -> 311.2262 | J50: =资本开支与折旧!J89 -> 311.2262 | K50: =资本开支与折旧!K89 -> 311.2262 | L50: =资本开支与折旧!L89 -> 311.2262
A51: 递延所得税资产 | C51: =N(历史资产负债表!E31) -> 98.7072 | D51: =N(历史资产负债表!F31) -> 187.4023 | E51: =N(历史资产负债表!G31) -> 182.164 | F51: =N(历史资产负债表!H31) -> 247.2083 | G51: =N(历史资产负债表!I31) -> 163.9345 | H51: =G51 -> 163.9345 | I51: =H51 -> 163.9345 | J51: =I51 -> 163.9345 | K51: =J51 -> 163.9345 | L51: =K51 -> 163.9345
A52: 其他非流动资产（含定期存款） | C52: =N(历史资产负债表!E32) -> 148.8167 | D52: =N(历史资产负债表!F32) -> 52.3243 | E52: =N(历史资产负债表!G32) -> 3712.1273 | F52: =N(历史资产负债表!H32) -> 2960.8591 | G52: =N(历史资产负债表!I32) -> 5884.1223 | H52: =融资与资金!H12 -> 5884.1223 | I52: =融资与资金!I12 -> 5884.1223 | J52: =融资与资金!J12 -> 5884.1223 | K52: =融资与资金!K12 -> 5884.1223 | L52: =融资与资金!L12 -> 5884.1223
A53: 非流动资产合计 | C53: =SUM(C47:C52) -> 5833.5216 | D53: =SUM(D47:D52) -> 6772.5912 | E53: =SUM(E47:E52) -> 10547.586 | F53: =SUM(F47:F52) -> 10313.768 | G53: =SUM(G47:G52) -> 13424.565 | H53: =SUM(H47:H52) -> 14357.672 | I53: =SUM(I47:I52) -> 16011.771 | J53: =SUM(J47:J52) -> 17280.787 | ... L53: =SUM(L47:L52) -> 18241.548
A54: 资产总计 | C54: =C46+C53 -> 18620.049 | D54: =D46+D53 -> 19593.377 | E54: =E46+E53 -> 21826.965 | F54: =F46+F53 -> 23915.803 | G54: =G46+G53 -> 26506.088 | H54: =H46+H53 -> 36274.471 | I54: =I46+I53 -> 41535.498 | J54: =J46+J53 -> 46732.423 | ... L54: =L46+L53 -> 57335.078
A55: 短期借款 | C55: =N(历史资产负债表!E35) -> 42.1648 | D55: =N(历史资产负债表!F35) -> 151.8424 | E55: =N(历史资产负债表!G35) -> 740.5347 | F55: =N(历史资产负债表!H35) -> 474.7949 | G55: =N(历史资产负债表!I35) -> 539.4178 | H55: =融资与资金!H21 -> 539.4178 | I55: =融资与资金!I21 -> 539.4178 | J55: =融资与资金!J21 -> 539.4178 | K55: =融资与资金!K21 -> 539.4178 | L55: =融资与资金!L21 -> 539.4178
A56: 长期借款（含一年内到期） | C56: =N(历史资产负债表!E49)+N(历史资产负债表!E46) -> 7.7844 | D56: =N(历史资产负债表!F49)+N(历史资产负债表!F46) -> 33.593 | E56: =N(历史资产负债表!G49)+N(历史资产负债表!G46) -> 4.7445 | F56: =N(历史资产负债表!H49)+N(历史资产负债表!H46) -> 4.5523 | G56: =N(历史资产负债表!I49)+N(历史资产负债表!I46) -> 28.2196 | H56: =融资与资金!H22 -> 28.2196 | I56: =融资与资金!I22 -> 28.2196 | J56: =融资与资金!J22 -> 28.2196 | K56: =融资与资金!K22 -> 28.2196 | L56: =融资与资金!L22 -> 28.2196
A57: 应付票据 | C57: =N(历史资产负债表!E37) -> 0 | D57: =N(历史资产负债表!F37) -> 27.8661 | E57: =N(历史资产负债表!G37) -> 242.5137 | F57: =N(历史资产负债表!H37) -> 521.4807 | G57: =N(历史资产负债表!I37) -> 1119.1886 | H57: =营运资金!H21 -> 1568.7606 | I57: =营运资金!I21 -> 1975.7674 | J57: =营运资金!J21 -> 2303.7342 | K57: =营运资金!K21 -> 2580.2326 | L57: =营运资金!L21 -> 2780.5495
A58: 应付账款 | C58: =N(历史资产负债表!E38) -> 830.1951 | D58: =N(历史资产负债表!F38) -> 607.185 | E58: =N(历史资产负债表!G38) -> 738.1858 | F58: =N(历史资产负债表!H38) -> 773.8232 | G58: =N(历史资产负债表!I38) -> 808.7966 | H58: =营运资金!H22 -> 1255.0085 | I58: =营运资金!I22 -> 1580.6139 | J58: =营运资金!J22 -> 1842.9874 | K58: =营运资金!K22 -> 2064.1861 | L58: =营运资金!L22 -> 2224.4396
A59: 合同负债及预收款项 | C59: =N(历史资产负债表!E39)+N(历史资产负债表!E40) -> 25.358 | D59: =N(历史资产负债表!F39)+N(历史资产负债表!F40) -> 18.6235 | E59: =N(历史资产负债表!G39)+N(历史资产负债表!G40) -> 22.6123 | F59: =N(历史资产负债表!H39)+N(历史资产负债表!H40) -> 30.7816 | G59: =N(历史资产负债表!I39)+N(历史资产负债表!I40) -> 23.8862 | H59: =营运资金!H23 -> 55.45275 | I59: =营运资金!I23 -> 70.203612 | J59: =营运资金!J23 -> 80.620869 | K59: =营运资金!K23 -> 88.787827 | L59: =营运资金!L23 -> 94.775558
A60: 应付职工薪酬 | C60: =N(历史资产负债表!E41) -> 283.548 | D60: =N(历史资产负债表!F41) -> 242.2859 | E60: =N(历史资产负债表!G41) -> 267.3971 | F60: =N(历史资产负债表!H41) -> 347.7306 | G60: =N(历史资产负债表!I41) -> 395.6466 | H60: =营运资金!H24 -> 466.956 | I60: =营运资金!I24 -> 544.20007 | J60: =营运资金!J24 -> 612.76186 | K60: =营运资金!K24 -> 672.96198 | L60: =营运资金!L24 -> 730.19212
A61: 应交税费 | C61: =N(历史资产负债表!E42) -> 54.9989 | D61: =N(历史资产负债表!F42) -> 198.0626 | E61: =N(历史资产负债表!G42) -> 157.7104 | F61: =N(历史资产负债表!H42) -> 146.4485 | G61: =N(历史资产负债表!I42) -> 213.8164 | H61: =营运资金!H25 -> 291.12694 | I61: =营运资金!I25 -> 368.56896 | J61: =营运资金!J25 -> 423.25956 | K61: =营运资金!K25 -> 466.13609 | L61: =营运资金!L25 -> 497.57168
A62: 其他应付款 | C62: =N(历史资产负债表!E43) -> 34.0223 | D62: =N(历史资产负债表!F43) -> 54.6813 | E62: =N(历史资产负债表!G43) -> 58.1247 | F62: =N(历史资产负债表!H43) -> 90.8459 | G62: =N(历史资产负债表!I43) -> 114.3282 | H62: =营运资金!H26 -> 180.22144 | I62: =营运资金!I26 -> 228.16174 | J62: =营运资金!J26 -> 262.01782 | K62: =营运资金!K26 -> 288.56044 | L62: =营运资金!L26 -> 308.02056
A63: 其他流动负债 | C63: =N(历史资产负债表!E47) -> 295.9292 | D63: =N(历史资产负债表!F47) -> 149.1519 | E63: =N(历史资产负债表!G47) -> 168.719 | F63: =N(历史资产负债表!H47) -> 203.7941 | G63: =N(历史资产负债表!I47) -> 262.1147 | H63: =营运资金!H27 -> 318.85331 | I63: =营运资金!I27 -> 403.67077 | J63: =营运资金!J27 -> 463.56999 | K63: =营运资金!K27 -> 510.53 | L63: =营运资金!L27 -> 544.95946
A64: 租赁负债 | C64: =N(历史资产负债表!E50) -> 1.7371 | D64: =N(历史资产负债表!F50) -> 30.6415 | E64: =N(历史资产负债表!G50) -> 26.5735 | F64: =N(历史资产负债表!H50) -> 22.2459 | G64: =N(历史资产负债表!I50) -> 18.7998 | H64: =融资与资金!H24 -> 18.7998 | I64: =融资与资金!I24 -> 18.7998 | J64: =融资与资金!J24 -> 18.7998 | K64: =融资与资金!K24 -> 18.7998 | L64: =融资与资金!L24 -> 18.7998
A65: 其他非流动负债（递延收益、递延所得税负债、预计负债等） | C65: =N(历史资产负债表!E51)+N(历史资产负债表!E54)+N(历史资产负债表!E55)+N(历史资产负债表!E56)+N(历史资产负债表!E57) -> 852.7379 | D65: =N(历史资产负债表!F51)+N(历史资产负债表!F54)+N(历史资产负债表!F55)+N(历史资产负债表!F56)+N(历史资产负债表!F57) -> 976.0318 | E65: =N(历史资产负债表!G51)+N(历史资产负债表!G54)+N(历史资产负债表!G55)+N(历史资产负债表!G56)+N(历史资产负债表!G57) -> 1160.7486 | F65: =N(历史资产负债表!H51)+N(历史资产负债表!H54)+N(历史资产负债表!H55)+N(历史资产负债表!H56)+N(历史资产负债表!H57) -> 1427.5369 | G65: =N(历史资产负债表!I51)+N(历史资产负债表!I54)+N(历史资产负债表!I55)+N(历史资产负债表!I56)+N(历史资产负债表!I57) -> 1318.8309 | H65: =G65 -> 1318.8309 | I65: =H65 -> 1318.8309 | J65: =I65 -> 1318.8309 | K65: =J65 -> 1318.8309 | L65: =K65 -> 1318.8309
A66: 负债合计 | C66: =SUM(C55:C65) -> 2428.4757 | D66: =SUM(D55:D65) -> 2489.965 | E66: =SUM(E55:E65) -> 3587.8643 | F66: =SUM(F55:F65) -> 4044.0346 | G66: =SUM(G55:G65) -> 4843.0454 | H66: =SUM(H55:H65) -> 6041.6477 | I66: =SUM(I55:I65) -> 7076.4546 | J66: =SUM(J55:J65) -> 7894.2198 | ... L66: =SUM(L55:L65) -> 9085.7766
A67: 归母所有者权益 | C67: =历史资产负债表!E66 -> 16190.297 | D67: =历史资产负债表!F66 -> 17099.674 | E67: =历史资产负债表!G66 -> 18233.198 | F67: =历史资产负债表!H66 -> 19866.081 | G67: =历史资产负债表!I66 -> 21658.759 | H67: =融资与资金!H36 -> 30228.541 | I67: =融资与资金!I36 -> 34454.76 | J67: =融资与资金!J36 -> 38833.92 | K67: =融资与资金!K36 -> 43442.489 | L67: =融资与资金!L36 -> 48245.018
A68: 少数股东权益 | C68: =N(历史资产负债表!E67) -> 1.2769 | D68: =N(历史资产负债表!F67) -> 3.7382 | E68: =N(历史资产负债表!G67) -> 5.9029 | F68: =N(历史资产负债表!H67) -> 5.6872 | G68: =N(历史资产负债表!I67) -> 4.2831 | H68: =G68+H25 -> 4.2831 | I68: =H68+I25 -> 4.2831 | J68: =I68+J25 -> 4.2831 | K68: =J68+K25 -> 4.2831 | L68: =K68+L25 -> 4.2831
A69: 所有者权益合计 | C69: =C67+C68 -> 16191.574 | D69: =D67+D68 -> 17103.412 | E69: =E67+E68 -> 18239.101 | F69: =F67+F68 -> 19871.768 | G69: =G67+G68 -> 21663.042 | H69: =H67+H68 -> 30232.824 | I69: =I67+I68 -> 34459.043 | J69: =J67+J68 -> 38838.203 | ... L69: =L67+L68 -> 48249.301
A70: 负债和所有者权益总计 | C70: =C66+C69 -> 18620.049 | D70: =D66+D69 -> 19593.377 | E70: =E66+E69 -> 21826.965 | F70: =F66+F69 -> 23915.803 | G70: =G66+G69 -> 26506.088 | H70: =H66+H69 -> 36274.471 | I70: =I66+I69 -> 41535.498 | J70: =J66+J69 -> 46732.423 | ... L70: =L66+L69 -> 57335.078
A71: 校验：资产-负债-权益 | C71: =ROUND(C54-C70,3) -> 0 | D71: =ROUND(D54-D70,3) -> 0 | E71: =ROUND(E54-E70,3) -> 0 | F71: =ROUND(F54-F70,3) -> 0 | G71: =ROUND(G54-G70,3) -> 0 | H71: =ROUND(H54-H70,3) -> 0 | I71: =ROUND(I54-I70,3) -> 0 | J71: =ROUND(J54-J70,3) -> 0 | ... L71: =ROUND(L54-L70,3) -> 0
A72: 校验：资产总计-报告值（历史） | C72: =ROUND(C54-历史资产负债表!E34,3) -> 0 | D72: =ROUND(D54-历史资产负债表!F34,3) -> 0 | E72: =ROUND(E54-历史资产负债表!G34,3) -> 0 | F72: =ROUND(F54-历史资产负债表!H34,3) -> 0 | G72: =ROUND(G54-历史资产负债表!I34,3) -> 0
A73: 校验：负债合计-报告值（历史） | C73: =ROUND(C66-历史资产负债表!E59,3) -> 0 | D73: =ROUND(D66-历史资产负债表!F59,3) -> 0 | E73: =ROUND(E66-历史资产负债表!G59,3) -> 0 | F73: =ROUND(F66-历史资产负债表!H59,3) -> 0 | G73: =ROUND(G66-历史资产负债表!I59,3) -> 0
A74: 现金流量表（预测为间接法；历史为报告值）
A75: 净利润 | C75: =历史现金流量表!E40 -> 2013.312 | D75: =历史现金流量表!F40 -> 1506.1032 | E75: =历史现金流量表!G40 -> 1583.1506 | F75: =历史现金流量表!H40 -> 2190.2338 | G75: =历史现金流量表!I40 -> 2616.9802 | H75: =H24 -> 4260.3565 | I75: =I24 -> 5632.1372 | J75: =J24 -> 6237.7654 | K75: =K24 -> 6667.0317 | L75: =L24 -> 7002.6492
A76: 折旧与摊销 | C76: =N(历史现金流量表!E43)+N(历史现金流量表!E44)+N(历史现金流量表!E45)+N(历史现金流量表!E46) -> 387.5088 | D76: =N(历史现金流量表!F43)+N(历史现金流量表!F44)+N(历史现金流量表!F45)+N(历史现金流量表!F46) -> 544.3751 | E76: =N(历史现金流量表!G43)+N(历史现金流量表!G44)+N(历史现金流量表!G45)+N(历史现金流量表!G46) -> 609.4324 | F76: =N(历史现金流量表!H43)+N(历史现金流量表!H44)+N(历史现金流量表!H45)+N(历史现金流量表!H46) -> 659.1195 | G76: =N(历史现金流量表!I43)+N(历史现金流量表!I44)+N(历史现金流量表!I45)+N(历史现金流量表!I46) -> 744.1504 | H76: =H32 -> 813.65692 | I76: =I32 -> 914.99495 | J76: =J32 -> 1060.0309 | K76: =K32 -> 1212.6478 | L76: =L32 -> 1348.2187
A77: 营运资本变动（增加为负） | C77: =N(历史现金流量表!E54)+N(历史现金流量表!E55)+N(历史现金流量表!E56) -> -1302.7071 | D77: =N(历史现金流量表!F54)+N(历史现金流量表!F55)+N(历史现金流量表!F56) -> 129.5803 | E77: =N(历史现金流量表!G54)+N(历史现金流量表!G55)+N(历史现金流量表!G56) -> -335.6004 | F77: =N(历史现金流量表!H54)+N(历史现金流量表!H55)+N(历史现金流量表!H56) -> -360.6942 | G77: =N(历史现金流量表!I54)+N(历史现金流量表!I55)+N(历史现金流量表!I56) -> -322.7482 | H77: =-营运资金!H31 -> -1367.3013 | I77: =-营运资金!I31 -> -1317.9144 | J77: =-营运资金!J31 -> -926.57003 | K77: =-营运资金!K31 -> -724.33507 | L77: =-营运资金!L31 -> -509.81094
A78: 其他调整（预测：扣除理财收益、加回固定资产减值） | C78: =历史现金流量表!E14-C75-C76-C77 -> 56.2085 | D78: =历史现金流量表!F14-D75-D76-D77 -> -106.185 | E78: =历史现金流量表!G14-E75-E76-E77 -> -138.0146 | F78: =历史现金流量表!H14-F75-F76-F77 -> -85.5368 | G78: =历史现金流量表!I14-G75-G76-G77 -> -160.7733 | H78: =-H17-税务与其他损益!H17 -> -40.696186 | I78: =-I17-税务与其他损益!I17 -> -56.377674 | J78: =-J17-税务与其他损益!J17 -> -56.377674 | K78: =-K17-税务与其他损益!K17 -> -56.377674 | L78: =-L17-税务与其他损益!L17 -> -56.377674
A79: 经营活动现金流量净额 | C79: =历史现金流量表!E14 -> 1154.3222 | D79: =历史现金流量表!F14 -> 2073.8736 | E79: =历史现金流量表!G14 -> 1718.968 | F79: =历史现金流量表!H14 -> 2403.1223 | G79: =历史现金流量表!I14 -> 2877.6091 | H79: =H75+H76+H77+H78 -> 3666.0159 | I79: =I75+I76+I77+I78 -> 5172.8401 | J79: =J75+J76+J77+J78 -> 6314.8486 | K79: =K75+K76+K77+K78 -> 7098.9668 | L79: =L75+L76+L77+L78 -> 7784.6793
A80: 资本开支（流出为负） | C80: =-历史现金流量表!E20 -> -1910.3652 | D80: =-历史现金流量表!F20 -> -1124.8091 | E80: =-历史现金流量表!G20 -> -545.8847 | F80: =-历史现金流量表!H20 -> -639.0352 | G80: =-历史现金流量表!I20 -> -580.092 | H80: =-资本开支与折旧!H11 -> -1787.9753 | I80: =-资本开支与折旧!I11 -> -2593.5925 | J80: =-资本开支与折旧!J11 -> -2358.5137 | K80: =-资本开支与折旧!K11 -> -1918.9354 | L80: =-资本开支与折旧!L11 -> -1679.4592
A81: 处置长期资产收回现金 | C81: =N(历史现金流量表!E17) -> 4.687 | D81: =N(历史现金流量表!F17) -> 61.3832 | E81: =N(历史现金流量表!G17) -> 14.3567 | F81: =N(历史现金流量表!H17) -> 29.458 | G81: =N(历史现金流量表!I17) -> 3.726 | H81: =资本开支与折旧!H79 -> 26.771821 | I81: =资本开支与折旧!I79 -> 29.498599 | J81: =资本开支与折旧!J79 -> 34.46691 | K81: =资本开支与折旧!K79 -> 40.577488 | L81: =资本开支与折旧!L79 -> 46.189582
A82: 理财收益、理财与定期存款净额及其他投资 | C82: =历史现金流量表!E24-C80-C81 -> 28.914 | D82: =历史现金流量表!F24-D80-D81 -> -2743.301 | E82: =历史现金流量表!G24-E80-E81 -> -3243.397 | F82: =历史现金流量表!H24-F80-F81 -> -744.3539 | G82: =历史现金流量表!I24-G80-G81 -> -247.9944 | H82: =H17-(H38-G38)-(H52-G52)-(H51-G51)-(H50-G50) -> 60.136186 | I82: =I17-(I38-H38)-(I52-H52)-(I51-H51)-(I50-H50) -> 56.377674 | J82: =J17-(J38-I38)-(J52-I52)-(J51-I51)-(J50-I50) -> 56.377674 | K82: =K17-(K38-J38)-(K52-J52)-(K51-J51)-(K50-J50) -> 56.377674 | L82: =L17-(L38-K38)-(L52-K52)-(L51-K51)-(L50-K50) -> 56.377674
A83: 投资活动现金流量净额 | C83: =历史现金流量表!E24 -> -1876.7642 | D83: =历史现金流量表!F24 -> -3806.7269 | E83: =历史现金流量表!G24 -> -3774.925 | F83: =历史现金流量表!H24 -> -1353.9311 | G83: =历史现金流量表!I24 -> -824.3604 | H83: =H80+H81+H82 -> -1701.0673 | I83: =I80+I81+I82 -> -2507.7162 | J83: =J80+J81+J82 -> -2267.6691 | K83: =K80+K81+K82 -> -1821.9802 | L83: =L80+L81+L82 -> -1576.8919
A84: 借款净增加 | C84: =N(历史现金流量表!E27)-N(历史现金流量表!E30) -> -90 | D84: =N(历史现金流量表!F27)-N(历史现金流量表!F30) -> 0 | E84: =N(历史现金流量表!G27)-N(历史现金流量表!G30) -> 650.1106 | F84: =N(历史现金流量表!H27)-N(历史现金流量表!H30) -> -650.3425 | G84: =N(历史现金流量表!I27)-N(历史现金流量表!I30) -> 24.975 | H84: =H55-G55+H56-G56 -> 0 | I84: =I55-H55+I56-H56 -> 0 | J84: =J55-I55+J56-I56 -> 0 | K84: =K55-J55+K56-J56 -> 0 | L84: =L55-K55+L56-K56 -> 0
A85: 现金股利（历史含利息支付） | C85: =-历史现金流量表!E31 -> -454.2265 | D85: =-历史现金流量表!F31 -> -617.7758 | E85: =-历史现金流量表!G31 -> -489.9347 | F85: =-历史现金流量表!H31 -> -553.6596 | G85: =-历史现金流量表!I31 -> -726.6256 | H85: =-融资与资金!H39 -> -860.11 | I85: =-融资与资金!I39 -> -1405.9177 | J85: =-融资与资金!J39 -> -1858.6053 | K85: =-融资与资金!K39 -> -2058.4626 | L85: =-融资与资金!L39 -> -2200.1205
A86: 股份回购 | C86: =0 -> 0 | D86: =0 -> 0 | E86: =0 -> 0 | F86: =0 -> 0 | G86: =-股本与每股!G9 -> -175.44073 | H86: =-融资与资金!H42 -> -1644.66 | I86: =-融资与资金!I42 -> 0 | J86: =-融资与资金!J42 -> 0 | K86: =-融资与资金!K42 -> 0 | L86: =-融资与资金!L42 -> 0
A87: H股募资净额及其他股权融资 | C87: =N(历史现金流量表!E25) -> 3882.12 | D87: =N(历史现金流量表!F25) -> 0 | E87: =N(历史现金流量表!G25) -> 0 | F87: =N(历史现金流量表!H25) -> 0 | G87: =N(历史现金流量表!I25) -> 0 | H87: =股本与每股!H7 -> 6814.1945 | I87: =股本与每股!I7 -> 0 | J87: =股本与每股!J7 -> 0 | K87: =股本与每股!K7 -> 0 | L87: =股本与每股!L7 -> 0
A88: 租赁付款（本金） | H88: =-资本开支与折旧!H88 -> -5 | I88: =-资本开支与折旧!I88 -> -5 | J88: =-资本开支与折旧!J88 -> -5 | K88: =-资本开支与折旧!K88 -> -5 | L88: =-资本开支与折旧!L88 -> -5
A89: 其他筹资活动 | C89: =历史现金流量表!E35-C84-C85-C86-C87 -> -9.7845 | D89: =历史现金流量表!F35-D84-D85-D86-D87 -> -11.1512 | E89: =历史现金流量表!G35-E84-E85-E86-E87 -> -6.2401 | F89: =历史现金流量表!H35-F84-F85-F86-F87 -> -1.525 | G89: =历史现金流量表!I35-G84-G85-G86-G87 -> -16.589268 | H89: =(H65-G65)+(H64-G64) -> 0 | I89: =(I65-H65)+(I64-H64) -> 0 | J89: =(J65-I65)+(J64-I64) -> 0 | K89: =(K65-J65)+(K64-J64) -> 0 | L89: =(L65-K65)+(L64-K64) -> 0
A90: 筹资活动现金流量净额 | C90: =历史现金流量表!E35 -> 3328.109 | D90: =历史现金流量表!F35 -> -628.927 | E90: =历史现金流量表!G35 -> 153.9358 | F90: =历史现金流量表!H35 -> -1205.5271 | G90: =历史现金流量表!I35 -> -893.6806 | H90: =H84+H85+H86+H87+H88+H89 -> 4304.4245 | I90: =I84+I85+I86+I87+I88+I89 -> -1410.9177 | J90: =J84+J85+J86+J87+J88+J89 -> -1863.6053 | K90: =K84+K85+K86+K87+K88+K89 -> -2063.4626 | L90: =L84+L85+L86+L87+L88+L89 -> -2205.1205
A91: 汇率变动影响 | C91: =历史现金流量表!E36 -> -8.1464 | D91: =历史现金流量表!F36 -> 9.9994 | E91: =历史现金流量表!G36 -> 7.436 | F91: =历史现金流量表!H36 -> -0.4631 | G91: =历史现金流量表!I36 -> -14.4299 | H91: =0 -> 0 | I91: =0 -> 0 | J91: =0 -> 0 | K91: =0 -> 0 | L91: =0 -> 0
A92: 现金净增加额 | C92: =C79+C83+C90+C91 -> 2597.5206 | D92: =D79+D83+D90+D91 -> -2351.7809 | E92: =E79+E83+E90+E91 -> -1894.5852 | F92: =F79+F83+F90+F91 -> -156.799 | G92: =G79+G83+G90+G91 -> 1145.1382 | H92: =H79+H83+H90+H91 -> 6269.3731 | I92: =I79+I83+I90+I91 -> 1254.2063 | J92: =J79+J83+J90+J91 -> 2183.5741 | ... L92: =L79+L83+L90+L91 -> 4002.6669
A93: 自由现金流（经营现金流-资本开支） | C93: =C79+C80 -> -756.043 | D93: =D79+D80 -> 949.0645 | E93: =E79+E80 -> 1173.0833 | F93: =F79+F80 -> 1764.0871 | G93: =G79+G80 -> 2297.5171 | H93: =H79+H80 -> 1878.0406 | I93: =I79+I80 -> 2579.2476 | J93: =J79+J80 -> 3956.3348 | ... L93: =L79+L80 -> 6105.2201
A94: 校验：现金净增加额-报告值（历史） | C94: =ROUND(C92-历史现金流量表!E37,2) -> 0 | D94: =ROUND(D92-历史现金流量表!F37,2) -> 0 | E94: =ROUND(E92-历史现金流量表!G37,2) -> 0 | F94: =ROUND(F92-历史现金流量表!H37,2) -> 0 | G94: =ROUND(G92-历史现金流量表!I37,2) -> 0
A95: 校验：货币资金变动-现金净增加额（预测） | H95: =ROUND((H37-G37)-H92,4) -> 0 | I95: =ROUND((I37-H37)-I92,4) -> 0 | J95: =ROUND((J37-I37)-J92,4) -> 0 | K95: =ROUND((K37-J37)-K92,4) -> 0 | L95: =ROUND((L37-K37)-L92,4) -> 0

Sheet 回报分析
A1: 回报、杜邦分解与现金转换
A2: ROE=净利率×总资产周转率×权益乘数（平均口径）；ROIC=NOPAT/平均投入资本（权益+有息负债+租赁负债-现金类资产）。
A4: 项目（百万元，另注明除外） | B4: 单位 | C4: 2021A | D4: 2022A | E4: 2023A | F4: 2024A | G4: 2025A | H4: 2026E | I4: 2027E | J4: 2028E | K4: 2029E | L4: 2030E | M4: 来源/说明
A5: 归母净利率 | B5: % | C5: =三表预测!C28 -> 0.32338339 | D5: =三表预测!D28 -> 0.29221071 | E5: =三表预测!E28 -> 0.2760733 | F5: =三表预测!F28 -> 0.29701043 | G5: =三表预测!G28 -> 0.29070047 | H5: =三表预测!H28 -> 0.30731436 | I5: =三表预测!I28 -> 0.32090299 | J5: =三表预测!J28 -> 0.30948639 | ... L5: =三表预测!L28 -> 0.29554663
A6: 总资产周转率（收入/平均总资产） | B6: x | D6: =IFERROR(三表预测!D6/AVERAGE(三表预测!C54,三表预测!D54),0) -> 0.26950669 | E6: =IFERROR(三表预测!E6/AVERAGE(三表预测!D54,三表预测!E54),0) -> 0.27651576 | F6: =IFERROR(三表预测!F6/AVERAGE(三表预测!E54,三表预测!F54),0) -> 0.32245495 | G6: =IFERROR(三表预测!G6/AVERAGE(三表预测!F54,三表预测!G54),0) -> 0.35727157 | H6: =IFERROR(三表预测!H6/AVERAGE(三表预测!G54,三表预测!H54),0) -> 0.44163951 | I6: =IFERROR(三表预测!I6/AVERAGE(三表预测!H54,三表预测!I54),0) -> 0.45112222 | J6: =IFERROR(三表预测!J6/AVERAGE(三表预测!I54,三表预测!J54),0) -> 0.45668272 | K6: =IFERROR(三表预测!K6/AVERAGE(三表预测!J54,三表预测!K54),0) -> 0.44953195 | L6: =IFERROR(三表预测!L6/AVERAGE(三表预测!K54,三表预测!L54),0) -> 0.43332501
A7: 权益乘数（平均总资产/平均归母权益） | B7: x | D7: =IFERROR(AVERAGE(三表预测!C54,三表预测!D54)/AVERAGE(三表预测!C67,三表预测!D67),0) -> 1.1478961 | E7: =IFERROR(AVERAGE(三表预测!D54,三表预测!E54)/AVERAGE(三表预测!D67,三表预测!E67),0) -> 1.1722891 | F7: =IFERROR(AVERAGE(三表预测!E54,三表预测!F54)/AVERAGE(三表预测!E67,三表预测!F67),0) -> 1.2006203 | G7: =IFERROR(AVERAGE(三表预测!F54,三表预测!G54)/AVERAGE(三表预测!F67,三表预测!G67),0) -> 1.2142585 | H7: =IFERROR(AVERAGE(三表预测!G54,三表预测!H54)/AVERAGE(三表预测!G67,三表预测!H67),0) -> 1.2099408 | I7: =IFERROR(AVERAGE(三表预测!H54,三表预测!I54)/AVERAGE(三表预测!H67,三表预测!I67),0) -> 1.2029375 | J7: =IFERROR(AVERAGE(三表预测!I54,三表预测!J54)/AVERAGE(三表预测!I67,三表预测!J67),0) -> 1.2043868 | K7: =IFERROR(AVERAGE(三表预测!J54,三表预测!K54)/AVERAGE(三表预测!J67,三表预测!K67),0) -> 1.2002937 | L7: =IFERROR(AVERAGE(三表预测!K54,三表预测!L54)/AVERAGE(三表预测!K67,三表预测!L67),0) -> 1.1927308
A8: ROE（杜邦，平均口径） | B8: % | D8: =D5*D6*D7 -> 0.090399961 | E8: =E5*E6*E7 -> 0.089490933 | F8: =F5*F6*F7 -> 0.11498639 | G8: =G5*G6*G7 -> 0.12611169 | H8: =H5*H6*H7 -> 0.16421577 | I8: =I5*I6*I7 -> 0.17414502 | J8: =J5*J6*J7 -> 0.17022453 | K8: =K5*K6*K7 -> 0.16206424 | L8: =L5*L6*L7 -> 0.15275034
A9: NOPAT（EBIT×(1-实际税率)） | B9: 百万元 | C9: =三表预测!C31*(1-税务与其他损益!C28) -> 1854.6016 | D9: =三表预测!D31*(1-税务与其他损益!D28) -> 1263.5839 | E9: =三表预测!E31*(1-税务与其他损益!E28) -> 1344.0928 | F9: =三表预测!F31*(1-税务与其他损益!F28) -> 1982.3998 | G9: =三表预测!G31*(1-税务与其他损益!G28) -> 2400.9121 | H9: =三表预测!H31*(1-税务与其他损益!H28) -> 3989.8532 | I9: =三表预测!I31*(1-税务与其他损益!I28) -> 5348.8946 | J9: =三表预测!J31*(1-税务与其他损益!J28) -> 5949.0804 | ... L9: =三表预测!L31*(1-税务与其他损益!L28) -> 6653.2581
A10: 投入资本（权益+有息负债+租赁-现金-理财-其他非流动资产） | B10: 百万元 | C10: =三表预测!C69+三表预测!C55+三表预测!C56+三表预测!C64-三表预测!C37-三表预测!C38-三表预测!C52 -> 7848.4362 | D10: =三表预测!D69+三表预测!D55+三表预测!D56+三表预测!D64-三表预测!D37-三表预测!D38-三表预测!D52 -> 8502.7208 | E10: =三表预测!E69+三表预测!E55+三表预测!E56+三表预测!E64-三表预测!E37-三表预测!E38-三表预测!E52 -> 8610.5029 | F10: =三表预测!F69+三表预测!F55+三表预测!F56+三表预测!F64-三表预测!F37-三表预测!F38-三表预测!F52 -> 9296.2702 | G10: =三表预测!G69+三表预测!G55+三表预测!G56+三表预测!G64-三表预测!G37-三表预测!G38-三表预测!G52 -> 9549.0671 | H10: =三表预测!H69+三表预测!H55+三表预测!H56+三表预测!H64-三表预测!H37-三表预测!H38-三表预测!H52 -> 11849.475 | I10: =三表预测!I69+三表预测!I55+三表预测!I56+三表预测!I64-三表预测!I37-三表预测!I38-三表预测!I52 -> 14821.489 | J10: =三表预测!J69+三表预测!J55+三表预测!J56+三表预测!J64-三表预测!J37-三表预测!J38-三表预测!J52 -> 17017.075 | ... L10: =三表预测!L69+三表预测!L55+三表预测!L56+三表预测!L64-三表预测!L37-三表预测!L38-三表预测!L52 -> 19211.981
A11: ROIC（NOPAT/平均投入资本） | B11: % | D11: =IFERROR(D9/AVERAGE(C10,D10),0) -> 0.15455591 | E11: =IFERROR(E9/AVERAGE(D10,E10),0) -> 0.15708236 | F11: =IFERROR(F9/AVERAGE(E10,F10),0) -> 0.22141341 | G11: =IFERROR(G9/AVERAGE(F10,G10),0) -> 0.25480171 | H11: =IFERROR(H9/AVERAGE(G10,H10),0) -> 0.37290887 | I11: =IFERROR(I9/AVERAGE(H10,I10),0) -> 0.40110246 | J11: =IFERROR(J9/AVERAGE(I10,J10),0) -> 0.37370282 | K11: =IFERROR(K9/AVERAGE(J10,K10),0) -> 0.35914986 | L11: =IFERROR(L9/AVERAGE(K10,L10),0) -> 0.35367001
A12: 增量ROIC（ΔNOPAT/Δ投入资本） | B12: % | D12: =IFERROR((D9-C9)/(D10-C10),0) -> -0.90330361 | E12: =IFERROR((E9-D9)/(E10-D10),0) -> 0.74695945 | F12: =IFERROR((F9-E9)/(F10-E10),0) -> 0.93079242 | G12: =IFERROR((G9-F9)/(G10-F10),0) -> 1.6555277 | H12: =IFERROR((H9-G9)/(H10-G10),0) -> 0.69072138 | I12: =IFERROR((I9-H9)/(I10-H10),0) -> 0.45727971 | J12: =IFERROR((J9-I9)/(J10-I10),0) -> 0.27336019 | K12: =IFERROR((K9-J9)/(K10-J10),0) -> 0.29613004 | L12: =IFERROR((L9-K9)/(L10-K10),0) -> 0.36389162
A13: 现金转换率（经营现金流/净利润） | B13: % | C13: =IFERROR(三表预测!C79/三表预测!C24,0) -> 0.57334489 | D13: =IFERROR(三表预测!D79/三表预测!D24,0) -> 1.3769797 | E13: =IFERROR(三表预测!E79/三表预测!E24,0) -> 1.0857894 | F13: =IFERROR(三表预测!F79/三表预测!F24,0) -> 1.0971991 | G13: =IFERROR(三表预测!G79/三表预测!G24,0) -> 1.0995916 | H13: =IFERROR(三表预测!H79/三表预测!H24,0) -> 0.8604951 | I13: =IFERROR(三表预测!I79/三表预测!I24,0) -> 0.91845065 | J13: =IFERROR(三表预测!J79/三表预测!J24,0) -> 1.0123575 | ... L13: =IFERROR(三表预测!L79/三表预测!L24,0) -> 1.1116763
A14: 自由现金流/净利润 | B14: % | C14: =IFERROR(三表预测!C93/三表预测!C24,0) -> -0.37552201 | D14: =IFERROR(三表预测!D93/三表预测!D24,0) -> 0.63014573 | E14: =IFERROR(三表预测!E93/三表预测!E24,0) -> 0.74098033 | F14: =IFERROR(三表预测!F93/三表预测!F24,0) -> 0.80543331 | G14: =IFERROR(三表预测!G93/三表预测!G24,0) -> 0.87792695 | H14: =IFERROR(三表预测!H93/三表预测!H24,0) -> 0.44081771 | I14: =IFERROR(三表预测!I93/三表预测!I24,0) -> 0.45795185 | J14: =IFERROR(三表预测!J93/三表预测!J24,0) -> 0.63425515 | ... L14: =IFERROR(三表预测!L93/三表预测!L24,0) -> 0.87184435
A15: 自由现金流收益率（FCF/当前市值） | B15: % | H15: =IFERROR(三表预测!H93/(假设!$C$6*股本与每股!H12),0) -> 0.0080175933 | I15: =IFERROR(三表预测!I93/(假设!$C$6*股本与每股!I12),0) -> 0.011011135 | J15: =IFERROR(三表预测!J93/(假设!$C$6*股本与每股!J12),0) -> 0.016890095 | K15: =IFERROR(三表预测!K93/(假设!$C$6*股本与每股!K12),0) -> 0.022114211 | L15: =IFERROR(三表预测!L93/(假设!$C$6*股本与每股!L12),0) -> 0.026063959
A16: PE（当前股价/EPS） | B16: x | C16: =IFERROR(假设!$C$6/三表预测!C29,0) -> 112.94193 | D16: =IFERROR(假设!$C$6/三表预测!D29,0) -> 150.92978 | E16: =IFERROR(假设!$C$6/三表预测!E29,0) -> 143.64768 | F16: =IFERROR(假设!$C$6/三表预测!F29,0) -> 103.67962 | G16: =IFERROR(假设!$C$6/三表预测!G29,0) -> 86.502435 | H16: =IFERROR(假设!$C$6/三表预测!H29,0) -> 54.9813 | I16: =IFERROR(假设!$C$6/三表预测!I29,0) -> 41.589885 | J16: =IFERROR(假设!$C$6/三表预测!J29,0) -> 37.5519 | ... L16: =IFERROR(假设!$C$6/三表预测!L29,0) -> 33.450189
