Workbook

Sheet 封面
A1: 烽火通信（600498.SH）财务与估值模型
A2: 单位：人民币百万元（除特别注明）｜模型日期：2026-10-06｜数据：2021–2026H1定期报告、Wind
A5: 市场数据
A6: 股价（元） | C6: =假设!$C$8 -> 35.7
A7: 总股本（百万股，2025年末） | C7: =融资!G35 -> 1358.1675
A8: 总市值（百万元） | C8: =C6*C7 -> 48486.58
A9: 净负债（2026H1末） | C9: =融资!N19 -> 7606.4549
A10: 当前情景 | C10: =假设!$D$5 -> 基准
A11: 模型核对 | C11: =核对!$C$18 -> OK
A13: 核心财务摘要
A14: 百万元 | C14: 2023A | D14: 2024A | E14: 2025A | F14: 2026E | G14: 2027E | H14: 2028E
A15: 营业收入 | C15: =利润表!E6 -> 31129.574 | D15: =利润表!F6 -> 28548.831 | E15: =利润表!G6 -> 24918.554 | F15: =利润表!H6 -> 27563.516 | G15: =利润表!I6 -> 29404.632 | H15: =利润表!J6 -> 30868.269
A16: 增速 | C16: =利润表!E39 -> 0.0068476148 | D16: =利润表!F39 -> -0.082903267 | E16: =利润表!G39 -> -0.12716024 | F16: =利润表!H39 -> 0.10614427 | G16: =利润表!I39 -> 0.066795386 | H16: =利润表!J39 -> 0.049775731
A17: 毛利率 | C17: =利润表!E41 -> 0.20563882 | D17: =利润表!F41 -> 0.2124839 | E17: =利润表!G41 -> 0.21098038 | F17: =利润表!H41 -> 0.21047025 | G17: =利润表!I41 -> 0.20761988 | H17: =利润表!J41 -> 0.20216644
A18: 其中：光纤及线缆毛利 | C18: =分业务!E20 -> 1144.0746 | D18: =分业务!F20 -> 1191.1576 | E18: =分业务!G20 -> 1171.2275 | F18: =分业务!H20 -> 2559.7537 | G18: =分业务!I20 -> 2363.6765 | H18: =分业务!J20 -> 2003.6361
A19: 通信系统设备毛利率 | C19: =分业务!E11 -> 0.19240917 | D19: =分业务!F11 -> 0.19455531 | E19: =分业务!G11 -> 0.18813578 | F19: =分业务!H11 -> 0.138 | G19: =分业务!I11 -> 0.148 | H19: =分业务!J11 -> 0.158
A20: 归母净利润 | C20: =利润表!E29 -> 505.3671 | D20: =利润表!F29 -> 702.7062 | E20: =利润表!G29 -> 435.8343 | F20: =利润表!H29 -> 751.93618 | G20: =利润表!I29 -> 1075.8572 | H20: =利润表!J29 -> 1153.3271
A21: 增速 | C21: =利润表!E40 -> 0.24538059 | D21: =利润表!F40 -> 0.39048664 | E21: =利润表!G40 -> -0.37977735 | F21: =利润表!H40 -> 0.72527995 | G21: =利润表!I40 -> 0.43078253 | H21: =利润表!J40 -> 0.072007641
A22: 其中：广发基金权益法收益 | C22: =费用!E31 -> 276.60252 | D22: =费用!F31 -> 283.69318 | E22: =费用!G31 -> 390.63195 | F22: =费用!H31 -> 636.73008 | G22: =费用!I31 -> 668.56658 | H22: =费用!J31 -> 701.99491
A23: 扣除广发基金后归母净利润 | C23: =费用!E47 -> 228.76458 | D23: =费用!F47 -> 419.01302 | E23: =费用!G47 -> 45.202348 | F23: =费用!H47 -> 115.2061 | G23: =费用!I47 -> 407.29057 | H23: =费用!J47 -> 451.33217
A24: EPS（元） | C24: =利润表!E33 -> 0.42629339 | D24: =利润表!F33 -> 0.59326911 | E24: =利润表!G33 -> 0.32089878 | F24: =利润表!H33 -> 0.55364024 | G24: =利润表!I33 -> 0.73928836 | H24: =利润表!J33 -> 0.79252277
A25: PE（现价） | C25: =假设!$C$8/利润表!E33 -> 83.745142 | D25: =假设!$C$8/利润表!F33 -> 60.175053 | E25: =假设!$C$8/利润表!G33 -> 111.25003 | F25: =假设!$C$8/利润表!H33 -> 64.482307 | G25: =假设!$C$8/利润表!I33 -> 48.289682 | H25: =假设!$C$8/利润表!J33 -> 45.046024
A26: ROE | C26: =利润表!E48 -> 0.03994201 | D26: =利润表!F48 -> 0.05181508 | E26: =利润表!G48 -> 0.027681914 | F26: =利润表!H48 -> 0.042129914 | G26: =利润表!I48 -> 0.053729334 | H26: =利润表!J48 -> 0.0517084
A27: 经营活动现金流 | C27: =现金流量表!E14 -> 59.1655 | D27: =现金流量表!F14 -> 4638.1759 | E27: =现金流量表!G14 -> 4772.5558 | F27: =现金流量表!H14 -> 1854.9649 | G27: =现金流量表!I14 -> 2483.0044 | H27: =现金流量表!J14 -> 2948.6133
A28: 资本开支（含资本化研发） | C28: =资本开支折旧!E72 -> 1202.9214 | D28: =资本开支折旧!F72 -> 1600.9212 | E28: =资本开支折旧!G72 -> 1710.5607 | F28: =资本开支折旧!H72 -> 1964.5516 | G28: =资本开支折旧!I72 -> 2349.626 | H28: =资本开支折旧!J72 -> 2228.9986
A29: 应收账款周转天数 | C29: =营运资本!E12 -> 145.53059 | D29: =营运资本!F12 -> 195.11176 | E29: =营运资本!G12 -> 216.94813 | F29: =营运资本!H12 -> 200 | G29: =营运资本!I12 -> 190 | H29: =营运资本!J12 -> 180
A30: 净负债 | C30: =融资!E19 -> 1791.1842 | D30: =融资!F19 -> 5034.7064 | E30: =融资!G19 -> 5247.5823 | F30: =融资!H19 -> 5739.031 | G30: =融资!I19 -> 3052.8433 | H30: =融资!J19 -> 2676.4591
A32: 估值汇总（元/股）
A33: 方法 | C33: 每股价值 | D33: 空间
A34: DCF（FCFF） | C34: =估值_DCF!$D$37 -> 15.647377 | D34: =IF(ISNUMBER(C34),C34/假设!$C$8-1,"n.m.") -> -0.56169812 | I34: WACC/永续增长见估值_DCF；对营运资本高度敏感
A35: SOTP（2027E分部PE+广发基金股权） | C35: =估值_SOTP!$E$44 -> 37.79882 | D35: =IF(ISNUMBER(C35),C35/假设!$C$8-1,"n.m.") -> 0.058790466 | I35: 光纤按周期折价PE；广发基金按15x PE
A36: 目标PE（2027E） | C36: =估值_相对!$C$39 -> 22.178651 | D36: =IF(ISNUMBER(C36),C36/假设!$C$8-1,"n.m.") -> -0.37874927 | I36: 目标PE见假设表
A37: 三种方法简单平均 | C37: =AVERAGE(C34:C36) -> 25.208283 | D37: =C37/假设!$C$8-1 -> -0.29388564
A39: 模型结构（工作表导航）
A40: 假设 | C40: 情景开关（1基准/2乐观/3悲观）、市场与估值参数、全部经营驱动假设（三情景）
A41: 分业务 | C41: 通信系统设备/光纤及线缆（量×价）/数据网络产品/其他：收入、成本、毛利；分地区；H1对比；成本构成
A42: 费用 | C42: 期间费用、研发投入与资本化、其他收益、减值、广发基金投资收益、盈利质量分析
A43: 资本开支折旧 | C43: 固定资产原值/累计折旧滚动、在建工程、无形资产、开发支出、D&A与资本开支汇总
A44: 营运资本 | C44: 应收/存货/预付/应付/合同负债等驱动与周转天数、净营运资本变动
A45: 融资 | C45: 现金、短期借款平衡项、长期借款、利息、股本与定增、分红、少数股东、偿债指标
A46: 利润表/资产负债表/现金流量表 | C46: 三表联动（历史链接“历史报表”，预测由明细表驱动），含平衡核对
A47: 估值_DCF / 估值_SOTP / 估值_相对 | C47: FCFF折现+敏感性；分部加总+市场隐含预期；可比PE、一致预期对比、PE矩阵
A48: 情景分析 | C48: 三情景关键结果快照对比
A49: 季度数据 / 历史报表 / 核对 | C49: 单季利润表；Wind原始三表（2019–2026H1）；全模型核对
A51: 颜色约定
A52: 蓝色字体 | C52: 硬编码输入（历史数据、假设）
A53: 黑色字体 | C53: 公式计算
A54: 绿色字体 | C54: 链接其他工作表
A55: 黄色底色 | C55: 关键开关/输入（情景、股价、广发基金PE、永续增长率）
A56: 浅绿底色 | C56: “▶采用”假设行与关键输出
A57: 灰色底色列 | C57: 预测期（2026E–2030E）
A59: 关键发现
A60: 1. 利润的“隐形支柱”是广发基金：烽火持股14.187%，2025年权益法收益约3.9亿元，占归母净利润90%；2026H1广发基金净利润24.6亿元（同比+108%），贡献约3.5亿元，超过同期归母净利润1.93亿元。
A61: 2. 光纤涨价真实但被主业毛利率下滑抵消：2026H1光纤及线缆收入+48%、毛利率42.3%（+16.8pp），而通信系统设备毛利率从21.2%降至15.0%，毛利减少约5.1亿元。
A62: 3. 盈利质量：研发资本化率由2021–2023年约7%升至2024–2025年约19%，每年额外资本化约4亿元；Q4研发费用异常偏低。
A63: 4. 营运资本与现金流：应收账款周转天数由2021年59天升至2025年217天；2024–2025年经营现金流46–48亿元主要来自供应链融资列报（短期借款非现金增加68.5亿/60.0亿元），剔除后约−22亿/−12亿元。
A64: 5. 光纤利润集中在子公司武汉烽火光纤：2026H1净利4.88亿元（2025全年0.21亿元），4月已收回藤仓40%股权；但同期烽火星空亏3.75亿、烽火国际亏1.72亿，其余业务合计约亏6.6亿元。
A65: 6. 2026年7月定增预案（≤29.13亿元）：多模/特种光纤9.42亿、超大规格光棒5.28亿、收购藤仓烽火60%股权5.00亿、泰国3.61亿、空芯研发2.81亿、补流3.00亿——押注光纤景气延续，按30元发行摊薄约7%。

Sheet 假设
A1: 核心假设与情景（百万元）
A2: 黄色单元格=情景开关/关键输入；蓝色=硬编码假设；“▶采用”行为模型实际引用的数值（随情景切换）；历史列为实际值（链接自各明细表）
A5: 情景选择（1=基准，2=乐观，3=悲观） | C5: 1 | D5: =CHOOSE($C$5,"基准","乐观","悲观") -> 基准 | O5: 切换后全模型重算；“情景分析”表为三种情景的快照对比
A7: 市场与估值参数
A8: 当前股价（元/股） | C8: 35.7 | O8: 2026-10-06 Wind一致预期页倒推：PE(2026E)37.50x × EPS 0.952 = 35.70；9/29收盘37.00（跌停）。可手动更新
A9: 估值基准日 | C9: 46301 | O9: 国庆休市，最后交易日约9/30
A10: DCF折现基准（2026年末） | C10: 46387 | O10: 先求2026年末价值，再按股权成本折回估值基准日
A11: 无风险利率 | C11: 0.019 | O11: 10年期国债收益率（假设，约1.8%–2.0%）
A12: 股权风险溢价 | C12: 0.065 | O12: A股常用5.5%–7%
A13: Beta | C13: 1.2 | O13: 通信设备/光纤高波动；52周区间21.34–87.58元
A14: 税前债务成本 | C14: 0.03 | O14: 2025年利息支出3.28亿/平均有息借款约108.7亿≈3.0%
A15: 目标债务占比 D/(D+E) | C15: 0.2 | O15: 按市值计约19%（2025年末有息负债116亿/(市值485亿+116亿)）
A16: WACC所用税率 | C16: 0.15 | O16: 高新技术企业15%
A17: 永续增长率 | C17: 0.02
A18: 广发基金持股比例 | C18: 0.14187 | O18: 2025年年报 附注十、3：14.187%，权益法
A19: 广发基金股权估值PE（x） | C19: 15 | O19: 公募基金公司股权交易常见10–20x PE；可调
A20: SOTP PE：通信系统设备（x） | C20: 25 | O20: 参考中兴通讯PE(TTM)36.7x（2026-08-10），考虑毛利率较低打折
A21: SOTP PE：光纤及线缆（x） | C21: 18 | O21: 景气高点盈利给周期性折价；亨通43x/中天34x/长飞109x（TTM，2026-09）
A22: SOTP PE：数据网络产品（x） | C22: 25 | O22: 烽火星空等软件/数据业务
A23: SOTP PE：其他业务（x） | C23: 10
A24: 费用分摊系数：通信系统设备 | C24: 1.15 | O24: 期间费用（含研发、财务费用）按“收入×系数”分摊至各分部
A25: 费用分摊系数：光纤及线缆 | C25: 0.5 | O25: 光纤光缆研发/销售强度低
A26: 费用分摊系数：数据网络产品 | C26: 1.2
A27: 费用分摊系数：其他业务 | C27: 0.5
A28: SOTP P/S下限：通信系统设备（x） | C28: 0.4 | O28: 分部亏损时按市销率兜底（运营商设备/服务器资产的重置与战略价值）
A29: SOTP P/S下限：光纤及线缆（x） | C29: 1
A30: SOTP P/S下限：数据网络产品（x） | C30: 1
A31: SOTP P/S下限：其他业务（x） | C31: 0.2
A32: 少数股东权益估值倍数（P/B） | C32: 1
A33: 相对估值目标PE（2027E，x） | C33: 30 | O33: 参考光通信/通信设备可比公司PE(TTM)中位数约40x，考虑盈利质量折价
A34: 最低现金余额（百万元） | C34: 4500 | O34: 低于此值以短期借款补足；高于此值优先偿还短期借款
A35: 短期借款下限（百万元） | C35: 3000 | O35: 维持银行授信与票据业务
A36: 长期借款中一年内到期比例 | C36: 0.1 | O36: 2025年末4.64/47.04亿≈9.9%
A37: 一年内到期的租赁负债（百万元） | C37: 59.958738 | O37: 2025年末一年内到期非流动负债524.37−长期借款一年内到期464.41
A38: 广发基金分红/上年权益法收益 | C38: 0.4 | O38: 2025年收到1.20亿/2024年收益2.84亿=42%；2026H1已收1.44亿
A39: 无形资产摊销中内部研发形成部分占比 | C39: 0.6 | O39: 2025年非专利技术摊销1.87亿/总摊销3.05亿=61%
A40: 2026年定增发行价（元/股） | C40: 30 | O40: 预案：不低于定价基准日前20日均价80%；假设值
A41: 定增发行费用率 | C41: 0.011 | O41: 参考2025年定增：费用690万/募资11.0亿≈0.6%；取1.1%保守
A43: 项目 | B43: 单位 | C43: 2021A | D43: 2022A | E43: 2023A | F43: 2024A | G43: 2025A | H43: 2026E | I43: 2027E | J43: 2028E | K43: 2029E | L43: 2030E | O43: 说明 / 来源
A44: 一、分业务驱动
A45: 通信系统设备 收入增速 ▶采用 | C45: =分业务!C8 -> 0.31695121 | D45: =分业务!D8 -> 0.22413118 | E45: =分业务!E8 -> 0.1371869 | F45: =分业务!F8 -> -0.061877014 | G45: =分业务!G8 -> -0.16396604 | H45: =CHOOSE(假设!$C$5,H46,H47,H48) -> 0.04 | I45: =CHOOSE(假设!$C$5,I46,I47,I48) -> 0.08 | J45: =CHOOSE(假设!$C$5,J46,J47,J48) -> 0.07 | K45: =CHOOSE(假设!$C$5,K46,K47,K48) -> 0.06 | L45: =CHOOSE(假设!$C$5,L46,L47,L48) -> 0.05 | O45: 2026H1 +2.7%；运营商传统网络投资下行 vs 服务器/AI算力、海外增量
A46: 基准 | H46: 0.04 | I46: 0.08 | J46: 0.07 | K46: 0.06 | L46: 0.05
A47: 乐观 | H47: 0.08 | I47: 0.12 | J47: 0.1 | K47: 0.08 | L47: 0.06
A48: 悲观 | H48: 0 | I48: 0 | J48: 0.02 | K48: 0.02 | L48: 0.02
A49: 通信系统设备 毛利率 ▶采用 | C49: =分业务!C11 -> 0.19244654 | D49: =分业务!D11 -> 0.20463558 | E49: =分业务!E11 -> 0.19240917 | F49: =分业务!F11 -> 0.19455531 | G49: =分业务!G11 -> 0.18813578 | H49: =CHOOSE(假设!$C$5,H50,H51,H52) -> 0.138 | I49: =CHOOSE(假设!$C$5,I50,I51,I52) -> 0.148 | J49: =CHOOSE(假设!$C$5,J50,J51,J52) -> 0.158 | K49: =CHOOSE(假设!$C$5,K50,K51,K52) -> 0.165 | L49: =CHOOSE(假设!$C$5,L50,L51,L52) -> 0.165 | O49: 2026H1仅15.0%（2025H1 21.2%）；2024/2025年下半年较上半年低2.9/4.5pp，基准2026E 13.8%隐含H2约12.7%；母公司（光网络主体）H1主营毛利率12.5%
A50: 基准 | H50: 0.138 | I50: 0.148 | J50: 0.158 | K50: 0.165 | L50: 0.165
A51: 乐观 | H51: 0.148 | I51: 0.165 | J51: 0.175 | K51: 0.18 | L51: 0.18
A52: 悲观 | H52: 0.13 | I52: 0.135 | J52: 0.14 | K52: 0.14 | L52: 0.14
A53: 光纤及线缆 销量增速 ▶采用 | H53: =CHOOSE(假设!$C$5,H54,H55,H56) -> 0.1 | I53: =CHOOSE(假设!$C$5,I54,I55,I56) -> 0.08 | J53: =CHOOSE(假设!$C$5,J54,J55,J56) -> 0.07 | K53: =CHOOSE(假设!$C$5,K54,K55,K56) -> 0.05 | L53: =CHOOSE(假设!$C$5,L54,L55,L56) -> 0.04 | O53: CRU：全球光缆需求2025–2030 CAGR 6.6%；AI数据中心/海外拉动；公司未披露产销量
A54: 基准 | H54: 0.1 | I54: 0.08 | J54: 0.07 | K54: 0.05 | L54: 0.04
A55: 乐观 | H55: 0.12 | I55: 0.12 | J55: 0.1 | K55: 0.08 | L55: 0.06
A56: 悲观 | H56: 0.08 | I56: 0.04 | J56: 0.04 | K56: 0.03 | L56: 0.03
A57: 光纤及线缆 均价变动 ▶采用 | H57: =CHOOSE(假设!$C$5,H58,H59,H60) -> 0.25 | I57: =CHOOSE(假设!$C$5,I58,I59,I60) -> -0.05 | J57: =CHOOSE(假设!$C$5,J58,J59,J60) -> -0.08 | K57: =CHOOSE(假设!$C$5,K58,K59,K60) -> -0.03 | L57: =CHOOSE(假设!$C$5,L58,L59,L60) -> 0 | O57: G.652D裸纤2026年3月83.4元/芯公里（同比+418%），9月现货105–110元；中国移动2026–27集采均价102.57元（+115%），烽火份额9.42%
A58: 基准 | H58: 0.25 | I58: -0.05 | J58: -0.08 | K58: -0.03 | L58: 0
A59: 乐观 | H59: 0.3 | I59: 0.08 | J59: -0.03 | K59: 0 | L59: 0
A60: 悲观 | H60: 0.2 | I60: -0.2 | J60: -0.1 | K60: -0.03 | L60: 0
A61: 光纤及线缆 毛利率 ▶采用 | C61: =分业务!C21 -> 0.17697439 | D61: =分业务!D21 -> 0.17433348 | E61: =分业务!E21 -> 0.21238903 | F61: =分业务!F21 -> 0.25351144 | G61: =分业务!G21 -> 0.25165512 | H61: =CHOOSE(假设!$C$5,H62,H63,H64) -> 0.4 | I61: =CHOOSE(假设!$C$5,I62,I63,I64) -> 0.36 | J61: =CHOOSE(假设!$C$5,J62,J63,J64) -> 0.31 | K61: =CHOOSE(假设!$C$5,K62,K63,K64) -> 0.29 | L61: =CHOOSE(假设!$C$5,L62,L63,L64) -> 0.28 | O61: 2026H1 42.3%（2025年25.2%，2021年17.7%）
A62: 基准 | H62: 0.4 | I62: 0.36 | J62: 0.31 | K62: 0.29 | L62: 0.28
A63: 乐观 | H63: 0.43 | I63: 0.43 | J63: 0.4 | K63: 0.37 | L63: 0.35
A64: 悲观 | H64: 0.38 | I64: 0.28 | J64: 0.24 | K64: 0.22 | L64: 0.22
A65: 数据网络产品 收入增速 ▶采用 | C65: =分业务!C24 -> 0.20496268 | D65: =分业务!D24 -> 0.030326459 | E65: =分业务!E24 -> -0.49626451 | F65: =分业务!F24 -> -0.27441395 | G65: =分业务!G24 -> 0.24050865 | H65: =CHOOSE(假设!$C$5,H66,H67,H68) -> 0.08 | I65: =CHOOSE(假设!$C$5,I66,I67,I68) -> 0.08 | J65: =CHOOSE(假设!$C$5,J66,J67,J68) -> 0.06 | K65: =CHOOSE(假设!$C$5,K66,K67,K68) -> 0.05 | L65: =CHOOSE(假设!$C$5,L66,L67,L68) -> 0.05 | O65: 收入集中于下半年（2025H1仅占15%）
A66: 基准 | H66: 0.08 | I66: 0.08 | J66: 0.06 | K66: 0.05 | L66: 0.05
A67: 乐观 | H67: 0.15 | I67: 0.12 | J67: 0.1 | K67: 0.08 | L67: 0.08
A68: 悲观 | H68: 0 | I68: 0 | J68: 0 | K68: 0 | L68: 0
A69: 数据网络产品 毛利率 ▶采用 | C69: =分业务!C27 -> 0.43249902 | D69: =分业务!D27 -> 0.4160947 | E69: =分业务!E27 -> 0.41354377 | F69: =分业务!F27 -> 0.43917211 | G69: =分业务!G27 -> 0.39284752 | H69: =CHOOSE(假设!$C$5,H70,H71,H72) -> 0.35 | I69: =CHOOSE(假设!$C$5,I70,I71,I72) -> 0.37 | J69: =CHOOSE(假设!$C$5,J70,J71,J72) -> 0.38 | K69: =CHOOSE(假设!$C$5,K70,K71,K72) -> 0.38 | L69: =CHOOSE(假设!$C$5,L70,L71,L72) -> 0.38
A70: 基准 | H70: 0.35 | I70: 0.37 | J70: 0.38 | K70: 0.38 | L70: 0.38
A71: 乐观 | H71: 0.39 | I71: 0.39 | J71: 0.39 | K71: 0.39 | L71: 0.39
A72: 悲观 | H72: 0.3 | I72: 0.3 | J72: 0.3 | K72: 0.3 | L72: 0.3
A73: 其他业务 收入增速 ▶采用 | C73: =分业务!C30 -> 0.0055075089 | D73: =分业务!D30 -> 0.066306962 | E73: =分业务!E30 -> 0.049665182 | F73: =分业务!F30 -> 0.031199602 | G73: =分业务!G30 -> -0.51562387 | H73: =CHOOSE(假设!$C$5,H74,H75,H76) -> 0.21 | I73: =CHOOSE(假设!$C$5,I74,I75,I76) -> 0 | J73: =CHOOSE(假设!$C$5,J74,J75,J76) -> 0 | K73: =CHOOSE(假设!$C$5,K74,K75,K76) -> 0 | L73: =CHOOSE(假设!$C$5,L74,L75,L76) -> 0 | O73: 2026H1已达2.03亿（2025全年1.90亿），2026E设为2.30亿
A74: 基准 | H74: 0.21 | I74: 0 | J74: 0 | K74: 0 | L74: 0
A75: 乐观 | H75: 0.21 | I75: 0 | J75: 0 | K75: 0 | L75: 0
A76: 悲观 | H76: 0.21 | I76: 0 | J76: 0 | K76: 0 | L76: 0
A77: 其他业务 毛利率 ▶采用 | C77: =分业务!C33 -> 0.21227511 | D77: =分业务!D33 -> 0.20307476 | E77: =分业务!E33 -> 0.075302768 | F77: =分业务!F33 -> 0.079600074 | G77: =分业务!G33 -> 0.098783294 | H77: =CHOOSE(假设!$C$5,H78,H79,H80) -> 0.12 | I77: =CHOOSE(假设!$C$5,I78,I79,I80) -> 0.12 | J77: =CHOOSE(假设!$C$5,J78,J79,J80) -> 0.12 | K77: =CHOOSE(假设!$C$5,K78,K79,K80) -> 0.12 | L77: =CHOOSE(假设!$C$5,L78,L79,L80) -> 0.12
A78: 基准 | H78: 0.12 | I78: 0.12 | J78: 0.12 | K78: 0.12 | L78: 0.12
A79: 乐观 | H79: 0.12 | I79: 0.12 | J79: 0.12 | K79: 0.12 | L79: 0.12
A80: 悲观 | H80: 0.12 | I80: 0.12 | J80: 0.12 | K80: 0.12 | L80: 0.12
A81: 二、费用与其他损益
A82: 税金及附加/收入 ▶采用 | C82: =费用!C9 -> 0.0033519995 | D82: =费用!D9 -> 0.0033017226 | E82: =费用!E9 -> 0.0035096914 | F82: =费用!F9 -> 0.0040711545 | G82: =费用!G9 -> 0.0044080767 | H82: =CHOOSE(假设!$C$5,H83,H84,H85) -> 0.005 | I82: =CHOOSE(假设!$C$5,I83,I84,I85) -> 0.005 | J82: =CHOOSE(假设!$C$5,J83,J84,J85) -> 0.005 | K82: =CHOOSE(假设!$C$5,K83,K84,K85) -> 0.005 | L82: =CHOOSE(假设!$C$5,L83,L84,L85) -> 0.005
A83: 基准 | H83: 0.005 | I83: 0.005 | J83: 0.005 | K83: 0.005 | L83: 0.005
A84: 乐观 | H84: 0.005 | I84: 0.005 | J84: 0.005 | K84: 0.005 | L84: 0.005
A85: 悲观 | H85: 0.005 | I85: 0.005 | J85: 0.005 | K85: 0.005 | L85: 0.005
A86: 销售费用率 ▶采用 | C86: =费用!C11 -> 0.053883582 | D86: =费用!D11 -> 0.053235737 | E86: =费用!E11 -> 0.057394739 | F86: =费用!F11 -> 0.065899658 | G86: =费用!G11 -> 0.079284643 | H86: =CHOOSE(假设!$C$5,H87,H88,H89) -> 0.076 | I86: =CHOOSE(假设!$C$5,I87,I88,I89) -> 0.073 | J86: =CHOOSE(假设!$C$5,J87,J88,J89) -> 0.07 | K86: =CHOOSE(假设!$C$5,K87,K88,K89) -> 0.068 | L86: =CHOOSE(假设!$C$5,L87,L88,L89) -> 0.066 | O86: 2026H1 8.6%（上半年季节性偏高）
A87: 基准 | H87: 0.076 | I87: 0.073 | J87: 0.07 | K87: 0.068 | L87: 0.066
A88: 乐观 | H88: 0.073 | I88: 0.069 | J88: 0.066 | K88: 0.064 | L88: 0.062
A89: 悲观 | H89: 0.078 | I89: 0.078 | J89: 0.078 | K89: 0.078 | L89: 0.078
A90: 管理费用率 ▶采用 | C90: =费用!C13 -> 0.011187643 | D90: =费用!D13 -> 0.010629202 | E90: =费用!E13 -> 0.010954631 | F90: =费用!F13 -> 0.01539656 | G90: =费用!G13 -> 0.019438925 | H90: =CHOOSE(假设!$C$5,H91,H92,H93) -> 0.019 | I90: =CHOOSE(假设!$C$5,I91,I92,I93) -> 0.0185 | J90: =CHOOSE(假设!$C$5,J91,J92,J93) -> 0.018 | K90: =CHOOSE(假设!$C$5,K91,K92,K93) -> 0.018 | L90: =CHOOSE(假设!$C$5,L91,L92,L93) -> 0.018
A91: 基准 | H91: 0.019 | I91: 0.0185 | J91: 0.018 | K91: 0.018 | L91: 0.018
A92: 乐观 | H92: 0.018 | I92: 0.018 | J92: 0.018 | K92: 0.018 | L92: 0.018
A93: 悲观 | H93: 0.02 | I93: 0.02 | J93: 0.02 | K93: 0.02 | L93: 0.02
A94: 研发投入总额/收入 ▶采用 | C94: =费用!C16 -> 0.14158233 | D94: =费用!D16 -> 0.14210827 | E94: =费用!E16 -> 0.12388526 | F94: =费用!F16 -> 0.12533278 | G94: =费用!G16 -> 0.12672985 | H94: =CHOOSE(假设!$C$5,H95,H96,H97) -> 0.112 | I94: =CHOOSE(假设!$C$5,I95,I96,I97) -> 0.108 | J94: =CHOOSE(假设!$C$5,J95,J96,J97) -> 0.105 | K94: =CHOOSE(假设!$C$5,K95,K96,K97) -> 0.103 | L94: =CHOOSE(假设!$C$5,L95,L96,L97) -> 0.102 | O94: 2025年12.7%；2026H1研发费用−11.8%（“适度收缩研发业务范围”）
A95: 基准 | H95: 0.112 | I95: 0.108 | J95: 0.105 | K95: 0.103 | L95: 0.102
A96: 乐观 | H96: 0.11 | I96: 0.105 | J96: 0.1 | K96: 0.098 | L96: 0.098
A97: 悲观 | H97: 0.115 | I97: 0.115 | J97: 0.115 | K97: 0.115 | L97: 0.115
A98: 研发资本化率 ▶采用 | C98: =费用!C18 -> 0.071208832 | D98: =费用!D18 -> 0.06643669 | E98: =费用!E18 -> 0.072128726 | F98: =费用!F18 -> 0.19475508 | G98: =费用!G18 -> 0.18614326 | H98: =CHOOSE(假设!$C$5,H99,H100,H101) -> 0.19 | I98: =CHOOSE(假设!$C$5,I99,I100,I101) -> 0.18 | J98: =CHOOSE(假设!$C$5,J99,J100,J101) -> 0.17 | K98: =CHOOSE(假设!$C$5,K99,K100,K101) -> 0.16 | L98: =CHOOSE(假设!$C$5,L99,L100,L101) -> 0.15 | O98: 2021–2023年约7%，2024年跳升至19.5%，2025年18.6%——悲观情景假设回归
A99: 基准 | H99: 0.19 | I99: 0.18 | J99: 0.17 | K99: 0.16 | L99: 0.15
A100: 乐观 | H100: 0.2 | I100: 0.2 | J100: 0.2 | K100: 0.2 | L100: 0.2
A101: 悲观 | H101: 0.15 | I101: 0.13 | J101: 0.12 | K101: 0.11 | L101: 0.1
A102: 其他收益/收入 ▶采用 | C102: =费用!C23 -> 0.0098835263 | D102: =费用!D23 -> 0.0088950527 | E102: =费用!E23 -> 0.014391067 | F102: =费用!F23 -> 0.027014038 | G102: =费用!G23 -> 0.029000498 | H102: =CHOOSE(假设!$C$5,H103,H104,H105) -> 0.022 | I102: =CHOOSE(假设!$C$5,I103,I104,I105) -> 0.02 | J102: =CHOOSE(假设!$C$5,J103,J104,J105) -> 0.019 | K102: =CHOOSE(假设!$C$5,K103,K104,K105) -> 0.018 | L102: =CHOOSE(假设!$C$5,L103,L104,L105) -> 0.018 | O102: 政府补助+软件增值税退税；2025年2.9%，2026H1 1.8%
A103: 基准 | H103: 0.022 | I103: 0.02 | J103: 0.019 | K103: 0.018 | L103: 0.018
A104: 乐观 | H104: 0.024 | I104: 0.022 | J104: 0.02 | K104: 0.02 | L104: 0.02
...

Sheet 分业务
A1: 分业务收入与毛利拆分（百万元）
A2: 历史：年报“主营业务分产品情况”/Wind主营构成；预测：收入=上年×(1+增速)，光纤及线缆=上年×(1+销量)×(1+价格)；成本=收入×(1−毛利率)
A5: 项目 | B5: 百万元 | C5: 2021A | D5: 2022A | E5: 2023A | F5: 2024A | G5: 2025A | H5: 2026E | I5: 2027E | J5: 2028E | K5: 2029E | L5: 2030E | N5: 2026H1A | O5: 说明 / 来源
A6: 通信系统设备
A7: 通信系统设备 收入 | C7: 17086.233 | D7: 20915.791 | E7: 23785.164 | F7: 22313.409 | G7: 18654.767 | H7: =G7*(1+假设!H45) -> 19400.958 | I7: =H7*(1+假设!I45) -> 20953.035 | J7: =I7*(1+假设!J45) -> 22419.747 | K7: =J7*(1+假设!K45) -> 23764.932 | L7: =K7*(1+假设!L45) -> 24953.179 | N7: 8959.4508 | O7: 历史=年报分产品收入（Wind主营构成，万元÷100）
A8: 同比 | C8: 0.31695121 | D8: =D7/C7-1 -> 0.22413118 | E8: =E7/D7-1 -> 0.1371869 | F8: =F7/E7-1 -> -0.061877014 | G8: =G7/F7-1 -> -0.16396604 | H8: =H7/G7-1 -> 0.04 | I8: =I7/H7-1 -> 0.08 | J8: =J7/I7-1 -> 0.07 | K8: =K7/J7-1 -> 0.06 | L8: =L7/K7-1 -> 0.05 | N8: 0.026559395 | O8: 2021A同比按2020A收入计算；2026H1A为同比
A9: 通信系统设备 成本 | C9: 13798.047 | D9: 16635.676 | E9: 19208.68 | F9: 17972.216 | G9: 15145.138 | H9: =H7*(1-H11) -> 16723.626 | I9: =I7*(1-I11) -> 17851.986 | J9: =J7*(1-J11) -> 18877.427 | K9: =K7*(1-K11) -> 19843.718 | L9: =L7*(1-L11) -> 20835.904 | N9: 7617.8717
A10: 通信系统设备 毛利 | C10: =C7-C9 -> 3288.1865 | D10: =D7-D9 -> 4280.115 | E10: =E7-E9 -> 4576.4835 | F10: =F7-F9 -> 4341.1922 | G10: =G7-G9 -> 3509.6293 | H10: =H7-H9 -> 2677.3322 | I10: =I7-I9 -> 3101.0491 | J10: =J7-J9 -> 3542.3201 | ... L10: =L7-L9 -> 4117.2745 | N10: =N7-N9 -> 1341.5791
A11: 通信系统设备 毛利率 | C11: =IF(C7=0,0,C10/C7) -> 0.19244654 | D11: =IF(D7=0,0,D10/D7) -> 0.20463558 | E11: =IF(E7=0,0,E10/E7) -> 0.19240917 | F11: =IF(F7=0,0,F10/F7) -> 0.19455531 | G11: =IF(G7=0,0,G10/G7) -> 0.18813578 | H11: =假设!H49 -> 0.138 | I11: =假设!I49 -> 0.148 | J11: =假设!J49 -> 0.158 | K11: =假设!K49 -> 0.165 | L11: =假设!L49 -> 0.165 | N11: =IF(N7=0,0,N10/N7) -> 0.14973899
A12: 光纤及线缆
A13: 销量增速 | H13: =假设!H53 -> 0.1 | I13: =假设!I53 -> 0.08 | J13: =假设!J53 -> 0.07 | K13: =假设!K53 -> 0.05 | L13: =假设!L53 -> 0.04
A14: 均价变动 | H14: =假设!H57 -> 0.25 | I14: =假设!I57 -> -0.05 | J14: =假设!J57 -> -0.08 | K14: =假设!K57 -> -0.03 | L14: =假设!L57 -> 0
A15: 销量指数（2025A=100） | G15: 100 | H15: =G15*(1+H13) -> 110 | I15: =H15*(1+I13) -> 118.8 | J15: =I15*(1+J13) -> 127.116 | K15: =J15*(1+K13) -> 133.4718 | L15: =K15*(1+L13) -> 138.81067
A16: 价格指数（2025A=100） | G16: 100 | H16: =G16*(1+H14) -> 125 | I16: =H16*(1+I14) -> 118.75 | J16: =I16*(1+J14) -> 109.25 | K16: =J16*(1+K14) -> 105.9725 | L16: =K16*(1+L14) -> 105.9725
A17: 光纤及线缆 收入 | C17: 5849.9396 | D17: 6508.5623 | E17: 5386.6935 | F17: 4698.6346 | G17: 4654.0976 | H17: =G17*(1+H13)*(1+H14) -> 6399.3842 | I17: =H17*(1+I13)*(1+I14) -> 6565.7682 | J17: =I17*(1+J13)*(1+J14) -> 6463.3422 | K17: =J17*(1+K13)*(1+K14) -> 6582.914 | L17: =K17*(1+L13)*(1+L14) -> 6846.2306 | N17: 2964.6573 | O17: 历史=年报分产品收入（Wind主营构成，万元÷100）
A18: 同比 | C18: 0.11633456 | D18: =D17/C17-1 -> 0.11258624 | E18: =E17/D17-1 -> -0.17236814 | F18: =F17/E17-1 -> -0.12773307 | G18: =G17/F17-1 -> -0.0094787111 | H18: =H17/G17-1 -> 0.375 | I18: =I17/H17-1 -> 0.026 | J18: =J17/I17-1 -> -0.0156 | K18: =K17/J17-1 -> 0.0185 | L18: =L17/K17-1 -> 0.04 | N18: 0.47953322 | O18: 2021A同比按2020A收入计算；2026H1A为同比
A19: 光纤及线缆 成本 | C19: 4814.6501 | D19: 5373.902 | E19: 4242.6189 | F19: 3507.477 | G19: 3482.8701 | H19: =H17*(1-H21) -> 3839.6305 | I19: =I17*(1-I21) -> 4202.0916 | J19: =J17*(1-J21) -> 4459.7061 | K19: =K17*(1-K21) -> 4673.869 | L19: =L17*(1-L21) -> 4929.286 | N19: 1711.9269
A20: 光纤及线缆 毛利 | C20: =C17-C19 -> 1035.2895 | D20: =D17-D19 -> 1134.6603 | E20: =E17-E19 -> 1144.0746 | F20: =F17-F19 -> 1191.1576 | G20: =G17-G19 -> 1171.2275 | H20: =H17-H19 -> 2559.7537 | I20: =I17-I19 -> 2363.6765 | J20: =J17-J19 -> 2003.6361 | ... L20: =L17-L19 -> 1916.9446 | N20: =N17-N19 -> 1252.7304
A21: 光纤及线缆 毛利率 | C21: =IF(C17=0,0,C20/C17) -> 0.17697439 | D21: =IF(D17=0,0,D20/D17) -> 0.17433348 | E21: =IF(E17=0,0,E20/E17) -> 0.21238903 | F21: =IF(F17=0,0,F20/F17) -> 0.25351144 | G21: =IF(G17=0,0,G20/G17) -> 0.25165512 | H21: =假设!H61 -> 0.4 | I21: =假设!I61 -> 0.36 | J21: =假设!J61 -> 0.31 | K21: =假设!K61 -> 0.29 | L21: =假设!L61 -> 0.28 | N21: =IF(N17=0,0,N20/N17) -> 0.42255488
A22: 数据网络产品
A23: 数据网络产品 收入 | C23: 3038.8249 | D23: 3130.9817 | E23: 1577.1866 | F23: 1144.3846 | G23: 1419.619 | H23: =G23*(1+假设!H65) -> 1533.1885 | I23: =H23*(1+假设!I65) -> 1655.8436 | J23: =I23*(1+假设!J65) -> 1755.1942 | K23: =J23*(1+假设!K65) -> 1842.9539 | L23: =K23*(1+假设!L65) -> 1935.1016 | N23: 248.8312 | O23: 历史=年报分产品收入（Wind主营构成，万元÷100）
A24: 同比 | C24: 0.20496268 | D24: =D23/C23-1 -> 0.030326459 | E24: =E23/D23-1 -> -0.49626451 | F24: =F23/E23-1 -> -0.27441395 | G24: =G23/F23-1 -> 0.24050865 | H24: =H23/G23-1 -> 0.08 | I24: =I23/H23-1 -> 0.08 | J24: =J23/I23-1 -> 0.06 | K24: =K23/J23-1 -> 0.05 | L24: =L23/K23-1 -> 0.05 | N24: 0.12995331 | O24: 2021A同比按2020A收入计算；2026H1A为同比
A25: 数据网络产品 成本 | C25: 1724.5361 | D25: 1828.1968 | E25: 924.9509 | F25: 641.8028 | G25: 861.9252 | H25: =H23*(1-H27) -> 996.57254 | I25: =I23*(1-I27) -> 1043.1815 | J25: =J23*(1-J27) -> 1088.2204 | K25: =K23*(1-K27) -> 1142.6314 | L25: =L23*(1-L27) -> 1199.763 | N25: 233.8039
A26: 数据网络产品 毛利 | C26: =C23-C25 -> 1314.2888 | D26: =D23-D25 -> 1302.7849 | E26: =E23-E25 -> 652.2357 | F26: =F23-F25 -> 502.5818 | G26: =G23-G25 -> 557.6938 | H26: =H23-H25 -> 536.61598 | I26: =I23-I25 -> 612.66213 | J26: =J23-J25 -> 666.9738 | ... L26: =L23-L25 -> 735.33862 | N26: =N23-N25 -> 15.0273
A27: 数据网络产品 毛利率 | C27: =IF(C23=0,0,C26/C23) -> 0.43249902 | D27: =IF(D23=0,0,D26/D23) -> 0.4160947 | E27: =IF(E23=0,0,E26/E23) -> 0.41354377 | F27: =IF(F23=0,0,F26/F23) -> 0.43917211 | G27: =IF(G23=0,0,G26/G23) -> 0.39284752 | H27: =假设!H69 -> 0.35 | I27: =假设!I69 -> 0.37 | J27: =假设!J69 -> 0.38 | K27: =假设!K69 -> 0.38 | L27: =假设!L69 -> 0.38 | N27: =IF(N23=0,0,N26/N23) -> 0.060391543
A28: 其他业务
A29: 其他业务 收入 | C29: 339.9824 | D29: 362.5256 | E29: 380.5305 | F29: 392.4029 | G29: 190.0706 | H29: =G29*(1+假设!H73) -> 229.98543 | I29: =H29*(1+假设!I73) -> 229.98543 | J29: =I29*(1+假设!J73) -> 229.98543 | K29: =J29*(1+假设!K73) -> 229.98543 | L29: =K29*(1+假设!L73) -> 229.98543 | N29: 203.4191 | O29: 历史=年报分产品收入（Wind主营构成，万元÷100）
A30: 同比 | C30: 0.0055075089 | D30: =D29/C29-1 -> 0.066306962 | E30: =E29/D29-1 -> 0.049665182 | F30: =F29/E29-1 -> 0.031199602 | G30: =G29/F29-1 -> -0.51562387 | H30: =H29/G29-1 -> 0.21 | I30: =I29/H29-1 -> 0 | J30: =J29/I29-1 -> 0 | K30: =K29/J29-1 -> 0 | L30: =L29/K29-1 -> 0 | N30: 0.23150852 | O30: 2021A同比按2020A收入计算；2026H1A为同比
A31: 其他业务 成本 | C31: 267.8126 | D31: 288.9058 | E31: 351.8755 | F31: 361.1676 | G31: 171.2948 | H31: =H29*(1-H33) -> 202.38717 | I31: =I29*(1-I33) -> 202.38717 | J31: =J29*(1-J33) -> 202.38717 | K31: =K29*(1-K33) -> 202.38717 | L31: =L29*(1-L33) -> 202.38717 | N31: 164.2589
A32: 其他业务 毛利 | C32: =C29-C31 -> 72.1698 | D32: =D29-D31 -> 73.6198 | E32: =E29-E31 -> 28.655 | F32: =F29-F31 -> 31.2353 | G32: =G29-G31 -> 18.7758 | H32: =H29-H31 -> 27.598251 | I32: =I29-I31 -> 27.598251 | J32: =J29-J31 -> 27.598251 | ... L32: =L29-L31 -> 27.598251 | N32: =N29-N31 -> 39.1602
A33: 其他业务 毛利率 | C33: =IF(C29=0,0,C32/C29) -> 0.21227511 | D33: =IF(D29=0,0,D32/D29) -> 0.20307476 | E33: =IF(E29=0,0,E32/E29) -> 0.075302768 | F33: =IF(F29=0,0,F32/F29) -> 0.079600074 | G33: =IF(G29=0,0,G32/G29) -> 0.098783294 | H33: =假设!H77 -> 0.12 | I33: =假设!I77 -> 0.12 | J33: =假设!J77 -> 0.12 | K33: =假设!K77 -> 0.12 | L33: =假设!L77 -> 0.12 | N33: =IF(N29=0,0,N32/N29) -> 0.19250995
A34: 合计
A35: 营业收入合计 | C35: =C7+C17+C23+C29 -> 26314.98 | D35: =D7+D17+D23+D29 -> 30917.861 | E35: =E7+E17+E23+E29 -> 31129.574 | F35: =F7+F17+F23+F29 -> 28548.831 | G35: =G7+G17+G23+G29 -> 24918.555 | H35: =H7+H17+H23+H29 -> 27563.516 | I35: =I7+I17+I23+I29 -> 29404.632 | J35: =J7+J17+J23+J29 -> 30868.269 | ... L35: =L7+L17+L23+L29 -> 33964.496 | N35: =N7+N17+N23+N29 -> 12376.358
A36: 同比 | C36: 0.24866823 | D36: =D35/C35-1 -> 0.17491483 | E36: =E35/D35-1 -> 0.0068476148 | F36: =F35/E35-1 -> -0.082903267 | G36: =G35/F35-1 -> -0.12716024 | H36: =H35/G35-1 -> 0.10614426 | I36: =I35/H35-1 -> 0.066795386 | J36: =J35/I35-1 -> 0.049775731 | K36: =K35/J35-1 -> 0.050294896 | L36: =L35/K35-1 -> 0.047614851 | N36: 0.11330014
A37: 营业成本合计 | C37: =C9+C19+C25+C31 -> 20605.046 | D37: =D9+D19+D25+D31 -> 24126.681 | E37: =E9+E19+E25+E31 -> 24728.125 | F37: =F9+F19+F25+F31 -> 22482.664 | G37: =G9+G19+G25+G31 -> 19661.228 | H37: =H9+H19+H25+H31 -> 21762.216 | I37: =I9+I19+I25+I31 -> 23299.646 | J37: =J9+J19+J25+J31 -> 24627.741 | ... L37: =L9+L19+L25+L31 -> 27167.34 | N37: =N9+N19+N25+N31 -> 9727.8614
A38: 毛利合计 | C38: =C35-C37 -> 5709.9346 | D38: =D35-D37 -> 6791.18 | E38: =E35-E37 -> 6401.4488 | F38: =F35-F37 -> 6066.1669 | G38: =G35-G37 -> 5257.3264 | H38: =H35-H37 -> 5801.3001 | I38: =I35-I37 -> 6104.9861 | J38: =J35-J37 -> 6240.5282 | ... L38: =L35-L37 -> 6797.1559 | N38: =N35-N37 -> 2648.497
A39: 综合毛利率 | C39: =C38/C35 -> 0.21698419 | D39: =D38/D35 -> 0.21965233 | E39: =E38/E35 -> 0.20563882 | F39: =F38/F35 -> 0.2124839 | G39: =G38/G35 -> 0.21098039 | H39: =H38/H35 -> 0.21047025 | I39: =I38/I35 -> 0.20761988 | J39: =J38/J35 -> 0.20216644 | ... L39: =L38/L35 -> 0.20012533 | N39: =N38/N35 -> 0.21399647
A40: 核对：分部合计−报表营业收入 | C40: =C35-历史报表!E8 -> -0.0001 | D40: =D35-历史报表!F8 -> 0 | E40: =E35-历史报表!G8 -> -9.9999997e-05 | F40: =F35-历史报表!H8 -> -9.9999997e-05 | G40: =G35-历史报表!I8 -> 0.0001 | N40: =N35-历史报表!K8 -> 0 | O40: 应为0
A41: 收入结构与毛利贡献
A42: 通信系统设备 收入占比 | C42: =C7/C35 -> 0.64929683 | D42: =D7/D35 -> 0.67649542 | E42: =E7/E35 -> 0.76406967 | F42: =F7/F35 -> 0.78158748 | G42: =G7/G35 -> 0.74862959 | H42: =H7/H35 -> 0.70386368 | I42: =I7/I35 -> 0.71257599 | J42: =J7/J35 -> 0.726304 | ... L42: =L7/L35 -> 0.7346842 | N42: =N7/N35 -> 0.72391656
A43: 光纤及线缆 收入占比 | C43: =C17/C35 -> 0.22230454 | D43: =D17/D35 -> 0.21051141 | E43: =E17/E35 -> 0.17304103 | F43: =F17/F35 -> 0.16458238 | G43: =G17/G35 -> 0.18677237 | H43: =H17/H35 -> 0.23216864 | I43: =I17/I35 -> 0.22329027 | J43: =J17/J35 -> 0.20938467 | ... L43: =L17/L35 -> 0.20157021 | N43: =N17/N35 -> 0.23954197
A44: 数据网络产品 收入占比 | C44: =C23/C35 -> 0.1154789 | D44: =D23/D35 -> 0.10126773 | E44: =E23/E35 -> 0.050665216 | F44: =F23/F35 -> 0.040085165 | G44: =G23/G35 -> 0.056970359 | H44: =H23/H35 -> 0.055623836 | I44: =I23/I35 -> 0.056312339 | J44: =J23/J35 -> 0.056860792 | ... L44: =L23/L35 -> 0.056974248 | N44: =N23/N35 -> 0.020105365
A45: 其他业务 收入占比 | C45: =C29/C35 -> 0.012919729 | D45: =D29/D35 -> 0.011725443 | E45: =E29/E35 -> 0.012224083 | F45: =F29/F35 -> 0.013744973 | G45: =G29/G35 -> 0.0076276736 | H45: =H29/H35 -> 0.0083438348 | I45: =I29/I35 -> 0.0078214013 | J45: =J29/J35 -> 0.007450545 | ... L45: =L29/L35 -> 0.0067713481 | N45: =N29/N35 -> 0.016436103
A46: 通信系统设备 毛利占比 | C46: =C10/C38 -> 0.57587113 | D46: =D10/D38 -> 0.63024614 | E46: =E10/E38 -> 0.71491371 | F46: =F10/F38 -> 0.71564009 | G46: =G10/G38 -> 0.66756922 | H46: =H10/H38 -> 0.46150555 | I46: =I10/I38 -> 0.50795352 | J46: =J10/J38 -> 0.56763145 | ... L46: =L10/L38 -> 0.60573489 | N46: =N10/N38 -> 0.50654356
A47: 光纤及线缆 毛利占比 | C47: =C20/C38 -> 0.18131372 | D47: =D20/D38 -> 0.16707852 | E47: =E20/E38 -> 0.1787212 | F47: =F20/F38 -> 0.19636084 | G47: =G20/G38 -> 0.22278006 | H47: =H20/H38 -> 0.44123793 | I47: =I20/I38 -> 0.38717149 | J47: =J20/J38 -> 0.32106835 | ... L47: =L20/L38 -> 0.28202157 | N47: =N20/N38 -> 0.47299672
A48: 数据网络产品 毛利占比 | C48: =C26/C38 -> 0.23017581 | D48: =D26/D38 -> 0.19183484 | E48: =E26/E38 -> 0.10188876 | F48: =F26/F38 -> 0.082849979 | G48: =G26/G38 -> 0.10607936 | H48: =H26/H38 -> 0.092499262 | I48: =I26/I38 -> 0.10035439 | J48: =J26/J38 -> 0.10687778 | ... L48: =L26/L38 -> 0.10818328 | N48: =N26/N38 -> 0.0056738973
A49: 其他业务 毛利占比 | C49: =C32/C38 -> 0.012639339 | D49: =D32/D38 -> 0.010840502 | E49: =E32/E38 -> 0.0044763304 | F49: =F32/F38 -> 0.0051491 | G49: =G32/G38 -> 0.003571359 | H49: =H32/H38 -> 0.0047572528 | I49: =I32/I38 -> 0.0045206084 | J49: =J32/J38 -> 0.0044224223 | ... L49: =L32/L38 -> 0.0040602645 | N49: =N32/N38 -> 0.01478582
A50: 分地区（历史）
A51: 中国大陆 收入 | C51: 16763.084 | D51: 19139.157 | E51: 21310.911 | F51: 20548.201 | G51: 16925.279 | N51: 8035.1331
A52: 中国大陆 成本 | C52: 13594.528 | D52: 15364.839 | E52: 17676.963 | F52: 16659.459 | G52: 13677.094 | N52: 6880.51
A53: 中国大陆 毛利率 | C53: =C51/C51-C52/C51 -> 0.18901988 | D53: =D51/D51-D52/D51 -> 0.19720398 | E53: =E51/E51-E52/E51 -> 0.1705205 | F53: =F51/F51-F52/F51 -> 0.18924975 | G53: =G51/G51-G52/G51 -> 0.19191323 | N53: =1-N52/N51 -> 0.14369682
A54: 国外 收入 | C54: 9211.9143 | D54: 11416.178 | E54: 9818.6637 | F54: 8000.6302 | G54: 7993.2759 | N54: 4341.2253
A55: 国外 成本 | C55: 6742.7055 | D55: 8472.9358 | E55: 7051.162 | F55: 5823.2051 | G55: 5984.1345 | N55: 2847.3514
A56: 国外 毛利率 | C56: =C54/C54-C55/C54 -> 0.26804513 | D56: =D54/D54-D55/D54 -> 0.25781328 | E56: =E54/E54-E55/E54 -> 0.28186134 | F56: =F54/F54-F55/F54 -> 0.2721567 | G56: =G54/G54-G55/G54 -> 0.25135394 | N56: =1-N55/N54 -> 0.34411342
A57: 海外收入占比 | C57: =C54/(C51+C54) -> 0.35464543 | D57: =D54/(D51+D54) -> 0.37362308 | E57: =E54/(E51+E54) -> 0.31541272 | F57: =F54/(F51+F54) -> 0.28024371 | G57: =G54/(G51+G54) -> 0.32077607 | N57: =N54/(N51+N54) -> 0.35076758 | O57: 2021–2023年分地区口径不含其他业务；2024年起含
A59: 半年度对比（2025H1 vs 2026H1） | C59: 25H1收入 | D59: 26H1收入 | E59: 同比 | F59: 25H1毛利率 | G59: 26H1毛利率 | H59: 变动pp | I59: 26H1毛利
A60: 通信系统设备 | C60: 8727.6497 | D60: 8959.4508 | E60: =D60/C60-1 -> 0.026559395 | F60: 0.21237185 | G60: 0.14973899 | H60: =(G60-F60)*100 -> -6.263286 | I60: =D60*G60 -> 1341.5791
A61: 光纤及线缆 | C61: 2003.7788 | D61: 2964.6573 | E61: =D61/C61-1 -> 0.47953322 | F61: 0.2548182 | G61: 0.42255488 | H61: =(G61-F61)*100 -> 16.773668 | I61: =D61*G61 -> 1252.7304
A62: 数据网络产品 | C62: 220.2137 | D62: 248.8312 | E62: =D62/C62-1 -> 0.12995331 | F62: 0.30319095 | G62: 0.060391543 | H62: =(G62-F62)*100 -> -24.27994 | I62: =D62*G62 -> 15.0273
A63: 其他业务 | C63: 165.1788 | D63: 203.4191 | E63: =D63/C63-1 -> 0.23150852 | F63: 0.23822488 | G63: 0.19250995 | H63: =(G63-F63)*100 -> -4.5714935 | I63: =D63*G63 -> 39.1602
A64: 国内 | C64: 7334.2763 | D64: 8035.1331 | E64: =D64/C64-1 -> 0.095559094 | F64: 0.19725922 | G64: 0.14369682 | H64: =(G64-F64)*100 -> -5.3562394 | I64: =D64*G64 -> 1154.6231
A65: 国外 | C65: 3782.5447 | D65: 4341.2253 | E65: =D65/C65-1 -> 0.14769967 | F65: 0.27057689 | G65: 0.34411342 | H65: =(G65-F65)*100 -> 7.3536528 | I65: =D65*G65 -> 1493.8739
A66: 要点：光纤线缆26H1收入+48%、毛利率+16.8pp，贡献毛利增量约7.4亿；通信系统设备毛利率−6.3pp，毛利减少约5.1亿——“光纤涨价”收益被主业毛利率下滑基本抵消。
A68: 成本构成（2025A，百万元） | C68: 原材料 | D68: 人工 | E68: 折旧 | F68: 能源 | G68: 合计 | H68: 原材料占比 | I68: 折旧占比
A69: 通信系统设备 | C69: 14906.07 | D69: 165.48 | E69: 49.68 | F69: 23.91 | G69: =SUM(C69:F69) -> 15145.14 | H69: =C69/G69 -> 0.98421474 | I69: =E69/G69 -> 0.0032802602
A70: 光纤及线缆 | C70: 3255.64 | D70: 82.84 | E70: 80.73 | F70: 63.66 | G70: =SUM(C70:F70) -> 3482.87 | H70: =C70/G70 -> 0.93475783 | I70: =E70/G70 -> 0.02317916
A71: 数据网络产品 | C71: 850.9 | D71: 7.74 | E71: 2.26 | F71: 1.02 | G71: =SUM(C71:F71) -> 861.92 | H71: =C71/G71 -> 0.98721459 | I71: =E71/G71 -> 0.0026220531
A72: 来源：2025年年报“成本分析表”。通信系统设备98%为原材料（外购器件/服务器部件），经营杠杆低、毛利率对价格与结构高度敏感。

Sheet 费用
A1: 费用、其他损益与盈利质量（百万元）
A2: 费用以正数列示；减值损失以负数列示；预测=收入×比率（比率链接“假设”）
A5: 项目 | B5: 百万元 | C5: 2021A | D5: 2022A | E5: 2023A | F5: 2024A | G5: 2025A | H5: 2026E | I5: 2027E | J5: 2028E | K5: 2029E | L5: 2030E | N5: 2026H1A | O5: 说明 / 来源
A6: 营业收入 | C6: =利润表!C6 -> 26314.98 | D6: =利润表!D6 -> 30917.861 | E6: =利润表!E6 -> 31129.574 | F6: =利润表!F6 -> 28548.831 | G6: =利润表!G6 -> 24918.554 | H6: =利润表!H6 -> 27563.516 | I6: =利润表!I6 -> 29404.632 | J6: =利润表!J6 -> 30868.269 | ... L6: =利润表!L6 -> 33964.496 | N6: =利润表!N6 -> 12376.358
A7: 期间费用
A8: 税金及附加 | C8: =历史报表!E11 -> 88.2078 | D8: =历史报表!F11 -> 102.0822 | E8: =历史报表!G11 -> 109.2552 | F8: =历史报表!H11 -> 116.2267 | G8: =历史报表!I11 -> 109.8429 | H8: =H6*H9 -> 137.81758 | I8: =I6*I9 -> 147.02316 | J8: =J6*J9 -> 154.34135 | K8: =K6*K9 -> 162.10393 | L8: =L6*L9 -> 169.82248 | N8: =历史报表!K11 -> 79.0084
A9: 占收入比 | C9: =C8/C6 -> 0.0033519995 | D9: =D8/D6 -> 0.0033017226 | E9: =E8/E6 -> 0.0035096914 | F9: =F8/F6 -> 0.0040711545 | G9: =G8/G6 -> 0.0044080767 | H9: =假设!H82 -> 0.005 | I9: =假设!I82 -> 0.005 | J9: =假设!J82 -> 0.005 | K9: =假设!K82 -> 0.005 | L9: =假设!L82 -> 0.005 | N9: =N8/N6 -> 0.0063838164
A10: 销售费用 | C10: =历史报表!E12 -> 1417.9454 | D10: =历史报表!F12 -> 1645.9351 | E10: =历史报表!G12 -> 1786.6738 | F10: =历史报表!H12 -> 1881.3582 | G10: =历史报表!I12 -> 1975.6587 | H10: =H6*H11 -> 2094.8272 | I10: =I6*I11 -> 2146.5381 | J10: =J6*J11 -> 2160.7788 | K10: =K6*K11 -> 2204.6134 | L10: =L6*L11 -> 2241.6568 | N10: =历史报表!K12 -> 1061.5176
A11: 占收入比 | C11: =C10/C6 -> 0.053883582 | D11: =D10/D6 -> 0.053235737 | E11: =E10/E6 -> 0.057394739 | F11: =F10/F6 -> 0.065899658 | G11: =G10/G6 -> 0.079284643 | H11: =假设!H86 -> 0.076 | I11: =假设!I86 -> 0.073 | J11: =假设!J86 -> 0.07 | K11: =假设!K86 -> 0.068 | L11: =假设!L86 -> 0.066 | N11: =N10/N6 -> 0.085769785
A12: 管理费用 | C12: =历史报表!E13 -> 294.4026 | D12: =历史报表!F13 -> 328.6322 | E12: =历史报表!G13 -> 341.013 | F12: =历史报表!H13 -> 439.5538 | G12: =历史报表!I13 -> 484.3899 | H12: =H6*H13 -> 523.70681 | I12: =I6*I13 -> 543.98569 | J12: =J6*J13 -> 555.62884 | K12: =K6*K13 -> 583.57414 | L12: =L6*L13 -> 611.36093 | N12: =历史报表!K13 -> 190.1205
A13: 占收入比 | C13: =C12/C6 -> 0.011187643 | D13: =D12/D6 -> 0.010629202 | E13: =E12/E6 -> 0.010954631 | F13: =F12/F6 -> 0.01539656 | G13: =G12/G6 -> 0.019438925 | H13: =假设!H90 -> 0.019 | I13: =假设!I90 -> 0.0185 | J13: =假设!J90 -> 0.018 | K13: =假设!K90 -> 0.018 | L13: =假设!L90 -> 0.018 | N13: =N12/N6 -> 0.015361586
A14: 研发投入与资本化
A15: 研发投入总额 | C15: 3725.7363 | D15: 4393.6838 | E15: 3856.4953 | F15: 3578.1044 | G15: 3157.9247 | H15: =H6*H16 -> 3087.1138 | I15: =I6*I16 -> 3175.7003 | J15: =J6*J16 -> 3241.1682 | K15: =K6*K16 -> 3339.3409 | L15: =L6*L16 -> 3464.3786 | O15: 年报“研发投入情况表”
A16: 研发投入/收入 | C16: =C15/C6 -> 0.14158233 | D16: =D15/D6 -> 0.14210827 | E16: =E15/E6 -> 0.12388526 | F16: =F15/F6 -> 0.12533278 | G16: =G15/G6 -> 0.12672985 | H16: =假设!H94 -> 0.112 | I16: =假设!I94 -> 0.108 | J16: =假设!J94 -> 0.105 | K16: =假设!K94 -> 0.103 | L16: =假设!L94 -> 0.102
A17: 其中：资本化研发投入（计入开发支出） | C17: 265.30533 | D17: 291.90181 | E17: 278.16409 | F17: 696.85401 | G17: 587.82641 | H17: =H15*H18 -> 586.55163 | I17: =I15*I18 -> 571.62605 | J17: =J15*J18 -> 550.9986 | K17: =K15*K18 -> 534.29454 | L17: =L15*L18 -> 519.65679
A18: 研发资本化率 | C18: =C17/C15 -> 0.071208832 | D18: =D17/D15 -> 0.06643669 | E18: =E17/E15 -> 0.072128726 | F18: =F17/F15 -> 0.19475508 | G18: =G17/G15 -> 0.18614326 | H18: =假设!H98 -> 0.19 | I18: =假设!I98 -> 0.18 | J18: =假设!J98 -> 0.17 | K18: =假设!K98 -> 0.16 | L18: =假设!L98 -> 0.15 | O18: 2021–2023年约7%，2024年起升至19%左右
A19: 研发费用（费用化部分，计入利润表） | C19: =历史报表!E14 -> 3460.4309 | D19: =历史报表!F14 -> 4101.782 | E19: =历史报表!G14 -> 3578.3312 | F19: =历史报表!H14 -> 2881.2504 | G19: =历史报表!I14 -> 2570.0983 | H19: =H15-H17 -> 2500.5622 | I19: =I15-I17 -> 2604.0742 | J19: =J15-J17 -> 2690.1696 | K19: =K15-K17 -> 2805.0464 | L19: =L15-L17 -> 2944.7218 | N19: =历史报表!K14 -> 1269.9684
A20: 核对：投入−资本化−费用化 | C20: =C15-C17-C19 -> 3.9e-05 | D20: =D15-D17-D19 -> -5e-05 | E20: =E15-E17-E19 -> -2e-05 | F20: =F15-F17-F19 -> 1.6e-05 | G20: =G15-G17-G19 -> -4.6e-05 | O20: 应≈0
A21: 其他收益与减值
A22: 其他收益（政府补助、增值税退税等） | C22: =历史报表!E18 -> 260.0848 | D22: =历史报表!F18 -> 275.016 | E22: =历史报表!G18 -> 447.9878 | F22: =历史报表!H18 -> 771.2192 | G22: =历史报表!I18 -> 722.6505 | H22: =H6*H23 -> 606.39736 | I22: =I6*I23 -> 588.09264 | J22: =J6*J23 -> 586.49711 | K22: =K6*K23 -> 583.57414 | L22: =L6*L23 -> 611.36093 | N22: =历史报表!K18 -> 219.0644 | O22: 2025年：政府补助5.71亿+税收返还1.52亿
A23: 占收入比 | C23: =C22/C6 -> 0.0098835263 | D23: =D22/D6 -> 0.0088950527 | E23: =E22/E6 -> 0.014391067 | F23: =F22/F6 -> 0.027014038 | G23: =G22/G6 -> 0.029000498 | H23: =假设!H102 -> 0.022 | I23: =假设!I102 -> 0.02 | J23: =假设!J102 -> 0.019 | K23: =假设!K102 -> 0.018 | L23: =假设!L102 -> 0.018 | N23: =N22/N6 -> 0.017700231
A24: 信用减值损失 | C24: =历史报表!E24 -> -17.4286 | D24: =历史报表!F24 -> -232.8913 | E24: =历史报表!G24 -> -291.6802 | F24: =历史报表!H24 -> -345.4449 | G24: =历史报表!I24 -> -81.4387 | H24: =H6*H25 -> -192.94461 | I24: =I6*I25 -> -176.42779 | J24: =J6*J25 -> -185.20961 | K24: =K6*K25 -> -194.52471 | L24: =L6*L25 -> -203.78698 | N24: =历史报表!K24 -> 4.1395
A25: 占收入比 | C25: =C24/C6 -> -0.00066230717 | D25: =D24/D6 -> -0.0075325813 | E25: =E24/E6 -> -0.0093698744 | F25: =F24/F6 -> -0.012100142 | G25: =G24/G6 -> -0.0032681952 | H25: =假设!H106 -> -0.007 | I25: =假设!I106 -> -0.006 | J25: =假设!J106 -> -0.006 | K25: =假设!K106 -> -0.006 | L25: =假设!L106 -> -0.006
A26: 资产减值损失 | C26: =历史报表!E23 -> -239.801 | D26: =历史报表!F23 -> -122.3486 | E26: =历史报表!G23 -> -147.8754 | F26: =历史报表!H23 -> -107.2242 | G26: =历史报表!I23 -> -294.1611 | H26: =H6*H27 -> -192.94461 | I26: =I6*I27 -> -176.42779 | J26: =J6*J27 -> -185.20961 | K26: =K6*K27 -> -194.52471 | L26: =L6*L27 -> -203.78698 | N26: =历史报表!K23 -> -44.045
A27: 占收入比 | C27: =C26/C6 -> -0.0091127182 | D27: =D26/D6 -> -0.0039572143 | E27: =E26/E6 -> -0.0047503187 | F27: =F26/F6 -> -0.0037558175 | G27: =G26/G6 -> -0.011804902 | H27: =假设!H110 -> -0.007 | I27: =假设!I110 -> -0.006 | J27: =假设!J110 -> -0.006 | K27: =假设!K110 -> -0.006 | L27: =假设!L110 -> -0.006
A28: 投资收益：广发基金（14.187%，权益法）
A29: 广发基金净利润 | C29: 2586.93 | D29: 2133.57 | E29: 1949.69 | F29: 1999.67 | G29: 2753.45 | H29: =G29*(1+H30) -> 4488.1235 | I29: =H29*(1+I30) -> 4712.5297 | J29: =I29*(1+J30) -> 4948.1562 | K29: =J29*(1+K30) -> 5195.564 | L29: =K29*(1+L30) -> 5455.3422 | N29: 2458.57 | O29: 烽火通信年报附注“重要联营企业的主要财务信息”；2026H1A为半年数
A30: 同比 | C30: 0.41831968 | D30: =D29/C29-1 -> -0.1752502 | E30: =E29/D29-1 -> -0.086184189 | F30: =F29/E29-1 -> 0.025634845 | G30: =G29/F29-1 -> 0.3769522 | H30: =假设!H114 -> 0.63 | I30: =假设!I114 -> 0.05 | J30: =假设!J114 -> 0.05 | K30: =假设!K114 -> 0.05 | L30: =假设!L114 -> 0.05 | N30: 1.0838341
A31: 烽火应享权益法收益（=净利润×持股比例） | C31: =C29*假设!$C$18 -> 367.00776 | D31: =D29*假设!$C$18 -> 302.68958 | E31: =E29*假设!$C$18 -> 276.60252 | F31: =F29*假设!$C$18 -> 283.69318 | G31: =G29*假设!$C$18 -> 390.63195 | H31: =H29*假设!$C$18 -> 636.73008 | I31: =I29*假设!$C$18 -> 668.56658 | J31: =J29*假设!$C$18 -> 701.99491 | ... L31: =L29*假设!$C$18 -> 773.94939 | N31: =N29*假设!$C$18 -> 348.79733
A32: 收到广发基金现金分红 | D32: 160 | E32: 180 | F32: 120 | G32: 120 | H32: 144 | I32: =H31*假设!$C$38 -> 254.69203 | J32: =I31*假设!$C$38 -> 267.42663 | K32: =J31*假设!$C$38 -> 280.79797 | L32: =K31*假设!$C$38 -> 294.83786 | N32: 144 | O32: 2026E=2026H1已收1.44亿
A33: 长期股权投资—广发基金账面价值 | E33: 1519.73 | F33: 1684.08 | G33: 1953.76 | H33: =G33+H31-H32 -> 2446.4901 | I33: =H33+I31-I32 -> 2860.3646 | J33: =I33+J31-J32 -> 3294.9329 | K33: =J33+K31-K32 -> 3751.2296 | L33: =K33+L31-L32 -> 4230.3411 | N33: 2156.75
A34: 投资收益合计及其他损益
A35: 权益法投资收益合计 | C35: =历史报表!E20 -> 402.1722 | D35: =历史报表!F20 -> 378.8812 | E35: =历史报表!G20 -> 325.9203 | F35: =历史报表!H20 -> 285.6265 | G35: =历史报表!I20 -> 442.3 | H35: =H31+H36 -> 686.73008 | I35: =I31+I36 -> 718.56658 | J35: =J31+J36 -> 751.99491 | K35: =K31+K36 -> 787.09466 | L35: =L31+L36 -> 823.94939 | N35: =历史报表!K20 -> 400.0886
A36: 其中：其他联营企业 | C36: =C35-C31 -> 35.164441 | D36: =D35-D31 -> 76.191624 | E36: =E35-E31 -> 49.31778 | F36: =F35-F31 -> 1.9333171 | G36: =G35-G31 -> 51.668049 | H36: =假设!H118 -> 50 | I36: =假设!I118 -> 50 | J36: =假设!J118 -> 50 | K36: =假设!K118 -> 50 | L36: =假设!L118 -> 50 | N36: =N35-N31 -> 51.291274
A37: 其他投资收益（含票据终止确认损失） | C37: =历史报表!E19-C35 -> 0.3954 | D37: =历史报表!F19-D35 -> 10.7646 | E37: =历史报表!G19-E35 -> -24.0725 | F37: =历史报表!H19-F35 -> 2.1588 | G37: =历史报表!I19-G35 -> 2.8525 | H37: =假设!H122 -> -25 | I37: =假设!I122 -> -25 | J37: =假设!J122 -> -25 | K37: =假设!K122 -> -25 | L37: =假设!L122 -> -25 | N37: =历史报表!K19-N35 -> -11.1528
A38: 投资收益合计 | C38: =C35+C37 -> 402.5676 | D38: =D35+D37 -> 389.6458 | E38: =E35+E37 -> 301.8478 | F38: =F35+F37 -> 287.7853 | G38: =G35+G37 -> 445.1525 | H38: =H35+H37 -> 661.73008 | I38: =I35+I37 -> 693.56658 | J38: =J35+J37 -> 726.99491 | ... L38: =L35+L37 -> 798.94939 | N38: =N35+N37 -> 388.9358
A39: 公允价值变动收益 | C39: =历史报表!E22 -> 2.7352 | D39: =历史报表!F22 -> -2.4842 | E39: =历史报表!G22 -> 0.3342 | F39: =历史报表!H22 -> 0.269 | G39: =历史报表!I22 -> -12.6198 | H39: 0 | I39: 0 | J39: 0 | K39: 0 | L39: 0 | N39: =历史报表!K22 -> 0
A40: 资产处置收益 | C40: =历史报表!E25 -> 1.838 | D40: =历史报表!F25 -> 4.1996 | E40: =历史报表!G25 -> -14.9768 | F40: =历史报表!H25 -> 6.6168 | G40: =历史报表!I25 -> 0.4398 | H40: 0 | I40: 0 | J40: 0 | K40: 0 | L40: 0 | N40: =历史报表!K25 -> -0.3458
A41: 营业外收支净额 | C41: =历史报表!E27-历史报表!E28 -> -2.6277 | D41: =历史报表!F27-历史报表!F28 -> -0.9538 | E41: =历史报表!G27-历史报表!G28 -> 15.0161 | F41: =历史报表!H27-历史报表!H28 -> -11.2164 | G41: =历史报表!I27-历史报表!I28 -> -11.1238 | H41: =假设!H126 -> -10 | I41: =假设!I126 -> -10 | J41: =假设!J126 -> -10 | K41: =假设!K126 -> -10 | L41: =假设!L126 -> -10 | N41: =历史报表!K27-历史报表!K28 -> 1.4673
A42: 实际所得税率 | C42: =历史报表!E30/历史报表!E29 -> 0.27575799 | D42: =历史报表!F30/历史报表!F29 -> 0.24273553 | E42: =历史报表!G30/历史报表!G29 -> 0.15905757 | F42: =历史报表!H30/历史报表!H29 -> 0.10343917 | G42: =历史报表!I30/历史报表!I29 -> 0.18610153 | H42: =假设!H130 -> 0.13 | I42: =假设!I130 -> 0.13 | J42: =假设!J130 -> 0.13 | K42: =假设!K130 -> 0.13 | L42: =假设!L130 -> 0.13 | N42: =历史报表!K30/历史报表!K29 -> 0.2325974
A43: 盈利质量分析
A44: 核心经营利润（营业利润−投资收益−公允价值−处置） | C44: =利润表!C23-C38-C39-C40 -> 86.5288 | D44: =利润表!D23-D38-D39-D40 -> 149.9902 | E44: =利润表!E23-E38-E39-E40 -> 279.0152 | F44: =利润表!F23-F38-F39-F40 -> 508.6835 | G44: =利润表!G23-G38-G39-G40 -> 40.186 | H44: =利润表!H23-H38-H39-H40 -> 195.323 | I44: =利润表!I23-I38-I39-I40 -> 553.05083 | J44: =利润表!J23-J38-J39-J40 -> 620.16266 | ... L44: =利润表!L23-L38-L39-L40 -> 765.0328 | N44: =利润表!N23-N38-N39-N40 -> -148.6393
A45: 核心经营利润率 | C45: =C44/C6 -> 0.0032881955 | D45: =D44/D6 -> 0.0048512477 | E45: =E44/E6 -> 0.0089630265 | F45: =F44/F6 -> 0.017818015 | G45: =G44/G6 -> 0.0016126939 | H45: =H44/H6 -> 0.0070862874 | I45: =I44/I6 -> 0.01880829 | J45: =J44/J6 -> 0.02009062 | ... L45: =L44/L6 -> 0.022524485 | N45: =N44/N6 -> -0.012009938
A46: 广发基金收益占归母净利润比例 | C46: =C31/利润表!C29 -> 1.2744409 | D46: =D31/利润表!D29 -> 0.74592059 | E46: =E31/利润表!E29 -> 0.54732989 | F46: =F31/利润表!F29 -> 0.40371521 | G46: =G31/利润表!G29 -> 0.89628547 | H46: =H31/利润表!H29 -> 0.8467874 | I46: =I31/利润表!I29 -> 0.62142691 | J46: =J31/利润表!J29 -> 0.60866941 | ... L46: =L31/利润表!L29 -> 0.58105857 | N46: =N31/利润表!N29 -> 1.8091176
A47: 扣除广发基金后的归母净利润 | C47: =利润表!C29-C31 -> -79.032259 | D47: =利润表!D29-D31 -> 103.10372 | E47: =利润表!E29-E31 -> 228.76458 | F47: =利润表!F29-F31 -> 419.01302 | G47: =利润表!G29-G31 -> 45.202348 | H47: =利润表!H29-H31 -> 115.2061 | I47: =利润表!I29-I31 -> 407.29057 | J47: =利润表!J29-J31 -> 451.33217 | ... L47: =利润表!L29-L31 -> 558.01511 | N47: =利润表!N29-N31 -> -155.99763 | O47: 权益法收益免税，故直接扣减
A48: 内部研发形成无形资产的摊销（估算） | C48: =资本开支折旧!C40*假设!$C$39 -> 63.439864 | D48: =资本开支折旧!D40*假设!$C$39 -> 92.226879 | E48: =资本开支折旧!E40*假设!$C$39 -> 125.71326 | F48: =资本开支折旧!F40*假设!$C$39 -> 154.31833 | G48: =资本开支折旧!G40*假设!$C$39 -> 182.80577 | H48: =资本开支折旧!H40*假设!$C$39 -> 245.78949 | I48: =资本开支折旧!I40*假设!$C$39 -> 286.42288 | J48: =资本开支折旧!J40*假设!$C$39 -> 325.95441 | ... L48: =资本开支折旧!L40*假设!$C$39 -> 401.75773 | O48: 公式：无形资产摊销×内部研发占比假设
A49: 研发资本化对税前利润的净增厚（资本化−摊销） | C49: =C17-C48 -> 201.86546 | D49: =D17-D48 -> 199.67493 | E49: =E17-E48 -> 152.45083 | F49: =F17-F48 -> 542.53568 | G49: =G17-G48 -> 405.02064 | H49: =H17-H48 -> 340.76214 | I49: =I17-I48 -> 285.20317 | J49: =J17-J48 -> 225.04419 | ... L49: =L17-L48 -> 117.89907
A50: 若研发全部费用化的归母净利润（估算） | C50: =利润表!C29-C49*(1-C42) -> 141.77605 | D50: =利润表!D29-D49*(1-D42) -> 254.58657 | E50: =利润表!E29-E49*(1-E42) -> 377.16473 | F50: =利润表!F29-F49*(1-F42) -> 216.28996 | G50: =利润表!G29-G49*(1-G42) -> 106.18862 | H50: =利润表!H29-H49*(1-H42) -> 455.47312 | I50: =利润表!I29-I49*(1-I42) -> 827.7304 | J50: =利润表!J29-J49*(1-J42) -> 957.53864 | ... L50: =利润表!L29-L49*(1-L42) -> 1229.3923
A51: 相对2021–23年7%资本化率的“超额资本化” | C51: =C15*MAX(0,C18-0.07) -> 4.5037902 | D51: =D15*MAX(0,D18-0.07) -> 0 | E51: =E15*MAX(0,E18-0.07) -> 8.209423 | F51: =F15*MAX(0,F18-0.07) -> 446.3867 | G51: =G15*MAX(0,G18-0.07) -> 366.77168 | H51: =H15*MAX(0,H18-0.07) -> 370.45366 | I51: =I15*MAX(0,I18-0.07) -> 349.32703 | J51: =J15*MAX(0,J18-0.07) -> 324.11682 | ... L51: =L15*MAX(0,L18-0.07) -> 277.15029 | O51: 7%为2021–2023年平均资本化率（硬编码基准）

Sheet 资本开支折旧
A1: 投资、固定资产与折旧摊销（百万元）
A2: 历史：年报附注固定资产/无形资产/开发支出变动表；预测：在建工程→转固→按原值计提折旧；资本化研发→开发支出→无形资产→摊销
A5: 项目 | B5: 百万元 | C5: 2021A | D5: 2022A | E5: 2023A | F5: 2024A | G5: 2025A | H5: 2026E | I5: 2027E | J5: 2028E | K5: 2029E | L5: 2030E | N5: 2026H1A | O5: 说明 / 来源
A6: 固定资产原值
A7: 期初原值 | C7: 6244.3305 | D7: =C12 -> 6739.3251 | E7: =D12 -> 7360.7014 | F7: =E12 -> 8208.4852 | G7: =F12 -> 8109.039 | H7: =G12 -> 8535.4324 | I7: =H12 -> 9580.9576 | J7: =I12 -> 10833.04 | K7: =J12 -> 12141.542 | L7: =K12 -> 13244.918 | N7: 8535.4324
A8: + 直接购置 | C8: 391.41101 | D8: 418.78004 | E8: 391.74527 | F8: 248.55301 | G8: 224.39685 | H8: 0 | I8: 0 | J8: 0 | K8: 0 | L8: 0 | N8: 323.77315 | O8: 预测期假设全部经在建工程转入
A9: + 在建工程转入 | C9: 256.72105 | D9: 406.12671 | E9: 801.90355 | F9: 93.839617 | G9: 356.72407 | H9: =H28 -> 1199.1631 | I9: =I28 -> 1424.5397 | J9: =J28 -> 1503.4968 | K9: =K28 -> 1321.9233 | L9: =L28 -> 1132.0578 | N9: 451.40111
A10: + 其他（企业合并/汇率/重分类，轧差） | C10: -2.2737368e-13 | D10: 2.6614868 | E10: 6.4101029 | F10: 87.662271 | G10: -3.4346921 | H10: 0 | I10: 0 | J10: 0 | K10: 0 | L10: 0
A11: − 处置/报废 | C11: 153.13744 | D11: 206.19192 | E11: 352.27517 | F11: 529.50114 | G11: 151.29281 | H11: =H7*H23 -> 153.63778 | I11: =I7*I23 -> 172.45724 | J11: =J7*J23 -> 194.99472 | K11: =K7*K23 -> 218.54776 | L11: =L7*L23 -> 238.40852 | N11: 72.159974
A12: 期末原值 | C12: =C7+C8+C9+C10-C11 -> 6739.3251 | D12: =D7+D8+D9+D10-D11 -> 7360.7014 | E12: =E7+E8+E9+E10-E11 -> 8208.4852 | F12: =F7+F8+F9+F10-F11 -> 8109.039 | G12: =G7+G8+G9+G10-G11 -> 8535.4324 | H12: =H7+H8+H9+H10-H11 -> 9580.9576 | I12: =I7+I8+I9+I10-I11 -> 10833.04 | J12: =J7+J8+J9+J10-J11 -> 12141.542 | ... L12: =L7+L8+L9+L10-L11 -> 14138.567 | N12: 9238.4467
A13: 累计折旧
A14: 期初累计折旧 | C14: 2882.0809 | D14: =C18 -> 3273.8431 | E14: =D18 -> 3680.8563 | F14: =E18 -> 4013.2494 | G14: =F18 -> 4345.515 | H14: =G18 -> 4926.1414 | I14: =H18 -> 5558.1148 | J14: =I18 -> 6270.8751 | K14: =J18 -> 7072.1722 | L14: =K18 -> 7954.6398 | N14: 4926.1414
A15: + 本期计提折旧 | C15: 537.45957 | D15: 482.38679 | E15: 657.70459 | F15: 689.9163 | G15: 704.60417 | H15: =H22*(H7+0.5*(H8+H9)) -> 785.6112 | I15: =I22*(I7+0.5*(I8+I9)) -> 885.21756 | J15: =J22*(J7+0.5*(J8+J9)) -> 996.29181 | K15: =K22*(K7+0.5*(K8+K9)) -> 1101.0153 | L15: =L22*(L7+0.5*(L8+L9)) -> 1187.7414 | N15: 403.5562
A16: + 其他（轧差） | C16: -2.2737368e-13 | D16: 0.29455668 | E16: 3.6729557 | F16: 160.68636 | G16: -2.2478351 | H16: 0 | I16: 0 | J16: 0 | K16: 0 | L16: 0
A17: − 处置/报废转出 | C17: 145.69746 | D17: 75.668146 | E17: 328.98436 | F17: 518.33706 | G17: 121.72997 | H17: =H11 -> 153.63778 | I17: =I11 -> 172.45724 | J17: =J11 -> 194.99472 | K17: =K11 -> 218.54776 | L17: =L11 -> 238.40852 | N17: 64.900082 | O17: 预测假设报废资产已提足折旧
A18: 期末累计折旧 | C18: =C14+C15+C16-C17 -> 3273.8431 | D18: =D14+D15+D16-D17 -> 3680.8563 | E18: =E14+E15+E16-E17 -> 4013.2494 | F18: =F14+F15+F16-F17 -> 4345.515 | G18: =G14+G15+G16-G17 -> 4926.1414 | H18: =H14+H15+H16-H17 -> 5558.1148 | I18: =I14+I15+I16-I17 -> 6270.8751 | J18: =J14+J15+J16-J17 -> 7072.1722 | ... L18: =L14+L15+L16-L17 -> 8903.9727 | N18: 5264.7975
A19: 减值准备（历史含尾差） | C19: =C12-C18-历史报表!E59 -> 6.5134798 | D19: =D12-D18-历史报表!F59 -> 6.5134857 | E19: =E12-E18-历史报表!G59 -> 0.98285974 | F19: =F12-F18-历史报表!H59 -> 0.84972134 | G19: =G12-G18-历史报表!I59 -> 0.84977073 | H19: =G19 -> 0.84977073 | I19: =H19 -> 0.84977073 | J19: =I19 -> 0.84977073 | K19: =J19 -> 0.84977073 | L19: =K19 -> 0.84977073 | N19: 0.84973506 | O19: 历史=原值−累计折旧−报表净值（附注减值准备0.8亿元级，差额为四舍五入）
A20: 固定资产净值 | C20: =C12-C18-C19 -> 3458.9686 | D20: =D12-D18-D19 -> 3673.3317 | E20: =E12-E18-E19 -> 4194.2529 | F20: =F12-F18-F19 -> 3762.6742 | G20: =G12-G18-G19 -> 3608.4412 | H20: =H12-H18-H19 -> 4021.9931 | I20: =I12-I18-I19 -> 4561.3152 | J20: =J12-J18-J19 -> 5068.5202 | ... L20: =L12-L18-L19 -> 5233.7445 | N20: =N12-N18-N19 -> 3972.7994
A21: 核对：净值−资产负债表 | C21: =C20-历史报表!E59 -> 0 | D21: =D20-历史报表!F59 -> 0 | E21: =E20-历史报表!G59 -> 0 | F21: =F20-历史报表!H59 -> 0 | G21: =G20-历史报表!I59 -> 0 | N21: =N20-历史报表!K59 -> -2.3299999e-06
A22: 折旧率（折旧/(期初原值+½新增)） | C22: =C15/(C7+0.5*(C8+C9)) -> 0.08182508 | D22: =D15/(D7+0.5*(D8+D9)) -> 0.067449907 | E22: =E15/(E7+0.5*(E8+E9)) -> 0.082651895 | F22: =F15/(F7+0.5*(F8+F9)) -> 0.082332043 | G22: =G15/(G7+0.5*(G8+G9)) -> 0.08388545 | H22: =假设!H151 -> 0.086 | I22: =假设!I151 -> 0.086 | J22: =假设!J151 -> 0.086 | K22: =假设!K151 -> 0.086 | L22: =假设!L151 -> 0.086
A23: 报废率（报废原值/期初原值） | C23: =C11/C7 -> 0.024524236 | D23: =D11/D7 -> 0.030595337 | E23: =E11/E7 -> 0.047858913 | F23: =F11/F7 -> 0.06450656 | G23: =G11/G7 -> 0.018657305 | H23: =假设!H155 -> 0.018 | I23: =假设!I155 -> 0.018 | J23: =假设!J155 -> 0.018 | K23: =假设!K155 -> 0.018 | L23: =假设!L155 -> 0.018
A24: 已提折旧比例（成新率反向指标） | C24: =C18/C12 -> 0.48578203 | D24: =D18/D12 -> 0.50006868 | E24: =E18/E12 -> 0.48891474 | F24: =F18/F12 -> 0.53588533 | G24: =G18/G12 -> 0.57714023 | H24: =H18/H12 -> 0.58012101 | I24: =I18/I12 -> 0.57886568 | J24: =J18/J12 -> 0.58247726 | ... L24: =L18/L12 -> 0.62976486
A25: 在建工程
A26: 期初余额 | C26: 877.2857 | D26: =C30 -> 1191.0416 | E26: =D30 -> 916.072 | F26: =E30 -> 429.2772 | G26: =F30 -> 889.8926 | H26: =G30 -> 1364.8068 | I26: =H30 -> 1465.6437 | J26: =I30 -> 1741.1041 | K26: =J30 -> 1837.6072 | L26: =K30 -> 1615.684
A27: + 本期投入 | C27: =C30-C26+C28+C29 -> 570.47695 | D27: =D30-D26+D28+D29 -> 296.40205 | E27: =E30-E26+E28+E29 -> 315.10875 | F27: =F30-F26+F28+F29 -> 554.45502 | G27: =G30-G26+G28+G29 -> 831.63827 | H27: =假设!H139 -> 1300 | I27: =假设!I139 -> 1700 | J27: =假设!J139 -> 1600 | K27: =假设!K139 -> 1100 | L27: =假设!L139 -> 900 | O27: 历史为轧差推算
A28: − 转入固定资产 | C28: =C9 -> 256.72105 | D28: =D9 -> 406.12671 | E28: =E9 -> 801.90355 | F28: =F9 -> 93.839617 | G28: =G9 -> 356.72407 | H28: =(H26+H27)*H31 -> 1199.1631 | I28: =(I26+I27)*I31 -> 1424.5397 | J28: =(J26+J27)*J31 -> 1503.4968 | K28: =(K26+K27)*K31 -> 1321.9233 | L28: =(L26+L27)*L31 -> 1132.0578
A29: − 转入无形资产等 | C29: 0 | D29: 165.24494 | E29: 0 | F29: 0 | G29: 0 | H29: 0 | I29: 0 | J29: 0 | K29: 0 | L29: 0
A30: 期末余额 | C30: =历史报表!E61 -> 1191.0416 | D30: =历史报表!F61 -> 916.072 | E30: =历史报表!G61 -> 429.2772 | F30: =历史报表!H61 -> 889.8926 | G30: =历史报表!I61 -> 1364.8068 | H30: =H26+H27-H28-H29 -> 1465.6437 | I30: =I26+I27-I28-I29 -> 1741.1041 | J30: =J26+J27-J28-J29 -> 1837.6072 | K30: =K26+K27-K28-K29 -> 1615.684 | L30: =L26+L27-L28-L29 -> 1383.6262 | N30: =历史报表!K61 -> 1155.3614
A31: 转固比例 | C31: =C28/(C26+C27) -> 0.17732261 | D31: =D28/(D26+D27) -> 0.2730367 | E31: =E28/(E26+E27) -> 0.65132886 | F31: =F28/(F26+F27) -> 0.095391424 | G31: =G28/(G26+G27) -> 0.20721329 | H31: =假设!H147 -> 0.45 | I31: =假设!I147 -> 0.45 | J31: =假设!J147 -> 0.45 | K31: =假设!K147 -> 0.45 | L31: =假设!L147 -> 0.45
A32: 无形资产
A33: 期初原值 | C33: 1427.5411 | D33: =C38 -> 1487.1611 | E33: =D38 -> 1874.7888 | F33: =E38 -> 2376.7389 | G33: =F38 -> 2804.2838 | H33: =G38 -> 3753.4302 | I33: =H38 -> 4439.5527 | J33: =I38 -> 5107.8766 | K33: =J38 -> 5757.2704 | L33: =K38 -> 6388.6245 | N33: 3753.4302
A34: + 外购（土地、软件等） | C34: 61.420921 | D34: 115.89485 | E34: 217.90332 | F34: 101.05921 | G34: 66.699171 | H34: =假设!H143 -> 70 | I34: =假设!I143 -> 70 | J34: =假设!J143 -> 70 | K34: =假设!K143 -> 70 | L34: =假设!L143 -> 70 | N34: 7.9348225
A35: + 开发支出转入（内部研发） | C35: 1.78 | D35: 124.28471 | E35: 351.50396 | F35: 361.35008 | G35: 906.8602 | H35: =H51 -> 616.12253 | I35: =I51 -> 598.32394 | J35: =J51 -> 579.3938 | K35: =K51 -> 561.3541 | L35: =L51 -> 544.67518 | N35: 25.834634
A36: + 其他（在建工程转入/重分类，轧差） | C36: 3.952394e-14 | D36: 180.30612 | E36: 0.05379566 | F36: 56.5794 | G36: 2.0298546 | H36: =H29 -> 0 | I36: =I29 -> 0 | J36: =J29 -> 0 | K36: =K29 -> 0 | L36: =L29 -> 0
A37: − 处置 | C37: 3.5809342 | D37: 32.857928 | E37: 67.51104 | F37: 91.443788 | G37: 26.442815 | H37: 0 | I37: 0 | J37: 0 | K37: 0 | L37: 0 | N37: 2.7340477
A38: 期末原值 | C38: =C33+C34+C35+C36-C37 -> 1487.1611 | D38: =D33+D34+D35+D36-D37 -> 1874.7888 | E38: =E33+E34+E35+E36-E37 -> 2376.7389 | F38: =F33+F34+F35+F36-F37 -> 2804.2838 | G38: =G33+G34+G35+G36-G37 -> 3753.4302 | H38: =H33+H34+H35+H36-H37 -> 4439.5527 | I38: =I33+I34+I35+I36-I37 -> 5107.8766 | J38: =J33+J34+J35+J36-J37 -> 5757.2704 | ... L38: =L33+L34+L35+L36-L37 -> 7003.2997 | N38: 3784.4656
A39: 期初累计摊销 | C39: 427.55604 | D39: =C43 -> 529.84178 | E39: =D43 -> 666.52787 | F39: =E43 -> 817.31539 | G39: =F43 -> 1056.1686 | H39: =G43 -> 1339.5017 | I39: =H43 -> 1749.1508 | J39: =I43 -> 2226.5223 | K39: =J43 -> 2769.7797 | L39: =K43 -> 3377.0744 | N39: 1339.5017
A40: + 本期摊销 | C40: 105.73311 | D40: 153.71147 | E40: 209.5221 | F40: 257.19722 | G40: 304.67628 | H40: =H47*(H33+0.5*(H34+H35+H36)) -> 409.64914 | I40: =I47*(I33+0.5*(I34+I35+I36)) -> 477.37147 | J40: =J47*(J33+0.5*(J34+J35+J36)) -> 543.25735 | K40: =K47*(K33+0.5*(K34+K35+K36)) -> 607.29475 | L40: =L47*(L33+0.5*(L34+L35+L36)) -> 669.59621 | N40: 191.21776
A41: + 其他（轧差） | C41: -4.7961635e-14 | D41: 11.612211 | E41: 0.00596508 | F41: 1.0658141e-14 | G41: 0.001342 | H41: 0 | I41: 0 | J41: 0 | K41: 0 | L41: 0
A42: − 处置转出 | C42: 3.4473738 | D42: 28.637587 | E42: 58.740546 | F42: 18.343975 | G42: 21.344565 | H42: 0 | I42: 0 | J42: 0 | K42: 0 | L42: 0 | N42: 1.6930227
A43: 期末累计摊销 | C43: =C39+C40+C41-C42 -> 529.84178 | D43: =D39+D40+D41-D42 -> 666.52787 | E43: =E39+E40+E41-E42 -> 817.31539 | F43: =F39+F40+F41-F42 -> 1056.1686 | G43: =G39+G40+G41-G42 -> 1339.5017 | H43: =H39+H40+H41-H42 -> 1749.1508 | I43: =I39+I40+I41-I42 -> 2226.5223 | J43: =J39+J40+J41-J42 -> 2769.7797 | ... L43: =L39+L40+L41-L42 -> 4046.6706 | N43: 1529.0264
A44: 减值准备（历史含尾差） | C44: =C38-C43-历史报表!E64 -> 0.42218815 | D44: =D38-D43-历史报表!F64 -> 6.1222437 | E44: =E38-E43-历史报表!G64 -> 6.1221649 | F44: =F38-F43-历史报表!H64 -> 6.1222242 | G44: =G38-G43-历史报表!I64 -> 6.1221801 | H44: =G44 -> 6.1221801 | I44: =H44 -> 6.1221801 | J44: =I44 -> 6.1221801 | K44: =J44 -> 6.1221801 | L44: =K44 -> 6.1221801 | N44: 6.14 | O44: 附注：软件类减值准备约0.06亿元
A45: 无形资产净值 | C45: =C38-C43-C44 -> 956.8971 | D45: =D38-D43-D44 -> 1202.1387 | E45: =E38-E43-E44 -> 1553.3013 | F45: =F38-F43-F44 -> 1741.9929 | G45: =G38-G43-G44 -> 2407.8063 | H45: =H38-H43-H44 -> 2684.2797 | I45: =I38-I43-I44 -> 2875.2322 | J45: =J38-J43-J44 -> 2981.3686 | ... L45: =L38-L43-L44 -> 2950.5069 | N45: =N38-N43-N44 -> 2249.2992
A46: 核对：净值−资产负债表 | C46: =C45-历史报表!E64 -> 0 | D46: =D45-历史报表!F64 -> 0 | E46: =E45-历史报表!G64 -> 0 | F46: =F45-历史报表!H64 -> 0 | G46: =G45-历史报表!I64 -> 0 | N46: =N45-历史报表!K64 -> -0.01784435
A47: 摊销率（摊销/(期初原值+½新增)） | C47: =C40/(C33+0.5*(C34+C35+C36)) -> 0.072462543 | D47: =D40/(D33+0.5*(D34+D35+D36)) -> 0.0905568 | E47: =E40/(E33+0.5*(E34+E35+E36)) -> 0.097022563 | F47: =F40/(F33+0.5*(F34+F35+F36)) -> 0.097562392 | G47: =G40/(G33+0.5*(G34+G35+G36)) -> 0.092548306 | H47: =假设!H159 -> 0.1 | I47: =假设!I159 -> 0.1 | J47: =假设!J159 -> 0.1 | K47: =假设!K159 -> 0.1 | L47: =假设!L159 -> 0.1
A48: 开发支出（资本化研发）
A49: 期初余额 | C49: 1134.4627 | D49: =C53 -> 1124.4628 | E49: =D53 -> 1020.541 | F49: =E53 -> 938.2379 | G49: =F53 -> 1273.7418 | H49: =G53 -> 953.7547 | I49: =H53 -> 924.1838 | J49: =I53 -> 897.4859 | K49: =J53 -> 869.0907 | L49: =K53 -> 842.03115
A50: + 本期资本化研发投入 | C50: =费用!C17 -> 265.30533 | D50: =费用!D17 -> 291.90181 | E50: =费用!E17 -> 278.16409 | F50: =费用!F17 -> 696.85401 | G50: =费用!G17 -> 587.82641 | H50: =费用!H17 -> 586.55163 | I50: =费用!I17 -> 571.62605 | J50: =费用!J17 -> 550.9986 | ... L50: =费用!L17 -> 519.65679
A51: − 转入无形资产 | C51: =C35 -> 1.78 | D51: =D35 -> 124.28471 | E51: =E35 -> 351.50396 | F51: =F35 -> 361.35008 | G51: =G35 -> 906.8602 | H51: =(H49+H50)*H54 -> 616.12253 | I51: =(I49+I50)*I54 -> 598.32394 | J51: =(J49+J50)*J54 -> 579.3938 | K51: =(K49+K50)*K54 -> 561.3541 | L51: =(L49+L50)*L54 -> 544.67518
A52: ± 其他（费用化转出等，轧差） | C52: =C53-C49-C50+C51 -> -273.52523 | D52: =D53-D49-D50+D51 -> -271.5389 | E52: =E53-E49-E50+E51 -> -8.9632279 | F52: =F53-F49-F50+F51 -> -3.47e-05 | G52: =G53-G49-G50+G51 -> -0.95330667 | H52: 0 | I52: 0 | J52: 0 | K52: 0 | L52: 0
A53: 期末余额 | C53: =历史报表!E65 -> 1124.4628 | D53: =历史报表!F65 -> 1020.541 | E53: =历史报表!G65 -> 938.2379 | F53: =历史报表!H65 -> 1273.7418 | G53: =历史报表!I65 -> 953.7547 | H53: =H49+H50-H51+H52 -> 924.1838 | I53: =I49+I50-I51+I52 -> 897.4859 | J53: =J49+J50-J51+J52 -> 869.0907 | K53: =K49+K50-K51+K52 -> 842.03115 | L53: =L49+L50-L51+L52 -> 817.01276 | N53: =历史报表!K65 -> 1229.9452
A54: 转无形资产比例 | C54: =C51/(C49+C50) -> 0.0012716393 | D54: =D51/(D49+D50) -> 0.087749091 | E54: =E51/(E49+E50) -> 0.27065726 | F54: =F51/(F49+F50) -> 0.2209968 | G54: =G51/(G49+G50) -> 0.48714852 | H54: =假设!H163 -> 0.4 | I54: =假设!I163 -> 0.4 | J54: =假设!J163 -> 0.4 | K54: =假设!K163 -> 0.4 | L54: =假设!L163 -> 0.4
A55: 使用权资产与长期待摊费用
A56: 使用权资产净值 | C56: =历史报表!E63 -> 88.6436 | D56: =历史报表!F63 -> 147.4453 | E56: =历史报表!G63 -> 78.6099 | F56: =历史报表!H63 -> 160.5597 | G56: =历史报表!I63 -> 108.2493 | H56: =G56 -> 108.2493 | I56: =H56 -> 108.2493 | J56: =I56 -> 108.2493 | K56: =J56 -> 108.2493 | L56: =K56 -> 108.2493 | N56: =历史报表!K63 -> 79.9477 | O56: 假设新增租赁=折旧，余额持平
A57: 使用权资产折旧 | C57: =历史报表!E151 -> 29.1999 | D57: =历史报表!F151 -> 83.9439 | E57: =历史报表!G151 -> 88.8283 | F57: =历史报表!H151 -> 69.341 | G57: =历史报表!I151 -> 69.2566 | H57: =假设!H167 -> 60 | I57: =假设!I167 -> 60 | J57: =假设!J167 -> 60 | K57: =假设!K167 -> 60 | L57: =假设!L167 -> 60
A58: 长期待摊费用 | C58: =历史报表!E67 -> 57.8415 | D58: =历史报表!F67 -> 50.8145 | E58: =历史报表!G67 -> 48.4462 | F58: =历史报表!H67 -> 39.0585 | G58: =历史报表!I67 -> 36.4732 | H58: =G58 -> 36.4732 | I58: =H58 -> 36.4732 | J58: =I58 -> 36.4732 | K58: =J58 -> 36.4732 | L58: =K58 -> 36.4732
A59: 长期待摊费用摊销 | C59: =历史报表!E152 -> 12.7651 | D59: =历史报表!F152 -> 10.2963 | E59: =历史报表!G152 -> 7.4813 | F59: =历史报表!H152 -> 9.405 | G59: =历史报表!I152 -> 7.4958 | H59: =假设!H171 -> 8 | I59: =假设!I171 -> 8 | J59: =假设!J171 -> 8 | K59: =假设!K171 -> 8 | L59: =假设!L171 -> 8
A60: 折旧摊销合计（现金流量表口径）
A61: 固定资产折旧（含投资性房地产） | C61: =历史报表!E149 -> 542.2143 | D61: =历史报表!F149 -> 487.1415 | E61: =历史报表!G149 -> 662.437 | F61: =历史报表!H149 -> 694.6932 | G61: =历史报表!I149 -> 709.3589 | H61: =H15 -> 785.6112 | I61: =I15 -> 885.21756 | J61: =J15 -> 996.29181 | K61: =K15 -> 1101.0153 | L61: =L15 -> 1187.7414 | N61: =历史报表!K149 -> 405.9335
A62: 无形资产摊销 | C62: =历史报表!E150 -> 105.7331 | D62: =历史报表!F150 -> 235.0587 | E62: =历史报表!G150 -> 209.5221 | F62: =历史报表!H150 -> 257.1972 | G62: =历史报表!I150 -> 304.6763 | H62: =H40 -> 409.64914 | I62: =I40 -> 477.37147 | J62: =J40 -> 543.25735 | K62: =K40 -> 607.29475 | L62: =L40 -> 669.59621 | N62: =历史报表!K150 -> 191.2178
A63: 使用权资产折旧 | C63: =C57 -> 29.1999 | D63: =D57 -> 83.9439 | E63: =E57 -> 88.8283 | F63: =F57 -> 69.341 | G63: =G57 -> 69.2566 | H63: =H57 -> 60 | I63: =I57 -> 60 | J63: =J57 -> 60 | ... L63: =L57 -> 60 | N63: =历史报表!K151 -> 21.1434
A64: 长期待摊费用摊销 | C64: =C59 -> 12.7651 | D64: =D59 -> 10.2963 | E64: =E59 -> 7.4813 | F64: =F59 -> 9.405 | G64: =G59 -> 7.4958 | H64: =H59 -> 8 | I64: =I59 -> 8 | J64: =J59 -> 8 | ... L64: =L59 -> 8 | N64: =历史报表!K152 -> 1.6197
A65: 折旧摊销合计 | C65: =SUM(C61:C64) -> 689.9124 | D65: =SUM(D61:D64) -> 816.4404 | E65: =SUM(E61:E64) -> 968.2687 | F65: =SUM(F61:F64) -> 1030.6364 | G65: =SUM(G61:G64) -> 1090.7876 | H65: =SUM(H61:H64) -> 1263.2603 | I65: =SUM(I61:I64) -> 1430.589 | J65: =SUM(J61:J64) -> 1607.5492 | ... L65: =SUM(L61:L64) -> 1925.3376 | N65: =SUM(N61:N64) -> 619.9144
A66: 折旧摊销/收入 | C66: =C65/利润表!C6 -> 0.026217477 | D66: =D65/利润表!D6 -> 0.026406756 | E66: =E65/利润表!E6 -> 0.031104463 | F66: =F65/利润表!F6 -> 0.036100827 | G66: =G65/利润表!G6 -> 0.043774112 | H66: =H65/利润表!H6 -> 0.045830885 | I66: =I65/利润表!I6 -> 0.048651826 | J66: =J65/利润表!J6 -> 0.052077723 | ... L66: =L65/利润表!L6 -> 0.056686771
A67: 资本开支合计
A68: 固定资产及在建工程投入 | C68: =C27+C8 -> 961.88797 | D68: =D27+D8 -> 715.18209 | E68: =E27+E8 -> 706.85402 | F68: =F27+F8 -> 803.00802 | G68: =G27+G8 -> 1056.0351 | H68: =H27+H8 -> 1300 | I68: =I27+I8 -> 1700 | J68: =J27+J8 -> 1600 | ... L68: =L27+L8 -> 900
A69: 外购无形资产 | C69: =C34 -> 61.420921 | D69: =D34 -> 115.89485 | E69: =E34 -> 217.90332 | F69: =F34 -> 101.05921 | G69: =G34 -> 66.699171 | H69: =H34 -> 70 | I69: =I34 -> 70 | J69: =J34 -> 70 | ... L69: =L34 -> 70
A70: 资本化研发支出 | C70: =C50 -> 265.30533 | D70: =D50 -> 291.90181 | E70: =E50 -> 278.16409 | F70: =F50 -> 696.85401 | G70: =G50 -> 587.82641 | H70: =H50 -> 586.55163 | I70: =I50 -> 571.62605 | J70: =J50 -> 550.9986 | ... L70: =L50 -> 519.65679
A71: 长期待摊费用支出 | H71: =H59 -> 8 | I71: =I59 -> 8 | J71: =J59 -> 8 | K71: =K59 -> 8 | L71: =L59 -> 8
A72: 资本开支合计（权责口径） | C72: =SUM(C68:C71) -> 1288.6142 | D72: =SUM(D68:D71) -> 1122.9787 | E72: =SUM(E68:E71) -> 1202.9214 | F72: =SUM(F68:F71) -> 1600.9212 | G72: =SUM(G68:G71) -> 1710.5607 | H72: =SUM(H68:H71) -> 1964.5516 | I72: =SUM(I68:I71) -> 2349.626 | J72: =SUM(J68:J71) -> 2228.9986 | ... L72: =SUM(L68:L71) -> 1497.6568
A73: 报表：购建固定资产、无形资产和其他长期资产支付的现金 | C73: =历史报表!E126 -> 700.5675 | D73: =历史报表!F126 -> 732.8186 | E73: =历史报表!G126 -> 749.8998 | F73: =历史报表!H126 -> 1368.6518 | G73: =历史报表!I126 -> 1436.5548 | N73: =历史报表!K126 -> 648.24 | O73: 历史现金口径与权责口径差异来自应付工程款等时点差
A74: 资本开支/收入 | C74: =C72/利润表!C6 -> 0.048968846 | D74: =D72/利润表!D6 -> 0.03632136 | E74: =E72/利润表!E6 -> 0.038642399 | F74: =F72/利润表!F6 -> 0.056076596 | G74: =G72/利润表!G6 -> 0.068646064 | H74: =H72/利润表!H6 -> 0.071273622 | I74: =I72/利润表!I6 -> 0.079906664 | J74: =J72/利润表!J6 -> 0.072210029 | ... L74: =L72/利润表!L6 -> 0.044094774
A75: 资本开支/折旧摊销 | C75: =C72/C65 -> 1.867794 | D75: =D72/D65 -> 1.3754571 | E75: =E72/E65 -> 1.2423426 | F75: =F72/F65 -> 1.5533327 | G75: =G72/G65 -> 1.5681886 | H75: =H72/H65 -> 1.5551439 | I75: =I72/I65 -> 1.6424186 | J75: =J72/J65 -> 1.3865819 | ... L75: =L72/L65 -> 0.7778671

Sheet 营运资本
A1: 营运资本（百万元）
A2: 周转天数按期末余额/全年收入（或营业成本）×365；预测余额=驱动×基数
A5: 项目 | B5: 百万元 | C5: 2021A | D5: 2022A | E5: 2023A | F5: 2024A | G5: 2025A | H5: 2026E | I5: 2027E | J5: 2028E | K5: 2029E | L5: 2030E | N5: 2026H1A | O5: 说明 / 来源
A6: 营业收入 | C6: =利润表!C6 -> 26314.98 | D6: =利润表!D6 -> 30917.861 | E6: =利润表!E6 -> 31129.574 | F6: =利润表!F6 -> 28548.831 | G6: =利润表!G6 -> 24918.554 | H6: =利润表!H6 -> 27563.516 | I6: =利润表!I6 -> 29404.632 | J6: =利润表!J6 -> 30868.269 | ... L6: =利润表!L6 -> 33964.496
A7: 营业成本 | C7: =利润表!C7 -> 20605.046 | D7: =利润表!D7 -> 24126.68 | E7: =利润表!E7 -> 24728.125 | F7: =利润表!F7 -> 22482.664 | G7: =利润表!G7 -> 19661.228 | H7: =利润表!H7 -> 21762.216 | I7: =利润表!I7 -> 23299.646 | J7: =利润表!J7 -> 24627.741 | ... L7: =利润表!L7 -> 27167.34
A8: 经营性流动资产
A9: 应收票据及应收款项融资 | C9: =历史报表!E44+历史报表!E46 -> 791.3691 | D9: =历史报表!F44+历史报表!F46 -> 722.2022 | E9: =历史报表!G44+历史报表!G46 -> 1387.9972 | F9: =历史报表!H44+历史报表!H46 -> 1704.2001 | G9: =历史报表!I44+历史报表!I46 -> 967.2344 | H9: =H6*H10 -> 1102.5406 | I9: =I6*I10 -> 1176.1853 | J9: =J6*J10 -> 1234.7308 | K9: =K6*K10 -> 1296.8314 | L9: =L6*L10 -> 1358.5799 | N9: =历史报表!K44+历史报表!K46 -> 1214.8501
A10: 占比 | C10: =C9/C6 -> 0.030072951 | D10: =D9/D6 -> 0.023358738 | E10: =E9/E6 -> 0.044587735 | F10: =F9/F6 -> 0.059694217 | G10: =G9/G6 -> 0.038815831 | H10: =假设!H180 -> 0.04 | I10: =假设!I180 -> 0.04 | J10: =假设!J180 -> 0.04 | K10: =假设!K180 -> 0.04 | L10: =假设!L180 -> 0.04
A11: 应收账款 | C11: =历史报表!E45 -> 4219.3462 | D11: =历史报表!F45 -> 6830.3427 | E11: =历史报表!G45 -> 12411.795 | F11: =历史报表!H45 -> 15260.857 | G11: =历史报表!I45 -> 14811.052 | H11: =H6*H12/365 -> 15103.297 | I11: =I6*I12/365 -> 15306.521 | J11: =J6*J12/365 -> 15222.708 | K11: =K6*K12/365 -> 15544.212 | L11: =L6*L12/365 -> 15819.08 | N11: =历史报表!K45 -> 13100.291 | O11: 2021年42亿→2025年148亿
A12: 周转天数 | C12: =C11/C6*365 -> 58.524131 | D12: =D11/D6*365 -> 80.635433 | E12: =E11/E6*365 -> 145.53059 | F12: =F11/F6*365 -> 195.11176 | G12: =G11/G6*365 -> 216.94813 | H12: =假设!H176 -> 200 | I12: =假设!I176 -> 190 | J12: =假设!J176 -> 180 | K12: =假设!K176 -> 175 | L12: =假设!L176 -> 170
A13: 预付款项 | C13: =历史报表!E47 -> 345.0894 | D13: =历史报表!F47 -> 744.5724 | E13: =历史报表!G47 -> 1204.0073 | F13: =历史报表!H47 -> 659.2119 | G13: =历史报表!I47 -> 1461.3915 | H13: =H7*H14 -> 1632.1662 | I13: =I7*I14 -> 1630.9752 | J13: =J7*J14 -> 1600.8032 | K13: =K7*K14 -> 1681.0694 | L13: =L7*L14 -> 1765.8771 | N13: =历史报表!K47 -> 2516.0374
A14: 占比 | C14: =C13/C7 -> 0.016747811 | D14: =D13/D7 -> 0.030860955 | E14: =E13/E7 -> 0.048689793 | F14: =F13/F7 -> 0.029320898 | G14: =G13/G7 -> 0.074328596 | H14: =假设!H184 -> 0.075 | I14: =假设!I184 -> 0.07 | J14: =假设!J184 -> 0.065 | K14: =假设!K184 -> 0.065 | L14: =假设!L184 -> 0.065
A15: 其他应收款 | C15: =历史报表!E48 -> 680.7874 | D15: =历史报表!F48 -> 484.3906 | E15: =历史报表!G48 -> 646.0326 | F15: =历史报表!H48 -> 496.4689 | G15: =历史报表!I48 -> 367.0848 | H15: =G15 -> 367.0848 | I15: =H15 -> 367.0848 | J15: =I15 -> 367.0848 | K15: =J15 -> 367.0848 | L15: =K15 -> 367.0848 | N15: =历史报表!K48 -> 315.1794
A16: 存货 | C16: =历史报表!E52 -> 14605.128 | D16: =历史报表!F52 -> 14390.162 | E16: =历史报表!G52 -> 9718.9319 | F16: =历史报表!H52 -> 9329.2257 | G16: =历史报表!I52 -> 10575.039 | H16: =H7*H17/365 -> 11030.164 | I16: =I7*I17/365 -> 11490.236 | J16: =J7*J17/365 -> 11807.821 | K16: =K7*K17/365 -> 12045.597 | L16: =L7*L17/365 -> 12653.282 | N16: =历史报表!K52 -> 13560.093
A17: 周转天数 | C17: =C16/C7*365 -> 258.71681 | D17: =D16/D7*365 -> 217.70127 | E17: =E16/E7*365 -> 143.45649 | F17: =F16/F7*365 -> 151.45747 | G17: =G16/G7*365 -> 196.31984 | H17: =假设!H188 -> 185 | I17: =假设!I188 -> 180 | J17: =假设!J188 -> 175 | K17: =假设!K188 -> 170 | L17: =假设!L188 -> 170
A18: 其他流动资产（含合同资产等，轧差） | C18: =历史报表!E54-历史报表!E42-C9-C11-C13-C15-C16 -> 543.3164 | D18: =历史报表!F54-历史报表!F42-D9-D11-D13-D15-D16 -> 633.5327 | E18: =历史报表!G54-历史报表!G42-E9-E11-E13-E15-E16 -> 725.1378 | F18: =历史报表!H54-历史报表!H42-F9-F11-F13-F15-F16 -> 917.7123 | G18: =历史报表!I54-历史报表!I42-G9-G11-G13-G15-G16 -> 539.4725 | H18: =H6*H19 -> 606.39736 | I18: =I6*I19 -> 646.9019 | J18: =J6*J19 -> 679.10192 | K18: =K6*K19 -> 713.25728 | L18: =L6*L19 -> 747.21892 | N18: =历史报表!K54-历史报表!K42-N9-N11-N13-N15-N16 -> 706.3645
A19: 占比 | C19: =C18/C6 -> 0.020646658 | D19: =D18/D6 -> 0.020490832 | E19: =E18/E6 -> 0.023294177 | F19: =F18/F6 -> 0.032145355 | G19: =G18/G6 -> 0.02164943 | H19: =假设!H192 -> 0.022 | I19: =假设!I192 -> 0.022 | J19: =假设!J192 -> 0.022 | K19: =假设!K192 -> 0.022 | L19: =假设!L192 -> 0.022
A20: 经营性流动资产合计 | C20: =C9+C11+C13+C15+C16+C18 -> 21185.036 | D20: =D9+D11+D13+D15+D16+D18 -> 23805.202 | E20: =E9+E11+E13+E15+E16+E18 -> 26093.902 | F20: =F9+F11+F13+F15+F16+F18 -> 28367.676 | G20: =G9+G11+G13+G15+G16+G18 -> 28721.274 | H20: =H9+H11+H13+H15+H16+H18 -> 29841.65 | I20: =I9+I11+I13+I15+I16+I18 -> 30617.904 | J20: =J9+J11+J13+J15+J16+J18 -> 30912.25 | ... L20: =L9+L11+L13+L15+L16+L18 -> 32711.123 | N20: =N9+N11+N13+N15+N16+N18 -> 31412.816
A21: 经营性流动负债
A22: 应付票据及应付账款 | C22: =C24+C25 -> 11601.425 | D22: =D24+D25 -> 14019.216 | E22: =E24+E25 -> 14566.488 | F22: =F24+F25 -> 14506.032 | G22: =G24+G25 -> 12627.496 | H22: =H7*H23/365 -> 13713.177 | I22: =I7*I23/365 -> 14681.969 | J22: =J7*J23/365 -> 15518.85 | K22: =K7*K23/365 -> 16296.984 | L22: =L7*L23/365 -> 17119.146 | N22: =N24+N25 -> 13548.851
A23: 周转天数 | C23: =C22/C7*365 -> 205.50889 | D23: =D22/D7*365 -> 212.08943 | E23: =E22/E7*365 -> 215.00895 | F23: =F22/F7*365 -> 235.50153 | G23: =G22/G7*365 -> 234.42258 | H23: =假设!H196 -> 230 | I23: =假设!I196 -> 230 | J23: =假设!J196 -> 230 | K23: =假设!K196 -> 230 | L23: =假设!L196 -> 230
A24: 其中：应付票据 | C24: =历史报表!E76 -> 5945.8226 | D24: =历史报表!F76 -> 7526.9418 | E24: =历史报表!G76 -> 7752.2333 | F24: =历史报表!H76 -> 8512.7803 | G24: =历史报表!I76 -> 6071.3562 | H24: =H22*H26 -> 6582.3251 | I24: =I22*I26 -> 7047.3449 | J24: =J22*J26 -> 7449.0482 | K24: =K22*K26 -> 7822.5525 | L24: =L22*L26 -> 8217.1901 | N24: =历史报表!K76 -> 7293.6379
A25: 其中：应付账款 | C25: =历史报表!E77 -> 5655.6024 | D25: =历史报表!F77 -> 6492.2746 | E25: =历史报表!G77 -> 6814.2548 | F25: =历史报表!H77 -> 5993.2517 | G25: =历史报表!I77 -> 6556.1394 | H25: =H22-H24 -> 7130.8522 | I25: =I22-I24 -> 7634.6237 | J25: =J22-J24 -> 8069.8022 | K25: =K22-K24 -> 8474.4319 | L25: =L22-L24 -> 8901.9559 | N25: =历史报表!K77 -> 6255.2128
A26: 应付票据占比 | C26: =C24/C22 -> 0.51250795 | D26: =D24/D22 -> 0.53690175 | E26: =E24/E22 -> 0.53219645 | F26: =F24/F22 -> 0.58684417 | G26: =G24/G22 -> 0.48080446 | H26: =假设!H200 -> 0.48 | I26: =假设!I200 -> 0.48 | J26: =假设!J200 -> 0.48 | K26: =假设!K200 -> 0.48 | L26: =假设!L200 -> 0.48
A27: 合同负债及预收款项 | C27: =历史报表!E79+历史报表!E78 -> 3168.6748 | D27: =历史报表!F79+历史报表!F78 -> 1320.7421 | E27: =历史报表!G79+历史报表!G78 -> 1337.322 | F27: =历史报表!H79+历史报表!H78 -> 776.1394 | G27: =历史报表!I79+历史报表!I78 -> 977.6682 | H27: =H6*H28 -> 1074.9771 | I27: =I6*I28 -> 1146.7806 | J27: =J6*J28 -> 1203.8625 | K27: =K6*K28 -> 1264.4106 | L27: =L6*L28 -> 1324.6154 | N27: =历史报表!K79+历史报表!K78 -> 1107.5807 | O27: 2021年31.7亿→2025年9.8亿，预收订单显著减少
A28: 占比 | C28: =C27/C6 -> 0.12041334 | D28: =D27/D6 -> 0.042717771 | E28: =E27/E6 -> 0.042959855 | F28: =F27/F6 -> 0.027186381 | G28: =G27/G6 -> 0.039234547 | H28: =假设!H204 -> 0.039 | I28: =假设!I204 -> 0.039 | J28: =假设!J204 -> 0.039 | K28: =假设!K204 -> 0.039 | L28: =假设!L204 -> 0.039
A29: 应付职工薪酬 | C29: =历史报表!E80 -> 235.4881 | D29: =历史报表!F80 -> 231.3288 | E29: =历史报表!G80 -> 283.6855 | F29: =历史报表!H80 -> 256.2975 | G29: =历史报表!I80 -> 270.1812 | H29: =H6*H30 -> 303.19868 | I29: =I6*I30 -> 323.45095 | J29: =J6*J30 -> 339.55096 | K29: =K6*K30 -> 356.62864 | L29: =L6*L30 -> 373.60946 | N29: =历史报表!K80 -> 183.8769
A30: 占比 | C30: =C29/C6 -> 0.008948823 | D30: =D29/D6 -> 0.0074820442 | E30: =E29/E6 -> 0.0091130543 | F30: =F29/F6 -> 0.008977513 | G30: =G29/G6 -> 0.010842571 | H30: =假设!H208 -> 0.011 | I30: =假设!I208 -> 0.011 | J30: =假设!J208 -> 0.011 | K30: =假设!K208 -> 0.011 | L30: =假设!L208 -> 0.011
A31: 应交税费 | C31: =历史报表!E81 -> 244.7092 | D31: =历史报表!F81 -> 524.5033 | E31: =历史报表!G81 -> 905.9197 | F31: =历史报表!H81 -> 754.1246 | G31: =历史报表!I81 -> 402.134 | H31: =H6*H32 -> 441.01626 | I31: =I6*I32 -> 470.47411 | J31: =J6*J32 -> 493.8923 | K31: =K6*K32 -> 518.73257 | L31: =L6*L32 -> 543.43194 | N31: =历史报表!K81 -> 248.2249
A32: 占比 | C32: =C31/C6 -> 0.0092992355 | D32: =D31/D6 -> 0.016964411 | E32: =E31/E6 -> 0.029101577 | F32: =F31/F6 -> 0.026415253 | G32: =G31/G6 -> 0.016137934 | H32: =假设!H212 -> 0.016 | I32: =假设!I212 -> 0.016 | J32: =假设!J212 -> 0.016 | K32: =假设!K212 -> 0.016 | L32: =假设!L212 -> 0.016
A33: 其他应付款（含应付股利/利息） | C33: =历史报表!E82 -> 1700.9199 | D33: =历史报表!F82 -> 2131.7705 | E33: =历史报表!G82 -> 2036.3337 | F33: =历史报表!H82 -> 1765.2361 | G33: =历史报表!I82 -> 1304.7764 | H33: =H6*H34 -> 1378.1758 | I33: =I6*I34 -> 1470.2316 | J33: =J6*J34 -> 1543.4135 | K33: =K6*K34 -> 1621.0393 | L33: =L6*L34 -> 1698.2248 | N33: =历史报表!K82 -> 1579.4903
A34: 占比 | C34: =C33/C6 -> 0.064636944 | D34: =D33/D6 -> 0.068949483 | E34: =E33/E6 -> 0.065414762 | F34: =F33/F6 -> 0.061832168 | G34: =G33/G6 -> 0.052361641 | H34: =假设!H216 -> 0.05 | I34: =假设!I216 -> 0.05 | J34: =假设!J216 -> 0.05 | K34: =假设!K216 -> 0.05 | L34: =假设!L216 -> 0.05
A35: 其他流动负债（轧差） | C35: =历史报表!E88-历史报表!E73-历史报表!E74-C22-C27-C29-C31-C33-历史报表!E86 -> 458.7291 | D35: =历史报表!F88-历史报表!F73-历史报表!F74-D22-D27-D29-D31-D33-历史报表!F86 -> 269.3734 | E35: =历史报表!G88-历史报表!G73-历史报表!G74-E22-E27-E29-E31-E33-历史报表!G86 -> 246.4759 | F35: =历史报表!H88-历史报表!H73-历史报表!H74-F22-F27-F29-F31-F33-历史报表!H86 -> 186.5249 | G35: =历史报表!I88-历史报表!I73-历史报表!I74-G22-G27-G29-G31-G33-历史报表!I86 -> 159.7008 | H35: =H6*H36 -> 179.16286 | I35: =I6*I36 -> 191.13011 | J35: =J6*J36 -> 200.64375 | K35: =K6*K36 -> 210.73511 | L35: =L6*L36 -> 220.76923 | N35: =历史报表!K88-历史报表!K73-历史报表!K74-N22-N27-N29-N31-N33-历史报表!K86 -> 142.5412
A36: 占比 | C36: =C35/C6 -> 0.017432242 | D36: =D35/D6 -> 0.0087125498 | E36: =E35/E6 -> 0.0079177408 | F36: =F35/F6 -> 0.006533539 | G36: =G35/G6 -> 0.0064089111 | H36: =假设!H220 -> 0.0065 | I36: =假设!I220 -> 0.0065 | J36: =假设!J220 -> 0.0065 | K36: =假设!K220 -> 0.0065 | L36: =假设!L220 -> 0.0065
A37: 交易性金融负债 | C37: =历史报表!E74 -> 0 | D37: =历史报表!F74 -> 0 | E37: =历史报表!G74 -> 0 | F37: =历史报表!H74 -> 0 | G37: =历史报表!I74 -> 18.9335 | H37: =G37 -> 18.9335 | I37: =H37 -> 18.9335 | J37: =I37 -> 18.9335 | K37: =J37 -> 18.9335 | L37: =K37 -> 18.9335 | N37: =历史报表!K74 -> 18.9335
A38: 经营性流动负债合计 | C38: =C22+C27+C29+C31+C33+C35+C37 -> 17409.946 | D38: =D22+D27+D29+D31+D33+D35+D37 -> 18496.934 | E38: =E22+E27+E29+E31+E33+E35+E37 -> 19376.225 | F38: =F22+F27+F29+F31+F33+F35+F37 -> 18244.355 | G38: =G22+G27+G29+G31+G33+G35+G37 -> 15760.89 | H38: =H22+H27+H29+H31+H33+H35+H37 -> 17108.642 | I38: =I22+I27+I29+I31+I33+I35+I37 -> 18302.97 | J38: =J22+J27+J29+J31+J33+J35+J37 -> 19319.147 | ... L38: =L22+L27+L29+L31+L33+L35+L37 -> 21298.73 | N38: =N22+N27+N29+N31+N33+N35+N37 -> 16829.498
A39: 净营运资本
A40: 净营运资本 | C40: =C20-C38 -> 3775.0902 | D40: =D20-D38 -> 5308.2678 | E40: =E20-E38 -> 6717.677 | F40: =F20-F38 -> 10123.321 | G40: =G20-G38 -> 12960.384 | H40: =H20-H38 -> 12733.008 | I40: =I20-I38 -> 12314.935 | J40: =J20-J38 -> 11593.103 | ... L40: =L20-L38 -> 11412.393 | N40: =N20-N38 -> 14583.317
A41: 净营运资本增加（现金流出为正） | D41: =D40-C40 -> 1533.1776 | E41: =E40-D40 -> 1409.4092 | F41: =F40-E40 -> 3405.6442 | G41: =G40-F40 -> 2837.0629 | H41: =H40-G40 -> -227.3757 | I41: =I40-H40 -> -418.07369 | J41: =J40-I40 -> -721.83196 | K41: =K40-J40 -> -232.51467 | L41: =L40-K40 -> 51.804598 | N41: =N40-G40 -> 1622.9334 | O41: 2026H1A为较2025年末变动
A42: 净营运资本/收入 | C42: =C40/C6 -> 0.14345784 | D42: =D40/D6 -> 0.17168936 | E42: =E40/E6 -> 0.21579727 | F42: =F40/F6 -> 0.3545967 | G42: =G40/G6 -> 0.52010979 | H42: =H40/H6 -> 0.46195153 | I42: =I40/I6 -> 0.41880935 | J42: =J40/J6 -> 0.37556699 | ... L42: =L40/L6 -> 0.33600948
A43: 现金转换周期（应收+存货−应付天数） | C43: =C12+C17-C23 -> 111.73205 | D43: =D12+D17-D23 -> 86.247272 | E43: =E12+E17-E23 -> 73.978134 | F43: =F12+F17-F23 -> 111.06771 | G43: =G12+G17-G23 -> 178.84539 | H43: =H12+H17-H23 -> 155 | I43: =I12+I17-I23 -> 140 | J43: =J12+J17-J23 -> 125 | ... L43: =L12+L17-L23 -> 110

Sheet 融资
A1: 融资、股本与股东回报（百万元）
A2: 短期借款为平衡项：期末现金低于“最低现金”时增借，高于时偿还（不低于下限）；利息按期初余额计提，避免循环引用
A5: 项目 | B5: 百万元 | C5: 2021A | D5: 2022A | E5: 2023A | F5: 2024A | G5: 2025A | H5: 2026E | I5: 2027E | J5: 2028E | K5: 2029E | L5: 2030E | N5: 2026H1A | O5: 说明 / 来源
A6: 现金
A7: 现金及现金等价物（现金流量表口径） | C7: =历史报表!E145 -> 4533.5814 | D7: =历史报表!F145 -> 4085.1596 | E7: =历史报表!G145 -> 4848.3305 | F7: =历史报表!H145 -> 4810.2668 | G7: =历史报表!I145 -> 6364.4738 | H7: =现金流量表!H36 -> 4500 | I7: =现金流量表!I36 -> 4625.0356 | J7: =现金流量表!J36 -> 5001.4198 | K7: =现金流量表!K36 -> 5650.2721 | L7: =现金流量表!L36 -> 6388.1162 | N7: =历史报表!K145 -> 4816.5155
A8: 受限货币资金 | C8: =历史报表!E42-历史报表!E145 -> 188.7475 | D8: =历史报表!F42-历史报表!F145 -> 303.8136 | E8: =历史报表!G42-历史报表!G145 -> 359.3982 | F8: =历史报表!H42-历史报表!H145 -> 433.4901 | G8: =历史报表!I42-历史报表!I145 -> 122.0201 | H8: =G8 -> 122.0201 | I8: =H8 -> 122.0201 | J8: =I8 -> 122.0201 | K8: =J8 -> 122.0201 | L8: =K8 -> 122.0201 | N8: =历史报表!K42-历史报表!K145 -> 148.6104 | O8: 主要为保证金质押
A9: 货币资金（资产负债表） | C9: =历史报表!E42 -> 4722.3289 | D9: =历史报表!F42 -> 4388.9732 | E9: =历史报表!G42 -> 5207.7287 | F9: =历史报表!H42 -> 5243.7569 | G9: =历史报表!I42 -> 6486.4939 | H9: =H7+H8 -> 4622.0201 | I9: =I7+I8 -> 4747.0557 | J9: =J7+J8 -> 5123.4399 | K9: =K7+K8 -> 5772.2922 | L9: =L7+L8 -> 6510.1363 | N9: =历史报表!K42 -> 4965.1259
A10: 有息负债
A11: 短期借款—期初 | H11: =G12 -> 6930.4263 | I11: =H12 -> 5561.1521 | J11: =I12 -> 3000 | K11: =J12 -> 3000 | L11: =K12 -> 3000
A12: 短期借款—期末（平衡项） | C12: =历史报表!E73 -> 288.5518 | D12: =历史报表!F73 -> 638.6606 | E12: =历史报表!G73 -> 2026.2359 | F12: =历史报表!H73 -> 5079.8579 | G12: =历史报表!I73 -> 6930.4263 | H12: =MAX(假设!$C$35,H11+假设!$C$34-现金流量表!H27) -> 5561.1521 | I12: =MAX(假设!$C$35,I11+假设!$C$34-现金流量表!I27) -> 3000 | J12: =MAX(假设!$C$35,J11+假设!$C$34-现金流量表!J27) -> 3000 | K12: =MAX(假设!$C$35,K11+假设!$C$34-现金流量表!K27) -> 3000 | L12: =MAX(假设!$C$35,L11+假设!$C$34-现金流量表!L27) -> 3000 | N12: =历史报表!K73 -> 7776.7969
A13: 长期借款合计（含一年内到期） | C13: =历史报表!E89+历史报表!E86 -> 2471.9005 | D13: =历史报表!F89+历史报表!F86 -> 2569.3013 | E13: =历史报表!G89+历史报表!G86 -> 2079.0444 | F13: 2075.71 | G13: 4703.75 | H13: =假设!H225 -> 4700 | I13: =假设!I225 -> 4700 | J13: =假设!J225 -> 4700 | K13: =假设!K225 -> 4700 | L13: =假设!L225 -> 4700 | O13: 2024–2025为附注口径；2021–2023为长期借款+一年内到期非流动负债（近似）
A14: 长期借款（非流动） | C14: =历史报表!E89 -> 2455.8 | D14: =历史报表!F89 -> 1672.1 | E14: =历史报表!G89 -> 717.2 | F14: =历史报表!H89 -> 1937.29 | G14: =历史报表!I89 -> 4239.3389 | H14: =H13*(1-假设!$C$36) -> 4230 | I14: =I13*(1-假设!$C$36) -> 4230 | J14: =J13*(1-假设!$C$36) -> 4230 | K14: =K13*(1-假设!$C$36) -> 4230 | L14: =L13*(1-假设!$C$36) -> 4230 | N14: =历史报表!K89 -> 1781.3981
A15: 一年内到期的非流动负债 | C15: =历史报表!E86 -> 16.1005 | D15: =历史报表!F86 -> 897.2013 | E15: =历史报表!G86 -> 1361.8444 | F15: =历史报表!H86 -> 3162.1433 | G15: =历史报表!I86 -> 524.3707 | H15: =H13*假设!$C$36+假设!$C$37 -> 529.95874 | I15: =I13*假设!$C$36+假设!$C$37 -> 529.95874 | J15: =J13*假设!$C$36+假设!$C$37 -> 529.95874 | K15: =K13*假设!$C$36+假设!$C$37 -> 529.95874 | L15: =L13*假设!$C$36+假设!$C$37 -> 529.95874 | N15: =历史报表!K86 -> 2996.6449 | O15: 2024年末含烽火转债29.6亿（2025年12月到期，大部分转股）
A16: 应付债券（烽火转债） | C16: =历史报表!E90 -> 2598.1583 | D16: =历史报表!F90 -> 2722.4942 | E16: =历史报表!G90 -> 2843.957 | F16: =历史报表!H90 -> 0 | G16: =历史报表!I90 -> 0 | H16: 0 | I16: 0 | J16: 0 | K16: 0 | L16: 0 | N16: =历史报表!K90 -> 0
A17: 租赁负债（非流动） | C17: =历史报表!E91 -> 72.0342 | D17: =历史报表!F91 -> 84.52 | E17: =历史报表!G91 -> 49.6756 | F17: =历史报表!H91 -> 99.1721 | G17: =历史报表!I91 -> 39.9403 | H17: =G17 -> 39.9403 | I17: =H17 -> 39.9403 | J17: =I17 -> 39.9403 | K17: =J17 -> 39.9403 | L17: =K17 -> 39.9403 | N17: =历史报表!K91 -> 16.7409
A18: 有息负债合计 | C18: =C12+C14+C15+C16+C17 -> 5430.6448 | D18: =D12+D14+D15+D16+D17 -> 6014.9761 | E18: =E12+E14+E15+E16+E17 -> 6998.9129 | F18: =F12+F14+F15+F16+F17 -> 10278.463 | G18: =G12+G14+G15+G16+G17 -> 11734.076 | H18: =H12+H14+H15+H16+H17 -> 10361.051 | I18: =I12+I14+I15+I16+I17 -> 7799.899 | J18: =J12+J14+J15+J16+J17 -> 7799.899 | ... L18: =L12+L14+L15+L16+L17 -> 7799.899 | N18: =N12+N14+N15+N16+N17 -> 12571.581
A19: 净负债（有息负债−货币资金） | C19: =C18-C9 -> 708.3159 | D19: =D18-D9 -> 1626.0029 | E19: =E18-E9 -> 1791.1842 | F19: =F18-F9 -> 5034.7064 | G19: =G18-G9 -> 5247.5823 | H19: =H18-H9 -> 5739.031 | I19: =I18-I9 -> 3052.8433 | J19: =J18-J9 -> 2676.4591 | ... L19: =L18-L9 -> 1289.7627 | N19: =N18-N9 -> 7606.4549
A20: 财务费用
A21: 计息借款期初余额（短借+长借合计+债券） | H21: =G12+G13+G16 -> 11634.176 | I21: =H12+H13+H16 -> 10261.152 | J21: =I12+I13+I16 -> 7700 | K21: =J12+J13+J16 -> 7700 | L21: =K12+K13+K16 -> 7700
A22: 利息支出 | C22: =历史报表!E16 -> 215.601 | D22: =历史报表!F16 -> 313.6005 | E22: =历史报表!G16 -> 338.3448 | F22: =历史报表!H16 -> 460.6155 | G22: =历史报表!I16 -> 327.7565 | H22: =H21*H23 -> 314.12276 | I22: =I21*I23 -> 277.05111 | J22: =J21*J23 -> 207.9 | K22: =K21*K23 -> 207.9 | L22: =L21*L23 -> 207.9 | N22: =历史报表!K16 -> 149.8608 | O22: 2024年含可转债利息调整（实际利率法）
A23: 借款利率 | D23: =D22/AVERAGE(C18,D18) -> 0.054798338 | E23: =E22/AVERAGE(D18,E18) -> 0.051997493 | F23: =F22/AVERAGE(E18,F18) -> 0.053320075 | G23: =G22/AVERAGE(F18,G18) -> 0.029779072 | H23: =假设!H229 -> 0.027 | I23: =假设!I229 -> 0.027 | J23: =假设!J229 -> 0.027 | K23: =假设!K229 -> 0.027 | L23: =假设!L229 -> 0.027 | O23: 历史=利息支出/平均有息负债
A24: 利息收入 | C24: =历史报表!E17 -> 31.8052 | D24: =历史报表!F17 -> 45.4798 | E24: =历史报表!G17 -> 42.8973 | F24: =历史报表!H17 -> 46.4411 | G24: =历史报表!I17 -> 41.9207 | H24: =G7*H25 -> 44.551317 | I24: =H7*I25 -> 31.5 | J24: =I7*J25 -> 32.375249 | K24: =J7*K25 -> 35.009939 | L24: =K7*L25 -> 39.551904 | N24: =历史报表!K17 -> 17.8741
A25: 存款收益率 | D25: =D24/AVERAGE(C9,D9) -> 0.0099831615 | E25: =E24/AVERAGE(D9,E9) -> 0.0089400089 | F25: =F24/AVERAGE(E9,F9) -> 0.0088869854 | G25: =G24/AVERAGE(F9,G9) -> 0.0071474516 | H25: =假设!H233 -> 0.007 | I25: =假设!I233 -> 0.007 | J25: =假设!J233 -> 0.007 | K25: =假设!K233 -> 0.007 | L25: =假设!L233 -> 0.007
A26: 汇兑损益及手续费等 | C26: =历史报表!E15-C22+C24 -> 181.4787 | D26: =历史报表!F15-D22+D24 -> 114.4138 | E26: =历史报表!G15-E22+E24 -> 20.1453 | F26: =历史报表!H15-F22+F24 -> 143.4701 | G26: =历史报表!I15-G22+G24 -> 138.3653 | H26: =假设!H237 -> 300 | I26: =假设!I237 -> 100 | J26: =假设!J237 -> 100 | K26: =假设!K237 -> 100 | L26: =假设!L237 -> 100 | N26: =历史报表!K15-N22+N24 -> 243.6936
A27: 财务费用合计 | C27: =C22-C24+C26 -> 365.2745 | D27: =D22-D24+D26 -> 382.5345 | E27: =E22-E24+E26 -> 315.5928 | F27: =F22-F24+F26 -> 557.6445 | G27: =G22-G24+G26 -> 424.2011 | H27: =H22-H24+H26 -> 569.57144 | I27: =I22-I24+I26 -> 345.55111 | J27: =J22-J24+J26 -> 275.52475 | ... L27: =L22-L24+L26 -> 268.3481 | N27: =N22-N24+N26 -> 375.6803
A28: 股本与股权融资（百万股/百万元）
A29: 期初股本（百万股） | C29: 1170.154 | D29: =C35 -> 1187.8277 | E29: =D35 -> 1186.5645 | F29: =E35 -> 1185.4913 | G29: =F35 -> 1184.4645 | H29: =G35 -> 1358.1675 | I29: =H35 -> 1358.1675 | J29: =I35 -> 1455.2605 | K29: =J35 -> 1455.2605 | L29: =K35 -> 1455.2605
A30: 定增募资总额 | G30: 1100 | H30: =假设!H249 -> 0 | I30: =假设!I249 -> 2912.79 | J30: =假设!J249 -> 0 | K30: =假设!K249 -> 0 | L30: =假设!L249 -> 0 | O30: 2025A：向中国信科定增8,654.6万股@12.71元
A31: 定增募资净额 | G31: 1093.1 | H31: =H30*(1-假设!$C$41) -> 0 | I31: =I30*(1-假设!$C$41) -> 2880.7493 | J31: =J30*(1-假设!$C$41) -> 0 | K31: =K30*(1-假设!$C$41) -> 0 | L31: =L30*(1-假设!$C$41) -> 0
A32: + 新增股份（定增/可转债转股等） | C32: =C35-C29+C34 -> 17.6737 | D32: =D35-D29+D34 -> -1.2632 | E32: =E35-E29+E34 -> -1.0732 | F32: =F35-F29+F34 -> -1.0268 | G32: =G35-G29+G34 -> 176.803 | H32: =H30/假设!$C$40 -> 0 | I32: =I30/假设!$C$40 -> 97.093 | J32: =J30/假设!$C$40 -> 0 | K32: =K30/假设!$C$40 -> 0 | L32: =L30/假设!$C$40 -> 0 | O32: 2025A含可转债转股9,089万股+定增8,655万股
A33: 股份回购金额 | C33: 0 | D33: 0 | E33: 0 | F33: 0 | G33: 75 | H33: =假设!H245 -> 0 | I33: =假设!I245 -> 0 | J33: =假设!J245 -> 0 | K33: =假设!K245 -> 0 | L33: =假设!L245 -> 0 | O33: 2025年回购309.97万股并注销
A34: − 回购注销股份 | C34: 0 | D34: 0 | E34: 0 | F34: 0 | G34: 3.1 | H34: =H33/假设!$C$8 -> 0 | I34: =I33/假设!$C$8 -> 0 | J34: =J33/假设!$C$8 -> 0 | K34: =K33/假设!$C$8 -> 0 | L34: =L33/假设!$C$8 -> 0
A35: 期末股本（百万股） | C35: =历史报表!E97 -> 1187.8277 | D35: =历史报表!F97 -> 1186.5645 | E35: =历史报表!G97 -> 1185.4913 | F35: =历史报表!H97 -> 1184.4645 | G35: =历史报表!I97 -> 1358.1675 | H35: =H29+H32-H34 -> 1358.1675 | I35: =I29+I32-I34 -> 1455.2605 | J35: =J29+J32-J34 -> 1455.2605 | K35: =K29+K32-K34 -> 1455.2605 | L35: =L29+L32-L34 -> 1455.2605 | N35: =历史报表!K97 -> 1358.1675
A36: 加权平均股本（简化：期初期末平均） | C36: =AVERAGE(C29,C35) -> 1178.9908 | D36: =AVERAGE(D29,D35) -> 1187.1961 | E36: =AVERAGE(E29,E35) -> 1186.0279 | F36: =AVERAGE(F29,F35) -> 1184.9779 | G36: =AVERAGE(G29,G35) -> 1271.316 | H36: =AVERAGE(H29,H35) -> 1358.1675 | I36: =AVERAGE(I29,I35) -> 1406.714 | J36: =AVERAGE(J29,J35) -> 1455.2605 | ... L36: =AVERAGE(L29,L35) -> 1455.2605
A37: 分红
A38: 归属本年度的现金分红（次年派发） | C38: 95.03 | D38: 130.52 | E38: 151.74 | F38: 212.02 | G38: 131.74 | H38: =利润表!H29*假设!H241 -> 225.58085 | I38: =利润表!I29*假设!I241 -> 322.75715 | J38: =利润表!J29*假设!J241 -> 345.99813 | K38: =利润表!K29*假设!K241 -> 380.88505 | L38: =利润表!L29*假设!L241 -> 399.58935 | O38: 历史为年报利润分配方案；2021年=每股0.08元×期末股本
A39: 分红率 | C39: =C38/利润表!C29 -> 0.32999335 | D39: =D38/利润表!D29 -> 0.32164158 | E39: =E38/利润表!E29 -> 0.30025698 | F39: =F38/利润表!F29 -> 0.30171927 | G39: =G38/利润表!G29 -> 0.30227084 | H39: =假设!H241 -> 0.3 | I39: =假设!I241 -> 0.3 | J39: =假设!J241 -> 0.3 | K39: =假设!K241 -> 0.3 | L39: =假设!L241 -> 0.3
A40: 每股股利（元） | C40: 0.08 | D40: 0.11 | E40: 0.128 | F40: 0.179 | G40: 0.097 | H40: =H38/H35 -> 0.16609207 | I40: =I38/I35 -> 0.22178651 | J40: =J38/J35 -> 0.23775683 | K40: =K38/K35 -> 0.26172981 | L40: =L38/L35 -> 0.2745827
A41: 本年支付的现金分红 | D41: =C38 -> 95.03 | E41: =D38 -> 130.52 | F41: =E38 -> 151.74 | G41: =F38 -> 212.02 | H41: =G38 -> 131.74 | I41: =H38 -> 225.58085 | J41: =I38 -> 322.75715 | K41: =J38 -> 345.99813 | L41: =K38 -> 380.88505
A42: 少数股东权益
A43: 期初 | C43: 602.0284 | D43: =C47 -> 858.608 | E43: =D47 -> 1389.5164 | F43: =E47 -> 1741.8913 | G43: =F47 -> 1719.5595 | H43: =G47 -> 1573.3797 | I43: =H47 -> 1538.3797 | J43: =I47 -> 1518.3797 | K43: =J47 -> 1508.3797 | L43: =K47 -> 1503.3797
A44: + 少数股东损益 | C44: =利润表!C28 -> 67.6577 | D44: =利润表!D28 -> 3.4306 | E44: =利润表!E28 -> -16.5807 | F44: =利润表!F28 -> 7.4939 | G44: =利润表!G28 -> -59.785 | H44: =利润表!H28 -> -15 | I44: =利润表!I28 -> 0 | J44: =利润表!J28 -> 10 | ... L44: =利润表!L28 -> 20
A45: − 向少数股东分红 | C45: =历史报表!E138 -> 12.6649 | D45: =历史报表!F138 -> 0 | E45: =历史报表!G138 -> 0.2215 | F45: =历史报表!H138 -> 2.9198 | G45: =历史报表!I138 -> 21.775 | H45: =假设!H253 -> 20 | I45: =假设!I253 -> 20 | J45: =假设!J253 -> 20 | K45: =假设!K253 -> 20 | L45: =假设!L253 -> 20
A46: ± 其他（增资/其他综合收益等，轧差） | C46: =C47-C43-C44+C45 -> 201.5868 | D46: =D47-D43-D44+D45 -> 527.4778 | E46: =E47-E43-E44+E45 -> 369.1771 | F46: =F47-F43-F44+F45 -> -26.9059 | G46: =G47-G43-G44+G45 -> -64.6198 | H46: 0 | I46: 0 | J46: 0 | K46: 0 | L46: 0
A47: 期末 | C47: =历史报表!E106 -> 858.608 | D47: =历史报表!F106 -> 1389.5164 | E47: =历史报表!G106 -> 1741.8913 | F47: =历史报表!H106 -> 1719.5595 | G47: =历史报表!I106 -> 1573.3797 | H47: =H43+H44-H45+H46 -> 1538.3797 | I47: =I43+I44-I45+I46 -> 1518.3797 | J47: =J43+J44-J45+J46 -> 1508.3797 | K47: =K43+K44-K45+K46 -> 1503.3797 | L47: =L43+L44-L45+L46 -> 1503.3797
A48: 偿债指标
A49: 净负债/EBITDA | C49: =C19/利润表!C38 -> 0.62039604 | D49: =D19/利润表!D38 -> 1.2053706 | E49: =E19/利润表!E38 -> 1.1460816 | F49: =F19/利润表!F38 -> 2.4009499 | G49: =G19/利润表!G38 -> 3.3742719 | H49: =H19/利润表!H38 -> 2.829681 | I49: =I19/利润表!I38 -> 1.3106883 | J49: =J19/利润表!J38 -> 1.0691994 | ... L49: =L19/利润表!L38 -> 0.43591938
A50: 有息负债/总资产 | C50: =C18/资产负债表!C28 -> 0.15135441 | D50: =D18/资产负债表!D28 -> 0.15604695 | E50: =E18/资产负债表!E28 -> 0.16690471 | F50: =F18/资产负债表!F28 -> 0.22964815 | G50: =G18/资产负债表!G28 -> 0.24869824 | H50: =H18/资产负债表!H28 -> 0.21702215 | I50: =I18/资产负债表!I28 -> 0.15572979 | J50: =J18/资产负债表!J28 -> 0.15022092 | ... L50: =L18/资产负债表!L28 -> 0.13985297
A51: 资产负债率 | C51: =资产负债表!C47/资产负债表!C28 -> 0.64905292 | D51: =资产负债表!D47/资产负债表!D28 -> 0.64920446 | E51: =资产负债表!E47/资产负债表!E28 -> 0.64432553 | F51: =资产负债表!F47/资产负债表!F28 -> 0.64988251 | G51: =资产负债表!G47/资产负债表!G28 -> 0.59494461 | H51: =资产负债表!H47/资产负债表!H28 -> 0.58743764 | I51: =资产负债表!I47/资产负债表!I28 -> 0.53265406 | J51: =资产负债表!J47/资产负债表!J28 -> 0.53338257 | ... L51: =资产负债表!L47/资产负债表!L28 -> 0.5320637
A52: 利息保障倍数（EBIT/利息支出） | C52: =利润表!C37/C22 -> 2.0955529 | D52: =利润表!D37/D22 -> 1.698099 | E52: =利润表!E37/E22 -> 1.7574025 | F52: =利润表!F37/F22 -> 2.3150068 | G52: =利润表!G37/G22 -> 1.4168662 | H52: =利润表!H37/H22 -> 2.4350176 | I52: =利润表!I37/I22 -> 3.2434519 | J52: =利润表!J37/J22 -> 4.3082607 | ... L52: =利润表!L37/L22 -> 4.9705671

Sheet 利润表
A1: 利润表（百万元）
A2: 历史链接“历史报表”；预测由分业务/费用/融资明细驱动。费用以正数列示，减值损失以负数列示
A5: 项目 | B5: 百万元 | C5: 2021A | D5: 2022A | E5: 2023A | F5: 2024A | G5: 2025A | H5: 2026E | I5: 2027E | J5: 2028E | K5: 2029E | L5: 2030E | N5: 2026H1A | O5: 说明 / 来源
A6: 营业收入 | C6: =历史报表!E8 -> 26314.98 | D6: =历史报表!F8 -> 30917.861 | E6: =历史报表!G8 -> 31129.574 | F6: =历史报表!H8 -> 28548.831 | G6: =历史报表!I8 -> 24918.554 | H6: =分业务!H35 -> 27563.516 | I6: =分业务!I35 -> 29404.632 | J6: =分业务!J35 -> 30868.269 | K6: =分业务!K35 -> 32420.785 | L6: =分业务!L35 -> 33964.496 | N6: =历史报表!K8 -> 12376.358
A7: 营业成本 | C7: =历史报表!E10 -> 20605.046 | D7: =历史报表!F10 -> 24126.68 | E7: =历史报表!G10 -> 24728.125 | F7: =历史报表!H10 -> 22482.664 | G7: =历史报表!I10 -> 19661.228 | H7: =分业务!H37 -> 21762.216 | I7: =分业务!I37 -> 23299.646 | J7: =分业务!J37 -> 24627.741 | K7: =分业务!K37 -> 25862.606 | L7: =分业务!L37 -> 27167.34 | N7: =历史报表!K10 -> 9727.8614
A8: 毛利 | C8: =C6-C7 -> 5709.9348 | D8: =D6-D7 -> 6791.1801 | E8: =E6-E7 -> 6401.449 | F8: =F6-F7 -> 6066.167 | G8: =G6-G7 -> 5257.3262 | H8: =H6-H7 -> 5801.3001 | I8: =I6-I7 -> 6104.9861 | J8: =J6-J7 -> 6240.5282 | ... L8: =L6-L7 -> 6797.1559 | N8: =N6-N7 -> 2648.497
A9: 税金及附加 | C9: =历史报表!E11 -> 88.2078 | D9: =历史报表!F11 -> 102.0822 | E9: =历史报表!G11 -> 109.2552 | F9: =历史报表!H11 -> 116.2267 | G9: =历史报表!I11 -> 109.8429 | H9: =费用!H8 -> 137.81758 | I9: =费用!I8 -> 147.02316 | J9: =费用!J8 -> 154.34135 | K9: =费用!K8 -> 162.10393 | L9: =费用!L8 -> 169.82248 | N9: =历史报表!K11 -> 79.0084
A10: 销售费用 | C10: =历史报表!E12 -> 1417.9454 | D10: =历史报表!F12 -> 1645.9351 | E10: =历史报表!G12 -> 1786.6738 | F10: =历史报表!H12 -> 1881.3582 | G10: =历史报表!I12 -> 1975.6587 | H10: =费用!H10 -> 2094.8272 | I10: =费用!I10 -> 2146.5381 | J10: =费用!J10 -> 2160.7788 | K10: =费用!K10 -> 2204.6134 | L10: =费用!L10 -> 2241.6568 | N10: =历史报表!K12 -> 1061.5176
A11: 管理费用 | C11: =历史报表!E13 -> 294.4026 | D11: =历史报表!F13 -> 328.6322 | E11: =历史报表!G13 -> 341.013 | F11: =历史报表!H13 -> 439.5538 | G11: =历史报表!I13 -> 484.3899 | H11: =费用!H12 -> 523.70681 | I11: =费用!I12 -> 543.98569 | J11: =费用!J12 -> 555.62884 | K11: =费用!K12 -> 583.57414 | L11: =费用!L12 -> 611.36093 | N11: =历史报表!K13 -> 190.1205
A12: 研发费用 | C12: =历史报表!E14 -> 3460.4309 | D12: =历史报表!F14 -> 4101.782 | E12: =历史报表!G14 -> 3578.3312 | F12: =历史报表!H14 -> 2881.2504 | G12: =历史报表!I14 -> 2570.0983 | H12: =费用!H19 -> 2500.5622 | I12: =费用!I19 -> 2604.0742 | J12: =费用!J19 -> 2690.1696 | K12: =费用!K19 -> 2805.0464 | L12: =费用!L19 -> 2944.7218 | N12: =历史报表!K14 -> 1269.9684
A13: 财务费用 | C13: =历史报表!E15 -> 365.2745 | D13: =历史报表!F15 -> 382.5345 | E13: =历史报表!G15 -> 315.5928 | F13: =历史报表!H15 -> 557.6445 | G13: =历史报表!I15 -> 424.2011 | H13: =融资!H27 -> 569.57144 | I13: =融资!I27 -> 345.55111 | J13: =融资!J27 -> 275.52475 | K13: =融资!K27 -> 272.89006 | L13: =融资!L27 -> 268.3481 | N13: =历史报表!K15 -> 375.6803
A14: 其中：利息费用 | C14: =历史报表!E16 -> 215.601 | D14: =历史报表!F16 -> 313.6005 | E14: =历史报表!G16 -> 338.3448 | F14: =历史报表!H16 -> 460.6155 | G14: =历史报表!I16 -> 327.7565 | H14: =融资!H22 -> 314.12276 | I14: =融资!I22 -> 277.05111 | J14: =融资!J22 -> 207.9 | K14: =融资!K22 -> 207.9 | L14: =融资!L22 -> 207.9 | N14: =历史报表!K16 -> 149.8608
A15: 利息收入 | C15: =历史报表!E17 -> 31.8052 | D15: =历史报表!F17 -> 45.4798 | E15: =历史报表!G17 -> 42.8973 | F15: =历史报表!H17 -> 46.4411 | G15: =历史报表!I17 -> 41.9207 | H15: =融资!H24 -> 44.551317 | I15: =融资!I24 -> 31.5 | J15: =融资!J24 -> 32.375249 | K15: =融资!K24 -> 35.009939 | L15: =融资!L24 -> 39.551904 | N15: =历史报表!K17 -> 17.8741
A16: 加：其他收益 | C16: =历史报表!E18 -> 260.0848 | D16: =历史报表!F18 -> 275.016 | E16: =历史报表!G18 -> 447.9878 | F16: =历史报表!H18 -> 771.2192 | G16: =历史报表!I18 -> 722.6505 | H16: =费用!H22 -> 606.39736 | I16: =费用!I22 -> 588.09264 | J16: =费用!J22 -> 586.49711 | K16: =费用!K22 -> 583.57414 | L16: =费用!L22 -> 611.36093 | N16: =历史报表!K18 -> 219.0644
A17: 投资收益 | C17: =历史报表!E19 -> 402.5676 | D17: =历史报表!F19 -> 389.6458 | E17: =历史报表!G19 -> 301.8478 | F17: =历史报表!H19 -> 287.7853 | G17: =历史报表!I19 -> 445.1525 | H17: =费用!H38 -> 661.73008 | I17: =费用!I38 -> 693.56658 | J17: =费用!J38 -> 726.99491 | K17: =费用!K38 -> 762.09466 | L17: =费用!L38 -> 798.94939 | N17: =历史报表!K19 -> 388.9358
A18: 其中：对联营企业的投资收益 | C18: =历史报表!E20 -> 402.1722 | D18: =历史报表!F20 -> 378.8812 | E18: =历史报表!G20 -> 325.9203 | F18: =历史报表!H20 -> 285.6265 | G18: =历史报表!I20 -> 442.3 | H18: =费用!H35 -> 686.73008 | I18: =费用!I35 -> 718.56658 | J18: =费用!J35 -> 751.99491 | K18: =费用!K35 -> 787.09466 | L18: =费用!L35 -> 823.94939 | N18: =历史报表!K20 -> 400.0886
A19: 公允价值变动收益 | C19: =历史报表!E22 -> 2.7352 | D19: =历史报表!F22 -> -2.4842 | E19: =历史报表!G22 -> 0.3342 | F19: =历史报表!H22 -> 0.269 | G19: =历史报表!I22 -> -12.6198 | H19: =费用!H39 -> 0 | I19: =费用!I39 -> 0 | J19: =费用!J39 -> 0 | K19: =费用!K39 -> 0 | L19: =费用!L39 -> 0 | N19: =历史报表!K22 -> 0
A20: 信用减值损失 | C20: =历史报表!E24 -> -17.4286 | D20: =历史报表!F24 -> -232.8913 | E20: =历史报表!G24 -> -291.6802 | F20: =历史报表!H24 -> -345.4449 | G20: =历史报表!I24 -> -81.4387 | H20: =费用!H24 -> -192.94461 | I20: =费用!I24 -> -176.42779 | J20: =费用!J24 -> -185.20961 | K20: =费用!K24 -> -194.52471 | L20: =费用!L24 -> -203.78698 | N20: =历史报表!K24 -> 4.1395
A21: 资产减值损失 | C21: =历史报表!E23 -> -239.801 | D21: =历史报表!F23 -> -122.3486 | E21: =历史报表!G23 -> -147.8754 | F21: =历史报表!H23 -> -107.2242 | G21: =历史报表!I23 -> -294.1611 | H21: =费用!H26 -> -192.94461 | I21: =费用!I26 -> -176.42779 | J21: =费用!J26 -> -185.20961 | K21: =费用!K26 -> -194.52471 | L21: =费用!L26 -> -203.78698 | N21: =历史报表!K23 -> -44.045
A22: 资产处置收益 | C22: =历史报表!E25 -> 1.838 | D22: =历史报表!F25 -> 4.1996 | E22: =历史报表!G25 -> -14.9768 | F22: =历史报表!H25 -> 6.6168 | G22: =历史报表!I25 -> 0.4398 | H22: =费用!H40 -> 0 | I22: =费用!I40 -> 0 | J22: =费用!J40 -> 0 | K22: =费用!K40 -> 0 | L22: =费用!L40 -> 0 | N22: =历史报表!K25 -> -0.3458
A23: 营业利润 | C23: =C8-C9-C10-C11-C12-C13+C16+C17+C19+C20+C21+C22 -> 493.6696 | D23: =D8-D9-D10-D11-D12-D13+D16+D17+D19+D20+D21+D22 -> 541.3514 | E23: =E8-E9-E10-E11-E12-E13+E16+E17+E19+E20+E21+E22 -> 566.2204 | F23: =F8-F9-F10-F11-F12-F13+F16+F17+F19+F20+F21+F22 -> 803.3546 | G23: =G8-G9-G10-G11-G12-G13+G16+G17+G19+G20+G21+G22 -> 473.1585 | H23: =H8-H9-H10-H11-H12-H13+H16+H17+H19+H20+H21+H22 -> 857.05308 | I23: =I8-I9-I10-I11-I12-I13+I16+I17+I19+I20+I21+I22 -> 1246.6174 | J23: =J8-J9-J10-J11-J12-J13+J16+J17+J19+J20+J21+J22 -> 1347.1576 | ... L23: =L8-L9-L10-L11-L12-L13+L16+L17+L19+L20+L21+L22 -> 1563.9822 | N23: =N8-N9-N10-N11-N12-N13+N16+N17+N19+N20+N21+N22 -> 239.9507
A24: 营业外收支净额 | C24: =历史报表!E27-历史报表!E28 -> -2.6277 | D24: =历史报表!F27-历史报表!F28 -> -0.9538 | E24: =历史报表!G27-历史报表!G28 -> 15.0161 | F24: =历史报表!H27-历史报表!H28 -> -11.2164 | G24: =历史报表!I27-历史报表!I28 -> -11.1238 | H24: =费用!H41 -> -10 | I24: =费用!I41 -> -10 | J24: =费用!J41 -> -10 | K24: =费用!K41 -> -10 | L24: =费用!L41 -> -10 | N24: =历史报表!K27-历史报表!K28 -> 1.4673
A25: 利润总额 | C25: =C23+C24 -> 491.0419 | D25: =D23+D24 -> 540.3976 | E25: =E23+E24 -> 581.2365 | F25: =F23+F24 -> 792.1382 | G25: =G23+G24 -> 462.0347 | H25: =H23+H24 -> 847.05308 | I25: =I23+I24 -> 1236.6174 | J25: =J23+J24 -> 1337.1576 | ... L25: =L23+L24 -> 1553.9822 | N25: =N23+N24 -> 241.418
A26: 所得税 | C26: =历史报表!E30 -> 135.4087 | D26: =历史报表!F30 -> 131.1737 | E26: =历史报表!G30 -> 92.4501 | F26: =历史报表!H30 -> 81.9381 | G26: =历史报表!I30 -> 85.9854 | H26: =H25*费用!H42 -> 110.1169 | I26: =I25*费用!I42 -> 160.76026 | J26: =J25*费用!J42 -> 173.83048 | K26: =K25*费用!K42 -> 191.95424 | L26: =L25*费用!L42 -> 202.01768 | N26: =历史报表!K30 -> 56.1532
A27: 净利润 | C27: =C25-C26 -> 355.6332 | D27: =D25-D26 -> 409.2239 | E27: =E25-E26 -> 488.7864 | F27: =F25-F26 -> 710.2001 | G27: =G25-G26 -> 376.0493 | H27: =H25-H26 -> 736.93618 | I27: =I25-I26 -> 1075.8572 | J27: =J25-J26 -> 1163.3271 | ... L27: =L25-L26 -> 1351.9645 | N27: =N25-N26 -> 185.2648
A28: 少数股东损益 | C28: =历史报表!E33 -> 67.6577 | D28: =历史报表!F33 -> 3.4306 | E28: =历史报表!G33 -> -16.5807 | F28: =历史报表!H33 -> 7.4939 | G28: =历史报表!I33 -> -59.785 | H28: =假设!H134 -> -15 | I28: =假设!I134 -> 0 | J28: =假设!J134 -> 10 | K28: =假设!K134 -> 15 | L28: =假设!L134 -> 20 | N28: =历史报表!K33 -> -7.5349
A29: 归属于母公司股东的净利润 | C29: =C27-C28 -> 287.9755 | D29: =D27-D28 -> 405.7933 | E29: =E27-E28 -> 505.3671 | F29: =F27-F28 -> 702.7062 | G29: =G27-G28 -> 435.8343 | H29: =H27-H28 -> 751.93618 | I29: =I27-I28 -> 1075.8572 | J29: =J27-J28 -> 1153.3271 | ... L29: =L27-L28 -> 1331.9645 | N29: =N27-N28 -> 192.7997
A30: 核对：归母净利润−报表值 | C30: =C29-历史报表!E34 -> 9.9999999e-05 | D30: =D29-历史报表!F34 -> 1.8189894e-12 | E30: =E29-历史报表!G34 -> -0.0001 | F30: =F29-历史报表!H34 -> 0.0002 | G30: =G29-历史报表!I34 -> -0.0002 | N30: =N29-历史报表!K34 -> -7.1054274e-13 | O30: 应为0
A31: 每股指标（元）
A32: EPS（按加权平均股本） | C32: =C29/融资!C36 -> 0.24425592 | D32: =D29/融资!D36 -> 0.34180815 | E32: =E29/融资!E36 -> 0.42610052 | F32: =F29/融资!F36 -> 0.59301207 | G32: =G29/融资!G36 -> 0.34282138 | H32: =H29/融资!H36 -> 0.55364024 | I32: =I29/融资!I36 -> 0.76480163 | J32: =J29/融资!J36 -> 0.79252277 | ... L32: =L29/融资!L36 -> 0.91527565 | O32: 历史报表基本EPS：2025A 0.36元（按加权股本）
A33: EPS（按期末总股本摊薄） | C33: =C29/融资!C35 -> 0.24243878 | D33: =D29/融资!D35 -> 0.34199009 | E33: =E29/融资!E35 -> 0.42629339 | F33: =F29/融资!F35 -> 0.59326911 | G33: =G29/融资!G35 -> 0.32089878 | H33: =H29/融资!H35 -> 0.55364024 | I33: =I29/融资!I35 -> 0.73928836 | J33: =J29/融资!J35 -> 0.79252277 | ... L33: =L29/融资!L35 -> 0.91527565
A34: DPS | C34: =融资!C40 -> 0.08 | D34: =融资!D40 -> 0.11 | E34: =融资!E40 -> 0.128 | F34: =融资!F40 -> 0.179 | G34: =融资!G40 -> 0.097 | H34: =融资!H40 -> 0.16609207 | I34: =融资!I40 -> 0.22178651 | J34: =融资!J40 -> 0.23775683 | ... L34: =融资!L40 -> 0.2745827
A35: 每股净资产 | C35: =资产负债表!C56/融资!C35 -> 9.8781045 | D35: =资产负债表!D56/融资!D35 -> 10.224667 | E35: =资产负债表!E56/融资!E35 -> 11.111692 | F35: =资产负债表!F56/融资!F35 -> 11.778152 | G35: =资产负债表!G56/融资!G35 -> 12.912941 | H35: =资产负债表!H56/融资!H35 -> 13.369583 | I35: =资产负债表!I56/融资!I35 -> 15.041402 | J35: =资产负债表!J56/融资!J35 -> 15.612139 | ... L35: =资产负债表!L56/融资!L35 -> 16.90036
A36: 利润质量与增长
A37: EBIT（经营口径：营业利润+财务费用−投资收益−公允价值−处置） | C37: =C23+C13-C17-C19-C22 -> 451.8033 | D37: =D23+D13-D17-D19-D22 -> 532.5247 | E37: =E23+E13-E17-E19-E22 -> 594.608 | F37: =F23+F13-F17-F19-F22 -> 1066.328 | G37: =G23+G13-G17-G19-G22 -> 464.3871 | H37: =H23+H13-H17-H19-H22 -> 764.89444 | I37: =I23+I13-I17-I19-I22 -> 898.60194 | J37: =J23+J13-J17-J19-J22 -> 895.68741 | ... L37: =L23+L13-L17-L19-L22 -> 1033.3809 | N37: =N23+N13-N17-N19-N22 -> 227.041
A38: EBITDA | C38: =C37+资本开支折旧!C65 -> 1141.7157 | D38: =D37+资本开支折旧!D65 -> 1348.9651 | E38: =E37+资本开支折旧!E65 -> 1562.8767 | F38: =F37+资本开支折旧!F65 -> 2096.9644 | G38: =G37+资本开支折旧!G65 -> 1555.1747 | H38: =H37+资本开支折旧!H65 -> 2028.1548 | I38: =I37+资本开支折旧!I65 -> 2329.191 | J38: =J37+资本开支折旧!J65 -> 2503.2366 | ... L38: =L37+资本开支折旧!L65 -> 2958.7185 | N38: =N37+资本开支折旧!N65 -> 846.9554
A39: 收入增速 | C39: =分业务!C36 -> 0.24866823 | D39: =分业务!D36 -> 0.17491483 | E39: =分业务!E36 -> 0.0068476148 | F39: =分业务!F36 -> -0.082903267 | G39: =分业务!G36 -> -0.12716024 | H39: =H6/G6-1 -> 0.10614427 | I39: =I6/H6-1 -> 0.066795386 | J39: =J6/I6-1 -> 0.049775731 | K39: =K6/J6-1 -> 0.050294896 | L39: =L6/K6-1 -> 0.047614851
A40: 归母净利润增速 | D40: =D29/C29-1 -> 0.40912439 | E40: =E29/D29-1 -> 0.24538059 | F40: =F29/E29-1 -> 0.39048664 | G40: =G29/F29-1 -> -0.37977735 | H40: =H29/G29-1 -> 0.72527995 | I40: =I29/H29-1 -> 0.43078253 | J40: =J29/I29-1 -> 0.072007641 | K40: =K29/J29-1 -> 0.10082981 | L40: =L29/K29-1 -> 0.049107463
A41: 毛利率 | C41: =C8/C6 -> 0.21698419 | D41: =D8/D6 -> 0.21965233 | E41: =E8/E6 -> 0.20563882 | F41: =F8/F6 -> 0.2124839 | G41: =G8/G6 -> 0.21098038 | H41: =H8/H6 -> 0.21047025 | I41: =I8/I6 -> 0.20761988 | J41: =J8/J6 -> 0.20216644 | ... L41: =L8/L6 -> 0.20012533 | N41: =N8/N6 -> 0.21399647
A42: EBIT利润率 | C42: =C37/C6 -> 0.017169053 | D42: =D37/D6 -> 0.017223853 | E42: =E37/E6 -> 0.019101064 | F42: =F37/F6 -> 0.037351022 | G42: =G37/G6 -> 0.018636197 | H42: =H37/H6 -> 0.027750249 | I42: =I37/I6 -> 0.030559877 | J42: =J37/J6 -> 0.029016444 | ... L42: =L37/L6 -> 0.030425327 | N42: =N37/N6 -> 0.018344734
A43: 归母净利率 | C43: =C29/C6 -> 0.010943405 | D43: =D29/D6 -> 0.013124883 | E43: =E29/E6 -> 0.016234308 | F43: =F29/F6 -> 0.024614185 | G43: =G29/G6 -> 0.017490352 | H43: =H29/H6 -> 0.027280125 | I43: =I29/I6 -> 0.036588016 | J43: =J29/J6 -> 0.037362869 | ... L43: =L29/L6 -> 0.039216377 | N43: =N29/N6 -> 0.015578064
A44: 销售费用率 | C44: =C10/C6 -> 0.053883582 | D44: =D10/D6 -> 0.053235737 | E44: =E10/E6 -> 0.057394739 | F44: =F10/F6 -> 0.065899658 | G44: =G10/G6 -> 0.079284643 | H44: =H10/H6 -> 0.076 | I44: =I10/I6 -> 0.073 | J44: =J10/J6 -> 0.07 | ... L44: =L10/L6 -> 0.066 | N44: =N10/N6 -> 0.085769785
A45: 管理费用率 | C45: =C11/C6 -> 0.011187643 | D45: =D11/D6 -> 0.010629202 | E45: =E11/E6 -> 0.010954631 | F45: =F11/F6 -> 0.01539656 | G45: =G11/G6 -> 0.019438925 | H45: =H11/H6 -> 0.019 | I45: =I11/I6 -> 0.0185 | J45: =J11/J6 -> 0.018 | ... L45: =L11/L6 -> 0.018 | N45: =N11/N6 -> 0.015361586
A46: 研发费用率（费用化） | C46: =C12/C6 -> 0.13150042 | D46: =D12/D6 -> 0.13266707 | E46: =E12/E6 -> 0.11494957 | F46: =F12/F6 -> 0.10092359 | G46: =G12/G6 -> 0.10313994 | H46: =H12/H6 -> 0.09072 | I46: =I12/I6 -> 0.08856 | J46: =J12/J6 -> 0.08715 | ... L46: =L12/L6 -> 0.0867 | N46: =N12/N6 -> 0.10261245
A47: 财务费用率 | C47: =C13/C6 -> 0.013880858 | D47: =D13/D6 -> 0.012372606 | E47: =E13/E6 -> 0.010138038 | F47: =F13/F6 -> 0.019533007 | G47: =G13/G6 -> 0.017023504 | H47: =H13/H6 -> 0.020663962 | I47: =I13/I6 -> 0.011751588 | J47: =J13/J6 -> 0.0089258245 | ... L47: =L13/L6 -> 0.0079008413 | N47: =N13/N6 -> 0.030354672
A48: ROE（归母净利润/平均归母权益） | D48: =D29/AVERAGE(资产负债表!C56,资产负债表!D56) -> 0.034006384 | E48: =E29/AVERAGE(资产负债表!D56,资产负债表!E56) -> 0.03994201 | F48: =F29/AVERAGE(资产负债表!E56,资产负债表!F56) -> 0.05181508 | G48: =G29/AVERAGE(资产负债表!F56,资产负债表!G56) -> 0.027681914 | H48: =H29/AVERAGE(资产负债表!G56,资产负债表!H56) -> 0.042129914 | I48: =I29/AVERAGE(资产负债表!H56,资产负债表!I56) -> 0.053729334 | J48: =J29/AVERAGE(资产负债表!I56,资产负债表!J56) -> 0.0517084 | K48: =K29/AVERAGE(资产负债表!J56,资产负债表!K56) -> 0.054768447 | L48: =L29/AVERAGE(资产负债表!K56,资产负债表!L56) -> 0.055224957
A49: ROIC（EBIT×(1−15%)/(净负债+权益)） | C49: =C37*(1-假设!$C$16)/(融资!C19+资产负债表!C58) -> 0.028873757 | D49: =D37*(1-假设!$C$16)/(融资!D19+资产负债表!D58) -> 0.029882069 | E49: =E37*(1-假设!$C$16)/(融资!E19+资产负债表!E58) -> 0.030253809 | F49: =F37*(1-假设!$C$16)/(融资!F19+资产负债表!F58) -> 0.043775696 | G49: =G37*(1-假设!$C$16)/(融资!G19+资产负债表!G58) -> 0.016204716 | H49: =H37*(1-假设!$C$16)/(融资!H19+资产负债表!H58) -> 0.025561092 | I49: =I37*(1-假设!$C$16)/(融资!I19+资产负债表!I58) -> 0.028866237 | J49: =J37*(1-假设!$C$16)/(融资!J19+资产负债表!J58) -> 0.028297586 | ... L49: =L37*(1-假设!$C$16)/(融资!L19+资产负债表!L58) -> 0.032071987

Sheet 资产负债表
A1: 资产负债表（百万元）
A2: 历史链接“历史报表”（部分科目合并列示，其他项为轧差）；预测由营运资本/资本开支/融资明细驱动
A5: 项目 | B5: 百万元 | C5: 2021A | D5: 2022A | E5: 2023A | F5: 2024A | G5: 2025A | H5: 2026E | I5: 2027E | J5: 2028E | K5: 2029E | L5: 2030E | N5: 2026H1A | O5: 说明 / 来源
A6: 资产
A7: 货币资金 | C7: =融资!C9 -> 4722.3289 | D7: =融资!D9 -> 4388.9732 | E7: =融资!E9 -> 5207.7287 | F7: =融资!F9 -> 5243.7569 | G7: =融资!G9 -> 6486.4939 | H7: =融资!H9 -> 4622.0201 | I7: =融资!I9 -> 4747.0557 | J7: =融资!J9 -> 5123.4399 | ... L7: =融资!L9 -> 6510.1363 | N7: =融资!N9 -> 4965.1259
A8: 应收票据及应收款项融资 | C8: =营运资本!C9 -> 791.3691 | D8: =营运资本!D9 -> 722.2022 | E8: =营运资本!E9 -> 1387.9972 | F8: =营运资本!F9 -> 1704.2001 | G8: =营运资本!G9 -> 967.2344 | H8: =营运资本!H9 -> 1102.5406 | I8: =营运资本!I9 -> 1176.1853 | J8: =营运资本!J9 -> 1234.7308 | ... L8: =营运资本!L9 -> 1358.5799 | N8: =营运资本!N9 -> 1214.8501
A9: 应收账款 | C9: =营运资本!C11 -> 4219.3462 | D9: =营运资本!D11 -> 6830.3427 | E9: =营运资本!E11 -> 12411.795 | F9: =营运资本!F11 -> 15260.857 | G9: =营运资本!G11 -> 14811.052 | H9: =营运资本!H11 -> 15103.297 | I9: =营运资本!I11 -> 15306.521 | J9: =营运资本!J11 -> 15222.708 | ... L9: =营运资本!L11 -> 15819.08 | N9: =营运资本!N11 -> 13100.291
A10: 预付款项 | C10: =营运资本!C13 -> 345.0894 | D10: =营运资本!D13 -> 744.5724 | E10: =营运资本!E13 -> 1204.0073 | F10: =营运资本!F13 -> 659.2119 | G10: =营运资本!G13 -> 1461.3915 | H10: =营运资本!H13 -> 1632.1662 | I10: =营运资本!I13 -> 1630.9752 | J10: =营运资本!J13 -> 1600.8032 | ... L10: =营运资本!L13 -> 1765.8771 | N10: =营运资本!N13 -> 2516.0374
A11: 其他应收款 | C11: =营运资本!C15 -> 680.7874 | D11: =营运资本!D15 -> 484.3906 | E11: =营运资本!E15 -> 646.0326 | F11: =营运资本!F15 -> 496.4689 | G11: =营运资本!G15 -> 367.0848 | H11: =营运资本!H15 -> 367.0848 | I11: =营运资本!I15 -> 367.0848 | J11: =营运资本!J15 -> 367.0848 | ... L11: =营运资本!L15 -> 367.0848 | N11: =营运资本!N15 -> 315.1794
A12: 存货 | C12: =营运资本!C16 -> 14605.128 | D12: =营运资本!D16 -> 14390.162 | E12: =营运资本!E16 -> 9718.9319 | F12: =营运资本!F16 -> 9329.2257 | G12: =营运资本!G16 -> 10575.039 | H12: =营运资本!H16 -> 11030.164 | I12: =营运资本!I16 -> 11490.236 | J12: =营运资本!J16 -> 11807.821 | ... L12: =营运资本!L16 -> 12653.282 | N12: =营运资本!N16 -> 13560.093
A13: 其他流动资产（含合同资产等） | C13: =营运资本!C18 -> 543.3164 | D13: =营运资本!D18 -> 633.5327 | E13: =营运资本!E18 -> 725.1378 | F13: =营运资本!F18 -> 917.7123 | G13: =营运资本!G18 -> 539.4725 | H13: =营运资本!H18 -> 606.39736 | I13: =营运资本!I18 -> 646.9019 | J13: =营运资本!J18 -> 679.10192 | ... L13: =营运资本!L18 -> 747.21892 | N13: =营运资本!N18 -> 706.3645
A14: 流动资产合计 | C14: =SUM(C7:C13) -> 25907.365 | D14: =SUM(D7:D13) -> 28194.176 | E14: =SUM(E7:E13) -> 31301.631 | F14: =SUM(F7:F13) -> 33611.433 | G14: =SUM(G7:G13) -> 35207.768 | H14: =SUM(H7:H13) -> 34463.67 | I14: =SUM(I7:I13) -> 35364.96 | J14: =SUM(J7:J13) -> 36035.69 | ... L14: =SUM(L7:L13) -> 39221.259 | N14: =SUM(N7:N13) -> 36377.942
A15: 长期股权投资 | C15: =历史报表!E55 -> 2504.3889 | D15: =历史报表!F55 -> 2726.3613 | E15: =历史报表!G55 -> 2743.0593 | F15: =历史报表!H55 -> 2745.9269 | G15: =历史报表!I55 -> 2987.0148 | H15: =G15+费用!H35-费用!H32 -> 3529.7449 | I15: =H15+费用!I35-费用!I32 -> 3993.6194 | J15: =I15+费用!J35-费用!J32 -> 4478.1877 | K15: =J15+费用!K35-费用!K32 -> 4984.4844 | L15: =K15+费用!L35-费用!L32 -> 5513.5959 | N15: =历史报表!K55 -> 3243.2863 | O15: 其中广发基金2025年末账面19.5亿；预测=上期+权益法收益−收到分红（其他联营企业分红假设为0）
A16: 金融资产投资（其他权益工具/其他非流动金融资产等） | C16: =历史报表!E56+历史报表!E57 -> 296.1554 | D16: =历史报表!F56+历史报表!F57 -> 307.1575 | E16: =历史报表!G56+历史报表!G57 -> 244.3584 | F16: =历史报表!H56+历史报表!H57 -> 135.5233 | G16: =历史报表!I56+历史报表!I57 -> 132.1372 | H16: =G16 -> 132.1372 | I16: =H16 -> 132.1372 | J16: =I16 -> 132.1372 | K16: =J16 -> 132.1372 | L16: =K16 -> 132.1372 | N16: =历史报表!K56+历史报表!K57 -> 132.1372
A17: 投资性房地产 | C17: =历史报表!E58 -> 118.3596 | D17: =历史报表!F58 -> 113.6049 | E17: =历史报表!G58 -> 108.8725 | F17: =历史报表!H58 -> 104.0955 | G17: =历史报表!I58 -> 99.29 | H17: =G17 -> 99.29 | I17: =H17 -> 99.29 | J17: =I17 -> 99.29 | K17: =J17 -> 99.29 | L17: =K17 -> 99.29 | N17: =历史报表!K58 -> 96.9127
A18: 固定资产 | C18: =历史报表!E59 -> 3458.9686 | D18: =历史报表!F59 -> 3673.3317 | E18: =历史报表!G59 -> 4194.2529 | F18: =历史报表!H59 -> 3762.6742 | G18: =历史报表!I59 -> 3608.4412 | H18: =资本开支折旧!H20 -> 4021.9931 | I18: =资本开支折旧!I20 -> 4561.3152 | J18: =资本开支折旧!J20 -> 5068.5202 | K18: =资本开支折旧!K20 -> 5289.4281 | L18: =资本开支折旧!L20 -> 5233.7445 | N18: =历史报表!K59 -> 3972.7994
A19: 在建工程 | C19: =历史报表!E61 -> 1191.0416 | D19: =历史报表!F61 -> 916.072 | E19: =历史报表!G61 -> 429.2772 | F19: =历史报表!H61 -> 889.8926 | G19: =历史报表!I61 -> 1364.8068 | H19: =资本开支折旧!H30 -> 1465.6437 | I19: =资本开支折旧!I30 -> 1741.1041 | J19: =资本开支折旧!J30 -> 1837.6072 | K19: =资本开支折旧!K30 -> 1615.684 | L19: =资本开支折旧!L30 -> 1383.6262 | N19: =历史报表!K61 -> 1155.3614
A20: 使用权资产 | C20: =历史报表!E63 -> 88.6436 | D20: =历史报表!F63 -> 147.4453 | E20: =历史报表!G63 -> 78.6099 | F20: =历史报表!H63 -> 160.5597 | G20: =历史报表!I63 -> 108.2493 | H20: =资本开支折旧!H56 -> 108.2493 | I20: =资本开支折旧!I56 -> 108.2493 | J20: =资本开支折旧!J56 -> 108.2493 | K20: =资本开支折旧!K56 -> 108.2493 | L20: =资本开支折旧!L56 -> 108.2493 | N20: =历史报表!K63 -> 79.9477
A21: 无形资产 | C21: =历史报表!E64 -> 956.8971 | D21: =历史报表!F64 -> 1202.1387 | E21: =历史报表!G64 -> 1553.3013 | F21: =历史报表!H64 -> 1741.9929 | G21: =历史报表!I64 -> 2407.8063 | H21: =资本开支折旧!H45 -> 2684.2797 | I21: =资本开支折旧!I45 -> 2875.2322 | J21: =资本开支折旧!J45 -> 2981.3686 | K21: =资本开支折旧!K45 -> 3005.428 | L21: =资本开支折旧!L45 -> 2950.5069 | N21: =历史报表!K64 -> 2249.317
A22: 开发支出 | C22: =历史报表!E65 -> 1124.4628 | D22: =历史报表!F65 -> 1020.541 | E22: =历史报表!G65 -> 938.2379 | F22: =历史报表!H65 -> 1273.7418 | G22: =历史报表!I65 -> 953.7547 | H22: =资本开支折旧!H53 -> 924.1838 | I22: =资本开支折旧!I53 -> 897.4859 | J22: =资本开支折旧!J53 -> 869.0907 | K22: =资本开支折旧!K53 -> 842.03115 | L22: =资本开支折旧!L53 -> 817.01276 | N22: =历史报表!K65 -> 1229.9452
A23: 商誉 | C23: =历史报表!E66 -> 2.1761 | D23: =历史报表!F66 -> 2.1761 | E23: =历史报表!G66 -> 86.3484 | F23: =历史报表!H66 -> 86.3484 | G23: =历史报表!I66 -> 86.3484 | H23: =G23 -> 86.3484 | I23: =H23 -> 86.3484 | J23: =I23 -> 86.3484 | K23: =J23 -> 86.3484 | L23: =K23 -> 86.3484 | N23: =历史报表!K66 -> 86.3484
A24: 长期待摊费用 | C24: =历史报表!E67 -> 57.8415 | D24: =历史报表!F67 -> 50.8145 | E24: =历史报表!G67 -> 48.4462 | F24: =历史报表!H67 -> 39.0585 | G24: =历史报表!I67 -> 36.4732 | H24: =资本开支折旧!H58 -> 36.4732 | I24: =资本开支折旧!I58 -> 36.4732 | J24: =资本开支折旧!J58 -> 36.4732 | K24: =资本开支折旧!K58 -> 36.4732 | L24: =资本开支折旧!L58 -> 36.4732 | N24: =历史报表!K67 -> 39.016
A25: 递延所得税资产 | C25: =历史报表!E68 -> 174.021 | D25: =历史报表!F68 -> 192.1203 | E25: =历史报表!G68 -> 207.1906 | F25: =历史报表!H68 -> 202.3741 | G25: =历史报表!I68 -> 186.1557 | H25: =G25 -> 186.1557 | I25: =H25 -> 186.1557 | J25: =I25 -> 186.1557 | K25: =J25 -> 186.1557 | L25: =K25 -> 186.1557 | N25: =历史报表!K68 -> 189.3518
A26: 其他非流动资产（轧差） | C26: =历史报表!E70-C15-C16-C17-C18-C19-C20-C21-C22-C23-C24-C25 -> -0.0002 | D26: =历史报表!F70-D15-D16-D17-D18-D19-D20-D21-D22-D23-D24-D25 -> 9.9999999e-05 | E26: =历史报表!G70-E15-E16-E17-E18-E19-E20-E21-E22-E23-E24-E25 -> -1.6200374e-12 | F26: =历史报表!H70-F15-F16-F17-F18-F19-F20-F21-F22-F23-F24-F25 -> 3.819 | G26: =历史报表!I70-G15-G16-G17-G18-G19-G20-G21-G22-G23-G24-G25 -> 3.7374 | H26: =G26 -> 3.7374 | I26: =H26 -> 3.7374 | J26: =I26 -> 3.7374 | K26: =J26 -> 3.7374 | L26: =K26 -> 3.7374 | N26: =历史报表!K70-N15-N16-N17-N18-N19-N20-N21-N22-N23-N24-N25 -> 5.3999
A27: 非流动资产合计 | C27: =SUM(C15:C26) -> 9972.956 | D27: =SUM(D15:D26) -> 10351.763 | E27: =SUM(E15:E26) -> 10631.955 | F27: =SUM(F15:F26) -> 11146.007 | G27: =SUM(G15:G26) -> 11974.215 | H27: =SUM(H15:H26) -> 13278.236 | I27: =SUM(I15:I26) -> 14721.148 | J27: =SUM(J15:J26) -> 15887.166 | ... L27: =SUM(L15:L26) -> 16550.878 | N27: =SUM(N15:N26) -> 12479.823
A28: 资产总计 | C28: =C14+C27 -> 35880.321 | D28: =D14+D27 -> 38545.939 | E28: =E14+E27 -> 41933.585 | F28: =F14+F27 -> 44757.44 | G28: =G14+G27 -> 47181.983 | H28: =H14+H27 -> 47741.906 | I28: =I14+I27 -> 50086.108 | J28: =J14+J27 -> 51922.855 | ... L28: =L14+L27 -> 55772.137 | N28: =N14+N27 -> 48857.765
A29: 负债
A30: 短期借款 | C30: =融资!C12 -> 288.5518 | D30: =融资!D12 -> 638.6606 | E30: =融资!E12 -> 2026.2359 | F30: =融资!F12 -> 5079.8579 | G30: =融资!G12 -> 6930.4263 | H30: =融资!H12 -> 5561.1521 | I30: =融资!I12 -> 3000 | J30: =融资!J12 -> 3000 | ... L30: =融资!L12 -> 3000 | N30: =融资!N12 -> 7776.7969
A31: 交易性金融负债 | C31: =营运资本!C37 -> 0 | D31: =营运资本!D37 -> 0 | E31: =营运资本!E37 -> 0 | F31: =营运资本!F37 -> 0 | G31: =营运资本!G37 -> 18.9335 | H31: =营运资本!H37 -> 18.9335 | I31: =营运资本!I37 -> 18.9335 | J31: =营运资本!J37 -> 18.9335 | ... L31: =营运资本!L37 -> 18.9335 | N31: =营运资本!N37 -> 18.9335
A32: 应付票据 | C32: =营运资本!C24 -> 5945.8226 | D32: =营运资本!D24 -> 7526.9418 | E32: =营运资本!E24 -> 7752.2333 | F32: =营运资本!F24 -> 8512.7803 | G32: =营运资本!G24 -> 6071.3562 | H32: =营运资本!H24 -> 6582.3251 | I32: =营运资本!I24 -> 7047.3449 | J32: =营运资本!J24 -> 7449.0482 | ... L32: =营运资本!L24 -> 8217.1901 | N32: =营运资本!N24 -> 7293.6379
A33: 应付账款 | C33: =营运资本!C25 -> 5655.6024 | D33: =营运资本!D25 -> 6492.2746 | E33: =营运资本!E25 -> 6814.2548 | F33: =营运资本!F25 -> 5993.2517 | G33: =营运资本!G25 -> 6556.1394 | H33: =营运资本!H25 -> 7130.8522 | I33: =营运资本!I25 -> 7634.6237 | J33: =营运资本!J25 -> 8069.8022 | ... L33: =营运资本!L25 -> 8901.9559 | N33: =营运资本!N25 -> 6255.2128
A34: 合同负债及预收款项 | C34: =营运资本!C27 -> 3168.6748 | D34: =营运资本!D27 -> 1320.7421 | E34: =营运资本!E27 -> 1337.322 | F34: =营运资本!F27 -> 776.1394 | G34: =营运资本!G27 -> 977.6682 | H34: =营运资本!H27 -> 1074.9771 | I34: =营运资本!I27 -> 1146.7806 | J34: =营运资本!J27 -> 1203.8625 | ... L34: =营运资本!L27 -> 1324.6154 | N34: =营运资本!N27 -> 1107.5807
A35: 应付职工薪酬 | C35: =营运资本!C29 -> 235.4881 | D35: =营运资本!D29 -> 231.3288 | E35: =营运资本!E29 -> 283.6855 | F35: =营运资本!F29 -> 256.2975 | G35: =营运资本!G29 -> 270.1812 | H35: =营运资本!H29 -> 303.19868 | I35: =营运资本!I29 -> 323.45095 | J35: =营运资本!J29 -> 339.55096 | ... L35: =营运资本!L29 -> 373.60946 | N35: =营运资本!N29 -> 183.8769
A36: 应交税费 | C36: =营运资本!C31 -> 244.7092 | D36: =营运资本!D31 -> 524.5033 | E36: =营运资本!E31 -> 905.9197 | F36: =营运资本!F31 -> 754.1246 | G36: =营运资本!G31 -> 402.134 | H36: =营运资本!H31 -> 441.01626 | I36: =营运资本!I31 -> 470.47411 | J36: =营运资本!J31 -> 493.8923 | ... L36: =营运资本!L31 -> 543.43194 | N36: =营运资本!N31 -> 248.2249
A37: 其他应付款 | C37: =营运资本!C33 -> 1700.9199 | D37: =营运资本!D33 -> 2131.7705 | E37: =营运资本!E33 -> 2036.3337 | F37: =营运资本!F33 -> 1765.2361 | G37: =营运资本!G33 -> 1304.7764 | H37: =营运资本!H33 -> 1378.1758 | I37: =营运资本!I33 -> 1470.2316 | J37: =营运资本!J33 -> 1543.4135 | ... L37: =营运资本!L33 -> 1698.2248 | N37: =营运资本!N33 -> 1579.4903
A38: 一年内到期的非流动负债 | C38: =融资!C15 -> 16.1005 | D38: =融资!D15 -> 897.2013 | E38: =融资!E15 -> 1361.8444 | F38: =融资!F15 -> 3162.1433 | G38: =融资!G15 -> 524.3707 | H38: =融资!H15 -> 529.95874 | I38: =融资!I15 -> 529.95874 | J38: =融资!J15 -> 529.95874 | ... L38: =融资!L15 -> 529.95874 | N38: =融资!N15 -> 2996.6449
A39: 其他流动负债 | C39: =营运资本!C35 -> 458.7291 | D39: =营运资本!D35 -> 269.3734 | E39: =营运资本!E35 -> 246.4759 | F39: =营运资本!F35 -> 186.5249 | G39: =营运资本!G35 -> 159.7008 | H39: =营运资本!H35 -> 179.16286 | I39: =营运资本!I35 -> 191.13011 | J39: =营运资本!J35 -> 200.64375 | ... L39: =营运资本!L35 -> 220.76923 | N39: =营运资本!N35 -> 142.5412
A40: 流动负债合计 | C40: =SUM(C30:C39) -> 17714.598 | D40: =SUM(D30:D39) -> 20032.796 | E40: =SUM(E30:E39) -> 22764.305 | F40: =SUM(F30:F39) -> 26486.356 | G40: =SUM(G30:G39) -> 23215.687 | H40: =SUM(H30:H39) -> 23199.752 | I40: =SUM(I30:I39) -> 21832.928 | J40: =SUM(J30:J39) -> 22849.106 | ... L40: =SUM(L30:L39) -> 24828.689 | N40: =SUM(N30:N39) -> 27602.94
A41: 长期借款 | C41: =融资!C14 -> 2455.8 | D41: =融资!D14 -> 1672.1 | E41: =融资!E14 -> 717.2 | F41: =融资!F14 -> 1937.29 | G41: =融资!G14 -> 4239.3389 | H41: =融资!H14 -> 4230 | I41: =融资!I14 -> 4230 | J41: =融资!J14 -> 4230 | ... L41: =融资!L14 -> 4230 | N41: =融资!N14 -> 1781.3981
A42: 应付债券 | C42: =融资!C16 -> 2598.1583 | D42: =融资!D16 -> 2722.4942 | E42: =融资!E16 -> 2843.957 | F42: =融资!F16 -> 0 | G42: =融资!G16 -> 0 | H42: =融资!H16 -> 0 | I42: =融资!I16 -> 0 | J42: =融资!J16 -> 0 | ... L42: =融资!L16 -> 0 | N42: =融资!N16 -> 0
A43: 租赁负债 | C43: =融资!C17 -> 72.0342 | D43: =融资!D17 -> 84.52 | E43: =融资!E17 -> 49.6756 | F43: =融资!F17 -> 99.1721 | G43: =融资!G17 -> 39.9403 | H43: =融资!H17 -> 39.9403 | I43: =融资!I17 -> 39.9403 | J43: =融资!J17 -> 39.9403 | ... L43: =融资!L17 -> 39.9403 | N43: =融资!N17 -> 16.7409
A44: 递延收益 | C44: =历史报表!E94 -> 413.1172 | D44: =历史报表!F94 -> 466.6561 | E44: =历史报表!G94 -> 592.4055 | F44: =历史报表!H94 -> 516.1313 | G44: =历史报表!I94 -> 537.9914 | H44: =G44 -> 537.9914 | I44: =H44 -> 537.9914 | J44: =I44 -> 537.9914 | K44: =J44 -> 537.9914 | L44: =K44 -> 537.9914 | N44: =历史报表!K94 -> 501.1296
A45: 其他非流动负债（预计负债/递延所得税负债等，轧差） | C45: =历史报表!E95-C41-C42-C43-C44 -> 34.519 | D45: =历史报表!F95-D41-D42-D43-D44 -> 45.6288 | E45: =历史报表!G95-E41-E42-E43-E44 -> 51.3364 | F45: =历史报表!H95-F41-F42-F43-F44 -> 48.1279 | G45: =历史报表!I95-G41-G42-G43-G44 -> 37.7089 | H45: =G45 -> 37.7089 | I45: =H45 -> 37.7089 | J45: =I45 -> 37.7089 | K45: =J45 -> 37.7089 | L45: =K45 -> 37.7089 | N45: =历史报表!K95-N41-N42-N43-N44 -> 35.736
A46: 非流动负债合计 | C46: =SUM(C41:C45) -> 5573.6287 | D46: =SUM(D41:D45) -> 4991.3991 | E46: =SUM(E41:E45) -> 4254.5745 | F46: =SUM(F41:F45) -> 2600.7213 | G46: =SUM(G41:G45) -> 4854.9795 | H46: =SUM(H41:H45) -> 4845.6406 | I46: =SUM(I41:I45) -> 4845.6406 | J46: =SUM(J41:J45) -> 4845.6406 | ... L46: =SUM(L41:L45) -> 4845.6406 | N46: =SUM(N41:N45) -> 2335.0046
A47: 负债合计 | C47: =C40+C46 -> 23288.227 | D47: =D40+D46 -> 25024.196 | E47: =E40+E46 -> 27018.88 | F47: =F40+F46 -> 29087.077 | G47: =G40+G46 -> 28070.666 | H47: =H40+H46 -> 28045.393 | I47: =I40+I46 -> 26678.569 | J47: =J40+J46 -> 27694.746 | ... L47: =L40+L46 -> 29674.33 | N47: =N40+N46 -> 29937.945
A48: 所有者权益
A49: 股本 | C49: =历史报表!E97 -> 1187.8277 | D49: =历史报表!F97 -> 1186.5645 | E49: =历史报表!G97 -> 1185.4913 | F49: =历史报表!H97 -> 1184.4645 | G49: =历史报表!I97 -> 1358.1675 | H49: =融资!H35 -> 1358.1675 | I49: =融资!I35 -> 1455.2605 | J49: =融资!J35 -> 1455.2605 | K49: =融资!K35 -> 1455.2605 | L49: =融资!L35 -> 1455.2605 | N49: =历史报表!K97 -> 1358.1675
A50: 其他权益工具（可转债权益成分） | C50: =历史报表!E98 -> 736.4456 | D50: =历史报表!F98 -> 736.4411 | E50: =历史报表!G98 -> 736.4387 | F50: =历史报表!H98 -> 736.4344 | G50: =历史报表!I98 -> 0 | H50: =G50 -> 0 | I50: =H50 -> 0 | J50: =I50 -> 0 | K50: =J50 -> 0 | L50: =K50 -> 0 | N50: =历史报表!K98 -> 0
A51: 资本公积 | C51: =历史报表!E99 -> 5849.0049 | D51: =历史报表!F99 -> 5876.0603 | E51: =历史报表!G99 -> 6232.649 | F51: =历史报表!H99 -> 6284.7788 | G51: =历史报表!I99 -> 9829.9698 | H51: =G51+融资!H31-融资!H32 -> 9829.9698 | I51: =H51+融资!I31-融资!I32 -> 12613.626 | J51: =I51+融资!J31-融资!J32 -> 12613.626 | K51: =J51+融资!K31-融资!K32 -> 12613.626 | L51: =K51+融资!L31-融资!L32 -> 12613.626 | N51: =历史报表!K99 -> 9874.2939
A52: 减：库存股 | C52: =历史报表!E100 -> 660.7624 | D52: =历史报表!F100 -> 641.6411 | E52: =历史报表!G100 -> 424.6667 | F52: =历史报表!H100 -> 209.9661 | G52: =历史报表!I100 -> 0 | H52: =G52+融资!H33-融资!H34 -> 0 | I52: =H52+融资!I33-融资!I34 -> 0 | J52: =I52+融资!J33-融资!J34 -> 0 | K52: =J52+融资!K33-融资!K34 -> 0 | L52: =K52+融资!L33-融资!L34 -> 0 | N52: =历史报表!K100 -> 0 | O52: 预测假设回购股份注销：股本减少计入股本，差额冲减库存股
A53: 其他综合收益及专项储备 | C53: =历史报表!E101+历史报表!E102 -> -57.7561 | D53: =历史报表!F101+历史报表!F102 -> -15.4933 | E53: =历史报表!G101+历史报表!G102 -> 55.8051 | F53: =历史报表!H101+历史报表!H102 -> 20.209 | G53: =历史报表!I101+历史报表!I102 -> 191.1034 | H53: =G53 -> 191.1034 | I53: =H53 -> 191.1034 | J53: =I53 -> 191.1034 | K53: =J53 -> 191.1034 | L53: =K53 -> 191.1034 | N53: =历史报表!K101+历史报表!K102 -> 148.7154
A54: 盈余公积 | C54: =历史报表!E103 -> 423.8983 | D54: =历史报表!F103 -> 438.563 | E54: =历史报表!G103 -> 467.7518 | F54: =历史报表!H103 -> 518.7715 | G54: =历史报表!I103 -> 550.7272 | H54: =G54 -> 550.7272 | I54: =H54 -> 550.7272 | J54: =I54 -> 550.7272 | K54: =J54 -> 550.7272 | L54: =K54 -> 550.7272 | N54: =历史报表!K103 -> 550.7272
A55: 未分配利润 | C55: =历史报表!E104 -> 4254.8281 | D55: =历史报表!F104 -> 4551.7324 | E55: =历史报表!G104 -> 4919.3451 | F55: =历史报表!H104 -> 5416.111 | G55: =历史报表!I104 -> 5607.969 | H55: =G55+利润表!H29-融资!H41 -> 6228.1652 | I55: =H55+利润表!I29-融资!I41 -> 7078.4415 | J55: =I55+利润表!J29-融资!J41 -> 7909.0114 | K55: =J55+利润表!K29-融资!K41 -> 8832.6301 | L55: =K55+利润表!L29-融资!L41 -> 9783.7096 | N55: =历史报表!K104 -> 5669.0265
A56: 归属于母公司股东权益 | C56: =C49+C50+C51-C52+C53+C54+C55 -> 11733.486 | D56: =D49+D50+D51-D52+D53+D54+D55 -> 12132.227 | E56: =E49+E50+E51-E52+E53+E54+E55 -> 13172.814 | F56: =F49+F50+F51-F52+F53+F54+F55 -> 13950.803 | G56: =G49+G50+G51-G52+G53+G54+G55 -> 17537.937 | H56: =H49+H50+H51-H52+H53+H54+H55 -> 18158.133 | I56: =I49+I50+I51-I52+I53+I54+I55 -> 21889.159 | J56: =J49+J50+J51-J52+J53+J54+J55 -> 22719.729 | ... L56: =L49+L50+L51-L52+L53+L54+L55 -> 24594.427 | N56: =N49+N50+N51-N52+N53+N54+N55 -> 17600.93
A57: 少数股东权益 | C57: =融资!C47 -> 858.608 | D57: =融资!D47 -> 1389.5164 | E57: =融资!E47 -> 1741.8913 | F57: =融资!F47 -> 1719.5595 | G57: =融资!G47 -> 1573.3797 | H57: =融资!H47 -> 1538.3797 | I57: =融资!I47 -> 1518.3797 | J57: =融资!J47 -> 1508.3797 | ... L57: =融资!L47 -> 1503.3797 | N57: =历史报表!K106 -> 1318.8897
A58: 所有者权益合计 | C58: =C56+C57 -> 12592.094 | D58: =D56+D57 -> 13521.743 | E58: =E56+E57 -> 14914.706 | F58: =F56+F57 -> 15670.363 | G58: =G56+G57 -> 19111.317 | H58: =H56+H57 -> 19696.513 | I58: =I56+I57 -> 23407.538 | J58: =J56+J57 -> 24228.108 | ... L58: =L56+L57 -> 26097.806 | N58: =N56+N57 -> 18919.82
A59: 负债和所有者权益总计 | C59: =C47+C58 -> 35880.321 | D59: =D47+D58 -> 38545.939 | E59: =E47+E58 -> 41933.585 | F59: =F47+F58 -> 44757.44 | G59: =G47+G58 -> 47181.983 | H59: =H47+H58 -> 47741.906 | I59: =I47+I58 -> 50086.107 | J59: =J47+J58 -> 51922.855 | ... L59: =L47+L58 -> 55772.136 | N59: =N47+N58 -> 48857.765
A60: 核对：资产−负债−权益 | C60: =C28-C59 -> 0 | D60: =D28-D59 -> 9.9999997e-05 | E60: =E28-E59 -> -9.999999e-05 | F60: =F28-F59 -> -0.0001 | G60: =G28-G59 -> -0.0001 | H60: =H28-H59 -> 0.00066199999 | I60: =I28-I59 -> 0.00066199999 | J60: =J28-J59 -> 0.00066199999 | ... L60: =L28-L59 -> 0.00066199998 | N60: =N28-N59 -> -0.00019999999 | O60: 应为0
A61: 核对：资产总计−报表值（历史） | C61: =C28-历史报表!E72 -> -9.9999997e-05 | D61: =D28-历史报表!F72 -> 0 | E61: =E28-历史报表!G72 -> 0 | F61: =F28-历史报表!H72 -> 0 | G61: =G28-历史报表!I72 -> 0 | N61: =N28-历史报表!K72 -> 0
A62: 核对：归母权益−报表值（历史） | C62: =C56-历史报表!E105 -> -9.9999999e-05 | D62: =D56-历史报表!F105 -> -0.0001 | E62: =E56-历史报表!G105 -> 0 | F62: =F56-历史报表!H105 -> 0.0001 | G62: =G56-历史报表!I105 -> 0.0001 | N62: =N56-历史报表!K105 -> 0.0002

Sheet 现金流量表
A1: 现金流量表（百万元，间接法）
A2: 历史按报表补充资料重分类；预测：净利润+折旧摊销+利息−权益法收益−营运资本增加；短期借款为平衡项
A5: 项目 | B5: 百万元 | C5: 2021A | D5: 2022A | E5: 2023A | F5: 2024A | G5: 2025A | H5: 2026E | I5: 2027E | J5: 2028E | K5: 2029E | L5: 2030E | N5: 2026H1A | O5: 说明 / 来源
A6: 经营活动
A7: 净利润 | C7: =利润表!C27 -> 355.6332 | D7: =利润表!D27 -> 409.2239 | E7: =利润表!E27 -> 488.7864 | F7: =利润表!F27 -> 710.2001 | G7: =利润表!G27 -> 376.0493 | H7: =利润表!H27 -> 736.93618 | I7: =利润表!I27 -> 1075.8572 | J7: =利润表!J27 -> 1163.3271 | ... L7: =利润表!L27 -> 1351.9645 | N7: =利润表!N27 -> 185.2648
A8: 加：折旧与摊销 | C8: =资本开支折旧!C65 -> 689.9124 | D8: =资本开支折旧!D65 -> 816.4404 | E8: =资本开支折旧!E65 -> 968.2687 | F8: =资本开支折旧!F65 -> 1030.6364 | G8: =资本开支折旧!G65 -> 1090.7876 | H8: =资本开支折旧!H65 -> 1263.2603 | I8: =资本开支折旧!I65 -> 1430.589 | J8: =资本开支折旧!J65 -> 1607.5492 | ... L8: =资本开支折旧!L65 -> 1925.3376 | N8: =资本开支折旧!N65 -> 619.9144
A9: 加：资产及信用减值准备 | C9: =历史报表!E147+历史报表!E148 -> 257.2296 | D9: =历史报表!F147+历史报表!F148 -> 355.2399 | E9: =历史报表!G147+历史报表!G148 -> 439.5556 | F9: =历史报表!H147+历史报表!H148 -> 452.6691 | G9: =历史报表!I147+历史报表!I148 -> 375.5998 | H9: 0 | I9: 0 | J9: 0 | K9: 0 | L9: 0 | N9: =历史报表!K147+历史报表!K148 -> 39.9055 | O9: 预测期营运资本按净额驱动，减值已体现在净额变动中，故不再加回
A10: 加：财务费用（利息） | C10: =历史报表!E156 -> 124.8007 | D10: =历史报表!F156 -> 317.6675 | E10: =历史报表!G156 -> 338.3448 | F10: =历史报表!H156 -> 550.1596 | G10: =历史报表!I156 -> 347.1598 | H10: =融资!H22 -> 314.12276 | I10: =融资!I22 -> 277.05111 | J10: =融资!J22 -> 207.9 | K10: =融资!K22 -> 207.9 | L10: =融资!L22 -> 207.9 | N10: =历史报表!K156 -> 149.8608
A11: 减：投资收益（权益法等非现金） | C11: =历史报表!E157 -> -402.5676 | D11: =历史报表!F157 -> -389.6458 | E11: =历史报表!G157 -> -301.8478 | F11: =历史报表!H157 -> -287.7853 | G11: =历史报表!I157 -> -465.8928 | H11: =-费用!H35 -> -686.73008 | I11: =-费用!I35 -> -718.56658 | J11: =-费用!J35 -> -751.99491 | K11: =-费用!K35 -> -787.09466 | L11: =-费用!L35 -> -823.94939 | N11: =历史报表!K157 -> -388.9358
A12: 营运资本变动 | C12: =历史报表!E160+历史报表!E161+历史报表!E162 -> -970.2809 | D12: =历史报表!F160+历史报表!F161+历史报表!F162 -> -1442.3351 | E12: =历史报表!G160+历史报表!G161+历史报表!G162 -> -1876.5092 | F12: =历史报表!H160+历史报表!H161+历史报表!H162 -> 2185.9284 | G12: =历史报表!I160+历史报表!I161+历史报表!I162 -> 3015.6536 | H12: =-营运资本!H41 -> 227.3757 | I12: =-营运资本!I41 -> 418.07369 | J12: =-营运资本!J41 -> 721.83196 | K12: =-营运资本!K41 -> 232.51467 | L12: =-营运资本!L41 -> -51.804598 | N12: =历史报表!K160+历史报表!K161+历史报表!K162 -> -93.9803
A13: 其他（递延税项、处置损益等，轧差） | C13: =历史报表!E120-C7-C8-C9-C10-C11-C12 -> -2.2985 | D13: =历史报表!F120-D7-D8-D9-D10-D11-D12 -> -19.557 | E13: =历史报表!G120-E7-E8-E9-E10-E11-E12 -> 2.567 | F13: =历史报表!H120-F7-F8-F9-F10-F11-F12 -> -3.6324 | G13: =历史报表!I120-G7-G8-G9-G10-G11-G12 -> 33.1985 | H13: 0 | I13: 0 | J13: 0 | K13: 0 | L13: 0 | N13: =历史报表!K120-N7-N8-N9-N10-N11-N12 -> -2.901
A14: 经营活动现金流量净额 | C14: =SUM(C7:C13) -> 52.4289 | D14: =SUM(D7:D13) -> 47.0338 | E14: =SUM(E7:E13) -> 59.1655 | F14: =SUM(F7:F13) -> 4638.1759 | G14: =SUM(G7:G13) -> 4772.5558 | H14: =SUM(H7:H13) -> 1854.9649 | I14: =SUM(I7:I13) -> 2483.0044 | J14: =SUM(J7:J13) -> 2948.6133 | ... L14: =SUM(L7:L13) -> 2609.4481 | N14: =SUM(N7:N13) -> 509.1284
A15: 投资活动
A16: 购建固定资产、无形资产和其他长期资产 | C16: =-历史报表!E126 -> -700.5675 | D16: =-历史报表!F126 -> -732.8186 | E16: =-历史报表!G126 -> -749.8998 | F16: =-历史报表!H126 -> -1368.6518 | G16: =-历史报表!I126 -> -1436.5548 | H16: =-资本开支折旧!H72 -> -1964.5516 | I16: =-资本开支折旧!I72 -> -2349.626 | J16: =-资本开支折旧!J72 -> -2228.9986 | K16: =-资本开支折旧!K72 -> -1712.2945 | L16: =-资本开支折旧!L72 -> -1497.6568 | N16: =-历史报表!K126 -> -648.24 | O16: 预测含资本化研发支出
A17: 取得投资收益收到的现金（广发基金分红等） | C17: =历史报表!E122 -> 321.0687 | D17: =历史报表!F122 -> 166.8766 | E17: =历史报表!G122 -> 310.737 | F17: =历史报表!H122 -> 325.2183 | G17: =历史报表!I122 -> 328.6511 | H17: =费用!H32 -> 144 | I17: =费用!I32 -> 254.69203 | J17: =费用!J32 -> 267.42663 | K17: =费用!K32 -> 280.79797 | L17: =费用!L32 -> 294.83786 | N17: =历史报表!K122 -> 4.5138
A18: 其他投资活动（轧差） | C18: =历史报表!E131-C16-C17 -> -202.0769 | D18: =历史报表!F131-D16-D17 -> -132.301 | E18: =历史报表!G131-E16-E17 -> 83.3883 | F18: =历史报表!H131-F16-F17 -> 40.0592 | G18: =历史报表!I131-G16-G17 -> 8.8492 | H18: 0 | I18: 0 | J18: 0 | K18: 0 | L18: 0 | N18: =历史报表!K131-N16-N17 -> -113.162
A19: 投资活动现金流量净额 | C19: =SUM(C16:C18) -> -581.5757 | D19: =SUM(D16:D18) -> -698.243 | E19: =SUM(E16:E18) -> -355.7745 | F19: =SUM(F16:F18) -> -1003.3743 | G19: =SUM(G16:G18) -> -1099.0545 | H19: =SUM(H16:H18) -> -1820.5516 | I19: =SUM(I16:I18) -> -2094.934 | J19: =SUM(J16:J18) -> -1961.572 | ... L19: =SUM(L16:L18) -> -1202.8189 | N19: =SUM(N16:N18) -> -756.8882
A20: 筹资活动
A21: 长期借款/债券净增加 | H21: =融资!H13-融资!G13+融资!H16-融资!G16 -> -3.75 | I21: =融资!I13-融资!H13+融资!I16-融资!H16 -> 0 | J21: =融资!J13-融资!I13+融资!J16-融资!I16 -> 0 | K21: =融资!K13-融资!J13+融资!K16-融资!J16 -> 0 | L21: =融资!L13-融资!K13+融资!L16-融资!K16 -> 0
A22: 股权融资（定增净额等） | C22: =历史报表!E132 -> 892.7624 | D22: =历史报表!F132 -> 547.8 | E22: =历史报表!G132 -> 601.8952 | F22: =历史报表!H132 -> 0 | G22: =历史报表!I132 -> 1094.15 | H22: =融资!H31 -> 0 | I22: =融资!I31 -> 2880.7493 | J22: =融资!J31 -> 0 | K22: =融资!K31 -> 0 | L22: =融资!L31 -> 0 | N22: =历史报表!K132 -> 0
A23: 分配股利、利润或偿付利息 | C23: =-历史报表!E137 -> -227.3401 | D23: =-历史报表!F137 -> -289.026 | E23: =-历史报表!G137 -> -373.8762 | F23: =-历史报表!H137 -> -472.7796 | G23: =-历史报表!I137 -> -444.0674 | H23: =-(融资!H41+融资!H45+融资!H22) -> -465.86276 | I23: =-(融资!I41+融资!I45+融资!I22) -> -522.63196 | J23: =-(融资!J41+融资!J45+融资!J22) -> -550.65715 | K23: =-(融资!K41+融资!K45+融资!K22) -> -573.89813 | L23: =-(融资!L41+融资!L45+融资!L22) -> -608.78505 | N23: =-历史报表!K137 -> -124.1461
A24: 股份回购 | H24: =-融资!H33 -> 0 | I24: =-融资!I33 -> 0 | J24: =-融资!J33 -> 0 | K24: =-融资!K33 -> 0 | L24: =-融资!L33 -> 0
A25: 租赁付款 | H25: =-资本开支折旧!H57 -> -60 | I25: =-资本开支折旧!I57 -> -60 | J25: =-资本开支折旧!J57 -> -60 | K25: =-资本开支折旧!K57 -> -60 | L25: =-资本开支折旧!L57 -> -60
A26: 筹资现金流（不含短期借款变动） | H26: =SUM(H21:H25) -> -529.61276 | I26: =SUM(I21:I25) -> 2298.1173 | J26: =SUM(J21:J25) -> -610.65715 | K26: =SUM(K21:K25) -> -633.89813 | L26: =SUM(L21:L25) -> -668.78505
A27: 现金余额（偿还/新增短期借款前） | H27: =G36+H14+H19+H26+H33 -> 5869.2742 | I27: =H36+I14+I19+I26+I33 -> 7186.1877 | J27: =I36+J14+J19+J26+J33 -> 5001.4198 | K27: =J36+K14+K19+K26+K33 -> 5650.2721 | L27: =K36+L14+L19+L26+L33 -> 6388.1162 | O27: 用于“融资”表短期借款平衡项
A28: 短期借款净增加（平衡项） | H28: =融资!H12-融资!H11 -> -1369.2742 | I28: =融资!I12-融资!I11 -> -2561.1521 | J28: =融资!J12-融资!J11 -> 0 | K28: =融资!K12-融资!K11 -> 0 | L28: =融资!L12-融资!L11 -> 0
A29: 借款净增加（历史：取得借款−偿还债务） | C29: =历史报表!E134-历史报表!E136 -> 1147.9244 | D29: =历史报表!F134-历史报表!F136 -> -88.0874 | E29: =历史报表!G134-历史报表!G136 -> 860.6168 | F29: =历史报表!H134-历史报表!H136 -> -3094.2253 | G29: =历史报表!I134-历史报表!I136 -> -2575.0947 | N29: =历史报表!K134-历史报表!K136 -> -1073.3382
A30: 其他筹资活动（历史轧差，含租赁/回购） | C30: =历史报表!E141-C22-C23-C29 -> -536.6673 | D30: =历史报表!F141-D22-D23-D29 -> -113.3778 | E30: =历史报表!G141-E22-E23-E29 -> -74.7243 | F30: =历史报表!H141-F22-F23-F29 -> -84.4664 | G30: =历史报表!I141-G22-G23-G29 -> -188.3664 | N30: =历史报表!K141-N22-N23-N29 -> -31.6205
A31: 筹资活动现金流量净额 | C31: =C22+C23+C29+C30 -> 1276.6794 | D31: =D22+D23+D29+D30 -> 57.3088 | E31: =E22+E23+E29+E30 -> 1013.9115 | F31: =F22+F23+F29+F30 -> -3651.4713 | G31: =G22+G23+G29+G30 -> -2113.3785 | H31: =H26+H28 -> -1898.887 | I31: =I26+I28 -> -263.03474 | J31: =J26+J28 -> -610.65715 | K31: =K26+K28 -> -633.89813 | L31: =L26+L28 -> -668.78505 | N31: =N22+N23+N29+N30 -> -1229.1048
A32: 现金变动
A33: 汇率变动影响 | C33: =历史报表!E142 -> -65.6549 | D33: =历史报表!F142 -> 6.6898 | E33: =历史报表!G142 -> 45.8685 | F33: =历史报表!H142 -> -21.394 | G33: =历史报表!I142 -> -5.9159 | H33: 0 | I33: 0 | J33: 0 | K33: 0 | L33: 0 | N33: =历史报表!K142 -> -71.0937
A34: 现金净增加额 | C34: =C14+C19+C31+C33 -> 681.8777 | D34: =D14+D19+D31+D33 -> -587.2106 | E34: =E14+E19+E31+E33 -> 763.171 | F34: =F14+F19+F31+F33 -> -38.0637 | G34: =G14+G19+G31+G33 -> 1554.2069 | H34: =H14+H19+H31+H33 -> -1864.4737 | I34: =I14+I19+I31+I33 -> 125.03564 | J34: =J14+J19+J31+J33 -> 376.38419 | ... L34: =L14+L19+L31+L33 -> 737.84415 | N34: =N14+N19+N31+N33 -> -1547.9583
A35: 期初现金 | C35: =历史报表!E144 -> 3851.7037 | D35: =历史报表!F144 -> 4672.3702 | E35: =历史报表!G144 -> 4085.1596 | F35: =历史报表!H144 -> 4848.3305 | G35: =历史报表!I144 -> 4810.2668 | H35: =G36 -> 6364.4737 | I35: =H36 -> 4500 | J35: =I36 -> 4625.0356 | K35: =J36 -> 5001.4198 | L35: =K36 -> 5650.2721 | N35: =历史报表!K144 -> 6364.4738
A36: 期末现金 | C36: =C35+C34 -> 4533.5814 | D36: =D35+D34 -> 4085.1596 | E36: =E35+E34 -> 4848.3306 | F36: =F35+F34 -> 4810.2668 | G36: =G35+G34 -> 6364.4737 | H36: =H35+H34 -> 4500 | I36: =I35+I34 -> 4625.0356 | J36: =J35+J34 -> 5001.4198 | ... L36: =L35+L34 -> 6388.1162 | N36: =N35+N34 -> 4816.5155
A37: 核对：期末现金−报表值（历史） | C37: =C36-历史报表!E145 -> 0 | D37: =D36-历史报表!F145 -> 0 | E37: =E36-历史报表!G145 -> 0.0001 | F37: =F36-历史报表!H145 -> 0 | G37: =G36-历史报表!I145 -> -9.9999999e-05 | N37: =N36-历史报表!K145 -> 0
A38: 自由现金流
A39: FCFF（EBIT×(1−t)+折旧摊销−资本开支−营运资本增加） | D39: =利润表!D37*(1-费用!D42)+资本开支折旧!D65-资本开支折旧!D72-营运资本!D41 -> -1436.4539 | E39: =利润表!E37*(1-费用!E42)+资本开支折旧!E65-资本开支折旧!E72-营运资本!E41 -> -1144.0308 | F39: =利润表!F37*(1-费用!F42)+资本开支折旧!F65-资本开支折旧!F72-营运资本!F41 -> -3019.9011 | G39: =利润表!G37*(1-费用!G42)+资本开支折旧!G65-资本开支折旧!G72-营运资本!G41 -> -3078.872 | H39: =利润表!H37*(1-费用!H42)+资本开支折旧!H65-资本开支折旧!H72-营运资本!H41 -> 191.54258 | I39: =利润表!I37*(1-费用!I42)+资本开支折旧!I65-资本开支折旧!I72-营运资本!I41 -> 280.82036 | J39: =利润表!J37*(1-费用!J42)+资本开支折旧!J65-资本开支折旧!J72-营运资本!J41 -> 879.63057 | K39: =利润表!K37*(1-费用!K42)+资本开支折旧!K65-资本开支折旧!K72-营运资本!K41 -> 1164.239 | L39: =利润表!L37*(1-费用!L42)+资本开支折旧!L65-资本开支折旧!L72-营运资本!L41 -> 1274.9176
A40: FCFE（经营现金流+投资现金流+有息负债净增加−租赁付款） | C40: =C14+C19+C29 -> 618.7776 | D40: =D14+D19+D29 -> -739.2966 | E40: =E14+E19+E29 -> 564.0078 | F40: =F14+F19+F29 -> 540.5763 | G40: =G14+G19+G29 -> 1098.4066 | H40: =H14+H19+H21+H28+H25 -> -1398.6109 | I40: =I14+I19+I21+I28+I25 -> -2233.0817 | J40: =J14+J19+J21+J28+J25 -> 927.04133 | K40: =K14+K19+K21+K28+K25 -> 1222.7503 | L40: =L14+L19+L21+L28+L25 -> 1346.6292 | N40: =N14+N19+N29 -> -1321.098
A41: 经营现金流/净利润 | C41: =C14/C7 -> 0.14742409 | D41: =D14/D7 -> 0.11493415 | E41: =E14/E7 -> 0.12104572 | F41: =F14/F7 -> 6.5308015 | G41: =G14/G7 -> 12.691304 | H41: =H14/H7 -> 2.517131 | I41: =I14/I7 -> 2.3079313 | J41: =J14/J7 -> 2.5346382 | ... L41: =L14/L7 -> 1.9301159
A42: 经营现金流质量：供应链融资列报影响（历史）
A43: 短期借款“非现金变动增加”（供应链融资等） | E43: 406.38697 | F43: 6852.8684 | G43: 5998.2355 | N43: 1974.5088 | O43: 来源：各期“筹资活动产生的各项负债变动情况”；2024年报：经营/筹资现金流变动“主要是供应链融资新准则列示调整所致”
A44: 剔除后的经营现金流（经营现金流−上项） | E44: =E14-E43 -> -347.22147 | F44: =F14-F43 -> -2214.6925 | G44: =G14-G43 -> -1225.6797 | N44: =N14-N43 -> -1465.3804 | O44: 供应商货款由银行代付、计入短期借款，现金流出由经营活动转至筹资活动；预测期未假设新增此类安排

Sheet 估值_DCF
A1: DCF估值（FCFF，百万元）
A2: 以2026年末为折现基准：2027E–2030E自由现金流按年中折现+永续价值；加回非经营资产、扣除净负债与少数股东权益后折回估值基准日
A5: 项目 | B5: 百万元 | C5: 2021A | D5: 2022A | E5: 2023A | F5: 2024A | G5: 2025A | H5: 2026E | I5: 2027E | J5: 2028E | K5: 2029E | L5: 2030E | O5: 说明 / 来源
A6: EBIT（经营口径，不含投资收益） | C6: =利润表!C37 -> 451.8033 | D6: =利润表!D37 -> 532.5247 | E6: =利润表!E37 -> 594.608 | F6: =利润表!F37 -> 1066.328 | G6: =利润表!G37 -> 464.3871 | H6: =利润表!H37 -> 764.89444 | I6: =利润表!I37 -> 898.60194 | J6: =利润表!J37 -> 895.68741 | ... L6: =利润表!L37 -> 1033.3809
A7: 经营所得税率 | H7: =假设!$C$16 -> 0.15 | I7: =假设!$C$16 -> 0.15 | J7: =假设!$C$16 -> 0.15 | K7: =假设!$C$16 -> 0.15 | L7: =假设!$C$16 -> 0.15
A8: NOPAT | H8: =H6*(1-H7) -> 650.16028 | I8: =I6*(1-I7) -> 763.81165 | J8: =J6*(1-J7) -> 761.3343 | K8: =K6*(1-K7) -> 847.76151 | L8: =L6*(1-L7) -> 878.37376
A9: 加：折旧摊销 | C9: =资本开支折旧!C65 -> 689.9124 | D9: =资本开支折旧!D65 -> 816.4404 | E9: =资本开支折旧!E65 -> 968.2687 | F9: =资本开支折旧!F65 -> 1030.6364 | G9: =资本开支折旧!G65 -> 1090.7876 | H9: =资本开支折旧!H65 -> 1263.2603 | I9: =资本开支折旧!I65 -> 1430.589 | J9: =资本开支折旧!J65 -> 1607.5492 | ... L9: =资本开支折旧!L65 -> 1925.3376
A10: 减：资本开支（含资本化研发） | C10: =资本开支折旧!C72 -> 1288.6142 | D10: =资本开支折旧!D72 -> 1122.9787 | E10: =资本开支折旧!E72 -> 1202.9214 | F10: =资本开支折旧!F72 -> 1600.9212 | G10: =资本开支折旧!G72 -> 1710.5607 | H10: =资本开支折旧!H72 -> 1964.5516 | I10: =资本开支折旧!I72 -> 2349.626 | J10: =资本开支折旧!J72 -> 2228.9986 | ... L10: =资本开支折旧!L72 -> 1497.6568
A11: 减：营运资本增加 | C11: =营运资本!C41 -> 0 | D11: =营运资本!D41 -> 1533.1776 | E11: =营运资本!E41 -> 1409.4092 | F11: =营运资本!F41 -> 3405.6442 | G11: =营运资本!G41 -> 2837.0629 | H11: =营运资本!H41 -> -227.3757 | I11: =营运资本!I41 -> -418.07369 | J11: =营运资本!J41 -> -721.83196 | ... L11: =营运资本!L41 -> 51.804598
A12: FCFF | H12: =H8+H9-H10-H11 -> 176.24469 | I12: =I8+I9-I10-I11 -> 262.84832 | J12: =J8+J9-J10-J11 -> 861.71682 | K12: =K8+K9-K10-K11 -> 1144.2917 | L12: =L8+L9-L10-L11 -> 1254.25
A13: 折现期（年，自2026年末，年中法） | I13: 0.5 | J13: 1.5 | K13: 2.5 | L13: 3.5
A14: 折现系数 | I14: =1/(1+估值_DCF!$D$20)^I13 -> 0.96104989 | J14: =1/(1+估值_DCF!$D$20)^J13 -> 0.8876419 | K14: =1/(1+估值_DCF!$D$20)^K13 -> 0.81984105 | L14: =1/(1+估值_DCF!$D$20)^L13 -> 0.75721903
A15: FCFF现值 | I15: =I12*I14 -> 252.61035 | J15: =J12*J14 -> 764.89596 | K15: =K12*K14 -> 938.13732 | L15: =L12*L14 -> 949.74196
A17: WACC
A18: 股权成本 Ke = Rf + β×ERP | D18: =假设!$C$11+假设!$C$13*假设!$C$12 -> 0.097
A19: 税后债务成本 | D19: =假设!$C$14*(1-假设!$C$16) -> 0.0255
A20: WACC | D20: =(1-假设!$C$15)*估值_DCF!$D$18+假设!$C$15*估值_DCF!$D$19 -> 0.0827
A21: 永续增长率 | D21: =假设!$C$17 -> 0.02
A22: 企业价值与股权价值（2026年末）
A23: 2027E–2030E FCFF现值合计 | D23: =SUM(I15:L15) -> 2905.3856
A24: 永续价值（2030年末） | D24: =L12*(1+估值_DCF!$D$21)/(估值_DCF!$D$20-估值_DCF!$D$21) -> 20404.067
A25: 永续价值现值 | D25: =估值_DCF!$D$24/(1+估值_DCF!$D$20)^4 -> 14848.555
A26: 经营性企业价值 EV | D26: =估值_DCF!$D$23+估值_DCF!$D$25 -> 17753.94
A27: 永续价值占EV比例 | D27: =估值_DCF!$D$25/估值_DCF!$D$26 -> 0.83635263
A28: 加：广发基金14.187%股权（2027E净利润×PE） | D28: =费用!I29*假设!$C$18*假设!$C$19 -> 10028.499 | O28: 非经营资产：权益法投资收益不在FCFF中
A29: 加：其他联营企业（账面价值） | D29: =资产负债表!H15-费用!H33 -> 1083.2548
A30: 加：金融资产投资（账面价值） | D30: =资产负债表!H16 -> 132.1372
A31: 减：净负债（2026E末，含租赁负债） | D31: =融资!H19 -> 5739.031
A32: 减：少数股东权益（账面×P/B） | D32: =融资!H47*假设!$C$32 -> 1538.3797
A33: 股权价值（2026年末） | D33: =估值_DCF!$D$26+估值_DCF!$D$28+估值_DCF!$D$29+估值_DCF!$D$30-估值_DCF!$D$31-估值_DCF!$D$32 -> 21720.421
A34: 折回估值基准日年数 | D34: =(假设!$C$10-假设!$C$9)/365 -> 0.23561644
A35: 股权价值（估值基准日） | D35: =估值_DCF!$D$33/(1+估值_DCF!$D$18)^估值_DCF!$D$34 -> 21251.759
A36: 总股本（2026E末，百万股） | D36: =融资!H35 -> 1358.1675
A37: 每股价值（元） | D37: =估值_DCF!$D$35/估值_DCF!$D$36 -> 15.647377
A38: 其中：经营业务每股价值 | D38: =(估值_DCF!$D$26-估值_DCF!$D$31-估值_DCF!$D$32)/(1+估值_DCF!$D$18)^估值_DCF!$D$34/估值_DCF!$D$36 -> 7.5472854
A39: 其中：广发基金股权每股价值 | D39: =估值_DCF!$D$28/(1+估值_DCF!$D$18)^估值_DCF!$D$34/估值_DCF!$D$36 -> 7.2245242
A40: 相对现价空间 | D40: =估值_DCF!$D$37/假设!$C$8-1 -> -0.56169812
A41: 隐含 EV/EBITDA（2027E） | D41: =估值_DCF!$D$26/利润表!I38 -> 7.6223636
A42: 隐含 PE（2027E） | D42: =估值_DCF!$D$33/利润表!I29 -> 20.188945
A44: 敏感性：每股价值（元）— WACC（行）× 永续增长率（列）
A45: WACC \ g | D45: 0.01 | E45: 0.015 | F45: 0.02 | G45: 0.025 | H45: 0.03
C46: 0.07 | D46: =((SUMPRODUCT($I$12:$L$12,1/(1+$C46)^$I$13:$L$13)+$L$12*(1+D$45)/($C46-D$45)/(1+$C46)^4)+(估值_DCF!$D$28+估值_DCF!$D$29+估值_DCF!$D$30-估值_DCF!$D$31-估值_DCF!$D$32))/(1+估值_DCF!$D$18)^估值_DCF!$D$34/估值_DCF!$D$36 -> 16.614075 | E46: =((SUMPRODUCT($I$12:$L$12,1/(1+$C46)^$I$13:$L$13)+$L$12*(1+E$45)/($C46-E$45)/(1+$C46)^4)+(估值_DCF!$D$28+估值_DCF!$D$29+估值_DCF!$D$30-估值_DCF!$D$31-估值_DCF!$D$32))/(1+估值_DCF!$D$18)^估值_DCF!$D$34/估值_DCF!$D$36 -> 17.731613 | F46: =((SUMPRODUCT($I$12:$L$12,1/(1+$C46)^$I$13:$L$13)+$L$12*(1+F$45)/($C46-F$45)/(1+$C46)^4)+(估值_DCF!$D$28+估值_DCF!$D$29+估值_DCF!$D$30-估值_DCF!$D$31-估值_DCF!$D$32))/(1+估值_DCF!$D$18)^估值_DCF!$D$34/估值_DCF!$D$36 -> 19.072658 | G46: =((SUMPRODUCT($I$12:$L$12,1/(1+$C46)^$I$13:$L$13)+$L$12*(1+G$45)/($C46-G$45)/(1+$C46)^4)+(估值_DCF!$D$28+估值_DCF!$D$29+估值_DCF!$D$30-估值_DCF!$D$31-估值_DCF!$D$32))/(1+估值_DCF!$D$18)^估值_DCF!$D$34/估值_DCF!$D$36 -> 20.711714 | H46: =((SUMPRODUCT($I$12:$L$12,1/(1+$C46)^$I$13:$L$13)+$L$12*(1+H$45)/($C46-H$45)/(1+$C46)^4)+(估值_DCF!$D$28+估值_DCF!$D$29+估值_DCF!$D$30-估值_DCF!$D$31-估值_DCF!$D$32))/(1+估值_DCF!$D$18)^估值_DCF!$D$34/估值_DCF!$D$36 -> 22.760533
C47: 0.075 | D47: =((SUMPRODUCT($I$12:$L$12,1/(1+$C47)^$I$13:$L$13)+$L$12*(1+D$45)/($C47-D$45)/(1+$C47)^4)+(估值_DCF!$D$28+估值_DCF!$D$29+估值_DCF!$D$30-估值_DCF!$D$31-估值_DCF!$D$32))/(1+估值_DCF!$D$18)^估值_DCF!$D$34/估值_DCF!$D$36 -> 15.499662 | E47: =((SUMPRODUCT($I$12:$L$12,1/(1+$C47)^$I$13:$L$13)+$L$12*(1+E$45)/($C47-E$45)/(1+$C47)^4)+(估值_DCF!$D$28+估值_DCF!$D$29+估值_DCF!$D$30-估值_DCF!$D$31-估值_DCF!$D$32))/(1+估值_DCF!$D$18)^估值_DCF!$D$34/估值_DCF!$D$36 -> 16.432138 | F47: =((SUMPRODUCT($I$12:$L$12,1/(1+$C47)^$I$13:$L$13)+$L$12*(1+F$45)/($C47-F$45)/(1+$C47)^4)+(估值_DCF!$D$28+估值_DCF!$D$29+估值_DCF!$D$30-估值_DCF!$D$31-估值_DCF!$D$32))/(1+估值_DCF!$D$18)^估值_DCF!$D$34/估值_DCF!$D$36 -> 17.534154 | G47: =((SUMPRODUCT($I$12:$L$12,1/(1+$C47)^$I$13:$L$13)+$L$12*(1+G$45)/($C47-G$45)/(1+$C47)^4)+(估值_DCF!$D$28+估值_DCF!$D$29+估值_DCF!$D$30-估值_DCF!$D$31-估值_DCF!$D$32))/(1+估值_DCF!$D$18)^估值_DCF!$D$34/估值_DCF!$D$36 -> 18.856574 | H47: =((SUMPRODUCT($I$12:$L$12,1/(1+$C47)^$I$13:$L$13)+$L$12*(1+H$45)/($C47-H$45)/(1+$C47)^4)+(估值_DCF!$D$28+估值_DCF!$D$29+估值_DCF!$D$30-估值_DCF!$D$31-估值_DCF!$D$32))/(1+估值_DCF!$D$18)^估值_DCF!$D$34/估值_DCF!$D$36 -> 20.472865
C48: 0.08 | D48: =((SUMPRODUCT($I$12:$L$12,1/(1+$C48)^$I$13:$L$13)+$L$12*(1+D$45)/($C48-D$45)/(1+$C48)^4)+(估值_DCF!$D$28+估值_DCF!$D$29+估值_DCF!$D$30-估值_DCF!$D$31-估值_DCF!$D$32))/(1+估值_DCF!$D$18)^估值_DCF!$D$34/估值_DCF!$D$36 -> 14.545672 | E48: =((SUMPRODUCT($I$12:$L$12,1/(1+$C48)^$I$13:$L$13)+$L$12*(1+E$45)/($C48-E$45)/(1+$C48)^4)+(估值_DCF!$D$28+估值_DCF!$D$29+估值_DCF!$D$30-估值_DCF!$D$31-估值_DCF!$D$32))/(1+估值_DCF!$D$18)^估值_DCF!$D$34/估值_DCF!$D$36 -> 15.333888 | F48: =((SUMPRODUCT($I$12:$L$12,1/(1+$C48)^$I$13:$L$13)+$L$12*(1+F$45)/($C48-F$45)/(1+$C48)^4)+(估值_DCF!$D$28+估值_DCF!$D$29+估值_DCF!$D$30-估值_DCF!$D$31-估值_DCF!$D$32))/(1+估值_DCF!$D$18)^估值_DCF!$D$34/估值_DCF!$D$36 -> 16.253472 | G48: =((SUMPRODUCT($I$12:$L$12,1/(1+$C48)^$I$13:$L$13)+$L$12*(1+G$45)/($C48-G$45)/(1+$C48)^4)+(估值_DCF!$D$28+估值_DCF!$D$29+估值_DCF!$D$30-估值_DCF!$D$31-估值_DCF!$D$32))/(1+估值_DCF!$D$18)^估值_DCF!$D$34/估值_DCF!$D$36 -> 17.340253 | H48: =((SUMPRODUCT($I$12:$L$12,1/(1+$C48)^$I$13:$L$13)+$L$12*(1+H$45)/($C48-H$45)/(1+$C48)^4)+(估值_DCF!$D$28+估值_DCF!$D$29+估值_DCF!$D$30-估值_DCF!$D$31-估值_DCF!$D$32))/(1+估值_DCF!$D$18)^估值_DCF!$D$34/估值_DCF!$D$36 -> 18.644391
C49: 0.085 | D49: =((SUMPRODUCT($I$12:$L$12,1/(1+$C49)^$I$13:$L$13)+$L$12*(1+D$45)/($C49-D$45)/(1+$C49)^4)+(估值_DCF!$D$28+估值_DCF!$D$29+估值_DCF!$D$30-估值_DCF!$D$31-估值_DCF!$D$32))/(1+估值_DCF!$D$18)^估值_DCF!$D$34/估值_DCF!$D$36 -> 13.719987 | E49: =((SUMPRODUCT($I$12:$L$12,1/(1+$C49)^$I$13:$L$13)+$L$12*(1+E$45)/($C49-E$45)/(1+$C49)^4)+(估值_DCF!$D$28+估值_DCF!$D$29+估值_DCF!$D$30-估值_DCF!$D$31-估值_DCF!$D$32))/(1+估值_DCF!$D$18)^估值_DCF!$D$34/估值_DCF!$D$36 -> 14.393706 | F49: =((SUMPRODUCT($I$12:$L$12,1/(1+$C49)^$I$13:$L$13)+$L$12*(1+F$45)/($C49-F$45)/(1+$C49)^4)+(估值_DCF!$D$28+估值_DCF!$D$29+估值_DCF!$D$30-估值_DCF!$D$31-估值_DCF!$D$32))/(1+估值_DCF!$D$18)^估值_DCF!$D$34/估值_DCF!$D$36 -> 15.171074 | G49: =((SUMPRODUCT($I$12:$L$12,1/(1+$C49)^$I$13:$L$13)+$L$12*(1+G$45)/($C49-G$45)/(1+$C49)^4)+(估值_DCF!$D$28+估值_DCF!$D$29+估值_DCF!$D$30-估值_DCF!$D$31-估值_DCF!$D$32))/(1+估值_DCF!$D$18)^估值_DCF!$D$34/估值_DCF!$D$36 -> 16.078004 | H49: =((SUMPRODUCT($I$12:$L$12,1/(1+$C49)^$I$13:$L$13)+$L$12*(1+H$45)/($C49-H$45)/(1+$C49)^4)+(估值_DCF!$D$28+估值_DCF!$D$29+估值_DCF!$D$30-估值_DCF!$D$31-估值_DCF!$D$32))/(1+估值_DCF!$D$18)^估值_DCF!$D$34/估值_DCF!$D$36 -> 17.14983
C50: 0.09 | D50: =((SUMPRODUCT($I$12:$L$12,1/(1+$C50)^$I$13:$L$13)+$L$12*(1+D$45)/($C50-D$45)/(1+$C50)^4)+(估值_DCF!$D$28+估值_DCF!$D$29+估值_DCF!$D$30-估值_DCF!$D$31-估值_DCF!$D$32))/(1+估值_DCF!$D$18)^估值_DCF!$D$34/估值_DCF!$D$36 -> 12.998518 | E50: =((SUMPRODUCT($I$12:$L$12,1/(1+$C50)^$I$13:$L$13)+$L$12*(1+E$45)/($C50-E$45)/(1+$C50)^4)+(估值_DCF!$D$28+估值_DCF!$D$29+估值_DCF!$D$30-估值_DCF!$D$31-估值_DCF!$D$32))/(1+估值_DCF!$D$18)^估值_DCF!$D$34/估值_DCF!$D$36 -> 13.579947 | F50: =((SUMPRODUCT($I$12:$L$12,1/(1+$C50)^$I$13:$L$13)+$L$12*(1+F$45)/($C50-F$45)/(1+$C50)^4)+(估值_DCF!$D$28+估值_DCF!$D$29+估值_DCF!$D$30-估值_DCF!$D$31-估值_DCF!$D$32))/(1+估值_DCF!$D$18)^估值_DCF!$D$34/估值_DCF!$D$36 -> 14.244437 | G50: =((SUMPRODUCT($I$12:$L$12,1/(1+$C50)^$I$13:$L$13)+$L$12*(1+G$45)/($C50-G$45)/(1+$C50)^4)+(估值_DCF!$D$28+估值_DCF!$D$29+估值_DCF!$D$30-估值_DCF!$D$31-估值_DCF!$D$32))/(1+估值_DCF!$D$18)^估值_DCF!$D$34/估值_DCF!$D$36 -> 15.011157 | H50: =((SUMPRODUCT($I$12:$L$12,1/(1+$C50)^$I$13:$L$13)+$L$12*(1+H$45)/($C50-H$45)/(1+$C50)^4)+(估值_DCF!$D$28+估值_DCF!$D$29+估值_DCF!$D$30-估值_DCF!$D$31-估值_DCF!$D$32))/(1+估值_DCF!$D$18)^估值_DCF!$D$34/估值_DCF!$D$36 -> 15.905663
C51: 0.095 | D51: =((SUMPRODUCT($I$12:$L$12,1/(1+$C51)^$I$13:$L$13)+$L$12*(1+D$45)/($C51-D$45)/(1+$C51)^4)+(估值_DCF!$D$28+估值_DCF!$D$29+估值_DCF!$D$30-估值_DCF!$D$31-估值_DCF!$D$32))/(1+估值_DCF!$D$18)^估值_DCF!$D$34/估值_DCF!$D$36 -> 12.362846 | E51: =((SUMPRODUCT($I$12:$L$12,1/(1+$C51)^$I$13:$L$13)+$L$12*(1+E$45)/($C51-E$45)/(1+$C51)^4)+(估值_DCF!$D$28+估值_DCF!$D$29+估值_DCF!$D$30-估值_DCF!$D$31-估值_DCF!$D$32))/(1+估值_DCF!$D$18)^估值_DCF!$D$34/估值_DCF!$D$36 -> 12.868876 | F51: =((SUMPRODUCT($I$12:$L$12,1/(1+$C51)^$I$13:$L$13)+$L$12*(1+F$45)/($C51-F$45)/(1+$C51)^4)+(估值_DCF!$D$28+估值_DCF!$D$29+估值_DCF!$D$30-估值_DCF!$D$31-估值_DCF!$D$32))/(1+估值_DCF!$D$18)^估值_DCF!$D$34/估值_DCF!$D$36 -> 13.442376 | G51: =((SUMPRODUCT($I$12:$L$12,1/(1+$C51)^$I$13:$L$13)+$L$12*(1+G$45)/($C51-G$45)/(1+$C51)^4)+(估值_DCF!$D$28+估值_DCF!$D$29+估值_DCF!$D$30-估值_DCF!$D$31-估值_DCF!$D$32))/(1+估值_DCF!$D$18)^估值_DCF!$D$34/估值_DCF!$D$36 -> 14.097805 | H51: =((SUMPRODUCT($I$12:$L$12,1/(1+$C51)^$I$13:$L$13)+$L$12*(1+H$45)/($C51-H$45)/(1+$C51)^4)+(估值_DCF!$D$28+估值_DCF!$D$29+估值_DCF!$D$30-估值_DCF!$D$31-估值_DCF!$D$32))/(1+估值_DCF!$D$18)^估值_DCF!$D$34/估值_DCF!$D$36 -> 14.85407
C52: 0.1 | D52: =((SUMPRODUCT($I$12:$L$12,1/(1+$C52)^$I$13:$L$13)+$L$12*(1+D$45)/($C52-D$45)/(1+$C52)^4)+(估值_DCF!$D$28+估值_DCF!$D$29+估值_DCF!$D$30-估值_DCF!$D$31-估值_DCF!$D$32))/(1+估值_DCF!$D$18)^估值_DCF!$D$34/估值_DCF!$D$36 -> 11.798646 | E52: =((SUMPRODUCT($I$12:$L$12,1/(1+$C52)^$I$13:$L$13)+$L$12*(1+E$45)/($C52-E$45)/(1+$C52)^4)+(估值_DCF!$D$28+估值_DCF!$D$29+估值_DCF!$D$30-估值_DCF!$D$31-估值_DCF!$D$32))/(1+估值_DCF!$D$18)^估值_DCF!$D$34/估值_DCF!$D$36 -> 12.242344 | F52: =((SUMPRODUCT($I$12:$L$12,1/(1+$C52)^$I$13:$L$13)+$L$12*(1+F$45)/($C52-F$45)/(1+$C52)^4)+(估值_DCF!$D$28+估值_DCF!$D$29+估值_DCF!$D$30-估值_DCF!$D$31-估值_DCF!$D$32))/(1+估值_DCF!$D$18)^估值_DCF!$D$34/估值_DCF!$D$36 -> 12.741505 | G52: =((SUMPRODUCT($I$12:$L$12,1/(1+$C52)^$I$13:$L$13)+$L$12*(1+G$45)/($C52-G$45)/(1+$C52)^4)+(估值_DCF!$D$28+估值_DCF!$D$29+估值_DCF!$D$30-估值_DCF!$D$31-估值_DCF!$D$32))/(1+估值_DCF!$D$18)^估值_DCF!$D$34/估值_DCF!$D$36 -> 13.307221 | H52: =((SUMPRODUCT($I$12:$L$12,1/(1+$C52)^$I$13:$L$13)+$L$12*(1+H$45)/($C52-H$45)/(1+$C52)^4)+(估值_DCF!$D$28+估值_DCF!$D$29+估值_DCF!$D$30-估值_DCF!$D$31-估值_DCF!$D$32))/(1+估值_DCF!$D$18)^估值_DCF!$D$34/估值_DCF!$D$36 -> 13.953753
A53: 注：FCFF对营运资本假设高度敏感（应收账款天数每变动10天≈影响营运资本约7–8亿）；永续价值占比高，DCF应与SOTP/PE交叉验证。

Sheet 估值_SOTP
A1: 分部加总估值 SOTP（百万元）
A2: 分部税前利润=分部毛利−按“收入×分摊系数”分摊的费用净额（含研发、财务费用、其他收益、减值）；分部净利润×目标PE + 广发基金股权 + 其他投资
A5: 项目 | B5: 百万元 | C5: 2021A | D5: 2022A | E5: 2023A | F5: 2024A | G5: 2025A | H5: 2026E | I5: 2027E | J5: 2028E | K5: 2029E | L5: 2030E | O5: 说明 / 来源
A6: 待分摊费用净额（毛利−(利润总额−权益法收益)） | C6: =利润表!C8-(利润表!C25-费用!C35) -> 5621.0651 | D6: =利润表!D8-(利润表!D25-费用!D35) -> 6629.6637 | E6: =利润表!E8-(利润表!E25-费用!E35) -> 6146.1328 | F6: =利润表!F8-(利润表!F25-费用!F35) -> 5559.6553 | G6: =利润表!G8-(利润表!G25-费用!G35) -> 5237.5915 | H6: =利润表!H8-(利润表!H25-费用!H35) -> 5640.9771 | I6: =利润表!I8-(利润表!I25-费用!I35) -> 5586.9352 | J6: =利润表!J8-(利润表!J25-费用!J35) -> 5655.3655 | ... L6: =利润表!L8-(利润表!L25-费用!L35) -> 6067.1231
A7: 加权收入合计 | C7: =分业务!C7*假设!$C$24+分业务!C17*假设!$C$25+分业务!C23*假设!$C$26+分业务!C29*假设!$C$27 -> 26390.719 | D7: =分业务!D7*假设!$C$24+分业务!D17*假设!$C$25+分业务!D23*假设!$C$26+分业务!D29*假设!$C$27 -> 31245.882 | E7: =分业务!E7*假设!$C$24+分业务!E17*假设!$C$25+分业务!E23*假设!$C$26+分业务!E29*假设!$C$27 -> 32129.174 | F7: =分业务!F7*假设!$C$24+分业务!F17*假设!$C$25+分业务!F23*假设!$C$26+分业务!F29*假设!$C$27 -> 29579.2 | G7: =分业务!G7*假设!$C$24+分业务!G17*假设!$C$25+分业务!G23*假设!$C$26+分业务!G29*假设!$C$27 -> 25578.609 | H7: =分业务!H7*假设!$C$24+分业务!H17*假设!$C$25+分业务!H23*假设!$C$26+分业务!H29*假设!$C$27 -> 27465.613 | I7: =分业务!I7*假设!$C$24+分业务!I17*假设!$C$25+分业务!I23*假设!$C$26+分业务!I29*假设!$C$27 -> 29480.879 | J7: =分业务!J7*假设!$C$24+分业务!J17*假设!$C$25+分业务!J23*假设!$C$26+分业务!J29*假设!$C$27 -> 31235.606 | ... L7: =分业务!L7*假设!$C$24+分业务!L17*假设!$C$25+分业务!L23*假设!$C$26+分业务!L29*假设!$C$27 -> 34556.385
A8: 通信系统设备
A9: 毛利 | C9: =分业务!C10 -> 3288.1865 | D9: =分业务!D10 -> 4280.115 | E9: =分业务!E10 -> 4576.4835 | F9: =分业务!F10 -> 4341.1922 | G9: =分业务!G10 -> 3509.6293 | H9: =分业务!H10 -> 2677.3322 | I9: =分业务!I10 -> 3101.0491 | J9: =分业务!J10 -> 3542.3201 | ... L9: =分业务!L10 -> 4117.2745
A10: 分摊费用净额 | C10: =C6*分业务!C7*假设!$C$24/C7 -> 4185.1551 | D10: =D6*分业务!D7*假设!$C$24/D7 -> 5103.5321 | E10: =E6*分业务!E7*假设!$C$24/E7 -> 5232.4654 | F10: =F6*分业务!F7*假设!$C$24/F7 -> 4823.0881 | G10: =G6*分业务!G7*假设!$C$24/G7 -> 4392.8095 | H10: =H6*分业务!H7*假设!$C$24/H7 -> 4582.3268 | I10: =I6*分业务!I7*假设!$C$24/I7 -> 4566.4424 | J10: =J6*分业务!J7*假设!$C$24/J7 -> 4668.0908 | ... L10: =L6*分业务!L7*假设!$C$24/L7 -> 5038.2326
A11: 分部税前利润 | C11: =C9-C10 -> -896.96865 | D11: =D9-D10 -> -823.41708 | E11: =E9-E10 -> -655.98186 | F11: =F9-F10 -> -481.89594 | G11: =G9-G10 -> -883.18022 | H11: =H9-H10 -> -1904.9946 | I11: =I9-I10 -> -1465.3932 | J11: =J9-J10 -> -1125.7707 | ... L11: =L9-L10 -> -920.95814
A12: 分部归母净利润（税率15%，少数股东按收入分摊） | C12: =C11*(1-假设!$C$16)-利润表!C28*分业务!C7/分业务!C35 -> -806.35328 | D12: =D11*(1-假设!$C$16)-利润表!D28*分业务!D7/分业务!D35 -> -702.22531 | E12: =E11*(1-假设!$C$16)-利润表!E28*分业务!E7/分业务!E35 -> -544.91577 | F12: =F11*(1-假设!$C$16)-利润表!F28*分业务!F7/分业务!F35 -> -415.46869 | G12: =G11*(1-假设!$C$16)-利润表!G28*分业务!G7/分业务!G35 -> -705.94636 | H12: =H11*(1-假设!$C$16)-利润表!H28*分业务!H7/分业务!H35 -> -1608.6875 | I12: =I11*(1-假设!$C$16)-利润表!I28*分业务!I7/分业务!I35 -> -1245.5842 | J12: =J11*(1-假设!$C$16)-利润表!J28*分业务!J7/分业务!J35 -> -964.16816 | ... L12: =L11*(1-假设!$C$16)-利润表!L28*分业务!L7/分业务!L35 -> -797.5081
A13: 分部净利率 | C13: =C12/分业务!C7 -> -0.047193156 | D13: =D12/分业务!D7 -> -0.03357393 | E13: =E12/分业务!E7 -> -0.022909902 | F13: =F12/分业务!F7 -> -0.018619687 | G13: =G12/分业务!G7 -> -0.037842678 | H13: =H12/分业务!H7 -> -0.08291794 | I13: =I12/分业务!I7 -> -0.059446484 | J13: =J12/分业务!J7 -> -0.043005309 | ... L13: =L12/分业务!L7 -> -0.031960181
A14: 光纤及线缆
A15: 毛利 | C15: =分业务!C20 -> 1035.2895 | D15: =分业务!D20 -> 1134.6603 | E15: =分业务!E20 -> 1144.0746 | F15: =分业务!F20 -> 1191.1576 | G15: =分业务!G20 -> 1171.2275 | H15: =分业务!H20 -> 2559.7537 | I15: =分业务!I20 -> 2363.6765 | J15: =分业务!J20 -> 2003.6361 | ... L15: =分业务!L20 -> 1916.9446
A16: 分摊费用净额 | C16: =C6*分业务!C17*假设!$C$25/C7 -> 623.00105 | D16: =D6*分业务!D17*假设!$C$25/D7 -> 690.48426 | E16: =E6*分业务!E17*假设!$C$25/E7 -> 515.2223 | F16: =F6*分业务!F17*假设!$C$25/F7 -> 441.57361 | G16: =G6*分业务!G17*假设!$C$25/G7 -> 476.49701 | H16: =H6*分业务!H17*假设!$C$25/H7 -> 657.1632 | I16: =I6*分业务!I17*假设!$C$25/I7 -> 622.14091 | J16: =J6*分业务!J17*假设!$C$25/J7 -> 585.11051 | ... L16: =L6*分业务!L17*假设!$C$25/L7 -> 601.00215
A17: 分部税前利润 | C17: =C15-C16 -> 412.28845 | D17: =D15-D16 -> 444.17604 | E17: =E15-E16 -> 628.8523 | F17: =F15-F16 -> 749.58399 | G17: =G15-G16 -> 694.73049 | H17: =H15-H16 -> 1902.5905 | I17: =I15-I16 -> 1741.5356 | J17: =J15-J16 -> 1418.5256 | ... L17: =L15-L16 -> 1315.9424
A18: 分部归母净利润（税率15%，少数股东按收入分摊） | C18: =C17*(1-假设!$C$16)-利润表!C28*分业务!C17/分业务!C35 -> 335.40457 | D18: =D17*(1-假设!$C$16)-利润表!D28*分业务!D17/分业务!D35 -> 376.82745 | E18: =E17*(1-假设!$C$16)-利润表!E28*分业务!E17/分业务!E35 -> 537.3936 | F18: =F17*(1-假设!$C$16)-利润表!F28*分业务!F17/分业务!F35 -> 635.91302 | G18: =G17*(1-假设!$C$16)-利润表!G28*分业务!G17/分业务!G35 -> 601.6871 | H18: =H17*(1-假设!$C$16)-利润表!H28*分业务!H17/分业务!H35 -> 1620.6844 | I18: =I17*(1-假设!$C$16)-利润表!I28*分业务!I17/分业务!I35 -> 1480.3053 | J18: =J17*(1-假设!$C$16)-利润表!J28*分业务!J17/分业务!J35 -> 1203.6529 | ... L18: =L17*(1-假设!$C$16)-利润表!L28*分业务!L17/分业务!L35 -> 1114.5196
A19: 分部净利率 | C19: =C18/分业务!C17 -> 0.057334707 | D19: =D18/分业务!D17 -> 0.057897187 | E19: =E18/分业务!E17 -> 0.099763166 | F19: =F18/分业务!F17 -> 0.13533996 | G19: =G18/分业务!G17 -> 0.12928115 | H19: =H18/分业务!H17 -> 0.25325631 | I19: =I18/分业务!I17 -> 0.22545805 | J19: =J18/分业务!J17 -> 0.18622763 | ... L19: =L18/分业务!L17 -> 0.16279318
A20: 数据网络产品
A21: 毛利 | C21: =分业务!C26 -> 1314.2888 | D21: =分业务!D26 -> 1302.7849 | E21: =分业务!E26 -> 652.2357 | F21: =分业务!F26 -> 502.5818 | G21: =分业务!G26 -> 557.6938 | H21: =分业务!H26 -> 536.61598 | I21: =分业务!I26 -> 612.66213 | J21: =分业务!J26 -> 666.9738 | ... L21: =分业务!L26 -> 735.33862
A22: 分摊费用净额 | C22: =C6*分业务!C23*假设!$C$26/C7 -> 776.7018 | D22: =D6*分业务!D23*假设!$C$26/D7 -> 797.18752 | E22: =E6*分业务!E23*假设!$C$26/E7 -> 362.04846 | F22: =F6*分业务!F23*假设!$C$26/F7 -> 258.11586 | G22: =G6*分业务!G23*假设!$C$26/G7 -> 348.82511 | H22: =H6*分业务!H23*假设!$C$26/H7 -> 377.86951 | I22: =I6*分业务!I23*假设!$C$26/I7 -> 376.55964 | J22: =J6*分业务!J23*假设!$C$26/J7 -> 381.34422 | ... L22: =L6*分业务!L23*假设!$C$26/L7 -> 407.69888
A23: 分部税前利润 | C23: =C21-C22 -> 537.587 | D23: =D21-D22 -> 505.59738 | E23: =E21-E22 -> 290.18724 | F23: =F21-F22 -> 244.46594 | G23: =G21-G22 -> 208.86869 | H23: =H21-H22 -> 158.74647 | I23: =I21-I22 -> 236.10249 | J23: =J21-J22 -> 285.62958 | ... L23: =L21-L22 -> 327.63973
A24: 分部归母净利润（税率15%，少数股东按收入分摊） | C24: =C23*(1-假设!$C$16)-利润表!C28*分业务!C23/分业务!C35 -> 449.13591 | D24: =D23*(1-假设!$C$16)-利润表!D28*分业务!D23/分业务!D35 -> 429.41036 | E24: =E23*(1-假设!$C$16)-利润表!E28*分业务!E23/分业务!E35 -> 247.49922 | F24: =F23*(1-假设!$C$16)-利润表!F28*分业务!F23/分业务!F35 -> 207.49566 | G24: =G23*(1-假设!$C$16)-利润表!G28*分业务!G23/分业务!G35 -> 180.94436 | H24: =H23*(1-假设!$C$16)-利润表!H28*分业务!H23/分业务!H35 -> 135.76886 | I24: =I23*(1-假设!$C$16)-利润表!I28*分业务!I23/分业务!I35 -> 200.68712 | J24: =J23*(1-假设!$C$16)-利润表!J28*分业务!J23/分业务!J35 -> 242.21654 | ... L24: =L23*(1-假设!$C$16)-利润表!L28*分业务!L23/分业务!L35 -> 277.35429
A25: 分部净利率 | C25: =C24/分业务!C23 -> 0.14779921 | D25: =D24/分业务!D23 -> 0.13714879 | E25: =E24/分业务!E23 -> 0.1569245 | F25: =F24/分业务!F23 -> 0.18131636 | G25: =G24/分业务!G23 -> 0.1274598 | H25: =H24/分业务!H23 -> 0.088553271 | I25: =I24/分业务!I23 -> 0.12119932 | J25: =J24/分业务!J23 -> 0.13799985 | ... L25: =L24/分业务!L23 -> 0.14332802
A26: 其他业务
A27: 毛利 | C27: =分业务!C32 -> 72.1698 | D27: =分业务!D32 -> 73.6198 | E27: =分业务!E32 -> 28.655 | F27: =分业务!F32 -> 31.2353 | G27: =分业务!G32 -> 18.7758 | H27: =分业务!H32 -> 27.598251 | I27: =分业务!I32 -> 27.598251 | J27: =分业务!J32 -> 27.598251 | ... L27: =分业务!L32 -> 27.598251
A28: 分摊费用净额 | C28: =C6*分业务!C29*假设!$C$27/C7 -> 36.207107 | D28: =D6*分业务!D29*假设!$C$27/D7 -> 38.459833 | E28: =E6*分业务!E29*假设!$C$27/E7 -> 36.396687 | F28: =F6*分业务!F29*假设!$C$27/F7 -> 36.877685 | G28: =G6*分业务!G29*假设!$C$27/G7 -> 19.459857 | H28: =H6*分业务!H29*假设!$C$27/H7 -> 23.617578 | I28: =I6*分业务!I29*假设!$C$27/I7 -> 21.792323 | J28: =J6*分业务!J29*假设!$C$27/J7 -> 20.820016 | ... L28: =L6*分业务!L29*假设!$C$27/L7 -> 20.189465
A29: 分部税前利润 | C29: =C27-C28 -> 35.962693 | D29: =D27-D28 -> 35.159967 | E29: =E27-E28 -> -7.7416871 | F29: =F27-F28 -> -5.642385 | G29: =G27-G28 -> -0.68405693 | H29: =H27-H28 -> 3.9806727 | I29: =I27-I28 -> 5.8059281 | J29: =J27-J28 -> 6.7782349 | ... L29: =L27-L28 -> 7.4087857
A30: 分部归母净利润（税率15%，少数股东按收入分摊） | C30: =C29*(1-假设!$C$16)-利润表!C28*分业务!C29/分业务!C35 -> 29.69417 | D30: =D29*(1-假设!$C$16)-利润表!D28*分业务!D29/分业务!D35 -> 29.845746 | E30: =E29*(1-假设!$C$16)-利润表!E28*分业务!E29/分业务!E35 -> -6.3777501 | F30: =F29*(1-假设!$C$16)-利润表!F28*分业务!F29/分业务!F35 -> -4.8990307 | G30: =G29*(1-假设!$C$16)-利润表!G28*分业务!G29/分业务!G35 -> -0.12542792 | H30: =H29*(1-假设!$C$16)-利润表!H28*分业务!H29/分业务!H35 -> 3.5087293 | I30: =I29*(1-假设!$C$16)-利润表!I28*分业务!I29/分业务!I35 -> 4.9350389 | J30: =J29*(1-假设!$C$16)-利润表!J28*分业务!J29/分业务!J35 -> 5.6869942 | ... L30: =L29*(1-假设!$C$16)-利润表!L28*分业务!L29/分业务!L35 -> 6.1620409
A31: 分部净利率 | C31: =C30/分业务!C29 -> 0.087340314 | D31: =D30/分业务!D29 -> 0.082327279 | E31: =E30/分业务!E29 -> -0.016760155 | F31: =F30/分业务!F29 -> -0.012484696 | G31: =G30/分业务!G29 -> -0.00065990176 | H31: =H30/分业务!H29 -> 0.015256312 | I31: =I30/分业务!I29 -> 0.02145805 | J31: =J30/分业务!J29 -> 0.024727629 | ... L31: =L30/分业务!L29 -> 0.02679318
A32: 核对：分部净利润合计+广发/联营收益 vs 归母净利润（差异来自税率口径） | C32: =C12+C18+C24+C30+费用!C35-利润表!C29 -> 122.07807 | D32: =D12+D18+D24+D30+费用!D35-利润表!D29 -> 106.94616 | E32: =E12+E18+E24+E30+费用!E35-利润表!E29 -> 54.1525 | F32: =F12+F18+F24+F30+费用!F35-利润表!F29 -> 5.96126 | G32: =G12+G18+G24+G30+费用!G35-利润表!G29 -> 83.025365 | H32: =H12+H18+H24+H30+费用!H35-利润表!H29 -> 86.068451 | I32: =I12+I18+I24+I30+费用!I35-利润表!I29 -> 83.052639 | J32: =J12+J18+J24+J30+费用!J35-利润表!J29 -> 86.056086 | ... L32: =L12+L18+L24+L30+费用!L35-利润表!L29 -> 92.512765
A34: SOTP（基于2027E）
A35: 组成部分 | C35: 2027E净利润 | D35: PE(x) | E35: 价值 | F35: 每股(元) | G35: 占比 | H35: P/S下限价值
A36: 通信系统设备 | C36: =估值_SOTP!I12 -> -1245.5842 | D36: =假设!$C$20 -> 25 | E36: =MAX(C36*D36,H36) -> 8381.2139 | F36: =E36/估值_SOTP!$E$43 -> 6.1709722 | G36: =E36/估值_SOTP!$E$42 -> 0.16325833 | H36: =分业务!I7*假设!$C$28 -> 8381.2139
A37: 光纤及线缆 | C37: =估值_SOTP!I18 -> 1480.3053 | D37: =假设!$C$21 -> 18 | E37: =MAX(C37*D37,H37) -> 26645.495 | F37: =E37/估值_SOTP!$E$43 -> 19.618711 | G37: =E37/估值_SOTP!$E$42 -> 0.51902972 | H37: =分业务!I17*假设!$C$29 -> 6565.7682
A38: 数据网络产品 | C38: =估值_SOTP!I24 -> 200.68712 | D38: =假设!$C$22 -> 25 | E38: =MAX(C38*D38,H38) -> 5017.178 | F38: =E38/估值_SOTP!$E$43 -> 3.694079 | G38: =E38/估值_SOTP!$E$42 -> 0.097730009 | H38: =分业务!I23*假设!$C$30 -> 1655.8436
A39: 其他业务 | C39: =估值_SOTP!I30 -> 4.9350389 | D39: =假设!$C$23 -> 10 | E39: =MAX(C39*D39,H39) -> 49.350389 | F39: =E39/估值_SOTP!$E$43 -> 0.036336011 | G39: =E39/估值_SOTP!$E$42 -> 0.00096130014 | H39: =分业务!I29*假设!$C$31 -> 45.997085
A40: 广发基金14.187%股权 | C40: =费用!I31 -> 668.56658 | D40: =假设!$C$19 -> 15 | E40: =MAX(0,C40*D40) -> 10028.499 | F40: =E40/估值_SOTP!$E$43 -> 7.3838453 | G40: =E40/估值_SOTP!$E$42 -> 0.19534592
A41: 其他联营企业+金融资产（2026E账面） | E41: =资产负债表!H15-费用!H33+资产负债表!H16 -> 1215.392 | F41: =E41/估值_SOTP!$E$43 -> 0.89487637 | G41: =E41/估值_SOTP!$E$42 -> 0.023674717
A42: 股权价值合计 | E42: =E36+E37+E38+E39+E40+E41 -> 51337.128
A43: 总股本（2026E末，百万股） | E43: =融资!H35 -> 1358.1675
A44: SOTP每股价值（元） | E44: =E42/E43 -> 37.79882
A45: 相对现价空间 | E45: =E44/假设!$C$8-1 -> 0.058790466
A46: 注：PE法下分部净利润已扣除分摊的财务费用，故不再单独扣减净负债；分部价值=MAX(净利润×PE, 收入×P/S下限)。
A48: 2026H1归母净利润来源拆解（估算，百万元）
A49: 广发基金权益法收益（14.187%） | E49: 348.8 | H49: 2026半年报 长期股权投资附注：348,797,214.65元
A50: 其他联营企业（藤仓烽火、南京华信藤仓等） | E50: 51.29 | H50: 权益法合计400.09−广发基金348.80
A51: 武汉烽火光纤（原烽火藤仓光纤）归母净利润 | E51: 452 | H51: 子公司净利4.88亿；2026年4月前持股60%，估算归母约4.52亿（据少数股权收购资本公积倒推）
A52: 归母净利润（报表） | E52: =历史报表!K34 -> 192.7997
A53: 其余业务合计（通信系统设备/服务器/烽火星空/烽火国际/总部等，轧差） | E53: =E52-E49-E50-E51 -> -659.2903 | H53: 同期子公司：烽火星空净利−3.75亿、烽火国际−1.72亿、烽火超微−0.28亿（2026半年报 主要子公司表）
A55: 市场隐含预期（现价反推）
A56: 当前市值 | E56: =假设!$C$8*融资!G35 -> 48486.58
A57: 减：广发基金股权价值 | E57: =E40 -> 10028.499
A58: 减：其他联营企业及金融资产 | E58: =E41 -> 1215.392
A59: 市场对主业的定价（市值−广发基金−其他投资） | E59: =E56-E57-E58 -> 37242.689
A60: 主业2027E归母净利润（扣除权益法收益） | E60: =利润表!I29-费用!I35 -> 357.29057
A61: 隐含主业PE（2027E） | E61: =IF(E60<=0,"n.m.",E59/E60) -> 104.23642
A62: 隐含主业市销率 P/S（2027E） | E62: =E59/利润表!I6 -> 1.2665586

Sheet 估值_相对
A1: 相对估值与一致预期对比
A2: 可比公司PE为网络检索所得（PE TTM，日期见表）——使用前请以Wind/Choice最新数据更新；蓝色为输入
A5: 可比公司（PE TTM）
A6: 公司 | B6: 代码 | C6: PE(TTM) | D6: 日期 | I6: 来源
A7: 长飞光纤 | B7: 601869.SH | C7: 109.42 | D7: 2026-09-18 | I7: 同花顺“昨日估值”：PE(TTM)109.42倍，历史分位90.6%；http://stock.10jqka.com.cn/20260921/c680111695.shtml
A8: 亨通光电 | B8: 600487.SH | C8: 43 | D8: 2026-09-22 | I8: PE(TTM)43倍，历史分位96.8%；http://stock.10jqka.com.cn/20260923/c680199516.shtml
A9: 中天科技 | B9: 600522.SH | C9: 33.82 | D9: 2026-09-22 | I9: PE(TTM)33.82倍，历史分位87.1%；http://stock.10jqka.com.cn/20260923/c680199594.shtml
A10: 中兴通讯 | B10: 000063.SZ | C10: 36.66 | D10: 2026-08-10 | I10: PE(TTM)36.66倍，历史分位87.8%；https://stock.10jqka.com.cn/20260811/c678839945.shtml
A11: 中位数 | C11: =MEDIAN(C7:C10) -> 39.83
A12: 中位数（剔除长飞光纤） | C12: =MEDIAN(C8:C10) -> 36.66
A14: 烽火通信估值指标（现价）
A15: 指标 | C15: 2025A | D15: 2026E | E15: 2027E | F15: 2028E
A16: 归母净利润（模型） | C16: =利润表!G29 -> 435.8343 | D16: =利润表!H29 -> 751.93618 | E16: =利润表!I29 -> 1075.8572 | F16: =利润表!J29 -> 1153.3271
A17: EPS（期末股本摊薄，元） | C17: =利润表!G33 -> 0.32089878 | D17: =利润表!H33 -> 0.55364024 | E17: =利润表!I33 -> 0.73928836 | F17: =利润表!J33 -> 0.79252277
A18: PE（现价） | C18: =假设!$C$8/利润表!G33 -> 111.25003 | D18: =假设!$C$8/利润表!H33 -> 64.482307 | E18: =假设!$C$8/利润表!I33 -> 48.289682 | F18: =假设!$C$8/利润表!J33 -> 45.046024
A19: PE（剔除广发基金股权价值后） | C19: =IF(利润表!G29-费用!G31<=0,"n.m.",(假设!$C$8*融资!G35-估值_SOTP!$E$40)/(利润表!G29-费用!G31)) -> 850.79829 | D19: =IF(利润表!H29-费用!H31<=0,"n.m.",(假设!$C$8*融资!H35-估值_SOTP!$E$40)/(利润表!H29-费用!H31)) -> 333.81984 | E19: =IF(利润表!I29-费用!I31<=0,"n.m.",(假设!$C$8*融资!I35-估值_SOTP!$E$40)/(利润表!I29-费用!I31)) -> 102.93462 | F19: =IF(利润表!J29-费用!J31<=0,"n.m.",(假设!$C$8*融资!J35-估值_SOTP!$E$40)/(利润表!J29-费用!J31)) -> 92.890123
A20: PB（现价） | C20: =假设!$C$8/利润表!G35 -> 2.7646684 | D20: =假设!$C$8/利润表!H35 -> 2.6702404 | E20: =假设!$C$8/利润表!I35 -> 2.3734489 | F20: =假设!$C$8/利润表!J35 -> 2.2866822
A21: 股息率 | C21: =利润表!G34/假设!$C$8 -> 0.0027170868 | D21: =利润表!H34/假设!$C$8 -> 0.004652439 | E21: =利润表!I34/假设!$C$8 -> 0.0062125073 | F21: =利润表!J34/假设!$C$8 -> 0.0066598552
A22: PE(TTM)：2025H2+2026H1归母净利润 | C22: =假设!$C$8*融资!G35/(利润表!G29-历史报表!J34+历史报表!K34) -> 141.7466
A24: 模型 vs Wind一致预期（2026-10-06，6家机构）
A25: 项目 | D25: 2026E | E25: 2027E | F25: 2028E
A26: 一致预期：营业收入 | D26: 27985.3 | E26: 31094.94 | F26: 34918.24
A27: 模型：营业收入 | D27: =利润表!H6 -> 27563.516 | E27: =利润表!I6 -> 29404.632 | F27: =利润表!J6 -> 30868.269
A28: 差异 | D28: =D27/D26-1 -> -0.015071618 | E28: =E27/E26-1 -> -0.054359585 | F28: =F27/F26-1 -> -0.1159844
A29: 一致预期：归母净利润 | D29: 1292.81 | E29: 1631.12 | F29: 2156.96
A30: 一致预期最高值 | D30: 1949 | E30: 2731 | F30: 4957
A31: 一致预期最低值 | D31: 609 | E31: 721 | F31: 856
A32: 模型：归母净利润 | D32: =利润表!H29 -> 751.93618 | E32: =利润表!I29 -> 1075.8572 | F32: =利润表!J29 -> 1153.3271
A33: 差异 | D33: =D32/D29-1 -> -0.4183707 | E33: =E32/E29-1 -> -0.34041815 | F33: =F32/F29-1 -> -0.46529973
A34: 模型：其中广发基金权益法收益 | D34: =费用!H31 -> 636.73008 | E34: =费用!I31 -> 668.56658 | F34: =费用!J31 -> 701.99491
A35: 来源：Wind盈利预测（2026-10-06导出）。6家机构中多数为中报前（5–6月）预测；中报后唯一更新（2026-09-06）为2026E 6.09亿、2027E 7.21亿。
A37: 目标PE法
A38: 目标PE（2027E） | C38: =假设!$C$33 -> 30
A39: 目标PE法每股价值（元） | C39: =IF(利润表!I33<=0,"n.m.",假设!$C$33*利润表!I33) -> 22.178651
A40: 相对现价空间 | C40: =IF(ISNUMBER(C39),C39/假设!$C$8-1,"n.m.") -> -0.37874927
A42: PE × EPS 矩阵（每股价值，元）
A43: PE \ EPS年份 | D43: 2026E | E43: 2027E | F43: 2028E
A44: 20 | D44: =$A44*利润表!H33 -> 11.072805 | E44: =$A44*利润表!I33 -> 14.785767 | F44: =$A44*利润表!J33 -> 15.850455
A45: 25 | D45: =$A45*利润表!H33 -> 13.841006 | E45: =$A45*利润表!I33 -> 18.482209 | F45: =$A45*利润表!J33 -> 19.813069
A46: 30 | D46: =$A46*利润表!H33 -> 16.609207 | E46: =$A46*利润表!I33 -> 22.178651 | F46: =$A46*利润表!J33 -> 23.775683
A47: 35 | D47: =$A47*利润表!H33 -> 19.377408 | E47: =$A47*利润表!I33 -> 25.875093 | F47: =$A47*利润表!J33 -> 27.738297
A48: 40 | D48: =$A48*利润表!H33 -> 22.14561 | E48: =$A48*利润表!I33 -> 29.571535 | F48: =$A48*利润表!J33 -> 31.700911
A49: 45 | D49: =$A49*利润表!H33 -> 24.913811 | E49: =$A49*利润表!I33 -> 33.267976 | F49: =$A49*利润表!J33 -> 35.663525

Sheet 情景分析
A1: 情景分析
A2: “当前”列随假设表情景开关实时计算；基准/乐观/悲观三列为模型分别切换情景后重算得到的快照值（蓝色）
A5: 指标 | C5: 当前情景 | D5: 基准 | E5: 乐观 | F5: 悲观
A6: 当前情景名称 | C6: =假设!$D$5 -> 基准 | D6: 基准 | E6: 乐观 | F6: 悲观
A7: 营业收入 2026E | C7: =利润表!H6 -> 27563.516 | D7: 27563.516 | E7: 28786.062 | F7: 26336.082
A8: 营业收入 2027E | C8: =利润表!I6 -> 29404.632 | D8: 29404.632 | E8: 32819.954 | F8: 25322.755
A9: 营业收入 2028E | C9: =利润表!J6 -> 30868.269 | D9: 30868.269 | E9: 35808.46 | F9: 25374.674
A10: 归母净利润 2026E | C10: =利润表!H29 -> 751.93618 | D10: 751.93618 | E10: 1681.2058 | F10: -30.034868
A11: 归母净利润 2027E | C11: =利润表!I29 -> 1075.8572 | D11: 1075.8572 | E11: 2779.1106 | F11: -575.92034
A12: 归母净利润 2028E | C12: =利润表!J29 -> 1153.3271 | D12: 1153.3271 | E12: 3171.3813 | F12: -779.77903
A13: EPS 2026E（元） | C13: =利润表!H33 -> 0.55364024 | D13: 0.55364024 | E13: 1.2378486 | F13: -0.022114259
A14: EPS 2027E（元） | C14: =利润表!I33 -> 0.73928836 | D14: 0.73928836 | E14: 1.9096997 | F14: -0.4240422
A15: 扣除广发基金后归母净利润 2027E | C15: =费用!I47 -> 407.29057 | D15: 407.29057 | E15: 1991.5966 | F15: -1057.3742
A16: 光纤及线缆毛利 2027E | C16: =分业务!I20 -> 2363.6765 | D16: 2363.6765 | E16: 3524.5777 | F16: 1405.1473
A17: FCFF 2027E | C17: =估值_DCF!I12 -> 262.84832 | D17: 262.84832 | E17: 1591.2045 | F17: -319.11976
A18: 净负债 2026E末 | C18: =融资!H19 -> 5739.031 | D18: 5739.031 | E18: 3775.3693 | F18: 8122.2335
A19: DCF每股价值（元） | C19: =估值_DCF!$D$37 -> 15.647377 | D19: 15.647377 | E19: 41.123179 | F19: -8.8970622
A20: SOTP每股价值（元） | C20: =估值_SOTP!$E$44 -> 37.79882 | D20: 37.79882 | E20: 53.097085 | F20: 22.533701
A21: 目标PE法每股价值（元） | C21: =估值_相对!$C$39 -> 22.178651 | D21: 22.178651 | E21: 57.290992 | F21: n.m.
A23: 情景设定要点
A24: 基准：通信系统设备收入4%–8%增长、毛利率2026E 13.8%（延续下半年低于上半年的季节性）后逐步修复至16.5%（存储涨价压制缓解、服务器规模效应）；光纤2026年量价齐升（价+25%）后2027–2028年价格回落5%–8%、毛利率由40%回落至28%；广发基金2026年净利润约45亿元、此后+5%；应收账款天数由217天改善至170天；2027年完成29亿元定增。
A25: 乐观：AI算力（昇腾超节点、数据中心光互联）与海外拉动通信系统设备增长8%–12%、毛利率由14.8%修复至18%；光纤价格2027年再涨8%、毛利率维持40%以上；广发基金2026年利润+80%、2027年再+12%；研发资本化率维持20%；营运资本显著改善。
A26: 悲观：通信系统设备收入停滞、毛利率13%–14%；光纤价格2027年回落20%、毛利率降至28%后继续下探至22%；广发基金2027年利润回落15%；研发资本化率回归10%–15%；应收账款天数维持215天、减值率上升；定增未落地。

Sheet 季度数据
A1: 季度数据（单季，百万元）
A2: 来源：Wind 单季利润表；用于季节性分析及2026E下半年隐含值校验。
A5: 项目 | B5: 2021Q1 | C5: 2021Q2 | D5: 2021Q3 | E5: 2021Q4 | F5: 2022Q1 | G5: 2022Q2 | H5: 2022Q3 | I5: 2022Q4 | J5: 2023Q1 | K5: 2023Q2 | L5: 2023Q3 | M5: 2023Q4 | N5: 2024Q1 | O5: 2024Q2 | P5: 2024Q3 | Q5: 2024Q4 | R5: 2025Q1 | S5: 2025Q2 | T5: 2025Q3 | U5: 2025Q4 | V5: 2026Q1 | W5: 2026Q2
A6: 营业收入 | B6: 4029.5657 | C6: 7979.0636 | D6: 6531.067 | E6: 7775.2841 | F6: 4538.7189 | G6: 9465.4281 | H6: 7523.6788 | I6: 9390.0347 | J6: 5016.2508 | K6: 9878.2522 | L6: 7664.7455 | M6: 8570.3259 | N6: 5058.8093 | O6: 8790.629 | P6: 7304.4004 | Q6: 7394.9922 | R6: 4048.5401 | S6: 7068.2808 | T6: 5954.8119 | U6: 7846.9217 | V6: 4510.1774 | W6: 7866.181
A7: 营业成本 | B7: 3075.4809 | C7: 6508.7154 | D7: 4931.1539 | E7: 6089.6953 | F7: 3462.4554 | G7: 7586.4888 | H7: 5788.3543 | I7: 7289.382 | J7: 3832.7275 | K7: 7951.6826 | L7: 5818.6131 | M7: 7125.1022 | N7: 3802.5821 | O7: 7092.2537 | P7: 5577.8108 | Q7: 6010.0173 | R7: 2998.6181 | S7: 5647.9801 | T7: 4597.927 | U7: 6416.7031 | V7: 3317.4836 | W7: 6410.3778
A8: 销售费用 | B8: 310.6839 | C8: 450.6548 | D8: 506.8671 | E8: 149.7396 | F8: 349.1421 | G8: 536.8722 | H8: 584.3303 | I8: 175.5904 | J8: 379.6342 | K8: 582.7553 | L8: 593.0662 | M8: 231.2181 | N8: 380.3841 | O8: 603.7779 | P8: 461.4869 | Q8: 435.7093 | R8: 369.6816 | S8: 593.6688 | T8: 517.5002 | U8: 494.808 | V8: 390.4067 | W8: 671.1109
A9: 管理费用 | B9: 80.3105 | C9: 60.6217 | D9: 85.7817 | E9: 67.6887 | F9: 88.243 | G9: 72.1725 | H9: 82.3589 | I9: 85.8579 | J9: 93.7648 | K9: 75.4461 | L9: 76.5619 | M9: 95.2401 | N9: 94.1008 | O9: 73.809 | P9: 75.8956 | Q9: 195.7484 | R9: 85.5122 | S9: 86.0402 | T9: 79.6612 | U9: 233.1763 | V9: 92.2349 | W9: 97.8856
A10: 研发费用 | B10: 555.4353 | C10: 838.0294 | D10: 877.3268 | E10: 1189.6395 | F10: 649.1345 | G10: 1071.8439 | H10: 1002.6944 | I10: 1378.1092 | J10: 712.4591 | K10: 1185.8138 | L10: 1018.2695 | M10: 661.7888 | N10: 728.6759 | O10: 861.2194 | P10: 1224.8669 | Q10: 66.4882 | R10: 691.6827 | S10: 747.4744 | T10: 934.6398 | U10: 196.3013 | V10: 632.6666 | W10: 637.3018
A11: 财务费用 | B11: 45.8105 | C11: 81.8479 | D11: 119.6178 | E11: 117.9983 | F11: 35.9651 | G11: 113.0079 | H11: 64.45 | I11: 169.1114 | J11: 12.3105 | K11: 104.5833 | L11: 98.8119 | M11: 99.8871 | N11: 93.6555 | O11: 169.9363 | P11: 41.006 | Q11: 253.0467 | R11: 102.6094 | S11: 16.2669 | T11: 88.93 | U11: 216.3949 | V11: 183.7154 | W11: 191.9649
A12: 投资净收益 | B12: 54.27 | C12: 100.8695 | D12: 94.7707 | E12: 152.6574 | F12: 47.6243 | G12: 94.521 | H12: 105.6035 | I12: 141.8969 | J12: 64.4272 | K12: 136.4804 | L12: 66.3472 | M12: 34.5931 | N12: 38.1126 | O12: 75.1205 | P12: 117.9204 | Q12: 56.6318 | R12: 95.8146 | S12: 114.9307 | T12: 135.8313 | U12: 98.576 | V12: 142.1435 | W12: 246.7923
A13: 其中：权益法投资收益 | B13: 62.006 | C13: 99.976 | D13: 87.4589 | E13: 152.7313 | F13: 47.6243 | G13: 94.521 | H13: 67.2871 | I13: 169.4487 | J13: 93.9719 | K13: 101.219 | L13: 66.3472 | M13: 64.3822 | N13: 41.6377 | O13: 71.5954 | P13: 117.7004 | Q13: 54.693 | R13: 79.9825 | S13: 114.9307 | T13: 139.1696 | U13: 108.2172 | V13: 142.1435 | W13: 257.9451
A14: 资产减值损失 | B14: 1.1215 | C14: -8.8003 | D14: -1.8119 | E14: -230.3102 | G14: -6.0618 | H14: -5.8879 | I14: -110.399 | J14: -5.0789 | K14: -0.9238 | L14: -7.8922 | M14: -133.9805 | N14: 0.8942 | O14: 24.5733 | P14: -17.8803 | Q14: -114.8114 | R14: -6.9144 | S14: 24.7391 | T14: 16.5309 | U14: -328.5167 | V14: -4.2613 | W14: -39.7837
A15: 信用减值损失 | C15: -34.227 | D15: -2.441 | E15: 19.2394 | F15: -0.6077 | G15: -39.5626 | H15: -0.4815 | I15: -192.2394 | J15: -0.9026 | K15: -43.4398 | L15: -15.3989 | M15: -231.9389 | N15: 15.9791 | O15: -73.6348 | P15: 1.3234 | Q15: -289.1126 | R15: 19.9282 | S15: -35.0099 | T15: 22.7857 | U15: -89.1426 | V15: -10.6306 | W15: 14.7701
A16: 营业利润 | B16: 33.4888 | C16: 132.4708 | D16: 138.5864 | E16: 189.1236 | F16: 37.0882 | G16: 168.3005 | H16: 119.1032 | I16: 216.8594 | J16: 44.1095 | K16: 162.8467 | L16: 137.0521 | M16: 222.2123 | N16: 48.9095 | O16: 168.4214 | P16: 176.843 | Q16: 409.1806 | R16: 68.1205 | S16: 226.4461 | T16: 227.1039 | U16: -48.5118 | V16: 43.1271 | W16: 196.8236
A17: 归属于母公司所有者的净利润 | B17: 30.1002 | C17: 120.103 | D17: 133.6946 | E17: 4.0776 | F17: 33.122 | G17: 142.8649 | H17: 125.5869 | I17: 104.2195 | J17: 37.3904 | K17: 162.3349 | L17: 128.0062 | M17: 177.6358 | N17: 41.4765 | O17: 175.5842 | P17: 176.4537 | Q17: 309.1916 | R17: 55.1969 | S17: 231.3719 | T17: 226.1162 | U17: -76.8505 | V17: 38.3925 | W17: 154.4072
A18: 毛利 | B18: =B6-B7 -> 954.0848 | C18: =C6-C7 -> 1470.3482 | D18: =D6-D7 -> 1599.9131 | E18: =E6-E7 -> 1685.5888 | F18: =F6-F7 -> 1076.2635 | G18: =G6-G7 -> 1878.9393 | H18: =H6-H7 -> 1735.3245 | I18: =I6-I7 -> 2100.6527 | ... W18: =W6-W7 -> 1455.8032
A19: 毛利率 | B19: =IF(B6=0,0,B18/B6) -> 0.23677112 | C19: =IF(C6=0,0,C18/C6) -> 0.18427578 | D19: =IF(D6=0,0,D18/D6) -> 0.24496964 | E19: =IF(E6=0,0,E18/E6) -> 0.21678807 | F19: =IF(F6=0,0,F18/F6) -> 0.23712936 | G19: =IF(G6=0,0,G18/G6) -> 0.19850547 | H19: =IF(H6=0,0,H18/H6) -> 0.2306484 | I19: =IF(I6=0,0,I18/I6) -> 0.22371086 | ... W19: =IF(W6=0,0,W18/W6) -> 0.18507115
A20: 期间费用率（销售+管理+研发+财务） | B20: =(B8+B9+B10+B11)/B6 -> 0.24623999 | C20: =(C8+C9+C10+C11)/C6 -> 0.17936363 | D20: =(D8+D9+D10+D11)/D6 -> 0.24338954 | E20: =(E8+E9+E10+E11)/E6 -> 0.19614281 | F20: =(F8+F9+F10+F11)/F6 -> 0.24731311 | G20: =(G8+G9+G10+G11)/G6 -> 0.18952091 | H20: =(H8+H9+H10+H11)/H6 -> 0.23045024 | I20: =(I8+I9+I10+I11)/I6 -> 0.19261578 | ... W20: =(W8+W9+W10+W11)/W6 -> 0.20318159
A21: 核心经营利润（营业利润−投资收益） | B21: =B16-B12 -> -20.7812 | C21: =C16-C12 -> 31.6013 | D21: =D16-D12 -> 43.8157 | E21: =E16-E12 -> 36.4662 | F21: =F16-F12 -> -10.5361 | G21: =G16-G12 -> 73.7795 | H21: =H16-H12 -> 13.4997 | I21: =I16-I12 -> 74.9625 | ... W21: =W16-W12 -> -49.9687
A22: 收入同比 | F22: =F6/B6-1 -> 0.12635436 | G22: =G6/C6-1 -> 0.18628307 | H22: =H6/D6-1 -> 0.1519831 | I22: =I6/E6-1 -> 0.20767738 | J22: =J6/F6-1 -> 0.10521293 | K22: =K6/G6-1 -> 0.043613886 | L22: =L6/H6-1 -> 0.018749697 | M22: =M6/I6-1 -> -0.087295609 | ... W22: =W6/S6-1 -> 0.11288462
A23: 归母净利同比 | F23: =IF(B17<=0,"n.m.",F17/B17-1) -> 0.10039136 | G23: =IF(C17<=0,"n.m.",G17/C17-1) -> 0.18951983 | H23: =IF(D17<=0,"n.m.",H17/D17-1) -> -0.060643437 | I23: =IF(E17<=0,"n.m.",I17/E17-1) -> 24.55903 | J23: =IF(F17<=0,"n.m.",J17/F17-1) -> 0.12886903 | K23: =IF(G17<=0,"n.m.",K17/G17-1) -> 0.1362826 | L23: =IF(H17<=0,"n.m.",L17/H17-1) -> 0.019263952 | M23: =IF(I17<=0,"n.m.",M17/I17-1) -> 0.70443919 | ... W23: =IF(S17<=0,"n.m.",W17/S17-1) -> -0.33264498
A24: 2026E下半年隐含值校验 | B24: 2025H1A | C24: 2025H2A | D24: 2026H1A | E24: 2026H2E隐含 | F24: H2同比 | G24: 2026E全年
A25: 营业收入 | B25: =历史报表!J8 -> 11116.821 | C25: =历史报表!I8-历史报表!J8 -> 13801.734 | D25: =历史报表!K8 -> 12376.358 | E25: =利润表!H6-D25 -> 15187.158 | F25: =E25/C25-1 -> 0.10038046 | G25: =利润表!H6 -> 27563.516
A26: 毛利 | B26: =(历史报表!J8-历史报表!J10) -> 2470.2228 | C26: =(历史报表!I8-历史报表!I10)-(历史报表!J8-历史报表!J10) -> 2787.1034 | D26: =(历史报表!K8-历史报表!K10) -> 2648.497 | E26: =利润表!H8-D26 -> 3152.8031 | F26: =E26/C26-1 -> 0.1312114 | G26: =利润表!H8 -> 5801.3001
A27: 归母净利润 | B27: =历史报表!J34 -> 286.5688 | C27: =历史报表!I34-历史报表!J34 -> 149.2657 | D27: =历史报表!K34 -> 192.7997 | E27: =利润表!H29-D27 -> 559.13648 | F27: =E27/C27-1 -> 2.745914 | G27: =利润表!H29 -> 751.93618
A28: 注：2024Q4/2025Q4 研发费用异常偏低（0.66亿/1.96亿），与年末研发资本化集中确认有关——见“费用”表研发资本化分析。

Sheet 历史报表
A1: 历史报表（合并口径，百万元）
A2: 来源：Wind 导出（万元，已÷100）；与2021–2026H1定期报告核对。蓝色=原始数据。EPS为元/股。
A5: 项目 | C5: 2019A | D5: 2020A | E5: 2021A | F5: 2022A | G5: 2023A | H5: 2024A | I5: 2025A | J5: 2025H1A | K5: 2026H1A
A6: 合并利润表
A7: 营业总收入 | C7: 24661.977 | D7: 21074.437 | E7: 26314.98 | F7: 30917.861 | G7: 31129.574 | H7: 28548.831 | I7: 24918.554 | J7: 11116.821 | K7: 12376.358
A8: 营业收入 | C8: 24661.977 | D8: 21074.437 | E8: 26314.98 | F8: 30917.861 | G8: 31129.574 | H8: 28548.831 | I8: 24918.554 | J8: 11116.821 | K8: 12376.358
A9: 营业总成本 | C9: 23861.662 | D9: 21012.388 | E9: 26231.307 | F9: 30687.646 | G9: 30858.991 | H9: 28358.698 | I9: 25225.419 | J9: 11383.249 | K9: 12704.157
A10: 营业成本 | C10: 19284.972 | D10: 16489.858 | E10: 20605.046 | F10: 24126.68 | G10: 24728.125 | H10: 22482.664 | I10: 19661.228 | J10: 8646.5982 | K10: 9727.8614
A11: 税金及附加 | C11: 91.4066 | D11: 79.8805 | E11: 88.2078 | F11: 102.0822 | G11: 109.2552 | H11: 116.2267 | I11: 109.8429 | J11: 43.7141 | K11: 79.0084
A12: 销售费用 | C12: 1641.58 | D12: 1360.2349 | E12: 1417.9454 | F12: 1645.9351 | G12: 1786.6738 | H12: 1881.3582 | I12: 1975.6587 | J12: 963.3505 | K12: 1061.5176
A13: 管理费用 | C13: 282.9862 | D13: 270.0334 | E13: 294.4026 | F13: 328.6322 | G13: 341.013 | H13: 439.5538 | I13: 484.3899 | J13: 171.5524 | K13: 190.1205
A14: 研发费用 | C14: 2332.4556 | D14: 2578.5058 | E14: 3460.4309 | F14: 4101.782 | G14: 3578.3312 | H14: 2881.2504 | I14: 2570.0983 | J14: 1439.1572 | K14: 1269.9684
A15: 财务费用 | C15: 228.2615 | D15: 233.8754 | E15: 365.2745 | F15: 382.5345 | G15: 315.5928 | H15: 557.6445 | I15: 424.2011 | J15: 118.8763 | K15: 375.6803
A16: 其中：利息费用 | C16: 243.5235 | D16: 190.9962 | E16: 215.601 | F16: 313.6005 | G16: 338.3448 | H16: 460.6155 | I16: 327.7565 | J16: 132.9425 | K16: 149.8608
A17: 减：利息收入 | C17: 33.7161 | D17: 39.0508 | E17: 31.8052 | F17: 45.4798 | G17: 42.8973 | H17: 46.4411 | I17: 41.9207 | J17: 21.9787 | K17: 17.8741
A18: 加：其他收益 | C18: 284.4784 | D18: 281.3287 | E18: 260.0848 | F18: 275.016 | G18: 447.9878 | H18: 771.2192 | I18: 722.6505 | J18: 347.4784 | K18: 219.0644
... A20: 其中：对联营企业和合营企业的投资收益 | C20: 322.1917 | D20: 230.2545 | E20: 402.1722 | F20: 378.8812 | G20: 325.9203 | H20: 285.6265 | I20: 442.3 | J20: 194.9132 | K20: 400.0886
A21: 以摊余成本计量的金融资产终止确认收益 | G21: -42.1765 | H21: -27.055 | I21: -20.7403
A22: 公允价值变动净收益 | E22: 2.7352 | F22: -2.4842 | G22: 0.3342 | H22: 0.269 | I22: -12.6198
A23: 资产减值损失 | C23: -122.2809 | D23: -257.77 | E23: -239.801 | F23: -122.3486 | G23: -147.8754 | H23: -107.2242 | I23: -294.1611 | J23: 17.8247 | K23: -44.045
A24: 信用减值损失 | C24: -133.5542 | D24: -83.893 | E24: -17.4286 | F24: -232.8913 | G24: -291.6802 | H24: -345.4449 | I24: -81.4387 | J24: -15.0817 | K24: 4.1395
A25: 资产处置收益 | C25: -0.9195 | D25: -1.323 | E25: 1.838 | F25: 4.1996 | G25: -14.9768 | H25: 6.6168 | I25: 0.4398 | J25: 0.0275 | K25: -0.3458
A26: 营业利润 | C26: 1116.439 | D26: 208.6891 | E26: 493.6696 | F26: 541.3513 | G26: 566.2206 | H26: 803.3545 | I26: 473.1587 | J26: 294.5666 | K26: 239.9507
A27: 加：营业外收入 | C27: 7.3927 | D27: 6.9448 | E27: 10.9054 | F27: 11.797 | G27: 22.2615 | H27: 9.5196 | I27: 7.9355 | J27: 3.4934 | K27: 5.7925
A28: 减：营业外支出 | C28: 9.6317 | D28: 10.3236 | E28: 13.5331 | F28: 12.7508 | G28: 7.2454 | H28: 20.736 | I28: 19.0593 | J28: 4.1883 | K28: 4.3252
A29: 利润总额 | C29: 1114.2 | D29: 205.3102 | E29: 491.0418 | F29: 540.3976 | G29: 581.2367 | H29: 792.138 | I29: 462.0349 | J29: 293.8716 | K29: 241.418
A30: 减：所得税 | C30: 60.3514 | D30: 62.4449 | E30: 135.4087 | F30: 131.1737 | G30: 92.4501 | H30: 81.9381 | I30: 85.9854 | J30: 9.3354 | K30: 56.1532
A31: 净利润 | C31: 1053.8486 | D31: 142.8653 | E31: 355.6331 | F31: 409.2239 | G31: 488.7866 | H31: 710.1999 | I31: 376.0495 | J31: 284.5362 | K31: 185.2648
A32: 持续经营净利润 | C32: 1053.8486 | D32: 142.8653 | E32: 355.6331 | F32: 409.2239 | G32: 488.7866 | H32: 710.1999 | I32: 376.0495 | J32: 284.5362 | K32: 185.2648
A33: 减：少数股东损益 | C33: 75.0692 | D33: 40.5731 | E33: 67.6577 | F33: 3.4306 | G33: -16.5807 | H33: 7.4939 | I33: -59.785 | J33: -2.0325 | K33: -7.5349
A34: 归属于母公司所有者的净利润 | C34: 978.7794 | D34: 102.2922 | E34: 287.9754 | F34: 405.7933 | G34: 505.3672 | H34: 702.706 | I34: 435.8345 | J34: 286.5688 | K34: 192.7997
... A40: 稀释每股收益 | C40: 0.82 | D40: 0.09 | E40: 0.23 | F40: 0.3 | G40: 0.42 | H40: 0.61 | I40: 0.36 | J40: 0.24 | K40: 0.14
A41: 合并资产负债表
A42: 货币资金 | C42: 4637.6073 | D42: 3970.119 | E42: 4722.3289 | F42: 4388.9732 | G42: 5207.7287 | H42: 5243.7569 | I42: 6486.4939 | J42: 3603.3337 | K42: 4965.1259
A43: 应收票据及应收账款 | C43: 8546.9054 | D43: 6273.9124 | E43: 4783.9256 | F43: 7420.2102 | G43: 13452.903 | H43: 16646.828 | I43: 15422.802 | J43: 15876.729 | K43: 14070.951
A44: 应收票据 | C44: 1053.2769 | D44: 514.4739 | E44: 564.5794 | F44: 589.8675 | G44: 1041.1075 | H44: 1385.9713 | I44: 611.7505 | J44: 654.0552 | K44: 970.6595
A45: 应收账款 | C45: 7493.6285 | D45: 5759.4385 | E45: 4219.3462 | F45: 6830.3427 | G45: 12411.795 | H45: 15260.857 | I45: 14811.052 | J45: 15222.674 | K45: 13100.291
A46: 应收款项融资 | D46: 329.3958 | E46: 226.7897 | F46: 132.3347 | G46: 346.8897 | H46: 318.2288 | I46: 355.4839 | J46: 231.9013 | K46: 244.1906
A47: 预付款项 | C47: 340.8775 | D47: 503.6771 | E47: 345.0894 | F47: 744.5724 | G47: 1204.0073 | H47: 659.2119 | I47: 1461.3915 | J47: 691.8123 | K47: 2516.0374
A48: 其他应收款(合计) | C48: 710.8265 | D48: 596.1824 | E48: 680.7874 | F48: 484.3906 | G48: 646.0326 | H48: 496.4689 | I48: 367.0848 | J48: 309.9272 | K48: 315.1794
A49: 应收股利 | C49: 157.5054 | D49: 122.9364 | E49: 120.8834 | F49: 115.7414 | G49: 105.4014 | H49: 92.8764 | J49: 75.3414 | K49: 144
A50: 应收利息 | C50: 3.2736 | D50: 0.6422 | E50: 0 | F50: 1.0072 | G50: 0 | H50: 0 | J50: 0
A51: 其他应收款 | C51: 550.0475 | D51: 472.6037 | E51: 559.904 | F51: 367.642 | G51: 540.6312 | H51: 403.5925 | I51: 367.0848 | J51: 234.5857 | K51: 171.1794
A52: 存货 | C52: 8938.8192 | D52: 13573.77 | E52: 14605.128 | F52: 14390.162 | G52: 9718.9319 | H52: 9329.2257 | I52: 10575.039 | J52: 10028.121 | K52: 13560.093
A53: 其他流动资产 | C53: 494.899 | D53: 584.3077 | E53: 543.3164 | F53: 633.5327 | G53: 725.1377 | H53: 917.7124 | I53: 539.4726 | J53: 1041.1841 | K53: 706.3645
A54: 流动资产合计 | C54: 23669.935 | D54: 25831.364 | E54: 25907.365 | F54: 28194.176 | G54: 31301.631 | H54: 33611.433 | I54: 35207.768 | J54: 31783.008 | K54: 36377.942
A55: 长期股权投资 | C55: 2216.9789 | D55: 2303.0559 | E55: 2504.3889 | F55: 2726.3613 | G55: 2743.0593 | H55: 2745.9269 | I55: 2987.0148 | J55: 2775.9563 | K55: 3243.2863
A56: 其他权益工具投资 | C56: 180.2966 | D56: 180.1809 | E56: 208.3202 | F56: 210.8065 | G56: 147.6732 | H56: 119.0697 | I56: 115.8727 | J56: 119.0697 | K56: 115.8727
A57: 其他非流动金融资产 | E57: 87.8352 | F57: 96.351 | G57: 96.6852 | H57: 16.4536 | I57: 16.2645 | J57: 16.4536 | K57: 16.2645
A58: 投资性房地产 | C58: 127.9268 | D58: 123.1721 | E58: 118.3596 | F58: 113.6049 | G58: 108.8725 | H58: 104.0955 | I58: 99.29 | J58: 101.7182 | K58: 96.9127
A59: 固定资产(合计) | C59: 2567.4984 | D59: 3351.0126 | E59: 3458.9686 | F59: 3673.3317 | G59: 4194.2529 | H59: 3762.6742 | I59: 3608.4412 | J59: 3633.5006 | K59: 3972.7994
A60: 固定资产 | C60: 2567.4984 | D60: 3351.0126 | E60: 3458.9686 | F60: 3673.3317 | G60: 4194.2529 | H60: 3762.6742 | I60: 3608.4412 | J60: 3633.5006 | K60: 3972.7994
A61: 在建工程(合计) | C61: 1027.4012 | D61: 877.2857 | E61: 1191.0416 | F61: 916.072 | G61: 429.2772 | H61: 889.8926 | I61: 1364.8068 | J61: 976.2217 | K61: 1155.3614
A62: 在建工程 | C62: 1027.4012 | D62: 877.2857 | E62: 1191.0416 | F62: 916.072 | G62: 429.2772 | H62: 889.8926 | I62: 1364.8068 | J62: 976.2217 | K62: 1155.3614
A63: 使用权资产 | E63: 88.6436 | F63: 147.4453 | G63: 78.6099 | H63: 160.5597 | I63: 108.2493 | J63: 127.7982 | K63: 79.9477
A64: 无形资产 | C64: 720.5225 | D64: 999.5628 | E64: 956.8971 | F64: 1202.1387 | G64: 1553.3013 | H64: 1741.9929 | I64: 2407.8063 | J64: 1870.7386 | K64: 2249.317
A65: 开发支出 | C65: 765.7027 | D65: 1134.4627 | E65: 1124.4628 | F65: 1020.541 | G65: 938.2379 | H65: 1273.7418 | I65: 953.7547 | J65: 1284.2544 | K65: 1229.9452
A66: 商誉 | C66: 2.1761 | D66: 2.1761 | E66: 2.1761 | F66: 2.1761 | G66: 86.3484 | H66: 86.3484 | I66: 86.3484 | J66: 86.3484 | K66: 86.3484
A67: 长期待摊费用 | C67: 46.8583 | D67: 63.8367 | E67: 57.8415 | F67: 50.8145 | G67: 48.4462 | H67: 39.0585 | I67: 36.4732 | J67: 38.2908 | K67: 39.016
A68: 递延所得税资产 | C68: 165.7614 | D68: 175.4291 | E68: 174.021 | F68: 192.1203 | G68: 207.1906 | H68: 202.3741 | I68: 186.1557 | J68: 202.5498 | K68: 189.3518
A69: 其他非流动资产 | H69: 3.8189 | I69: 3.7373 | K69: 5.4
A70: 非流动资产合计 | C70: 7821.1228 | D70: 9210.1746 | E70: 9972.956 | F70: 10351.763 | G70: 10631.955 | H70: 11146.007 | I70: 11974.215 | J70: 11232.9 | K70: 12479.823
A71: 资产差额(合计平衡项目) | J71: 0
A72: 资产总计 | C72: 31491.058 | D72: 35041.539 | E72: 35880.321 | F72: 38545.939 | G72: 41933.585 | H72: 44757.44 | I72: 47181.983 | J72: 43015.909 | K72: 48857.765
A73: 短期借款 | C73: 548.81 | D73: 478.9947 | E73: 288.5518 | F73: 638.6606 | G73: 2026.2359 | H73: 5079.8579 | I73: 6930.4263 | J73: 5431.6344 | K73: 7776.7969
A74: 交易性金融负债 | I74: 18.9335 | K74: 18.9335
A75: 应付票据及应付账款 | C75: 10242.019 | D75: 12235.85 | E75: 11601.425 | F75: 14019.216 | G75: 14566.488 | H75: 14506.032 | I75: 12627.496 | J75: 11146.551 | K75: 13548.851
A76: 应付票据 | C76: 4445.2668 | D76: 5735.9551 | E76: 5945.8226 | F76: 7526.9418 | G76: 7752.2333 | H76: 8512.7803 | I76: 6071.3562 | J76: 5132.2303 | K76: 7293.6379
A77: 应付账款 | C77: 5796.7522 | D77: 6499.8953 | E77: 5655.6024 | F77: 6492.2746 | G77: 6814.2548 | H77: 5993.2517 | I77: 6556.1394 | J77: 6014.3203 | K77: 6255.2128
A78: 预收款项 | C78: 3200.1447 | D78: 1.8429 | E78: 1.3439 | F78: 1.57 | G78: 27.4386 | H78: 1.4648 | I78: 1.1602 | J78: 1.3297 | K78: 1.4241
A79: 合同负债 | D79: 3673.7189 | E79: 3167.3309 | F79: 1319.1721 | G79: 1309.8834 | H79: 774.6746 | I79: 976.508 | J79: 916.7206 | K79: 1106.1566
A80: 应付职工薪酬 | C80: 418.233 | D80: 276.9085 | E80: 235.4881 | F80: 231.3288 | G80: 283.6855 | H80: 256.2975 | I80: 270.1812 | J80: 188.8223 | K80: 183.8769
A81: 应交税费 | C81: 268.338 | D81: 108.0554 | E81: 244.7092 | F81: 524.5033 | G81: 905.9197 | H81: 754.1246 | I81: 402.134 | J81: 553.4728 | K81: 248.2249
A82: 其他应付款(合计) | C82: 1657.6674 | D82: 1569.7353 | E82: 1700.9199 | F82: 2131.7705 | G82: 2036.3337 | H82: 1765.2361 | I82: 1304.7764 | J82: 1575.166 | K82: 1579.4903
A83: 应付利息 | C83: 4.679 | D83: 9.5452 | E83: 19.8792 | F83: 5.4066 | G83: 0 | H83: 0 | I83: 0 | J83: 0
A84: 应付股利 | C84: 22.3631 | D84: 25.8009 | E84: 3.6271 | F84: 7.8831 | G84: 15.2082 | H84: 15.0025 | I84: 12.658 | J84: 12.658 | K84: 135.8262
A85: 其他应付款 | C85: 1630.6253 | D85: 1534.3893 | E85: 1677.4137 | F85: 2118.4807 | G85: 2021.1255 | H85: 1750.2335 | I85: 1292.1184 | J85: 1562.508 | K85: 1443.6641
A86: 一年内到期的非流动负债 | C86: 285 | E86: 16.1005 | F86: 897.2013 | G86: 1361.8444 | H86: 3162.1433 | I86: 524.3707 | J86: 3881.4565 | K86: 2996.6449
A87: 其他流动负债 | D87: 234.4927 | E87: 458.7292 | F87: 269.3733 | G87: 246.4759 | H87: 186.5249 | I87: 159.7009 | J87: 113.6001 | K87: 142.5411
A88: 流动负债合计 | C88: 16620.212 | D88: 18579.599 | E88: 17714.598 | F88: 20032.796 | G88: 22764.305 | H88: 26486.356 | I88: 23215.687 | J88: 23808.753 | K88: 27602.94
A89: 长期借款 | C89: 50 | D89: 1399 | E89: 2455.8 | F89: 1672.1 | G89: 717.2 | H89: 1937.29 | I89: 4239.3389 | J89: 2856.8748 | K89: 1781.3981
A90: 应付债券 | C90: 2332.9248 | D90: 2466.2784 | E90: 2598.1583 | F90: 2722.4942 | G90: 2843.957
A91: 租赁负债 | E91: 72.0342 | F91: 84.52 | G91: 49.6756 | H91: 99.1721 | I91: 39.9403 | J91: 73.8416 | K91: 16.7409
A92: 预计负债 | C92: 37.1596 | D92: 31.2699 | E92: 33.6435 | F92: 44.7878 | G92: 46.9745 | H92: 47.3562 | I92: 36.8866 | J92: 43.3021 | K92: 34.9643
A93: 递延所得税负债 | C93: 1.1543 | D93: 1.209 | E93: 0.8755 | F93: 0.841 | G93: 4.362 | H93: 0.7717 | I93: 0.8223 | J93: 5.1765 | K93: 0.7717
A94: 递延收益-非流动负债 | C94: 393.8654 | D94: 489.7262 | E94: 413.1172 | F94: 466.6561 | G94: 592.4055 | H94: 516.1313 | I94: 537.9914 | J94: 443.5526 | K94: 501.1296
A95: 非流动负债合计 | C95: 2815.1041 | D95: 4387.4834 | E95: 5573.6287 | F95: 4991.3991 | G95: 4254.5745 | H95: 2600.7213 | I95: 4854.9795 | J95: 3422.7476 | K95: 2335.0046
A96: 负债合计 | C96: 19435.316 | D96: 22967.082 | E96: 23288.227 | F96: 25024.196 | G96: 27018.88 | H96: 29087.077 | I96: 28070.666 | J96: 27231.501 | K96: 29937.945
A97: 实收资本(或股本) | C97: 1170.9846 | D97: 1170.154 | E97: 1187.8277 | F97: 1186.5645 | G97: 1185.4913 | H97: 1184.4645 | I97: 1358.1675 | J97: 1184.4741 | K97: 1358.1675
A98: 其他权益工具 | C98: 736.615 | D98: 736.4561 | E98: 736.4456 | F98: 736.4411 | G98: 736.4387 | H98: 736.4344 | J98: 736.3829
A99: 资本公积 | C99: 5583.458 | D99: 5670.2153 | E99: 5849.0049 | F99: 5876.0603 | G99: 6232.649 | H99: 6284.7788 | I99: 9829.9698 | J99: 6285.0274 | K99: 9874.2939
A100: 减：库存股 | C100: 745.4128 | D100: 502.8856 | E100: 660.7624 | F100: 641.6411 | G100: 424.6667 | H100: 209.9661 | J100: 209.9661
A101: 其他综合收益 | C101: 5.9273 | D101: -29.0214 | E101: -61.7893 | F101: -19.3545 | G101: 55.8051 | H101: 20.209 | I101: 191.1034 | J101: 62.2071 | K101: 148.7154
A102: 专项储备 | D102: 4.1145 | E102: 4.0332 | F102: 3.8612
A103: 盈余公积 | C103: 374.7125 | D103: 385.7827 | E103: 423.8983 | F103: 438.563 | G103: 467.7518 | H103: 518.7715 | I103: 550.7272 | J103: 518.7715 | K103: 550.7272
A104: 未分配利润 | C104: 4343.9736 | D104: 4037.6125 | E104: 4254.8281 | F104: 4551.7324 | G104: 4919.3451 | H104: 5416.111 | I104: 5607.969 | J104: 5490.6589 | K104: 5669.0265
A105: 归属于母公司所有者权益合计 | C105: 11470.258 | D105: 11472.428 | E105: 11733.486 | F105: 12132.227 | G105: 13172.814 | H105: 13950.803 | I105: 17537.937 | J105: 14067.556 | K105: 17600.93
A106: 少数股东权益 | C106: 585.4833 | D106: 602.0284 | E106: 858.608 | F106: 1389.5164 | G106: 1741.8913 | H106: 1719.5595 | I106: 1573.3797 | J106: 1716.8524 | K106: 1318.8897
A107: 所有者权益合计 | C107: 12055.742 | D107: 12074.457 | E107: 12592.094 | F107: 13521.743 | G107: 14914.706 | H107: 15670.362 | I107: 19111.316 | J107: 15784.408 | K107: 18919.82
A108: 负债及股东权益差额(合计平衡项目) | J108: 0
...

Sheet 核对
A1: 模型核对
A2: 所有核对应为0（或“OK”）
A5: 项目 | B5: 百万元 | C5: 2021A | D5: 2022A | E5: 2023A | F5: 2024A | G5: 2025A | H5: 2026E | I5: 2027E | J5: 2028E | K5: 2029E | L5: 2030E | O5: 说明 / 来源
A6: 资产负债表平衡（资产−负债−权益） | C6: =资产负债表!C60 -> 0 | D6: =资产负债表!D60 -> 9.9999997e-05 | E6: =资产负债表!E60 -> -9.999999e-05 | F6: =资产负债表!F60 -> -0.0001 | G6: =资产负债表!G60 -> -0.0001 | H6: =资产负债表!H60 -> 0.00066199999 | I6: =资产负债表!I60 -> 0.00066199999 | J6: =资产负债表!J60 -> 0.00066199999 | ... L6: =资产负债表!L60 -> 0.00066199998
A7: 历史资产总计 vs 报表 | C7: =资产负债表!C61 -> -9.9999997e-05 | D7: =资产负债表!D61 -> 0 | E7: =资产负债表!E61 -> 0 | F7: =资产负债表!F61 -> 0 | G7: =资产负债表!G61 -> 0
A8: 历史归母权益 vs 报表 | C8: =资产负债表!C62 -> -9.9999999e-05 | D8: =资产负债表!D62 -> -0.0001 | E8: =资产负债表!E62 -> 0 | F8: =资产负债表!F62 -> 0.0001 | G8: =资产负债表!G62 -> 0.0001
A9: 历史归母净利润 vs 报表 | C9: =利润表!C30 -> 9.9999999e-05 | D9: =利润表!D30 -> 1.8189894e-12 | E9: =利润表!E30 -> -0.0001 | F9: =利润表!F30 -> 0.0002 | G9: =利润表!G30 -> -0.0002
A10: 历史期末现金 vs 报表 | C10: =现金流量表!C37 -> 0 | D10: =现金流量表!D37 -> 0 | E10: =现金流量表!E37 -> 0.0001 | F10: =现金流量表!F37 -> 0 | G10: =现金流量表!G37 -> -9.9999999e-05
A11: 预测：现金流量表期末现金+受限资金−资产负债表货币资金 | H11: =现金流量表!H36+融资!H8-资产负债表!H7 -> 0 | I11: =现金流量表!I36+融资!I8-资产负债表!I7 -> 0 | J11: =现金流量表!J36+融资!J8-资产负债表!J7 -> 0 | K11: =现金流量表!K36+融资!K8-资产负债表!K7 -> 0 | L11: =现金流量表!L36+融资!L8-资产负债表!L7 -> 0
A12: 分部收入合计 vs 报表营业收入 | C12: =分业务!C40 -> -0.0001 | D12: =分业务!D40 -> 0 | E12: =分业务!E40 -> -9.9999997e-05 | F12: =分业务!F40 -> -9.9999997e-05 | G12: =分业务!G40 -> 0.0001 | H12: =分业务!H35-利润表!H6 -> 0 | I12: =分业务!I35-利润表!I6 -> 0 | J12: =分业务!J35-利润表!J6 -> 0 | K12: =分业务!K35-利润表!K6 -> 0 | L12: =分业务!L35-利润表!L6 -> 0
A13: 固定资产净值 vs 报表 | C13: =资本开支折旧!C21 -> 0 | D13: =资本开支折旧!D21 -> 0 | E13: =资本开支折旧!E21 -> 0 | F13: =资本开支折旧!F21 -> 0 | G13: =资本开支折旧!G21 -> 0
A14: 无形资产净值 vs 报表 | C14: =资本开支折旧!C46 -> 0 | D14: =资本开支折旧!D46 -> 0 | E14: =资本开支折旧!E46 -> 0 | F14: =资本开支折旧!F46 -> 0 | G14: =资本开支折旧!G46 -> 0
A15: 研发投入=资本化+费用化 | C15: =费用!C20 -> 3.9e-05 | D15: =费用!D20 -> -5e-05 | E15: =费用!E20 -> -2e-05 | F15: =费用!F20 -> 1.6e-05 | G15: =费用!G20 -> -4.6e-05
A16: 短期借款不低于下限 | H16: =MIN(0,融资!H12-假设!$C$35) -> 0 | I16: =MIN(0,融资!I12-假设!$C$35) -> 0 | J16: =MIN(0,融资!J12-假设!$C$35) -> 0 | K16: =MIN(0,融资!K12-假设!$C$35) -> 0 | L16: =MIN(0,融资!L12-假设!$C$35) -> 0
A18: 总体核对结果 | C18: =IF(SUMPRODUCT(ABS(C6:L16))<0.1,"OK","ERROR") -> OK | D18: =SUMPRODUCT(ABS(C6:L16)) -> 0.0055809999
