Workbook

Sheet 封面
B2: 菲利华（300395.SZ）财务与估值模型
B3: 笃研究 | 2026年10月6日 | 新材料·石英 | 数据截至2026年半年报，股价截至2026年9月30日
B5: 关键输出 | C5: 2025A | D5: 2026E | E5: 2027E | F5: 2028E
B6: 营业收入（百万元） | C6: =利润表!H5 -> 2016.3489 | D6: =利润表!I5 -> 2741.007 | E6: =利润表!J5 -> 3510.4561 | F6: =利润表!K5 -> 4419.9684
B7: 同比 | C7: =利润表!H6 -> 0.15761609 | D7: =利润表!I6 -> 0.35939122 | E7: =利润表!J6 -> 0.28071769 | F7: =利润表!K6 -> 0.25908663
B8: 综合毛利率 | C8: =利润表!H9 -> 0.47376553 | D8: =利润表!I9 -> 0.50234003 | E8: =利润表!J9 -> 0.50210968 | F8: =利润表!K9 -> 0.49254316
B9: 归母净利润（百万元） | C9: =利润表!H27 -> 443.1847 | D9: =利润表!I27 -> 617.92312 | E9: =利润表!J27 -> 751.23552 | F9: =利润表!K27 -> 964.73358
B10: 同比 | C10: =利润表!H28 -> 0.41047518 | D10: =利润表!I28 -> 0.394279 | E10: =利润表!J28 -> 0.2157427 | F10: =利润表!K28 -> 0.28419591
B11: EPS（元） | C11: =利润表!H29 -> 0.84857392 | D11: =利润表!I29 -> 1.1753621 | E11: =利润表!J29 -> 1.4265473 | F11: =利润表!K29 -> 1.8289066
B12: ROE | C12: =利润表!H37 -> 0.09577148 | D12: =利润表!I37 -> 0.11202174 | E12: =利润表!J37 -> 0.1195494 | F12: =利润表!K37 -> 0.13436674
B13: PE（当前股价） | C13: =DCF!$C$5/利润表!H29 -> 114.81616 | D13: =DCF!$C$5/利润表!I29 -> 82.893603 | E13: =DCF!$C$5/利润表!J29 -> 68.297768 | F13: =DCF!$C$5/利润表!K29 -> 53.272268
B14: 一致预期归母净利润（百万元） | C14: 443.18 | D14: 739.39 | E14: 1105.27 | F14: 1553.36
B15: 模型 / 一致预期 − 1 | D15: =D9/D14-1 -> -0.16427985 | E15: =E9/E14-1 -> -0.32031493 | F15: =F9/F14-1 -> -0.37893754
B17: 估值（元/股） | C17: 下限 | D17: 基准 | E17: 上限 | F17: 相对股价
B18: =相对估值!A74 -> DCF（WACC ±0.5%） | C18: =相对估值!B74 -> 27.344501 | D18: =相对估值!C74 -> 29.685689 | E18: =相对估值!D74 -> 32.425837 | F18: =IFERROR(D18/DCF!$C$5-1,0) -> -0.69531264
B19: =相对估值!A75 -> PE（2027E） | C19: =相对估值!B75 -> 49.929157 | D19: =相对估值!C75 -> 64.19463 | E19: =相对估值!D75 -> 78.460104 | F19: =IFERROR(D19/DCF!$C$5-1,0) -> -0.34112049
B20: =相对估值!A76 -> SOTP（2027E / 2028E折现） | C20: =相对估值!B76 -> 49.546571 | D20: =相对估值!C76 -> 51.3497 | E20: =相对估值!D76 -> 53.152828 | F20: =IFERROR(D20/DCF!$C$5-1,0) -> -0.47295802
B21: =相对估值!A77 -> 卖方目标价（近3个月） | C21: =相对估值!B77 -> 107.05 | D21: =相对估值!C77 -> 124.7 | E21: =相对估值!D77 -> 142.59 | F21: =IFERROR(D21/DCF!$C$5-1,0) -> 0.27989326
B22: =相对估值!A78 -> 52周股价区间 | C22: =相对估值!B78 -> 75.36 | D22: =相对估值!C78 -> 97.43 | E22: =相对估值!D78 -> 150 | F22: =IFERROR(D22/DCF!$C$5-1,0) -> 0
B24: 当前情景 / 当前价格 | C24: =假设!C5 -> 基准 | D24: =DCF!C5 -> 97.43 | E24: =DCF!C7/100 -> 512.21591 | F24: 模型检查： | G24: =检查!B19 -> 通过
B26: 三情景结果快照（静态值，由模型分别切换情景计算后写入）
B27: 情景 | C27: 2026E 归母净利 | D27: 2027E 归母净利 | E27: 2028E 归母净利 | F27: DCF每股价值 | G27: SOTP(2027E)每股 | H27: 2028E电子布收入
B28: 悲观 | C28: 566.19 | D28: 506.01 | E28: 568.58 | F28: 17.49 | G28: 33.48 | H28: 595
B29: 基准 | C29: 617.92 | D29: 751.24 | E29: 964.73 | F29: 29.69 | G29: 49.55 | H29: 1365
B30: 乐观 | C30: 699.05 | D30: 1053.39 | E30: 1544.96 | F30: 43.64 | G30: 69.43 | H30: 3055
B32: 图例与约定
B33: 蓝色字体 | C33: 硬编码输入（历史报告值、假设、外部数据）
B34: 黑色字体 | C34: 公式计算
B35: 绿色字体 | C35: 跨表引用
B36: 浅黄底色 | C36: 预测期可调输入
B37: 亮黄底色 | C37: 关键假设 / 关键输出（含情景选择单元格“假设!C4”）
B38: 单位 | C38: 除注明外均为人民币百万元；股本为百万股；电子布销量为万米、均价为元/米
B39: 时间 | C39: 历史 2020A–2025A（年报）；2026E–2030E 为全年预测，“季度”表以全年预测减上半年实际推算2026Q3E/Q4E
B41: 表单导航
B42: 假设 | C42: 情景切换（C4）与分业务情景驱动：增速、毛利率、电子布产能/销量/价格
B43: 业务拆分 | C43: 七大应用的收入、毛利、经营利润、少数股东比例与归母利润
B44: 资本开支 | C44: 项目级资本开支、在建工程转固、分年度折旧（年中法）
B45: 营运资本 | C45: 应收、存货、应付等周转天数驱动
B46: 费用税率 | C46: 费用率、其他收益、减值、税率、少数股东损益
B47: 融资 | C47: 借款、利息、金融资产、股本、股份支付、分红、少数股东
B48: 利润表/资产负债表/现金流量表 | C48: 三表联动，现金为平衡项
B49: 季度 | C49: 单季利润表与2026Q3/Q4隐含值
B50: DCF | C50: FCFF：显性期2026-30E＋10年衰减期＋永续；WACC×g、衰减期起始增速×RONIC敏感性；反向DCF
B51: 相对估值 | C51: 可比公司、PE、SOTP、市场隐含电子布预期、估值汇总
B52: 一致预期 | C52: 模型与Wind一致预期对比、预期修正、卖方明细
B53: 历史数据/底稿 | C53: Wind原表（万元）与定期报告附注摘录
B54: 检查 | C54: 平衡与勾稽检查
B56: 主要数据来源
B57: 公司2021-2025年年报、2021-2026年半年报及季报；Wind三大报表（万元，换算为百万元）
B58: Wind一致预期（2026-10-06）；公司投资者关系活动记录、互动易问答（至2026-09-04）
B59: 行业数据：券商研报与媒体公开报道（详见各单元格备注）；可比公司估值为公开报道快照，需以Wind复核

Sheet 假设
A1: 核心假设与情景切换（黄色底色=可调输入；蓝字=硬编码输入；黑字=公式；绿字=跨表引用）
A2: 切换 C4 情景编号（1=悲观 2=基准 3=乐观），全模型随之重算。每个驱动项下方三行为三种情景输入，“选用”行为 CHOOSE 结果。
A4: 情景选择（1=悲观, 2=基准, 3=乐观） | C4: 2 | D4: 改变此单元格即可切换全模型情景
A5: 当前情景 | C5: =CHOOSE(C4,"悲观","基准","乐观") -> 基准
A7: 情景驱动（百万元 / 指标） | B7: 单位 | C7: 2020A | D7: 2021A | E7: 2022A | F7: 2023A | G7: 2024A | H7: 2025A | I7: 2026E | J7: 2027E | K7: 2028E | L7: 2029E | M7: 2030E | N7: 说明 / 来源
A8: 半导体 收入增速
A9: 悲观 | B9: % | I9: 0.24 | J9: 0.1 | K9: 0.08 | L9: 0.06 | M9: 0.05
A10: 基准 | B10: % | I10: 0.28 | J10: 0.18 | K10: 0.14 | L10: 0.11 | M10: 0.09
A11: 乐观 | B11: % | I11: 0.33 | J11: 0.26 | K11: 0.2 | L11: 0.15 | M11: 0.12
A12: 选用（半导体 收入增速） | B12: % | I12: =CHOOSE($C$4,I9,I10,I11) -> 0.28 | J12: =CHOOSE($C$4,J9,J10,J11) -> 0.18 | K12: =CHOOSE($C$4,K9,K10,K11) -> 0.14 | L12: =CHOOSE($C$4,L9,L10,L11) -> 0.11 | M12: =CHOOSE($C$4,M9,M10,M11) -> 0.09 | N12: 2026H1半导体用石英材料+35%（半年报）；石创器件受光伏/研发拖累，合计按+28%；之后随国产替代与存储/先进制程扩产放缓
A13: 半导体 毛利率
A14: 悲观 | B14: % | I14: 0.5 | J14: 0.46 | K14: 0.45 | L14: 0.45 | M14: 0.44
A15: 基准 | B15: % | I15: 0.51 | J15: 0.51 | K15: 0.51 | L15: 0.5 | M15: 0.5
A16: 乐观 | B16: % | I16: 0.53 | J16: 0.54 | K16: 0.54 | L16: 0.54 | M16: 0.53
A17: 选用（半导体 毛利率） | B17: % | I17: =CHOOSE($C$4,I14,I15,I16) -> 0.51 | J17: =CHOOSE($C$4,J14,J15,J16) -> 0.51 | K17: =CHOOSE($C$4,K14,K15,K16) -> 0.51 | L17: =CHOOSE($C$4,L14,L15,L16) -> 0.5 | M17: =CHOOSE($C$4,M14,M15,M16) -> 0.5 | N17: 估算2025年51%、2026H1约51%（材料毛利率-7.5pct，合成石英五/六期折旧与产品结构）；基准维持51%
A18: 航空航天 收入增速
A19: 悲观 | B19: % | I19: 0.1 | J19: 0.03 | K19: 0.03 | L19: 0.03 | M19: 0.03
A20: 基准 | B20: % | I20: 0.15 | J20: 0.12 | K20: 0.1 | L20: 0.07 | M20: 0.06
A21: 乐观 | B21: % | I21: 0.2 | J21: 0.18 | K21: 0.14 | L21: 0.1 | M21: 0.08
A22: 选用（航空航天 收入增速） | B22: % | I22: =CHOOSE($C$4,I19,I20,I21) -> 0.15 | J22: =CHOOSE($C$4,J19,J20,J21) -> 0.12 | K22: =CHOOSE($C$4,K19,K20,K21) -> 0.1 | L22: =CHOOSE($C$4,L19,L20,L21) -> 0.07 | M22: =CHOOSE($C$4,M19,M20,M21) -> 0.06 | N22: 2024需求回落、2025持续恢复、复合材料获批量订单；2026H1估算+19%，全年按+15%（下半年约+11%）；军工行业“十五五”批量采购预计2027年起改善
A23: 航空航天 毛利率
A24: 悲观 | B24: % | I24: 0.59 | J24: 0.54 | K24: 0.53 | L24: 0.53 | M24: 0.53
A25: 基准 | B25: % | I25: 0.61 | J25: 0.61 | K25: 0.6 | L25: 0.6 | M25: 0.59
A26: 乐观 | B26: % | I26: 0.64 | J26: 0.64 | K26: 0.64 | L26: 0.63 | M26: 0.63
A27: 选用（航空航天 毛利率） | B27: % | I27: =CHOOSE($C$4,I24,I25,I26) -> 0.61 | J27: =CHOOSE($C$4,J24,J25,J26) -> 0.61 | K27: =CHOOSE($C$4,K24,K25,K26) -> 0.6 | L27: =CHOOSE($C$4,L24,L25,L26) -> 0.6 | M27: =CHOOSE($C$4,M24,M25,M26) -> 0.59 | N27: 军品价格机制改革存在压价风险，基准毛利率较2021-23年高点下调
A28: 光学（合成石英/光掩膜基板） 收入增速
A29: 悲观 | B29: % | I29: 0.3 | J29: 0.12 | K29: 0.1 | L29: 0.08 | M29: 0.06
A30: 基准 | B30: % | I30: 0.38 | J30: 0.28 | K30: 0.22 | L30: 0.16 | M30: 0.12
A31: 乐观 | B31: % | I31: 0.45 | J31: 0.4 | K31: 0.32 | L31: 0.22 | M31: 0.15
A32: 选用（光学（合成石英/光掩膜基板） 收入增速） | B32: % | I32: =CHOOSE($C$4,I29,I30,I31) -> 0.38 | J32: =CHOOSE($C$4,J29,J30,J31) -> 0.28 | K32: =CHOOSE($C$4,K29,K30,K31) -> 0.22 | L32: =CHOOSE($C$4,L29,L30,L31) -> 0.16 | M32: =CHOOSE($C$4,M29,M30,M31) -> 0.12 | N32: 2025高端光学材料“大幅增长”；2026H1估算+46%，济南光微建成、合肥光微逐步批量出货，全年按+38%（目标达产收入4亿元）
A33: 光学（合成石英/光掩膜基板） 毛利率
A34: 悲观 | B34: % | I34: 0.47 | J34: 0.45 | K34: 0.45 | L34: 0.45 | M34: 0.45
A35: 基准 | B35: % | I35: 0.49 | J35: 0.5 | K35: 0.5 | L35: 0.5 | M35: 0.5
A36: 乐观 | B36: % | I36: 0.51 | J36: 0.53 | K36: 0.54 | L36: 0.54 | M36: 0.54
A37: 选用（光学（合成石英/光掩膜基板） 毛利率） | B37: % | I37: =CHOOSE($C$4,I34,I35,I36) -> 0.49 | J37: =CHOOSE($C$4,J34,J35,J36) -> 0.5 | K37: =CHOOSE($C$4,K34,K35,K36) -> 0.5 | L37: =CHOOSE($C$4,L34,L35,L36) -> 0.5 | M37: =CHOOSE($C$4,M34,M35,M36) -> 0.5 | N37: 光掩膜基板仍在爬坡、上海石创亏损；毛利率随规模提升
A38: 光通讯 收入增速
A39: 悲观 | B39: % | I39: 0.4 | J39: -0.08 | K39: -0.1 | L39: 0 | M39: 0
A40: 基准 | B40: % | I40: 0.45 | J40: 0.08 | K40: -0.05 | L40: 0 | M40: 0.03
A41: 乐观 | B41: % | I41: 0.55 | J41: 0.2 | K41: 0.05 | L41: 0.03 | M41: 0.03
A42: 选用（光通讯 收入增速） | B42: % | I42: =CHOOSE($C$4,I39,I40,I41) -> 0.45 | J42: =CHOOSE($C$4,J39,J40,J41) -> 0.08 | K42: =CHOOSE($C$4,K39,K40,K41) -> -0.05 | L42: =CHOOSE($C$4,L39,L40,L41) -> 0 | M42: =CHOOSE($C$4,M39,M40,M41) -> 0.03 | N42: 光纤预制棒价格自2025年底上涨数倍（AI数据中心），2025年制品一销量+31%；2026H1估算+62%。周期性回落风险在2028年
A43: 光通讯 毛利率
A44: 悲观 | B44: % | I44: 0.33 | J44: 0.25 | K44: 0.23 | L44: 0.23 | M44: 0.23
A45: 基准 | B45: % | I45: 0.34 | J45: 0.3 | K45: 0.27 | L45: 0.27 | M45: 0.27
A46: 乐观 | B46: % | I46: 0.36 | J46: 0.34 | K46: 0.3 | L46: 0.29 | M46: 0.29
A47: 选用（光通讯 毛利率） | B47: % | I47: =CHOOSE($C$4,I44,I45,I46) -> 0.34 | J47: =CHOOSE($C$4,J44,J45,J46) -> 0.3 | K47: =CHOOSE($C$4,K44,K45,K46) -> 0.27 | L47: =CHOOSE($C$4,L44,L45,L46) -> 0.27 | M47: =CHOOSE($C$4,M44,M45,M46) -> 0.27 | N47: 涨价周期抬升毛利率，2027年后回落
A48: 光伏 收入增速
A49: 悲观 | B49: % | I49: -0.35 | J49: -0.1 | K49: 0 | L49: 0 | M49: 0
A50: 基准 | B50: % | I50: -0.25 | J50: 0 | K50: 0.03 | L50: 0.03 | M50: 0.03
A51: 乐观 | B51: % | I51: -0.15 | J51: 0.1 | K51: 0.08 | L51: 0.05 | M51: 0.05
A52: 选用（光伏 收入增速） | B52: % | I52: =CHOOSE($C$4,I49,I50,I51) -> -0.25 | J52: =CHOOSE($C$4,J49,J50,J51) -> 0 | K52: =CHOOSE($C$4,K49,K50,K51) -> 0.03 | L52: =CHOOSE($C$4,L49,L50,L51) -> 0.03 | M52: =CHOOSE($C$4,M49,M50,M51) -> 0.03 | N52: 光伏需求下降与竞争加剧（上海石创收入下滑主因）；高纯石英砂价格自2023年高点回落八成
A53: 光伏 毛利率
A54: 悲观 | B54: % | I54: 0.02 | J54: 0.03 | K54: 0.05 | L54: 0.05 | M54: 0.05
A55: 基准 | B55: % | I55: 0.03 | J55: 0.08 | K55: 0.1 | L55: 0.12 | M55: 0.12
A56: 乐观 | B56: % | I56: 0.06 | J56: 0.12 | K56: 0.15 | L56: 0.15 | M56: 0.15
A57: 选用（光伏 毛利率） | B57: % | I57: =CHOOSE($C$4,I54,I55,I56) -> 0.03 | J57: =CHOOSE($C$4,J54,J55,J56) -> 0.08 | K57: =CHOOSE($C$4,K54,K55,K56) -> 0.1 | L57: =CHOOSE($C$4,L54,L55,L56) -> 0.12 | M57: =CHOOSE($C$4,M54,M55,M56) -> 0.12 | N57: 低毛利，含存货跌价压力
A58: 玻纤工业布及其他 收入增速
A59: 悲观 | B59: % | I59: 0.1 | J59: 0 | K59: 0 | L59: 0 | M59: 0
A60: 基准 | B60: % | I60: 0.15 | J60: 0.04 | K60: 0.04 | L60: 0.03 | M60: 0.03
A61: 乐观 | B61: % | I61: 0.18 | J61: 0.06 | K61: 0.05 | L61: 0.04 | M61: 0.04
A62: 选用（玻纤工业布及其他 收入增速） | B62: % | I62: =CHOOSE($C$4,I59,I60,I61) -> 0.15 | J62: =CHOOSE($C$4,J59,J60,J61) -> 0.04 | K62: =CHOOSE($C$4,K59,K60,K61) -> 0.04 | L62: =CHOOSE($C$4,L59,L60,L61) -> 0.03 | M62: =CHOOSE($C$4,M59,M60,M61) -> 0.03 | N62: 中益新材无碱玻纤工业布（2025年非石英电子布收入约1.48亿元）+技术服务等其他收入；2026H1估算+17%，7628布价格自4.6元/米涨至11-12元/米
A63: 玻纤工业布及其他 毛利率
A64: 悲观 | B64: % | I64: 0.27 | J64: 0.2 | K64: 0.2 | L64: 0.2 | M64: 0.2
A65: 基准 | B65: % | I65: 0.29 | J65: 0.24 | K65: 0.23 | L65: 0.22 | M65: 0.22
A66: 乐观 | B66: % | I66: 0.3 | J66: 0.27 | K66: 0.26 | L66: 0.25 | M66: 0.25
A67: 选用（玻纤工业布及其他 毛利率） | B67: % | I67: =CHOOSE($C$4,I64,I65,I66) -> 0.29 | J67: =CHOOSE($C$4,J64,J65,J66) -> 0.24 | K67: =CHOOSE($C$4,K64,K65,K66) -> 0.23 | L67: =CHOOSE($C$4,L64,L65,L66) -> 0.22 | M67: =CHOOSE($C$4,M64,M65,M66) -> 0.22 | N67: 电子级/工业玻纤布2026年涨价，毛利率改善
A68: 石英电子布 年末有效产能
A69: 悲观 | B69: 万米/年 | I69: 200 | J69: 600 | K69: 700 | L69: 750 | M69: 800
A70: 基准 | B70: 万米/年 | I70: 250 | J70: 700 | K70: 1100 | L70: 1400 | M70: 1600
A71: 乐观 | B71: 万米/年 | I71: 300 | J71: 1100 | K71: 1900 | L71: 2400 | M71: 2700
A72: 选用（石英电子布 年末有效产能） | B72: 万米/年 | I72: =CHOOSE($C$4,I69,I70,I71) -> 250 | J72: =CHOOSE($C$4,J69,J70,J71) -> 700 | K72: =CHOOSE($C$4,K69,K70,K71) -> 1100 | L72: =CHOOSE($C$4,L69,L70,L71) -> 1400 | M72: =CHOOSE($C$4,M69,M70,M71) -> 1600 | N72: 年化有效产能（万米/年）。1,000吨电子纱约可支撑800万米以上电子布（按1吨纱≈1万平方米、幅宽1.27米，为自媒体经验口径，可信度低）；产能扩张节奏决定资本开支
A73: 石英电子布 销量
A74: 悲观 | B74: 万米 | I74: 125 | J74: 220 | K74: 350 | L74: 450 | M74: 500
A75: 基准 | B75: 万米 | I75: 134 | J75: 320 | K75: 650 | L75: 950 | M75: 1200
A76: 乐观 | B76: 万米 | I76: 160 | J76: 600 | K76: 1300 | L76: 1800 | M76: 2200
A77: 选用（石英电子布 销量） | B77: 万米 | I77: =CHOOSE($C$4,I74,I75,I76) -> 134 | J77: =CHOOSE($C$4,J74,J75,J76) -> 320 | K77: =CHOOSE($C$4,K74,K75,K76) -> 650 | L77: =CHOOSE($C$4,L74,L75,L76) -> 950 | M77: =CHOOSE($C$4,M74,M75,M76) -> 1200 | N77: 2026H1收入1.53亿元，按约270元/米折约57万米；2026年下半年按约210百万元收入（年化约155万米）。英伟达Rubin Ultra背板选用PTFE、Kyber推迟至2028年，M9预计2027年下半年才成主流，基准2027年约为2026年的2.4倍；悲观情景在建电子纱项目照常投产、产能利用率偏低
A78: 石英电子布 均价（不含税）
A79: 悲观 | B79: 元/米 | I79: 265 | J79: 210 | K79: 170 | L79: 150 | M79: 140
A80: 基准 | B80: 元/米 | I80: 270 | J80: 240 | K80: 210 | L80: 190 | M80: 175
A81: 乐观 | B81: 元/米 | I81: 275 | J81: 260 | K81: 235 | L81: 215 | M81: 200
A82: 选用（石英电子布 均价（不含税）） | B82: 元/米 | I82: =CHOOSE($C$4,I79,I80,I81) -> 270 | J82: =CHOOSE($C$4,J79,J80,J81) -> 240 | K82: =CHOOSE($C$4,K79,K80,K81) -> 210 | L82: =CHOOSE($C$4,L79,L80,L81) -> 190 | M82: =CHOOSE($C$4,M79,M80,M81) -> 175 | N82: 行业报价：2026年3月主流约300元/米（区间250-450）；国内产品较进口低20-30%。中材科技2,400万米、宏和、再升等扩产后价格下行
A83: 石英电子布 毛利率
A84: 悲观 | B84: % | I84: 0.62 | J84: 0.5 | K84: 0.42 | L84: 0.38 | M84: 0.35
A85: 基准 | B85: % | I85: 0.64 | J85: 0.58 | K85: 0.52 | L85: 0.48 | M85: 0.45
A86: 乐观 | B86: % | I86: 0.66 | J86: 0.62 | K86: 0.58 | L86: 0.55 | M86: 0.52
A87: 选用（石英电子布 毛利率） | B87: % | I87: =CHOOSE($C$4,I84,I85,I86) -> 0.64 | J87: =CHOOSE($C$4,J84,J85,J86) -> 0.58 | K87: =CHOOSE($C$4,K84,K85,K86) -> 0.52 | L87: =CHOOSE($C$4,L84,L85,L86) -> 0.48 | M87: =CHOOSE($C$4,M84,M85,M86) -> 0.45 | N87: 中益新材2026H1净利率35%（营收2.28亿、净利0.81亿），推算石英电子布毛利率约60%-65%；竞争加剧后逐年下行

Sheet 业务拆分
A1: 业务拆分：按下游应用的收入与毛利（百万元）
A2: 历史拆分为基于公司公告（分产品/产销量/子公司/管理层口径）的估算，置信度见备注；预测由“假设”表情景驱动。
A4: 百万元 | B4: 单位 | C4: 2020A | D4: 2021A | E4: 2022A | F4: 2023A | G4: 2024A | H4: 2025A | I4: 2026E | J4: 2027E | K4: 2028E | L4: 2029E | M4: 2030E | N4: 说明 / 来源
A5: 半导体
A6: 收入 | B6: 百万元 | C6: 377.5 | D6: 487 | E6: 654.78 | F6: 726.52 | G6: 806.46 | H6: 897.5 | I6: =H6*(1+假设!I12) -> 1148.8 | J6: =I6*(1+假设!J12) -> 1355.584 | K6: =J6*(1+假设!K12) -> 1545.3658 | L6: =K6*(1+假设!L12) -> 1715.356 | M6: =L6*(1+假设!M12) -> 1869.738 | N6: 历史分业务为本报告估算：两套方法（自下而上产销量法、子公司+增速法，共用部分披露锚点）取均值，收入与毛利均与报表勾稽；航空航天收入与半导体、航空航天毛利率为倒算项（两法差异见“底稿”），半导体置信度中等，其余偏低
A7: 同比 | B7: % | D7: =IFERROR(D6/C6-1,0) -> 0.29006623 | E7: =IFERROR(E6/D6-1,0) -> 0.34451745 | F7: =IFERROR(F6/E6-1,0) -> 0.10956352 | G7: =IFERROR(G6/F6-1,0) -> 0.11003138 | H7: =IFERROR(H6/G6-1,0) -> 0.11288843 | I7: =IFERROR(I6/H6-1,0) -> 0.28 | J7: =IFERROR(J6/I6-1,0) -> 0.18 | K7: =IFERROR(K6/J6-1,0) -> 0.14 | ... M7: =IFERROR(M6/L6-1,0) -> 0.09
A8: 毛利率 | B8: % | C8: 0.5052 | D8: 0.5118 | E8: 0.548 | F8: 0.554 | G8: 0.4911 | H8: 0.5136 | I8: =假设!I17 -> 0.51 | J8: =假设!J17 -> 0.51 | K8: =假设!K17 -> 0.51 | L8: =假设!L17 -> 0.5 | M8: =假设!M17 -> 0.5
A9: 毛利 | B9: 百万元 | C9: =C6*C8 -> 190.713 | D9: =D6*D8 -> 249.2466 | E9: =E6*E8 -> 358.81944 | F9: =F6*F8 -> 402.49208 | G9: =G6*G8 -> 396.05251 | H9: =H6*H8 -> 460.956 | I9: =I6*I8 -> 585.888 | J9: =J6*J8 -> 691.34784 | ... M9: =M6*M8 -> 934.86902
A10: 航空航天
A11: 收入 | B11: 百万元 | C11: 306.14 | D11: 430.71 | E11: 545.74 | F11: 548.59 | G11: 322.58 | H11: 426.94 | I11: =H11*(1+假设!I22) -> 490.981 | J11: =I11*(1+假设!J22) -> 549.89872 | K11: =J11*(1+假设!K22) -> 604.88859 | L11: =K11*(1+假设!L22) -> 647.23079 | M11: =L11*(1+假设!M22) -> 686.06464 | N11: 历史分业务为本报告估算：两套方法（自下而上产销量法、子公司+增速法，共用部分披露锚点）取均值，收入与毛利均与报表勾稽；航空航天收入与半导体、航空航天毛利率为倒算项（两法差异见“底稿”），半导体置信度中等，其余偏低
A12: 同比 | B12: % | D12: =IFERROR(D11/C11-1,0) -> 0.40690534 | E12: =IFERROR(E11/D11-1,0) -> 0.26707065 | F12: =IFERROR(F11/E11-1,0) -> 0.005222267 | G12: =IFERROR(G11/F11-1,0) -> -0.41198345 | H12: =IFERROR(H11/G11-1,0) -> 0.32351665 | I12: =IFERROR(I11/H11-1,0) -> 0.15 | J12: =IFERROR(J11/I11-1,0) -> 0.12 | K12: =IFERROR(K11/J11-1,0) -> 0.1 | ... M12: =IFERROR(M11/L11-1,0) -> 0.06
A13: 毛利率 | B13: % | C13: 0.6307 | D13: 0.6288 | E13: 0.673 | F13: 0.6935 | G13: 0.5821 | H13: 0.6366 | I13: =假设!I27 -> 0.61 | J13: =假设!J27 -> 0.61 | K13: =假设!K27 -> 0.6 | L13: =假设!L27 -> 0.6 | M13: =假设!M27 -> 0.59
A14: 毛利 | B14: 百万元 | C14: =C11*C13 -> 193.0825 | D14: =D11*D13 -> 270.83045 | E14: =E11*E13 -> 367.28302 | F14: =F11*F13 -> 380.44716 | G14: =G11*G13 -> 187.77382 | H14: =H11*H13 -> 271.79 | I14: =I11*I13 -> 299.49841 | J14: =J11*J13 -> 335.43822 | ... M14: =M11*M13 -> 404.77814
A15: 光学（合成石英/光掩膜基板）
A16: 收入 | B16: 百万元 | C16: 72.5 | D16: 87.5 | E16: 104 | F16: 122.5 | G16: 128.5 | H16: 184 | I16: =H16*(1+假设!I32) -> 253.92 | J16: =I16*(1+假设!J32) -> 325.0176 | K16: =J16*(1+假设!K32) -> 396.52147 | L16: =K16*(1+假设!L32) -> 459.96491 | M16: =L16*(1+假设!M32) -> 515.1607 | N16: 历史分业务为本报告估算：两套方法（自下而上产销量法、子公司+增速法，共用部分披露锚点）取均值，收入与毛利均与报表勾稽；航空航天收入与半导体、航空航天毛利率为倒算项（两法差异见“底稿”），半导体置信度中等，其余偏低
A17: 同比 | B17: % | D17: =IFERROR(D16/C16-1,0) -> 0.20689655 | E17: =IFERROR(E16/D16-1,0) -> 0.18857143 | F17: =IFERROR(F16/E16-1,0) -> 0.17788462 | G17: =IFERROR(G16/F16-1,0) -> 0.048979592 | H17: =IFERROR(H16/G16-1,0) -> 0.43190661 | I17: =IFERROR(I16/H16-1,0) -> 0.38 | J17: =IFERROR(J16/I16-1,0) -> 0.28 | K17: =IFERROR(K16/J16-1,0) -> 0.22 | ... M17: =IFERROR(M16/L16-1,0) -> 0.12
A18: 毛利率 | B18: % | C18: 0.5045 | D18: 0.5045 | E18: 0.5025 | F18: 0.4975 | G18: 0.4725 | H18: 0.487 | I18: =假设!I37 -> 0.49 | J18: =假设!J37 -> 0.5 | K18: =假设!K37 -> 0.5 | L18: =假设!L37 -> 0.5 | M18: =假设!M37 -> 0.5
A19: 毛利 | B19: 百万元 | C19: =C16*C18 -> 36.57625 | D19: =D16*D18 -> 44.14375 | E19: =E16*E18 -> 52.26 | F19: =F16*F18 -> 60.94375 | G19: =G16*G18 -> 60.71625 | H19: =H16*H18 -> 89.608 | I19: =I16*I18 -> 124.4208 | J19: =J16*J18 -> 162.5088 | ... M19: =M16*M18 -> 257.58035
A20: 光通讯
A21: 收入 | B21: 百万元 | C21: 62.27 | D21: 73.76 | E21: 110.12 | F21: 146.83 | G21: 137.81 | H21: 167.26 | I21: =H21*(1+假设!I42) -> 242.527 | J21: =I21*(1+假设!J42) -> 261.92916 | K21: =J21*(1+假设!K42) -> 248.8327 | L21: =K21*(1+假设!L42) -> 248.8327 | M21: =L21*(1+假设!M42) -> 256.29768 | N21: 历史分业务为本报告估算：两套方法（自下而上产销量法、子公司+增速法，共用部分披露锚点）取均值，收入与毛利均与报表勾稽；航空航天收入与半导体、航空航天毛利率为倒算项（两法差异见“底稿”），半导体置信度中等，其余偏低
A22: 同比 | B22: % | D22: =IFERROR(D21/C21-1,0) -> 0.18451903 | E22: =IFERROR(E21/D21-1,0) -> 0.49295011 | F22: =IFERROR(F21/E21-1,0) -> 0.3333636 | G22: =IFERROR(G21/F21-1,0) -> -0.061431588 | H22: =IFERROR(H21/G21-1,0) -> 0.21370002 | I22: =IFERROR(I21/H21-1,0) -> 0.45 | J22: =IFERROR(J21/I21-1,0) -> 0.08 | K22: =IFERROR(K21/J21-1,0) -> -0.05 | ... M22: =IFERROR(M21/L21-1,0) -> 0.03
A23: 毛利率 | B23: % | C23: 0.31 | D23: 0.31 | E23: 0.31 | F23: 0.315 | G23: 0.23 | H23: 0.26 | I23: =假设!I47 -> 0.34 | J23: =假设!J47 -> 0.3 | K23: =假设!K47 -> 0.27 | L23: =假设!L47 -> 0.27 | M23: =假设!M47 -> 0.27
A24: 毛利 | B24: 百万元 | C24: =C21*C23 -> 19.3037 | D24: =D21*D23 -> 22.8656 | E24: =E21*E23 -> 34.1372 | F24: =F21*F23 -> 46.25145 | G24: =G21*G23 -> 31.6963 | H24: =H21*H23 -> 43.4876 | I24: =I21*I23 -> 82.45918 | J24: =J21*J23 -> 78.578748 | ... M24: =M21*M23 -> 69.200374
A25: 光伏
A26: 收入 | B26: 百万元 | C26: 26.5 | D26: 50 | E26: 168.45 | F26: 349.8 | G26: 180.34 | H26: 89.05 | I26: =H26*(1+假设!I52) -> 66.7875 | J26: =I26*(1+假设!J52) -> 66.7875 | K26: =J26*(1+假设!K52) -> 68.791125 | L26: =K26*(1+假设!L52) -> 70.854859 | M26: =L26*(1+假设!M52) -> 72.980505 | N26: 历史分业务为本报告估算：两套方法（自下而上产销量法、子公司+增速法，共用部分披露锚点）取均值，收入与毛利均与报表勾稽；航空航天收入与半导体、航空航天毛利率为倒算项（两法差异见“底稿”），半导体置信度中等，其余偏低
A27: 同比 | B27: % | D27: =IFERROR(D26/C26-1,0) -> 0.88679245 | E27: =IFERROR(E26/D26-1,0) -> 2.369 | F27: =IFERROR(F26/E26-1,0) -> 1.0765806 | G27: =IFERROR(G26/F26-1,0) -> -0.48444826 | H27: =IFERROR(H26/G26-1,0) -> -0.50621049 | I27: =IFERROR(I26/H26-1,0) -> -0.25 | J27: =IFERROR(J26/I26-1,0) -> 0 | K27: =IFERROR(K26/J26-1,0) -> 0.03 | ... M27: =IFERROR(M26/L26-1,0) -> 0.03
A28: 毛利率 | B28: % | C28: 0.24 | D28: 0.24 | E28: 0.265 | F28: 0.3 | G28: 0.126 | H28: 0.045 | I28: =假设!I57 -> 0.03 | J28: =假设!J57 -> 0.08 | K28: =假设!K57 -> 0.1 | L28: =假设!L57 -> 0.12 | M28: =假设!M57 -> 0.12
A29: 毛利 | B29: 百万元 | C29: =C26*C28 -> 6.36 | D29: =D26*D28 -> 12 | E29: =E26*E28 -> 44.63925 | F29: =F26*F28 -> 104.94 | G29: =G26*G28 -> 22.72284 | H29: =H26*H28 -> 4.00725 | I29: =I26*I28 -> 2.003625 | J29: =J26*J28 -> 5.343 | ... M29: =M26*M28 -> 8.7576605
A30: 石英电子布
A31: 年末有效产能 | B31: 万米/年 | H31: 100 | I31: =假设!I72 -> 250 | J31: =假设!J72 -> 700 | K31: =假设!K72 -> 1100 | L31: =假设!L72 -> 1400 | M31: =假设!M72 -> 1600 | N31: 年化有效产能（万米/年）。1,000吨电子纱约可支撑800万米以上电子布（按1吨纱≈1万平方米、幅宽1.27米，为自媒体经验口径，可信度低）；产能扩张节奏决定资本开支
A32: 销量 | B32: 万米 | H32: 37.8 | I32: =假设!I77 -> 134 | J32: =假设!J77 -> 320 | K32: =假设!K77 -> 650 | L32: =假设!L77 -> 950 | M32: =假设!M77 -> 1200
A33: 产能利用率（销量/年均产能） | B33: % | I33: =IFERROR(I32/AVERAGE(I31,H31),0) -> 0.76571429 | J33: =IFERROR(J32/AVERAGE(J31,I31),0) -> 0.67368421 | K33: =IFERROR(K32/AVERAGE(K31,J31),0) -> 0.72222222 | L33: =IFERROR(L32/AVERAGE(L31,K31),0) -> 0.76 | M33: =IFERROR(M32/AVERAGE(M31,L31),0) -> 0.8 | N33: >100% 说明销量假设超出产能，需上调产能或下调销量
A34: 均价（不含税） | B34: 元/米 | H34: 260 | I34: =假设!I82 -> 270 | J34: =假设!J82 -> 240 | K34: =假设!K82 -> 210 | L34: =假设!L82 -> 190 | M34: =假设!M82 -> 175
A35: 收入 | B35: 百万元 | C35: 0 | D35: 0 | E35: 0 | F35: 0 | G35: 2.5 | H35: 98.39 | I35: =I32*I34/100 -> 361.8 | J35: =J32*J34/100 -> 768 | K35: =K32*K34/100 -> 1365 | L35: =L32*L34/100 -> 1805 | M35: =M32*M34/100 -> 2100 | N35: 万米×元/米÷100 = 百万元；2025年石英电子布收入9,837.37万元（公司披露）；2026H1 1.53亿元
A36: 毛利率 | B36: % | C36: 0.6 | D36: 0.6 | E36: 0.6 | F36: 0.6 | G36: 0.45 | H36: 0.54 | I36: =假设!I87 -> 0.64 | J36: =假设!J87 -> 0.58 | K36: =假设!K87 -> 0.52 | L36: =假设!L87 -> 0.48 | M36: =假设!M87 -> 0.45
A37: 毛利 | B37: 百万元 | C37: =C35*C36 -> 0 | D37: =D35*D36 -> 0 | E37: =E35*E36 -> 0 | F37: =F35*F36 -> 0 | G37: =G35*G36 -> 1.125 | H37: =H35*H36 -> 53.1306 | I37: =I35*I36 -> 231.552 | J37: =J35*J36 -> 445.44 | ... M37: =M35*M36 -> 945
A38: 收入同比 | B38: % | D38: =IFERROR(D35/C35-1,0) -> 0 | E38: =IFERROR(E35/D35-1,0) -> 0 | F38: =IFERROR(F35/E35-1,0) -> 0 | G38: =IFERROR(G35/F35-1,0) -> 0 | H38: =IFERROR(H35/G35-1,0) -> 38.356 | I38: =IFERROR(I35/H35-1,0) -> 2.677203 | J38: =IFERROR(J35/I35-1,0) -> 1.1227197 | K38: =IFERROR(K35/J35-1,0) -> 0.77734375 | ... M38: =IFERROR(M35/L35-1,0) -> 0.1634349
A39: 玻纤工业布及其他
A40: 收入 | B40: 百万元 | C40: 18.67 | D40: 94.58 | E40: 136.28 | F40: 196.31 | G40: 163.62 | H40: 153.21 | I40: =H40*(1+假设!I62) -> 176.1915 | J40: =I40*(1+假设!J62) -> 183.23916 | K40: =J40*(1+假设!K62) -> 190.56873 | L40: =K40*(1+假设!L62) -> 196.28579 | M40: =L40*(1+假设!M62) -> 202.17436 | N40: 历史分业务为本报告估算：两套方法（自下而上产销量法、子公司+增速法，共用部分披露锚点）取均值，收入与毛利均与报表勾稽；航空航天收入与半导体、航空航天毛利率为倒算项（两法差异见“底稿”），半导体置信度中等，其余偏低
A41: 同比 | B41: % | D41: =IFERROR(D40/C40-1,0) -> 4.0658811 | E41: =IFERROR(E40/D40-1,0) -> 0.4408966 | F41: =IFERROR(F40/E40-1,0) -> 0.44049017 | G41: =IFERROR(G40/F40-1,0) -> -0.16652234 | H41: =IFERROR(H40/G40-1,0) -> -0.063623029 | I41: =IFERROR(I40/H40-1,0) -> 0.15 | J41: =IFERROR(J40/I40-1,0) -> 0.04 | K41: =IFERROR(K40/J40-1,0) -> 0.04 | ... M41: =IFERROR(M40/L40-1,0) -> 0.03
A42: 毛利率 | B42: % | C42: 0.1955 | D42: 0.237 | E42: 0.1725 | F42: 0.2 | G42: 0.2105 | H42: 0.211 | I42: =假设!I67 -> 0.29 | J42: =假设!J67 -> 0.24 | K42: =假设!K67 -> 0.23 | L42: =假设!L67 -> 0.22 | M42: =假设!M67 -> 0.22
A43: 毛利 | B43: 百万元 | C43: =C40*C42 -> 3.649985 | D43: =D40*D42 -> 22.41546 | E43: =E40*E42 -> 23.5083 | F43: =F40*F42 -> 39.262 | G43: =G40*G42 -> 34.44201 | H43: =H40*H42 -> 32.32731 | I43: =I40*I42 -> 51.095535 | J43: =J40*J42 -> 43.977398 | ... M43: =M40*M42 -> 44.47836
A44: 合计
A45: 营业收入合计（分业务加总） | B45: 百万元 | C45: =C6+C11+C16+C21+C26+C35+C40 -> 863.58 | D45: =D6+D11+D16+D21+D26+D35+D40 -> 1223.55 | E45: =E6+E11+E16+E21+E26+E35+E40 -> 1719.37 | F45: =F6+F11+F16+F21+F26+F35+F40 -> 2090.55 | G45: =G6+G11+G16+G21+G26+G35+G40 -> 1741.81 | H45: =H6+H11+H16+H21+H26+H35+H40 -> 2016.35 | I45: =I6+I11+I16+I21+I26+I35+I40 -> 2741.007 | J45: =J6+J11+J16+J21+J26+J35+J40 -> 3510.4561 | ... M45: =M6+M11+M16+M21+M26+M35+M40 -> 5702.4159
A46: 报告营业收入（历史） | B46: 百万元 | C46: 863.5783 | D46: 1223.5484 | E46: 1719.3652 | F46: 2090.5426 | G46: 1741.8114 | H46: 2016.3489 | N46: 来源：Wind（公司公告值），万元÷100
A47: 差异（应为0） | B47: 百万元 | C47: =C45-C46 -> 0.0017 | D47: =D45-D46 -> 0.0016 | E47: =E45-E46 -> 0.0048 | F47: =F45-F46 -> 0.0074 | G47: =G45-G46 -> -0.0014 | H47: =H45-H46 -> 0.0011
A48: 收入同比 | B48: % | D48: =IFERROR(D45/C45-1,0) -> 0.41683457 | E48: =IFERROR(E45/D45-1,0) -> 0.40523068 | F48: =IFERROR(F45/E45-1,0) -> 0.2158814 | G48: =IFERROR(G45/F45-1,0) -> -0.16681734 | H48: =IFERROR(H45/G45-1,0) -> 0.15761765 | I48: =I45/H45-1 -> 0.35939048 | J48: =J45/I45-1 -> 0.28071769 | K48: =K45/J45-1 -> 0.25908663 | L48: =L45/K45-1 -> 0.16370177 | M48: =M45/L45-1 -> 0.10865911
A49: 毛利合计 | B49: 百万元 | C49: =C9+C14+C19+C24+C29+C37+C43 -> 449.68543 | D49: =D9+D14+D19+D24+D29+D37+D43 -> 621.50186 | E49: =E9+E14+E19+E24+E29+E37+E43 -> 880.64721 | F49: =F9+F14+F19+F24+F29+F37+F43 -> 1034.3364 | G49: =G9+G14+G19+G24+G29+G37+G43 -> 734.52872 | H49: =H9+H14+H19+H24+H29+H37+H43 -> 955.30676 | I49: =I9+I14+I19+I24+I29+I37+I43 -> 1376.9175 | J49: =J9+J14+J19+J24+J29+J37+J43 -> 1762.634 | ... M49: =M9+M14+M19+M24+M29+M37+M43 -> 2664.6639
A50: 营业成本合计 | B50: 百万元 | C50: =C45-C49 -> 413.89457 | D50: =D45-D49 -> 602.04814 | E50: =E45-E49 -> 838.72279 | F50: =F45-F49 -> 1056.2136 | G50: =G45-G49 -> 1007.2813 | H50: =H45-H49 -> 1061.0432 | I50: =I45-I49 -> 1364.0894 | J50: =J45-J49 -> 1747.8221 | ... M50: =M45-M49 -> 3037.752
A51: 综合毛利率 | B51: % | C51: =IFERROR(C49/C45,0) -> 0.52072238 | D51: =IFERROR(D49/D45,0) -> 0.5079497 | E51: =IFERROR(E49/E45,0) -> 0.5121918 | F51: =IFERROR(F49/F45,0) -> 0.49476762 | G51: =IFERROR(G49/G45,0) -> 0.42170428 | H51: =IFERROR(H49/H45,0) -> 0.47378023 | I51: =I49/I45 -> 0.50234003 | J51: =J49/J45 -> 0.50210968 | K51: =K49/K45 -> 0.49254316 | L51: =L49/L45 -> 0.47851798 | M51: =M49/M45 -> 0.46728684
A52: 报告毛利率（历史） | B52: % | C52: 0.5207 | D52: 0.5079 | E52: 0.5122 | F52: 0.4948 | G52: 0.4217 | H52: 0.4738 | N52: 历史分业务毛利率为估算，加总后与报告毛利率的差异计入“其他”
A54: 收入结构
A55: 半导体 占比 | B55: % | C55: =IFERROR(C6/C45,0) -> 0.43713379 | D55: =IFERROR(D6/D45,0) -> 0.39802215 | E55: =IFERROR(E6/E45,0) -> 0.38082553 | F55: =IFERROR(F6/F45,0) -> 0.34752577 | G55: =IFERROR(G6/G45,0) -> 0.46300113 | H55: =IFERROR(H6/H45,0) -> 0.44511122 | I55: =I6/I45 -> 0.41911604 | J55: =J6/J45 -> 0.38615609 | K55: =K6/K45 -> 0.34963276 | L55: =L6/L45 -> 0.33349813 | M55: =M6/M45 -> 0.32788524
A56: 航空航天 占比 | B56: % | C56: =IFERROR(C11/C45,0) -> 0.35450103 | D56: =IFERROR(D11/D45,0) -> 0.35201667 | E56: =IFERROR(E11/E45,0) -> 0.31740696 | F56: =IFERROR(F11/F45,0) -> 0.2624142 | G56: =IFERROR(G11/G45,0) -> 0.18519816 | H56: =IFERROR(H11/H45,0) -> 0.21173903 | I56: =I11/I45 -> 0.17912431 | J56: =J11/J45 -> 0.15664595 | K56: =K11/K45 -> 0.1368536 | L56: =L11/L45 -> 0.12583409 | M56: =M11/M45 -> 0.12031122
A57: 光学（合成石英/光掩膜基板） 占比 | B57: % | C57: =IFERROR(C16/C45,0) -> 0.083952847 | D57: =IFERROR(D16/D45,0) -> 0.07151322 | E57: =IFERROR(E16/E45,0) -> 0.060487272 | F57: =IFERROR(F16/F45,0) -> 0.05859702 | G57: =IFERROR(G16/G45,0) -> 0.073773833 | H57: =IFERROR(H16/H45,0) -> 0.091253999 | I57: =I16/I45 -> 0.092637487 | J57: =J16/J45 -> 0.092585575 | K57: =K16/K45 -> 0.089711382 | L57: =L16/L45 -> 0.089426007 | M57: =M16/M45 -> 0.090340779
A58: 光通讯 占比 | B58: % | C58: =IFERROR(C21/C45,0) -> 0.072106811 | D58: =IFERROR(D21/D45,0) -> 0.060283601 | E58: =IFERROR(E21/E45,0) -> 0.064046715 | F58: =IFERROR(F21/F45,0) -> 0.070235106 | G58: =IFERROR(G21/G45,0) -> 0.079118848 | H58: =IFERROR(H21/H45,0) -> 0.082951868 | I58: =I21/I45 -> 0.088480985 | J58: =J21/J45 -> 0.074613996 | K58: =K21/K45 -> 0.056297394 | L58: =L21/L45 -> 0.048377854 | M58: =M21/M45 -> 0.044945456
A59: 光伏 占比 | B59: % | C59: =IFERROR(C26/C45,0) -> 0.030686213 | D59: =IFERROR(D26/D45,0) -> 0.040864697 | E59: =IFERROR(E26/E45,0) -> 0.097971932 | F59: =IFERROR(F26/F45,0) -> 0.16732439 | G59: =IFERROR(G26/G45,0) -> 0.10353598 | H59: =IFERROR(H26/H45,0) -> 0.04416396 | I59: =I26/I45 -> 0.024366045 | J59: =J26/J45 -> 0.019025305 | K59: =K26/K45 -> 0.015563714 | L59: =L26/L45 -> 0.013775545 | M59: =M26/M45 -> 0.012798173
A60: 石英电子布 占比 | B60: % | C60: =IFERROR(C35/C45,0) -> 0 | D60: =IFERROR(D35/D45,0) -> 0 | E60: =IFERROR(E35/E45,0) -> 0 | F60: =IFERROR(F35/F45,0) -> 0 | G60: =IFERROR(G35/G45,0) -> 0.0014352886 | H60: =IFERROR(H35/H45,0) -> 0.048796092 | I60: =I35/I45 -> 0.13199528 | J60: =J35/J45 -> 0.21877499 | K60: =K35/K45 -> 0.30882574 | L60: =L35/L45 -> 0.35092665 | M60: =M35/M45 -> 0.36826497
A61: 玻纤工业布及其他 占比 | B61: % | C61: =IFERROR(C40/C45,0) -> 0.021619306 | D61: =IFERROR(D40/D45,0) -> 0.077299661 | E61: =IFERROR(E40/E45,0) -> 0.07926159 | F61: =IFERROR(F40/F45,0) -> 0.093903518 | G61: =IFERROR(G40/G45,0) -> 0.093936767 | H61: =IFERROR(H40/H45,0) -> 0.075983832 | I61: =I40/I45 -> 0.064279843 | J61: =J40/J45 -> 0.052198106 | K61: =K40/K45 -> 0.043115405 | L61: =L40/L45 -> 0.038161725 | M61: =M40/M45 -> 0.035454159
A62: 毛利结构
A63: 半导体 毛利占比 | B63: % | C63: =IFERROR(C9/C49,0) -> 0.42410313 | D63: =IFERROR(D9/D49,0) -> 0.40103919 | E63: =IFERROR(E9/E49,0) -> 0.4074497 | F63: =IFERROR(F9/F49,0) -> 0.38913071 | G63: =IFERROR(G9/G49,0) -> 0.53919267 | H63: =IFERROR(H9/H49,0) -> 0.48252144 | I63: =I9/I49 -> 0.42550696 | J63: =J9/J49 -> 0.39222427 | K63: =K9/K49 -> 0.36202454 | L63: =L9/L49 -> 0.3484698 | M63: =M9/M49 -> 0.35083938
A64: 航空航天 毛利占比 | B64: % | C64: =IFERROR(C14/C49,0) -> 0.42937237 | D64: =IFERROR(D14/D49,0) -> 0.43576772 | E64: =IFERROR(E14/E49,0) -> 0.41706033 | F64: =IFERROR(F14/F49,0) -> 0.36781762 | G64: =IFERROR(G14/G49,0) -> 0.2556385 | H64: =IFERROR(H14/H49,0) -> 0.28450547 | I64: =I14/I49 -> 0.21751368 | J64: =J14/J49 -> 0.19030509 | K64: =K14/K49 -> 0.16671059 | L64: =L14/L49 -> 0.15777976 | M64: =M14/M49 -> 0.15190589
A65: 光学（合成石英/光掩膜基板） 毛利占比 | B65: % | C65: =IFERROR(C19/C49,0) -> 0.081337413 | D65: =IFERROR(D19/D49,0) -> 0.071027543 | E65: =IFERROR(E19/E49,0) -> 0.059342719 | F65: =IFERROR(F19/F49,0) -> 0.058920625 | G65: =IFERROR(G19/G49,0) -> 0.082660144 | H65: =IFERROR(H19/H49,0) -> 0.093800236 | I65: =I19/I49 -> 0.090361838 | J65: =J19/J49 -> 0.092196565 | K65: =K19/K49 -> 0.091069565 | L65: =L19/L49 -> 0.093440593 | M65: =M19/M49 -> 0.09666523
A66: 光通讯 毛利占比 | B66: % | C66: =IFERROR(C24/C49,0) -> 0.042927119 | D66: =IFERROR(D24/D49,0) -> 0.03679088 | E66: =IFERROR(E24/E49,0) -> 0.038763763 | F66: =IFERROR(F24/F49,0) -> 0.044716059 | G66: =IFERROR(G24/G49,0) -> 0.043151886 | H66: =IFERROR(H24/H49,0) -> 0.045522131 | I66: =I24/I49 -> 0.059886796 | J66: =J24/J49 -> 0.044580297 | K66: =K24/K49 -> 0.030860842 | L66: =L24/L49 -> 0.027296823 | M66: =M24/M49 -> 0.025969645
A67: 光伏 毛利占比 | B67: % | C67: =IFERROR(C29/C49,0) -> 0.01414322 | D67: =IFERROR(D29/D49,0) -> 0.019308068 | E67: =IFERROR(E29/E49,0) -> 0.05068914 | F67: =IFERROR(F29/F49,0) -> 0.10145635 | G67: =IFERROR(G29/G49,0) -> 0.030935264 | H67: =IFERROR(H29/H49,0) -> 0.0041947259 | I67: =I29/I49 -> 0.0014551525 | J67: =J29/J49 -> 0.0030312589 | K67: =K29/K49 -> 0.0031598681 | L67: =L29/L49 -> 0.0034545522 | M67: =M29/M49 -> 0.0032865911
A68: 石英电子布 毛利占比 | B68: % | C68: =IFERROR(C37/C49,0) -> 0 | D68: =IFERROR(D37/D49,0) -> 0 | E68: =IFERROR(E37/E49,0) -> 0 | F68: =IFERROR(F37/F49,0) -> 0 | G68: =IFERROR(G37/G49,0) -> 0.0015315943 | H68: =IFERROR(H37/H49,0) -> 0.055616271 | I68: =I37/I49 -> 0.16816693 | J68: =J37/J49 -> 0.2527127 | K68: =K37/K49 -> 0.32604125 | L68: =L37/L49 -> 0.3520135 | M68: =M37/M49 -> 0.35464135
A69: 玻纤工业布及其他 毛利占比 | B69: % | C69: =IFERROR(C43/C49,0) -> 0.0081167517 | D69: =IFERROR(D43/D49,0) -> 0.036066602 | E69: =IFERROR(E43/E49,0) -> 0.026694344 | F69: =IFERROR(F43/F49,0) -> 0.037958635 | G69: =IFERROR(G43/G49,0) -> 0.046889943 | H69: =IFERROR(H43/H49,0) -> 0.033839716 | I69: =I43/I49 -> 0.037108638 | J69: =J43/J49 -> 0.024949818 | K69: =K43/K49 -> 0.020133349 | L69: =L43/L49 -> 0.017544961 | M69: =M43/M49 -> 0.016691921
A71: 分部经营利润与归母净利润（用于SOTP；费用按收入占比分摊，研发对电子布/半导体加权）
A72: 分摊口径：期间费用（销售+管理+研发+税金及附加）按“费用权重×收入”分摊；所得税按有效税率；少数股东比例为该业务所在主体的少数股东持股（见“底稿-子公司”）。
A73: 半导体 费用权重 | B73: x | I73: 1.2 | J73: 1.2 | K73: 1.2 | L73: 1.2 | M73: 1.2
A74: 航空航天 费用权重 | B74: x | I74: 1 | J74: 1 | K74: 1 | L74: 1 | M74: 1
A75: 光学（合成石英/光掩膜基板） 费用权重 | B75: x | I75: 1.8 | J75: 1.8 | K75: 1.8 | L75: 1.8 | M75: 1.8
A76: 光通讯 费用权重 | B76: x | I76: 0.6 | J76: 0.6 | K76: 0.6 | L76: 0.6 | M76: 0.6
A77: 光伏 费用权重 | B77: x | I77: 0.6 | J77: 0.6 | K77: 0.6 | L77: 0.6 | M77: 0.6
A78: 石英电子布 费用权重 | B78: x | I78: 0.5 | J78: 0.5 | K78: 0.5 | L78: 0.5 | M78: 0.5
A79: 玻纤工业布及其他 费用权重 | B79: x | I79: 0.5 | J79: 0.5 | K79: 0.5 | L79: 0.5 | M79: 0.5
A80: 加权收入合计 | B80: 百万元 | I80: =I6*I73+I11*I74+I16*I75+I21*I76+I26*I77+I35*I78+I40*I79 -> 2781.1815 | J80: =J6*J73+J11*J74+J16*J75+J21*J76+J26*J77+J35*J78+J40*J79 -> 3434.4808 | K80: =K6*K73+K11*K74+K16*K75+K21*K76+K26*K77+K35*K78+K40*K79 -> 4141.4248 | L80: =L6*L73+L11*L74+L16*L75+L21*L76+L26*L77+L35*L78+L40*L79 -> 4726.0502 | M80: =M6*M73+M11*M74+M16*M75+M21*M76+M26*M77+M35*M78+M40*M79 -> 5205.6936
A81: 半导体 经营利润 | B81: 百万元 | I81: =I9-(利润表!I31)*I6*I73/I80 -> 262.42314 | J81: =J9-(利润表!J31)*J6*J73/J80 -> 314.07668 | K81: =K9-(利润表!K31)*K6*K73/K80 -> 402.85301 | L81: =L9-(利润表!L31)*L6*L73/L80 -> 458.78909 | M81: =M9-(利润表!M31)*M6*M73/M80 -> 520.11037
A82: 航空航天 经营利润 | B82: 百万元 | I82: =I14-(利润表!I31)*I11*I74/I80 -> 184.29479 | J82: =J14-(利润表!J31)*J11*J74/J80 -> 207.90344 | K82: =K14-(利润表!K31)*K11*K74/K80 -> 237.25977 | L82: =L14-(利润表!L31)*L11*L74/L80 -> 262.91593 | M82: =M14-(利润表!M31)*M11*M74/M80 -> 277.955
A83: 光学（合成石英/光掩膜基板） 经营利润 | B83: 百万元 | I83: =I19-(利润表!I31)*I16*I75/I80 -> 17.177331 | J83: =J19-(利润表!J31)*J16*J75/J80 -> 26.82584 | K83: =K19-(利润表!K31)*K16*K75/K80 -> 49.972356 | L83: =L19-(利润表!L31)*L16*L75/L80 -> 69.542084 | M83: =M19-(利润表!M31)*M16*M75/M80 -> 86.165409
A84: 光通讯 经营利润 | B84: 百万元 | I84: =I24-(利润表!I31)*I21*I76/I80 -> 48.315307 | J84: =J24-(利润表!J31)*J21*J76/J80 -> 42.130133 | K84: =K24-(利润表!K31)*K21*K76/K80 -> 36.165914 | L84: =L24-(利润表!L31)*L21*L76/L80 -> 38.253049 | M84: =M24-(利润表!M31)*M21*M76/M80 -> 40.773483
A85: 光伏 经营利润 | B85: 百万元 | I85: =I29-(利润表!I31)*I26*I77/I80 -> -7.3989732 | J85: =J29-(利润表!J31)*J26*J77/J80 -> -3.9507795 | K85: =K29-(利润表!K31)*K26*K77/K80 -> -1.6962318 | L85: =L29-(利润表!L31)*L26*L77/L80 -> 0.26428807 | M85: =M29-(利润表!M31)*M26*M77/M80 -> 0.6631321
A86: 石英电子布 经营利润 | B86: 百万元 | I86: =I37-(利润表!I31)*I35*I78/I80 -> 189.10568 | J86: =J37-(利润表!J31)*J35*J78/J80 -> 356.38114 | K86: =K37-(利润表!K31)*K35*K78/K80 -> 568.00185 | L86: =L37-(利润表!L31)*L35*L78/L80 -> 691.51053 | M86: =M37-(利润表!M31)*M35*M78/M80 -> 750.90125
A87: 玻纤工业布及其他 经营利润 | B87: 百万元 | I87: =I43-(利润表!I31)*I40*I79/I80 -> 30.424777 | J87: =J43-(利润表!J31)*J40*J79/J80 -> 22.728608 | K87: =K43-(利润表!K31)*K40*K79/K80 -> 24.034256 | L87: =L43-(利润表!L31)*L40*L79/L80 -> 24.164415 | M87: =M43-(利润表!M31)*M40*M79/M80 -> 25.791792
A88: 半导体 少数股东比例 | B88: % | I88: 0 | J88: 0.03 | K88: 0.06 | L88: 0.08 | M88: 0.1 | N88: 半导体器件经上海石创（穿透持股51.13%）销售，约占半导体收入1/4；石创目前亏损（其少数股东分担额在“费用税率”单列），随扭亏逐步恢复至约10%
A89: 航空航天 少数股东比例 | B89: % | I89: 0 | J89: 0 | K89: 0 | L89: 0 | M89: 0 | N89: 石英纤维为母公司业务
A90: 光学（合成石英/光掩膜基板） 少数股东比例 | B90: % | I90: 0 | J90: 0.08 | K90: 0.14 | L90: 0.15 | M90: 0.15 | N90: 光掩膜基板主体合肥光微（51.13%）、济南光微（30.68%）
A91: 光通讯 少数股东比例 | B91: % | I91: 0 | J91: 0.05 | K91: 0.08 | L91: 0.08 | M91: 0.08 | N91: 2026年6月设立湖北聚通（持股51%）衬管/套管合资项目
A92: 光伏 少数股东比例 | B92: % | I92: 0 | J92: 0 | K92: 0.1 | L92: 0.15 | M92: 0.15 | N92: 光伏器件多经上海石创（48.87%少数股东）
A93: 石英电子布 少数股东比例 | B93: % | I93: 0.5 | J93: 0.44 | K93: 0.38 | L93: 0.35 | M93: 0.35 | N93: 织造主体江苏中益新材料少数股东51.89%（2025年两次增资后公司穿透持股48.11%）；1,000吨电子纱由全资子公司湖北鼎益建设，假设纱线环节利润逐步留在全资主体（未经公司披露，关联交易定价未知）；对应鼎益适用25%税率，额外税负见“费用税率”
A94: 玻纤工业布及其他 少数股东比例 | B94: % | I94: 0.45 | J94: 0.45 | K94: 0.45 | L94: 0.45 | M94: 0.45 | N94: 主要在中益新材（少数股东51.89%）
A95: 半导体 归母净利润（估算） | B95: 百万元 | I95: =I81*(1-费用税率!I23)*(1-I88) -> 231.70751 | J95: =J81*(1-费用税率!J23)*(1-J88) -> 267.38627 | K95: =K81*(1-费用税率!K23)*(1-K88) -> 330.53848 | L95: =L81*(1-费用税率!L23)*(1-L88) -> 367.72125 | M95: =M81*(1-费用税率!M23)*(1-M88) -> 407.12499
A96: 航空航天 归母净利润（估算） | B96: 百万元 | I96: =I82*(1-费用税率!I23)*(1-I89) -> 162.72379 | J96: =J82*(1-费用税率!J23)*(1-J89) -> 182.47079 | K96: =K82*(1-费用税率!K23)*(1-K89) -> 207.09598 | L96: =L82*(1-费用税率!L23)*(1-L89) -> 229.05233 | M96: =M82*(1-费用税率!M23)*(1-M89) -> 241.74875
A97: 光学（合成石英/光掩膜基板） 归母净利润（估算） | B97: 百万元 | I97: =I83*(1-费用税率!I23)*(1-I90) -> 15.16679 | J97: =J83*(1-费用税率!J23)*(1-J90) -> 21.660717 | K97: =K83*(1-费用税率!K23)*(1-K90) -> 37.512485 | L97: =L83*(1-费用税率!L23)*(1-L90) -> 51.497298 | M97: =M83*(1-费用税率!M23)*(1-M90) -> 63.700321
A98: 光通讯 归母净利润（估算） | B98: 百万元 | I98: =I84*(1-费用税率!I23)*(1-I91) -> 42.660184 | J98: =J84*(1-费用税率!J23)*(1-J91) -> 35.127571 | K98: =K84*(1-费用税率!K23)*(1-K91) -> 29.042556 | L98: =L84*(1-费用税率!L23)*(1-L91) -> 30.659969 | M98: =M84*(1-费用税率!M23)*(1-M91) -> 32.625365
A99: 光伏 归母净利润（估算） | B99: 百万元 | I99: =I85*(1-费用税率!I23)*(1-I92) -> -6.5329515 | J99: =J85*(1-费用税率!J23)*(1-J92) -> -3.467484 | K99: =K85*(1-费用税率!K23)*(1-K92) -> -1.3325247 | L99: =L85*(1-费用税率!L23)*(1-L92) -> 0.19571058 | M99: =M85*(1-费用税率!M23)*(1-M92) -> 0.49023997
A100: 石英电子布 归母净利润（估算） | B100: 百万元 | I100: =I86*(1-费用税率!I23)*(1-I93) -> 83.485791 | J100: =J86*(1-费用税率!J23)*(1-J93) -> 175.15979 | K100: =K86*(1-费用税率!K23)*(1-K93) -> 307.38948 | L100: =L86*(1-费用税率!L23)*(1-L93) -> 391.58854 | M100: =M86*(1-费用税率!M23)*(1-M93) -> 424.50805
A101: 玻纤工业布及其他 归母净利润（估算） | B101: 百万元 | I101: =I87*(1-费用税率!I23)*(1-I94) -> 14.77502 | J101: =J87*(1-费用税率!J23)*(1-J94) -> 10.97153 | K101: =K87*(1-费用税率!K23)*(1-K94) -> 11.538276 | L101: =L87*(1-费用税率!L23)*(1-L94) -> 11.57862 | M101: =M87*(1-费用税率!M23)*(1-M94) -> 12.337693
A102: 分部归母净利润合计 | B102: 百万元 | I102: =I95+I96+I97+I98+I99+I100+I101 -> 543.98612 | J102: =J95+J96+J97+J98+J99+J100+J101 -> 689.30918 | K102: =K95+K96+K97+K98+K99+K100+K101 -> 921.78474 | L102: =L95+L96+L97+L98+L99+L100+L101 -> 1082.2937 | M102: =M95+M96+M97+M98+M99+M100+M101 -> 1182.5354
A103: 非经营项目及差异（财务、投资收益、其他收益、减值等） | B103: 百万元 | I103: =利润表!I27-I102 -> 73.936996 | J103: =利润表!J27-J102 -> 61.926337 | K103: =利润表!K27-K102 -> 42.948841 | L103: =利润表!L27-L102 -> 28.034415 | M103: =利润表!M27-M102 -> 24.675964 | N103: 报表归母净利润 − 分部加总；SOTP中单独估值或按净现金处理

Sheet 资本开支
A1: 投资、在建工程、固定资产与折旧摊销（百万元）
A2: 项目级资本开支 → 在建工程 → 转固 → 分年度折旧（年中法）；历史值来自报表附注与现金流量表补充资料。
A4: 百万元 | B4: 单位 | C4: 2020A | D4: 2021A | E4: 2022A | F4: 2023A | G4: 2024A | H4: 2025A | I4: 2026E | J4: 2027E | K4: 2028E | L4: 2029E | M4: 2030E | N4: 说明 / 来源
A5: 一、项目级资本开支（现金口径，含设备预付）
A6: 其中：已开工电子布项目承诺投资（下限） | B6: 百万元 | I6: 450 | J6: 150 | K6: 0 | L6: 0 | M6: 0 | N6: 已开工的石英电子纱智能制造（一期，预算4.95亿元）与超薄石英电子布基材项目（预算2.00亿元）剩余投资，各情景相同
A7: 石英电子纱/电子布产能（与情景产能联动） | B7: 百万元 | I7: =MAX(I6,MAX(0,业务拆分!J31-业务拆分!I31)*$C$53)+0 -> 450 | J7: =MAX(J6,MAX(0,业务拆分!K31-业务拆分!J31)*$C$53)+0 -> 360 | K7: =MAX(K6,MAX(0,业务拆分!L31-业务拆分!K31)*$C$53)+0 -> 270 | L7: =MAX(L6,MAX(0,业务拆分!M31-业务拆分!L31)*$C$53)+0 -> 180 | M7: =MAX(M6,$C$54*$C$53)+0 -> 180 | N7: ＝下一年产能增量×单位产能投资（2030年按“资本开支”表2031E新增产能输入）。在建：石英电子纱智能制造（一期，湖北鼎益，预算4.95亿元，2026H1进度40%）、超薄石英电子布基材项目（预算2.00亿元，进度50%）
A8: 合成石英材料扩产（六/七期等） | B8: 百万元 | I8: 100 | J8: 100 | K8: 80 | L8: 60 | M8: 60 | N8: 五期（预算0.95亿元）2025年、六期（0.37亿元）2026年竣工投产，七期2026年启动建设
A9: 光掩膜基板（合肥光微/济南光微） | B9: 百万元 | I9: 50 | J9: 40 | K9: 30 | L9: 20 | M9: 20 | N9: 济南光微预算4.49亿元已投入4.04亿元（2026H1建设完成）；合肥光微预算2.46亿元已投入2.00亿元
A10: 嘉殷新材料基地（荆州，穿透持股65.64%） | B10: 百万元 | I10: 100 | J10: 120 | K10: 40 | L10: 0 | M10: 0 | N10: 基建工程预算3.28亿元，2026H1进度25%；合作方深创投新材料基金等
A11: 半导体材料/器件及航空航天复合材料扩产 | B11: 百万元 | I11: 120 | J11: 130 | K11: 120 | L11: 100 | M11: 100 | N11: 气熔/电熔材料、半导体器件（湖北石创）、立体编织与复合材料
A12: 光纤配套高纯精密石英材料（湖北聚通，持股51%） | B12: 百万元 | I12: 60 | J12: 40 | K12: 0 | L12: 0 | M12: 0 | N12: 注册资本1亿元，年产70吨衬管/套管（2026-06-09公告）
A13: 维护性资本开支 / 收入 | B13: % | I13: 0.03 | J13: 0.04 | K13: 0.05 | L13: 0.06 | M13: 0.065 | N13: 维护性及零星工程，随资产规模扩大逐年提高，使2030E资本开支不低于折旧摊销；2023-2025年资本开支/收入21%-28%，2026H1为32%
A14: 维护性及其他零星资本开支 | B14: 百万元 | I14: =I13*利润表!I5 -> 82.23021 | J14: =J13*利润表!J5 -> 140.41825 | K14: =K13*利润表!K5 -> 220.99842 | L14: =L13*利润表!L5 -> 308.6115 | M14: =M13*利润表!M5 -> 370.65703
A15: 土地使用权及其他无形资产购置 | B15: 百万元 | I15: 40 | J15: 30 | K15: 20 | L15: 20 | M15: 20 | N15: 新基地土地款；历史见无形资产附注
A16: 长期待摊费用新增（=当年摊销，维持余额） | B16: 百万元 | I16: =I47 -> 13.3 | J16: =J47 -> 13.3 | K16: =K47 -> 13.3 | L16: =L47 -> 13.3 | M16: =M47 -> 13.3
A17: 资本开支合计（购建长期资产支付的现金） | B17: 百万元 | C17: 203.6003 | D17: 318.8237 | E17: 572.6832 | F17: 544.5963 | G17: 369.8711 | H17: 558.9568 | I17: =I7+I8+I9+I10+I11+I12+I14+I15+I16 -> 1015.5302 | J17: =J7+J8+J9+J10+J11+J12+J14+J15+J16 -> 973.71825 | K17: =K7+K8+K9+K10+K11+K12+K14+K15+K16 -> 794.29842 | L17: =L7+L8+L9+L10+L11+L12+L14+L15+L16 -> 701.9115 | M17: =M7+M8+M9+M10+M11+M12+M14+M15+M16 -> 763.95703 | N17: 历史：来源：Wind（公司公告值），万元÷100
A18: 资本开支 / 收入 | B18: % | C18: =C17/利润表!C5 -> 0.23576357 | D18: =D17/利润表!D5 -> 0.26057302 | E18: =E17/利润表!E5 -> 0.33307828 | F18: =F17/利润表!F5 -> 0.26050476 | G18: =G17/利润表!G5 -> 0.21234854 | H18: =H17/利润表!H5 -> 0.27721234 | I18: =I17/利润表!I5 -> 0.3704953 | J18: =J17/利润表!J5 -> 0.27737656 | ... M18: =M17/利润表!M5 -> 0.13397077
A19: 资本开支 / 折旧摊销 | B19: x | C19: =IFERROR(C17/C49,0) -> 3.320032 | D19: =IFERROR(D17/D49,0) -> 3.745698 | E19: =IFERROR(E17/E49,0) -> 4.9787499 | F19: =IFERROR(F17/F49,0) -> 3.2501337 | G19: =IFERROR(G17/G49,0) -> 1.7869093 | H19: =IFERROR(H17/H49,0) -> 2.2510597 | I19: =I17/I49 -> 3.3792078 | J19: =J17/J49 -> 2.6742679 | K19: =K17/K49 -> 1.7905478 | L19: =L17/L49 -> 1.350187 | M19: =M17/M49 -> 1.2985676
A20: 二、设备及工程预付款（其他非流动资产）
A21: 预付款 / 当年资本开支 | B21: % | C21: =IFERROR(C22/C17,0) -> 0 | D21: =IFERROR(D22/D17,0) -> 0.29743021 | E21: =IFERROR(E22/E17,0) -> 0.12608681 | F21: =IFERROR(F22/F17,0) -> 0.31401646 | G21: =IFERROR(G22/G17,0) -> 0.42300818 | H21: =IFERROR(H22/H17,0) -> 0.41882056 | I21: 0.4 | J21: 0.4 | K21: 0.4 | L21: 0.4 | M21: 0.4
A22: 其他非流动资产余额 | B22: 百万元 | C22: 0 | D22: 94.8278 | E22: 72.2078 | F22: 171.0122 | G22: 156.4585 | H22: 234.1026 | I22: =I21*I17 -> 406.21208 | J22: =J21*J17 -> 389.4873 | K22: =K21*K17 -> 317.71937 | L22: =L21*L17 -> 280.7646 | M22: =M21*M17 -> 305.58281
A23: 预付款增加（占用现金、尚未进入在建工程） | B23: 百万元 | I23: =I22-H22 -> 172.10948 | J23: =J22-I22 -> -16.724786 | K23: =K22-J22 -> -71.767931 | L23: =L22-K22 -> -36.954767 | M23: =M22-L22 -> 24.818213
A24: 三、在建工程
A25: 期初 | B25: 百万元 | I25: =H29 -> 207.0485 | J25: =I29 -> 411.72256 | K25: =J29 -> 487.37894 | L25: =K29 -> 384.7014 | M25: =L29 -> 273.57966
A26: 本期增加（项目资本开支−预付款增加） | B26: 百万元 | I26: =I7+I8+I9+I10+I11+I12-I23 -> 707.89052 | J26: =J7+J8+J9+J10+J11+J12-J23 -> 806.72479 | K26: =K7+K8+K9+K10+K11+K12-K23 -> 611.76793 | L26: =L7+L8+L9+L10+L11+L12-L23 -> 396.95477 | M26: =M7+M8+M9+M10+M11+M12-M23 -> 335.18179
A27: 转固比例（期初+本期增加） | B27: % | I27: 0.55 | J27: 0.6 | K27: 0.65 | L27: 0.65 | M27: 0.65 | N27: 按项目投产节奏设定；历史转固见“底稿”在建工程表
A28: 转入固定资产 | B28: 百万元 | I28: =(I25+I26)*I27 -> 503.21646 | J28: =(J25+J26)*J27 -> 731.06841 | K28: =(K25+K26)*K27 -> 714.44546 | L28: =(L25+L26)*L27 -> 508.07651 | M28: =(M25+M26)*M27 -> 395.69494
A29: 期末在建工程 | B29: 百万元 | C29: 118.3541 | D29: 57.9785 | E29: 179.4215 | F29: 134.2695 | G29: 265.7579 | H29: 207.0485 | I29: =I25+I26-I28 -> 411.72256 | J29: =J25+J26-J28 -> 487.37894 | K29: =K25+K26-K28 -> 384.7014 | L29: =L25+L26-L28 -> 273.57966 | M29: =M25+M26-M28 -> 213.06651
A30: 四、固定资产与折旧
A31: 固定资产增加（在建转固+维护性开支） | B31: 百万元 | I31: =I28+I14 -> 585.44667 | J31: =J28+J14 -> 871.48665 | K31: =K28+K14 -> 935.44388 | L31: =L28+L14 -> 816.68801 | M31: =M28+M14 -> 766.35198
A32: 存量资产折旧（2025年末资产） | B32: 百万元 | I32: =H40*$C$55 -> 238.64263 | J32: =I32*(1-$C$52) -> 231.48335 | K32: =J32*(1-$C$52) -> 224.53885 | L32: =K32*(1-$C$52) -> 217.80269 | M32: =L32*(1-$C$52) -> 211.26861 | N32: 2026年含2025年新增资产的全年化效应；之后按到期比例逐年滚出
A33: 新增资产综合折旧年限 | B33: 年 | I33: 10 | J33: 10 | K33: 10 | L33: 10 | M33: 10 | N33: 机器设备10年、房屋20-30年，新增资产以设备为主，综合按10年；残值率5%
A34: 残值率 | B34: % | I34: 0.05 | J34: 0.05 | K34: 0.05 | L34: 0.05 | M34: 0.05
A35: 2026年新增资产折旧 | B35: 百万元 | I35: =$I$31*(1-$I$34)/$I$33*0.5 -> 27.808717 | J35: =$I$31*(1-$I$34)/$I$33*1 -> 55.617434 | K35: =$I$31*(1-$I$34)/$I$33*1 -> 55.617434 | L35: =$I$31*(1-$I$34)/$I$33*1 -> 55.617434 | M35: =$I$31*(1-$I$34)/$I$33*1 -> 55.617434
A36: 2027年新增资产折旧 | B36: 百万元 | J36: =$J$31*(1-$J$34)/$J$33*0.5 -> 41.395616 | K36: =$J$31*(1-$J$34)/$J$33*1 -> 82.791232 | L36: =$J$31*(1-$J$34)/$J$33*1 -> 82.791232 | M36: =$J$31*(1-$J$34)/$J$33*1 -> 82.791232
A37: 2028年新增资产折旧 | B37: 百万元 | K37: =$K$31*(1-$K$34)/$K$33*0.5 -> 44.433584 | L37: =$K$31*(1-$K$34)/$K$33*1 -> 88.867169 | M37: =$K$31*(1-$K$34)/$K$33*1 -> 88.867169
A38: 2029年新增资产折旧 | B38: 百万元 | L38: =$L$31*(1-$L$34)/$L$33*0.5 -> 38.792681 | M38: =$L$31*(1-$L$34)/$L$33*1 -> 77.585361
A39: 2030年新增资产折旧 | B39: 百万元 | M39: =$M$31*(1-$M$34)/$M$33*0.5 -> 36.401719
A40: 固定资产折旧合计 | B40: 百万元 | C40: 58.189 | D40: 77.6038 | E40: 103.5931 | F40: 151.4175 | G40: 182.7184 | H40: 220.9654 | I40: =I32+SUM(I35:I39) -> 266.45135 | J40: =J32+SUM(J35:J39) -> 328.4964 | K40: =K32+SUM(K35:K39) -> 407.3811 | L40: =L32+SUM(L35:L39) -> 483.8712 | M40: =M32+SUM(M35:M39) -> 552.53152 | N40: 历史：现金流量表补充资料
A41: 固定资产净值 | B41: 百万元 | C41: 605.6634 | D41: 970.4833 | E41: 1343.0813 | F41: 1765.0717 | G41: 1863.2982 | H41: 2318.4985 | I41: =H41+I31-I40 -> 2637.4938 | J41: =I41+J31-J40 -> 3180.4841 | K41: =J41+K31-K40 -> 3708.5468 | L41: =K41+L31-L40 -> 4041.3637 | M41: =L41+M31-M40 -> 4255.1841
A42: 折旧 / 期初固定资产净值 | B42: % | D42: =IFERROR(D40/C41,0) -> 0.12813025 | E42: =IFERROR(E40/D41,0) -> 0.10674383 | F42: =IFERROR(F40/E41,0) -> 0.11273889 | G42: =IFERROR(G40/F41,0) -> 0.10351897 | H42: =IFERROR(H40/G41,0) -> 0.11858832 | I42: =I40/H41 -> 0.1149241 | J42: =J40/I41 -> 0.12454869 | K42: =K40/J41 -> 0.12808777 | L42: =L40/K41 -> 0.13047461 | M42: =M40/L41 -> 0.13671908
A43: 五、无形资产、长期待摊费用与使用权资产
A44: 无形资产摊销率（摊销/期初余额） | B44: % | D44: =IFERROR(D45/C46,0) -> 0.053542838 | E44: =IFERROR(E45/D46,0) -> 0.052117588 | F44: =IFERROR(F45/E46,0) -> 0.054038232 | G44: =IFERROR(G45/F46,0) -> 0.057755312 | H44: =IFERROR(H45/G46,0) -> 0.056884767 | I44: 0.08 | J44: 0.08 | K44: 0.08 | L44: 0.08 | M44: 0.08
A45: 无形资产摊销 | B45: 百万元 | C45: 1.6127 | D45: 3.0365 | E45: 5.032 | F45: 8.1786 | G45: 10.5402 | H45: 12.1041 | I45: =H46*I44 -> 20.771816 | J45: =I46*J44 -> 22.310071 | K45: =J46*K44 -> 22.925265 | L45: =K46*L44 -> 22.691244 | M45: =L46*M44 -> 22.475944
A46: 无形资产净值 | B46: 百万元 | C46: 56.7116 | D46: 96.5509 | E46: 151.3484 | F46: 182.4975 | G46: 212.7828 | H46: 259.6477 | I46: =H46+I15-I45 -> 278.87588 | J46: =I46+J15-J45 -> 286.56581 | K46: =J46+K15-K45 -> 283.64055 | L46: =K46+L15-L45 -> 280.9493 | M46: =L46+M15-M45 -> 278.47336
A47: 长期待摊费用摊销（假设等额新增，余额持平） | B47: 百万元 | C47: 1.5231 | D47: 2.9327 | E47: 4.2927 | F47: 3.7967 | G47: 6.5064 | H47: 8.5917 | I47: 13.3 | J47: =I47 -> 13.3 | K47: =J47 -> 13.3 | L47: =K47 -> 13.3 | M47: =L47 -> 13.3 | N47: 2026E按上半年6.65百万元年化
A48: 使用权资产折旧 | B48: 百万元 | C48: 0 | D48: 1.5443 | E48: 2.1077 | F48: 4.1684 | G48: 7.2243 | H48: 6.6471 | I48: 0 | J48: 0 | K48: 0 | L48: 0 | M48: 0 | N48: 金额小，预测期并入其他
A49: 折旧摊销合计（D&A） | B49: 百万元 | C49: =C40+C45+C47+C48 -> 61.3248 | D49: =D40+D45+D47+D48 -> 85.1173 | E49: =E40+E45+E47+E48 -> 115.0255 | F49: =F40+F45+F47+F48 -> 167.5612 | G49: =G40+G45+G47+G48 -> 206.9893 | H49: =H40+H45+H47+H48 -> 248.3083 | I49: =I40+I45+I47+I48 -> 300.52316 | J49: =J40+J45+J47+J48 -> 364.10647 | ... M49: =M40+M45+M47+M48 -> 588.30747
A50: D&A / 收入 | B50: % | C50: =C49/利润表!C5 -> 0.071012437 | D50: =D49/利润表!D5 -> 0.069565944 | E50: =E49/利润表!E5 -> 0.066899981 | F50: =F49/利润表!F5 -> 0.080152014 | G50: =G49/利润表!G5 -> 0.11883566 | H50: =H49/利润表!H5 -> 0.12314749 | I50: =I49/利润表!I5 -> 0.10963969 | J50: =J49/利润表!J5 -> 0.10372056 | ... M50: =M49/利润表!M5 -> 0.10316811
A52: 存量资产折旧年滚出比例 | B52: % | C52: 0.03 | D52: 部分早期设备逐步提足折旧
A53: 石英电子布单位产能投资（纱+织造+后处理） | B53: 百万元/万米 | C53: 0.9 | D53: 募投电子纱6.24亿元/1,000吨（约800万米当量，吨纱换米为低可信度经验口径）≈0.78百万元/万米，另加织造后处理；中材科技2,400万米项目17.51亿元≈0.73百万元/万米
A54: 2031E电子布新增产能（决定2030年设备投入） | B54: 万米/年 | C54: 200 | D54: 2031E计划新增电子布产能（万米/年），决定2030年电子布设备投入；与2030年产能增量相当
A55: 2026年存量资产折旧 / 2025年折旧 | B55: x | C55: 1.08 | D55: 反映2025年新增资产在2026年的全年化折旧
A57: 六、产能里程碑（文字记录，见底稿-项目表）

Sheet 营运资本
A1: 营运资本：周转天数驱动（百万元 / 天）
A2: 应收类按营业收入、存货与应付类按营业成本计算周转天数（期末余额/年额×365）。历史天数为公式，预测天数为输入。
A4: 百万元 | B4: 单位 | C4: 2020A | D4: 2021A | E4: 2022A | F4: 2023A | G4: 2024A | H4: 2025A | I4: 2026E | J4: 2027E | K4: 2028E | L4: 2029E | M4: 2030E | N4: 说明 / 来源
A5: 周转天数（预测期为输入）
A6: 应收账款周转天数（基于收入） | B6: 天 | C6: =IFERROR(C21/利润表!C5*365,0) -> 92.72036 | D6: =IFERROR(D21/利润表!D5*365,0) -> 69.193685 | E6: =IFERROR(E21/利润表!E5*365,0) -> 71.126489 | F6: =IFERROR(F21/利润表!F5*365,0) -> 84.239533 | G6: =IFERROR(G21/利润表!G5*365,0) -> 105.07181 | H6: =IFERROR(H21/利润表!H5*365,0) -> 129.65476 | I6: 125 | J6: 124 | K6: 123 | L6: 122 | M6: 122 | N6: 年末应收天数低于上半年年化水平（2024年131→105天，2025年137→130天），2026H1年化129天，取125天
A7: 应收票据周转天数（基于收入） | B7: 天 | C7: =IFERROR(C22/利润表!C5*365,0) -> 92.499689 | D7: =IFERROR(D22/利润表!D5*365,0) -> 71.843 | E7: =IFERROR(E22/利润表!E5*365,0) -> 84.589348 | F7: =IFERROR(F22/利润表!F5*365,0) -> 70.836807 | G7: =IFERROR(G22/利润表!G5*365,0) -> 58.766606 | H7: =IFERROR(H22/利润表!H5*365,0) -> 63.490412 | I7: 60 | J7: 58 | K7: 56 | L7: 55 | M7: 55
A8: 应收款项融资周转天数（基于收入） | B8: 天 | C8: =IFERROR(C23/利润表!C5*365,0) -> 0 | D8: =IFERROR(D23/利润表!D5*365,0) -> 16.511756 | E8: =IFERROR(E23/利润表!E5*365,0) -> 8.7759503 | F8: =IFERROR(F23/利润表!F5*365,0) -> 18.542181 | G8: =IFERROR(G23/利润表!G5*365,0) -> 23.893052 | H8: =IFERROR(H23/利润表!H5*365,0) -> 16.188443 | I8: 15 | J8: 15 | K8: 15 | L8: 15 | M8: 15
A9: 预付款项周转天数（基于成本） | B9: 天 | C9: =IFERROR(C24/利润表!C7*365,0) -> 88.092231 | D9: =IFERROR(D24/利润表!D7*365,0) -> 23.930381 | E9: =IFERROR(E24/利润表!E7*365,0) -> 27.957249 | F9: =IFERROR(F24/利润表!F7*365,0) -> 68.04065 | G9: =IFERROR(G24/利润表!G7*365,0) -> 32.735618 | H9: =IFERROR(H24/利润表!H7*365,0) -> 37.19155 | I9: 30 | J9: 30 | K9: 30 | L9: 30 | M9: 30
A10: 其他应收款周转天数（基于收入） | B10: 天 | C10: =IFERROR(C25/利润表!C5*365,0) -> 0.29319924 | D10: =IFERROR(D25/利润表!D5*365,0) -> 1.7630279 | E10: =IFERROR(E25/利润表!E5*365,0) -> 0.39411202 | F10: =IFERROR(F25/利润表!F5*365,0) -> 0.49077139 | G10: =IFERROR(G25/利润表!G5*365,0) -> 4.0113485 | H10: =IFERROR(H25/利润表!H5*365,0) -> 8.198498 | I10: 4 | J10: 4 | K10: 4 | L10: 4 | M10: 4
A11: 存货周转天数（基于成本） | B11: 天 | C11: =IFERROR(C26/利润表!C7*365,0) -> 175.75333 | D11: =IFERROR(D26/利润表!D7*365,0) -> 196.30002 | E11: =IFERROR(E26/利润表!E7*365,0) -> 201.90417 | F11: =IFERROR(F26/利润表!F7*365,0) -> 230.1033 | G11: =IFERROR(G26/利润表!G7*365,0) -> 269.29101 | H11: =IFERROR(H26/利润表!H7*365,0) -> 315.10793 | I11: 330 | J11: 320 | K11: 310 | L11: 300 | M11: 295 | N11: 存货天数年末高于上半年（2025年302→315天），2026H1为311天，取330天后逐步优化
A12: 其他流动资产周转天数（基于收入） | B12: 天 | C12: =IFERROR(C27/利润表!C5*365,0) -> 7.0850918 | D12: =IFERROR(D27/利润表!D5*365,0) -> 4.3436414 | E12: =IFERROR(E27/利润表!E5*365,0) -> 10.297055 | F12: =IFERROR(F27/利润表!F5*365,0) -> 13.78537 | G12: =IFERROR(G27/利润表!G5*365,0) -> 16.770423 | H12: =IFERROR(H27/利润表!H5*365,0) -> 11.931154 | I12: 10 | J12: 10 | K12: 10 | L12: 10 | M12: 10
A13: 应付票据周转天数（基于成本） | B13: 天 | C13: =IFERROR(C28/利润表!C7*365,0) -> 99.647195 | D13: =IFERROR(D28/利润表!D7*365,0) -> 68.161315 | E13: =IFERROR(E28/利润表!E7*365,0) -> 58.037717 | F13: =IFERROR(F28/利润表!F7*365,0) -> 109.67827 | G13: =IFERROR(G28/利润表!G7*365,0) -> 59.85492 | H13: =IFERROR(H28/利润表!H7*365,0) -> 69.388136 | I13: 75 | J13: 75 | K13: 75 | L13: 75 | M13: 75 | N13: 2026H1应付票据大幅增加（3.55亿元）
A14: 应付账款周转天数（基于成本） | B14: 天 | C14: =IFERROR(C29/利润表!C7*365,0) -> 134.96086 | D14: =IFERROR(D29/利润表!D7*365,0) -> 123.33193 | E14: =IFERROR(E29/利润表!E7*365,0) -> 135.22879 | F14: =IFERROR(F29/利润表!F7*365,0) -> 104.78632 | G14: =IFERROR(G29/利润表!G7*365,0) -> 78.204626 | H14: =IFERROR(H29/利润表!H7*365,0) -> 117.85549 | I14: 110 | J14: 112 | K14: 112 | L14: 112 | M14: 112
A15: 合同负债周转天数（基于收入） | B15: 天 | C15: =IFERROR(C30/利润表!C5*365,0) -> 4.2820952 | D15: =IFERROR(D30/利润表!D5*365,0) -> 2.6689439 | E15: =IFERROR(E30/利润表!E5*365,0) -> 4.9204881 | F15: =IFERROR(F30/利润表!F5*365,0) -> 2.9720224 | G15: =IFERROR(G30/利润表!G5*365,0) -> 4.7579402 | H15: =IFERROR(H30/利润表!H5*365,0) -> 3.6981353 | I15: 4 | J15: 4 | K15: 4 | L15: 4 | M15: 4
A16: 应付职工薪酬周转天数（基于收入） | B16: 天 | C16: =IFERROR(C31/利润表!C5*365,0) -> 17.372256 | D16: =IFERROR(D31/利润表!D5*365,0) -> 13.53734 | E16: =IFERROR(E31/利润表!E5*365,0) -> 10.022015 | F16: =IFERROR(F31/利润表!F5*365,0) -> 10.557687 | G16: =IFERROR(G31/利润表!G5*365,0) -> 13.365874 | H16: =IFERROR(H31/利润表!H5*365,0) -> 14.497822 | I16: 14 | J16: 14 | K16: 14 | L16: 14 | M16: 14
A17: 应交税费周转天数（基于收入） | B17: 天 | C17: =IFERROR(C32/利润表!C5*365,0) -> 10.155928 | D17: =IFERROR(D32/利润表!D5*365,0) -> 10.253574 | E17: =IFERROR(E32/利润表!E5*365,0) -> 10.370974 | F17: =IFERROR(F32/利润表!F5*365,0) -> 8.6930561 | G17: =IFERROR(G32/利润表!G5*365,0) -> 4.7224421 | H17: =IFERROR(H32/利润表!H5*365,0) -> 13.579054 | I17: 11 | J17: 11 | K17: 11 | L17: 11 | M17: 11
A18: 其他应付款周转天数（基于收入） | B18: 天 | C18: =IFERROR(C33/利润表!C5*365,0) -> 4.7550095 | D18: =IFERROR(D33/利润表!D5*365,0) -> 8.8369165 | E18: =IFERROR(E33/利润表!E5*365,0) -> 5.945328 | F18: =IFERROR(F33/利润表!F5*365,0) -> 5.3845176 | G18: =IFERROR(G33/利润表!G5*365,0) -> 1.0187578 | H18: =IFERROR(H33/利润表!H5*365,0) -> 18.039176 | I18: 14 | J18: 12 | K18: 12 | L18: 12 | M18: 12 | N18: 2026年含限制性股票回购义务
A19: 其他流动负债周转天数（基于收入） | B19: 天 | C19: =IFERROR(C34/利润表!C5*365,0) -> 1.2000585 | D19: =IFERROR(D34/利润表!D5*365,0) -> 16.831965 | E19: =IFERROR(E34/利润表!E5*365,0) -> 11.048001 | F19: =IFERROR(F34/利润表!F5*365,0) -> 16.528253 | G19: =IFERROR(G34/利润表!G5*365,0) -> 14.410113 | H19: =IFERROR(H34/利润表!H5*365,0) -> 15.968213 | I19: 16 | J19: 16 | K19: 16 | L19: 16 | M19: 16
A20: 期末余额
A21: 应收账款 | B21: 百万元 | C21: 219.3734 | D21: 231.9502 | E21: 335.0477 | F21: 482.4831 | G21: 501.4117 | H21: 716.2445 | I21: =I6/365*利润表!I5 -> 938.70103 | J21: =J6/365*利润表!J5 -> 1192.5933 | K21: =K6/365*利润表!K5 -> 1489.4688 | L21: =L6/365*利润表!L5 -> 1719.2056 | M21: =M6/365*利润表!M5 -> 1906.013
A22: 应收票据 | B22: 百万元 | C22: 218.8513 | D22: 240.8312 | E22: 398.4657 | F22: 405.7188 | G22: 280.4393 | H22: 350.7365 | I22: =I7/365*利润表!I5 -> 450.57649 | J22: =J7/365*利润表!J5 -> 557.82591 | K22: =K7/365*利润表!K5 -> 678.13213 | L22: =L7/365*利润表!L5 -> 775.05172 | M22: =M7/365*利润表!M5 -> 859.26815
A23: 应收款项融资 | B23: 百万元 | C23: 0 | D23: 55.3505 | E23: 41.3399 | F23: 106.2006 | G23: 114.0197 | H23: 89.4289 | I23: =I8/365*利润表!I5 -> 112.64412 | J23: =J8/365*利润表!J5 -> 144.26532 | K23: =K8/365*利润表!K5 -> 181.64254 | L23: =L8/365*利润表!L5 -> 211.37774 | M23: =M8/365*利润表!M5 -> 234.34586
A24: 预付款项 | B24: 百万元 | C24: 99.8956 | D24: 39.4738 | E24: 64.245 | F24: 196.8847 | G24: 90.3373 | H24: 108.1176 | I24: =I9/365*利润表!I7 -> 112.11694 | J24: =J9/365*利润表!J7 -> 143.65661 | K24: =K9/365*利润表!K7 -> 184.3515 | L24: =L9/365*利润表!L7 -> 220.45938 | M24: =M9/365*利润表!M7 -> 249.67825
A25: 其他应收款 | B25: 百万元 | C25: 0.6937 | D25: 5.91 | E25: 1.8565 | F25: 2.8109 | G25: 19.1425 | H25: 45.2905 | I25: =I10/365*利润表!I5 -> 30.038433 | J25: =J10/365*利润表!J5 -> 38.470752 | K25: =K10/365*利润表!K5 -> 48.43801 | L25: =L10/365*利润表!L5 -> 56.367398 | M25: =M10/365*利润表!M5 -> 62.492229
A26: 存货 | B26: 百万元 | C26: 199.3023 | D26: 323.8021 | E26: 463.9703 | F26: 665.8346 | G26: 743.1362 | H26: 916.0337 | I26: =I11/365*利润表!I7 -> 1233.2864 | J26: =J11/365*利润表!J7 -> 1532.3372 | K26: =K11/365*利润表!K7 -> 1904.9655 | L26: =L11/365*利润表!L7 -> 2204.5938 | M26: =M11/365*利润表!M7 -> 2455.1694
A27: 其他流动资产 | B27: 百万元 | C27: 16.7631 | D27: 14.5607 | E27: 48.5052 | F27: 78.9559 | G27: 80.0299 | H27: 65.9106 | I27: =I12/365*利润表!I5 -> 75.096082 | J27: =J12/365*利润表!J5 -> 96.176881 | K27: =K12/365*利润表!K5 -> 121.09502 | L27: =L12/365*利润表!L5 -> 140.91849 | M27: =M12/365*利润表!M5 -> 156.23057
A28: 应付票据 | B28: 百万元 | C28: 112.9988 | D28: 112.4339 | E28: 133.3691 | F28: 317.3687 | G28: 165.1758 | H28: 201.7146 | I28: =I13/365*利润表!I7 -> 280.29235 | J28: =J13/365*利润表!J7 -> 359.14153 | K28: =K13/365*利润表!K7 -> 460.87874 | L28: =L13/365*利润表!L7 -> 551.14846 | M28: =M13/365*利润表!M7 -> 624.19562
A29: 应付账款 | B29: 百万元 | C29: 153.0441 | D29: 203.4393 | E29: 310.7521 | F29: 303.2132 | G29: 215.8137 | H29: 342.6115 | I29: =I14/365*利润表!I7 -> 411.09545 | J29: =J14/365*利润表!J7 -> 536.31802 | K29: =K14/365*利润表!K7 -> 688.24558 | L29: =L14/365*利润表!L7 -> 823.04836 | M29: =M14/365*利润表!M7 -> 932.13213
A30: 合同负债 | B30: 百万元 | C30: 10.1313 | D30: 8.9468 | E30: 23.1784 | F30: 17.0223 | G30: 22.7053 | H30: 20.4294 | I30: =I15/365*利润表!I5 -> 30.038433 | J30: =J15/365*利润表!J5 -> 38.470752 | K30: =K15/365*利润表!K5 -> 48.43801 | L30: =L15/365*利润表!L5 -> 56.367398 | M30: =M15/365*利润表!M5 -> 62.492229
A31: 应付职工薪酬 | B31: 百万元 | C31: 41.1022 | D31: 45.3797 | E31: 47.2096 | F31: 60.4693 | G31: 63.7831 | H31: 80.0895 | I31: =I16/365*利润表!I5 -> 105.13452 | J31: =J16/365*利润表!J5 -> 134.64763 | K31: =K16/365*利润表!K5 -> 169.53303 | L31: =L16/365*利润表!L5 -> 197.28589 | M31: =M16/365*利润表!M5 -> 218.7228
A32: 应交税费 | B32: 百万元 | C32: 24.0286 | D32: 34.3719 | E32: 48.8534 | F32: 49.7896 | G32: 22.5359 | H32: 75.014 | I32: =I17/365*利润表!I5 -> 82.60569 | J32: =J17/365*利润表!J5 -> 105.79457 | K32: =K17/365*利润表!K5 -> 133.20453 | L32: =L17/365*利润表!L5 -> 155.01034 | M32: =M17/365*利润表!M5 -> 171.85363
A33: 其他应付款 | B33: 百万元 | C33: 11.2502 | D33: 29.623 | E33: 28.006 | F33: 30.8399 | G33: 4.8616 | H33: 99.6528 | I33: =I18/365*利润表!I5 -> 105.13452 | J33: =J18/365*利润表!J5 -> 115.41226 | K33: =K18/365*利润表!K5 -> 145.31403 | L33: =L18/365*利润表!L5 -> 169.10219 | M33: =M18/365*利润表!M5 -> 187.47669
A34: 其他流动负债 | B34: 百万元 | C34: 2.8393 | D34: 56.4239 | E34: 52.0426 | F34: 94.6658 | G34: 68.7663 | H34: 88.2123 | I34: =I19/365*利润表!I5 -> 120.15373 | J34: =J19/365*利润表!J5 -> 153.88301 | K34: =K19/365*利润表!K5 -> 193.75204 | L34: =L19/365*利润表!L5 -> 225.46959 | M34: =M19/365*利润表!M5 -> 249.96892
A35: 经营性流动资产 | B35: 百万元 | C35: =C21+C22+C23+C24+C25+C26+C27 -> 754.8794 | D35: =D21+D22+D23+D24+D25+D26+D27 -> 911.8785 | E35: =E21+E22+E23+E24+E25+E26+E27 -> 1353.4303 | F35: =F21+F22+F23+F24+F25+F26+F27 -> 1938.8886 | G35: =G21+G22+G23+G24+G25+G26+G27 -> 1828.5166 | H35: =H21+H22+H23+H24+H25+H26+H27 -> 2291.7623 | I35: =I21+I22+I23+I24+I25+I26+I27 -> 2952.4595 | J35: =J21+J22+J23+J24+J25+J26+J27 -> 3705.326 | ... M35: =M21+M22+M23+M24+M25+M26+M27 -> 5923.1975
A36: 经营性流动负债 | B36: 百万元 | C36: =C28+C29+C30+C31+C32+C33+C34 -> 355.3945 | D36: =D28+D29+D30+D31+D32+D33+D34 -> 490.6185 | E36: =E28+E29+E30+E31+E32+E33+E34 -> 643.4112 | F36: =F28+F29+F30+F31+F32+F33+F34 -> 873.3688 | G36: =G28+G29+G30+G31+G32+G33+G34 -> 563.6417 | H36: =H28+H29+H30+H31+H32+H33+H34 -> 907.7241 | I36: =I28+I29+I30+I31+I32+I33+I34 -> 1134.4547 | J36: =J28+J29+J30+J31+J32+J33+J34 -> 1443.6678 | ... M36: =M28+M29+M30+M31+M32+M33+M34 -> 2446.842
A37: 经营性净营运资本 | B37: 百万元 | C37: =C35-C36 -> 399.4849 | D37: =D35-D36 -> 421.26 | E37: =E35-E36 -> 710.0191 | F37: =F35-F36 -> 1065.5198 | G37: =G35-G36 -> 1264.8749 | H37: =H35-H36 -> 1384.0382 | I37: =I35-I36 -> 1818.0048 | J37: =J35-J36 -> 2261.6582 | ... M37: =M35-M36 -> 3476.3555
A38: 净营运资本 / 收入 | B38: % | C38: =C37/利润表!C5 -> 0.46259256 | D38: =D37/利润表!D5 -> 0.3442937 | E38: =E37/利润表!E5 -> 0.41295421 | F38: =F37/利润表!F5 -> 0.50968576 | G38: =G37/利润表!G5 -> 0.72618362 | H38: =H37/利润表!H5 -> 0.68640809 | I38: =I37/利润表!I5 -> 0.66326163 | J38: =J37/利润表!J5 -> 0.64426335 | ... M38: =M37/利润表!M5 -> 0.60962854
A39: 净营运资本增加（现金流出为正） | B39: 百万元 | D39: =D37-C37 -> 21.7751 | E39: =E37-D37 -> 288.7591 | F39: =F37-E37 -> 355.5007 | G39: =G37-F37 -> 199.3551 | H39: =H37-G37 -> 119.1633 | I39: =I37-H37 -> 433.96656 | J39: =J37-I37 -> 443.65346 | K39: =K37-J37 -> 507.06926 | ... M39: =M37-L37 -> 325.81352
A40: 现金转换周期
A41: 应收类合计天数（应收账款+票据+应收款项融资） | B41: 天 | C41: =(C21+C22+C23)/利润表!C5*365 -> 185.22005 | D41: =(D21+D22+D23)/利润表!D5*365 -> 157.54844 | E41: =(E21+E22+E23)/利润表!E5*365 -> 164.49179 | F41: =(F21+F22+F23)/利润表!F5*365 -> 173.61852 | G41: =(G21+G22+G23)/利润表!G5*365 -> 187.73146 | H41: =(H21+H22+H23)/利润表!H5*365 -> 209.33362 | I41: =(I21+I22+I23)/利润表!I5*365 -> 200 | J41: =(J21+J22+J23)/利润表!J5*365 -> 197 | ... M41: =(M21+M22+M23)/利润表!M5*365 -> 192
A42: 存货天数 | B42: 天 | C42: =C11 -> 175.75333 | D42: =D11 -> 196.30002 | E42: =E11 -> 201.90417 | F42: =F11 -> 230.1033 | G42: =G11 -> 269.29101 | H42: =H11 -> 315.10793 | I42: =I11 -> 330 | J42: =J11 -> 320 | ... M42: =M11 -> 295
A43: 应付类合计天数（应付账款+票据） | B43: 天 | C43: =(C29+C28)/利润表!C7*365 -> 234.60806 | D43: =(D29+D28)/利润表!D7*365 -> 191.49325 | E43: =(E29+E28)/利润表!E7*365 -> 193.26651 | F43: =(F29+F28)/利润表!F7*365 -> 214.46459 | G43: =(G29+G28)/利润表!G7*365 -> 138.05955 | H43: =(H29+H28)/利润表!H7*365 -> 187.24363 | I43: =(I29+I28)/利润表!I7*365 -> 185 | J43: =(J29+J28)/利润表!J7*365 -> 187 | ... M43: =(M29+M28)/利润表!M7*365 -> 187
A44: 现金转换周期（应收天数按收入，近似） | B44: 天 | C44: =C41+C42-C43 -> 126.36532 | D44: =D41+D42-D43 -> 162.35521 | E44: =E41+E42-E43 -> 173.12944 | F44: =F41+F42-F43 -> 189.25723 | G44: =G41+G42-G43 -> 318.96293 | H44: =H41+H42-H43 -> 337.19793 | I44: =I41+I42-I43 -> 345 | J44: =J41+J42-J43 -> 330 | ... M44: =M41+M42-M43 -> 300
A45: 经营现金流 / 净利润 | B45: x | C45: =现金流量表!C12/利润表!C25 -> 0.78901037 | D45: =现金流量表!D12/利润表!D25 -> 0.78262303 | E45: =现金流量表!E12/利润表!E25 -> 0.79457874 | F45: =现金流量表!F12/利润表!F25 -> 0.46408182 | G45: =现金流量表!G12/利润表!G25 -> 0.81154528 | H45: =现金流量表!H12/利润表!H25 -> 0.61413267 | I45: =现金流量表!I12/利润表!I25 -> 0.89845554 | J45: =现金流量表!J12/利润表!J25 -> 1.037094 | ... M45: =现金流量表!M12/利润表!M25 -> 1.1802795
A46: 注：经营现金流/净利润自2023年起降至0.5-0.8倍，主要因存货与应收增加、票据结算比例高。

Sheet 费用税率
A1: 期间费用、其他收益、减值、所得税与少数股东损益（百万元 / %）
A2: 费用率含股份支付摊销；股份支付金额单列于“融资”表用于现金流加回与资本公积。
A4: 百万元 | B4: 单位 | C4: 2020A | D4: 2021A | E4: 2022A | F4: 2023A | G4: 2024A | H4: 2025A | I4: 2026E | J4: 2027E | K4: 2028E | L4: 2029E | M4: 2030E | N4: 说明 / 来源
A5: 费用率（占营业收入）
A6: 税金及附加率 | B6: % | C6: =利润表!C10/利润表!C5 -> 0.010376477 | D6: =利润表!D10/利润表!D5 -> 0.0070204824 | E6: =利润表!E10/利润表!E5 -> 0.0098192054 | F6: =利润表!F10/利润表!F5 -> 0.010327606 | G6: =利润表!G10/利润表!G5 -> 0.010165796 | H6: =利润表!H10/利润表!H5 -> 0.012280563 | I6: 0.013 | J6: 0.013 | K6: 0.013 | L6: 0.013 | M6: 0.013
A7: 销售费用率 | B7: % | C7: =利润表!C11/利润表!C5 -> 0.014151583 | D7: =利润表!D11/利润表!D5 -> 0.011999035 | E7: =利润表!E11/利润表!E5 -> 0.010405526 | F7: =利润表!F11/利润表!F5 -> 0.01159742 | G7: =利润表!G11/利润表!G5 -> 0.014311882 | H7: =利润表!H11/利润表!H5 -> 0.015614758 | I7: 0.013 | J7: 0.012 | K7: 0.012 | L7: 0.012 | M7: 0.012
A8: 管理费用率（不含股份支付） | B8: % | C8: =(利润表!C12-N(融资!C26))/利润表!C5 -> 0.10454779 | D8: =(利润表!D12-N(融资!D26))/利润表!D5 -> 0.060323809 | E8: =(利润表!E12-N(融资!E26))/利润表!E5 -> 0.041591397 | F8: =(利润表!F12-N(融资!F26))/利润表!F5 -> 0.06054476 | G8: =(利润表!G12-N(融资!G26))/利润表!G5 -> 0.096779422 | H8: =(利润表!H12-N(融资!H26))/利润表!H5 -> 0.080836109 | I8: 0.062 | J8: 0.06 | K8: 0.057 | L8: 0.055 | M8: 0.053 | N8: 不含股份支付；2026H1管理费用+51%（薪酬、水电及折旧）
A9: 研发费用率 | B9: % | C9: =利润表!C13/利润表!C5 -> 0.085102532 | D9: =利润表!D13/利润表!D5 -> 0.077552306 | E9: =利润表!E13/利润表!E5 -> 0.089978906 | F9: =利润表!F13/利润表!F5 -> 0.10676979 | G9: =利润表!G13/利润表!G5 -> 0.14349659 | H9: =利润表!H13/利润表!H5 -> 0.13999408 | I9: 0.126 | J9: 0.11 | K9: 0.1 | L9: 0.093 | M9: 0.089 | N9: 2025年14.0%，2026H1 12.3%；下半年研发通常环比增加（2022/2023/2025年+26%/+35%/+31%），2026年取12.6%；之后随收入放量下降，且不低于2026H1年化金额
A10: 研发费用下限（2026H1年化） | B10: 百万元 | I10: 321.3 | J10: 321.3 | K10: 321.3 | L10: 321.3 | M10: 321.3 | N10: 研发团队与项目具有刚性，收入下行时研发费用不低于2026H1年化水平（160.63×2）
A11: 其他经营性损益
A12: 其他收益（政府补助、加计抵减等）/ 收入 | B12: % | C12: =利润表!C15/利润表!C5 -> 0.011384608 | D12: =利润表!D15/利润表!D5 -> 0.017061115 | E12: =利润表!E15/利润表!E5 -> 0.0085560648 | F12: =利润表!F15/利润表!F5 -> 0.024665749 | G12: =利润表!G15/利润表!G5 -> 0.033352807 | H12: =利润表!H15/利润表!H5 -> 0.026381595 | I12: 0.018 | J12: 0.016 | K12: 0.015 | L12: 0.014 | M12: 0.013 | N12: 政府补助及增值税加计抵减；2025年2.6%，2026H1 1.6%
A13: 信用减值损失 / 收入（损失为负） | B13: % | C13: =利润表!C18/利润表!C5 -> -0.00096343319 | D13: =利润表!D18/利润表!D5 -> -0.00049667018 | E13: =利润表!E18/利润表!E5 -> -0.0037095086 | F13: =利润表!F18/利润表!F5 -> -0.0050969543 | G13: =利润表!G18/利润表!G5 -> -0.004815906 | H13: =利润表!H18/利润表!H5 -> -0.0084916851 | I13: -0.006 | J13: -0.005 | K13: -0.005 | L13: -0.005 | M13: -0.005
A14: 资产减值损失 / 收入（损失为负） | B14: % | C14: =利润表!C19/利润表!C5 -> -0.00065321234 | D14: =利润表!D19/利润表!D5 -> -0.0018489665 | E14: =利润表!E19/利润表!E5 -> -0.0036490212 | F14: =利润表!F19/利润表!F5 -> -0.0047654135 | G14: =利润表!G19/利润表!G5 -> -0.011520421 | H14: =利润表!H19/利润表!H5 -> -0.017759129 | I14: -0.008 | J14: -0.007 | K14: -0.006 | L14: -0.006 | M14: -0.006 | N14: 主要为存货跌价；光伏相关产品价格压力
A15: 营业外收支净额 + 资产处置收益 | B15: 百万元 | C15: =利润表!C22+利润表!C20 -> -6.2964 | D15: =利润表!D22+利润表!D20 -> -7.7595 | E15: =利润表!E22+利润表!E20 -> -1.9804 | F15: =利润表!F22+利润表!F20 -> -3.7817 | G15: =利润表!G22+利润表!G20 -> -9.0021 | H15: =利润表!H22+利润表!H20 -> 11.3967 | I15: 0 | J15: 0 | K15: 0 | L15: 0 | M15: 0
A16: 所得税
A17: 法定税率（高新技术企业） | B17: % | I17: 0.15 | J17: 0.15 | K17: 0.15 | L17: 0.15 | M17: 0.15 | N17: 母公司、融鉴、湖北石创半导体高新证书2026年到期，已重新申请；若未通过适用25%
A18: 研发费用加计扣除比例 | B18: % | I18: 1 | J18: 1 | K18: 1 | L18: 1 | M18: 1 | N18: 2025年税率调节表：加计扣除节税46.51百万元（利润总额的10.0pct），约为研发费用×16.5%
A19: 研发加计扣除节税 | B19: 百万元 | I19: =利润表!I13*I18*I17 -> 51.805032 | J19: =利润表!J13*J18*J17 -> 57.922526 | K19: =利润表!K13*K18*K17 -> 66.299526 | L19: =利润表!L13*L18*L17 -> 71.752174 | M19: =利润表!M13*M18*M17 -> 76.127253
A20: 电子布利润留存于湖北鼎益（25%税率）的比例 | B20: % | I20: =MAX(0,1-业务拆分!I93/0.5189) -> 0.036423203 | J20: =MAX(0,1-业务拆分!J93/0.5189) -> 0.15205242 | K20: =MAX(0,1-业务拆分!K93/0.5189) -> 0.26768163 | L20: =MAX(0,1-业务拆分!L93/0.5189) -> 0.32549624 | M20: =MAX(0,1-业务拆分!M93/0.5189) -> 0.32549624 | N20: 由电子布少数股东比例反推：中益少数股东51.89%，其余利润视为留在全资子公司鼎益
A21: 鼎益25%税率的额外税负 | B21: 百万元 | I21: =I20*MAX(0,业务拆分!I86)*(0.25-I17) -> 0.68878347 | J21: =J20*MAX(0,业务拆分!J86)*(0.25-J17) -> 5.4188614 | K21: =K20*MAX(0,业务拆分!K86)*(0.25-K17) -> 15.204366 | L21: =L20*MAX(0,业务拆分!L86)*(0.25-L17) -> 22.508408 | M21: =M20*MAX(0,业务拆分!M86)*(0.25-M17) -> 24.441553
A22: 其他调整（占利润总额） | B22: % | I22: 0.035 | J22: 0.025 | K22: 0.015 | L22: 0.01 | M22: 0.01 | N22: 亏损子公司未确认递延所得税资产、不可抵扣项及25%税率主体；2025年约+3.6pct，2024年约+0.8pct（税率调节表倒算），随石创/济南光微减亏下降
A23: 有效所得税率 | B23: % | C23: =利润表!C24/利润表!C23 -> 0.12138366 | D23: =利润表!D24/利润表!D23 -> 0.11117402 | E23: =利润表!E24/利润表!E23 -> 0.094064065 | F23: =利润表!F24/利润表!F23 -> 0.10827052 | G23: =利润表!G24/利润表!G23 -> 0.052506904 | H23: =利润表!H24/利润表!H23 -> 0.086022665 | I23: =I17+(I21-I19)/利润表!I23+I22 -> 0.1170462 | J23: =J17+(J21-J19)/利润表!J23+J22 -> 0.12232914 | K23: =K17+(K21-K19)/利润表!K23+K22 -> 0.12713403 | L23: =L17+(L21-L19)/利润表!L23+L22 -> 0.1288001 | M23: =M17+(M21-M19)/利润表!M23+M22 -> 0.1302594 | N23: ＝法定15% − 研发加计扣除节税/利润总额 + 鼎益25%税率额外税负/利润总额 + 其他调整。2020-2025年全年有效税率5.3%-12.1%；半年报税率通常高于全年（加计扣除多在汇算清缴时确认）
A24: 少数股东损益
A25: 分部加权少数股东比例（按分部经营利润加权） | B25: % | I25: =IFERROR(SUMPRODUCT(业务拆分!I81:I87,业务拆分!I88:I94)/SUM(业务拆分!I81:I87),0) -> 0.14943767 | J25: =IFERROR(SUMPRODUCT(业务拆分!J81:J87,业务拆分!J88:J94)/SUM(业务拆分!J81:J87),0) -> 0.18705245 | K25: =IFERROR(SUMPRODUCT(业务拆分!K81:K87,业务拆分!K88:K94)/SUM(业务拆分!K81:K87),0) -> 0.19789524 | L25: =IFERROR(SUMPRODUCT(业务拆分!L81:L87,业务拆分!L88:L94)/SUM(业务拆分!L81:L87),0) -> 0.19614939 | M25: =IFERROR(SUMPRODUCT(业务拆分!M81:M87,业务拆分!M88:M94)/SUM(业务拆分!M81:M87),0) -> 0.20131985 | N25: 随业务结构变化：电子布、半导体加工等非全资主体占比提升会推高少数股东损益
A26: 亏损主体由少数股东分担的金额（上海石创/济南光微等） | B26: 百万元 | I26: -53 | J26: -40 | K26: -20 | L26: -5 | M26: 0 | N26: 上海石创2025年净亏损0.77亿元、2026H1亏损0.31亿元（少数股东48.87%，济南光微穿透少数股东约69%）；2026H1其他非全资子公司少数股东损益合计-6.5百万元，全年按-13计入；随光掩膜基板放量逐步收窄
A27: 少数股东损益 / 净利润 | B27: % | C27: =利润表!C26/利润表!C25 -> 0.0055927468 | D27: =利润表!D26/利润表!D25 -> 0.015097763 | E27: =利润表!E26/利润表!E25 -> 0.046869418 | F27: =利润表!F26/利润表!F25 -> 0.06400787 | G27: =利润表!G26/利润表!G25 -> 0.036959766 | H27: =利润表!H26/利润表!H25 -> -0.039365205 | I27: =利润表!I26/利润表!I25 -> 0.069639554 | J27: =利润表!J26/利润表!J25 -> 0.14133215 | ... M27: =利润表!M26/利润表!M25 -> 0.20131985 | N27: ＝ 分部经营利润加权的少数股东比例（见“业务拆分”）；2026H1实际4.4%（中益+41.8，石创-21.6，其他-6.5）

Sheet 融资
A1: 融资、金融资产与股东回报（百万元 / 百万股）
A2: 借款余额为输入；利息按平均余额计；现金为三表平衡项（来自现金流量表）。
A4: 百万元 | B4: 单位 | C4: 2020A | D4: 2021A | E4: 2022A | F4: 2023A | G4: 2024A | H4: 2025A | I4: 2026E | J4: 2027E | K4: 2028E | L4: 2029E | M4: 2030E | N4: 说明 / 来源
A5: 一、有息负债
A6: 短期借款 | B6: 百万元 | C6: 0 | D6: 0 | E6: 3 | F6: 142.9382 | G6: 117.4009 | H6: 195.6741 | I6: 120 | J6: 120 | K6: 120 | L6: 120 | M6: 120
A7: 一年内到期的非流动负债 | B7: 百万元 | C7: 0 | D7: 1.7833 | E7: 3.7349 | F7: 38.5681 | G7: 149.9592 | H7: 5.0356 | I7: 152 | J7: 50 | K7: 50 | L7: 50 | M7: 50
A8: 长期借款 | B8: 百万元 | C8: 0 | D8: 0 | E8: 32.9718 | F8: 113.5195 | G8: 69.012 | H8: 148.5 | I8: 29 | J8: 80 | K8: 80 | L8: 80 | M8: 80
A9: 有息负债合计 | B9: 百万元 | C9: =C6+C7+C8 -> 0 | D9: =D6+D7+D8 -> 1.7833 | E9: =E6+E7+E8 -> 39.7067 | F9: =F6+F7+F8 -> 295.0258 | G9: =G6+G7+G8 -> 336.3721 | H9: =H6+H7+H8 -> 349.2097 | I9: =I6+I7+I8 -> 301 | J9: =J6+J7+J8 -> 250 | ... M9: =M6+M7+M8 -> 250
A10: 借款利率 | B10: % | D10: =IFERROR(D11/AVERAGE(D9,C9),0) -> 0.31660405 | E10: =IFERROR(E11/AVERAGE(E9,D9),0) -> 0.02483008 | F10: =IFERROR(F11/AVERAGE(F9,E9),0) -> 0.02719007 | G10: =IFERROR(G11/AVERAGE(G9,F9),0) -> 0.041850313 | H10: =IFERROR(H11/AVERAGE(H9,G9),0) -> 0.027245764 | I10: 0.025 | J10: 0.025 | K10: 0.025 | L10: 0.025 | M10: 0.025
A11: 利息费用 | B11: 百万元 | C11: 0 | D11: 0.2823 | E11: 0.5151 | F11: 4.5507 | G11: 13.2121 | H11: 9.3396 | I11: =AVERAGE(I9,H9)*I10+H12*$C$39 -> 8.1276213 | J11: =AVERAGE(J9,I9)*J10+I12*$C$39 -> 6.8875 | K11: =AVERAGE(K9,J9)*K10+J12*$C$39 -> 6.25 | L11: =AVERAGE(L9,K9)*L10+K12*$C$39 -> 6.25 | M11: =AVERAGE(M9,L9)*M10+L12*$C$39 -> 6.25 | N11: 预测期含循环贷款利息（按期初余额计，避免循环引用）
A12: 循环贷款余额（最低现金缺口融资） | B12: 百万元 | C12: 0 | D12: 0 | E12: 0 | F12: 0 | G12: 0 | H12: 0 | I12: =MAX(0,H12+$C$38-资产负债表!H6-现金流量表!I27) -> 0 | J12: =MAX(0,I12+$C$38-资产负债表!I6-现金流量表!J27) -> 0 | K12: =MAX(0,J12+$C$38-资产负债表!J6-现金流量表!K27) -> 0 | L12: =MAX(0,K12+$C$38-资产负债表!K6-现金流量表!L27) -> 0 | M12: =MAX(0,L12+$C$38-资产负债表!L6-现金流量表!M27) -> 0 | N12: ＝ MAX(0, 期初余额 + 最低现金 − 期初现金 − 提款前现金净增加额)；现金充裕时自动偿还
A13: 二、现金与金融资产
A14: 货币资金（来自资产负债表） | B14: 百万元 | C14: 394.6839 | D14: 678.8377 | E14: 824.4059 | F14: 586.4147 | G14: 685.1896 | H14: 811.7069 | I14: =资产负债表!I6 -> 883.6335 | J14: =资产负债表!J6 -> 660.81006 | K14: =资产负债表!K6 -> 897.09512 | L14: =资产负债表!L6 -> 1562.8319 | M14: =资产负债表!M6 -> 2374.4046
A15: 现金收益率 | B15: % | D15: =IFERROR(D16/AVERAGE(D14,C14),0) -> 0.020741455 | E15: =IFERROR(E16/AVERAGE(E14,D14),0) -> 0.01733731 | F15: =IFERROR(F16/AVERAGE(F14,E14),0) -> 0.022655184 | G15: =IFERROR(G16/AVERAGE(G14,F14),0) -> 0.01438372 | H15: =IFERROR(H16/AVERAGE(H14,G14),0) -> 0.012917393 | I15: 0.01 | J15: 0.01 | K15: 0.01 | L15: 0.01 | M15: 0.01
A16: 利息收入 | B16: 百万元 | C16: 7.0732 | D16: 11.1332 | E16: 13.0311 | F16: 15.9812 | G16: 9.1452 | H16: 9.668 | I16: =H14*I15 -> 8.117069 | J16: =I14*J15 -> 8.836335 | K16: =J14*K15 -> 6.6081006 | L16: =K14*L15 -> 8.9709512 | M16: =L14*M15 -> 15.628319 | N16: 按期初现金计，避免循环引用
A17: 汇兑损益及手续费等（损失为正） | B17: 百万元 | C17: =利润表!C14-C11+C16 -> 8.6867 | D17: =利润表!D14-D11+D16 -> 2.81 | E17: =利润表!E14-E11+E16 -> -11.8685 | F17: =利润表!F14-F11+F16 -> -3.0723 | G17: =利润表!G14-G11+G16 -> -4.1674 | H17: =利润表!H14-H11+H16 -> 6.5618 | I17: 12 | J17: 0 | K17: 0 | L17: 0 | M17: 0 | N17: 2026H1汇兑损失较大（美元走弱）；境外收入约三成
A18: 交易性金融资产 | B18: 百万元 | C18: 452.7902 | D18: 280.944 | E18: 204.1341 | F18: 363.8887 | G18: 392.1992 | H18: 708.1757 | I18: 500 | J18: 500 | K18: 500 | L18: 500 | M18: 500 | N18: 结构性存款/理财，视同现金类资产
A19: 其他非流动金融资产 | B19: 百万元 | C19: 0 | D19: 0 | E19: 0 | F19: 566.2206 | G19: 452.9046 | H19: 244.1042 | I19: 170 | J19: 170 | K19: 170 | L19: 170 | M19: 170 | N19: 大额存单等
A20: 金融资产收益率（投资收益+公允价值变动） | B20: % | D20: =IFERROR((利润表!D16+利润表!D17)/AVERAGE(D18+D19,C18+C19),0) -> 0.038143786 | E20: =IFERROR((利润表!E16+利润表!E17)/AVERAGE(E18+E19,D18+D19),0) -> 0.034667407 | F20: =IFERROR((利润表!F16+利润表!F17)/AVERAGE(F18+F19,E18+E19),0) -> 0.033445202 | G20: =IFERROR((利润表!G16+利润表!G17)/AVERAGE(G18+G19,F18+F19),0) -> 0.032103977 | H20: =IFERROR((利润表!H16+利润表!H17)/AVERAGE(H18+H19,G18+G19),0) -> 0.02623313 | I20: 0.022 | J20: 0.022 | K20: 0.022 | L20: 0.022 | M20: 0.022
A21: 投资收益（含公允价值变动） | B21: 百万元 | I21: =AVERAGE(I18+I19,H18+H19)*I20 -> 17.845079 | J21: =AVERAGE(J18+J19,I18+I19)*J20 -> 14.74 | K21: =AVERAGE(K18+K19,J18+J19)*K20 -> 14.74 | L21: =AVERAGE(L18+L19,K18+K19)*L20 -> 14.74 | M21: =AVERAGE(M18+M19,L18+L19)*M20 -> 14.74
A22: 净现金（货币资金+金融资产−有息负债−循环贷款） | B22: 百万元 | C22: =C14+C18+C19-C9 -> 847.4741 | D22: =D14+D18+D19-D9 -> 957.9984 | E22: =E14+E18+E19-E9 -> 988.8333 | F22: =F14+F18+F19-F9 -> 1221.4982 | G22: =G14+G18+G19-G9 -> 1193.9213 | H22: =H14+H18+H19-H9 -> 1414.7771 | I22: =I14+I18+I19-I9-I12 -> 1252.6335 | J22: =J14+J18+J19-J9-J12 -> 1080.8101 | K22: =K14+K18+K19-K9-K12 -> 1317.0951 | L22: =L14+L18+L19-L9-L12 -> 1982.8319 | M22: =M14+M18+M19-M9-M12 -> 2794.4046
A23: 三、股本、股权融资与股份支付
A24: 新增股份（定增/股权激励行权） | B24: 百万股 | F24: 12.91 | G24: 2.45 | H24: 0 | I24: 3.46 | J24: 0.881 | K24: 0.881 | L24: 1.322 | M24: 1.322 | N24: 2026年：以简易程序定增3,459,409股（86.72元，2026-06-01上市）；2027-2030年：2026年计划（第二类限制性股票）首次授予440.60万股（2026-09-24授予，价格45.98元），按20%/20%/30%/30%四期归属，归属时发行并缴款；考核为以2025年营收为基数，2026-2029年增长不低于20%/40%/60%/80%（媒体报道口径）
A25: 上市公司股权融资现金（含激励行权款） | B25: 百万元 | I25: 294 | J25: 40.5 | K25: 40.5 | L25: 60.8 | M25: 60.8 | N25: 定增募资净额2.94亿元；之后为限制性股票归属缴款（归属股数×45.98元）
A26: 股份支付费用（非现金，计入费用） | B26: 百万元 | D26: 38.98 | E26: 86.47 | F26: 55.23 | G26: -21.71 | H26: 16.23 | I26: 66 | J26: 112 | K26: 56 | L26: 26 | M26: 10 | N26: 2025年计划总成本7,543万元（2026H1确认2,411万元）；2026年计划为第二类限制性股票（媒体报道），2026-09-24首次授予440.60万股、授予价45.98元，按公允价值约48元/股、四期归属估算总成本约2.1亿元；2024年因业绩未达标冲回2,171万元
A27: 股份回购（计入库存股） | B27: 百万元 | I27: 0 | J27: 0 | K27: 0 | L27: 0 | M27: 0
A28: 期末总股本 | B28: 百万股 | C28: 337.94 | D28: 337.94 | E28: 506.91 | F28: 519.82 | G28: 522.27 | H28: 522.27 | I28: =H28+I24 -> 525.73 | J28: =I28+J24 -> 526.611 | K28: =J28+K24 -> 527.492 | L28: =K28+L24 -> 528.814 | M28: =L28+M24 -> 530.136
A29: 摊薄股本（用于EPS） | B29: 百万股 | C29: 506.91 | D29: 506.91 | E29: 506.91 | F29: 519.82 | G29: 522.27 | H29: 522.27 | I29: =I28 -> 525.73 | J29: =J28 -> 526.611 | K29: =K28 -> 527.492 | L29: =L28 -> 528.814 | M29: =M28 -> 530.136 | N29: 按期末股本摊薄，与一致预期口径一致；2020–2021年按2022年每10股转增5股追溯调整
A30: 四、分红
A31: 分红率（上一年归母净利润） | B31: % | I31: 0.2016 | J31: 0.22 | K31: 0.22 | L31: 0.22 | M31: 0.22 | N31: 2024年度每10股派1.30元（2025年支付6,768万元）；2025年度未作年末分配，改为2026年中期每10股派1.70元（8,933万元，2026年下半年支付）；之后按上年归母净利润22%（公司章程：成长期现金分红比例不低于20%）
A32: 当年支付现金股利（上市公司股东） | B32: 百万元 | I32: =I31*利润表!H27 -> 89.346036 | J32: =J31*利润表!I27 -> 135.94309 | K32: =K31*利润表!J27 -> 165.27181 | L32: =L31*利润表!K27 -> 212.24139 | M32: =M31*利润表!L27 -> 244.27219
A33: 每股股利（按支付年） | B33: 元 | I33: =I32/H28 -> 0.1710725 | J33: =J32/I28 -> 0.25857966 | K33: =K32/J28 -> 0.31384041 | L33: =L32/K28 -> 0.40235944 | M33: =M32/L28 -> 0.46192459
A34: 五、少数股东
A35: 子公司吸收少数股东投资 | B35: 百万元 | C35: 0 | D35: 170.3155 | E35: 296.7675 | F35: 57.1025 | G35: 267.81 | H35: 503.4 | I35: 60 | J35: 0 | K35: 0 | L35: 0 | M35: 0 | N35: 2026H1子公司吸收少数股东投资0.60亿元
A36: 支付少数股东股利 | B36: 百万元 | C36: 0.8 | D36: 0.4 | E36: 6 | F36: 0.4 | G36: 11.4029 | H36: 8.4177 | I36: 8 | J36: 10 | K36: 15 | L36: 20 | M36: 25
A38: 最低现金余额 | B38: 百万元 | C38: 300 | D38: 最低经营现金（约1个月营业成本+费用）；现金低于此水平时自动提取循环贷款，有盈余时优先偿还
A39: 循环贷款利率 | B39: % | C39: 0.03

Sheet 利润表
A1: 利润表（百万元）
A2: 2020A–2025A 为公司公告值（Wind）；2026E–2030E 为模型预测。
A4: 百万元 | B4: 单位 | C4: 2020A | D4: 2021A | E4: 2022A | F4: 2023A | G4: 2024A | H4: 2025A | I4: 2026E | J4: 2027E | K4: 2028E | L4: 2029E | M4: 2030E | N4: 说明 / 来源
A5: 营业收入 | B5: 百万元 | C5: 863.5783 | D5: 1223.5484 | E5: 1719.3652 | F5: 2090.5426 | G5: 1741.8114 | H5: 2016.3489 | I5: =业务拆分!I45 -> 2741.007 | J5: =业务拆分!J45 -> 3510.4561 | K5: =业务拆分!K45 -> 4419.9684 | L5: =业务拆分!L45 -> 5143.525 | M5: =业务拆分!M45 -> 5702.4159
A6: 同比 | B6: % | D6: =D5/C5-1 -> 0.41683551 | E6: =E5/D5-1 -> 0.4052286 | F6: =F5/E5-1 -> 0.21588049 | G6: =G5/F5-1 -> -0.16681373 | H6: =H5/G5-1 -> 0.15761609 | I6: =I5/H5-1 -> 0.35939122 | J6: =J5/I5-1 -> 0.28071769 | K6: =K5/J5-1 -> 0.25908663 | ... M6: =M5/L5-1 -> 0.10865911
A7: 营业成本 | B7: 百万元 | C7: 413.9059 | D7: 602.0772 | E7: 838.7601 | F7: 1056.1762 | G7: 1007.255 | H7: 1061.0723 | I7: =业务拆分!I50 -> 1364.0894 | J7: =业务拆分!J50 -> 1747.8221 | K7: =业务拆分!K50 -> 2242.9432 | L7: =业务拆分!L50 -> 2682.2558 | M7: =业务拆分!M50 -> 3037.752
A8: 毛利 | B8: 百万元 | C8: =C5-C7 -> 449.6724 | D8: =D5-D7 -> 621.4712 | E8: =E5-E7 -> 880.6051 | F8: =F5-F7 -> 1034.3664 | G8: =G5-G7 -> 734.5564 | H8: =H5-H7 -> 955.2766 | I8: =I5-I7 -> 1376.9175 | J8: =J5-J7 -> 1762.634 | ... M8: =M5-M7 -> 2664.6639
A9: 毛利率 | B9: % | C9: =C8/C5 -> 0.52070831 | D9: =D8/D5 -> 0.50792531 | E9: =E8/E5 -> 0.51216874 | F9: =F8/F5 -> 0.4947837 | G9: =G8/G5 -> 0.42171983 | H9: =H8/H5 -> 0.47376553 | I9: =I8/I5 -> 0.50234003 | J9: =J8/J5 -> 0.50210968 | ... M9: =M8/M5 -> 0.46728684
A10: 税金及附加 | B10: 百万元 | C10: 8.9609 | D10: 8.5899 | E10: 16.8828 | F10: 21.5903 | G10: 17.7069 | H10: 24.7619 | I10: =I5*费用税率!I6 -> 35.633091 | J10: =J5*费用税率!J6 -> 45.63593 | K10: =K5*费用税率!K6 -> 57.459589 | L10: =L5*费用税率!L6 -> 66.865826 | M10: =M5*费用税率!M6 -> 74.131407
A11: 销售费用 | B11: 百万元 | C11: 12.221 | D11: 14.6814 | E11: 17.8909 | F11: 24.2449 | G11: 24.9286 | H11: 31.4848 | I11: =I5*费用税率!I7 -> 35.633091 | J11: =J5*费用税率!J7 -> 42.125474 | K11: =K5*费用税率!K7 -> 53.039621 | L11: =L5*费用税率!L7 -> 61.722301 | M11: =M5*费用税率!M7 -> 68.428991
A12: 管理费用 | B12: 百万元 | C12: 90.2852 | D12: 112.7891 | E12: 157.9808 | F12: 181.8014 | G12: 146.8615 | H12: 179.2238 | I12: =I5*费用税率!I8+融资!I26 -> 235.94243 | J12: =J5*费用税率!J8+融资!J26 -> 322.62737 | K12: =K5*费用税率!K8+融资!K26 -> 307.9382 | L12: =L5*费用税率!L8+融资!L26 -> 308.89388 | M12: =M5*费用税率!M8+融资!M26 -> 312.22804 | N12: 预测期 = 收入×管理费用率（不含股份支付）+ 股份支付费用
A13: 研发费用 | B13: 百万元 | C13: 73.4927 | D13: 94.889 | E13: 154.7066 | F13: 223.2068 | G13: 249.944 | H13: 282.2769 | I13: =MAX(I5*费用税率!I9,费用税率!I10) -> 345.36688 | J13: =MAX(J5*费用税率!J9,费用税率!J10) -> 386.15018 | K13: =MAX(K5*费用税率!K9,费用税率!K10) -> 441.99684 | L13: =MAX(L5*费用税率!L9,费用税率!L10) -> 478.34783 | M13: =MAX(M5*费用税率!M9,费用税率!M10) -> 507.51502 | N13: ＝ MAX(收入×研发费用率, 研发费用下限)
A14: 财务费用 | B14: 百万元 | C14: 1.6135 | D14: -8.0409 | E14: -24.3845 | F14: -14.5028 | G14: -0.1005 | H14: 6.2334 | I14: =融资!I11-融资!I16+融资!I17 -> 12.010552 | J14: =融资!J11-融资!J16+融资!J17 -> -1.948835 | K14: =融资!K11-融资!K16+融资!K17 -> -0.35810057 | L14: =融资!L11-融资!L16+融资!L17 -> -2.7209512 | M14: =融资!M11-融资!M16+融资!M17 -> -9.3783194
A15: 加：其他收益 | B15: 百万元 | C15: 9.8315 | D15: 20.8751 | E15: 14.711 | F15: 51.5648 | G15: 58.0943 | H15: 53.1945 | I15: =I5*费用税率!I12 -> 49.338126 | J15: =J5*费用税率!J12 -> 56.167298 | K15: =K5*费用税率!K12 -> 66.299526 | L15: =L5*费用税率!L12 -> 72.009351 | M15: =M5*费用税率!M12 -> 74.131407
A16: 投资净收益 | B16: 百万元 | C16: 4.5059 | D16: 13.0497 | E16: 7.9385 | F16: 2.8456 | G16: 11.9771 | H16: 3.7216 | I16: =融资!I21 -> 17.845079 | J16: =融资!J21 -> 14.74 | K16: =融资!K21 -> 14.74 | L16: =融资!L21 -> 14.74 | M16: =融资!M21 -> 14.74
A17: 公允价值变动净收益 | B17: 百万元 | C17: 2.7902 | D17: 0.944 | E17: 0.4697 | F17: 16.1219 | G17: 16.5186 | H17: 19.8539 | I17: 7.28 | J17: 0 | K17: 0 | L17: 0 | M17: 0 | N17: 2026E取上半年实际值；之后并入投资收益
A18: 信用减值损失 | B18: 百万元 | C18: -0.832 | D18: -0.6077 | E18: -6.378 | F18: -10.6554 | G18: -8.3884 | H18: -17.1222 | I18: =I5*费用税率!I13 -> -16.446042 | J18: =J5*费用税率!J13 -> -17.552281 | K18: =K5*费用税率!K13 -> -22.099842 | L18: =L5*费用税率!L13 -> -25.717625 | M18: =M5*费用税率!M13 -> -28.51208
A19: 资产减值损失 | B19: 百万元 | C19: -0.5641 | D19: -2.2623 | E19: -6.274 | F19: -9.9623 | G19: -20.0664 | H19: -35.8086 | I19: =I5*费用税率!I14 -> -21.928056 | J19: =J5*费用税率!J14 -> -24.573193 | K19: =K5*费用税率!K14 -> -26.51981 | L19: =L5*费用税率!L14 -> -30.86115 | M19: =M5*费用税率!M14 -> -34.214496
A20: 资产处置收益 | B20: 百万元 | C20: -0.0964 | D20: -5.3795 | E20: 0.2296 | F20: 0.3183 | G20: -2.0721 | H20: 0.7567 | I20: 3.8 | J20: 0 | K20: 0 | L20: 0 | M20: 0 | N20: 2026E取上半年实际值
A21: 营业利润 | B21: 百万元 | C21: =C8-C10-C11-C12-C13-C14+C15+C16+C17+C18+C19+C20 -> 278.7342 | D21: =D8-D10-D11-D12-D13-D14+D15+D16+D17+D18+D19+D20 -> 425.182 | E21: =E8-E10-E11-E12-E13-E14+E15+E16+E17+E18+E19+E20 -> 568.2253 | F21: =F8-F10-F11-F12-F13-F14+F15+F16+F17+F18+F19+F20 -> 648.2587 | G21: =G8-G10-G11-G12-G13-G14+G15+G16+G17+G18+G19+G20 -> 351.279 | H21: =H8-H10-H11-H12-H13-H14+H15+H16+H17+H18+H19+H20 -> 455.8917 | I21: =I8-I10-I11-I12-I13-I14+I15+I16+I17+I18+I19+I20 -> 752.22061 | J21: =J8-J10-J11-J12-J13-J14+J15+J16+J17+J18+J19+J20 -> 996.82572 | ... M21: =M8-M10-M11-M12-M13-M14+M15+M16+M17+M18+M19+M20 -> 1737.8836
A22: 加：营业外收支净额 | B22: 百万元 | C22: -6.2 | D22: -2.38 | E22: -2.21 | F22: -4.1 | G22: -6.93 | H22: 10.64 | I22: =费用税率!I15 -> 0 | J22: =费用税率!J15 -> 0 | K22: =费用税率!K15 -> 0 | L22: =费用税率!L15 -> 0 | M22: =费用税率!M15 -> 0
A23: 利润总额 | B23: 百万元 | C23: =C21+C22 -> 272.5342 | D23: =D21+D22 -> 422.802 | E23: =E21+E22 -> 566.0153 | F23: =F21+F22 -> 644.1587 | G23: =G21+G22 -> 344.349 | H23: =H21+H22 -> 466.5317 | I23: =I21+I22 -> 752.22061 | J23: =J21+J22 -> 996.82572 | ... M23: =M21+M22 -> 1737.8836
A24: 减：所得税 | B24: 百万元 | C24: 33.0812 | D24: 47.0046 | E24: 53.2417 | F24: 69.7434 | G24: 18.0807 | H24: 40.1323 | I24: =I23*费用税率!I23 -> 88.044563 | J24: =J23*费用税率!J23 -> 121.94084 | K24: =K23*费用税率!K23 -> 171.55071 | L24: =L23*费用税率!L23 -> 203.28918 | M24: =M23*费用税率!M23 -> 226.37568
A25: 净利润 | B25: 百万元 | C25: =C23-C24 -> 239.453 | D25: =D23-D24 -> 375.7974 | E25: =E23-E24 -> 512.7736 | F25: =F23-F24 -> 574.4153 | G25: =G23-G24 -> 326.2683 | H25: =H23-H24 -> 426.3994 | I25: =I23-I24 -> 664.17604 | J25: =J23-J24 -> 874.88488 | ... M25: =M23-M24 -> 1511.5079
A26: 减：少数股东损益 | B26: 百万元 | C26: 1.3392 | D26: 5.6737 | E26: 24.0334 | F26: 36.7671 | G26: 12.0588 | H26: -16.7853 | I26: =I25*费用税率!I25+费用税率!I26 -> 46.252923 | J26: =J25*费用税率!J25+费用税率!J26 -> 123.64936 | K26: =K25*费用税率!K25+费用税率!K26 -> 213.08462 | L26: =L25*费用税率!L25+费用税率!L26 -> 264.7136 | M26: =M25*费用税率!M25+费用税率!M26 -> 304.29654 | N26: ＝ 净利润×分部加权少数股东比例 + 亏损主体少数股东分担额
A27: 归属于母公司股东的净利润 | B27: 百万元 | C27: =C25-C26 -> 238.1138 | D27: =D25-D26 -> 370.1237 | E27: =E25-E26 -> 488.7402 | F27: =F25-F26 -> 537.6482 | G27: =G25-G26 -> 314.2095 | H27: =H25-H26 -> 443.1847 | I27: =I25-I26 -> 617.92312 | J27: =J25-J26 -> 751.23552 | ... M27: =M25-M26 -> 1207.2114
A28: 同比 | B28: % | D28: =D27/C27-1 -> 0.55439836 | E28: =E27/D27-1 -> 0.32047799 | F28: =F27/E27-1 -> 0.10006953 | G28: =G27/F27-1 -> -0.41558532 | H28: =H27/G27-1 -> 0.41047518 | I28: =I27/H27-1 -> 0.394279 | J28: =J27/I27-1 -> 0.2157427 | K28: =K27/J27-1 -> 0.28419591 | ... M28: =M27/L27-1 -> 0.087256413
A29: 每股收益（摊薄） | B29: 元 | C29: =C27/融资!C29 -> 0.46973585 | D29: =D27/融资!D29 -> 0.73015664 | E29: =E27/融资!E29 -> 0.96415577 | F29: =F27/融资!F29 -> 1.0342969 | G29: =G27/融资!G29 -> 0.60162272 | H29: =H27/融资!H29 -> 0.84857392 | I29: =I27/融资!I29 -> 1.1753621 | J29: =J27/融资!J29 -> 1.4265473 | ... M29: =M27/融资!M29 -> 2.277173
A30: 核心指标
A31: 期间费用合计（税金及附加+销售+管理+研发） | B31: 百万元 | C31: =C10+C11+C12+C13 -> 184.9598 | D31: =D10+D11+D12+D13 -> 230.9494 | E31: =E10+E11+E12+E13 -> 347.4611 | F31: =F10+F11+F12+F13 -> 450.8434 | G31: =G10+G11+G12+G13 -> 439.441 | H31: =H10+H11+H12+H13 -> 517.7474 | I31: =I10+I11+I12+I13 -> 652.5755 | J31: =J10+J11+J12+J13 -> 796.53895 | ... M31: =M10+M11+M12+M13 -> 962.30346
A32: EBIT（营业利润+财务费用−投资收益−公允价值变动） | B32: 百万元 | C32: =C21+C14-C16-C17 -> 273.0516 | D32: =D21+D14-D16-D17 -> 403.1474 | E32: =E21+E14-E16-E17 -> 535.4326 | F32: =F21+F14-F16-F17 -> 614.7884 | G32: =G21+G14-G16-G17 -> 322.6828 | H32: =H21+H14-H16-H17 -> 438.5496 | I32: =I21+I14-I16-I17 -> 739.10608 | J32: =J21+J14-J16-J17 -> 980.13688 | ... M32: =M21+M14-M16-M17 -> 1713.7653
A33: EBITDA | B33: 百万元 | C33: =C32+资本开支!C49 -> 334.3764 | D33: =D32+资本开支!D49 -> 488.2647 | E33: =E32+资本开支!E49 -> 650.4581 | F33: =F32+资本开支!F49 -> 782.3496 | G33: =G32+资本开支!G49 -> 529.6721 | H33: =H32+资本开支!H49 -> 686.8579 | I33: =I32+资本开支!I49 -> 1039.6292 | J33: =J32+资本开支!J49 -> 1344.2434 | ... M33: =M32+资本开支!M49 -> 2302.0727
A34: EBIT率 | B34: % | C34: =C32/C5 -> 0.31618627 | D34: =D32/D5 -> 0.32949036 | E34: =E32/E5 -> 0.31141296 | F34: =F32/F5 -> 0.29408078 | G34: =G32/G5 -> 0.18525703 | H34: =H32/H5 -> 0.21749688 | I34: =I32/I5 -> 0.26964764 | J34: =J32/J5 -> 0.27920499 | ... M34: =M32/M5 -> 0.30053319
A35: 归母净利率 | B35: % | C35: =C27/C5 -> 0.27572925 | D35: =D27/D5 -> 0.30250025 | E35: =E27/E5 -> 0.28425619 | F35: =F27/F5 -> 0.25718117 | G35: =G27/G5 -> 0.18039238 | H35: =H27/H5 -> 0.21979564 | I35: =I27/I5 -> 0.22543653 | J35: =J27/J5 -> 0.2139994 | ... M35: =M27/M5 -> 0.21170174
A36: 研发费用率 | B36: % | C36: =C13/C5 -> 0.085102532 | D36: =D13/D5 -> 0.077552306 | E36: =E13/E5 -> 0.089978906 | F36: =F13/F5 -> 0.10676979 | G36: =G13/G5 -> 0.14349659 | H36: =H13/H5 -> 0.13999408 | I36: =I13/I5 -> 0.126 | J36: =J13/J5 -> 0.11 | ... M36: =M13/M5 -> 0.089
A37: ROE（归母，期末） | B37: % | C37: =C27/资产负债表!C59 -> 0.11444528 | D37: =D27/资产负债表!D59 -> 0.15027944 | E37: =E27/资产负债表!E59 -> 0.16256808 | F37: =F27/资产负债表!F59 -> 0.13714292 | G37: =G27/资产负债表!G59 -> 0.076101319 | H37: =H27/资产负债表!H59 -> 0.09577148 | I37: =I27/资产负债表!I59 -> 0.11202174 | J37: =J27/资产负债表!J59 -> 0.1195494 | ... M37: =M27/资产负债表!M59 -> 0.13124031
A38: ROIC（税后EBIT/（净营运资本+固定资产+在建工程+无形资产）） | B38: % | C38: =C32*(1-费用税率!C23)/(营运资本!C37+资本开支!C41+资本开支!C29+资本开支!C46) -> 0.20327466 | D38: =D32*(1-费用税率!D23)/(营运资本!D37+资本开支!D41+资本开支!D29+资本开支!D46) -> 0.23173654 | E38: =E32*(1-费用税率!E23)/(营运资本!E37+资本开支!E41+资本开支!E29+资本开支!E46) -> 0.20347904 | F38: =F32*(1-费用税率!F23)/(营运资本!F37+资本开支!F41+资本开支!F29+资本开支!F46) -> 0.17418573 | G38: =G32*(1-费用税率!G23)/(营运资本!G37+资本开支!G41+资本开支!G29+资本开支!G46) -> 0.084769611 | H38: =H32*(1-费用税率!H23)/(营运资本!H37+资本开支!H41+资本开支!H29+资本开支!H46) -> 0.096138643 | I38: =I32*(1-费用税率!I23)/(营运资本!I37+资本开支!I41+资本开支!I29+资本开支!I46) -> 0.12681388 | J38: =J32*(1-费用税率!J23)/(营运资本!J37+资本开支!J41+资本开支!J29+资本开支!J46) -> 0.13838892 | ... M38: =M32*(1-费用税率!M23)/(营运资本!M37+资本开支!M41+资本开支!M29+资本开支!M46) -> 0.18126193
A39: 扣非归母净利润（历史） | B39: 百万元 | C39: 230.47 | D39: 349.17 | E39: 473 | F39: 495.81 | G39: 264.21 | H39: 386.25 | N39: 来源：年报“非经常性损益”

Sheet 资产负债表
A1: 资产负债表（百万元）
A2: 现金为平衡项：期末现金 = 上年现金 + 现金流量表净增加额。未单独建模的科目预测期保持不变。
A4: 百万元 | B4: 单位 | C4: 2020A | D4: 2021A | E4: 2022A | F4: 2023A | G4: 2024A | H4: 2025A | I4: 2026E | J4: 2027E | K4: 2028E | L4: 2029E | M4: 2030E | N4: 说明 / 来源
A5: 流动资产
A6: 货币资金 | B6: 百万元 | C6: 394.6839 | D6: 678.8377 | E6: 824.4059 | F6: 586.4147 | G6: 685.1896 | H6: 811.7069 | I6: =H6+现金流量表!I26 -> 883.6335 | J6: =I6+现金流量表!J26 -> 660.81006 | K6: =J6+现金流量表!K26 -> 897.09512 | L6: =K6+现金流量表!L26 -> 1562.8319 | M6: =L6+现金流量表!M26 -> 2374.4046
A7: 交易性金融资产 | B7: 百万元 | C7: 452.7902 | D7: 280.944 | E7: 204.1341 | F7: 363.8887 | G7: 392.1992 | H7: 708.1757 | I7: =融资!I18 -> 500 | J7: =融资!J18 -> 500 | K7: =融资!K18 -> 500 | L7: =融资!L18 -> 500 | M7: =融资!M18 -> 500
A8: 应收票据 | B8: 百万元 | C8: 218.8513 | D8: 240.8312 | E8: 398.4657 | F8: 405.7188 | G8: 280.4393 | H8: 350.7365 | I8: =营运资本!I22 -> 450.57649 | J8: =营运资本!J22 -> 557.82591 | K8: =营运资本!K22 -> 678.13213 | L8: =营运资本!L22 -> 775.05172 | M8: =营运资本!M22 -> 859.26815
A9: 应收账款 | B9: 百万元 | C9: 219.3734 | D9: 231.9502 | E9: 335.0477 | F9: 482.4831 | G9: 501.4117 | H9: 716.2445 | I9: =营运资本!I21 -> 938.70103 | J9: =营运资本!J21 -> 1192.5933 | K9: =营运资本!K21 -> 1489.4688 | L9: =营运资本!L21 -> 1719.2056 | M9: =营运资本!M21 -> 1906.013
A10: 应收款项融资 | B10: 百万元 | C10: 0 | D10: 55.3505 | E10: 41.3399 | F10: 106.2006 | G10: 114.0197 | H10: 89.4289 | I10: =营运资本!I23 -> 112.64412 | J10: =营运资本!J23 -> 144.26532 | K10: =营运资本!K23 -> 181.64254 | L10: =营运资本!L23 -> 211.37774 | M10: =营运资本!M23 -> 234.34586
A11: 预付款项 | B11: 百万元 | C11: 99.8956 | D11: 39.4738 | E11: 64.245 | F11: 196.8847 | G11: 90.3373 | H11: 108.1176 | I11: =营运资本!I24 -> 112.11694 | J11: =营运资本!J24 -> 143.65661 | K11: =营运资本!K24 -> 184.3515 | L11: =营运资本!L24 -> 220.45938 | M11: =营运资本!M24 -> 249.67825
A12: 其他应收款 | B12: 百万元 | C12: 0.6937 | D12: 5.91 | E12: 1.8565 | F12: 2.8109 | G12: 19.1425 | H12: 45.2905 | I12: =营运资本!I25 -> 30.038433 | J12: =营运资本!J25 -> 38.470752 | K12: =营运资本!K25 -> 48.43801 | L12: =营运资本!L25 -> 56.367398 | M12: =营运资本!M25 -> 62.492229
A13: 存货 | B13: 百万元 | C13: 199.3023 | D13: 323.8021 | E13: 463.9703 | F13: 665.8346 | G13: 743.1362 | H13: 916.0337 | I13: =营运资本!I26 -> 1233.2864 | J13: =营运资本!J26 -> 1532.3372 | K13: =营运资本!K26 -> 1904.9655 | L13: =营运资本!L26 -> 2204.5938 | M13: =营运资本!M26 -> 2455.1694
A14: 其他流动资产 | B14: 百万元 | C14: 16.7631 | D14: 14.5607 | E14: 48.5052 | F14: 78.9559 | G14: 80.0299 | H14: 65.9106 | I14: =营运资本!I27 -> 75.096082 | J14: =营运资本!J27 -> 96.176881 | K14: =营运资本!K27 -> 121.09502 | L14: =营运资本!L27 -> 140.91849 | M14: =营运资本!M27 -> 156.23057
A15: 流动资产合计 | B15: 百万元 | C15: =C6+C7+C8+C9+C10+C11+C12+C13+C14 -> 1602.3535 | D15: =D6+D7+D8+D9+D10+D11+D12+D13+D14 -> 1871.6602 | E15: =E6+E7+E8+E9+E10+E11+E12+E13+E14 -> 2381.9703 | F15: =F6+F7+F8+F9+F10+F11+F12+F13+F14 -> 2889.192 | G15: =G6+G7+G8+G9+G10+G11+G12+G13+G14 -> 2905.9054 | H15: =H6+H7+H8+H9+H10+H11+H12+H13+H14 -> 3811.6449 | I15: =I6+I7+I8+I9+I10+I11+I12+I13+I14 -> 4336.093 | J15: =J6+J7+J8+J9+J10+J11+J12+J13+J14 -> 4866.1361 | ... M15: =M6+M7+M8+M9+M10+M11+M12+M13+M14 -> 8797.6021
A16: 非流动资产
A17: 长期股权投资 | B17: 百万元 | C17: 0 | D17: 7.1281 | E17: 6.523 | F17: 6.1584 | G17: 5.6205 | H17: 11.14 | I17: =H17 -> 11.14 | J17: =I17 -> 11.14 | K17: =J17 -> 11.14 | L17: =K17 -> 11.14 | M17: =L17 -> 11.14
A18: 其他非流动金融资产 | B18: 百万元 | C18: 0 | D18: 0 | E18: 0 | F18: 566.2206 | G18: 452.9046 | H18: 244.1042 | I18: =融资!I19 -> 170 | J18: =融资!J19 -> 170 | K18: =融资!K19 -> 170 | L18: =融资!L19 -> 170 | M18: =融资!M19 -> 170
A19: 固定资产 | B19: 百万元 | C19: 605.6634 | D19: 970.4833 | E19: 1343.0813 | F19: 1765.0717 | G19: 1863.2982 | H19: 2318.4985 | I19: =资本开支!I41 -> 2637.4938 | J19: =资本开支!J41 -> 3180.4841 | K19: =资本开支!K41 -> 3708.5468 | L19: =资本开支!L41 -> 4041.3637 | M19: =资本开支!M41 -> 4255.1841
A20: 在建工程 | B20: 百万元 | C20: 118.3541 | D20: 57.9785 | E20: 179.4215 | F20: 134.2695 | G20: 265.7579 | H20: 207.0485 | I20: =资本开支!I29 -> 411.72256 | J20: =资本开支!J29 -> 487.37894 | K20: =资本开支!K29 -> 384.7014 | L20: =资本开支!L29 -> 273.57966 | M20: =资本开支!M29 -> 213.06651
A21: 使用权资产 | B21: 百万元 | C21: 0 | D21: 8.6316 | E21: 6.7115 | F21: 16.6802 | G21: 12.538 | H21: 6.5047 | I21: =H21 -> 6.5047 | J21: =I21 -> 6.5047 | K21: =J21 -> 6.5047 | L21: =K21 -> 6.5047 | M21: =L21 -> 6.5047
A22: 无形资产 | B22: 百万元 | C22: 56.7116 | D22: 96.5509 | E22: 151.3484 | F22: 182.4975 | G22: 212.7828 | H22: 259.6477 | I22: =资本开支!I46 -> 278.87588 | J22: =资本开支!J46 -> 286.56581 | K22: =资本开支!K46 -> 283.64055 | L22: =资本开支!L46 -> 280.9493 | M22: =资本开支!M46 -> 278.47336
A23: 开发支出 | B23: 百万元 | C23: 0 | D23: 0 | E23: 0 | F23: 0 | G23: 0 | H23: 0 | I23: =H23 -> 0 | J23: =I23 -> 0 | K23: =J23 -> 0 | L23: =K23 -> 0 | M23: =L23 -> 0
A24: 商誉 | B24: 百万元 | C24: 100.0871 | D24: 122.2838 | E24: 122.2838 | F24: 122.2838 | G24: 122.2838 | H24: 122.2838 | I24: =H24 -> 122.2838 | J24: =I24 -> 122.2838 | K24: =J24 -> 122.2838 | L24: =K24 -> 122.2838 | M24: =L24 -> 122.2838 | N24: 上海石创100.09百万元（2016年收购）+中益新材22.20百万元（2021年收购），2021年以来未减值
A25: 长期待摊费用 | B25: 百万元 | C25: 9.6909 | D25: 6.8636 | E25: 8.0646 | F25: 7.261 | G25: 20.1157 | H25: 29.6538 | I25: =H25 -> 29.6538 | J25: =I25 -> 29.6538 | K25: =J25 -> 29.6538 | L25: =K25 -> 29.6538 | M25: =L25 -> 29.6538
A26: 递延所得税资产 | B26: 百万元 | C26: 13.5358 | D26: 16.0784 | E26: 52.5425 | F26: 54.3663 | G26: 73.2587 | H26: 118.5456 | I26: =H26 -> 118.5456 | J26: =I26 -> 118.5456 | K26: =J26 -> 118.5456 | L26: =K26 -> 118.5456 | M26: =L26 -> 118.5456
A27: 其他非流动资产（设备及工程预付款） | B27: 百万元 | C27: 0 | D27: 94.8278 | E27: 72.2078 | F27: 171.0122 | G27: 156.4585 | H27: 234.1026 | I27: =资本开支!I22 -> 406.21208 | J27: =资本开支!J22 -> 389.4873 | K27: =资本开支!K22 -> 317.71937 | L27: =资本开支!L22 -> 280.7646 | M27: =资本开支!M22 -> 305.58281
A28: 非流动资产合计 | B28: 百万元 | C28: =C17+C18+C19+C20+C21+C22+C23+C24+C25+C26+C27 -> 904.0429 | D28: =D17+D18+D19+D20+D21+D22+D23+D24+D25+D26+D27 -> 1380.826 | E28: =E17+E18+E19+E20+E21+E22+E23+E24+E25+E26+E27 -> 1942.1844 | F28: =F17+F18+F19+F20+F21+F22+F23+F24+F25+F26+F27 -> 3025.8212 | G28: =G17+G18+G19+G20+G21+G22+G23+G24+G25+G26+G27 -> 3185.0187 | H28: =H17+H18+H19+H20+H21+H22+H23+H24+H25+H26+H27 -> 3551.5294 | I28: =I17+I18+I19+I20+I21+I22+I23+I24+I25+I26+I27 -> 4192.4322 | J28: =J17+J18+J19+J20+J21+J22+J23+J24+J25+J26+J27 -> 4802.044 | ... M28: =M17+M18+M19+M20+M21+M22+M23+M24+M25+M26+M27 -> 5510.4347
A29: 资产总计 | B29: 百万元 | C29: =C15+C28 -> 2506.3964 | D29: =D15+D28 -> 3252.4862 | E29: =E15+E28 -> 4324.1547 | F29: =F15+F28 -> 5915.0132 | G29: =G15+G28 -> 6090.9241 | H29: =H15+H28 -> 7363.1743 | I29: =I15+I28 -> 8528.5252 | J29: =J15+J28 -> 9668.1801 | ... M29: =M15+M28 -> 14308.037
A30: 流动负债
A31: 短期借款 | B31: 百万元 | C31: 0 | D31: 0 | E31: 3 | F31: 142.9382 | G31: 117.4009 | H31: 195.6741 | I31: =融资!I6 -> 120 | J31: =融资!J6 -> 120 | K31: =融资!K6 -> 120 | L31: =融资!L6 -> 120 | M31: =融资!M6 -> 120
A32: 应付票据 | B32: 百万元 | C32: 112.9988 | D32: 112.4339 | E32: 133.3691 | F32: 317.3687 | G32: 165.1758 | H32: 201.7146 | I32: =营运资本!I28 -> 280.29235 | J32: =营运资本!J28 -> 359.14153 | K32: =营运资本!K28 -> 460.87874 | L32: =营运资本!L28 -> 551.14846 | M32: =营运资本!M28 -> 624.19562
A33: 应付账款 | B33: 百万元 | C33: 153.0441 | D33: 203.4393 | E33: 310.7521 | F33: 303.2132 | G33: 215.8137 | H33: 342.6115 | I33: =营运资本!I29 -> 411.09545 | J33: =营运资本!J29 -> 536.31802 | K33: =营运资本!K29 -> 688.24558 | L33: =营运资本!L29 -> 823.04836 | M33: =营运资本!M29 -> 932.13213
A34: 预收款项 | B34: 百万元 | C34: 0.0669 | D34: 0 | E34: 0 | F34: 0 | G34: 0 | H34: 0 | I34: =H34 -> 0 | J34: =I34 -> 0 | K34: =J34 -> 0 | L34: =K34 -> 0 | M34: =L34 -> 0
A35: 合同负债 | B35: 百万元 | C35: 10.1313 | D35: 8.9468 | E35: 23.1784 | F35: 17.0223 | G35: 22.7053 | H35: 20.4294 | I35: =营运资本!I30 -> 30.038433 | J35: =营运资本!J30 -> 38.470752 | K35: =营运资本!K30 -> 48.43801 | L35: =营运资本!L30 -> 56.367398 | M35: =营运资本!M30 -> 62.492229
A36: 应付职工薪酬 | B36: 百万元 | C36: 41.1022 | D36: 45.3797 | E36: 47.2096 | F36: 60.4693 | G36: 63.7831 | H36: 80.0895 | I36: =营运资本!I31 -> 105.13452 | J36: =营运资本!J31 -> 134.64763 | K36: =营运资本!K31 -> 169.53303 | L36: =营运资本!L31 -> 197.28589 | M36: =营运资本!M31 -> 218.7228
A37: 应交税费 | B37: 百万元 | C37: 24.0286 | D37: 34.3719 | E37: 48.8534 | F37: 49.7896 | G37: 22.5359 | H37: 75.014 | I37: =营运资本!I32 -> 82.60569 | J37: =营运资本!J32 -> 105.79457 | K37: =营运资本!K32 -> 133.20453 | L37: =营运资本!L32 -> 155.01034 | M37: =营运资本!M32 -> 171.85363
A38: 其他应付款 | B38: 百万元 | C38: 11.2502 | D38: 29.623 | E38: 28.006 | F38: 30.8399 | G38: 4.8616 | H38: 99.6528 | I38: =营运资本!I33 -> 105.13452 | J38: =营运资本!J33 -> 115.41226 | K38: =营运资本!K33 -> 145.31403 | L38: =营运资本!L33 -> 169.10219 | M38: =营运资本!M33 -> 187.47669
A39: 一年内到期的非流动负债 | B39: 百万元 | C39: 0 | D39: 1.7833 | E39: 3.7349 | F39: 38.5681 | G39: 149.9592 | H39: 5.0356 | I39: =融资!I7 -> 152 | J39: =融资!J7 -> 50 | K39: =融资!K7 -> 50 | L39: =融资!L7 -> 50 | M39: =融资!M7 -> 50
A40: 循环贷款（模型平衡项） | B40: 百万元 | C40: 0 | D40: 0 | E40: 0 | F40: 0 | G40: 0 | H40: 0 | I40: =融资!I12 -> 0 | J40: =融资!J12 -> 0 | K40: =融资!K12 -> 0 | L40: =融资!L12 -> 0 | M40: =融资!M12 -> 0 | N40: 历史为0；预测期现金低于最低余额时提取
A41: 其他流动负债 | B41: 百万元 | C41: 2.8393 | D41: 56.4239 | E41: 52.0426 | F41: 94.6658 | G41: 68.7663 | H41: 88.2123 | I41: =营运资本!I34 -> 120.15373 | J41: =营运资本!J34 -> 153.88301 | K41: =营运资本!K34 -> 193.75204 | L41: =营运资本!L34 -> 225.46959 | M41: =营运资本!M34 -> 249.96892
A42: 流动负债合计 | B42: 百万元 | C42: =C31+C32+C33+C34+C35+C36+C37+C38+C39+C40+C41 -> 355.4614 | D42: =D31+D32+D33+D34+D35+D36+D37+D38+D39+D40+D41 -> 492.4018 | E42: =E31+E32+E33+E34+E35+E36+E37+E38+E39+E40+E41 -> 650.1461 | F42: =F31+F32+F33+F34+F35+F36+F37+F38+F39+F40+F41 -> 1054.8751 | G42: =G31+G32+G33+G34+G35+G36+G37+G38+G39+G40+G41 -> 831.0018 | H42: =H31+H32+H33+H34+H35+H36+H37+H38+H39+H40+H41 -> 1108.4338 | I42: =I31+I32+I33+I34+I35+I36+I37+I38+I39+I40+I41 -> 1406.4547 | J42: =J31+J32+J33+J34+J35+J36+J37+J38+J39+J40+J41 -> 1613.6678 | ... M42: =M31+M32+M33+M34+M35+M36+M37+M38+M39+M40+M41 -> 2616.842
A43: 非流动负债
A44: 长期借款 | B44: 百万元 | C44: 0 | D44: 0 | E44: 32.9718 | F44: 113.5195 | G44: 69.012 | H44: 148.5 | I44: =融资!I8 -> 29 | J44: =融资!J8 -> 80 | K44: =融资!K8 -> 80 | L44: =融资!L8 -> 80 | M44: =融资!M8 -> 80
A45: 租赁负债 | B45: 百万元 | C45: 0 | D45: 5.997 | E45: 4.3074 | F45: 8.8391 | G45: 5.0976 | H45: 1.8259 | I45: =H45 -> 1.8259 | J45: =I45 -> 1.8259 | K45: =J45 -> 1.8259 | L45: =K45 -> 1.8259 | M45: =L45 -> 1.8259
A46: 长期应付款（专项应付款） | B46: 百万元 | C46: 25.34 | D46: 27.4 | E46: 27.4 | F46: 10 | G46: 10 | H46: 10 | I46: =H46 -> 10 | J46: =I46 -> 10 | K46: =J46 -> 10 | L46: =K46 -> 10 | M46: =L46 -> 10
A47: 递延所得税负债 | B47: 百万元 | C47: 22.3126 | D47: 41.8922 | E47: 70.0443 | F47: 67.81 | G47: 67.8076 | H47: 73.7869 | I47: =H47 -> 73.7869 | J47: =I47 -> 73.7869 | K47: =J47 -> 73.7869 | L47: =K47 -> 73.7869 | M47: =L47 -> 73.7869
A48: 递延收益 | B48: 百万元 | C48: 14.867 | D48: 25.089 | E48: 61.0924 | F48: 158.7179 | G48: 160.8174 | H48: 231.2201 | I48: =H48 -> 231.2201 | J48: =I48 -> 231.2201 | K48: =J48 -> 231.2201 | L48: =K48 -> 231.2201 | M48: =L48 -> 231.2201 | N48: 政府补助，假设新增=摊销
A49: 其他非流动负债 | B49: 百万元 | C49: 0 | D49: 0 | E49: 0 | F49: 0 | G49: 0 | H49: 0 | I49: =H49 -> 0 | J49: =I49 -> 0 | K49: =J49 -> 0 | L49: =K49 -> 0 | M49: =L49 -> 0
A50: 非流动负债合计 | B50: 百万元 | C50: =C44+C45+C46+C47+C48+C49 -> 62.5196 | D50: =D44+D45+D46+D47+D48+D49 -> 100.3782 | E50: =E44+E45+E46+E47+E48+E49 -> 195.8159 | F50: =F44+F45+F46+F47+F48+F49 -> 358.8865 | G50: =G44+G45+G46+G47+G48+G49 -> 312.7346 | H50: =H44+H45+H46+H47+H48+H49 -> 465.3329 | I50: =I44+I45+I46+I47+I48+I49 -> 345.8329 | J50: =J44+J45+J46+J47+J48+J49 -> 396.8329 | ... M50: =M44+M45+M46+M47+M48+M49 -> 396.8329
A51: 负债合计 | B51: 百万元 | C51: =C42+C50 -> 417.981 | D51: =D42+D50 -> 592.78 | E51: =E42+E50 -> 845.962 | F51: =F42+F50 -> 1413.7616 | G51: =G42+G50 -> 1143.7364 | H51: =H42+H50 -> 1573.7667 | I51: =I42+I50 -> 1752.2876 | J51: =J42+J50 -> 2010.5007 | ... M51: =M42+M50 -> 3013.6749
A52: 股东权益
A53: 股本 | B53: 百万元 | C53: 337.9488 | D53: 337.9488 | E53: 506.9233 | F53: 519.823 | G53: 522.2677 | H53: 522.2677 | I53: =H53+融资!I24 -> 525.7277 | J53: =I53+融资!J24 -> 526.6087 | K53: =J53+融资!K24 -> 527.4897 | L53: =K53+融资!L24 -> 528.8117 | M53: =L53+融资!M24 -> 530.1337
A54: 资本公积 | B54: 百万元 | C54: 824.6386 | D54: 888.348 | E54: 851.8325 | F54: 1313.2825 | G54: 1364.2454 | H54: 1500.4491 | I54: =H54+融资!I25-融资!I24+融资!I26 -> 1856.9891 | J54: =I54+融资!J25-融资!J24+融资!J26 -> 2008.6081 | K54: =J54+融资!K25-融资!K24+融资!K26 -> 2104.2271 | L54: =K54+融资!L25-融资!L24+融资!L26 -> 2189.7051 | M54: =L54+融资!M25-融资!M24+融资!M26 -> 2259.1831
A55: 减：库存股 | B55: 百万元 | C55: 9.3132 | D55: 0 | E55: 0 | F55: 0 | G55: 50.1012 | H55: 63.1199 | I55: =H55+融资!I27 -> 63.1199 | J55: =I55+融资!J27 -> 63.1199 | K55: =J55+融资!K27 -> 63.1199 | L55: =K55+融资!L27 -> 63.1199 | M55: =L55+融资!M27 -> 63.1199
A56: 其他综合收益 | B56: 百万元 | C56: 0 | D56: 0 | E56: 0 | F56: 0 | G56: 0 | H56: 0 | I56: =H56 -> 0 | J56: =I56 -> 0 | K56: =J56 -> 0 | L56: =K56 -> 0 | M56: =L56 -> 0
A57: 盈余公积 | B57: 百万元 | C57: 110.6807 | D57: 142.4882 | E57: 182.4929 | F57: 225.0746 | G57: 248.5049 | H57: 261.1338 | I57: =H57 -> 261.1338 | J57: =I57 -> 261.1338 | K57: =J57 -> 261.1338 | L57: =K57 -> 261.1338 | M57: =L57 -> 261.1338 | N57: 预测期法定公积提取并入未分配利润列示
A58: 未分配利润 | B58: 百万元 | C58: 816.636 | D58: 1094.1181 | E58: 1465.1238 | F58: 1862.1697 | G58: 2043.9144 | H58: 2406.792 | I58: =H58+利润表!I27-融资!I32 -> 2935.3691 | J58: =I58+利润表!J27-融资!J32 -> 3550.6615 | K58: =J58+利润表!K27-融资!K32 -> 4350.1233 | L58: =K58+利润表!L27-融资!L32 -> 5248.21 | M58: =L58+利润表!M27-融资!M32 -> 6211.1492
A59: 归属于母公司股东权益 | B59: 百万元 | C59: =C53+C54-C55+C56+C57+C58 -> 2080.5909 | D59: =D53+D54-D55+D56+D57+D58 -> 2462.9031 | E59: =E53+E54-E55+E56+E57+E58 -> 3006.3725 | F59: =F53+F54-F55+F56+F57+F58 -> 3920.3498 | G59: =G53+G54-G55+G56+G57+G58 -> 4128.8312 | H59: =H53+H54-H55+H56+H57+H58 -> 4627.5227 | I59: =I53+I54-I55+I56+I57+I58 -> 5516.0998 | J59: =J53+J54-J55+J56+J57+J58 -> 6283.8922 | ... M59: =M53+M54-M55+M56+M57+M58 -> 9198.4799
A60: 少数股东权益 | B60: 百万元 | C60: 7.8242 | D60: 196.8032 | E60: 471.8202 | F60: 580.9015 | G60: 818.3565 | H60: 1161.885 | I60: =H60+利润表!I26+融资!I35-融资!I36 -> 1260.1379 | J60: =I60+利润表!J26+融资!J35-融资!J36 -> 1373.7873 | K60: =J60+利润表!K26+融资!K35-融资!K36 -> 1571.8719 | L60: =K60+利润表!L26+融资!L35-融资!L36 -> 1816.5855 | M60: =L60+利润表!M26+融资!M35-融资!M36 -> 2095.882
A61: 股东权益合计 | B61: 百万元 | C61: =C59+C60 -> 2088.4151 | D61: =D59+D60 -> 2659.7063 | E61: =E59+E60 -> 3478.1927 | F61: =F59+F60 -> 4501.2513 | G61: =G59+G60 -> 4947.1877 | H61: =H59+H60 -> 5789.4077 | I61: =I59+I60 -> 6776.2377 | J61: =J59+J60 -> 7657.6795 | ... M61: =M59+M60 -> 11294.362
A62: 负债和股东权益总计 | B62: 百万元 | C62: =C51+C61 -> 2506.3961 | D62: =D51+D61 -> 3252.4863 | E62: =E51+E61 -> 4324.1547 | F62: =F51+F61 -> 5915.0129 | G62: =G51+G61 -> 6090.9241 | H62: =H51+H61 -> 7363.1744 | I62: =I51+I61 -> 8528.5253 | J62: =J51+J61 -> 9668.1802 | ... M62: =M51+M61 -> 14308.037
A63: 平衡检查（资产−负债−权益，应为0） | B63: 百万元 | C63: =ROUND(C29-C62,3) -> 0 | D63: =ROUND(D29-D62,3) -> 0 | E63: =ROUND(E29-E62,3) -> 0 | F63: =ROUND(F29-F62,3) -> 0 | G63: =ROUND(G29-G62,3) -> 0 | H63: =ROUND(H29-H62,3) -> 0 | I63: =ROUND(I29-I62,3) -> 0 | J63: =ROUND(J29-J62,3) -> 0 | ... M63: =ROUND(M29-M62,3) -> 0
A64: 资产总计（报告值） | B64: 百万元 | C64: 2506.3963 | D64: 3252.4862 | E64: 4324.1547 | F64: 5915.013 | G64: 6090.9242 | H64: 7363.1743 | N64: 用于核对历史映射完整性
A65: 关键比率
A66: 每股净资产 | B66: 元 | C66: =C59/融资!C28 -> 6.1566873 | D66: =D59/融资!D28 -> 7.2879893 | E66: =E59/融资!E28 -> 5.9307816 | F66: =F59/融资!F28 -> 7.5417448 | G66: =G59/融资!G28 -> 7.9055492 | H66: =H59/融资!H28 -> 8.860403 | I66: =I59/融资!I28 -> 10.492267 | J66: =J59/融资!J28 -> 11.932702 | ... M66: =M59/融资!M28 -> 17.35117
A67: 资产负债率 | B67: % | C67: =C51/C29 -> 0.16676572 | D67: =D51/D29 -> 0.18225442 | E67: =E51/E29 -> 0.19563639 | F67: =F51/F29 -> 0.23901242 | G67: =G51/G29 -> 0.18777716 | H67: =H51/H29 -> 0.21373482 | I67: =I51/I29 -> 0.20546197 | J67: =J51/J29 -> 0.20795027 | ... M67: =M51/M29 -> 0.21062812
A68: 少数股东权益 / 股东权益合计 | B68: % | C68: =C60/C61 -> 0.0037464774 | D68: =D60/D61 -> 0.073994335 | E68: =E60/E61 -> 0.13565097 | F68: =F60/F61 -> 0.12905334 | G68: =G60/G61 -> 0.16541853 | H68: =H60/H61 -> 0.20069151 | I68: =I60/I61 -> 0.18596424 | J68: =J60/J61 -> 0.17939995 | ... M68: =M60/M61 -> 0.18556887

Sheet 现金流量表
A1: 现金流量表（百万元）
A2: 预测期采用间接法；利息支出保留在经营活动。历史“其他”项为报告值与列示项目的差额。
A4: 百万元 | B4: 单位 | C4: 2020A | D4: 2021A | E4: 2022A | F4: 2023A | G4: 2024A | H4: 2025A | I4: 2026E | J4: 2027E | K4: 2028E | L4: 2029E | M4: 2030E | N4: 说明 / 来源
A5: 经营活动
A6: 净利润 | B6: 百万元 | C6: 239.4519 | D6: 375.794 | E6: 512.7721 | F6: 574.4149 | G6: 326.2727 | H6: 426.3967 | I6: =利润表!I25 -> 664.17604 | J6: =利润表!J25 -> 874.88488 | K6: =利润表!K25 -> 1177.8182 | L6: =利润表!L25 -> 1375.0417 | M6: =利润表!M25 -> 1511.5079
A7: 折旧与摊销 | B7: 百万元 | C7: =资本开支!C49 -> 61.3248 | D7: =资本开支!D49 -> 85.1173 | E7: =资本开支!E49 -> 115.0255 | F7: =资本开支!F49 -> 167.5612 | G7: =资本开支!G49 -> 206.9893 | H7: =资本开支!H49 -> 248.3083 | I7: =资本开支!I49 -> 300.52316 | J7: =资本开支!J49 -> 364.10647 | ... M7: =资本开支!M49 -> 588.30747
A8: 股份支付（非现金） | B8: 百万元 | I8: =融资!I26 -> 66 | J8: =融资!J26 -> 112 | K8: =融资!K26 -> 56 | L8: =融资!L26 -> 26 | M8: =融资!M26 -> 10 | N8: 历史并入“其他”
A9: 资产减值准备 | B9: 百万元 | C9: -1.3961 | D9: 2.87 | E9: 12.6519 | F9: 20.6177 | G9: 28.4548 | H9: 52.9308 | I9: 0 | J9: 0 | K9: 0 | L9: 0 | M9: 0 | N9: 预测期减值视同营运资本损耗，不加回
A10: 营运资本变动 | B10: 百万元 | C10: -119.25 | D10: -169.37 | E10: -218.32 | F10: -538.32 | G10: -250.74 | H10: -433.06 | I10: =-营运资本!I39 -> -433.96656 | J10: =-营运资本!J39 -> -443.65346 | K10: =-营运资本!K39 -> -507.06926 | L10: =-营运资本!L39 -> -381.81447 | M10: =-营运资本!M39 -> -325.81352
A11: 其他 | B11: 百万元 | C11: =C12-C6-C7-C9-C10 -> 8.8003 | D11: =D12-D6-D7-D9-D10 -> -0.3036 | E11: =E12-E6-E7-E9-E10 -> -14.6905 | F11: =F12-F6-F7-F9-F10 -> 42.3019 | G11: =G12-G6-G7-G9-G10 -> -46.1953 | H11: =H12-H6-H7-H9-H10 -> -32.71 | I11: 0 | J11: 0 | K11: 0 | L11: 0 | M11: 0
A12: 经营活动现金流量净额 | B12: 百万元 | C12: 188.9309 | D12: 294.1077 | E12: 407.439 | F12: 266.5757 | G12: 264.7815 | H12: 261.8658 | I12: =I6+I7+I8+I9+I10+I11 -> 596.73264 | J12: =J6+J7+J8+J9+J10+J11 -> 907.33789 | K12: =K6+K7+K8+K9+K10+K11 -> 1170.3553 | L12: =L6+L7+L8+L9+L10+L11 -> 1539.0897 | M12: =M6+M7+M8+M9+M10+M11 -> 1784.0019
A13: 投资活动
A14: 购建固定资产、无形资产和其他长期资产 | B14: 百万元 | C14: -203.6003 | D14: -318.8237 | E14: -572.6832 | F14: -544.5963 | G14: -369.8711 | H14: -558.9568 | I14: =-资本开支!I17 -> -1015.5302 | J14: =-资本开支!J17 -> -973.71825 | K14: =-资本开支!K17 -> -794.29842 | L14: =-资本开支!L17 -> -701.9115 | M14: =-资本开支!M17 -> -763.95703
A15: 金融资产净投资（理财/大额存单） | B15: 百万元 | C15: -445.54 | D15: 178.71 | E15: 85.95 | F15: -668.39 | G15: 86.67 | H15: -89.12 | I15: =-(融资!I18+融资!I19-融资!H18-融资!H19) -> 282.2799 | J15: =-(融资!J18+融资!J19-融资!I18-融资!I19) -> 0 | K15: =-(融资!K18+融资!K19-融资!J18-融资!J19) -> 0 | L15: =-(融资!L18+融资!L19-融资!K18-融资!K19) -> 0 | M15: =-(融资!M18+融资!M19-融资!L18-融资!L19) -> 0
A16: 其他（处置、收购子公司、投资收益等） | B16: 百万元 | C16: =C17-C14-C15 -> 0.333 | D16: =D17-D14-D15 -> -5.0345 | E16: =E17-E14-E15 -> 0.8332 | F16: =F17-F14-F15 -> 0.7342 | G16: =G17-G14-G15 -> 0.6045 | H16: =H17-H14-H15 -> 39.9834 | I16: =-(资产负债表!I17-资产负债表!H17) -> 0 | J16: =-(资产负债表!J17-资产负债表!I17) -> 0 | K16: =-(资产负债表!K17-资产负债表!J17) -> 0 | L16: =-(资产负债表!L17-资产负债表!K17) -> 0 | M16: =-(资产负债表!M17-资产负债表!L17) -> 0
A17: 投资活动现金流量净额 | B17: 百万元 | C17: -648.8073 | D17: -145.1482 | E17: -485.9 | F17: -1212.2521 | G17: -282.5966 | H17: -608.0934 | I17: =I14+I15+I16 -> -733.25031 | J17: =J14+J15+J16 -> -973.71825 | K17: =K14+K15+K16 -> -794.29842 | L17: =L14+L15+L16 -> -701.9115 | M17: =M14+M15+M16 -> -763.95703
A18: 筹资活动
A19: 吸收投资（含子公司少数股东投入） | B19: 百万元 | C19: 0 | D19: 170.3155 | E19: 296.7675 | F19: 479.2113 | G19: 309.7122 | H19: 558.3268 | I19: =融资!I25+融资!I35 -> 354 | J19: =融资!J25+融资!J35 -> 40.5 | K19: =融资!K25+融资!K35 -> 40.5 | L19: =融资!L25+融资!L35 -> 60.8 | M19: =融资!M25+融资!M35 -> 60.8
A20: 借款净增加 | B20: 百万元 | C20: 0 | D20: -5 | E20: 37.73 | F20: 251.25 | G20: 39.25 | H20: 16.71 | I20: =融资!I9-融资!H9 -> -48.2097 | J20: =融资!J9-融资!I9 -> -51 | K20: =融资!K9-融资!J9 -> 0 | L20: =融资!L9-融资!K9 -> 0 | M20: =融资!M9-融资!L9 -> 0
A21: 循环贷款提取（偿还） | B21: 百万元 | I21: =融资!I12-融资!H12 -> 0 | J21: =融资!J12-融资!I12 -> 0 | K21: =融资!K12-融资!J12 -> 0 | L21: =融资!L12-融资!K12 -> 0 | M21: =融资!M12-融资!L12 -> 0
A22: 分配股利及偿付利息 | B22: 百万元 | C22: -61.6483 | D22: -61.3299 | E22: -84.1424 | F22: -102.9446 | G22: -132.9703 | H22: -86.2034 | I22: =-融资!I32-融资!I36 -> -97.346036 | J22: =-融资!J32-融资!J36 -> -145.94309 | K22: =-融资!K32-融资!K36 -> -180.27181 | L22: =-融资!L32-融资!L36 -> -232.24139 | M22: =-融资!M32-融资!M36 -> -269.27219 | N22: 预测期利息在经营活动列示
A23: 其他（回购、租赁等） | B23: 百万元 | C23: =C24-C19-C20-C22 -> -1.2808 | D23: =D24-D19-D20-D22 -> -0.4794 | E23: =E24-E19-E20-E22 -> 5.4398 | F23: =F24-F19-F20-F22 -> -6.3328 | G23: =G24-G19-G20-G22 -> -54.6298 | H23: =H24-H19-H20-H22 -> -32.6184 | I23: =-融资!I27 -> 0 | J23: =-融资!J27 -> 0 | K23: =-融资!K27 -> 0 | L23: =-融资!L27 -> 0 | M23: =-融资!M27 -> 0
A24: 筹资活动现金流量净额 | B24: 百万元 | C24: -62.9291 | D24: 103.5062 | E24: 255.7949 | F24: 621.1839 | G24: 161.3621 | H24: 456.215 | I24: =I19+I20+I21+I22+I23 -> 208.44426 | J24: =J19+J20+J21+J22+J23 -> -156.44309 | K24: =K19+K20+K21+K22+K23 -> -139.77181 | L24: =L19+L20+L21+L22+L23 -> -171.44139 | M24: =M19+M20+M21+M22+M23 -> -208.47219
A25: 汇率变动影响 | B25: 百万元 | C25: -2.5042 | D25: -1.0604 | E25: 6.6371 | F25: 3.5088 | G25: 3.6869 | H25: -2.2846 | I25: 0 | J25: 0 | K25: 0 | L25: 0 | M25: 0
A26: 现金及现金等价物净增加额 | B26: 百万元 | C26: -525.3098 | D26: 251.4053 | E26: 183.971 | F26: -320.9838 | G26: 147.2339 | H26: 107.7029 | I26: =I12+I17+I24+I25 -> 71.926599 | J26: =J12+J17+J24+J25 -> -222.82344 | K26: =K12+K17+K24+K25 -> 236.28507 | L26: =L12+L17+L24+L25 -> 665.73682 | M26: =M12+M17+M24+M25 -> 811.57263
A27: 其中：循环贷款提取前现金净增加额 | B27: 百万元 | I27: =I12+I17+I19+I20+I22+I23+I25 -> 71.926599 | J27: =J12+J17+J19+J20+J22+J23+J25 -> -222.82344 | K27: =K12+K17+K19+K20+K22+K23+K25 -> 236.28507 | L27: =L12+L17+L19+L20+L22+L23+L25 -> 665.73682 | M27: =M12+M17+M19+M20+M22+M23+M25 -> 811.57263 | N27: 用于计算循环贷款（逐项加总、不含循环贷款本身，避免循环引用）
A28: 自由现金流
A29: 经营现金流 − 资本开支 | B29: 百万元 | C29: =C12+C14 -> -14.6694 | D29: =D12+D14 -> -24.716 | E29: =E12+E14 -> -165.2442 | F29: =F12+F14 -> -278.0206 | G29: =G12+G14 -> -105.0896 | H29: =H12+H14 -> -297.091 | I29: =I12+I14 -> -418.79757 | J29: =J12+J14 -> -66.380355 | ... M29: =M12+M14 -> 1020.0448
A30: FCFF = EBIT×(1−t) + D&A − 资本开支 − 营运资本增加 | B30: 百万元 | D30: =利润表!D32*(1-费用税率!D23)+D7+D14-营运资本!D39 -> 102.84638 | E30: =利润表!E32*(1-费用税率!E23)+E7+E14-营运资本!E39 -> -261.34917 | F30: =利润表!F32*(1-费用税率!F23)+F7+F14-营运资本!F39 -> -184.31086 | G30: =利润表!G32*(1-费用税率!G23)+G7+G14-营运资本!G39 -> -56.497175 | H30: =利润表!H32*(1-费用税率!H23)+H7+H14-营运资本!H39 -> -28.987405 | I30: =利润表!I32*(1-费用税率!I23)+I7+I14-营运资本!I39 -> -496.37709 | J30: =利润表!J32*(1-费用税率!J23)+J7+J14-营运资本!J39 -> -193.02766 | K30: =利润表!K32*(1-费用税率!K23)+K7+K14-营运资本!K39 -> 306.87826 | ... M30: =利润表!M32*(1-费用税率!M23)+M7+M14-营运资本!M39 -> 989.06814 | N30: 股份支付视同现金成本，不加回（历史与预测、DCF口径一致）
A31: 每股经营现金流 | B31: 元 | C31: =C12/融资!C28 -> 0.5590664 | D31: =D12/融资!D28 -> 0.87029561 | E31: =E12/融资!E28 -> 0.8037699 | F31: =F12/融资!F28 -> 0.51282309 | G31: =G12/融资!G28 -> 0.50698202 | H31: =H12/融资!H28 -> 0.50139928 | I31: =I12/融资!I28 -> 1.1350553 | J31: =J12/融资!J28 -> 1.7229756 | ... M31: =M12/融资!M28 -> 3.3651777

Sheet 季度
A1: 季度跟踪：单季利润表（百万元）
A2: 2024Q1–2026Q2 为单季报告值（Wind 单季口径）；2026Q3E/Q4E = 年度预测 − 上半年实际：收入及费用按Q3占比拆分，减值集中于Q4，利润项由各行重算。
A4: Q3占下半年收入及各费用项比例（假设） | B4: % | C4: 0.45 | D4: 2023-2025年Q3占下半年收入44%/48%/43%，取45%
A5: Q3占下半年减值损失比例（假设） | B5: % | C5: 0 | D5: 减值损失集中在四季度：2024/2025年Q3资产减值-0.7/-0.0百万元，Q4为-16.7/-28.0百万元
A6: 百万元 | B6: 单位 | C6: 2024Q1 | D6: 2024Q2 | E6: 2024Q3 | F6: 2024Q4 | G6: 2025Q1 | H6: 2025Q2 | I6: 2025Q3 | J6: 2025Q4 | K6: 2026Q1 | L6: 2026Q2 | M6: 2026Q3E | N6: 2026Q4E | O6: 2026H1A | P6: 2026E(年)
A7: 营业收入 | B7: 百万元 | C7: 410.25 | D7: 504.66 | E7: 398.65 | F7: 428.25 | G7: 406.26 | H7: 501.58 | I7: 473.68 | J7: 634.82 | K7: 621.73 | L7: 686.1 | M7: =(P7-O7)*$C$4 -> 644.92965 | N7: =P7-O7-M7 -> 788.24735 | O7: =K7+L7 -> 1307.83 | P7: =利润表!I5 -> 2741.007
A8: 营业成本 | B8: 百万元 | C8: 247.64 | D8: 275.19 | E8: 234.28 | F8: 250.15 | G8: 203.31 | H8: 257.69 | I8: 244.1 | J8: 355.97 | K8: 306.26 | L8: 346.17 | M8: =(P8-O8)*$C$4 -> 320.24675 | N8: =P8-O8-M8 -> 391.4127 | O8: =K8+L8 -> 652.43 | P8: =利润表!I7 -> 1364.0894
A9: 税金及附加 | B9: 百万元 | C9: 3.02 | D9: 5.17 | E9: 3.95 | F9: 5.57 | G9: 4.28 | H9: 8.46 | I9: 4.75 | J9: 7.27 | K9: 8.66 | L9: 8.33 | M9: =(P9-O9)*$C$4 -> 8.3893909 | N9: =P9-O9-M9 -> 10.2537 | O9: =K9+L9 -> 16.99 | P9: =利润表!I10 -> 35.633091
A10: 销售费用 | B10: 百万元 | C10: 5.16 | D10: 9.22 | E10: 6.92 | F10: 3.63 | G10: 4.79 | H10: 6.92 | I10: 7.22 | J10: 12.56 | K10: 7.76 | L10: 9.04 | M10: =(P10-O10)*$C$4 -> 8.474891 | N10: =P10-O10-M10 -> 10.3582 | O10: =K10+L10 -> 16.8 | P10: =利润表!I11 -> 35.633091
A11: 管理费用 | B11: 百万元 | C11: 34.43 | D11: 42.63 | E11: 36.51 | F11: 33.29 | G11: 33.41 | H11: 37.71 | I11: 44.94 | J11: 63.16 | K11: 51.86 | L11: 55.48 | M11: =(P11-O11)*$C$4 -> 57.871095 | N11: =P11-O11-M11 -> 70.731339 | O11: =K11+L11 -> 107.34 | P11: =利润表!I12 -> 235.94243
A12: 研发费用 | B12: 百万元 | C12: 59.45 | D12: 71.23 | E12: 66.57 | F12: 52.69 | G12: 61.36 | H12: 60.69 | I12: 75.78 | J12: 84.45 | K12: 76.7 | L12: 83.93 | M12: =(P12-O12)*$C$4 -> 83.131597 | N12: =P12-O12-M12 -> 101.60529 | O12: =K12+L12 -> 160.63 | P12: =利润表!I13 -> 345.36688
A13: 财务费用 | B13: 百万元 | C13: 0.14 | D13: -0.26 | E13: 1.9 | F13: -1.88 | G13: -1.33 | H13: 0.41 | I13: 2 | J13: 5.16 | K13: 5.73 | L13: 7.33 | M13: =(P13-O13)*$C$4 -> -0.47225149 | N13: =P13-O13-M13 -> -0.57719626 | O13: =K13+L13 -> 13.06 | P13: =利润表!I14 -> 12.010552
A14: 其他收益 | B14: 百万元 | C14: 31.16 | D14: 8.16 | E14: 8.81 | F14: 9.96 | G14: 13.14 | H14: 8.04 | I14: 9.36 | J14: 22.65 | K14: 13.17 | L14: 7.5 | M14: =(P14-O14)*$C$4 -> 12.900657 | N14: =P14-O14-M14 -> 15.767469 | O14: =K14+L14 -> 20.67 | P14: =利润表!I15 -> 49.338126
A15: 投资净收益 | B15: 百万元 | C15: 2.88 | D15: 1.67 | E15: 3.11 | F15: 4.32 | G15: 9.84 | H15: 4.81 | I15: -10.86 | J15: -0.06 | K15: 1.62 | L15: 0.66 | M15: =(P15-O15)*$C$4 -> 7.0042855 | N15: =P15-O15-M15 -> 8.5607934 | O15: =K15+L15 -> 2.28 | P15: =利润表!I16 -> 17.845079
A16: 公允价值变动净收益 | B16: 百万元 | C16: 3.31 | D16: 6.44 | E16: 4.11 | F16: 2.66 | G16: -4.07 | H16: 1.13 | I16: 16.34 | J16: 6.45 | K16: 2.96 | L16: 4.32 | M16: =(P16-O16)*$C$4 -> 0 | N16: =P16-O16-M16 -> 0 | O16: =K16+L16 -> 7.28 | P16: =利润表!I17 -> 7.28
A17: 信用减值损失 | B17: 百万元 | C17: -4.77 | D17: -7.56 | E17: 4.04 | F17: -0.09 | G17: -11.32 | H17: -7.91 | I17: 2.07 | J17: 0.04 | K17: -10.27 | L17: 2.09 | M17: =(P17-O17)*$C$5 -> 0 | N17: =P17-O17-M17 -> -8.266042 | O17: =K17+L17 -> -8.18 | P17: =利润表!I18 -> -16.446042
A18: 资产减值损失 | B18: 百万元 | C18: 0.64 | D18: -3.29 | E18: -0.72 | F18: -16.69 | G18: -0.24 | H18: -7.59 | I18: -0.02 | J18: -27.96 | K18: 0 | L18: -0.33 | M18: =(P18-O18)*$C$5 -> 0 | N18: =P18-O18-M18 -> -21.598056 | O18: =K18+L18 -> -0.33 | P18: =利润表!I19 -> -21.928056
A19: 资产处置收益 | B19: 百万元 | C19: -0.45 | D19: -0.74 | E19: -0.17 | F19: -0.71 | G19: 0 | H19: -0.06 | I19: 0.81 | J19: 0.01 | K19: -0.07 | L19: 3.87 | M19: =(P19-O19)*$C$4 -> 0 | N19: =P19-O19-M19 -> 0 | O19: =K19+L19 -> 3.8 | P19: =利润表!I20 -> 3.8
A20: 营业利润 | B20: 百万元 | C20: 93.18 | D20: 106.17 | E20: 67.69 | F20: 84.23 | G20: 107.8 | H20: 128.12 | I20: 112.59 | J20: 107.38 | K20: 172.17 | L20: 193.92 | M20: =M7-M8-M9-M10-M11-M12-M13+M14+M15+M16+M17+M18+M19 -> 187.19312 | N20: =P20-O20-M20 -> 198.93749 | O20: =K20+L20 -> 366.09 | P20: =利润表!I21 -> 752.22061
A21: 利润总额 | B21: 百万元 | C21: 93.87 | D21: 106.64 | E21: 64.82 | F21: 79.02 | G21: 108.6 | H21: 128.03 | I21: 110.93 | J21: 118.97 | K21: 168.96 | L21: 194.16 | M21: =M20+((P21-O21)-(P20-O20))*$C$4 -> 188.52962 | N21: =P21-O21-M21 -> 200.57099 | O21: =K21+L21 -> 363.12 | P21: =利润表!I23 -> 752.22061
A22: 所得税 | B22: 百万元 | C22: 15.15 | D22: 3.43 | E22: 3.15 | F22: -3.66 | G22: 12.59 | H22: 15.37 | I22: 9.23 | J22: 2.95 | K22: 20.66 | L22: 34.06 | M22: =M21*(P22-O22)/(P21-O21) -> 16.146639 | N22: =P22-O22-M22 -> 17.177924 | O22: =K22+L22 -> 54.72 | P22: =利润表!I24 -> 88.044563
A23: 净利润 | B23: 百万元 | C23: 78.72 | D23: 103.21 | E23: 61.67 | F23: 82.68 | G23: 96.01 | H23: 112.66 | I23: 101.7 | J23: 116.02 | K23: 148.3 | L23: 160.1 | M23: =M21-M22 -> 172.38298 | N23: =P23-O23-M23 -> 183.39307 | O23: =K23+L23 -> 308.4 | P23: =利润表!I25 -> 664.17604
A24: 归母净利润 | B24: 百万元 | C24: 77.43 | D24: 94.82 | E24: 62.4 | F24: 79.57 | G24: 105.09 | H24: 116.63 | I24: 112.01 | J24: 109.46 | K24: 143.72 | L24: 151.06 | M24: =M23*(P24-O24)/(P23-O23) -> 156.57146 | N24: =P24-O24-M24 -> 166.57166 | O24: =K24+L24 -> 294.78 | P24: =利润表!I27 -> 617.92312
A25: 少数股东损益 | B25: 百万元 | C25: =C23-C24 -> 1.29 | D25: =D23-D24 -> 8.39 | E25: =E23-E24 -> -0.73 | F25: =F23-F24 -> 3.11 | G25: =G23-G24 -> -9.08 | H25: =H23-H24 -> -3.97 | I25: =I23-I24 -> -10.31 | J25: =J23-J24 -> 6.56 | ... P25: =P23-P24 -> 46.252923
A26: 毛利率 | B26: % | C26: =1-C8/C7 -> 0.39636807 | D26: =1-D8/D7 -> 0.45470218 | E26: =1-E8/E7 -> 0.41231657 | F26: =1-F8/F7 -> 0.41587858 | G26: =1-G8/G7 -> 0.49955693 | H26: =1-H8/H7 -> 0.48624347 | I26: =1-I8/I7 -> 0.4846732 | J26: =1-J8/J7 -> 0.43925837 | ... P26: =1-P8/P7 -> 0.50234003
A27: 期间费用率（销售+管理+研发） | B27: % | C27: =(C10+C11+C12)/C7 -> 0.24141377 | D27: =(D10+D11+D12)/D7 -> 0.24388697 | E27: =(E10+E11+E12)/E7 -> 0.27593127 | F27: =(F10+F11+F12)/F7 -> 0.20924694 | G27: =(G10+G11+G12)/G7 -> 0.24506474 | H27: =(H10+H11+H12)/H7 -> 0.20997647 | I27: =(I10+I11+I12)/I7 -> 0.27009796 | J27: =(J10+J11+J12)/J7 -> 0.25230774 | ... P27: =(P10+P11+P12)/P7 -> 0.22507874
A28: 研发费用率 | B28: % | C28: =C12/C7 -> 0.14491164 | D28: =D12/D7 -> 0.14114453 | E28: =E12/E7 -> 0.16698859 | F28: =F12/F7 -> 0.12303561 | G28: =G12/G7 -> 0.15103628 | H28: =H12/H7 -> 0.12099765 | I28: =I12/I7 -> 0.15998142 | J28: =J12/J7 -> 0.13302984 | ... P28: =P12/P7 -> 0.126
A29: 归母净利率 | B29: % | C29: =C24/C7 -> 0.18873857 | D29: =D24/D7 -> 0.18788888 | E29: =E24/E7 -> 0.15652828 | F29: =F24/F7 -> 0.18580269 | G29: =G24/G7 -> 0.25867671 | H29: =H24/H7 -> 0.23252522 | I29: =I24/I7 -> 0.23646766 | J29: =J24/J7 -> 0.17242683 | ... P29: =P24/P7 -> 0.22543653
A30: 收入同比 | B30: % | G30: =G7/C7-1 -> -0.009725777 | H30: =H7/D7-1 -> -0.0061031189 | I30: =I7/E7-1 -> 0.18821021 | J30: =J7/F7-1 -> 0.48235844 | K30: =K7/G7-1 -> 0.53037464 | L30: =L7/H7-1 -> 0.36787751 | M30: =M7/I7-1 -> 0.36153025 | N30: =N7/J7-1 -> 0.24168638
A31: 归母净利润同比 | B31: % | G31: =G24/C24-1 -> 0.35722588 | H31: =H24/D24-1 -> 0.23001476 | I31: =I24/E24-1 -> 0.79503205 | J31: =J24/F24-1 -> 0.37564409 | K31: =K24/G24-1 -> 0.36758969 | L31: =L24/H24-1 -> 0.29520707 | M31: =M24/I24-1 -> 0.39783463 | N31: =N24/J24-1 -> 0.5217583
A32: 收入环比 | B32: % | D32: =D7/C7-1 -> 0.23012797 | E32: =E7/D7-1 -> -0.21006222 | F32: =F7/E7-1 -> 0.074250596 | G32: =G7/F7-1 -> -0.051348511 | H32: =H7/G7-1 -> 0.23462807 | I32: =I7/H7-1 -> -0.055624227 | J32: =J7/I7-1 -> 0.34018747 | K32: =K7/J7-1 -> -0.020620018 | ... N32: =N7/M7-1 -> 0.22222222
A33: 经营活动现金流量净额 | B33: 百万元 | C33: -116.38 | D33: 122.25 | E33: 130.99 | F33: 127.93 | G33: 158.23 | H33: 32.96 | I33: 17.92 | J33: 52.75 | K33: 20.71 | L33: 115.54
A34: 购建长期资产支付的现金 | B34: 百万元 | C34: 74.84 | D34: 70.16 | E34: 103.1 | F34: 121.76 | G34: 107.29 | H34: 123.08 | I34: 197.75 | J34: 130.83 | K34: 195.28 | L34: 222.33
A36: 注：2026Q3E/Q4E为年度预测减上半年实际后的隐含值，非独立季度预测。

Sheet DCF
A1: DCF 估值（FCFF：显式期 + 十年衰减期 + 永续）
A2: 显式期 2026E–2030E 来自三表；衰减期 2031E–2040E 收入增速由“衰减期起始增速”线性降至永续增速、EBIT率线性收敛、再投资率由2030E水平过渡至稳态（g/RONIC）；2026年计入下半年FCFF，与6月30日净现金衔接。
A4: 一、资本成本与关键参数
A5: 当前股价 | B5: 元 | C5: 97.43 | D5: 2026-09-30收盘价（节前最后交易日；搜狐财经报道），总市值约512亿元
A6: 总股本（2026-06-30） | B6: 百万股 | C6: 525.7271 | D6: 来源：2026年半年报
A7: 总市值 | B7: 百万元 | C7: =C5*C6 -> 51221.591
A8: 估值基准日 | C8: =DATE(2026,10,6) -> 46301
A9: 无风险利率（10年期国债） | B9: % | C9: 0.0175 | D9: 10年期国债约1.71%（2026-08-12，tradingeconomics），取1.75%
A10: 股权风险溢价 | B10: % | C10: 0.065 | D10: A股常用股权风险溢价6-7%
A11: Beta | B11: x | C11: 1.2 | D11: 成长型新材料公司，取1.2（需以Wind近两年周Beta复核）
A12: 股权成本 Ke = Rf + β×ERP | B12: % | C12: =C9+C11*C10 -> 0.0955
A13: 税前债务成本 | B13: % | C13: 0.03
A14: 税率（高新技术企业） | B14: % | C14: 0.15
A15: 目标债务占比 D/(D+E) | B15: % | C15: 0.05 | D15: 公司净现金，按低杠杆处理
A16: WACC | B16: % | C16: =C12*(1-C15)+C13*(1-C14)*C15 -> 0.092
A17: 衰减期起始增速（2031E） | B17: % | C17: =MAX(利润表!M6,C18) -> 0.10865911 | D17: ＝2030E收入增速（随情景切换），避免衰减期增速跳升；之后十年线性衰减至永续增速
A18: 永续增长率 | B18: % | C18: 0.025
A19: 稳态新增投资回报率 RONIC | B19: % | C19: 0.15 | D19: 稳态再投资率 = 增速 / RONIC；衰减期再投资率由2030E实际水平线性过渡至稳态
A20: 永续期 EBIT 率 | B20: % | C20: 0.27 | D20: 永续期EBIT率27%：2020-2025年均值约27.6%，低于2028-2030E约30%，反映Q布价格下行与竞争
A21: 2026年剩余期（年） | B21: 年 | C21: =(DATE(2026,12,31)-C8)/365 -> 0.23561644
A22: 2026年下半年FCFF折现期（年中点9月30日，相对基准日） | B22: 年 | C22: =(DATE(2026,9,30)-C8)/365 -> -0.016438356 | D22: 负值表示略早于基准日，按WACC复利至基准日
A23: 2026H1已实现FCFF | B23: 百万元 | C23: -281.35 | D23: 2026H1经营现金流1.36亿元−购建长期资产支付4.18亿元（利息支出很小，未调整）；该部分已体现在6月30日净现金中
A25: 二、自由现金流预测
A26: 百万元 | B26: 单位 | C26: 2026E | D26: 2027E | E26: 2028E | F26: 2029E | G26: 2030E | H26: 2031E | I26: 2032E | J26: 2033E | K26: 2034E | L26: 2035E | M26: 2036E | N26: 2037E | O26: 2038E | P26: 2039E | Q26: 2040E
A27: 阶段 | C27: 显式 | D27: 显式 | E27: 显式 | F27: 显式 | G27: 显式 | H27: 衰减 | I27: 衰减 | J27: 衰减 | K27: 衰减 | L27: 衰减 | M27: 衰减 | N27: 衰减 | O27: 衰减 | P27: 衰减 | Q27: 衰减
A28: 营业收入 | B28: 百万元 | C28: =利润表!I5 -> 2741.007 | D28: =利润表!J5 -> 3510.4561 | E28: =利润表!K5 -> 4419.9684 | F28: =利润表!L5 -> 5143.525 | G28: =利润表!M5 -> 5702.4159 | H28: =G28*(1+H29) -> 6322.0354 | I28: =H28*(1+I29) -> 6950.2159 | J28: =I28*(1+J29) -> 7576.2094 | K28: =J28*(1+K29) -> 8188.1606 | L28: =K28*(1+L29) -> 8773.4281 | M28: =L28*(1+M29) -> 9318.9759 | N28: =M28*(1+N29) -> 9811.8227 | O28: =N28*(1+O29) -> 10239.529 | ... Q28: =P28*(1+Q29) -> 10855.466
A29: 收入增速 | B29: % | C29: =利润表!I6 -> 0.35939122 | D29: =利润表!J6 -> 0.28071769 | E29: =利润表!K6 -> 0.25908663 | F29: =利润表!L6 -> 0.16370177 | G29: =利润表!M6 -> 0.10865911 | H29: =$C$17+($C$18-$C$17)*0/9 -> 0.10865911 | I29: =$C$17+($C$18-$C$17)*1/9 -> 0.099363657 | J29: =$C$17+($C$18-$C$17)*2/9 -> 0.0900682 | K29: =$C$17+($C$18-$C$17)*3/9 -> 0.080772743 | L29: =$C$17+($C$18-$C$17)*4/9 -> 0.071477286 | M29: =$C$17+($C$18-$C$17)*5/9 -> 0.062181829 | N29: =$C$17+($C$18-$C$17)*6/9 -> 0.052886371 | O29: =$C$17+($C$18-$C$17)*7/9 -> 0.043590914 | P29: =$C$17+($C$18-$C$17)*8/9 -> 0.034295457 | Q29: =$C$17+($C$18-$C$17)*9/9 -> 0.025
A30: EBIT 率 | B30: % | C30: =C31/C28 -> 0.26964764 | D30: =D31/D28 -> 0.27920499 | E30: =E31/E28 -> 0.30187338 | F30: =F31/F28 -> 0.30346308 | G30: =G31/G28 -> 0.30053319 | H30: =$G$30+($C$20-$G$30)*1/10 -> 0.29747987 | I30: =$G$30+($C$20-$G$30)*2/10 -> 0.29442656 | J30: =$G$30+($C$20-$G$30)*3/10 -> 0.29137324 | K30: =$G$30+($C$20-$G$30)*4/10 -> 0.28831992 | L30: =$G$30+($C$20-$G$30)*5/10 -> 0.2852666 | M30: =$G$30+($C$20-$G$30)*6/10 -> 0.28221328 | N30: =$G$30+($C$20-$G$30)*7/10 -> 0.27915996 | O30: =$G$30+($C$20-$G$30)*8/10 -> 0.27610664 | P30: =$G$30+($C$20-$G$30)*9/10 -> 0.27305332 | Q30: =$G$30+($C$20-$G$30)*10/10 -> 0.27
A31: EBIT | B31: 百万元 | C31: =利润表!I32 -> 739.10608 | D31: =利润表!J32 -> 980.13688 | E31: =利润表!K32 -> 1334.2708 | F31: =利润表!L32 -> 1560.87 | G31: =利润表!M32 -> 1713.7653 | H31: =H28*H30 -> 1880.6783 | I31: =I28*I30 -> 2046.3281 | J31: =J28*J30 -> 2207.5046 | K31: =K28*K30 -> 2360.8098 | L31: =L28*L30 -> 2502.766 | M31: =M28*M30 -> 2629.9387 | N31: =N28*N30 -> 2739.068 | O31: =O28*O30 -> 2827.2019 | ... Q31: =Q28*Q30 -> 2930.9758
A32: 税率 | B32: % | C32: =费用税率!I23 -> 0.1170462 | D32: =费用税率!J23 -> 0.12232914 | E32: =费用税率!K23 -> 0.12713403 | F32: =费用税率!L23 -> 0.1288001 | G32: =费用税率!M23 -> 0.1302594 | H32: =$G$32 -> 0.1302594 | I32: =$G$32 -> 0.1302594 | J32: =$G$32 -> 0.1302594 | K32: =$G$32 -> 0.1302594 | L32: =$G$32 -> 0.1302594 | M32: =$G$32 -> 0.1302594 | N32: =$G$32 -> 0.1302594 | O32: =$G$32 -> 0.1302594 | ... Q32: =$G$32 -> 0.1302594
A33: NOPAT | B33: 百万元 | C33: =C31*(1-C32) -> 652.59652 | D33: =D31*(1-D32) -> 860.23758 | E33: =E31*(1-E32) -> 1164.6396 | F33: =F31*(1-F32) -> 1359.8297 | G33: =G31*(1-G32) -> 1490.5312 | H33: =H31*(1-H32) -> 1635.7023 | I33: =I31*(1-I32) -> 1779.7747 | J33: =J31*(1-J32) -> 1919.9564 | ... Q33: =Q31*(1-Q32) -> 2549.1886
A34: 折旧摊销 | B34: 百万元 | C34: =资本开支!I49 -> 300.52316 | D34: =资本开支!J49 -> 364.10647 | E34: =资本开支!K49 -> 443.60637 | F34: =资本开支!L49 -> 519.86245 | G34: =资本开支!M49 -> 588.30747
A35: 资本开支（负值） | B35: 百万元 | C35: =-资本开支!I17 -> -1015.5302 | D35: =-资本开支!J17 -> -973.71825 | E35: =-资本开支!K17 -> -794.29842 | F35: =-资本开支!L17 -> -701.9115 | G35: =-资本开支!M17 -> -763.95703
A36: 营运资本增加（负值） | B36: 百万元 | C36: =-营运资本!I39 -> -433.96656 | D36: =-营运资本!J39 -> -443.65346 | E36: =-营运资本!K39 -> -507.06926 | F36: =-营运资本!L39 -> -381.81447 | G36: =-营运资本!M39 -> -325.81352
A37: 再投资 = 资本开支 − 折旧摊销 + 营运资本增加 | B37: 百万元 | C37: =-C35-C36-C34 -> 1148.9736 | D37: =-D35-D36-D34 -> 1053.2652 | E37: =-E35-E36-E34 -> 857.76131 | F37: =-F35-F36-F34 -> 563.86352 | G37: =-G35-G36-G34 -> 501.46309 | H37: =H33*H38 -> 613.76231 | I37: =I33*I38 -> 714.8124 | J37: =J33*J38 -> 798.009 | K37: =K33*K38 -> 856.74323 | L37: =L33*L38 -> 884.79487 | M37: =M33*M38 -> 876.74749 | N37: =N33*N38 -> 828.39644 | O37: =O33*O38 -> 737.11751 | ... Q37: =Q33*Q38 -> 424.86477
A38: 再投资率（再投资 / NOPAT） | B38: % | C38: =C37/C33 -> 1.7606187 | D38: =D37/D33 -> 1.2243888 | E38: =E37/E33 -> 0.73650366 | F38: =F37/F33 -> 0.41465744 | G38: =G37/G33 -> 0.33643246 | H38: =$G$38+(H29/$C$19-$G$38)*1/10 -> 0.37522863 | I38: =$G$38+(I29/$C$19-$G$38)*2/10 -> 0.40163085 | J38: =$G$38+(J29/$C$19-$G$38)*3/10 -> 0.41563912 | K38: =$G$38+(K29/$C$19-$G$38)*4/10 -> 0.41725346 | L38: =$G$38+(L29/$C$19-$G$38)*5/10 -> 0.40647385 | M38: =$G$38+(M29/$C$19-$G$38)*6/10 -> 0.3833003 | N38: =$G$38+(N29/$C$19-$G$38)*7/10 -> 0.34773281 | O38: =$G$38+(O29/$C$19-$G$38)*8/10 -> 0.29977137 | P38: =$G$38+(P29/$C$19-$G$38)*9/10 -> 0.23941599 | Q38: =$G$38+(Q29/$C$19-$G$38)*10/10 -> 0.16666667
A39: 隐含新增投资回报率（增速 / 再投资率） | B39: % | H39: =H29/H38 -> 0.28958109 | I39: =I29/I38 -> 0.24740046 | J39: =J29/J38 -> 0.21669808 | K39: =K29/K38 -> 0.19358196 | L39: =L29/L38 -> 0.17584719 | M39: =M29/M38 -> 0.16222745 | N39: =N29/N38 -> 0.15208911 | O39: =O29/O38 -> 0.14541387 | ... Q39: =Q29/Q38 -> 0.15
A40: FCFF = NOPAT − 再投资 | B40: 百万元 | C40: =C33-C37 -> -496.37709 | D40: =D33-D37 -> -193.02766 | E40: =E33-E37 -> 306.87826 | F40: =F33-F37 -> 795.96622 | G40: =G33-G37 -> 989.06814 | H40: =H33-H37 -> 1021.94 | I40: =I33-I37 -> 1064.9623 | J40: =J33-J37 -> 1121.9474 | ... Q40: =Q33-Q37 -> 2124.3239
A41: 减：估值基准日前已实现（2026H1） | B41: 百万元 | C41: =-$C$23 -> 281.35
A42: 计入估值的FCFF | B42: 百万元 | C42: =C40+C41 -> -215.02709 | D42: =D40 -> -193.02766 | E42: =E40 -> 306.87826 | F42: =F40 -> 795.96622 | G42: =G40 -> 989.06814 | H42: =H40 -> 1021.94 | I42: =I40 -> 1064.9623 | J42: =J40 -> 1121.9474 | K42: =K40 -> 1196.5489 | ... Q42: =Q40 -> 2124.3239
A43: 折现期（年，年中法） | C43: =$C$22 -> -0.016438356 | D43: =$C$21+0+0.5 -> 0.73561644 | E43: =$C$21+1+0.5 -> 1.7356164 | F43: =$C$21+2+0.5 -> 2.7356164 | G43: =$C$21+3+0.5 -> 3.7356164 | H43: =$C$21+4+0.5 -> 4.7356164 | I43: =$C$21+5+0.5 -> 5.7356164 | J43: =$C$21+6+0.5 -> 6.7356164 | K43: =$C$21+7+0.5 -> 7.7356164 | L43: =$C$21+8+0.5 -> 8.7356164 | M43: =$C$21+9+0.5 -> 9.7356164 | N43: =$C$21+10+0.5 -> 10.735616 | O43: =$C$21+11+0.5 -> 11.735616 | P43: =$C$21+12+0.5 -> 12.735616 | Q43: =$C$21+13+0.5 -> 13.735616
A44: 折现因子 | C44: =1/(1+$C$16)^C43 -> 1.0014478 | D44: =1/(1+$C$16)^D43 -> 0.93730903 | E44: =1/(1+$C$16)^E43 -> 0.8583416 | F44: =1/(1+$C$16)^F43 -> 0.7860271 | G44: =1/(1+$C$16)^G43 -> 0.71980504 | H44: =1/(1+$C$16)^H43 -> 0.65916213 | I44: =1/(1+$C$16)^I43 -> 0.60362832 | J44: =1/(1+$C$16)^J43 -> 0.55277319 | ... Q44: =1/(1+$C$16)^Q43 -> 0.29853036
A45: FCFF 现值 | B45: 百万元 | C45: =C42*C44 -> -215.3384 | D45: =D42*D44 -> -180.92657 | E45: =E42*E44 -> 263.40638 | F45: =F42*F44 -> 625.65103 | G45: =G42*G44 -> 711.93623 | H45: =H42*H44 -> 673.62411 | I45: =I42*I44 -> 642.84138 | J45: =J42*J44 -> 620.18245 | ... Q45: =Q42*Q44 -> 634.17516
A46: 注：股份支付视同现金成本，不加回；2026年仅计入下半年FCFF（全年预测−上半年已实现），与6月30日净现金衔接。
A48: 三、企业价值到股权价值
A49: 显式期 FCFF 现值合计（2026H2–2030E） | B49: 百万元 | C49: =SUM(C45:G45) -> 1204.7287
A50: 衰减期 FCFF 现值合计（2031E–2040E） | B50: 百万元 | C50: =SUM(H45:Q45) -> 6214.8397
A51: 永续价值（2040年末） | B51: 百万元 | C51: =Q33*(1+$C$18)*(1-$C$18/$C$19)/($C$16-$C$18) -> 32498.984
A52: 永续价值现值 | B52: 百万元 | C52: =C51/(1+$C$16)^($C$21+13+0.5) -> 9701.9334 | D52: 年中法：永续期现金流与2040E现金流采用同一折现期
A53: 企业价值 EV | B53: 百万元 | C53: =C49+C50+C52 -> 17121.502
A54: 永续价值占EV比重 | B54: % | C54: =C52/C53 -> 0.56665201
A55: 加：货币资金（2026-06-30） | B55: 百万元 | C55: 1253.83 | D55: 来源：2026年半年报
A56: 加：交易性及其他非流动金融资产（2026-06-30） | B56: 百万元 | C56: 675.78 | D56: 来源：2026年半年报
A57: 加：长期股权投资（2026-06-30） | B57: 百万元 | C57: 10.84
A58: 减：有息负债（2026-06-30） | B58: 百万元 | C58: 300.96 | D58: 短期借款+一年内到期非流动负债+长期借款
A59: 归母净资产（2026-06-30，备查，用于PB） | B59: 百万元 | C59: 5237.58 | D59: 来源：2026年半年报
A60: 减：2026年中期股利（6月30日后支付） | B60: 百万元 | C60: 89.33 | D60: 2026年中期分红每10股派1.70元，共8,933万元（2026年8月董事会通过，下半年支付）；假设除息日早于估值基准日（未核实）
A61: 少数股东权益占比（2027E–2030E 少数股东损益/净利润均值） | B61: % | C61: =AVERAGE(费用税率!J27:M27) -> 0.17901996 | D61: 按少数股东对未来利润的分享比例扣减
A62: 减：少数股东应占经营价值（EV×少数股东占比） | B62: 百万元 | C62: =C53*C61 -> 3065.0905 | D62: 少数股东比例仅作用于经营价值；净现金按全额归属母公司处理（子公司现金占比小）
A63: 归母股权价值 = EV − 少数股东价值 + 净现金及金融资产 − 中期股利 | B63: 百万元 | C63: =C53-C62+($C$55+$C$56+$C$57-$C$58-$C$60) -> 15606.571
A64: 每股价值（DCF） | B64: 元 | C64: =C63/C6 -> 29.685689
A65: 相对当前股价 | B65: % | C65: =C64/C5-1 -> -0.69531264
A66: 隐含 2027E PE | B66: x | C66: =C63/利润表!J27 -> 20.774539
A68: 四、反向DCF：当前股价隐含的长期利润水平
A69: 隐含企业价值 =（市值 − 净现金等）/（1 − 少数股东占比） | B69: 百万元 | C69: =(C7-($C$55+$C$56+$C$57-$C$58-$C$60))/(1-C61) -> 60502.605
A70: 隐含2031E起利润路径倍数（显式期不变，衰减期及永续期整体缩放） | B70: x | C70: =(C69-C49)/(C50+C52) -> 3.7254961 | D70: >1 表示股价隐含的长期利润高于模型当前情景；衰减期再投资率与NOPAT成比例，故价值与路径倍数线性相关
A71: 模型2040年NOPAT | B71: 百万元 | C71: =Q33 -> 2549.1886
A72: 隐含2040年NOPAT | B72: 百万元 | C72: =C70*C71 -> 9496.9923
A73: 隐含 / 模型 | B73: x | C73: =C72/C71 -> 3.7254961
A74: 隐含2040年收入（EBIT率不变） | B74: 百万元 | C74: =C70*Q28 -> 40441.996
A75: 隐含收入2025–2040年复合增速 | B75: % | C75: =(C74/利润表!H5)^(1/15)-1 -> 0.22128717
A76: 模型收入2025–2040年复合增速 | B76: % | C76: =(Q28/利润表!H5)^(1/15)-1 -> 0.11876495
A77: 市场EV / 模型2030E NOPAT | B77: x | C77: =C69/G33 -> 40.591303
A79: 五、敏感性：每股价值（元）— WACC × 永续增长率
A80: WACC \ g | C80: =$C$18+(-0.01) -> 0.015 | D80: =$C$18+(-0.005) -> 0.02 | E80: =$C$18+(0) -> 0.025 | F80: =$C$18+(0.005) -> 0.03 | G80: =$C$18+(0.01) -> 0.035
A81: =$C$16+(-0.01) -> 0.082 | C81: =((SUMPRODUCT($C$42:$Q$42,(1+$A81)^(-$C$43:$Q$43))+$Q$33*(1+C$80)*(1-C$80/$C$19)/($A81-C$80)/(1+$A81)^($C$21+13+0.5))*(1-$C$61)+($C$55+$C$56+$C$57-$C$58-$C$60))/$C$6 -> 33.849372 | D81: =((SUMPRODUCT($C$42:$Q$42,(1+$A81)^(-$C$43:$Q$43))+$Q$33*(1+D$80)*(1-D$80/$C$19)/($A81-D$80)/(1+$A81)^($C$21+13+0.5))*(1-$C$61)+($C$55+$C$56+$C$57-$C$58-$C$60))/$C$6 -> 34.690463 | E81: =((SUMPRODUCT($C$42:$Q$42,(1+$A81)^(-$C$43:$Q$43))+$Q$33*(1+E$80)*(1-E$80/$C$19)/($A81-E$80)/(1+$A81)^($C$21+13+0.5))*(1-$C$61)+($C$55+$C$56+$C$57-$C$58-$C$60))/$C$6 -> 35.671227 | F81: =((SUMPRODUCT($C$42:$Q$42,(1+$A81)^(-$C$43:$Q$43))+$Q$33*(1+F$80)*(1-F$80/$C$19)/($A81-F$80)/(1+$A81)^($C$21+13+0.5))*(1-$C$61)+($C$55+$C$56+$C$57-$C$58-$C$60))/$C$6 -> 36.831955 | G81: =((SUMPRODUCT($C$42:$Q$42,(1+$A81)^(-$C$43:$Q$43))+$Q$33*(1+G$80)*(1-G$80/$C$19)/($A81-G$80)/(1+$A81)^($C$21+13+0.5))*(1-$C$61)+($C$55+$C$56+$C$57-$C$58-$C$60))/$C$6 -> 38.230084
A82: =$C$16+(-0.005) -> 0.087 | C82: =((SUMPRODUCT($C$42:$Q$42,(1+$A82)^(-$C$43:$Q$43))+$Q$33*(1+C$80)*(1-C$80/$C$19)/($A82-C$80)/(1+$A82)^($C$21+13+0.5))*(1-$C$61)+($C$55+$C$56+$C$57-$C$58-$C$60))/$C$6 -> 31.04698 | D82: =((SUMPRODUCT($C$42:$Q$42,(1+$A82)^(-$C$43:$Q$43))+$Q$33*(1+D$80)*(1-D$80/$C$19)/($A82-D$80)/(1+$A82)^($C$21+13+0.5))*(1-$C$61)+($C$55+$C$56+$C$57-$C$58-$C$60))/$C$6 -> 31.688107 | E82: =((SUMPRODUCT($C$42:$Q$42,(1+$A82)^(-$C$43:$Q$43))+$Q$33*(1+E$80)*(1-E$80/$C$19)/($A82-E$80)/(1+$A82)^($C$21+13+0.5))*(1-$C$61)+($C$55+$C$56+$C$57-$C$58-$C$60))/$C$6 -> 32.425837 | F82: =((SUMPRODUCT($C$42:$Q$42,(1+$A82)^(-$C$43:$Q$43))+$Q$33*(1+F$80)*(1-F$80/$C$19)/($A82-F$80)/(1+$A82)^($C$21+13+0.5))*(1-$C$61)+($C$55+$C$56+$C$57-$C$58-$C$60))/$C$6 -> 33.285591 | G82: =((SUMPRODUCT($C$42:$Q$42,(1+$A82)^(-$C$43:$Q$43))+$Q$33*(1+G$80)*(1-G$80/$C$19)/($A82-G$80)/(1+$A82)^($C$21+13+0.5))*(1-$C$61)+($C$55+$C$56+$C$57-$C$58-$C$60))/$C$6 -> 34.302569
A83: =$C$16+(0) -> 0.092 | C83: =((SUMPRODUCT($C$42:$Q$42,(1+$A83)^(-$C$43:$Q$43))+$Q$33*(1+C$80)*(1-C$80/$C$19)/($A83-C$80)/(1+$A83)^($C$21+13+0.5))*(1-$C$61)+($C$55+$C$56+$C$57-$C$58-$C$60))/$C$6 -> 28.633813 | D83: =((SUMPRODUCT($C$42:$Q$42,(1+$A83)^(-$C$43:$Q$43))+$Q$33*(1+D$80)*(1-D$80/$C$19)/($A83-D$80)/(1+$A83)^($C$21+13+0.5))*(1-$C$61)+($C$55+$C$56+$C$57-$C$58-$C$60))/$C$6 -> 29.125978 | E83: =((SUMPRODUCT($C$42:$Q$42,(1+$A83)^(-$C$43:$Q$43))+$Q$33*(1+E$80)*(1-E$80/$C$19)/($A83-E$80)/(1+$A83)^($C$21+13+0.5))*(1-$C$61)+($C$55+$C$56+$C$57-$C$58-$C$60))/$C$6 -> 29.685689 | F83: =((SUMPRODUCT($C$42:$Q$42,(1+$A83)^(-$C$43:$Q$43))+$Q$33*(1+F$80)*(1-F$80/$C$19)/($A83-F$80)/(1+$A83)^($C$21+13+0.5))*(1-$C$61)+($C$55+$C$56+$C$57-$C$58-$C$60))/$C$6 -> 30.329287 | G83: =((SUMPRODUCT($C$42:$Q$42,(1+$A83)^(-$C$43:$Q$43))+$Q$33*(1+G$80)*(1-G$80/$C$19)/($A83-G$80)/(1+$A83)^($C$21+13+0.5))*(1-$C$61)+($C$55+$C$56+$C$57-$C$58-$C$60))/$C$6 -> 31.078846
A84: =$C$16+(0.005) -> 0.097 | C84: =((SUMPRODUCT($C$42:$Q$42,(1+$A84)^(-$C$43:$Q$43))+$Q$33*(1+C$80)*(1-C$80/$C$19)/($A84-C$80)/(1+$A84)^($C$21+13+0.5))*(1-$C$61)+($C$55+$C$56+$C$57-$C$58-$C$60))/$C$6 -> 26.537343 | D84: =((SUMPRODUCT($C$42:$Q$42,(1+$A84)^(-$C$43:$Q$43))+$Q$33*(1+D$80)*(1-D$80/$C$19)/($A84-D$80)/(1+$A84)^($C$21+13+0.5))*(1-$C$61)+($C$55+$C$56+$C$57-$C$58-$C$60))/$C$6 -> 26.917131 | E84: =((SUMPRODUCT($C$42:$Q$42,(1+$A84)^(-$C$43:$Q$43))+$Q$33*(1+E$80)*(1-E$80/$C$19)/($A84-E$80)/(1+$A84)^($C$21+13+0.5))*(1-$C$61)+($C$55+$C$56+$C$57-$C$58-$C$60))/$C$6 -> 27.344501 | F84: =((SUMPRODUCT($C$42:$Q$42,(1+$A84)^(-$C$43:$Q$43))+$Q$33*(1+F$80)*(1-F$80/$C$19)/($A84-F$80)/(1+$A84)^($C$21+13+0.5))*(1-$C$61)+($C$55+$C$56+$C$57-$C$58-$C$60))/$C$6 -> 27.830105 | G84: =((SUMPRODUCT($C$42:$Q$42,(1+$A84)^(-$C$43:$Q$43))+$Q$33*(1+G$80)*(1-G$80/$C$19)/($A84-G$80)/(1+$A84)^($C$21+13+0.5))*(1-$C$61)+($C$55+$C$56+$C$57-$C$58-$C$60))/$C$6 -> 28.388031
A85: =$C$16+(0.01) -> 0.102 | C85: =((SUMPRODUCT($C$42:$Q$42,(1+$A85)^(-$C$43:$Q$43))+$Q$33*(1+C$80)*(1-C$80/$C$19)/($A85-C$80)/(1+$A85)^($C$21+13+0.5))*(1-$C$61)+($C$55+$C$56+$C$57-$C$58-$C$60))/$C$6 -> 24.701795 | D85: =((SUMPRODUCT($C$42:$Q$42,(1+$A85)^(-$C$43:$Q$43))+$Q$33*(1+D$80)*(1-D$80/$C$19)/($A85-D$80)/(1+$A85)^($C$21+13+0.5))*(1-$C$61)+($C$55+$C$56+$C$57-$C$58-$C$60))/$C$6 -> 24.995897 | E85: =((SUMPRODUCT($C$42:$Q$42,(1+$A85)^(-$C$43:$Q$43))+$Q$33*(1+E$80)*(1-E$80/$C$19)/($A85-E$80)/(1+$A85)^($C$21+13+0.5))*(1-$C$61)+($C$55+$C$56+$C$57-$C$58-$C$60))/$C$6 -> 25.323655 | F85: =((SUMPRODUCT($C$42:$Q$42,(1+$A85)^(-$C$43:$Q$43))+$Q$33*(1+F$80)*(1-F$80/$C$19)/($A85-F$80)/(1+$A85)^($C$21+13+0.5))*(1-$C$61)+($C$55+$C$56+$C$57-$C$58-$C$60))/$C$6 -> 25.69208 | G85: =((SUMPRODUCT($C$42:$Q$42,(1+$A85)^(-$C$43:$Q$43))+$Q$33*(1+G$80)*(1-G$80/$C$19)/($A85-G$80)/(1+$A85)^($C$21+13+0.5))*(1-$C$61)+($C$55+$C$56+$C$57-$C$58-$C$60))/$C$6 -> 26.110278
A87: 注：敏感性表仅改变折现率与永续增长率，衰减期路径保持当前设定；表中心单元格应等于上方DCF每股价值（见“检查”表）。
A89: 六、敏感性：每股价值（元）— 衰减期起始增速 × 稳态RONIC（WACC为基准）
A90: 起始增速 \ RONIC | C90: =$C$19+(-0.05) -> 0.1 | D90: =$C$19+(-0.03) -> 0.12 | E90: =$C$19+(0) -> 0.15 | F90: =$C$19+(0.03) -> 0.18 | G90: =$C$19+(0.07) -> 0.22
A91: =$C$17+(-0.04) -> 0.068659114 | C91: =(($C$49+$G$28*(1+$A91+($C$18-$A91)*0/9)*($G$30+($C$20-$G$30)*1/10)*(1-$G$32)*(1-($G$38+(($A91+($C$18-$A91)*0/9)/C$90-$G$38)*1/10))/(1+$C$16)^($C$21+4+0.5)+$G$28*(1+$A91+($C$18-$A91)*0/9)*(1+$A91+($C$18-$A91)*1/9)*($G$30+($C$20-$G$30)*2/10)*(1-$G$32)*(1-($G$38+(($A91+($C$18-$A91)*1/9)/C$90-$G$38)*2/10))/(1+$C$16)^($C$21+5+0.5)+$G$28*(1+$A91+($C$18-$A91)*0/9)*(1+$A91+($C$18-$A91)*1/9)*(1+$A91+($C$18-$A91)*2/9)*($G$30+($C$20-$G$30)*3/10)*(1-$G$32)*(1-($G$38+(($A91+($C$18-$A91)*2/9)/C$90-$G$38)*3/10))/(1+$C$16)^($C$21+6+0.5)+$G$28*(1+$A91+($C$18-$A91)*0/9)*(1+$A91+($C$18-$A91)*1/9)*(1+$A91+($C$18-$A91)*2/9)*(1+$A91+($C$18-$A91)*3/9)*($G$30+($C$20-$G$30)*4/10)*(1-$G$32)*(1-($G$38+(($A91+($C$18-$A91)*3/9)/C$90-$G$38)*4/10))/(1+$C$16)^($C$21+7+0.5)+$G$28*(1+$A91+($C$18-$A91)*0/9)*(1+$A91+($C$18-$A91)*1/9)*(1+$A91+($C$18-$A91)*2/9)*(1+$A91+($C$18-$A91)*3/9)*(1+$A91+($C$18-$A91)*4/9)*($G$30+($C$20-$G$30)*5/10)*(1-$G$32)*(1-($G$38+(($A91+($C$18-$A91)*4/9)/C$90-$G$38)*5/10))/(1+$C$16)^($C$21+8+0.5)+$G$28*(1+$A91+($C$18-$A91)*0/9)*(1+$A91+($C$18-$A91)*1/9)*(1+$A91+($C$18-$A91)*2/9)*(1+$A91+($C$18-$A91)*3/9)*(1+$A91+($C$18-$A91)*4/9)*(1+$A91+($C$18-$A91)*5/9)*($G$30+($C$20-$G$30)*6/10)*(1-$G$32)*(1-($G$38+(($A91+($C$18-$A91)*5/9)/C$90-$G$38)*6/10))/(1+$C$16)^($C$21+9+0.5)+$G$28*(1+$A91+($C$18-$A91)*0/9)*(1+$A91+($C$18-$A91)*1/9)*(1+$A91+($C$18-$A91)*2/9)*(1+$A91+($C$18-$A91)*3/9)*(1+$A91+($C$18-$A91)*4/9)*(1+$A91+($C$18-$A91)*5/9)*(1+$A91+($C$18-$A91)*6/9)*($G$30+($C$20-$G$30)*7/10)*(1-$G$32)*(1-($G$38+(($A91+($C$18-$A91)*6/9)/C$90-$G$38)*7/10))/(1+$C$16)^($C$21+10+0.5)+$G$28*(1+$A91+($C$18-$A91)*0/9)*(1+$A91+($C$18-$A91)*1/9)*(1+$A91+($C$18-$A91)*2/9)*(1+$A91+($C$18-$A91)*3/9)*(1+$A91+($C$18-$A91)*4/9)*(1+$A91+($C$18-$A91)*5/9)*(1+$A91+($C$18-$A91)*6/9)*(1+$A91+($C$18-$A91)*7/9)*($G$30+($C$20-$G$30)*8/10)*(1-$G$32)*(1-($G$38+(($A91+($C$18-$A91)*7/9)/C$90-$G$38)*8/10))/(1+$C$16)^($C$21+11+0.5)+$G$28*(1+$A91+($C$18-$A91)*0/9)*(1+$A91+($C$18-$A91)*1/9)*(1+$A91+($C$18-$A91)*2/9)*(1+$A91+($C$18-$A91)*3/9)*(1+$A91+($C$18-$A91)*4/9)*(1+$A91+($C$18-$A91)*5/9)*(1+$A91+($C$18-$A91)*6/9)*(1+$A91+($C$18-$A91)*7/9)*(1+$A91+($C$18-$A91)*8/9)*($G$30+($C$20-$G$30)*9/10)*(1-$G$32)*(1-($G$38+(($A91+($C$18-$A91)*8/9)/C$90-$G$38)*9/10))/(1+$C$16)^($C$21+12+0.5)+$G$28*(1+$A91+($C$18-$A91)*0/9)*(1+$A91+($C$18-$A91)*1/9)*(1+$A91+($C$18-$A91)*2/9)*(1+$A91+($C$18-$A91)*3/9)*(1+$A91+($C$18-$A91)*4/9)*(1+$A91+($C$18-$A91)*5/9)*(1+$A91+($C$18-$A91)*6/9)*(1+$A91+($C$18-$A91)*7/9)*(1+$A91+($C$18-$A91)*8/9)*(1+$A91+($C$18-$A91)*9/9)*($G$30+($C$20-$G$30)*10/10)*(1-$G$32)*(1-($G$38+(($A91+($C$18-$A91)*9/9)/C$90-$G$38)*10/10))/(1+$C$16)^($C$21+13+0.5)+$G$28*(1+$A91+($C$18-$A91)*0/9)*(1+$A91+($C$18-$A91)*1/9)*(1+$A91+($C$18-$A91)*2/9)*(1+$A91+($C$18-$A91)*3/9)*(1+$A91+($C$18-$A91)*4/9)*(1+$A91+($C$18-$A91)*5/9)*(1+$A91+($C$18-$A91)*6/9)*(1+$A91+($C$18-$A91)*7/9)*(1+$A91+($C$18-$A91)*8/9)*(1+$A91+($C$18-$A91)*9/9)*($G$30+($C$20-$G$30)*10/10)*(1-$G$32)*(1+$C$18)*(1-$C$18/C$90)/($C$16-$C$18)/(1+$C$16)^($C$21+13+0.5))*(1-$C$61)+($C$55+$C$56+$C$57-$C$58-$C$60))/$C$6 -> 24.374367 | D91: =(($C$49+$G$28*(1+$A91+($C$18-$A91)*0/9)*($G$30+($C$20-$G$30)*1/10)*(1-$G$32)*(1-($G$38+(($A91+($C$18-$A91)*0/9)/D$90-$G$38)*1/10))/(1+$C$16)^($C$21+4+0.5)+$G$28*(1+$A91+($C$18-$A91)*0/9)*(1+$A91+($C$18-$A91)*1/9)*($G$30+($C$20-$G$30)*2/10)*(1-$G$32)*(1-($G$38+(($A91+($C$18-$A91)*1/9)/D$90-$G$38)*2/10))/(1+$C$16)^($C$21+5+0.5)+$G$28*(1+$A91+($C$18-$A91)*0/9)*(1+$A91+($C$18-$A91)*1/9)*(1+$A91+($C$18-$A91)*2/9)*($G$30+($C$20-$G$30)*3/10)*(1-$G$32)*(1-($G$38+(($A91+($C$18-$A91)*2/9)/D$90-$G$38)*3/10))/(1+$C$16)^($C$21+6+0.5)+$G$28*(1+$A91+($C$18-$A91)*0/9)*(1+$A91+($C$18-$A91)*1/9)*(1+$A91+($C$18-$A91)*2/9)*(1+$A91+($C$18-$A91)*3/9)*($G$30+($C$20-$G$30)*4/10)*(1-$G$32)*(1-($G$38+(($A91+($C$18-$A91)*3/9)/D$90-$G$38)*4/10))/(1+$C$16)^($C$21+7+0.5)+$G$28*(1+$A91+($C$18-$A91)*0/9)*(1+$A91+($C$18-$A91)*1/9)*(1+$A91+($C$18-$A91)*2/9)*(1+$A91+($C$18-$A91)*3/9)*(1+$A91+($C$18-$A91)*4/9)*($G$30+($C$20-$G$30)*5/10)*(1-$G$32)*(1-($G$38+(($A91+($C$18-$A91)*4/9)/D$90-$G$38)*5/10))/(1+$C$16)^($C$21+8+0.5)+$G$28*(1+$A91+($C$18-$A91)*0/9)*(1+$A91+($C$18-$A91)*1/9)*(1+$A91+($C$18-$A91)*2/9)*(1+$A91+($C$18-$A91)*3/9)*(1+$A91+($C$18-$A91)*4/9)*(1+$A91+($C$18-$A91)*5/9)*($G$30+($C$20-$G$30)*6/10)*(1-$G$32)*(1-($G$38+(($A91+($C$18-$A91)*5/9)/D$90-$G$38)*6/10))/(1+$C$16)^($C$21+9+0.5)+$G$28*(1+$A91+($C$18-$A91)*0/9)*(1+$A91+($C$18-$A91)*1/9)*(1+$A91+($C$18-$A91)*2/9)*(1+$A91+($C$18-$A91)*3/9)*(1+$A91+($C$18-$A91)*4/9)*(1+$A91+($C$18-$A91)*5/9)*(1+$A91+($C$18-$A91)*6/9)*($G$30+($C$20-$G$30)*7/10)*(1-$G$32)*(1-($G$38+(($A91+($C$18-$A91)*6/9)/D$90-$G$38)*7/10))/(1+$C$16)^($C$21+10+0.5)+$G$28*(1+$A91+($C$18-$A91)*0/9)*(1+$A91+($C$18-$A91)*1/9)*(1+$A91+($C$18-$A91)*2/9)*(1+$A91+($C$18-$A91)*3/9)*(1+$A91+($C$18-$A91)*4/9)*(1+$A91+($C$18-$A91)*5/9)*(1+$A91+($C$18-$A91)*6/9)*(1+$A91+($C$18-$A91)*7/9)*($G$30+($C$20-$G$30)*8/10)*(1-$G$32)*(1-($G$38+(($A91+($C$18-$A91)*7/9)/D$90-$G$38)*8/10))/(1+$C$16)^($C$21+11+0.5)+$G$28*(1+$A91+($C$18-$A91)*0/9)*(1+$A91+($C$18-$A91)*1/9)*(1+$A91+($C$18-$A91)*2/9)*(1+$A91+($C$18-$A91)*3/9)*(1+$A91+($C$18-$A91)*4/9)*(1+$A91+($C$18-$A91)*5/9)*(1+$A91+($C$18-$A91)*6/9)*(1+$A91+($C$18-$A91)*7/9)*(1+$A91+($C$18-$A91)*8/9)*($G$30+($C$20-$G$30)*9/10)*(1-$G$32)*(1-($G$38+(($A91+($C$18-$A91)*8/9)/D$90-$G$38)*9/10))/(1+$C$16)^($C$21+12+0.5)+$G$28*(1+$A91+($C$18-$A91)*0/9)*(1+$A91+($C$18-$A91)*1/9)*(1+$A91+($C$18-$A91)*2/9)*(1+$A91+($C$18-$A91)*3/9)*(1+$A91+($C$18-$A91)*4/9)*(1+$A91+($C$18-$A91)*5/9)*(1+$A91+($C$18-$A91)*6/9)*(1+$A91+($C$18-$A91)*7/9)*(1+$A91+($C$18-$A91)*8/9)*(1+$A91+($C$18-$A91)*9/9)*($G$30+($C$20-$G$30)*10/10)*(1-$G$32)*(1-($G$38+(($A91+($C$18-$A91)*9/9)/D$90-$G$38)*10/10))/(1+$C$16)^($C$21+13+0.5)+$G$28*(1+$A91+($C$18-$A91)*0/9)*(1+$A91+($C$18-$A91)*1/9)*(1+$A91+($C$18-$A91)*2/9)*(1+$A91+($C$18-$A91)*3/9)*(1+$A91+($C$18-$A91)*4/9)*(1+$A91+($C$18-$A91)*5/9)*(1+$A91+($C$18-$A91)*6/9)*(1+$A91+($C$18-$A91)*7/9)*(1+$A91+($C$18-$A91)*8/9)*(1+$A91+($C$18-$A91)*9/9)*($G$30+($C$20-$G$30)*10/10)*(1-$G$32)*(1+$C$18)*(1-$C$18/D$90)/($C$16-$C$18)/(1+$C$16)^($C$21+13+0.5))*(1-$C$61)+($C$55+$C$56+$C$57-$C$58-$C$60))/$C$6 -> 25.46121 | E91: =(($C$49+$G$28*(1+$A91+($C$18-$A91)*0/9)*($G$30+($C$20-$G$30)*1/10)*(1-$G$32)*(1-($G$38+(($A91+($C$18-$A91)*0/9)/E$90-$G$38)*1/10))/(1+$C$16)^($C$21+4+0.5)+$G$28*(1+$A91+($C$18-$A91)*0/9)*(1+$A91+($C$18-$A91)*1/9)*($G$30+($C$20-$G$30)*2/10)*(1-$G$32)*(1-($G$38+(($A91+($C$18-$A91)*1/9)/E$90-$G$38)*2/10))/(1+$C$16)^($C$21+5+0.5)+$G$28*(1+$A91+($C$18-$A91)*0/9)*(1+$A91+($C$18-$A91)*1/9)*(1+$A91+($C$18-$A91)*2/9)*($G$30+($C$20-$G$30)*3/10)*(1-$G$32)*(1-($G$38+(($A91+($C$18-$A91)*2/9)/E$90-$G$38)*3/10))/(1+$C$16)^($C$21+6+0.5)+$G$28*(1+$A91+($C$18-$A91)*0/9)*(1+$A91+($C$18-$A91)*1/9)*(1+$A91+($C$18-$A91)*2/9)*(1+$A91+($C$18-$A91)*3/9)*($G$30+($C$20-$G$30)*4/10)*(1-$G$32)*(1-($G$38+(($A91+($C$18-$A91)*3/9)/E$90-$G$38)*4/10))/(1+$C$16)^($C$21+7+0.5)+$G$28*(1+$A91+($C$18-$A91)*0/9)*(1+$A91+($C$18-$A91)*1/9)*(1+$A91+($C$18-$A91)*2/9)*(1+$A91+($C$18-$A91)*3/9)*(1+$A91+($C$18-$A91)*4/9)*($G$30+($C$20-$G$30)*5/10)*(1-$G$32)*(1-($G$38+(($A91+($C$18-$A91)*4/9)/E$90-$G$38)*5/10))/(1+$C$16)^($C$21+8+0.5)+$G$28*(1+$A91+($C$18-$A91)*0/9)*(1+$A91+($C$18-$A91)*1/9)*(1+$A91+($C$18-$A91)*2/9)*(1+$A91+($C$18-$A91)*3/9)*(1+$A91+($C$18-$A91)*4/9)*(1+$A91+($C$18-$A91)*5/9)*($G$30+($C$20-$G$30)*6/10)*(1-$G$32)*(1-($G$38+(($A91+($C$18-$A91)*5/9)/E$90-$G$38)*6/10))/(1+$C$16)^($C$21+9+0.5)+$G$28*(1+$A91+($C$18-$A91)*0/9)*(1+$A91+($C$18-$A91)*1/9)*(1+$A91+($C$18-$A91)*2/9)*(1+$A91+($C$18-$A91)*3/9)*(1+$A91+($C$18-$A91)*4/9)*(1+$A91+($C$18-$A91)*5/9)*(1+$A91+($C$18-$A91)*6/9)*($G$30+($C$20-$G$30)*7/10)*(1-$G$32)*(1-($G$38+(($A91+($C$18-$A91)*6/9)/E$90-$G$38)*7/10))/(1+$C$16)^($C$21+10+0.5)+$G$28*(1+$A91+($C$18-$A91)*0/9)*(1+$A91+($C$18-$A91)*1/9)*(1+$A91+($C$18-$A91)*2/9)*(1+$A91+($C$18-$A91)*3/9)*(1+$A91+($C$18-$A91)*4/9)*(1+$A91+($C$18-$A91)*5/9)*(1+$A91+($C$18-$A91)*6/9)*(1+$A91+($C$18-$A91)*7/9)*($G$30+($C$20-$G$30)*8/10)*(1-$G$32)*(1-($G$38+(($A91+($C$18-$A91)*7/9)/E$90-$G$38)*8/10))/(1+$C$16)^($C$21+11+0.5)+$G$28*(1+$A91+($C$18-$A91)*0/9)*(1+$A91+($C$18-$A91)*1/9)*(1+$A91+($C$18-$A91)*2/9)*(1+$A91+($C$18-$A91)*3/9)*(1+$A91+($C$18-$A91)*4/9)*(1+$A91+($C$18-$A91)*5/9)*(1+$A91+($C$18-$A91)*6/9)*(1+$A91+($C$18-$A91)*7/9)*(1+$A91+($C$18-$A91)*8/9)*($G$30+($C$20-$G$30)*9/10)*(1-$G$32)*(1-($G$38+(($A91+($C$18-$A91)*8/9)/E$90-$G$38)*9/10))/(1+$C$16)^($C$21+12+0.5)+$G$28*(1+$A91+($C$18-$A91)*0/9)*(1+$A91+($C$18-$A91)*1/9)*(1+$A91+($C$18-$A91)*2/9)*(1+$A91+($C$18-$A91)*3/9)*(1+$A91+($C$18-$A91)*4/9)*(1+$A91+($C$18-$A91)*5/9)*(1+$A91+($C$18-$A91)*6/9)*(1+$A91+($C$18-$A91)*7/9)*(1+$A91+($C$18-$A91)*8/9)*(1+$A91+($C$18-$A91)*9/9)*($G$30+($C$20-$G$30)*10/10)*(1-$G$32)*(1-($G$38+(($A91+($C$18-$A91)*9/9)/E$90-$G$38)*10/10))/(1+$C$16)^($C$21+13+0.5)+$G$28*(1+$A91+($C$18-$A91)*0/9)*(1+$A91+($C$18-$A91)*1/9)*(1+$A91+($C$18-$A91)*2/9)*(1+$A91+($C$18-$A91)*3/9)*(1+$A91+($C$18-$A91)*4/9)*(1+$A91+($C$18-$A91)*5/9)*(1+$A91+($C$18-$A91)*6/9)*(1+$A91+($C$18-$A91)*7/9)*(1+$A91+($C$18-$A91)*8/9)*(1+$A91+($C$18-$A91)*9/9)*($G$30+($C$20-$G$30)*10/10)*(1-$G$32)*(1+$C$18)*(1-$C$18/E$90)/($C$16-$C$18)/(1+$C$16)^($C$21+13+0.5))*(1-$C$61)+($C$55+$C$56+$C$57-$C$58-$C$60))/$C$6 -> 26.548052 | F91: =(($C$49+$G$28*(1+$A91+($C$18-$A91)*0/9)*($G$30+($C$20-$G$30)*1/10)*(1-$G$32)*(1-($G$38+(($A91+($C$18-$A91)*0/9)/F$90-$G$38)*1/10))/(1+$C$16)^($C$21+4+0.5)+$G$28*(1+$A91+($C$18-$A91)*0/9)*(1+$A91+($C$18-$A91)*1/9)*($G$30+($C$20-$G$30)*2/10)*(1-$G$32)*(1-($G$38+(($A91+($C$18-$A91)*1/9)/F$90-$G$38)*2/10))/(1+$C$16)^($C$21+5+0.5)+$G$28*(1+$A91+($C$18-$A91)*0/9)*(1+$A91+($C$18-$A91)*1/9)*(1+$A91+($C$18-$A91)*2/9)*($G$30+($C$20-$G$30)*3/10)*(1-$G$32)*(1-($G$38+(($A91+($C$18-$A91)*2/9)/F$90-$G$38)*3/10))/(1+$C$16)^($C$21+6+0.5)+$G$28*(1+$A91+($C$18-$A91)*0/9)*(1+$A91+($C$18-$A91)*1/9)*(1+$A91+($C$18-$A91)*2/9)*(1+$A91+($C$18-$A91)*3/9)*($G$30+($C$20-$G$30)*4/10)*(1-$G$32)*(1-($G$38+(($A91+($C$18-$A91)*3/9)/F$90-$G$38)*4/10))/(1+$C$16)^($C$21+7+0.5)+$G$28*(1+$A91+($C$18-$A91)*0/9)*(1+$A91+($C$18-$A91)*1/9)*(1+$A91+($C$18-$A91)*2/9)*(1+$A91+($C$18-$A91)*3/9)*(1+$A91+($C$18-$A91)*4/9)*($G$30+($C$20-$G$30)*5/10)*(1-$G$32)*(1-($G$38+(($A91+($C$18-$A91)*4/9)/F$90-$G$38)*5/10))/(1+$C$16)^($C$21+8+0.5)+$G$28*(1+$A91+($C$18-$A91)*0/9)*(1+$A91+($C$18-$A91)*1/9)*(1+$A91+($C$18-$A91)*2/9)*(1+$A91+($C$18-$A91)*3/9)*(1+$A91+($C$18-$A91)*4/9)*(1+$A91+($C$18-$A91)*5/9)*($G$30+($C$20-$G$30)*6/10)*(1-$G$32)*(1-($G$38+(($A91+($C$18-$A91)*5/9)/F$90-$G$38)*6/10))/(1+$C$16)^($C$21+9+0.5)+$G$28*(1+$A91+($C$18-$A91)*0/9)*(1+$A91+($C$18-$A91)*1/9)*(1+$A91+($C$18-$A91)*2/9)*(1+$A91+($C$18-$A91)*3/9)*(1+$A91+($C$18-$A91)*4/9)*(1+$A91+($C$18-$A91)*5/9)*(1+$A91+($C$18-$A91)*6/9)*($G$30+($C$20-$G$30)*7/10)*(1-$G$32)*(1-($G$38+(($A91+($C$18-$A91)*6/9)/F$90-$G$38)*7/10))/(1+$C$16)^($C$21+10+0.5)+$G$28*(1+$A91+($C$18-$A91)*0/9)*(1+$A91+($C$18-$A91)*1/9)*(1+$A91+($C$18-$A91)*2/9)*(1+$A91+($C$18-$A91)*3/9)*(1+$A91+($C$18-$A91)*4/9)*(1+$A91+($C$18-$A91)*5/9)*(1+$A91+($C$18-$A91)*6/9)*(1+$A91+($C$18-$A91)*7/9)*($G$30+($C$20-$G$30)*8/10)*(1-$G$32)*(1-($G$38+(($A91+($C$18-$A91)*7/9)/F$90-$G$38)*8/10))/(1+$C$16)^($C$21+11+0.5)+$G$28*(1+$A91+($C$18-$A91)*0/9)*(1+$A91+($C$18-$A91)*1/9)*(1+$A91+($C$18-$A91)*2/9)*(1+$A91+($C$18-$A91)*3/9)*(1+$A91+($C$18-$A91)*4/9)*(1+$A91+($C$18-$A91)*5/9)*(1+$A91+($C$18-$A91)*6/9)*(1+$A91+($C$18-$A91)*7/9)*(1+$A91+($C$18-$A91)*8/9)*($G$30+($C$20-$G$30)*9/10)*(1-$G$32)*(1-($G$38+(($A91+($C$18-$A91)*8/9)/F$90-$G$38)*9/10))/(1+$C$16)^($C$21+12+0.5)+$G$28*(1+$A91+($C$18-$A91)*0/9)*(1+$A91+($C$18-$A91)*1/9)*(1+$A91+($C$18-$A91)*2/9)*(1+$A91+($C$18-$A91)*3/9)*(1+$A91+($C$18-$A91)*4/9)*(1+$A91+($C$18-$A91)*5/9)*(1+$A91+($C$18-$A91)*6/9)*(1+$A91+($C$18-$A91)*7/9)*(1+$A91+($C$18-$A91)*8/9)*(1+$A91+($C$18-$A91)*9/9)*($G$30+($C$20-$G$30)*10/10)*(1-$G$32)*(1-($G$38+(($A91+($C$18-$A91)*9/9)/F$90-$G$38)*10/10))/(1+$C$16)^($C$21+13+0.5)+$G$28*(1+$A91+($C$18-$A91)*0/9)*(1+$A91+($C$18-$A91)*1/9)*(1+$A91+($C$18-$A91)*2/9)*(1+$A91+($C$18-$A91)*3/9)*(1+$A91+($C$18-$A91)*4/9)*(1+$A91+($C$18-$A91)*5/9)*(1+$A91+($C$18-$A91)*6/9)*(1+$A91+($C$18-$A91)*7/9)*(1+$A91+($C$18-$A91)*8/9)*(1+$A91+($C$18-$A91)*9/9)*($G$30+($C$20-$G$30)*10/10)*(1-$G$32)*(1+$C$18)*(1-$C$18/F$90)/($C$16-$C$18)/(1+$C$16)^($C$21+13+0.5))*(1-$C$61)+($C$55+$C$56+$C$57-$C$58-$C$60))/$C$6 -> 27.272614 | G91: =(($C$49+$G$28*(1+$A91+($C$18-$A91)*0/9)*($G$30+($C$20-$G$30)*1/10)*(1-$G$32)*(1-($G$38+(($A91+($C$18-$A91)*0/9)/G$90-$G$38)*1/10))/(1+$C$16)^($C$21+4+0.5)+$G$28*(1+$A91+($C$18-$A91)*0/9)*(1+$A91+($C$18-$A91)*1/9)*($G$30+($C$20-$G$30)*2/10)*(1-$G$32)*(1-($G$38+(($A91+($C$18-$A91)*1/9)/G$90-$G$38)*2/10))/(1+$C$16)^($C$21+5+0.5)+$G$28*(1+$A91+($C$18-$A91)*0/9)*(1+$A91+($C$18-$A91)*1/9)*(1+$A91+($C$18-$A91)*2/9)*($G$30+($C$20-$G$30)*3/10)*(1-$G$32)*(1-($G$38+(($A91+($C$18-$A91)*2/9)/G$90-$G$38)*3/10))/(1+$C$16)^($C$21+6+0.5)+$G$28*(1+$A91+($C$18-$A91)*0/9)*(1+$A91+($C$18-$A91)*1/9)*(1+$A91+($C$18-$A91)*2/9)*(1+$A91+($C$18-$A91)*3/9)*($G$30+($C$20-$G$30)*4/10)*(1-$G$32)*(1-($G$38+(($A91+($C$18-$A91)*3/9)/G$90-$G$38)*4/10))/(1+$C$16)^($C$21+7+0.5)+$G$28*(1+$A91+($C$18-$A91)*0/9)*(1+$A91+($C$18-$A91)*1/9)*(1+$A91+($C$18-$A91)*2/9)*(1+$A91+($C$18-$A91)*3/9)*(1+$A91+($C$18-$A91)*4/9)*($G$30+($C$20-$G$30)*5/10)*(1-$G$32)*(1-($G$38+(($A91+($C$18-$A91)*4/9)/G$90-$G$38)*5/10))/(1+$C$16)^($C$21+8+0.5)+$G$28*(1+$A91+($C$18-$A91)*0/9)*(1+$A91+($C$18-$A91)*1/9)*(1+$A91+($C$18-$A91)*2/9)*(1+$A91+($C$18-$A91)*3/9)*(1+$A91+($C$18-$A91)*4/9)*(1+$A91+($C$18-$A91)*5/9)*($G$30+($C$20-$G$30)*6/10)*(1-$G$32)*(1-($G$38+(($A91+($C$18-$A91)*5/9)/G$90-$G$38)*6/10))/(1+$C$16)^($C$21+9+0.5)+$G$28*(1+$A91+($C$18-$A91)*0/9)*(1+$A91+($C$18-$A91)*1/9)*(1+$A91+($C$18-$A91)*2/9)*(1+$A91+($C$18-$A91)*3/9)*(1+$A91+($C$18-$A91)*4/9)*(1+$A91+($C$18-$A91)*5/9)*(1+$A91+($C$18-$A91)*6/9)*($G$30+($C$20-$G$30)*7/10)*(1-$G$32)*(1-($G$38+(($A91+($C$18-$A91)*6/9)/G$90-$G$38)*7/10))/(1+$C$16)^($C$21+10+0.5)+$G$28*(1+$A91+($C$18-$A91)*0/9)*(1+$A91+($C$18-$A91)*1/9)*(1+$A91+($C$18-$A91)*2/9)*(1+$A91+($C$18-$A91)*3/9)*(1+$A91+($C$18-$A91)*4/9)*(1+$A91+($C$18-$A91)*5/9)*(1+$A91+($C$18-$A91)*6/9)*(1+$A91+($C$18-$A91)*7/9)*($G$30+($C$20-$G$30)*8/10)*(1-$G$32)*(1-($G$38+(($A91+($C$18-$A91)*7/9)/G$90-$G$38)*8/10))/(1+$C$16)^($C$21+11+0.5)+$G$28*(1+$A91+($C$18-$A91)*0/9)*(1+$A91+($C$18-$A91)*1/9)*(1+$A91+($C$18-$A91)*2/9)*(1+$A91+($C$18-$A91)*3/9)*(1+$A91+($C$18-$A91)*4/9)*(1+$A91+($C$18-$A91)*5/9)*(1+$A91+($C$18-$A91)*6/9)*(1+$A91+($C$18-$A91)*7/9)*(1+$A91+($C$18-$A91)*8/9)*($G$30+($C$20-$G$30)*9/10)*(1-$G$32)*(1-($G$38+(($A91+($C$18-$A91)*8/9)/G$90-$G$38)*9/10))/(1+$C$16)^($C$21+12+0.5)+$G$28*(1+$A91+($C$18-$A91)*0/9)*(1+$A91+($C$18-$A91)*1/9)*(1+$A91+($C$18-$A91)*2/9)*(1+$A91+($C$18-$A91)*3/9)*(1+$A91+($C$18-$A91)*4/9)*(1+$A91+($C$18-$A91)*5/9)*(1+$A91+($C$18-$A91)*6/9)*(1+$A91+($C$18-$A91)*7/9)*(1+$A91+($C$18-$A91)*8/9)*(1+$A91+($C$18-$A91)*9/9)*($G$30+($C$20-$G$30)*10/10)*(1-$G$32)*(1-($G$38+(($A91+($C$18-$A91)*9/9)/G$90-$G$38)*10/10))/(1+$C$16)^($C$21+13+0.5)+$G$28*(1+$A91+($C$18-$A91)*0/9)*(1+$A91+($C$18-$A91)*1/9)*(1+$A91+($C$18-$A91)*2/9)*(1+$A91+($C$18-$A91)*3/9)*(1+$A91+($C$18-$A91)*4/9)*(1+$A91+($C$18-$A91)*5/9)*(1+$A91+($C$18-$A91)*6/9)*(1+$A91+($C$18-$A91)*7/9)*(1+$A91+($C$18-$A91)*8/9)*(1+$A91+($C$18-$A91)*9/9)*($G$30+($C$20-$G$30)*10/10)*(1-$G$32)*(1+$C$18)*(1-$C$18/G$90)/($C$16-$C$18)/(1+$C$16)^($C$21+13+0.5))*(1-$C$61)+($C$55+$C$56+$C$57-$C$58-$C$60))/$C$6 -> 27.931306
A92: =$C$17+(-0.02) -> 0.088659114 | C92: =(($C$49+$G$28*(1+$A92+($C$18-$A92)*0/9)*($G$30+($C$20-$G$30)*1/10)*(1-$G$32)*(1-($G$38+(($A92+($C$18-$A92)*0/9)/C$90-$G$38)*1/10))/(1+$C$16)^($C$21+4+0.5)+$G$28*(1+$A92+($C$18-$A92)*0/9)*(1+$A92+($C$18-$A92)*1/9)*($G$30+($C$20-$G$30)*2/10)*(1-$G$32)*(1-($G$38+(($A92+($C$18-$A92)*1/9)/C$90-$G$38)*2/10))/(1+$C$16)^($C$21+5+0.5)+$G$28*(1+$A92+($C$18-$A92)*0/9)*(1+$A92+($C$18-$A92)*1/9)*(1+$A92+($C$18-$A92)*2/9)*($G$30+($C$20-$G$30)*3/10)*(1-$G$32)*(1-($G$38+(($A92+($C$18-$A92)*2/9)/C$90-$G$38)*3/10))/(1+$C$16)^($C$21+6+0.5)+$G$28*(1+$A92+($C$18-$A92)*0/9)*(1+$A92+($C$18-$A92)*1/9)*(1+$A92+($C$18-$A92)*2/9)*(1+$A92+($C$18-$A92)*3/9)*($G$30+($C$20-$G$30)*4/10)*(1-$G$32)*(1-($G$38+(($A92+($C$18-$A92)*3/9)/C$90-$G$38)*4/10))/(1+$C$16)^($C$21+7+0.5)+$G$28*(1+$A92+($C$18-$A92)*0/9)*(1+$A92+($C$18-$A92)*1/9)*(1+$A92+($C$18-$A92)*2/9)*(1+$A92+($C$18-$A92)*3/9)*(1+$A92+($C$18-$A92)*4/9)*($G$30+($C$20-$G$30)*5/10)*(1-$G$32)*(1-($G$38+(($A92+($C$18-$A92)*4/9)/C$90-$G$38)*5/10))/(1+$C$16)^($C$21+8+0.5)+$G$28*(1+$A92+($C$18-$A92)*0/9)*(1+$A92+($C$18-$A92)*1/9)*(1+$A92+($C$18-$A92)*2/9)*(1+$A92+($C$18-$A92)*3/9)*(1+$A92+($C$18-$A92)*4/9)*(1+$A92+($C$18-$A92)*5/9)*($G$30+($C$20-$G$30)*6/10)*(1-$G$32)*(1-($G$38+(($A92+($C$18-$A92)*5/9)/C$90-$G$38)*6/10))/(1+$C$16)^($C$21+9+0.5)+$G$28*(1+$A92+($C$18-$A92)*0/9)*(1+$A92+($C$18-$A92)*1/9)*(1+$A92+($C$18-$A92)*2/9)*(1+$A92+($C$18-$A92)*3/9)*(1+$A92+($C$18-$A92)*4/9)*(1+$A92+($C$18-$A92)*5/9)*(1+$A92+($C$18-$A92)*6/9)*($G$30+($C$20-$G$30)*7/10)*(1-$G$32)*(1-($G$38+(($A92+($C$18-$A92)*6/9)/C$90-$G$38)*7/10))/(1+$C$16)^($C$21+10+0.5)+$G$28*(1+$A92+($C$18-$A92)*0/9)*(1+$A92+($C$18-$A92)*1/9)*(1+$A92+($C$18-$A92)*2/9)*(1+$A92+($C$18-$A92)*3/9)*(1+$A92+($C$18-$A92)*4/9)*(1+$A92+($C$18-$A92)*5/9)*(1+$A92+($C$18-$A92)*6/9)*(1+$A92+($C$18-$A92)*7/9)*($G$30+($C$20-$G$30)*8/10)*(1-$G$32)*(1-($G$38+(($A92+($C$18-$A92)*7/9)/C$90-$G$38)*8/10))/(1+$C$16)^($C$21+11+0.5)+$G$28*(1+$A92+($C$18-$A92)*0/9)*(1+$A92+($C$18-$A92)*1/9)*(1+$A92+($C$18-$A92)*2/9)*(1+$A92+($C$18-$A92)*3/9)*(1+$A92+($C$18-$A92)*4/9)*(1+$A92+($C$18-$A92)*5/9)*(1+$A92+($C$18-$A92)*6/9)*(1+$A92+($C$18-$A92)*7/9)*(1+$A92+($C$18-$A92)*8/9)*($G$30+($C$20-$G$30)*9/10)*(1-$G$32)*(1-($G$38+(($A92+($C$18-$A92)*8/9)/C$90-$G$38)*9/10))/(1+$C$16)^($C$21+12+0.5)+$G$28*(1+$A92+($C$18-$A92)*0/9)*(1+$A92+($C$18-$A92)*1/9)*(1+$A92+($C$18-$A92)*2/9)*(1+$A92+($C$18-$A92)*3/9)*(1+$A92+($C$18-$A92)*4/9)*(1+$A92+($C$18-$A92)*5/9)*(1+$A92+($C$18-$A92)*6/9)*(1+$A92+($C$18-$A92)*7/9)*(1+$A92+($C$18-$A92)*8/9)*(1+$A92+($C$18-$A92)*9/9)*($G$30+($C$20-$G$30)*10/10)*(1-$G$32)*(1-($G$38+(($A92+($C$18-$A92)*9/9)/C$90-$G$38)*10/10))/(1+$C$16)^($C$21+13+0.5)+$G$28*(1+$A92+($C$18-$A92)*0/9)*(1+$A92+($C$18-$A92)*1/9)*(1+$A92+($C$18-$A92)*2/9)*(1+$A92+($C$18-$A92)*3/9)*(1+$A92+($C$18-$A92)*4/9)*(1+$A92+($C$18-$A92)*5/9)*(1+$A92+($C$18-$A92)*6/9)*(1+$A92+($C$18-$A92)*7/9)*(1+$A92+($C$18-$A92)*8/9)*(1+$A92+($C$18-$A92)*9/9)*($G$30+($C$20-$G$30)*10/10)*(1-$G$32)*(1+$C$18)*(1-$C$18/C$90)/($C$16-$C$18)/(1+$C$16)^($C$21+13+0.5))*(1-$C$61)+($C$55+$C$56+$C$57-$C$58-$C$60))/$C$6 -> 25.523264 | D92: =(($C$49+$G$28*(1+$A92+($C$18-$A92)*0/9)*($G$30+($C$20-$G$30)*1/10)*(1-$G$32)*(1-($G$38+(($A92+($C$18-$A92)*0/9)/D$90-$G$38)*1/10))/(1+$C$16)^($C$21+4+0.5)+$G$28*(1+$A92+($C$18-$A92)*0/9)*(1+$A92+($C$18-$A92)*1/9)*($G$30+($C$20-$G$30)*2/10)*(1-$G$32)*(1-($G$38+(($A92+($C$18-$A92)*1/9)/D$90-$G$38)*2/10))/(1+$C$16)^($C$21+5+0.5)+$G$28*(1+$A92+($C$18-$A92)*0/9)*(1+$A92+($C$18-$A92)*1/9)*(1+$A92+($C$18-$A92)*2/9)*($G$30+($C$20-$G$30)*3/10)*(1-$G$32)*(1-($G$38+(($A92+($C$18-$A92)*2/9)/D$90-$G$38)*3/10))/(1+$C$16)^($C$21+6+0.5)+$G$28*(1+$A92+($C$18-$A92)*0/9)*(1+$A92+($C$18-$A92)*1/9)*(1+$A92+($C$18-$A92)*2/9)*(1+$A92+($C$18-$A92)*3/9)*($G$30+($C$20-$G$30)*4/10)*(1-$G$32)*(1-($G$38+(($A92+($C$18-$A92)*3/9)/D$90-$G$38)*4/10))/(1+$C$16)^($C$21+7+0.5)+$G$28*(1+$A92+($C$18-$A92)*0/9)*(1+$A92+($C$18-$A92)*1/9)*(1+$A92+($C$18-$A92)*2/9)*(1+$A92+($C$18-$A92)*3/9)*(1+$A92+($C$18-$A92)*4/9)*($G$30+($C$20-$G$30)*5/10)*(1-$G$32)*(1-($G$38+(($A92+($C$18-$A92)*4/9)/D$90-$G$38)*5/10))/(1+$C$16)^($C$21+8+0.5)+$G$28*(1+$A92+($C$18-$A92)*0/9)*(1+$A92+($C$18-$A92)*1/9)*(1+$A92+($C$18-$A92)*2/9)*(1+$A92+($C$18-$A92)*3/9)*(1+$A92+($C$18-$A92)*4/9)*(1+$A92+($C$18-$A92)*5/9)*($G$30+($C$20-$G$30)*6/10)*(1-$G$32)*(1-($G$38+(($A92+($C$18-$A92)*5/9)/D$90-$G$38)*6/10))/(1+$C$16)^($C$21+9+0.5)+$G$28*(1+$A92+($C$18-$A92)*0/9)*(1+$A92+($C$18-$A92)*1/9)*(1+$A92+($C$18-$A92)*2/9)*(1+$A92+($C$18-$A92)*3/9)*(1+$A92+($C$18-$A92)*4/9)*(1+$A92+($C$18-$A92)*5/9)*(1+$A92+($C$18-$A92)*6/9)*($G$30+($C$20-$G$30)*7/10)*(1-$G$32)*(1-($G$38+(($A92+($C$18-$A92)*6/9)/D$90-$G$38)*7/10))/(1+$C$16)^($C$21+10+0.5)+$G$28*(1+$A92+($C$18-$A92)*0/9)*(1+$A92+($C$18-$A92)*1/9)*(1+$A92+($C$18-$A92)*2/9)*(1+$A92+($C$18-$A92)*3/9)*(1+$A92+($C$18-$A92)*4/9)*(1+$A92+($C$18-$A92)*5/9)*(1+$A92+($C$18-$A92)*6/9)*(1+$A92+($C$18-$A92)*7/9)*($G$30+($C$20-$G$30)*8/10)*(1-$G$32)*(1-($G$38+(($A92+($C$18-$A92)*7/9)/D$90-$G$38)*8/10))/(1+$C$16)^($C$21+11+0.5)+$G$28*(1+$A92+($C$18-$A92)*0/9)*(1+$A92+($C$18-$A92)*1/9)*(1+$A92+($C$18-$A92)*2/9)*(1+$A92+($C$18-$A92)*3/9)*(1+$A92+($C$18-$A92)*4/9)*(1+$A92+($C$18-$A92)*5/9)*(1+$A92+($C$18-$A92)*6/9)*(1+$A92+($C$18-$A92)*7/9)*(1+$A92+($C$18-$A92)*8/9)*($G$30+($C$20-$G$30)*9/10)*(1-$G$32)*(1-($G$38+(($A92+($C$18-$A92)*8/9)/D$90-$G$38)*9/10))/(1+$C$16)^($C$21+12+0.5)+$G$28*(1+$A92+($C$18-$A92)*0/9)*(1+$A92+($C$18-$A92)*1/9)*(1+$A92+($C$18-$A92)*2/9)*(1+$A92+($C$18-$A92)*3/9)*(1+$A92+($C$18-$A92)*4/9)*(1+$A92+($C$18-$A92)*5/9)*(1+$A92+($C$18-$A92)*6/9)*(1+$A92+($C$18-$A92)*7/9)*(1+$A92+($C$18-$A92)*8/9)*(1+$A92+($C$18-$A92)*9/9)*($G$30+($C$20-$G$30)*10/10)*(1-$G$32)*(1-($G$38+(($A92+($C$18-$A92)*9/9)/D$90-$G$38)*10/10))/(1+$C$16)^($C$21+13+0.5)+$G$28*(1+$A92+($C$18-$A92)*0/9)*(1+$A92+($C$18-$A92)*1/9)*(1+$A92+($C$18-$A92)*2/9)*(1+$A92+($C$18-$A92)*3/9)*(1+$A92+($C$18-$A92)*4/9)*(1+$A92+($C$18-$A92)*5/9)*(1+$A92+($C$18-$A92)*6/9)*(1+$A92+($C$18-$A92)*7/9)*(1+$A92+($C$18-$A92)*8/9)*(1+$A92+($C$18-$A92)*9/9)*($G$30+($C$20-$G$30)*10/10)*(1-$G$32)*(1+$C$18)*(1-$C$18/D$90)/($C$16-$C$18)/(1+$C$16)^($C$21+13+0.5))*(1-$C$61)+($C$55+$C$56+$C$57-$C$58-$C$60))/$C$6 -> 26.795849 | E92: =(($C$49+$G$28*(1+$A92+($C$18-$A92)*0/9)*($G$30+($C$20-$G$30)*1/10)*(1-$G$32)*(1-($G$38+(($A92+($C$18-$A92)*0/9)/E$90-$G$38)*1/10))/(1+$C$16)^($C$21+4+0.5)+$G$28*(1+$A92+($C$18-$A92)*0/9)*(1+$A92+($C$18-$A92)*1/9)*($G$30+($C$20-$G$30)*2/10)*(1-$G$32)*(1-($G$38+(($A92+($C$18-$A92)*1/9)/E$90-$G$38)*2/10))/(1+$C$16)^($C$21+5+0.5)+$G$28*(1+$A92+($C$18-$A92)*0/9)*(1+$A92+($C$18-$A92)*1/9)*(1+$A92+($C$18-$A92)*2/9)*($G$30+($C$20-$G$30)*3/10)*(1-$G$32)*(1-($G$38+(($A92+($C$18-$A92)*2/9)/E$90-$G$38)*3/10))/(1+$C$16)^($C$21+6+0.5)+$G$28*(1+$A92+($C$18-$A92)*0/9)*(1+$A92+($C$18-$A92)*1/9)*(1+$A92+($C$18-$A92)*2/9)*(1+$A92+($C$18-$A92)*3/9)*($G$30+($C$20-$G$30)*4/10)*(1-$G$32)*(1-($G$38+(($A92+($C$18-$A92)*3/9)/E$90-$G$38)*4/10))/(1+$C$16)^($C$21+7+0.5)+$G$28*(1+$A92+($C$18-$A92)*0/9)*(1+$A92+($C$18-$A92)*1/9)*(1+$A92+($C$18-$A92)*2/9)*(1+$A92+($C$18-$A92)*3/9)*(1+$A92+($C$18-$A92)*4/9)*($G$30+($C$20-$G$30)*5/10)*(1-$G$32)*(1-($G$38+(($A92+($C$18-$A92)*4/9)/E$90-$G$38)*5/10))/(1+$C$16)^($C$21+8+0.5)+$G$28*(1+$A92+($C$18-$A92)*0/9)*(1+$A92+($C$18-$A92)*1/9)*(1+$A92+($C$18-$A92)*2/9)*(1+$A92+($C$18-$A92)*3/9)*(1+$A92+($C$18-$A92)*4/9)*(1+$A92+($C$18-$A92)*5/9)*($G$30+($C$20-$G$30)*6/10)*(1-$G$32)*(1-($G$38+(($A92+($C$18-$A92)*5/9)/E$90-$G$38)*6/10))/(1+$C$16)^($C$21+9+0.5)+$G$28*(1+$A92+($C$18-$A92)*0/9)*(1+$A92+($C$18-$A92)*1/9)*(1+$A92+($C$18-$A92)*2/9)*(1+$A92+($C$18-$A92)*3/9)*(1+$A92+($C$18-$A92)*4/9)*(1+$A92+($C$18-$A92)*5/9)*(1+$A92+($C$18-$A92)*6/9)*($G$30+($C$20-$G$30)*7/10)*(1-$G$32)*(1-($G$38+(($A92+($C$18-$A92)*6/9)/E$90-$G$38)*7/10))/(1+$C$16)^($C$21+10+0.5)+$G$28*(1+$A92+($C$18-$A92)*0/9)*(1+$A92+($C$18-$A92)*1/9)*(1+$A92+($C$18-$A92)*2/9)*(1+$A92+($C$18-$A92)*3/9)*(1+$A92+($C$18-$A92)*4/9)*(1+$A92+($C$18-$A92)*5/9)*(1+$A92+($C$18-$A92)*6/9)*(1+$A92+($C$18-$A92)*7/9)*($G$30+($C$20-$G$30)*8/10)*(1-$G$32)*(1-($G$38+(($A92+($C$18-$A92)*7/9)/E$90-$G$38)*8/10))/(1+$C$16)^($C$21+11+0.5)+$G$28*(1+$A92+($C$18-$A92)*0/9)*(1+$A92+($C$18-$A92)*1/9)*(1+$A92+($C$18-$A92)*2/9)*(1+$A92+($C$18-$A92)*3/9)*(1+$A92+($C$18-$A92)*4/9)*(1+$A92+($C$18-$A92)*5/9)*(1+$A92+($C$18-$A92)*6/9)*(1+$A92+($C$18-$A92)*7/9)*(1+$A92+($C$18-$A92)*8/9)*($G$30+($C$20-$G$30)*9/10)*(1-$G$32)*(1-($G$38+(($A92+($C$18-$A92)*8/9)/E$90-$G$38)*9/10))/(1+$C$16)^($C$21+12+0.5)+$G$28*(1+$A92+($C$18-$A92)*0/9)*(1+$A92+($C$18-$A92)*1/9)*(1+$A92+($C$18-$A92)*2/9)*(1+$A92+($C$18-$A92)*3/9)*(1+$A92+($C$18-$A92)*4/9)*(1+$A92+($C$18-$A92)*5/9)*(1+$A92+($C$18-$A92)*6/9)*(1+$A92+($C$18-$A92)*7/9)*(1+$A92+($C$18-$A92)*8/9)*(1+$A92+($C$18-$A92)*9/9)*($G$30+($C$20-$G$30)*10/10)*(1-$G$32)*(1-($G$38+(($A92+($C$18-$A92)*9/9)/E$90-$G$38)*10/10))/(1+$C$16)^($C$21+13+0.5)+$G$28*(1+$A92+($C$18-$A92)*0/9)*(1+$A92+($C$18-$A92)*1/9)*(1+$A92+($C$18-$A92)*2/9)*(1+$A92+($C$18-$A92)*3/9)*(1+$A92+($C$18-$A92)*4/9)*(1+$A92+($C$18-$A92)*5/9)*(1+$A92+($C$18-$A92)*6/9)*(1+$A92+($C$18-$A92)*7/9)*(1+$A92+($C$18-$A92)*8/9)*(1+$A92+($C$18-$A92)*9/9)*($G$30+($C$20-$G$30)*10/10)*(1-$G$32)*(1+$C$18)*(1-$C$18/E$90)/($C$16-$C$18)/(1+$C$16)^($C$21+13+0.5))*(1-$C$61)+($C$55+$C$56+$C$57-$C$58-$C$60))/$C$6 -> 28.068433 | F92: =(($C$49+$G$28*(1+$A92+($C$18-$A92)*0/9)*($G$30+($C$20-$G$30)*1/10)*(1-$G$32)*(1-($G$38+(($A92+($C$18-$A92)*0/9)/F$90-$G$38)*1/10))/(1+$C$16)^($C$21+4+0.5)+$G$28*(1+$A92+($C$18-$A92)*0/9)*(1+$A92+($C$18-$A92)*1/9)*($G$30+($C$20-$G$30)*2/10)*(1-$G$32)*(1-($G$38+(($A92+($C$18-$A92)*1/9)/F$90-$G$38)*2/10))/(1+$C$16)^($C$21+5+0.5)+$G$28*(1+$A92+($C$18-$A92)*0/9)*(1+$A92+($C$18-$A92)*1/9)*(1+$A92+($C$18-$A92)*2/9)*($G$30+($C$20-$G$30)*3/10)*(1-$G$32)*(1-($G$38+(($A92+($C$18-$A92)*2/9)/F$90-$G$38)*3/10))/(1+$C$16)^($C$21+6+0.5)+$G$28*(1+$A92+($C$18-$A92)*0/9)*(1+$A92+($C$18-$A92)*1/9)*(1+$A92+($C$18-$A92)*2/9)*(1+$A92+($C$18-$A92)*3/9)*($G$30+($C$20-$G$30)*4/10)*(1-$G$32)*(1-($G$38+(($A92+($C$18-$A92)*3/9)/F$90-$G$38)*4/10))/(1+$C$16)^($C$21+7+0.5)+$G$28*(1+$A92+($C$18-$A92)*0/9)*(1+$A92+($C$18-$A92)*1/9)*(1+$A92+($C$18-$A92)*2/9)*(1+$A92+($C$18-$A92)*3/9)*(1+$A92+($C$18-$A92)*4/9)*($G$30+($C$20-$G$30)*5/10)*(1-$G$32)*(1-($G$38+(($A92+($C$18-$A92)*4/9)/F$90-$G$38)*5/10))/(1+$C$16)^($C$21+8+0.5)+$G$28*(1+$A92+($C$18-$A92)*0/9)*(1+$A92+($C$18-$A92)*1/9)*(1+$A92+($C$18-$A92)*2/9)*(1+$A92+($C$18-$A92)*3/9)*(1+$A92+($C$18-$A92)*4/9)*(1+$A92+($C$18-$A92)*5/9)*($G$30+($C$20-$G$30)*6/10)*(1-$G$32)*(1-($G$38+(($A92+($C$18-$A92)*5/9)/F$90-$G$38)*6/10))/(1+$C$16)^($C$21+9+0.5)+$G$28*(1+$A92+($C$18-$A92)*0/9)*(1+$A92+($C$18-$A92)*1/9)*(1+$A92+($C$18-$A92)*2/9)*(1+$A92+($C$18-$A92)*3/9)*(1+$A92+($C$18-$A92)*4/9)*(1+$A92+($C$18-$A92)*5/9)*(1+$A92+($C$18-$A92)*6/9)*($G$30+($C$20-$G$30)*7/10)*(1-$G$32)*(1-($G$38+(($A92+($C$18-$A92)*6/9)/F$90-$G$38)*7/10))/(1+$C$16)^($C$21+10+0.5)+$G$28*(1+$A92+($C$18-$A92)*0/9)*(1+$A92+($C$18-$A92)*1/9)*(1+$A92+($C$18-$A92)*2/9)*(1+$A92+($C$18-$A92)*3/9)*(1+$A92+($C$18-$A92)*4/9)*(1+$A92+($C$18-$A92)*5/9)*(1+$A92+($C$18-$A92)*6/9)*(1+$A92+($C$18-$A92)*7/9)*($G$30+($C$20-$G$30)*8/10)*(1-$G$32)*(1-($G$38+(($A92+($C$18-$A92)*7/9)/F$90-$G$38)*8/10))/(1+$C$16)^($C$21+11+0.5)+$G$28*(1+$A92+($C$18-$A92)*0/9)*(1+$A92+($C$18-$A92)*1/9)*(1+$A92+($C$18-$A92)*2/9)*(1+$A92+($C$18-$A92)*3/9)*(1+$A92+($C$18-$A92)*4/9)*(1+$A92+($C$18-$A92)*5/9)*(1+$A92+($C$18-$A92)*6/9)*(1+$A92+($C$18-$A92)*7/9)*(1+$A92+($C$18-$A92)*8/9)*($G$30+($C$20-$G$30)*9/10)*(1-$G$32)*(1-($G$38+(($A92+($C$18-$A92)*8/9)/F$90-$G$38)*9/10))/(1+$C$16)^($C$21+12+0.5)+$G$28*(1+$A92+($C$18-$A92)*0/9)*(1+$A92+($C$18-$A92)*1/9)*(1+$A92+($C$18-$A92)*2/9)*(1+$A92+($C$18-$A92)*3/9)*(1+$A92+($C$18-$A92)*4/9)*(1+$A92+($C$18-$A92)*5/9)*(1+$A92+($C$18-$A92)*6/9)*(1+$A92+($C$18-$A92)*7/9)*(1+$A92+($C$18-$A92)*8/9)*(1+$A92+($C$18-$A92)*9/9)*($G$30+($C$20-$G$30)*10/10)*(1-$G$32)*(1-($G$38+(($A92+($C$18-$A92)*9/9)/F$90-$G$38)*10/10))/(1+$C$16)^($C$21+13+0.5)+$G$28*(1+$A92+($C$18-$A92)*0/9)*(1+$A92+($C$18-$A92)*1/9)*(1+$A92+($C$18-$A92)*2/9)*(1+$A92+($C$18-$A92)*3/9)*(1+$A92+($C$18-$A92)*4/9)*(1+$A92+($C$18-$A92)*5/9)*(1+$A92+($C$18-$A92)*6/9)*(1+$A92+($C$18-$A92)*7/9)*(1+$A92+($C$18-$A92)*8/9)*(1+$A92+($C$18-$A92)*9/9)*($G$30+($C$20-$G$30)*10/10)*(1-$G$32)*(1+$C$18)*(1-$C$18/F$90)/($C$16-$C$18)/(1+$C$16)^($C$21+13+0.5))*(1-$C$61)+($C$55+$C$56+$C$57-$C$58-$C$60))/$C$6 -> 28.916823 | G92: =(($C$49+$G$28*(1+$A92+($C$18-$A92)*0/9)*($G$30+($C$20-$G$30)*1/10)*(1-$G$32)*(1-($G$38+(($A92+($C$18-$A92)*0/9)/G$90-$G$38)*1/10))/(1+$C$16)^($C$21+4+0.5)+$G$28*(1+$A92+($C$18-$A92)*0/9)*(1+$A92+($C$18-$A92)*1/9)*($G$30+($C$20-$G$30)*2/10)*(1-$G$32)*(1-($G$38+(($A92+($C$18-$A92)*1/9)/G$90-$G$38)*2/10))/(1+$C$16)^($C$21+5+0.5)+$G$28*(1+$A92+($C$18-$A92)*0/9)*(1+$A92+($C$18-$A92)*1/9)*(1+$A92+($C$18-$A92)*2/9)*($G$30+($C$20-$G$30)*3/10)*(1-$G$32)*(1-($G$38+(($A92+($C$18-$A92)*2/9)/G$90-$G$38)*3/10))/(1+$C$16)^($C$21+6+0.5)+$G$28*(1+$A92+($C$18-$A92)*0/9)*(1+$A92+($C$18-$A92)*1/9)*(1+$A92+($C$18-$A92)*2/9)*(1+$A92+($C$18-$A92)*3/9)*($G$30+($C$20-$G$30)*4/10)*(1-$G$32)*(1-($G$38+(($A92+($C$18-$A92)*3/9)/G$90-$G$38)*4/10))/(1+$C$16)^($C$21+7+0.5)+$G$28*(1+$A92+($C$18-$A92)*0/9)*(1+$A92+($C$18-$A92)*1/9)*(1+$A92+($C$18-$A92)*2/9)*(1+$A92+($C$18-$A92)*3/9)*(1+$A92+($C$18-$A92)*4/9)*($G$30+($C$20-$G$30)*5/10)*(1-$G$32)*(1-($G$38+(($A92+($C$18-$A92)*4/9)/G$90-$G$38)*5/10))/(1+$C$16)^($C$21+8+0.5)+$G$28*(1+$A92+($C$18-$A92)*0/9)*(1+$A92+($C$18-$A92)*1/9)*(1+$A92+($C$18-$A92)*2/9)*(1+$A92+($C$18-$A92)*3/9)*(1+$A92+($C$18-$A92)*4/9)*(1+$A92+($C$18-$A92)*5/9)*($G$30+($C$20-$G$30)*6/10)*(1-$G$32)*(1-($G$38+(($A92+($C$18-$A92)*5/9)/G$90-$G$38)*6/10))/(1+$C$16)^($C$21+9+0.5)+$G$28*(1+$A92+($C$18-$A92)*0/9)*(1+$A92+($C$18-$A92)*1/9)*(1+$A92+($C$18-$A92)*2/9)*(1+$A92+($C$18-$A92)*3/9)*(1+$A92+($C$18-$A92)*4/9)*(1+$A92+($C$18-$A92)*5/9)*(1+$A92+($C$18-$A92)*6/9)*($G$30+($C$20-$G$30)*7/10)*(1-$G$32)*(1-($G$38+(($A92+($C$18-$A92)*6/9)/G$90-$G$38)*7/10))/(1+$C$16)^($C$21+10+0.5)+$G$28*(1+$A92+($C$18-$A92)*0/9)*(1+$A92+($C$18-$A92)*1/9)*(1+$A92+($C$18-$A92)*2/9)*(1+$A92+($C$18-$A92)*3/9)*(1+$A92+($C$18-$A92)*4/9)*(1+$A92+($C$18-$A92)*5/9)*(1+$A92+($C$18-$A92)*6/9)*(1+$A92+($C$18-$A92)*7/9)*($G$30+($C$20-$G$30)*8/10)*(1-$G$32)*(1-($G$38+(($A92+($C$18-$A92)*7/9)/G$90-$G$38)*8/10))/(1+$C$16)^($C$21+11+0.5)+$G$28*(1+$A92+($C$18-$A92)*0/9)*(1+$A92+($C$18-$A92)*1/9)*(1+$A92+($C$18-$A92)*2/9)*(1+$A92+($C$18-$A92)*3/9)*(1+$A92+($C$18-$A92)*4/9)*(1+$A92+($C$18-$A92)*5/9)*(1+$A92+($C$18-$A92)*6/9)*(1+$A92+($C$18-$A92)*7/9)*(1+$A92+($C$18-$A92)*8/9)*($G$30+($C$20-$G$30)*9/10)*(1-$G$32)*(1-($G$38+(($A92+($C$18-$A92)*8/9)/G$90-$G$38)*9/10))/(1+$C$16)^($C$21+12+0.5)+$G$28*(1+$A92+($C$18-$A92)*0/9)*(1+$A92+($C$18-$A92)*1/9)*(1+$A92+($C$18-$A92)*2/9)*(1+$A92+($C$18-$A92)*3/9)*(1+$A92+($C$18-$A92)*4/9)*(1+$A92+($C$18-$A92)*5/9)*(1+$A92+($C$18-$A92)*6/9)*(1+$A92+($C$18-$A92)*7/9)*(1+$A92+($C$18-$A92)*8/9)*(1+$A92+($C$18-$A92)*9/9)*($G$30+($C$20-$G$30)*10/10)*(1-$G$32)*(1-($G$38+(($A92+($C$18-$A92)*9/9)/G$90-$G$38)*10/10))/(1+$C$16)^($C$21+13+0.5)+$G$28*(1+$A92+($C$18-$A92)*0/9)*(1+$A92+($C$18-$A92)*1/9)*(1+$A92+($C$18-$A92)*2/9)*(1+$A92+($C$18-$A92)*3/9)*(1+$A92+($C$18-$A92)*4/9)*(1+$A92+($C$18-$A92)*5/9)*(1+$A92+($C$18-$A92)*6/9)*(1+$A92+($C$18-$A92)*7/9)*(1+$A92+($C$18-$A92)*8/9)*(1+$A92+($C$18-$A92)*9/9)*($G$30+($C$20-$G$30)*10/10)*(1-$G$32)*(1+$C$18)*(1-$C$18/G$90)/($C$16-$C$18)/(1+$C$16)^($C$21+13+0.5))*(1-$C$61)+($C$55+$C$56+$C$57-$C$58-$C$60))/$C$6 -> 29.688087
A93: =$C$17+(0) -> 0.10865911 | C93: =(($C$49+$G$28*(1+$A93+($C$18-$A93)*0/9)*($G$30+($C$20-$G$30)*1/10)*(1-$G$32)*(1-($G$38+(($A93+($C$18-$A93)*0/9)/C$90-$G$38)*1/10))/(1+$C$16)^($C$21+4+0.5)+$G$28*(1+$A93+($C$18-$A93)*0/9)*(1+$A93+($C$18-$A93)*1/9)*($G$30+($C$20-$G$30)*2/10)*(1-$G$32)*(1-($G$38+(($A93+($C$18-$A93)*1/9)/C$90-$G$38)*2/10))/(1+$C$16)^($C$21+5+0.5)+$G$28*(1+$A93+($C$18-$A93)*0/9)*(1+$A93+($C$18-$A93)*1/9)*(1+$A93+($C$18-$A93)*2/9)*($G$30+($C$20-$G$30)*3/10)*(1-$G$32)*(1-($G$38+(($A93+($C$18-$A93)*2/9)/C$90-$G$38)*3/10))/(1+$C$16)^($C$21+6+0.5)+$G$28*(1+$A93+($C$18-$A93)*0/9)*(1+$A93+($C$18-$A93)*1/9)*(1+$A93+($C$18-$A93)*2/9)*(1+$A93+($C$18-$A93)*3/9)*($G$30+($C$20-$G$30)*4/10)*(1-$G$32)*(1-($G$38+(($A93+($C$18-$A93)*3/9)/C$90-$G$38)*4/10))/(1+$C$16)^($C$21+7+0.5)+$G$28*(1+$A93+($C$18-$A93)*0/9)*(1+$A93+($C$18-$A93)*1/9)*(1+$A93+($C$18-$A93)*2/9)*(1+$A93+($C$18-$A93)*3/9)*(1+$A93+($C$18-$A93)*4/9)*($G$30+($C$20-$G$30)*5/10)*(1-$G$32)*(1-($G$38+(($A93+($C$18-$A93)*4/9)/C$90-$G$38)*5/10))/(1+$C$16)^($C$21+8+0.5)+$G$28*(1+$A93+($C$18-$A93)*0/9)*(1+$A93+($C$18-$A93)*1/9)*(1+$A93+($C$18-$A93)*2/9)*(1+$A93+($C$18-$A93)*3/9)*(1+$A93+($C$18-$A93)*4/9)*(1+$A93+($C$18-$A93)*5/9)*($G$30+($C$20-$G$30)*6/10)*(1-$G$32)*(1-($G$38+(($A93+($C$18-$A93)*5/9)/C$90-$G$38)*6/10))/(1+$C$16)^($C$21+9+0.5)+$G$28*(1+$A93+($C$18-$A93)*0/9)*(1+$A93+($C$18-$A93)*1/9)*(1+$A93+($C$18-$A93)*2/9)*(1+$A93+($C$18-$A93)*3/9)*(1+$A93+($C$18-$A93)*4/9)*(1+$A93+($C$18-$A93)*5/9)*(1+$A93+($C$18-$A93)*6/9)*($G$30+($C$20-$G$30)*7/10)*(1-$G$32)*(1-($G$38+(($A93+($C$18-$A93)*6/9)/C$90-$G$38)*7/10))/(1+$C$16)^($C$21+10+0.5)+$G$28*(1+$A93+($C$18-$A93)*0/9)*(1+$A93+($C$18-$A93)*1/9)*(1+$A93+($C$18-$A93)*2/9)*(1+$A93+($C$18-$A93)*3/9)*(1+$A93+($C$18-$A93)*4/9)*(1+$A93+($C$18-$A93)*5/9)*(1+$A93+($C$18-$A93)*6/9)*(1+$A93+($C$18-$A93)*7/9)*($G$30+($C$20-$G$30)*8/10)*(1-$G$32)*(1-($G$38+(($A93+($C$18-$A93)*7/9)/C$90-$G$38)*8/10))/(1+$C$16)^($C$21+11+0.5)+$G$28*(1+$A93+($C$18-$A93)*0/9)*(1+$A93+($C$18-$A93)*1/9)*(1+$A93+($C$18-$A93)*2/9)*(1+$A93+($C$18-$A93)*3/9)*(1+$A93+($C$18-$A93)*4/9)*(1+$A93+($C$18-$A93)*5/9)*(1+$A93+($C$18-$A93)*6/9)*(1+$A93+($C$18-$A93)*7/9)*(1+$A93+($C$18-$A93)*8/9)*($G$30+($C$20-$G$30)*9/10)*(1-$G$32)*(1-($G$38+(($A93+($C$18-$A93)*8/9)/C$90-$G$38)*9/10))/(1+$C$16)^($C$21+12+0.5)+$G$28*(1+$A93+($C$18-$A93)*0/9)*(1+$A93+($C$18-$A93)*1/9)*(1+$A93+($C$18-$A93)*2/9)*(1+$A93+($C$18-$A93)*3/9)*(1+$A93+($C$18-$A93)*4/9)*(1+$A93+($C$18-$A93)*5/9)*(1+$A93+($C$18-$A93)*6/9)*(1+$A93+($C$18-$A93)*7/9)*(1+$A93+($C$18-$A93)*8/9)*(1+$A93+($C$18-$A93)*9/9)*($G$30+($C$20-$G$30)*10/10)*(1-$G$32)*(1-($G$38+(($A93+($C$18-$A93)*9/9)/C$90-$G$38)*10/10))/(1+$C$16)^($C$21+13+0.5)+$G$28*(1+$A93+($C$18-$A93)*0/9)*(1+$A93+($C$18-$A93)*1/9)*(1+$A93+($C$18-$A93)*2/9)*(1+$A93+($C$18-$A93)*3/9)*(1+$A93+($C$18-$A93)*4/9)*(1+$A93+($C$18-$A93)*5/9)*(1+$A93+($C$18-$A93)*6/9)*(1+$A93+($C$18-$A93)*7/9)*(1+$A93+($C$18-$A93)*8/9)*(1+$A93+($C$18-$A93)*9/9)*($G$30+($C$20-$G$30)*10/10)*(1-$G$32)*(1+$C$18)*(1-$C$18/C$90)/($C$16-$C$18)/(1+$C$16)^($C$21+13+0.5))*(1-$C$61)+($C$55+$C$56+$C$57-$C$58-$C$60))/$C$6 -> 26.730017 | D93: =(($C$49+$G$28*(1+$A93+($C$18-$A93)*0/9)*($G$30+($C$20-$G$30)*1/10)*(1-$G$32)*(1-($G$38+(($A93+($C$18-$A93)*0/9)/D$90-$G$38)*1/10))/(1+$C$16)^($C$21+4+0.5)+$G$28*(1+$A93+($C$18-$A93)*0/9)*(1+$A93+($C$18-$A93)*1/9)*($G$30+($C$20-$G$30)*2/10)*(1-$G$32)*(1-($G$38+(($A93+($C$18-$A93)*1/9)/D$90-$G$38)*2/10))/(1+$C$16)^($C$21+5+0.5)+$G$28*(1+$A93+($C$18-$A93)*0/9)*(1+$A93+($C$18-$A93)*1/9)*(1+$A93+($C$18-$A93)*2/9)*($G$30+($C$20-$G$30)*3/10)*(1-$G$32)*(1-($G$38+(($A93+($C$18-$A93)*2/9)/D$90-$G$38)*3/10))/(1+$C$16)^($C$21+6+0.5)+$G$28*(1+$A93+($C$18-$A93)*0/9)*(1+$A93+($C$18-$A93)*1/9)*(1+$A93+($C$18-$A93)*2/9)*(1+$A93+($C$18-$A93)*3/9)*($G$30+($C$20-$G$30)*4/10)*(1-$G$32)*(1-($G$38+(($A93+($C$18-$A93)*3/9)/D$90-$G$38)*4/10))/(1+$C$16)^($C$21+7+0.5)+$G$28*(1+$A93+($C$18-$A93)*0/9)*(1+$A93+($C$18-$A93)*1/9)*(1+$A93+($C$18-$A93)*2/9)*(1+$A93+($C$18-$A93)*3/9)*(1+$A93+($C$18-$A93)*4/9)*($G$30+($C$20-$G$30)*5/10)*(1-$G$32)*(1-($G$38+(($A93+($C$18-$A93)*4/9)/D$90-$G$38)*5/10))/(1+$C$16)^($C$21+8+0.5)+$G$28*(1+$A93+($C$18-$A93)*0/9)*(1+$A93+($C$18-$A93)*1/9)*(1+$A93+($C$18-$A93)*2/9)*(1+$A93+($C$18-$A93)*3/9)*(1+$A93+($C$18-$A93)*4/9)*(1+$A93+($C$18-$A93)*5/9)*($G$30+($C$20-$G$30)*6/10)*(1-$G$32)*(1-($G$38+(($A93+($C$18-$A93)*5/9)/D$90-$G$38)*6/10))/(1+$C$16)^($C$21+9+0.5)+$G$28*(1+$A93+($C$18-$A93)*0/9)*(1+$A93+($C$18-$A93)*1/9)*(1+$A93+($C$18-$A93)*2/9)*(1+$A93+($C$18-$A93)*3/9)*(1+$A93+($C$18-$A93)*4/9)*(1+$A93+($C$18-$A93)*5/9)*(1+$A93+($C$18-$A93)*6/9)*($G$30+($C$20-$G$30)*7/10)*(1-$G$32)*(1-($G$38+(($A93+($C$18-$A93)*6/9)/D$90-$G$38)*7/10))/(1+$C$16)^($C$21+10+0.5)+$G$28*(1+$A93+($C$18-$A93)*0/9)*(1+$A93+($C$18-$A93)*1/9)*(1+$A93+($C$18-$A93)*2/9)*(1+$A93+($C$18-$A93)*3/9)*(1+$A93+($C$18-$A93)*4/9)*(1+$A93+($C$18-$A93)*5/9)*(1+$A93+($C$18-$A93)*6/9)*(1+$A93+($C$18-$A93)*7/9)*($G$30+($C$20-$G$30)*8/10)*(1-$G$32)*(1-($G$38+(($A93+($C$18-$A93)*7/9)/D$90-$G$38)*8/10))/(1+$C$16)^($C$21+11+0.5)+$G$28*(1+$A93+($C$18-$A93)*0/9)*(1+$A93+($C$18-$A93)*1/9)*(1+$A93+($C$18-$A93)*2/9)*(1+$A93+($C$18-$A93)*3/9)*(1+$A93+($C$18-$A93)*4/9)*(1+$A93+($C$18-$A93)*5/9)*(1+$A93+($C$18-$A93)*6/9)*(1+$A93+($C$18-$A93)*7/9)*(1+$A93+($C$18-$A93)*8/9)*($G$30+($C$20-$G$30)*9/10)*(1-$G$32)*(1-($G$38+(($A93+($C$18-$A93)*8/9)/D$90-$G$38)*9/10))/(1+$C$16)^($C$21+12+0.5)+$G$28*(1+$A93+($C$18-$A93)*0/9)*(1+$A93+($C$18-$A93)*1/9)*(1+$A93+($C$18-$A93)*2/9)*(1+$A93+($C$18-$A93)*3/9)*(1+$A93+($C$18-$A93)*4/9)*(1+$A93+($C$18-$A93)*5/9)*(1+$A93+($C$18-$A93)*6/9)*(1+$A93+($C$18-$A93)*7/9)*(1+$A93+($C$18-$A93)*8/9)*(1+$A93+($C$18-$A93)*9/9)*($G$30+($C$20-$G$30)*10/10)*(1-$G$32)*(1-($G$38+(($A93+($C$18-$A93)*9/9)/D$90-$G$38)*10/10))/(1+$C$16)^($C$21+13+0.5)+$G$28*(1+$A93+($C$18-$A93)*0/9)*(1+$A93+($C$18-$A93)*1/9)*(1+$A93+($C$18-$A93)*2/9)*(1+$A93+($C$18-$A93)*3/9)*(1+$A93+($C$18-$A93)*4/9)*(1+$A93+($C$18-$A93)*5/9)*(1+$A93+($C$18-$A93)*6/9)*(1+$A93+($C$18-$A93)*7/9)*(1+$A93+($C$18-$A93)*8/9)*(1+$A93+($C$18-$A93)*9/9)*($G$30+($C$20-$G$30)*10/10)*(1-$G$32)*(1+$C$18)*(1-$C$18/D$90)/($C$16-$C$18)/(1+$C$16)^($C$21+13+0.5))*(1-$C$61)+($C$55+$C$56+$C$57-$C$58-$C$60))/$C$6 -> 28.207853 | E93: =(($C$49+$G$28*(1+$A93+($C$18-$A93)*0/9)*($G$30+($C$20-$G$30)*1/10)*(1-$G$32)*(1-($G$38+(($A93+($C$18-$A93)*0/9)/E$90-$G$38)*1/10))/(1+$C$16)^($C$21+4+0.5)+$G$28*(1+$A93+($C$18-$A93)*0/9)*(1+$A93+($C$18-$A93)*1/9)*($G$30+($C$20-$G$30)*2/10)*(1-$G$32)*(1-($G$38+(($A93+($C$18-$A93)*1/9)/E$90-$G$38)*2/10))/(1+$C$16)^($C$21+5+0.5)+$G$28*(1+$A93+($C$18-$A93)*0/9)*(1+$A93+($C$18-$A93)*1/9)*(1+$A93+($C$18-$A93)*2/9)*($G$30+($C$20-$G$30)*3/10)*(1-$G$32)*(1-($G$38+(($A93+($C$18-$A93)*2/9)/E$90-$G$38)*3/10))/(1+$C$16)^($C$21+6+0.5)+$G$28*(1+$A93+($C$18-$A93)*0/9)*(1+$A93+($C$18-$A93)*1/9)*(1+$A93+($C$18-$A93)*2/9)*(1+$A93+($C$18-$A93)*3/9)*($G$30+($C$20-$G$30)*4/10)*(1-$G$32)*(1-($G$38+(($A93+($C$18-$A93)*3/9)/E$90-$G$38)*4/10))/(1+$C$16)^($C$21+7+0.5)+$G$28*(1+$A93+($C$18-$A93)*0/9)*(1+$A93+($C$18-$A93)*1/9)*(1+$A93+($C$18-$A93)*2/9)*(1+$A93+($C$18-$A93)*3/9)*(1+$A93+($C$18-$A93)*4/9)*($G$30+($C$20-$G$30)*5/10)*(1-$G$32)*(1-($G$38+(($A93+($C$18-$A93)*4/9)/E$90-$G$38)*5/10))/(1+$C$16)^($C$21+8+0.5)+$G$28*(1+$A93+($C$18-$A93)*0/9)*(1+$A93+($C$18-$A93)*1/9)*(1+$A93+($C$18-$A93)*2/9)*(1+$A93+($C$18-$A93)*3/9)*(1+$A93+($C$18-$A93)*4/9)*(1+$A93+($C$18-$A93)*5/9)*($G$30+($C$20-$G$30)*6/10)*(1-$G$32)*(1-($G$38+(($A93+($C$18-$A93)*5/9)/E$90-$G$38)*6/10))/(1+$C$16)^($C$21+9+0.5)+$G$28*(1+$A93+($C$18-$A93)*0/9)*(1+$A93+($C$18-$A93)*1/9)*(1+$A93+($C$18-$A93)*2/9)*(1+$A93+($C$18-$A93)*3/9)*(1+$A93+($C$18-$A93)*4/9)*(1+$A93+($C$18-$A93)*5/9)*(1+$A93+($C$18-$A93)*6/9)*($G$30+($C$20-$G$30)*7/10)*(1-$G$32)*(1-($G$38+(($A93+($C$18-$A93)*6/9)/E$90-$G$38)*7/10))/(1+$C$16)^($C$21+10+0.5)+$G$28*(1+$A93+($C$18-$A93)*0/9)*(1+$A93+($C$18-$A93)*1/9)*(1+$A93+($C$18-$A93)*2/9)*(1+$A93+($C$18-$A93)*3/9)*(1+$A93+($C$18-$A93)*4/9)*(1+$A93+($C$18-$A93)*5/9)*(1+$A93+($C$18-$A93)*6/9)*(1+$A93+($C$18-$A93)*7/9)*($G$30+($C$20-$G$30)*8/10)*(1-$G$32)*(1-($G$38+(($A93+($C$18-$A93)*7/9)/E$90-$G$38)*8/10))/(1+$C$16)^($C$21+11+0.5)+$G$28*(1+$A93+($C$18-$A93)*0/9)*(1+$A93+($C$18-$A93)*1/9)*(1+$A93+($C$18-$A93)*2/9)*(1+$A93+($C$18-$A93)*3/9)*(1+$A93+($C$18-$A93)*4/9)*(1+$A93+($C$18-$A93)*5/9)*(1+$A93+($C$18-$A93)*6/9)*(1+$A93+($C$18-$A93)*7/9)*(1+$A93+($C$18-$A93)*8/9)*($G$30+($C$20-$G$30)*9/10)*(1-$G$32)*(1-($G$38+(($A93+($C$18-$A93)*8/9)/E$90-$G$38)*9/10))/(1+$C$16)^($C$21+12+0.5)+$G$28*(1+$A93+($C$18-$A93)*0/9)*(1+$A93+($C$18-$A93)*1/9)*(1+$A93+($C$18-$A93)*2/9)*(1+$A93+($C$18-$A93)*3/9)*(1+$A93+($C$18-$A93)*4/9)*(1+$A93+($C$18-$A93)*5/9)*(1+$A93+($C$18-$A93)*6/9)*(1+$A93+($C$18-$A93)*7/9)*(1+$A93+($C$18-$A93)*8/9)*(1+$A93+($C$18-$A93)*9/9)*($G$30+($C$20-$G$30)*10/10)*(1-$G$32)*(1-($G$38+(($A93+($C$18-$A93)*9/9)/E$90-$G$38)*10/10))/(1+$C$16)^($C$21+13+0.5)+$G$28*(1+$A93+($C$18-$A93)*0/9)*(1+$A93+($C$18-$A93)*1/9)*(1+$A93+($C$18-$A93)*2/9)*(1+$A93+($C$18-$A93)*3/9)*(1+$A93+($C$18-$A93)*4/9)*(1+$A93+($C$18-$A93)*5/9)*(1+$A93+($C$18-$A93)*6/9)*(1+$A93+($C$18-$A93)*7/9)*(1+$A93+($C$18-$A93)*8/9)*(1+$A93+($C$18-$A93)*9/9)*($G$30+($C$20-$G$30)*10/10)*(1-$G$32)*(1+$C$18)*(1-$C$18/E$90)/($C$16-$C$18)/(1+$C$16)^($C$21+13+0.5))*(1-$C$61)+($C$55+$C$56+$C$57-$C$58-$C$60))/$C$6 -> 29.685689 | F93: =(($C$49+$G$28*(1+$A93+($C$18-$A93)*0/9)*($G$30+($C$20-$G$30)*1/10)*(1-$G$32)*(1-($G$38+(($A93+($C$18-$A93)*0/9)/F$90-$G$38)*1/10))/(1+$C$16)^($C$21+4+0.5)+$G$28*(1+$A93+($C$18-$A93)*0/9)*(1+$A93+($C$18-$A93)*1/9)*($G$30+($C$20-$G$30)*2/10)*(1-$G$32)*(1-($G$38+(($A93+($C$18-$A93)*1/9)/F$90-$G$38)*2/10))/(1+$C$16)^($C$21+5+0.5)+$G$28*(1+$A93+($C$18-$A93)*0/9)*(1+$A93+($C$18-$A93)*1/9)*(1+$A93+($C$18-$A93)*2/9)*($G$30+($C$20-$G$30)*3/10)*(1-$G$32)*(1-($G$38+(($A93+($C$18-$A93)*2/9)/F$90-$G$38)*3/10))/(1+$C$16)^($C$21+6+0.5)+$G$28*(1+$A93+($C$18-$A93)*0/9)*(1+$A93+($C$18-$A93)*1/9)*(1+$A93+($C$18-$A93)*2/9)*(1+$A93+($C$18-$A93)*3/9)*($G$30+($C$20-$G$30)*4/10)*(1-$G$32)*(1-($G$38+(($A93+($C$18-$A93)*3/9)/F$90-$G$38)*4/10))/(1+$C$16)^($C$21+7+0.5)+$G$28*(1+$A93+($C$18-$A93)*0/9)*(1+$A93+($C$18-$A93)*1/9)*(1+$A93+($C$18-$A93)*2/9)*(1+$A93+($C$18-$A93)*3/9)*(1+$A93+($C$18-$A93)*4/9)*($G$30+($C$20-$G$30)*5/10)*(1-$G$32)*(1-($G$38+(($A93+($C$18-$A93)*4/9)/F$90-$G$38)*5/10))/(1+$C$16)^($C$21+8+0.5)+$G$28*(1+$A93+($C$18-$A93)*0/9)*(1+$A93+($C$18-$A93)*1/9)*(1+$A93+($C$18-$A93)*2/9)*(1+$A93+($C$18-$A93)*3/9)*(1+$A93+($C$18-$A93)*4/9)*(1+$A93+($C$18-$A93)*5/9)*($G$30+($C$20-$G$30)*6/10)*(1-$G$32)*(1-($G$38+(($A93+($C$18-$A93)*5/9)/F$90-$G$38)*6/10))/(1+$C$16)^($C$21+9+0.5)+$G$28*(1+$A93+($C$18-$A93)*0/9)*(1+$A93+($C$18-$A93)*1/9)*(1+$A93+($C$18-$A93)*2/9)*(1+$A93+($C$18-$A93)*3/9)*(1+$A93+($C$18-$A93)*4/9)*(1+$A93+($C$18-$A93)*5/9)*(1+$A93+($C$18-$A93)*6/9)*($G$30+($C$20-$G$30)*7/10)*(1-$G$32)*(1-($G$38+(($A93+($C$18-$A93)*6/9)/F$90-$G$38)*7/10))/(1+$C$16)^($C$21+10+0.5)+$G$28*(1+$A93+($C$18-$A93)*0/9)*(1+$A93+($C$18-$A93)*1/9)*(1+$A93+($C$18-$A93)*2/9)*(1+$A93+($C$18-$A93)*3/9)*(1+$A93+($C$18-$A93)*4/9)*(1+$A93+($C$18-$A93)*5/9)*(1+$A93+($C$18-$A93)*6/9)*(1+$A93+($C$18-$A93)*7/9)*($G$30+($C$20-$G$30)*8/10)*(1-$G$32)*(1-($G$38+(($A93+($C$18-$A93)*7/9)/F$90-$G$38)*8/10))/(1+$C$16)^($C$21+11+0.5)+$G$28*(1+$A93+($C$18-$A93)*0/9)*(1+$A93+($C$18-$A93)*1/9)*(1+$A93+($C$18-$A93)*2/9)*(1+$A93+($C$18-$A93)*3/9)*(1+$A93+($C$18-$A93)*4/9)*(1+$A93+($C$18-$A93)*5/9)*(1+$A93+($C$18-$A93)*6/9)*(1+$A93+($C$18-$A93)*7/9)*(1+$A93+($C$18-$A93)*8/9)*($G$30+($C$20-$G$30)*9/10)*(1-$G$32)*(1-($G$38+(($A93+($C$18-$A93)*8/9)/F$90-$G$38)*9/10))/(1+$C$16)^($C$21+12+0.5)+$G$28*(1+$A93+($C$18-$A93)*0/9)*(1+$A93+($C$18-$A93)*1/9)*(1+$A93+($C$18-$A93)*2/9)*(1+$A93+($C$18-$A93)*3/9)*(1+$A93+($C$18-$A93)*4/9)*(1+$A93+($C$18-$A93)*5/9)*(1+$A93+($C$18-$A93)*6/9)*(1+$A93+($C$18-$A93)*7/9)*(1+$A93+($C$18-$A93)*8/9)*(1+$A93+($C$18-$A93)*9/9)*($G$30+($C$20-$G$30)*10/10)*(1-$G$32)*(1-($G$38+(($A93+($C$18-$A93)*9/9)/F$90-$G$38)*10/10))/(1+$C$16)^($C$21+13+0.5)+$G$28*(1+$A93+($C$18-$A93)*0/9)*(1+$A93+($C$18-$A93)*1/9)*(1+$A93+($C$18-$A93)*2/9)*(1+$A93+($C$18-$A93)*3/9)*(1+$A93+($C$18-$A93)*4/9)*(1+$A93+($C$18-$A93)*5/9)*(1+$A93+($C$18-$A93)*6/9)*(1+$A93+($C$18-$A93)*7/9)*(1+$A93+($C$18-$A93)*8/9)*(1+$A93+($C$18-$A93)*9/9)*($G$30+($C$20-$G$30)*10/10)*(1-$G$32)*(1+$C$18)*(1-$C$18/F$90)/($C$16-$C$18)/(1+$C$16)^($C$21+13+0.5))*(1-$C$61)+($C$55+$C$56+$C$57-$C$58-$C$60))/$C$6 -> 30.670913 | G93: =(($C$49+$G$28*(1+$A93+($C$18-$A93)*0/9)*($G$30+($C$20-$G$30)*1/10)*(1-$G$32)*(1-($G$38+(($A93+($C$18-$A93)*0/9)/G$90-$G$38)*1/10))/(1+$C$16)^($C$21+4+0.5)+$G$28*(1+$A93+($C$18-$A93)*0/9)*(1+$A93+($C$18-$A93)*1/9)*($G$30+($C$20-$G$30)*2/10)*(1-$G$32)*(1-($G$38+(($A93+($C$18-$A93)*1/9)/G$90-$G$38)*2/10))/(1+$C$16)^($C$21+5+0.5)+$G$28*(1+$A93+($C$18-$A93)*0/9)*(1+$A93+($C$18-$A93)*1/9)*(1+$A93+($C$18-$A93)*2/9)*($G$30+($C$20-$G$30)*3/10)*(1-$G$32)*(1-($G$38+(($A93+($C$18-$A93)*2/9)/G$90-$G$38)*3/10))/(1+$C$16)^($C$21+6+0.5)+$G$28*(1+$A93+($C$18-$A93)*0/9)*(1+$A93+($C$18-$A93)*1/9)*(1+$A93+($C$18-$A93)*2/9)*(1+$A93+($C$18-$A93)*3/9)*($G$30+($C$20-$G$30)*4/10)*(1-$G$32)*(1-($G$38+(($A93+($C$18-$A93)*3/9)/G$90-$G$38)*4/10))/(1+$C$16)^($C$21+7+0.5)+$G$28*(1+$A93+($C$18-$A93)*0/9)*(1+$A93+($C$18-$A93)*1/9)*(1+$A93+($C$18-$A93)*2/9)*(1+$A93+($C$18-$A93)*3/9)*(1+$A93+($C$18-$A93)*4/9)*($G$30+($C$20-$G$30)*5/10)*(1-$G$32)*(1-($G$38+(($A93+($C$18-$A93)*4/9)/G$90-$G$38)*5/10))/(1+$C$16)^($C$21+8+0.5)+$G$28*(1+$A93+($C$18-$A93)*0/9)*(1+$A93+($C$18-$A93)*1/9)*(1+$A93+($C$18-$A93)*2/9)*(1+$A93+($C$18-$A93)*3/9)*(1+$A93+($C$18-$A93)*4/9)*(1+$A93+($C$18-$A93)*5/9)*($G$30+($C$20-$G$30)*6/10)*(1-$G$32)*(1-($G$38+(($A93+($C$18-$A93)*5/9)/G$90-$G$38)*6/10))/(1+$C$16)^($C$21+9+0.5)+$G$28*(1+$A93+($C$18-$A93)*0/9)*(1+$A93+($C$18-$A93)*1/9)*(1+$A93+($C$18-$A93)*2/9)*(1+$A93+($C$18-$A93)*3/9)*(1+$A93+($C$18-$A93)*4/9)*(1+$A93+($C$18-$A93)*5/9)*(1+$A93+($C$18-$A93)*6/9)*($G$30+($C$20-$G$30)*7/10)*(1-$G$32)*(1-($G$38+(($A93+($C$18-$A93)*6/9)/G$90-$G$38)*7/10))/(1+$C$16)^($C$21+10+0.5)+$G$28*(1+$A93+($C$18-$A93)*0/9)*(1+$A93+($C$18-$A93)*1/9)*(1+$A93+($C$18-$A93)*2/9)*(1+$A93+($C$18-$A93)*3/9)*(1+$A93+($C$18-$A93)*4/9)*(1+$A93+($C$18-$A93)*5/9)*(1+$A93+($C$18-$A93)*6/9)*(1+$A93+($C$18-$A93)*7/9)*($G$30+($C$20-$G$30)*8/10)*(1-$G$32)*(1-($G$38+(($A93+($C$18-$A93)*7/9)/G$90-$G$38)*8/10))/(1+$C$16)^($C$21+11+0.5)+$G$28*(1+$A93+($C$18-$A93)*0/9)*(1+$A93+($C$18-$A93)*1/9)*(1+$A93+($C$18-$A93)*2/9)*(1+$A93+($C$18-$A93)*3/9)*(1+$A93+($C$18-$A93)*4/9)*(1+$A93+($C$18-$A93)*5/9)*(1+$A93+($C$18-$A93)*6/9)*(1+$A93+($C$18-$A93)*7/9)*(1+$A93+($C$18-$A93)*8/9)*($G$30+($C$20-$G$30)*9/10)*(1-$G$32)*(1-($G$38+(($A93+($C$18-$A93)*8/9)/G$90-$G$38)*9/10))/(1+$C$16)^($C$21+12+0.5)+$G$28*(1+$A93+($C$18-$A93)*0/9)*(1+$A93+($C$18-$A93)*1/9)*(1+$A93+($C$18-$A93)*2/9)*(1+$A93+($C$18-$A93)*3/9)*(1+$A93+($C$18-$A93)*4/9)*(1+$A93+($C$18-$A93)*5/9)*(1+$A93+($C$18-$A93)*6/9)*(1+$A93+($C$18-$A93)*7/9)*(1+$A93+($C$18-$A93)*8/9)*(1+$A93+($C$18-$A93)*9/9)*($G$30+($C$20-$G$30)*10/10)*(1-$G$32)*(1-($G$38+(($A93+($C$18-$A93)*9/9)/G$90-$G$38)*10/10))/(1+$C$16)^($C$21+13+0.5)+$G$28*(1+$A93+($C$18-$A93)*0/9)*(1+$A93+($C$18-$A93)*1/9)*(1+$A93+($C$18-$A93)*2/9)*(1+$A93+($C$18-$A93)*3/9)*(1+$A93+($C$18-$A93)*4/9)*(1+$A93+($C$18-$A93)*5/9)*(1+$A93+($C$18-$A93)*6/9)*(1+$A93+($C$18-$A93)*7/9)*(1+$A93+($C$18-$A93)*8/9)*(1+$A93+($C$18-$A93)*9/9)*($G$30+($C$20-$G$30)*10/10)*(1-$G$32)*(1+$C$18)*(1-$C$18/G$90)/($C$16-$C$18)/(1+$C$16)^($C$21+13+0.5))*(1-$C$61)+($C$55+$C$56+$C$57-$C$58-$C$60))/$C$6 -> 31.566571
A94: =$C$17+(0.02) -> 0.12865911 | C94: =(($C$49+$G$28*(1+$A94+($C$18-$A94)*0/9)*($G$30+($C$20-$G$30)*1/10)*(1-$G$32)*(1-($G$38+(($A94+($C$18-$A94)*0/9)/C$90-$G$38)*1/10))/(1+$C$16)^($C$21+4+0.5)+$G$28*(1+$A94+($C$18-$A94)*0/9)*(1+$A94+($C$18-$A94)*1/9)*($G$30+($C$20-$G$30)*2/10)*(1-$G$32)*(1-($G$38+(($A94+($C$18-$A94)*1/9)/C$90-$G$38)*2/10))/(1+$C$16)^($C$21+5+0.5)+$G$28*(1+$A94+($C$18-$A94)*0/9)*(1+$A94+($C$18-$A94)*1/9)*(1+$A94+($C$18-$A94)*2/9)*($G$30+($C$20-$G$30)*3/10)*(1-$G$32)*(1-($G$38+(($A94+($C$18-$A94)*2/9)/C$90-$G$38)*3/10))/(1+$C$16)^($C$21+6+0.5)+$G$28*(1+$A94+($C$18-$A94)*0/9)*(1+$A94+($C$18-$A94)*1/9)*(1+$A94+($C$18-$A94)*2/9)*(1+$A94+($C$18-$A94)*3/9)*($G$30+($C$20-$G$30)*4/10)*(1-$G$32)*(1-($G$38+(($A94+($C$18-$A94)*3/9)/C$90-$G$38)*4/10))/(1+$C$16)^($C$21+7+0.5)+$G$28*(1+$A94+($C$18-$A94)*0/9)*(1+$A94+($C$18-$A94)*1/9)*(1+$A94+($C$18-$A94)*2/9)*(1+$A94+($C$18-$A94)*3/9)*(1+$A94+($C$18-$A94)*4/9)*($G$30+($C$20-$G$30)*5/10)*(1-$G$32)*(1-($G$38+(($A94+($C$18-$A94)*4/9)/C$90-$G$38)*5/10))/(1+$C$16)^($C$21+8+0.5)+$G$28*(1+$A94+($C$18-$A94)*0/9)*(1+$A94+($C$18-$A94)*1/9)*(1+$A94+($C$18-$A94)*2/9)*(1+$A94+($C$18-$A94)*3/9)*(1+$A94+($C$18-$A94)*4/9)*(1+$A94+($C$18-$A94)*5/9)*($G$30+($C$20-$G$30)*6/10)*(1-$G$32)*(1-($G$38+(($A94+($C$18-$A94)*5/9)/C$90-$G$38)*6/10))/(1+$C$16)^($C$21+9+0.5)+$G$28*(1+$A94+($C$18-$A94)*0/9)*(1+$A94+($C$18-$A94)*1/9)*(1+$A94+($C$18-$A94)*2/9)*(1+$A94+($C$18-$A94)*3/9)*(1+$A94+($C$18-$A94)*4/9)*(1+$A94+($C$18-$A94)*5/9)*(1+$A94+($C$18-$A94)*6/9)*($G$30+($C$20-$G$30)*7/10)*(1-$G$32)*(1-($G$38+(($A94+($C$18-$A94)*6/9)/C$90-$G$38)*7/10))/(1+$C$16)^($C$21+10+0.5)+$G$28*(1+$A94+($C$18-$A94)*0/9)*(1+$A94+($C$18-$A94)*1/9)*(1+$A94+($C$18-$A94)*2/9)*(1+$A94+($C$18-$A94)*3/9)*(1+$A94+($C$18-$A94)*4/9)*(1+$A94+($C$18-$A94)*5/9)*(1+$A94+($C$18-$A94)*6/9)*(1+$A94+($C$18-$A94)*7/9)*($G$30+($C$20-$G$30)*8/10)*(1-$G$32)*(1-($G$38+(($A94+($C$18-$A94)*7/9)/C$90-$G$38)*8/10))/(1+$C$16)^($C$21+11+0.5)+$G$28*(1+$A94+($C$18-$A94)*0/9)*(1+$A94+($C$18-$A94)*1/9)*(1+$A94+($C$18-$A94)*2/9)*(1+$A94+($C$18-$A94)*3/9)*(1+$A94+($C$18-$A94)*4/9)*(1+$A94+($C$18-$A94)*5/9)*(1+$A94+($C$18-$A94)*6/9)*(1+$A94+($C$18-$A94)*7/9)*(1+$A94+($C$18-$A94)*8/9)*($G$30+($C$20-$G$30)*9/10)*(1-$G$32)*(1-($G$38+(($A94+($C$18-$A94)*8/9)/C$90-$G$38)*9/10))/(1+$C$16)^($C$21+12+0.5)+$G$28*(1+$A94+($C$18-$A94)*0/9)*(1+$A94+($C$18-$A94)*1/9)*(1+$A94+($C$18-$A94)*2/9)*(1+$A94+($C$18-$A94)*3/9)*(1+$A94+($C$18-$A94)*4/9)*(1+$A94+($C$18-$A94)*5/9)*(1+$A94+($C$18-$A94)*6/9)*(1+$A94+($C$18-$A94)*7/9)*(1+$A94+($C$18-$A94)*8/9)*(1+$A94+($C$18-$A94)*9/9)*($G$30+($C$20-$G$30)*10/10)*(1-$G$32)*(1-($G$38+(($A94+($C$18-$A94)*9/9)/C$90-$G$38)*10/10))/(1+$C$16)^($C$21+13+0.5)+$G$28*(1+$A94+($C$18-$A94)*0/9)*(1+$A94+($C$18-$A94)*1/9)*(1+$A94+($C$18-$A94)*2/9)*(1+$A94+($C$18-$A94)*3/9)*(1+$A94+($C$18-$A94)*4/9)*(1+$A94+($C$18-$A94)*5/9)*(1+$A94+($C$18-$A94)*6/9)*(1+$A94+($C$18-$A94)*7/9)*(1+$A94+($C$18-$A94)*8/9)*(1+$A94+($C$18-$A94)*9/9)*($G$30+($C$20-$G$30)*10/10)*(1-$G$32)*(1+$C$18)*(1-$C$18/C$90)/($C$16-$C$18)/(1+$C$16)^($C$21+13+0.5))*(1-$C$61)+($C$55+$C$56+$C$57-$C$58-$C$60))/$C$6 -> 27.996886 | D94: =(($C$49+$G$28*(1+$A94+($C$18-$A94)*0/9)*($G$30+($C$20-$G$30)*1/10)*(1-$G$32)*(1-($G$38+(($A94+($C$18-$A94)*0/9)/D$90-$G$38)*1/10))/(1+$C$16)^($C$21+4+0.5)+$G$28*(1+$A94+($C$18-$A94)*0/9)*(1+$A94+($C$18-$A94)*1/9)*($G$30+($C$20-$G$30)*2/10)*(1-$G$32)*(1-($G$38+(($A94+($C$18-$A94)*1/9)/D$90-$G$38)*2/10))/(1+$C$16)^($C$21+5+0.5)+$G$28*(1+$A94+($C$18-$A94)*0/9)*(1+$A94+($C$18-$A94)*1/9)*(1+$A94+($C$18-$A94)*2/9)*($G$30+($C$20-$G$30)*3/10)*(1-$G$32)*(1-($G$38+(($A94+($C$18-$A94)*2/9)/D$90-$G$38)*3/10))/(1+$C$16)^($C$21+6+0.5)+$G$28*(1+$A94+($C$18-$A94)*0/9)*(1+$A94+($C$18-$A94)*1/9)*(1+$A94+($C$18-$A94)*2/9)*(1+$A94+($C$18-$A94)*3/9)*($G$30+($C$20-$G$30)*4/10)*(1-$G$32)*(1-($G$38+(($A94+($C$18-$A94)*3/9)/D$90-$G$38)*4/10))/(1+$C$16)^($C$21+7+0.5)+$G$28*(1+$A94+($C$18-$A94)*0/9)*(1+$A94+($C$18-$A94)*1/9)*(1+$A94+($C$18-$A94)*2/9)*(1+$A94+($C$18-$A94)*3/9)*(1+$A94+($C$18-$A94)*4/9)*($G$30+($C$20-$G$30)*5/10)*(1-$G$32)*(1-($G$38+(($A94+($C$18-$A94)*4/9)/D$90-$G$38)*5/10))/(1+$C$16)^($C$21+8+0.5)+$G$28*(1+$A94+($C$18-$A94)*0/9)*(1+$A94+($C$18-$A94)*1/9)*(1+$A94+($C$18-$A94)*2/9)*(1+$A94+($C$18-$A94)*3/9)*(1+$A94+($C$18-$A94)*4/9)*(1+$A94+($C$18-$A94)*5/9)*($G$30+($C$20-$G$30)*6/10)*(1-$G$32)*(1-($G$38+(($A94+($C$18-$A94)*5/9)/D$90-$G$38)*6/10))/(1+$C$16)^($C$21+9+0.5)+$G$28*(1+$A94+($C$18-$A94)*0/9)*(1+$A94+($C$18-$A94)*1/9)*(1+$A94+($C$18-$A94)*2/9)*(1+$A94+($C$18-$A94)*3/9)*(1+$A94+($C$18-$A94)*4/9)*(1+$A94+($C$18-$A94)*5/9)*(1+$A94+($C$18-$A94)*6/9)*($G$30+($C$20-$G$30)*7/10)*(1-$G$32)*(1-($G$38+(($A94+($C$18-$A94)*6/9)/D$90-$G$38)*7/10))/(1+$C$16)^($C$21+10+0.5)+$G$28*(1+$A94+($C$18-$A94)*0/9)*(1+$A94+($C$18-$A94)*1/9)*(1+$A94+($C$18-$A94)*2/9)*(1+$A94+($C$18-$A94)*3/9)*(1+$A94+($C$18-$A94)*4/9)*(1+$A94+($C$18-$A94)*5/9)*(1+$A94+($C$18-$A94)*6/9)*(1+$A94+($C$18-$A94)*7/9)*($G$30+($C$20-$G$30)*8/10)*(1-$G$32)*(1-($G$38+(($A94+($C$18-$A94)*7/9)/D$90-$G$38)*8/10))/(1+$C$16)^($C$21+11+0.5)+$G$28*(1+$A94+($C$18-$A94)*0/9)*(1+$A94+($C$18-$A94)*1/9)*(1+$A94+($C$18-$A94)*2/9)*(1+$A94+($C$18-$A94)*3/9)*(1+$A94+($C$18-$A94)*4/9)*(1+$A94+($C$18-$A94)*5/9)*(1+$A94+($C$18-$A94)*6/9)*(1+$A94+($C$18-$A94)*7/9)*(1+$A94+($C$18-$A94)*8/9)*($G$30+($C$20-$G$30)*9/10)*(1-$G$32)*(1-($G$38+(($A94+($C$18-$A94)*8/9)/D$90-$G$38)*9/10))/(1+$C$16)^($C$21+12+0.5)+$G$28*(1+$A94+($C$18-$A94)*0/9)*(1+$A94+($C$18-$A94)*1/9)*(1+$A94+($C$18-$A94)*2/9)*(1+$A94+($C$18-$A94)*3/9)*(1+$A94+($C$18-$A94)*4/9)*(1+$A94+($C$18-$A94)*5/9)*(1+$A94+($C$18-$A94)*6/9)*(1+$A94+($C$18-$A94)*7/9)*(1+$A94+($C$18-$A94)*8/9)*(1+$A94+($C$18-$A94)*9/9)*($G$30+($C$20-$G$30)*10/10)*(1-$G$32)*(1-($G$38+(($A94+($C$18-$A94)*9/9)/D$90-$G$38)*10/10))/(1+$C$16)^($C$21+13+0.5)+$G$28*(1+$A94+($C$18-$A94)*0/9)*(1+$A94+($C$18-$A94)*1/9)*(1+$A94+($C$18-$A94)*2/9)*(1+$A94+($C$18-$A94)*3/9)*(1+$A94+($C$18-$A94)*4/9)*(1+$A94+($C$18-$A94)*5/9)*(1+$A94+($C$18-$A94)*6/9)*(1+$A94+($C$18-$A94)*7/9)*(1+$A94+($C$18-$A94)*8/9)*(1+$A94+($C$18-$A94)*9/9)*($G$30+($C$20-$G$30)*10/10)*(1-$G$32)*(1+$C$18)*(1-$C$18/D$90)/($C$16-$C$18)/(1+$C$16)^($C$21+13+0.5))*(1-$C$61)+($C$55+$C$56+$C$57-$C$58-$C$60))/$C$6 -> 29.70104 | E94: =(($C$49+$G$28*(1+$A94+($C$18-$A94)*0/9)*($G$30+($C$20-$G$30)*1/10)*(1-$G$32)*(1-($G$38+(($A94+($C$18-$A94)*0/9)/E$90-$G$38)*1/10))/(1+$C$16)^($C$21+4+0.5)+$G$28*(1+$A94+($C$18-$A94)*0/9)*(1+$A94+($C$18-$A94)*1/9)*($G$30+($C$20-$G$30)*2/10)*(1-$G$32)*(1-($G$38+(($A94+($C$18-$A94)*1/9)/E$90-$G$38)*2/10))/(1+$C$16)^($C$21+5+0.5)+$G$28*(1+$A94+($C$18-$A94)*0/9)*(1+$A94+($C$18-$A94)*1/9)*(1+$A94+($C$18-$A94)*2/9)*($G$30+($C$20-$G$30)*3/10)*(1-$G$32)*(1-($G$38+(($A94+($C$18-$A94)*2/9)/E$90-$G$38)*3/10))/(1+$C$16)^($C$21+6+0.5)+$G$28*(1+$A94+($C$18-$A94)*0/9)*(1+$A94+($C$18-$A94)*1/9)*(1+$A94+($C$18-$A94)*2/9)*(1+$A94+($C$18-$A94)*3/9)*($G$30+($C$20-$G$30)*4/10)*(1-$G$32)*(1-($G$38+(($A94+($C$18-$A94)*3/9)/E$90-$G$38)*4/10))/(1+$C$16)^($C$21+7+0.5)+$G$28*(1+$A94+($C$18-$A94)*0/9)*(1+$A94+($C$18-$A94)*1/9)*(1+$A94+($C$18-$A94)*2/9)*(1+$A94+($C$18-$A94)*3/9)*(1+$A94+($C$18-$A94)*4/9)*($G$30+($C$20-$G$30)*5/10)*(1-$G$32)*(1-($G$38+(($A94+($C$18-$A94)*4/9)/E$90-$G$38)*5/10))/(1+$C$16)^($C$21+8+0.5)+$G$28*(1+$A94+($C$18-$A94)*0/9)*(1+$A94+($C$18-$A94)*1/9)*(1+$A94+($C$18-$A94)*2/9)*(1+$A94+($C$18-$A94)*3/9)*(1+$A94+($C$18-$A94)*4/9)*(1+$A94+($C$18-$A94)*5/9)*($G$30+($C$20-$G$30)*6/10)*(1-$G$32)*(1-($G$38+(($A94+($C$18-$A94)*5/9)/E$90-$G$38)*6/10))/(1+$C$16)^($C$21+9+0.5)+$G$28*(1+$A94+($C$18-$A94)*0/9)*(1+$A94+($C$18-$A94)*1/9)*(1+$A94+($C$18-$A94)*2/9)*(1+$A94+($C$18-$A94)*3/9)*(1+$A94+($C$18-$A94)*4/9)*(1+$A94+($C$18-$A94)*5/9)*(1+$A94+($C$18-$A94)*6/9)*($G$30+($C$20-$G$30)*7/10)*(1-$G$32)*(1-($G$38+(($A94+($C$18-$A94)*6/9)/E$90-$G$38)*7/10))/(1+$C$16)^($C$21+10+0.5)+$G$28*(1+$A94+($C$18-$A94)*0/9)*(1+$A94+($C$18-$A94)*1/9)*(1+$A94+($C$18-$A94)*2/9)*(1+$A94+($C$18-$A94)*3/9)*(1+$A94+($C$18-$A94)*4/9)*(1+$A94+($C$18-$A94)*5/9)*(1+$A94+($C$18-$A94)*6/9)*(1+$A94+($C$18-$A94)*7/9)*($G$30+($C$20-$G$30)*8/10)*(1-$G$32)*(1-($G$38+(($A94+($C$18-$A94)*7/9)/E$90-$G$38)*8/10))/(1+$C$16)^($C$21+11+0.5)+$G$28*(1+$A94+($C$18-$A94)*0/9)*(1+$A94+($C$18-$A94)*1/9)*(1+$A94+($C$18-$A94)*2/9)*(1+$A94+($C$18-$A94)*3/9)*(1+$A94+($C$18-$A94)*4/9)*(1+$A94+($C$18-$A94)*5/9)*(1+$A94+($C$18-$A94)*6/9)*(1+$A94+($C$18-$A94)*7/9)*(1+$A94+($C$18-$A94)*8/9)*($G$30+($C$20-$G$30)*9/10)*(1-$G$32)*(1-($G$38+(($A94+($C$18-$A94)*8/9)/E$90-$G$38)*9/10))/(1+$C$16)^($C$21+12+0.5)+$G$28*(1+$A94+($C$18-$A94)*0/9)*(1+$A94+($C$18-$A94)*1/9)*(1+$A94+($C$18-$A94)*2/9)*(1+$A94+($C$18-$A94)*3/9)*(1+$A94+($C$18-$A94)*4/9)*(1+$A94+($C$18-$A94)*5/9)*(1+$A94+($C$18-$A94)*6/9)*(1+$A94+($C$18-$A94)*7/9)*(1+$A94+($C$18-$A94)*8/9)*(1+$A94+($C$18-$A94)*9/9)*($G$30+($C$20-$G$30)*10/10)*(1-$G$32)*(1-($G$38+(($A94+($C$18-$A94)*9/9)/E$90-$G$38)*10/10))/(1+$C$16)^($C$21+13+0.5)+$G$28*(1+$A94+($C$18-$A94)*0/9)*(1+$A94+($C$18-$A94)*1/9)*(1+$A94+($C$18-$A94)*2/9)*(1+$A94+($C$18-$A94)*3/9)*(1+$A94+($C$18-$A94)*4/9)*(1+$A94+($C$18-$A94)*5/9)*(1+$A94+($C$18-$A94)*6/9)*(1+$A94+($C$18-$A94)*7/9)*(1+$A94+($C$18-$A94)*8/9)*(1+$A94+($C$18-$A94)*9/9)*($G$30+($C$20-$G$30)*10/10)*(1-$G$32)*(1+$C$18)*(1-$C$18/E$90)/($C$16-$C$18)/(1+$C$16)^($C$21+13+0.5))*(1-$C$61)+($C$55+$C$56+$C$57-$C$58-$C$60))/$C$6 -> 31.405193 | F94: =(($C$49+$G$28*(1+$A94+($C$18-$A94)*0/9)*($G$30+($C$20-$G$30)*1/10)*(1-$G$32)*(1-($G$38+(($A94+($C$18-$A94)*0/9)/F$90-$G$38)*1/10))/(1+$C$16)^($C$21+4+0.5)+$G$28*(1+$A94+($C$18-$A94)*0/9)*(1+$A94+($C$18-$A94)*1/9)*($G$30+($C$20-$G$30)*2/10)*(1-$G$32)*(1-($G$38+(($A94+($C$18-$A94)*1/9)/F$90-$G$38)*2/10))/(1+$C$16)^($C$21+5+0.5)+$G$28*(1+$A94+($C$18-$A94)*0/9)*(1+$A94+($C$18-$A94)*1/9)*(1+$A94+($C$18-$A94)*2/9)*($G$30+($C$20-$G$30)*3/10)*(1-$G$32)*(1-($G$38+(($A94+($C$18-$A94)*2/9)/F$90-$G$38)*3/10))/(1+$C$16)^($C$21+6+0.5)+$G$28*(1+$A94+($C$18-$A94)*0/9)*(1+$A94+($C$18-$A94)*1/9)*(1+$A94+($C$18-$A94)*2/9)*(1+$A94+($C$18-$A94)*3/9)*($G$30+($C$20-$G$30)*4/10)*(1-$G$32)*(1-($G$38+(($A94+($C$18-$A94)*3/9)/F$90-$G$38)*4/10))/(1+$C$16)^($C$21+7+0.5)+$G$28*(1+$A94+($C$18-$A94)*0/9)*(1+$A94+($C$18-$A94)*1/9)*(1+$A94+($C$18-$A94)*2/9)*(1+$A94+($C$18-$A94)*3/9)*(1+$A94+($C$18-$A94)*4/9)*($G$30+($C$20-$G$30)*5/10)*(1-$G$32)*(1-($G$38+(($A94+($C$18-$A94)*4/9)/F$90-$G$38)*5/10))/(1+$C$16)^($C$21+8+0.5)+$G$28*(1+$A94+($C$18-$A94)*0/9)*(1+$A94+($C$18-$A94)*1/9)*(1+$A94+($C$18-$A94)*2/9)*(1+$A94+($C$18-$A94)*3/9)*(1+$A94+($C$18-$A94)*4/9)*(1+$A94+($C$18-$A94)*5/9)*($G$30+($C$20-$G$30)*6/10)*(1-$G$32)*(1-($G$38+(($A94+($C$18-$A94)*5/9)/F$90-$G$38)*6/10))/(1+$C$16)^($C$21+9+0.5)+$G$28*(1+$A94+($C$18-$A94)*0/9)*(1+$A94+($C$18-$A94)*1/9)*(1+$A94+($C$18-$A94)*2/9)*(1+$A94+($C$18-$A94)*3/9)*(1+$A94+($C$18-$A94)*4/9)*(1+$A94+($C$18-$A94)*5/9)*(1+$A94+($C$18-$A94)*6/9)*($G$30+($C$20-$G$30)*7/10)*(1-$G$32)*(1-($G$38+(($A94+($C$18-$A94)*6/9)/F$90-$G$38)*7/10))/(1+$C$16)^($C$21+10+0.5)+$G$28*(1+$A94+($C$18-$A94)*0/9)*(1+$A94+($C$18-$A94)*1/9)*(1+$A94+($C$18-$A94)*2/9)*(1+$A94+($C$18-$A94)*3/9)*(1+$A94+($C$18-$A94)*4/9)*(1+$A94+($C$18-$A94)*5/9)*(1+$A94+($C$18-$A94)*6/9)*(1+$A94+($C$18-$A94)*7/9)*($G$30+($C$20-$G$30)*8/10)*(1-$G$32)*(1-($G$38+(($A94+($C$18-$A94)*7/9)/F$90-$G$38)*8/10))/(1+$C$16)^($C$21+11+0.5)+$G$28*(1+$A94+($C$18-$A94)*0/9)*(1+$A94+($C$18-$A94)*1/9)*(1+$A94+($C$18-$A94)*2/9)*(1+$A94+($C$18-$A94)*3/9)*(1+$A94+($C$18-$A94)*4/9)*(1+$A94+($C$18-$A94)*5/9)*(1+$A94+($C$18-$A94)*6/9)*(1+$A94+($C$18-$A94)*7/9)*(1+$A94+($C$18-$A94)*8/9)*($G$30+($C$20-$G$30)*9/10)*(1-$G$32)*(1-($G$38+(($A94+($C$18-$A94)*8/9)/F$90-$G$38)*9/10))/(1+$C$16)^($C$21+12+0.5)+$G$28*(1+$A94+($C$18-$A94)*0/9)*(1+$A94+($C$18-$A94)*1/9)*(1+$A94+($C$18-$A94)*2/9)*(1+$A94+($C$18-$A94)*3/9)*(1+$A94+($C$18-$A94)*4/9)*(1+$A94+($C$18-$A94)*5/9)*(1+$A94+($C$18-$A94)*6/9)*(1+$A94+($C$18-$A94)*7/9)*(1+$A94+($C$18-$A94)*8/9)*(1+$A94+($C$18-$A94)*9/9)*($G$30+($C$20-$G$30)*10/10)*(1-$G$32)*(1-($G$38+(($A94+($C$18-$A94)*9/9)/F$90-$G$38)*10/10))/(1+$C$16)^($C$21+13+0.5)+$G$28*(1+$A94+($C$18-$A94)*0/9)*(1+$A94+($C$18-$A94)*1/9)*(1+$A94+($C$18-$A94)*2/9)*(1+$A94+($C$18-$A94)*3/9)*(1+$A94+($C$18-$A94)*4/9)*(1+$A94+($C$18-$A94)*5/9)*(1+$A94+($C$18-$A94)*6/9)*(1+$A94+($C$18-$A94)*7/9)*(1+$A94+($C$18-$A94)*8/9)*(1+$A94+($C$18-$A94)*9/9)*($G$30+($C$20-$G$30)*10/10)*(1-$G$32)*(1+$C$18)*(1-$C$18/F$90)/($C$16-$C$18)/(1+$C$16)^($C$21+13+0.5))*(1-$C$61)+($C$55+$C$56+$C$57-$C$58-$C$60))/$C$6 -> 32.541295 | G94: =(($C$49+$G$28*(1+$A94+($C$18-$A94)*0/9)*($G$30+($C$20-$G$30)*1/10)*(1-$G$32)*(1-($G$38+(($A94+($C$18-$A94)*0/9)/G$90-$G$38)*1/10))/(1+$C$16)^($C$21+4+0.5)+$G$28*(1+$A94+($C$18-$A94)*0/9)*(1+$A94+($C$18-$A94)*1/9)*($G$30+($C$20-$G$30)*2/10)*(1-$G$32)*(1-($G$38+(($A94+($C$18-$A94)*1/9)/G$90-$G$38)*2/10))/(1+$C$16)^($C$21+5+0.5)+$G$28*(1+$A94+($C$18-$A94)*0/9)*(1+$A94+($C$18-$A94)*1/9)*(1+$A94+($C$18-$A94)*2/9)*($G$30+($C$20-$G$30)*3/10)*(1-$G$32)*(1-($G$38+(($A94+($C$18-$A94)*2/9)/G$90-$G$38)*3/10))/(1+$C$16)^($C$21+6+0.5)+$G$28*(1+$A94+($C$18-$A94)*0/9)*(1+$A94+($C$18-$A94)*1/9)*(1+$A94+($C$18-$A94)*2/9)*(1+$A94+($C$18-$A94)*3/9)*($G$30+($C$20-$G$30)*4/10)*(1-$G$32)*(1-($G$38+(($A94+($C$18-$A94)*3/9)/G$90-$G$38)*4/10))/(1+$C$16)^($C$21+7+0.5)+$G$28*(1+$A94+($C$18-$A94)*0/9)*(1+$A94+($C$18-$A94)*1/9)*(1+$A94+($C$18-$A94)*2/9)*(1+$A94+($C$18-$A94)*3/9)*(1+$A94+($C$18-$A94)*4/9)*($G$30+($C$20-$G$30)*5/10)*(1-$G$32)*(1-($G$38+(($A94+($C$18-$A94)*4/9)/G$90-$G$38)*5/10))/(1+$C$16)^($C$21+8+0.5)+$G$28*(1+$A94+($C$18-$A94)*0/9)*(1+$A94+($C$18-$A94)*1/9)*(1+$A94+($C$18-$A94)*2/9)*(1+$A94+($C$18-$A94)*3/9)*(1+$A94+($C$18-$A94)*4/9)*(1+$A94+($C$18-$A94)*5/9)*($G$30+($C$20-$G$30)*6/10)*(1-$G$32)*(1-($G$38+(($A94+($C$18-$A94)*5/9)/G$90-$G$38)*6/10))/(1+$C$16)^($C$21+9+0.5)+$G$28*(1+$A94+($C$18-$A94)*0/9)*(1+$A94+($C$18-$A94)*1/9)*(1+$A94+($C$18-$A94)*2/9)*(1+$A94+($C$18-$A94)*3/9)*(1+$A94+($C$18-$A94)*4/9)*(1+$A94+($C$18-$A94)*5/9)*(1+$A94+($C$18-$A94)*6/9)*($G$30+($C$20-$G$30)*7/10)*(1-$G$32)*(1-($G$38+(($A94+($C$18-$A94)*6/9)/G$90-$G$38)*7/10))/(1+$C$16)^($C$21+10+0.5)+$G$28*(1+$A94+($C$18-$A94)*0/9)*(1+$A94+($C$18-$A94)*1/9)*(1+$A94+($C$18-$A94)*2/9)*(1+$A94+($C$18-$A94)*3/9)*(1+$A94+($C$18-$A94)*4/9)*(1+$A94+($C$18-$A94)*5/9)*(1+$A94+($C$18-$A94)*6/9)*(1+$A94+($C$18-$A94)*7/9)*($G$30+($C$20-$G$30)*8/10)*(1-$G$32)*(1-($G$38+(($A94+($C$18-$A94)*7/9)/G$90-$G$38)*8/10))/(1+$C$16)^($C$21+11+0.5)+$G$28*(1+$A94+($C$18-$A94)*0/9)*(1+$A94+($C$18-$A94)*1/9)*(1+$A94+($C$18-$A94)*2/9)*(1+$A94+($C$18-$A94)*3/9)*(1+$A94+($C$18-$A94)*4/9)*(1+$A94+($C$18-$A94)*5/9)*(1+$A94+($C$18-$A94)*6/9)*(1+$A94+($C$18-$A94)*7/9)*(1+$A94+($C$18-$A94)*8/9)*($G$30+($C$20-$G$30)*9/10)*(1-$G$32)*(1-($G$38+(($A94+($C$18-$A94)*8/9)/G$90-$G$38)*9/10))/(1+$C$16)^($C$21+12+0.5)+$G$28*(1+$A94+($C$18-$A94)*0/9)*(1+$A94+($C$18-$A94)*1/9)*(1+$A94+($C$18-$A94)*2/9)*(1+$A94+($C$18-$A94)*3/9)*(1+$A94+($C$18-$A94)*4/9)*(1+$A94+($C$18-$A94)*5/9)*(1+$A94+($C$18-$A94)*6/9)*(1+$A94+($C$18-$A94)*7/9)*(1+$A94+($C$18-$A94)*8/9)*(1+$A94+($C$18-$A94)*9/9)*($G$30+($C$20-$G$30)*10/10)*(1-$G$32)*(1-($G$38+(($A94+($C$18-$A94)*9/9)/G$90-$G$38)*10/10))/(1+$C$16)^($C$21+13+0.5)+$G$28*(1+$A94+($C$18-$A94)*0/9)*(1+$A94+($C$18-$A94)*1/9)*(1+$A94+($C$18-$A94)*2/9)*(1+$A94+($C$18-$A94)*3/9)*(1+$A94+($C$18-$A94)*4/9)*(1+$A94+($C$18-$A94)*5/9)*(1+$A94+($C$18-$A94)*6/9)*(1+$A94+($C$18-$A94)*7/9)*(1+$A94+($C$18-$A94)*8/9)*(1+$A94+($C$18-$A94)*9/9)*($G$30+($C$20-$G$30)*10/10)*(1-$G$32)*(1+$C$18)*(1-$C$18/G$90)/($C$16-$C$18)/(1+$C$16)^($C$21+13+0.5))*(1-$C$61)+($C$55+$C$56+$C$57-$C$58-$C$60))/$C$6 -> 33.574115
